Workbook

Sheet 彙整總表
C4: 年份 | D4: 2023 | E4: 2024 | F4: 2025 | G4: 2026 | H4: 2027 | I4: 2028 | J4: 2029 | K4: 2030 | L4: 2031 | M4: 2032 | N4: 2033 | O4: 2034 | P4: 2035 | Q4: 2036 | R4: 2037 | S4: 2038 | T4: 2039 | U4: 2040 | V4: 2041 | W4: 2042
C5: 預估發電度數
B6: 表 62 | D6: =ABS('表 62_滾算紀錄7'!D40) | E6: =ABS('表 62_滾算紀錄7'!E40) | F6: =ABS('表 62_滾算紀錄7'!F40) | G6: =ABS('表 62_滾算紀錄7'!G40) | H6: =ABS('表 62_滾算紀錄7'!H40) | I6: =ABS('表 62_滾算紀錄7'!I40) | J6: =ABS('表 62_滾算紀錄7'!J40) | K6: =ABS('表 62_滾算紀錄7'!K40) | ... W6: =ABS('表 62_滾算紀錄7'!W40)
B7: 表 62 | D7: =ABS('表 62_滾算紀錄6'!D40) | E7: =ABS('表 62_滾算紀錄6'!E40) | F7: =ABS('表 62_滾算紀錄6'!F40) | G7: =ABS('表 62_滾算紀錄6'!G40) | H7: =ABS('表 62_滾算紀錄6'!H40) | I7: =ABS('表 62_滾算紀錄6'!I40) | J7: =ABS('表 62_滾算紀錄6'!J40) | K7: =ABS('表 62_滾算紀錄6'!K40) | ... W7: =ABS('表 62_滾算紀錄6'!W40)
B8: 表 62 | D8: =ABS('表 62_滾算紀錄8'!D40) | E8: =ABS('表 62_滾算紀錄8'!E40) | F8: =ABS('表 62_滾算紀錄8'!F40) | G8: =ABS('表 62_滾算紀錄8'!G40) | H8: =ABS('表 62_滾算紀錄8'!H40) | I8: =ABS('表 62_滾算紀錄8'!I40) | J8: =ABS('表 62_滾算紀錄8'!J40) | K8: =ABS('表 62_滾算紀錄8'!K40) | ... W8: =ABS('表 62_滾算紀錄8'!W40)
C9: 預估發電度數/年總計 | D9: =SUM(D6:D8) | E9: =SUM(E6:E8) | F9: =SUM(F6:F8) | G9: =SUM(G6:G8) | H9: =SUM(H6:H8) | I9: =SUM(I6:I8) | J9: =SUM(J6:J8) | K9: =SUM(K6:K8) | ... W9: =SUM(W6:W8)
C10: 預估收入 | D10: 2023 | E10: 2024 | F10: 2025 | G10: 2026 | H10: 2027 | I10: 2028 | J10: 2029 | K10: 2030 | L10: 2031 | M10: 2032 | N10: 2033 | O10: 2034 | P10: 2035 | Q10: 2036 | R10: 2037 | S10: 2038 | T10: 2039 | U10: 2040 | V10: 2041 | W10: 2042
B11: 表 62 | D11: =ABS('表 62_滾算紀錄7'!D41) | E11: =ABS('表 62_滾算紀錄7'!E41) | F11: =ABS('表 62_滾算紀錄7'!F41) | G11: =ABS('表 62_滾算紀錄7'!G41) | H11: =ABS('表 62_滾算紀錄7'!H41) | I11: =ABS('表 62_滾算紀錄7'!I41) | J11: =ABS('表 62_滾算紀錄7'!J41) | K11: =ABS('表 62_滾算紀錄7'!K41) | ... W11: =ABS('表 62_滾算紀錄7'!W41)
B12: 表 62 | D12: =ABS('表 62_滾算紀錄6'!D41) | E12: =ABS('表 62_滾算紀錄6'!E41) | F12: =ABS('表 62_滾算紀錄6'!F41) | G12: =ABS('表 62_滾算紀錄6'!G41) | H12: =ABS('表 62_滾算紀錄6'!H41) | I12: =ABS('表 62_滾算紀錄6'!I41) | J12: =ABS('表 62_滾算紀錄6'!J41) | K12: =ABS('表 62_滾算紀錄6'!K41) | ... W12: =ABS('表 62_滾算紀錄6'!W41)
B13: 表 62 | D13: =ABS('表 62_滾算紀錄8'!D41) | E13: =ABS('表 62_滾算紀錄8'!E41) | F13: =ABS('表 62_滾算紀錄8'!F41) | G13: =ABS('表 62_滾算紀錄8'!G41) | H13: =ABS('表 62_滾算紀錄8'!H41) | I13: =ABS('表 62_滾算紀錄8'!I41) | J13: =ABS('表 62_滾算紀錄8'!J41) | K13: =ABS('表 62_滾算紀錄8'!K41) | ... W13: =ABS('表 62_滾算紀錄8'!W41)
C14: 預估收入/年總計 | D14: =SUM(D11:D13) | E14: =SUM(E11:E13) | F14: =SUM(F11:F13) | G14: =SUM(G11:G13) | H14: =SUM(H11:H13) | I14: =SUM(I11:I13) | J14: =SUM(J11:J13) | K14: =SUM(K11:K13) | ... W14: =SUM(W11:W13)
C15: 租金 | D15: 2023 | E15: 2024 | F15: 2025 | G15: 2026 | H15: 2027 | I15: 2028 | J15: 2029 | K15: 2030 | L15: 2031 | M15: 2032 | N15: 2033 | O15: 2034 | P15: 2035 | Q15: 2036 | R15: 2037 | S15: 2038 | T15: 2039 | U15: 2040 | V15: 2041 | W15: 2042
B16: 表 62 | D16: =ABS('表 62_滾算紀錄7'!D45) | E16: =ABS('表 62_滾算紀錄7'!E45) | F16: =ABS('表 62_滾算紀錄7'!F45) | G16: =ABS('表 62_滾算紀錄7'!G45) | H16: =ABS('表 62_滾算紀錄7'!H45) | I16: =ABS('表 62_滾算紀錄7'!I45) | J16: =ABS('表 62_滾算紀錄7'!J45) | K16: =ABS('表 62_滾算紀錄7'!K45) | ... W16: =ABS('表 62_滾算紀錄7'!W45)
B17: 表 62 | D17: =ABS('表 62_滾算紀錄6'!D45) | E17: =ABS('表 62_滾算紀錄6'!E45) | F17: =ABS('表 62_滾算紀錄6'!F45) | G17: =ABS('表 62_滾算紀錄6'!G45) | H17: =ABS('表 62_滾算紀錄6'!H45) | I17: =ABS('表 62_滾算紀錄6'!I45) | J17: =ABS('表 62_滾算紀錄6'!J45) | K17: =ABS('表 62_滾算紀錄6'!K45) | ... W17: =ABS('表 62_滾算紀錄6'!W45)
B18: 表 62 | D18: =ABS('表 62_滾算紀錄8'!D45) | E18: =ABS('表 62_滾算紀錄8'!E45) | F18: =ABS('表 62_滾算紀錄8'!F45) | G18: =ABS('表 62_滾算紀錄8'!G45) | H18: =ABS('表 62_滾算紀錄8'!H45) | I18: =ABS('表 62_滾算紀錄8'!I45) | J18: =ABS('表 62_滾算紀錄8'!J45) | K18: =ABS('表 62_滾算紀錄8'!K45) | ... W18: =ABS('表 62_滾算紀錄8'!W45)
C19: 租金/年總計 | D19: =SUM(D16:D18) | E19: =SUM(E16:E18) | F19: =SUM(F16:F18) | G19: =SUM(G16:G18) | H19: =SUM(H16:H18) | I19: =SUM(I16:I18) | J19: =SUM(J16:J18) | K19: =SUM(K16:K18) | ... W19: =SUM(W16:W18)
C20: 運維 | D20: 2023 | E20: 2024 | F20: 2025 | G20: 2026 | H20: 2027 | I20: 2028 | J20: 2029 | K20: 2030 | L20: 2031 | M20: 2032 | N20: 2033 | O20: 2034 | P20: 2035 | Q20: 2036 | R20: 2037 | S20: 2038 | T20: 2039 | U20: 2040 | V20: 2041 | W20: 2042
B21: 表 62 | D21: =ABS('表 62_滾算紀錄7'!D48) | E21: =ABS('表 62_滾算紀錄7'!E48) | F21: =ABS('表 62_滾算紀錄7'!F48) | G21: =ABS('表 62_滾算紀錄7'!G48) | H21: =ABS('表 62_滾算紀錄7'!H48) | I21: =ABS('表 62_滾算紀錄7'!I48) | J21: =ABS('表 62_滾算紀錄7'!J48) | K21: =ABS('表 62_滾算紀錄7'!K48) | ... W21: =ABS('表 62_滾算紀錄7'!W48)
B22: 表 62 | D22: =ABS('表 62_滾算紀錄6'!D48) | E22: =ABS('表 62_滾算紀錄6'!E48) | F22: =ABS('表 62_滾算紀錄6'!F48) | G22: =ABS('表 62_滾算紀錄6'!G48) | H22: =ABS('表 62_滾算紀錄6'!H48) | I22: =ABS('表 62_滾算紀錄6'!I48) | J22: =ABS('表 62_滾算紀錄6'!J48) | K22: =ABS('表 62_滾算紀錄6'!K48) | ... W22: =ABS('表 62_滾算紀錄6'!W48)
B23: 表 62 | D23: =ABS('表 62_滾算紀錄8'!D48) | E23: =ABS('表 62_滾算紀錄8'!E48) | F23: =ABS('表 62_滾算紀錄8'!F48) | G23: =ABS('表 62_滾算紀錄8'!G48) | H23: =ABS('表 62_滾算紀錄8'!H48) | I23: =ABS('表 62_滾算紀錄8'!I48) | J23: =ABS('表 62_滾算紀錄8'!J48) | K23: =ABS('表 62_滾算紀錄8'!K48) | ... W23: =ABS('表 62_滾算紀錄8'!W48)
C24: 運維/年總計 | D24: =SUM(D21:D23) | E24: =SUM(E21:E23) | F24: =SUM(F21:F23) | G24: =SUM(G21:G23) | H24: =SUM(H21:H23) | I24: =SUM(I21:I23) | J24: =SUM(J21:J23) | K24: =SUM(K21:K23) | ... W24: =SUM(W21:W23)
C25: 保險 | D25: 2023 | E25: 2024 | F25: 2025 | G25: 2026 | H25: 2027 | I25: 2028 | J25: 2029 | K25: 2030 | L25: 2031 | M25: 2032 | N25: 2033 | O25: 2034 | P25: 2035 | Q25: 2036 | R25: 2037 | S25: 2038 | T25: 2039 | U25: 2040 | V25: 2041 | W25: 2042
B26: 表 62 | D26: =ABS('表 62_滾算紀錄7'!D49) | E26: =ABS('表 62_滾算紀錄7'!E49) | F26: =ABS('表 62_滾算紀錄7'!F49) | G26: =ABS('表 62_滾算紀錄7'!G49) | H26: =ABS('表 62_滾算紀錄7'!H49) | I26: =ABS('表 62_滾算紀錄7'!I49) | J26: =ABS('表 62_滾算紀錄7'!J49) | K26: =ABS('表 62_滾算紀錄7'!K49) | ... W26: =ABS('表 62_滾算紀錄7'!W49)
B27: 表 62 | D27: =ABS('表 62_滾算紀錄6'!D49) | E27: =ABS('表 62_滾算紀錄6'!E49) | F27: =ABS('表 62_滾算紀錄6'!F49) | G27: =ABS('表 62_滾算紀錄6'!G49) | H27: =ABS('表 62_滾算紀錄6'!H49) | I27: =ABS('表 62_滾算紀錄6'!I49) | J27: =ABS('表 62_滾算紀錄6'!J49) | K27: =ABS('表 62_滾算紀錄6'!K49) | ... W27: =ABS('表 62_滾算紀錄6'!W49)
B28: 表 62 | D28: =ABS('表 62_滾算紀錄8'!D49) | E28: =ABS('表 62_滾算紀錄8'!E49) | F28: =ABS('表 62_滾算紀錄8'!F49) | G28: =ABS('表 62_滾算紀錄8'!G49) | H28: =ABS('表 62_滾算紀錄8'!H49) | I28: =ABS('表 62_滾算紀錄8'!I49) | J28: =ABS('表 62_滾算紀錄8'!J49) | K28: =ABS('表 62_滾算紀錄8'!K49) | ... W28: =ABS('表 62_滾算紀錄8'!W49)
C29: 保險/年總計 | D29: =SUM(D26:D28) | E29: =SUM(E26:E28) | F29: =SUM(F26:F28) | G29: =SUM(G26:G28) | H29: =SUM(H26:H28) | I29: =SUM(I26:I28) | J29: =SUM(J26:J28) | K29: =SUM(K26:K28) | ... W29: =SUM(W26:W28)
C30: 模組回收費 | D30: 2023 | E30: 2024 | F30: 2025 | G30: 2026 | H30: 2027 | I30: 2028 | J30: 2029 | K30: 2030 | L30: 2031 | M30: 2032 | N30: 2033 | O30: 2034 | P30: 2035 | Q30: 2036 | R30: 2037 | S30: 2038 | T30: 2039 | U30: 2040 | V30: 2041 | W30: 2042
B31: 表 62 | D31: =ABS('表 62_滾算紀錄7'!D50) | E31: =ABS('表 62_滾算紀錄7'!E50) | F31: =ABS('表 62_滾算紀錄7'!F50) | G31: =ABS('表 62_滾算紀錄7'!G50) | H31: =ABS('表 62_滾算紀錄7'!H50) | I31: =ABS('表 62_滾算紀錄7'!I50) | J31: =ABS('表 62_滾算紀錄7'!J50) | K31: =ABS('表 62_滾算紀錄7'!K50) | ... W31: =ABS('表 62_滾算紀錄7'!W50)
B32: 表 62 | D32: =ABS('表 62_滾算紀錄6'!D50) | E32: =ABS('表 62_滾算紀錄6'!E50) | F32: =ABS('表 62_滾算紀錄6'!F50) | G32: =ABS('表 62_滾算紀錄6'!G50) | H32: =ABS('表 62_滾算紀錄6'!H50) | I32: =ABS('表 62_滾算紀錄6'!I50) | J32: =ABS('表 62_滾算紀錄6'!J50) | K32: =ABS('表 62_滾算紀錄6'!K50) | ... W32: =ABS('表 62_滾算紀錄6'!W50)
B33: 表 62 | D33: =ABS('表 62_滾算紀錄8'!D50) | E33: =ABS('表 62_滾算紀錄8'!E50) | F33: =ABS('表 62_滾算紀錄8'!F50) | G33: =ABS('表 62_滾算紀錄8'!G50) | H33: =ABS('表 62_滾算紀錄8'!H50) | I33: =ABS('表 62_滾算紀錄8'!I50) | J33: =ABS('表 62_滾算紀錄8'!J50) | K33: =ABS('表 62_滾算紀錄8'!K50) | ... W33: =ABS('表 62_滾算紀錄8'!W50)
C34: 模組回收費/年總計 | D34: =SUM(D31:D33) | E34: =SUM(E31:E33) | F34: =SUM(F31:F33) | G34: =SUM(G31:G33) | H34: =SUM(H31:H33) | I34: =SUM(I31:I33) | J34: =SUM(J31:J33) | K34: =SUM(K31:K33) | ... W34: =SUM(W31:W33)
C35: 所得稅 | D35: 2023 | E35: 2024 | F35: 2025 | G35: 2026 | H35: 2027 | I35: 2028 | J35: 2029 | K35: 2030 | L35: 2031 | M35: 2032 | N35: 2033 | O35: 2034 | P35: 2035 | Q35: 2036 | R35: 2037 | S35: 2038 | T35: 2039 | U35: 2040 | V35: 2041 | W35: 2042
B36: 表 62 | D36: =ABS('表 62_滾算紀錄7'!D54) | E36: =ABS('表 62_滾算紀錄7'!E54) | F36: =ABS('表 62_滾算紀錄7'!F54) | G36: =ABS('表 62_滾算紀錄7'!G54) | H36: =ABS('表 62_滾算紀錄7'!H54) | I36: =ABS('表 62_滾算紀錄7'!I54) | J36: =ABS('表 62_滾算紀錄7'!J54) | K36: =ABS('表 62_滾算紀錄7'!K54) | ... W36: =ABS('表 62_滾算紀錄7'!W54)
B37: 表 62 | D37: =ABS('表 62_滾算紀錄6'!D54) | E37: =ABS('表 62_滾算紀錄6'!E54) | F37: =ABS('表 62_滾算紀錄6'!F54) | G37: =ABS('表 62_滾算紀錄6'!G54) | H37: =ABS('表 62_滾算紀錄6'!H54) | I37: =ABS('表 62_滾算紀錄6'!I54) | J37: =ABS('表 62_滾算紀錄6'!J54) | K37: =ABS('表 62_滾算紀錄6'!K54) | ... W37: =ABS('表 62_滾算紀錄6'!W54)
B38: 表 62 | D38: =ABS('表 62_滾算紀錄8'!D54) | E38: =ABS('表 62_滾算紀錄8'!E54) | F38: =ABS('表 62_滾算紀錄8'!F54) | G38: =ABS('表 62_滾算紀錄8'!G54) | H38: =ABS('表 62_滾算紀錄8'!H54) | I38: =ABS('表 62_滾算紀錄8'!I54) | J38: =ABS('表 62_滾算紀錄8'!J54) | K38: =ABS('表 62_滾算紀錄8'!K54) | ... W38: =ABS('表 62_滾算紀錄8'!W54)
C39: 所得稅/年總計 | D39: =SUM(D36:D38) | E39: =SUM(E36:E38) | F39: =SUM(F36:F38) | G39: =SUM(G36:G38) | H39: =SUM(H36:H38) | I39: =SUM(I36:I38) | J39: =SUM(J36:J38) | K39: =SUM(K36:K38) | ... W39: =SUM(W36:W38)
C40: 設備折舊 | D40: 2023 | E40: 2024 | F40: 2025 | G40: 2026 | H40: 2027 | I40: 2028 | J40: 2029 | K40: 2030 | L40: 2031 | M40: 2032 | N40: 2033 | O40: 2034 | P40: 2035 | Q40: 2036 | R40: 2037 | S40: 2038 | T40: 2039 | U40: 2040 | V40: 2041 | W40: 2042
B41: 表 62 | D41: =ABS('表 62_滾算紀錄7'!D67) | E41: =ABS('表 62_滾算紀錄7'!E67) | F41: =ABS('表 62_滾算紀錄7'!F67) | G41: =ABS('表 62_滾算紀錄7'!G67) | H41: =ABS('表 62_滾算紀錄7'!H67) | I41: =ABS('表 62_滾算紀錄7'!I67) | J41: =ABS('表 62_滾算紀錄7'!J67) | K41: =ABS('表 62_滾算紀錄7'!K67) | ... W41: =ABS('表 62_滾算紀錄7'!W67)
B42: 表 62 | D42: =ABS('表 62_滾算紀錄6'!D67) | E42: =ABS('表 62_滾算紀錄6'!E67) | F42: =ABS('表 62_滾算紀錄6'!F67) | G42: =ABS('表 62_滾算紀錄6'!G67) | H42: =ABS('表 62_滾算紀錄6'!H67) | I42: =ABS('表 62_滾算紀錄6'!I67) | J42: =ABS('表 62_滾算紀錄6'!J67) | K42: =ABS('表 62_滾算紀錄6'!K67) | ... W42: =ABS('表 62_滾算紀錄6'!W67)
B43: 表 62 | D43: =ABS('表 62_滾算紀錄8'!D67) | E43: =ABS('表 62_滾算紀錄8'!E67) | F43: =ABS('表 62_滾算紀錄8'!F67) | G43: =ABS('表 62_滾算紀錄8'!G67) | H43: =ABS('表 62_滾算紀錄8'!H67) | I43: =ABS('表 62_滾算紀錄8'!I67) | J43: =ABS('表 62_滾算紀錄8'!J67) | K43: =ABS('表 62_滾算紀錄8'!K67) | ... W43: =ABS('表 62_滾算紀錄8'!W67)
C44: 設備折舊/年總計 | D44: =SUM(D41:D43) | E44: =SUM(E41:E43) | F44: =SUM(F41:F43) | G44: =SUM(G41:G43) | H44: =SUM(H41:H43) | I44: =SUM(I41:I43) | J44: =SUM(J41:J43) | K44: =SUM(K41:K43) | ... W44: =SUM(W41:W43)
C51: 年份 | D51: 2023 | E51: 2024 | F51: 2025 | G51: 2026 | H51: 2027 | I51: 2028 | J51: 2029 | K51: 2030 | L51: 2031 | M51: 2032 | N51: 2033 | O51: 2034 | P51: 2035 | Q51: 2036 | R51: 2037 | S51: 2038 | T51: 2039 | U51: 2040 | V51: 2041 | W51: 2042
B52: 0
B53: (Unit : Currency) | C53: 0 | D53: 1 | E53: 2 | F53: 3 | G53: 4 | H53: 5 | I53: 6 | J53: 7 | K53: 8 | L53: 9 | M53: 10 | N53: 11 | O53: 12 | P53: 13 | Q53: 14 | R53: 15 | S53: 16 | T53: 17 | U53: 18 | V53: 19 | W53: 20
B54: 發電度數(KWH) | C54: 0 | D54: =D9 | E54: =E9 | F54: =F9 | G54: =G9 | H54: =H9 | I54: =I9 | J54: =J9 | K54: =K9 | ... W54: =W9
B55: Inflow : 電費收入 | C55: - | D55: =D14 | E55: =E14 | F55: =F14 | G55: =G14 | H55: =H14 | I55: =I14 | J55: =J14 | K55: =K14 | ... W55: =W14
B56: Inflow : 政府補助 | C56: - | G56: - | H56: - | I56: - | J56: - | K56: - | L56: - | M56: - | N56: - | O56: - | P56: - | Q56: - | R56: - | S56: - | T56: - | U56: - | V56: - | W56: -
B57: Inflow : 銀行借款 | C57: =SUM(D44:W44) | D57: 0 | E57: 0 | F57: 0 | G57: 0 | H57: 0 | I57: 0 | J57: 0 | K57: 0 | L57: 0 | M57: 0 | N57: 0 | O57: 0 | P57: 0 | Q57: 0 | R57: 0 | S57: 0 | T57: 0 | U57: 0 | V57: 0 | W57: 0
B58: Outflow : 設備費用 | C58: =-(D16/(1-D17)+D18)*C4
B59: Outflow : 設備放置區域租金 | C59: - | D59: =D19 | E59: =E19 | F59: =F19 | G59: =G19 | H59: =H19 | I59: =I19 | J59: =J19 | K59: =K19 | ... W59: =W19
B60: Outflow : 返還借款
B61: Outflow : 利息費用 | C61: -
B62: Outflow : 維運費 | C62: - | D62: =D24 | E62: =E24 | F62: =F24 | G62: =G24 | H62: =H24 | I62: =I24 | J62: =J24 | K62: =K24 | ... W62: =W24
B63: Outflow : 保險費 | C63: - | D63: =D29 | E63: =E29 | F63: =F29 | G63: =G29 | H63: =H29 | I63: =I29 | J63: =J29 | K63: =K29 | ... W63: =W29
B64: Outflow : 模組回收費 | D64: =D34 | E64: =E34 | F64: =F34 | G64: =G34 | H64: =H34 | I64: =I34 | J64: =J34 | K64: =K34 | ... W64: =W34
B65: Outflow : 其它費用(人事薪資…等)
B66: 1%管理費
B67: 績效獎金
B68: 所得稅20% | D68: =D91 | E68: =E91 | F68: =F91 | G68: =G91 | H68: =H91 | I68: =I91 | J68: =J91 | K68: =K91 | ... W68: =W91
B69: 現金流 | C69: =C44 | D69: =SUM(D55:D68) | E69: =SUM(E55:E68) | F69: =SUM(F55:F68) | G69: =SUM(G55:G68) | H69: =SUM(H55:H68) | I69: =SUM(I55:I68) | J69: =SUM(J55:J68) | K69: =SUM(K55:K68) | ... W69: =SUM(W55:W68)
B70: 累計現金流 | D70: =C55+D55 | E70: =D56+E55 | F70: =E56+F55 | G70: =F56+G55 | H70: =G56+H55 | I70: =H56+I55 | J70: =I56+J55 | K70: =J56+K55 | L70: =K56+L55 | ... W70: =V56+W55
B71: 回收年限評估 | D71: =IF((D56)>0,"回收","未回收") | E71: =IF((E56)>0,"回收","未回收") | F71: =IF((F56)>0,"回收","未回收") | G71: =IF((G56)>0,"回收","未回收") | H71: =IF((H56)>0,"回收","未回收") | I71: =IF((I56)>0,"回收","未回收") | J71: =IF((J56)>0,"回收","未回收") | K71: =IF((K56)>0,"回收","未回收") | ... W71: =IF((W56)>0,"回收","未回收")
B72: 專案法IRR | C72: =IRR(C55:W55)
C74: 年份 | D74: 2023 | E74: 2024 | F74: 2025 | G74: 2026 | H74: 2027 | I74: 2028 | J74: 2029 | K74: 2030 | L74: 2031 | M74: 2032 | N74: 2033 | O74: 2034 | P74: 2035 | Q74: 2036 | R74: 2037 | S74: 2038 | T74: 2039 | U74: 2040 | V74: 2041 | W74: 2042
B75: 0 | T75: 償還年限
B76: (Unit : Currency) | C76: 0 | D76: 1 | E76: 2 | F76: 3 | G76: 4 | H76: 5 | I76: 6 | J76: 7 | K76: 8 | L76: 9 | M76: 10 | N76: 11 | O76: 12 | P76: 13 | Q76: 14 | R76: 15 | S76: 16 | T76: 17 | U76: 18 | V76: 19 | W76: 20
B77: 發電度數(KWH) | C77: 0 | D77: =D9 | E77: =E9 | F77: =F9 | G77: =G9 | H77: =H9 | I77: =I9 | J77: =J9 | K77: =K9 | ... W77: =W9
B78: Inflow : 電費收入 | C78: - | D78: =D14 | E78: =E14 | F78: =F14 | G78: =G14 | H78: =H14 | I78: =I14 | J78: =J14 | K78: =K14 | ... W78: =W14
B79: Inflow : 政府補助 | C79: - | G79: - | H79: - | I79: - | J79: - | K79: - | L79: - | M79: - | N79: - | O79: - | P79: - | Q79: - | R79: - | S79: - | T79: - | U79: - | V79: - | W79: -
B80: Inflow : 銀行借款
B81: Outflow : 設備折舊 | D81: =D44 | E81: =E44 | F81: =F44 | G81: =G44 | H81: =H44 | I81: =I44 | J81: =J44 | K81: =K44 | ... W81: =W44
B82: Outflow : 設備放置區域租金 | C82: - | D82: =D19 | E82: =E19 | F82: =F19 | G82: =G19 | H82: =H19 | I82: =I19 | J82: =J19 | K82: =K19 | ... W82: =W19
B83: Outflow : 返還借款
B84: Outflow : 利息費用 | C84: -
B85: Outflow : 維運費 | C85: - | D85: =D24 | E85: =E24 | F85: =F24 | G85: =G24 | H85: =H24 | I85: =I24 | J85: =J24 | K85: =K24 | ... W85: =W24
B86: Outflow : 保險費 | C86: - | D86: =D29 | E86: =E29 | F86: =F29 | G86: =G29 | H86: =H29 | I86: =I29 | J86: =J29 | K86: =K29 | ... W86: =W29
B87: Outflow : 模組回收費 | D87: =D34 | E87: =E34 | F87: =F34 | G87: =G34 | H87: =H34 | I87: =I34 | J87: =J34 | K87: =K34 | ... W87: =W34
B88: Outflow : 其它費用(人事薪資…等)
B89: 1%管理費
B90: 稅前淨利 | D90: =SUM(D78:D89) | E90: =SUM(E78:E89) | F90: =SUM(F78:F89) | G90: =SUM(G78:G89) | H90: =SUM(H78:H89) | I90: =SUM(I78:I89) | J90: =SUM(J78:J89) | K90: =SUM(K78:K89) | ... W90: =SUM(W78:W89)
B91: 所得稅20% | D91: =D90*0.2 | E91: =E90*0.2 | F91: =F90*0.2 | G91: =G90*0.2 | H91: =H90*0.2 | I91: =I90*0.2 | J91: =J90*0.2 | K91: =K90*0.2 | ... W91: =W90*0.2
B92: 稅後淨利 | D92: =D90-D91 | E92: =E90-E91 | F92: =F90-F91 | G92: =G90-G91 | H92: =H90-H91 | I92: =I90-I91 | J92: =J90-J91 | K92: =K90-K91 | ... W92: =W90-W91
B93: 累計現金流
B94: 回收年限評估
C95: 年份 | D95: 2023 | E95: 2024 | F95: 2025 | G95: 2026 | H95: 2027 | I95: 2028 | J95: 2029 | K95: 2030 | L95: 2031 | M95: 2032 | N95: 2033 | O95: 2034 | P95: 2035 | Q95: 2036 | R95: 2037 | S95: 2038 | T95: 2039 | U95: 2040 | V95: 2041 | W95: 2042
B97: (Unit : Currency) | C97: 0 | D97: 1 | E97: 2 | F97: 3 | G97: 4 | H97: 5 | I97: 6 | J97: 7 | K97: 8 | L97: 9 | M97: 10 | N97: 11 | O97: 12 | P97: 13 | Q97: 14 | R97: 15 | S97: 16 | T97: 17 | U97: 18 | V97: 19 | W97: 20
B98: 稅後淨利 | D98: =D78 | E98: =E78 | F98: =F78 | G98: =G78 | H98: =H78 | I98: =I78 | J98: =J78 | K98: =K78 | ... W98: =W78
B99: 設備折舊 | D99: =-D67 | E99: =-E67 | F99: =-F67 | G99: =-G67 | H99: =-H67 | I99: =-I67 | J99: =-J67 | K99: =-K67 | ... W99: =-W67
B100: 營運活動現金流量 | D100: =SUM(D85:D86) | E100: =SUM(E85:E86) | F100: =SUM(F85:F86) | G100: =SUM(G85:G86) | H100: =SUM(H85:H86) | I100: =SUM(I85:I86) | J100: =SUM(J85:J86) | K100: =SUM(K85:K86) | ... W100: =SUM(W85:W86)
B102: 投資活動-設備支出 | D102: =C44
B105: 理財活動-借款 | D105: =-D89*D31
B106: 理財活動-還款
B107: 理財活動-現金增資 | D107: =-D89*(1-D31)
B108: 現金股利 | E108: =-D85*$D$33 | F108: =-E85*$D$33 | G108: =-F85*$D$33 | H108: =-G85*$D$33 | I108: =-H85*$D$33 | J108: =-I85*$D$33 | K108: =-J85*$D$33 | L108: =-K85*$D$33 | ... W108: =-V85*$D$33
B109: 年底減資
B112: 現金淨流入(出 ) | C112: 0 | D112: =SUM(D87:D96) | E112: =SUM(E87:E96) | F112: =SUM(F87:F96) | G112: =SUM(G87:G96) | H112: =SUM(H87:H96) | I112: =SUM(I87:I96) | J112: =SUM(J87:J96) | K112: =SUM(K87:K96) | ... W112: =SUM(W87:W96)
B113: 期初淨現金 | C113: 0 | D113: =C101 | E113: =D101 | F113: =E101 | G113: =F101 | H113: =G101 | I113: =H101 | J113: =I101 | K113: =J101 | ... W113: =V101
B114: 期未淨現金 | C114: 0 | D114: =D99+D100 | E114: =E99+E100 | F114: =F99+F100 | G114: =G99+G100 | H114: =H99+H100 | I114: =I99+I100 | J114: =J99+J100 | K114: =K99+K100 | ... W114: =W99+W100
B117: 成本法實際現金流 | D117: =-D94 | E117: =-E95-E96 | F117: =-F95-F96 | G117: =-G95-G96 | H117: =-H95-H96 | I117: =-I95-I96 | J117: =-J95-J96 | K117: =-K95-K96 | L117: =-L95-L96 | ... W117: =-W95-W96
B118: 成本法IRR | C118: =IRR(D104:X104)
...

Sheet 表 62_滾算紀錄7
B1: 電站基本資料
B2: 電站名稱 | C2: 淡江大學-財務模擬案場 | D2: - | E2: -
B3: 電站壽命 | C3: 20 | D3: - | E3: -
B4: 建置量(kWp) | C4: 436.1 | D4: - | E4: - | M4: 滾算紀錄編號: 7
B5: 起始年度 | C5: 2023 | D5: 結束年度 | E5: 2042 | M5: 第6次滾算摘要
M6: 價金: 24000
B7: 綜合損益表 | M7: 專案IRR: 6.59
B8: 收入 | M8: 權益法IRR: 20.81
B9: 收支項目 | C9: 相關參數 | D9: 參數數值 | E9: 年限 | M9: 利潤率: 20.00%
B10: 電費收入 | C10: 年度AC併網總發電量 | D10: 547002 | E10: 20 | M10: 第6次滾算，減少 1000 元 - 現金模式，每次減少 1000 元
C11: 首年衰退率 | D11: 0.01
C12: 次年衰退率 | D12: 0.004
C13: 躉售費率(FIT) | D13: 3.7152
B14: 支出
B15: 收支項目 | C15: 相關參數 | D15: 參數數值 | E15: 攤提年限
B16: 設備費用(價金) | C16: 每kWp設備成本 | D16: 24000 | E16: 20
C17: 信邦利潤率 | D17: 0.2
C18: 開發費 | D18: 2000
B19: 租金費用 | C19: 租金計算方式 (1=固定攤提/2=電費抽成) | D19: 1 | E19: 0
C20: 【方式1參數】租金總額 | D20: 5804025 | E20: 20
C21: 【方式2參數】抽成比率 | D21: 0 | E21: 0
B22: 運維費用 | C22: 每kw運維成本 | D22: 400 | E22: 20
B23: 保險費用 | C23: 占整體設備費用比例 | D23: 0.003 | E23: 20
B24: 模組回收費用 | C24: 每kw模組回收成本 | D24: 1000 | E24: 10
B25: 利息費用 | C25: 銀行利率 | D25: 0.025595 | E25: 0
B26: 所得稅 | C26: 所得稅率 | D26: 0.2 | E26: 0
B29: 現金流量表
B30: 金流項目 | C30: 相關參數 | D30: 參數數值
B31: 貸款成數 | C31: 占總設備費用比例 | D31: 0.8
B32: 貸款還款 | C32: 攤還期數 | D32: 15
B33: 現金股利 | C33: 股利比率 | D33: 0.9
B34: 年底減資 | C34: 攤還期數 | D34: 4
C37: 年份 | D37: 2023 | E37: 2024 | F37: 2025 | G37: 2026 | H37: 2027 | I37: 2028 | J37: 2029 | K37: 2030 | L37: 2031 | M37: 2032 | N37: 2033 | O37: 2034 | P37: 2035 | Q37: 2036 | R37: 2037 | S37: 2038 | T37: 2039 | U37: 2040 | V37: 2041 | W37: 2042
B38: 0
B39: (Unit : Currency) | C39: 0 | D39: 1 | E39: 2 | F39: 3 | G39: 4 | H39: 5 | I39: 6 | J39: 7 | K39: 8 | L39: 9 | M39: 10 | N39: 11 | O39: 12 | P39: 13 | Q39: 14 | R39: 15 | S39: 16 | T39: 17 | U39: 18 | V39: 19 | W39: 20
B40: 發電度數(KWH) | C40: 0 | D40: =$D$10*0.99 | E40: =$D$10*0.986 | F40: =$D$10*0.982 | G40: =$D$10*0.978 | H40: =$D$10*0.974 | I40: =$D$10*0.97 | J40: =$D$10*0.966 | K40: =$D$10*0.962 | L40: =$D$10*0.958 | M40: =$D$10*0.954 | N40: =$D$10*0.95 | O40: =$D$10*0.946 | P40: =$D$10*0.942 | Q40: =$D$10*0.938 | R40: =$D$10*0.934 | S40: =$D$10*0.93 | T40: =$D$10*0.926 | U40: =$D$10*0.922 | V40: =$D$10*0.918 | W40: =$D$10*0.914
B41: Inflow : 電費收入 | C41: - | D41: =D40*$D$13 | E41: =E40*$D$13 | F41: =F40*$D$13 | G41: =G40*$D$13 | H41: =H40*$D$13 | I41: =I40*$D$13 | J41: =J40*$D$13 | K41: =K40*$D$13 | ... W41: =W40*$D$13
B42: Inflow : 政府補助 | C42: - | G42: - | H42: - | I42: - | J42: - | K42: - | L42: - | M42: - | N42: - | O42: - | P42: - | Q42: - | R42: - | S42: - | T42: - | U42: - | V42: - | W42: -
B43: Inflow : 銀行借款
B44: Outflow : 設備費用 | C44: =-(D16/(1-D17)+D18)*C4
B45: Outflow : 設備放置區域租金 | C45: - | D45: 0 | E45: -290201.25 | F45: -290201.25 | G45: -290201.25 | H45: -290201.25 | I45: -290201.25 | J45: -290201.25 | K45: -290201.25 | L45: -290201.25 | M45: -290201.25 | N45: -290201.25 | O45: -290201.25 | P45: -290201.25 | Q45: -290201.25 | R45: -290201.25 | S45: -290201.25 | T45: -290201.25 | U45: -290201.25 | V45: -290201.25 | W45: -290201.25
B46: Outflow : 返還借款
B47: Outflow : 利息費用 | C47: -
B48: Outflow : 維運費 | C48: - | D48: -174440 | E48: -174440 | F48: -174440 | G48: -174440 | H48: -174440 | I48: -174440 | J48: -174440 | K48: -174440 | L48: -174440 | M48: -174440 | N48: -174440 | O48: -174440 | P48: -174440 | Q48: -174440 | R48: -174440 | S48: -174440 | T48: -174440 | U48: -174440 | V48: -174440 | W48: -174440
B49: Outflow : 保險費 | C49: - | D49: -31399.2 | E49: -31399.2 | F49: -31399.2 | G49: -31399.2 | H49: -31399.2 | I49: -31399.2 | J49: -31399.2 | K49: -31399.2 | L49: -31399.2 | M49: -31399.2 | N49: -31399.2 | O49: -31399.2 | P49: -31399.2 | Q49: -31399.2 | R49: -31399.2 | S49: -31399.2 | T49: -31399.2 | U49: -31399.2 | V49: -31399.2 | W49: -31399.2
B50: Outflow : 模組回收費 | D50: -43610 | E50: -43610 | F50: -43610 | G50: -43610 | H50: -43610 | I50: -43610 | J50: -43610 | K50: -43610 | L50: -43610 | M50: -43610 | N50: 0 | O50: 0 | P50: 0 | Q50: 0 | R50: 0 | S50: 0 | T50: 0 | U50: 0 | V50: 0 | W50: 0
B51: Outflow : 其它費用(人事薪資…等)
B52: 1%管理費
B53: 績效獎金
B54: 所得稅20% | D54: =D77 | E54: =E77 | F54: =F77 | G54: =G77 | H54: =H77 | I54: =I77 | J54: =J77 | K54: =K77 | ... W54: =W77
B55: 現金流 | C55: =C44 | D55: =SUM(D41:D54) | E55: =SUM(E41:E54) | F55: =SUM(F41:F54) | G55: =SUM(G41:G54) | H55: =SUM(H41:H54) | I55: =SUM(I41:I54) | J55: =SUM(J41:J54) | K55: =SUM(K41:K54) | ... W55: =SUM(W41:W54)
B56: 累計現金流 | D56: =C55+D55 | E56: =D56+E55 | F56: =E56+F55 | G56: =F56+G55 | H56: =G56+H55 | I56: =H56+I55 | J56: =I56+J55 | K56: =J56+K55 | L56: =K56+L55 | ... X56: =W56+X55
B57: 回收年限評估 | D57: =IF((D56)>0,"回收","未回收") | E57: =IF((E56)>0,"回收","未回收") | F57: =IF((F56)>0,"回收","未回收") | G57: =IF((G56)>0,"回收","未回收") | H57: =IF((H56)>0,"回收","未回收") | I57: =IF((I56)>0,"回收","未回收") | J57: =IF((J56)>0,"回收","未回收") | K57: =IF((K56)>0,"回收","未回收") | ... X57: =IF((X56)>0,"回收","未回收")
B58: 專案法IRR | C58: =IRR(C55:W55)
C60: 年份 | D60: =D37 | E60: =E37 | F60: =F37 | G60: =G37 | H60: =H37 | I60: =I37 | J60: =J37 | K60: =K37 | ... W60: =W37
B61: 0 | T61: 償還年限
B62: (Unit : Currency) | C62: 0 | D62: 1 | E62: 2 | F62: 3 | G62: 4 | H62: 5 | I62: 6 | J62: 7 | K62: 8 | L62: 9 | M62: 10 | N62: 11 | O62: 12 | P62: 13 | Q62: 14 | R62: 15 | S62: 16 | T62: 17 | U62: 18 | V62: 19 | W62: 20
B63: 發電度數(KWH) | C63: 0 | D63: =D40 | E63: =E40 | F63: =F40 | G63: =G40 | H63: =H40 | I63: =I40 | J63: =J40 | K63: =K40 | ... W63: =W40
B64: Inflow : 電費收入 | C64: - | D64: =D41 | E64: =E41 | F64: =F41 | G64: =G41 | H64: =H41 | I64: =I41 | J64: =J41 | K64: =K41 | ... W64: =W41
B65: Inflow : 政府補助 | C65: - | G65: - | H65: - | I65: - | J65: - | K65: - | L65: - | M65: - | N65: - | O65: - | P65: - | Q65: - | R65: - | S65: - | T65: - | U65: - | V65: - | W65: -
B66: Inflow : 銀行借款
B67: Outflow : 設備折舊 | D67: =$C$44/$E$16 | E67: =$C$44/$E$16 | F67: =$C$44/$E$16 | G67: =$C$44/$E$16 | H67: =$C$44/$E$16 | I67: =$C$44/$E$16 | J67: =$C$44/$E$16 | K67: =$C$44/$E$16 | ... W67: =$C$44/$E$16
B68: Outflow : 設備放置區域租金 | C68: - | D68: =D45 | E68: =E45 | F68: =F45 | G68: =G45 | H68: =H45 | I68: =I45 | J68: =J45 | K68: =K45 | ... W68: =W45
B69: Outflow : 返還借款
B70: Outflow : 利息費用 | C70: - | D70: 0 | E70: 0 | F70: 0 | G70: 0 | H70: 0 | I70: 0 | J70: 0 | K70: 0 | L70: 0 | M70: 0 | N70: 0 | O70: 0 | P70: 0 | Q70: 0 | R70: 0 | S70: 0 | T70: 0 | U70: 0 | V70: 0 | W70: 0
B71: Outflow : 維運費 | C71: - | D71: =D48 | E71: =E48 | F71: =F48 | G71: =G48 | H71: =H48 | I71: =I48 | J71: =J48 | K71: =K48 | ... W71: =W48
B72: Outflow : 保險費 | C72: - | D72: =D49 | E72: =E49 | F72: =F49 | G72: =G49 | H72: =H49 | I72: =I49 | J72: =J49 | K72: =K49 | ... W72: =W49
B73: Outflow : 模組回收費 | D73: =D50 | E73: =E50 | F73: =F50 | G73: =G50 | H73: =H50 | I73: =I50 | J73: =J50 | K73: =K50 | ... W73: =W50
B74: Outflow : 其它費用(人事薪資…等)
B75: 1%管理費
B76: 稅前淨利 | D76: =SUM(D64:D75) | E76: =SUM(E64:E75) | F76: =SUM(F64:F75) | G76: =SUM(G64:G75) | H76: =SUM(H64:H75) | I76: =SUM(I64:I75) | J76: =SUM(J64:J75) | K76: =SUM(K64:K75) | ... X76: =SUM(X64:X75)
B77: 所得稅20% | D77: =-D76*0.2 | E77: =-E76*0.2 | F77: =-F76*0.2 | G77: =-G76*0.2 | H77: =-H76*0.2 | I77: =-I76*0.2 | J77: =-J76*0.2 | K77: =-K76*0.2 | ... X77: =-X76*0.2
B78: 稅後淨利 | D78: =SUM(D76:D77) | E78: =SUM(E76:E77) | F78: =SUM(F76:F77) | G78: =SUM(G76:G77) | H78: =SUM(H76:H77) | I78: =SUM(I76:I77) | J78: =SUM(J76:J77) | K78: =SUM(K76:K77) | ... X78: =SUM(X76:X77)
B79: 累計現金流
B80: 回收年限評估

Sheet 表 62_滾算紀錄6
B1: 電站基本資料
B2: 電站名稱 | C2: 淡江大學-財務模擬案場 | D2: - | E2: -
B3: 電站壽命 | C3: 20 | D3: - | E3: -
B4: 建置量(kWp) | C4: 436.1 | D4: - | E4: - | M4: 滾算紀錄編號: 6
B5: 起始年度 | C5: 2023 | D5: 結束年度 | E5: 2042 | M5: 第5次滾算摘要
M6: 價金: 25000
B7: 綜合損益表 | M7: 專案IRR: 6.15
B8: 收入 | M8: 權益法IRR: 18.54
B9: 收支項目 | C9: 相關參數 | D9: 參數數值 | E9: 年限 | M9: 利潤率: 20.00%
B10: 電費收入 | C10: 年度AC併網總發電量 | D10: 547002 | E10: 20 | M10: 第5次滾算，減少 1000 元 - 現金模式，每次減少 1000 元
C11: 首年衰退率 | D11: 0.01
C12: 次年衰退率 | D12: 0.004
C13: 躉售費率(FIT) | D13: 3.7152
B14: 支出
B15: 收支項目 | C15: 相關參數 | D15: 參數數值 | E15: 攤提年限
B16: 設備費用(價金) | C16: 每kWp設備成本 | D16: 25000 | E16: 20
C17: 信邦利潤率 | D17: 0.2
C18: 開發費 | D18: 2000
B19: 租金費用 | C19: 租金計算方式 (1=固定攤提/2=電費抽成) | D19: 1 | E19: 0
C20: 【方式1參數】租金總額 | D20: 5804025 | E20: 20
C21: 【方式2參數】抽成比率 | D21: 0 | E21: 0
B22: 運維費用 | C22: 每kw運維成本 | D22: 400 | E22: 20
B23: 保險費用 | C23: 占整體設備費用比例 | D23: 0.003 | E23: 20
B24: 模組回收費用 | C24: 每kw模組回收成本 | D24: 1000 | E24: 10
B25: 利息費用 | C25: 銀行利率 | D25: 0.025595 | E25: 0
B26: 所得稅 | C26: 所得稅率 | D26: 0.2 | E26: 0
B29: 現金流量表
B30: 金流項目 | C30: 相關參數 | D30: 參數數值
B31: 貸款成數 | C31: 占總設備費用比例 | D31: 0.8
B32: 貸款還款 | C32: 攤還期數 | D32: 15
B33: 現金股利 | C33: 股利比率 | D33: 0.9
B34: 年底減資 | C34: 攤還期數 | D34: 4
C37: 年份 | D37: 2023 | E37: 2024 | F37: 2025 | G37: 2026 | H37: 2027 | I37: 2028 | J37: 2029 | K37: 2030 | L37: 2031 | M37: 2032 | N37: 2033 | O37: 2034 | P37: 2035 | Q37: 2036 | R37: 2037 | S37: 2038 | T37: 2039 | U37: 2040 | V37: 2041 | W37: 2042
B38: 0
B39: (Unit : Currency) | C39: 0 | D39: 1 | E39: 2 | F39: 3 | G39: 4 | H39: 5 | I39: 6 | J39: 7 | K39: 8 | L39: 9 | M39: 10 | N39: 11 | O39: 12 | P39: 13 | Q39: 14 | R39: 15 | S39: 16 | T39: 17 | U39: 18 | V39: 19 | W39: 20
B40: 發電度數(KWH) | C40: 0 | D40: =$D$10*0.99 | E40: =$D$10*0.986 | F40: =$D$10*0.982 | G40: =$D$10*0.978 | H40: =$D$10*0.974 | I40: =$D$10*0.97 | J40: =$D$10*0.966 | K40: =$D$10*0.962 | L40: =$D$10*0.958 | M40: =$D$10*0.954 | N40: =$D$10*0.95 | O40: =$D$10*0.946 | P40: =$D$10*0.942 | Q40: =$D$10*0.938 | R40: =$D$10*0.934 | S40: =$D$10*0.93 | T40: =$D$10*0.926 | U40: =$D$10*0.922 | V40: =$D$10*0.918 | W40: =$D$10*0.914
B41: Inflow : 電費收入 | C41: - | D41: =D40*$D$13 | E41: =E40*$D$13 | F41: =F40*$D$13 | G41: =G40*$D$13 | H41: =H40*$D$13 | I41: =I40*$D$13 | J41: =J40*$D$13 | K41: =K40*$D$13 | ... W41: =W40*$D$13
B42: Inflow : 政府補助 | C42: - | G42: - | H42: - | I42: - | J42: - | K42: - | L42: - | M42: - | N42: - | O42: - | P42: - | Q42: - | R42: - | S42: - | T42: - | U42: - | V42: - | W42: -
B43: Inflow : 銀行借款
B44: Outflow : 設備費用 | C44: =-(D16/(1-D17)+D18)*C4
B45: Outflow : 設備放置區域租金 | C45: - | D45: 0 | E45: -290201.25 | F45: -290201.25 | G45: -290201.25 | H45: -290201.25 | I45: -290201.25 | J45: -290201.25 | K45: -290201.25 | L45: -290201.25 | M45: -290201.25 | N45: -290201.25 | O45: -290201.25 | P45: -290201.25 | Q45: -290201.25 | R45: -290201.25 | S45: -290201.25 | T45: -290201.25 | U45: -290201.25 | V45: -290201.25 | W45: -290201.25
B46: Outflow : 返還借款
B47: Outflow : 利息費用 | C47: -
B48: Outflow : 維運費 | C48: - | D48: -174440 | E48: -174440 | F48: -174440 | G48: -174440 | H48: -174440 | I48: -174440 | J48: -174440 | K48: -174440 | L48: -174440 | M48: -174440 | N48: -174440 | O48: -174440 | P48: -174440 | Q48: -174440 | R48: -174440 | S48: -174440 | T48: -174440 | U48: -174440 | V48: -174440 | W48: -174440
B49: Outflow : 保險費 | C49: - | D49: -32707.5 | E49: -32707.5 | F49: -32707.5 | G49: -32707.5 | H49: -32707.5 | I49: -32707.5 | J49: -32707.5 | K49: -32707.5 | L49: -32707.5 | M49: -32707.5 | N49: -32707.5 | O49: -32707.5 | P49: -32707.5 | Q49: -32707.5 | R49: -32707.5 | S49: -32707.5 | T49: -32707.5 | U49: -32707.5 | V49: -32707.5 | W49: -32707.5
B50: Outflow : 模組回收費 | D50: -43610 | E50: -43610 | F50: -43610 | G50: -43610 | H50: -43610 | I50: -43610 | J50: -43610 | K50: -43610 | L50: -43610 | M50: -43610 | N50: 0 | O50: 0 | P50: 0 | Q50: 0 | R50: 0 | S50: 0 | T50: 0 | U50: 0 | V50: 0 | W50: 0
B51: Outflow : 其它費用(人事薪資…等)
B52: 1%管理費
B53: 績效獎金
B54: 所得稅20% | D54: =D77 | E54: =E77 | F54: =F77 | G54: =G77 | H54: =H77 | I54: =I77 | J54: =J77 | K54: =K77 | ... W54: =W77
B55: 現金流 | C55: =C44 | D55: =SUM(D41:D54) | E55: =SUM(E41:E54) | F55: =SUM(F41:F54) | G55: =SUM(G41:G54) | H55: =SUM(H41:H54) | I55: =SUM(I41:I54) | J55: =SUM(J41:J54) | K55: =SUM(K41:K54) | ... W55: =SUM(W41:W54)
B56: 累計現金流 | D56: =C55+D55 | E56: =D56+E55 | F56: =E56+F55 | G56: =F56+G55 | H56: =G56+H55 | I56: =H56+I55 | J56: =I56+J55 | K56: =J56+K55 | L56: =K56+L55 | ... X56: =W56+X55
B57: 回收年限評估 | D57: =IF((D56)>0,"回收","未回收") | E57: =IF((E56)>0,"回收","未回收") | F57: =IF((F56)>0,"回收","未回收") | G57: =IF((G56)>0,"回收","未回收") | H57: =IF((H56)>0,"回收","未回收") | I57: =IF((I56)>0,"回收","未回收") | J57: =IF((J56)>0,"回收","未回收") | K57: =IF((K56)>0,"回收","未回收") | ... X57: =IF((X56)>0,"回收","未回收")
B58: 專案法IRR | C58: =IRR(C55:W55)
C60: 年份 | D60: =D37 | E60: =E37 | F60: =F37 | G60: =G37 | H60: =H37 | I60: =I37 | J60: =J37 | K60: =K37 | ... W60: =W37
B61: 0 | T61: 償還年限
B62: (Unit : Currency) | C62: 0 | D62: 1 | E62: 2 | F62: 3 | G62: 4 | H62: 5 | I62: 6 | J62: 7 | K62: 8 | L62: 9 | M62: 10 | N62: 11 | O62: 12 | P62: 13 | Q62: 14 | R62: 15 | S62: 16 | T62: 17 | U62: 18 | V62: 19 | W62: 20
B63: 發電度數(KWH) | C63: 0 | D63: =D40 | E63: =E40 | F63: =F40 | G63: =G40 | H63: =H40 | I63: =I40 | J63: =J40 | K63: =K40 | ... W63: =W40
B64: Inflow : 電費收入 | C64: - | D64: =D41 | E64: =E41 | F64: =F41 | G64: =G41 | H64: =H41 | I64: =I41 | J64: =J41 | K64: =K41 | ... W64: =W41
B65: Inflow : 政府補助 | C65: - | G65: - | H65: - | I65: - | J65: - | K65: - | L65: - | M65: - | N65: - | O65: - | P65: - | Q65: - | R65: - | S65: - | T65: - | U65: - | V65: - | W65: -
B66: Inflow : 銀行借款
B67: Outflow : 設備折舊 | D67: =$C$44/$E$16 | E67: =$C$44/$E$16 | F67: =$C$44/$E$16 | G67: =$C$44/$E$16 | H67: =$C$44/$E$16 | I67: =$C$44/$E$16 | J67: =$C$44/$E$16 | K67: =$C$44/$E$16 | ... W67: =$C$44/$E$16
B68: Outflow : 設備放置區域租金 | C68: - | D68: =D45 | E68: =E45 | F68: =F45 | G68: =G45 | H68: =H45 | I68: =I45 | J68: =J45 | K68: =K45 | ... W68: =W45
B69: Outflow : 返還借款
B70: Outflow : 利息費用 | C70: - | D70: 0 | E70: 0 | F70: 0 | G70: 0 | H70: 0 | I70: 0 | J70: 0 | K70: 0 | L70: 0 | M70: 0 | N70: 0 | O70: 0 | P70: 0 | Q70: 0 | R70: 0 | S70: 0 | T70: 0 | U70: 0 | V70: 0 | W70: 0
B71: Outflow : 維運費 | C71: - | D71: =D48 | E71: =E48 | F71: =F48 | G71: =G48 | H71: =H48 | I71: =I48 | J71: =J48 | K71: =K48 | ... W71: =W48
B72: Outflow : 保險費 | C72: - | D72: =D49 | E72: =E49 | F72: =F49 | G72: =G49 | H72: =H49 | I72: =I49 | J72: =J49 | K72: =K49 | ... W72: =W49
B73: Outflow : 模組回收費 | D73: =D50 | E73: =E50 | F73: =F50 | G73: =G50 | H73: =H50 | I73: =I50 | J73: =J50 | K73: =K50 | ... W73: =W50
B74: Outflow : 其它費用(人事薪資…等)
B75: 1%管理費
B76: 稅前淨利 | D76: =SUM(D64:D75) | E76: =SUM(E64:E75) | F76: =SUM(F64:F75) | G76: =SUM(G64:G75) | H76: =SUM(H64:H75) | I76: =SUM(I64:I75) | J76: =SUM(J64:J75) | K76: =SUM(K64:K75) | ... X76: =SUM(X64:X75)
B77: 所得稅20% | D77: =-D76*0.2 | E77: =-E76*0.2 | F77: =-F76*0.2 | G77: =-G76*0.2 | H77: =-H76*0.2 | I77: =-I76*0.2 | J77: =-J76*0.2 | K77: =-K76*0.2 | ... X77: =-X76*0.2
B78: 稅後淨利 | D78: =SUM(D76:D77) | E78: =SUM(E76:E77) | F78: =SUM(F76:F77) | G78: =SUM(G76:G77) | H78: =SUM(H76:H77) | I78: =SUM(I76:I77) | J78: =SUM(J76:J77) | K78: =SUM(K76:K77) | ... X78: =SUM(X76:X77)
B79: 累計現金流
B80: 回收年限評估

Sheet 表 62_滾算紀錄8
B1: 電站基本資料
B2: 電站名稱 | C2: 淡江大學-財務模擬案場 | D2: - | E2: -
B3: 電站壽命 | C3: 20 | D3: - | E3: -
B4: 建置量(kWp) | C4: 436.1 | D4: - | E4: - | M4: 滾算紀錄編號: 8
B5: 起始年度 | C5: 2023 | D5: 結束年度 | E5: 2042 | M5: 第7次滾算摘要
M6: 價金: 23000
B7: 綜合損益表 | M7: 專案IRR: 7.06
B8: 收入 | M8: 權益法IRR: 23.4
B9: 收支項目 | C9: 相關參數 | D9: 參數數值 | E9: 年限 | M9: 利潤率: 20.00%
B10: 電費收入 | C10: 年度AC併網總發電量 | D10: 547002 | E10: 20 | M10: 第7次滾算，減少 1000 元 - 現金模式，每次減少 1000 元
C11: 首年衰退率 | D11: 0.01
C12: 次年衰退率 | D12: 0.004
C13: 躉售費率(FIT) | D13: 3.7152
B14: 支出
B15: 收支項目 | C15: 相關參數 | D15: 參數數值 | E15: 攤提年限
B16: 設備費用(價金) | C16: 每kWp設備成本 | D16: 23000 | E16: 20
C17: 信邦利潤率 | D17: 0.2
C18: 開發費 | D18: 2000
B19: 租金費用 | C19: 租金計算方式 (1=固定攤提/2=電費抽成) | D19: 1 | E19: 0
C20: 【方式1參數】租金總額 | D20: 5804025 | E20: 20
C21: 【方式2參數】抽成比率 | D21: 0 | E21: 0
B22: 運維費用 | C22: 每kw運維成本 | D22: 400 | E22: 20
B23: 保險費用 | C23: 占整體設備費用比例 | D23: 0.003 | E23: 20
B24: 模組回收費用 | C24: 每kw模組回收成本 | D24: 1000 | E24: 10
B25: 利息費用 | C25: 銀行利率 | D25: 0.025595 | E25: 0
B26: 所得稅 | C26: 所得稅率 | D26: 0.2 | E26: 0
B29: 現金流量表
B30: 金流項目 | C30: 相關參數 | D30: 參數數值
B31: 貸款成數 | C31: 占總設備費用比例 | D31: 0.8
B32: 貸款還款 | C32: 攤還期數 | D32: 15
B33: 現金股利 | C33: 股利比率 | D33: 0.9
B34: 年底減資 | C34: 攤還期數 | D34: 4
C37: 年份 | D37: 2023 | E37: 2024 | F37: 2025 | G37: 2026 | H37: 2027 | I37: 2028 | J37: 2029 | K37: 2030 | L37: 2031 | M37: 2032 | N37: 2033 | O37: 2034 | P37: 2035 | Q37: 2036 | R37: 2037 | S37: 2038 | T37: 2039 | U37: 2040 | V37: 2041 | W37: 2042
B38: 0
B39: (Unit : Currency) | C39: 0 | D39: 1 | E39: 2 | F39: 3 | G39: 4 | H39: 5 | I39: 6 | J39: 7 | K39: 8 | L39: 9 | M39: 10 | N39: 11 | O39: 12 | P39: 13 | Q39: 14 | R39: 15 | S39: 16 | T39: 17 | U39: 18 | V39: 19 | W39: 20
B40: 發電度數(KWH) | C40: 0 | D40: =$D$10*0.99 | E40: =$D$10*0.986 | F40: =$D$10*0.982 | G40: =$D$10*0.978 | H40: =$D$10*0.974 | I40: =$D$10*0.97 | J40: =$D$10*0.966 | K40: =$D$10*0.962 | L40: =$D$10*0.958 | M40: =$D$10*0.954 | N40: =$D$10*0.95 | O40: =$D$10*0.946 | P40: =$D$10*0.942 | Q40: =$D$10*0.938 | R40: =$D$10*0.934 | S40: =$D$10*0.93 | T40: =$D$10*0.926 | U40: =$D$10*0.922 | V40: =$D$10*0.918 | W40: =$D$10*0.914
B41: Inflow : 電費收入 | C41: - | D41: =D40*$D$13 | E41: =E40*$D$13 | F41: =F40*$D$13 | G41: =G40*$D$13 | H41: =H40*$D$13 | I41: =I40*$D$13 | J41: =J40*$D$13 | K41: =K40*$D$13 | ... W41: =W40*$D$13
B42: Inflow : 政府補助 | C42: - | G42: - | H42: - | I42: - | J42: - | K42: - | L42: - | M42: - | N42: - | O42: - | P42: - | Q42: - | R42: - | S42: - | T42: - | U42: - | V42: - | W42: -
B43: Inflow : 銀行借款
B44: Outflow : 設備費用 | C44: =-(D16/(1-D17)+D18)*C4
B45: Outflow : 設備放置區域租金 | C45: - | D45: 0 | E45: -290201.25 | F45: -290201.25 | G45: -290201.25 | H45: -290201.25 | I45: -290201.25 | J45: -290201.25 | K45: -290201.25 | L45: -290201.25 | M45: -290201.25 | N45: -290201.25 | O45: -290201.25 | P45: -290201.25 | Q45: -290201.25 | R45: -290201.25 | S45: -290201.25 | T45: -290201.25 | U45: -290201.25 | V45: -290201.25 | W45: -290201.25
B46: Outflow : 返還借款
B47: Outflow : 利息費用 | C47: -
B48: Outflow : 維運費 | C48: - | D48: -174440 | E48: -174440 | F48: -174440 | G48: -174440 | H48: -174440 | I48: -174440 | J48: -174440 | K48: -174440 | L48: -174440 | M48: -174440 | N48: -174440 | O48: -174440 | P48: -174440 | Q48: -174440 | R48: -174440 | S48: -174440 | T48: -174440 | U48: -174440 | V48: -174440 | W48: -174440
B49: Outflow : 保險費 | C49: - | D49: -30090.9 | E49: -30090.9 | F49: -30090.9 | G49: -30090.9 | H49: -30090.9 | I49: -30090.9 | J49: -30090.9 | K49: -30090.9 | L49: -30090.9 | M49: -30090.9 | N49: -30090.9 | O49: -30090.9 | P49: -30090.9 | Q49: -30090.9 | R49: -30090.9 | S49: -30090.9 | T49: -30090.9 | U49: -30090.9 | V49: -30090.9 | W49: -30090.9
B50: Outflow : 模組回收費 | D50: -43610 | E50: -43610 | F50: -43610 | G50: -43610 | H50: -43610 | I50: -43610 | J50: -43610 | K50: -43610 | L50: -43610 | M50: -43610 | N50: 0 | O50: 0 | P50: 0 | Q50: 0 | R50: 0 | S50: 0 | T50: 0 | U50: 0 | V50: 0 | W50: 0
B51: Outflow : 其它費用(人事薪資…等)
B52: 1%管理費
B53: 績效獎金
B54: 所得稅20% | D54: =D77 | E54: =E77 | F54: =F77 | G54: =G77 | H54: =H77 | I54: =I77 | J54: =J77 | K54: =K77 | ... W54: =W77
B55: 現金流 | C55: =C44 | D55: =SUM(D41:D54) | E55: =SUM(E41:E54) | F55: =SUM(F41:F54) | G55: =SUM(G41:G54) | H55: =SUM(H41:H54) | I55: =SUM(I41:I54) | J55: =SUM(J41:J54) | K55: =SUM(K41:K54) | ... W55: =SUM(W41:W54)
B56: 累計現金流 | D56: =C55+D55 | E56: =D56+E55 | F56: =E56+F55 | G56: =F56+G55 | H56: =G56+H55 | I56: =H56+I55 | J56: =I56+J55 | K56: =J56+K55 | L56: =K56+L55 | ... X56: =W56+X55
B57: 回收年限評估 | D57: =IF((D56)>0,"回收","未回收") | E57: =IF((E56)>0,"回收","未回收") | F57: =IF((F56)>0,"回收","未回收") | G57: =IF((G56)>0,"回收","未回收") | H57: =IF((H56)>0,"回收","未回收") | I57: =IF((I56)>0,"回收","未回收") | J57: =IF((J56)>0,"回收","未回收") | K57: =IF((K56)>0,"回收","未回收") | ... X57: =IF((X56)>0,"回收","未回收")
B58: 專案法IRR | C58: =IRR(C55:W55)
C60: 年份 | D60: =D37 | E60: =E37 | F60: =F37 | G60: =G37 | H60: =H37 | I60: =I37 | J60: =J37 | K60: =K37 | ... W60: =W37
B61: 0 | T61: 償還年限
B62: (Unit : Currency) | C62: 0 | D62: 1 | E62: 2 | F62: 3 | G62: 4 | H62: 5 | I62: 6 | J62: 7 | K62: 8 | L62: 9 | M62: 10 | N62: 11 | O62: 12 | P62: 13 | Q62: 14 | R62: 15 | S62: 16 | T62: 17 | U62: 18 | V62: 19 | W62: 20
B63: 發電度數(KWH) | C63: 0 | D63: =D40 | E63: =E40 | F63: =F40 | G63: =G40 | H63: =H40 | I63: =I40 | J63: =J40 | K63: =K40 | ... W63: =W40
B64: Inflow : 電費收入 | C64: - | D64: =D41 | E64: =E41 | F64: =F41 | G64: =G41 | H64: =H41 | I64: =I41 | J64: =J41 | K64: =K41 | ... W64: =W41
B65: Inflow : 政府補助 | C65: - | G65: - | H65: - | I65: - | J65: - | K65: - | L65: - | M65: - | N65: - | O65: - | P65: - | Q65: - | R65: - | S65: - | T65: - | U65: - | V65: - | W65: -
B66: Inflow : 銀行借款
B67: Outflow : 設備折舊 | D67: =$C$44/$E$16 | E67: =$C$44/$E$16 | F67: =$C$44/$E$16 | G67: =$C$44/$E$16 | H67: =$C$44/$E$16 | I67: =$C$44/$E$16 | J67: =$C$44/$E$16 | K67: =$C$44/$E$16 | ... W67: =$C$44/$E$16
B68: Outflow : 設備放置區域租金 | C68: - | D68: =D45 | E68: =E45 | F68: =F45 | G68: =G45 | H68: =H45 | I68: =I45 | J68: =J45 | K68: =K45 | ... W68: =W45
B69: Outflow : 返還借款
B70: Outflow : 利息費用 | C70: - | D70: 0 | E70: 0 | F70: 0 | G70: 0 | H70: 0 | I70: 0 | J70: 0 | K70: 0 | L70: 0 | M70: 0 | N70: 0 | O70: 0 | P70: 0 | Q70: 0 | R70: 0 | S70: 0 | T70: 0 | U70: 0 | V70: 0 | W70: 0
B71: Outflow : 維運費 | C71: - | D71: =D48 | E71: =E48 | F71: =F48 | G71: =G48 | H71: =H48 | I71: =I48 | J71: =J48 | K71: =K48 | ... W71: =W48
B72: Outflow : 保險費 | C72: - | D72: =D49 | E72: =E49 | F72: =F49 | G72: =G49 | H72: =H49 | I72: =I49 | J72: =J49 | K72: =K49 | ... W72: =W49
B73: Outflow : 模組回收費 | D73: =D50 | E73: =E50 | F73: =F50 | G73: =G50 | H73: =H50 | I73: =I50 | J73: =J50 | K73: =K50 | ... W73: =W50
B74: Outflow : 其它費用(人事薪資…等)
B75: 1%管理費
B76: 稅前淨利 | D76: =SUM(D64:D75) | E76: =SUM(E64:E75) | F76: =SUM(F64:F75) | G76: =SUM(G64:G75) | H76: =SUM(H64:H75) | I76: =SUM(I64:I75) | J76: =SUM(J64:J75) | K76: =SUM(K64:K75) | ... X76: =SUM(X64:X75)
B77: 所得稅20% | D77: =-D76*0.2 | E77: =-E76*0.2 | F77: =-F76*0.2 | G77: =-G76*0.2 | H77: =-H76*0.2 | I77: =-I76*0.2 | J77: =-J76*0.2 | K77: =-K76*0.2 | ... X77: =-X76*0.2
B78: 稅後淨利 | D78: =SUM(D76:D77) | E78: =SUM(E76:E77) | F78: =SUM(F76:F77) | G78: =SUM(G76:G77) | H78: =SUM(H76:H77) | I78: =SUM(I76:I77) | J78: =SUM(J76:J77) | K78: =SUM(K76:K77) | ... X78: =SUM(X76:X77)
B79: 累計現金流
B80: 回收年限評估
