Workbook

Sheet 多站彙整
C4: 年份 | D4: 2023 | E4: 2024 | F4: 2025 | G4: 2026 | H4: 2027 | I4: 2028 | J4: 2029 | K4: 2030 | L4: 2031 | M4: 2032 | N4: 2033 | O4: 2034 | P4: 2035 | Q4: 2036 | R4: 2037 | S4: 2038 | T4: 2039 | U4: 2040 | V4: 2041 | W4: 2042
C5: 預估發電度數
B6: 表 105 | D6: =ABS('表 105_滾算紀錄1'!D40) | E6: =ABS('表 105_滾算紀錄1'!E40) | F6: =ABS('表 105_滾算紀錄1'!F40) | G6: =ABS('表 105_滾算紀錄1'!G40) | H6: =ABS('表 105_滾算紀錄1'!H40) | I6: =ABS('表 105_滾算紀錄1'!I40) | J6: =ABS('表 105_滾算紀錄1'!J40) | K6: =ABS('表 105_滾算紀錄1'!K40) | ... W6: =ABS('表 105_滾算紀錄1'!W40)
B7: 表 105 | D7: =ABS('表 105_滾算紀錄2'!D40) | E7: =ABS('表 105_滾算紀錄2'!E40) | F7: =ABS('表 105_滾算紀錄2'!F40) | G7: =ABS('表 105_滾算紀錄2'!G40) | H7: =ABS('表 105_滾算紀錄2'!H40) | I7: =ABS('表 105_滾算紀錄2'!I40) | J7: =ABS('表 105_滾算紀錄2'!J40) | K7: =ABS('表 105_滾算紀錄2'!K40) | ... W7: =ABS('表 105_滾算紀錄2'!W40)
B8: 表 105 | D8: =ABS('表 105_滾算紀錄3'!D40) | E8: =ABS('表 105_滾算紀錄3'!E40) | F8: =ABS('表 105_滾算紀錄3'!F40) | G8: =ABS('表 105_滾算紀錄3'!G40) | H8: =ABS('表 105_滾算紀錄3'!H40) | I8: =ABS('表 105_滾算紀錄3'!I40) | J8: =ABS('表 105_滾算紀錄3'!J40) | K8: =ABS('表 105_滾算紀錄3'!K40) | ... W8: =ABS('表 105_滾算紀錄3'!W40)
C9: 預估發電度數/年總計 | D9: =SUM(D6:D8) | E9: =SUM(E6:E8) | F9: =SUM(F6:F8) | G9: =SUM(G6:G8) | H9: =SUM(H6:H8) | I9: =SUM(I6:I8) | J9: =SUM(J6:J8) | K9: =SUM(K6:K8) | ... W9: =SUM(W6:W8)
C10: 預估收入 | D10: 2023 | E10: 2024 | F10: 2025 | G10: 2026 | H10: 2027 | I10: 2028 | J10: 2029 | K10: 2030 | L10: 2031 | M10: 2032 | N10: 2033 | O10: 2034 | P10: 2035 | Q10: 2036 | R10: 2037 | S10: 2038 | T10: 2039 | U10: 2040 | V10: 2041 | W10: 2042
B11: 表 105 | D11: =ABS('表 105_滾算紀錄1'!D41) | E11: =ABS('表 105_滾算紀錄1'!E41) | F11: =ABS('表 105_滾算紀錄1'!F41) | G11: =ABS('表 105_滾算紀錄1'!G41) | H11: =ABS('表 105_滾算紀錄1'!H41) | I11: =ABS('表 105_滾算紀錄1'!I41) | J11: =ABS('表 105_滾算紀錄1'!J41) | K11: =ABS('表 105_滾算紀錄1'!K41) | ... W11: =ABS('表 105_滾算紀錄1'!W41)
B12: 表 105 | D12: =ABS('表 105_滾算紀錄2'!D41) | E12: =ABS('表 105_滾算紀錄2'!E41) | F12: =ABS('表 105_滾算紀錄2'!F41) | G12: =ABS('表 105_滾算紀錄2'!G41) | H12: =ABS('表 105_滾算紀錄2'!H41) | I12: =ABS('表 105_滾算紀錄2'!I41) | J12: =ABS('表 105_滾算紀錄2'!J41) | K12: =ABS('表 105_滾算紀錄2'!K41) | ... W12: =ABS('表 105_滾算紀錄2'!W41)
B13: 表 105 | D13: =ABS('表 105_滾算紀錄3'!D41) | E13: =ABS('表 105_滾算紀錄3'!E41) | F13: =ABS('表 105_滾算紀錄3'!F41) | G13: =ABS('表 105_滾算紀錄3'!G41) | H13: =ABS('表 105_滾算紀錄3'!H41) | I13: =ABS('表 105_滾算紀錄3'!I41) | J13: =ABS('表 105_滾算紀錄3'!J41) | K13: =ABS('表 105_滾算紀錄3'!K41) | ... W13: =ABS('表 105_滾算紀錄3'!W41)
C14: 預估收入/年總計 | D14: =SUM(D11:D13) | E14: =SUM(E11:E13) | F14: =SUM(F11:F13) | G14: =SUM(G11:G13) | H14: =SUM(H11:H13) | I14: =SUM(I11:I13) | J14: =SUM(J11:J13) | K14: =SUM(K11:K13) | ... W14: =SUM(W11:W13)
C15: 租金 | D15: 2023 | E15: 2024 | F15: 2025 | G15: 2026 | H15: 2027 | I15: 2028 | J15: 2029 | K15: 2030 | L15: 2031 | M15: 2032 | N15: 2033 | O15: 2034 | P15: 2035 | Q15: 2036 | R15: 2037 | S15: 2038 | T15: 2039 | U15: 2040 | V15: 2041 | W15: 2042
B16: 表 105 | D16: =ABS('表 105_滾算紀錄1'!D45) | E16: =ABS('表 105_滾算紀錄1'!E45) | F16: =ABS('表 105_滾算紀錄1'!F45) | G16: =ABS('表 105_滾算紀錄1'!G45) | H16: =ABS('表 105_滾算紀錄1'!H45) | I16: =ABS('表 105_滾算紀錄1'!I45) | J16: =ABS('表 105_滾算紀錄1'!J45) | K16: =ABS('表 105_滾算紀錄1'!K45) | ... W16: =ABS('表 105_滾算紀錄1'!W45)
B17: 表 105 | D17: =ABS('表 105_滾算紀錄2'!D45) | E17: =ABS('表 105_滾算紀錄2'!E45) | F17: =ABS('表 105_滾算紀錄2'!F45) | G17: =ABS('表 105_滾算紀錄2'!G45) | H17: =ABS('表 105_滾算紀錄2'!H45) | I17: =ABS('表 105_滾算紀錄2'!I45) | J17: =ABS('表 105_滾算紀錄2'!J45) | K17: =ABS('表 105_滾算紀錄2'!K45) | ... W17: =ABS('表 105_滾算紀錄2'!W45)
B18: 表 105 | D18: =ABS('表 105_滾算紀錄3'!D45) | E18: =ABS('表 105_滾算紀錄3'!E45) | F18: =ABS('表 105_滾算紀錄3'!F45) | G18: =ABS('表 105_滾算紀錄3'!G45) | H18: =ABS('表 105_滾算紀錄3'!H45) | I18: =ABS('表 105_滾算紀錄3'!I45) | J18: =ABS('表 105_滾算紀錄3'!J45) | K18: =ABS('表 105_滾算紀錄3'!K45) | ... W18: =ABS('表 105_滾算紀錄3'!W45)
C19: 租金/年總計 | D19: =SUM(D16:D18) | E19: =SUM(E16:E18) | F19: =SUM(F16:F18) | G19: =SUM(G16:G18) | H19: =SUM(H16:H18) | I19: =SUM(I16:I18) | J19: =SUM(J16:J18) | K19: =SUM(K16:K18) | ... W19: =SUM(W16:W18)
C20: 運維 | D20: 2023 | E20: 2024 | F20: 2025 | G20: 2026 | H20: 2027 | I20: 2028 | J20: 2029 | K20: 2030 | L20: 2031 | M20: 2032 | N20: 2033 | O20: 2034 | P20: 2035 | Q20: 2036 | R20: 2037 | S20: 2038 | T20: 2039 | U20: 2040 | V20: 2041 | W20: 2042
B21: 表 105 | D21: =ABS('表 105_滾算紀錄1'!D48) | E21: =ABS('表 105_滾算紀錄1'!E48) | F21: =ABS('表 105_滾算紀錄1'!F48) | G21: =ABS('表 105_滾算紀錄1'!G48) | H21: =ABS('表 105_滾算紀錄1'!H48) | I21: =ABS('表 105_滾算紀錄1'!I48) | J21: =ABS('表 105_滾算紀錄1'!J48) | K21: =ABS('表 105_滾算紀錄1'!K48) | ... W21: =ABS('表 105_滾算紀錄1'!W48)
B22: 表 105 | D22: =ABS('表 105_滾算紀錄2'!D48) | E22: =ABS('表 105_滾算紀錄2'!E48) | F22: =ABS('表 105_滾算紀錄2'!F48) | G22: =ABS('表 105_滾算紀錄2'!G48) | H22: =ABS('表 105_滾算紀錄2'!H48) | I22: =ABS('表 105_滾算紀錄2'!I48) | J22: =ABS('表 105_滾算紀錄2'!J48) | K22: =ABS('表 105_滾算紀錄2'!K48) | ... W22: =ABS('表 105_滾算紀錄2'!W48)
B23: 表 105 | D23: =ABS('表 105_滾算紀錄3'!D48) | E23: =ABS('表 105_滾算紀錄3'!E48) | F23: =ABS('表 105_滾算紀錄3'!F48) | G23: =ABS('表 105_滾算紀錄3'!G48) | H23: =ABS('表 105_滾算紀錄3'!H48) | I23: =ABS('表 105_滾算紀錄3'!I48) | J23: =ABS('表 105_滾算紀錄3'!J48) | K23: =ABS('表 105_滾算紀錄3'!K48) | ... W23: =ABS('表 105_滾算紀錄3'!W48)
C24: 運維/年總計 | D24: =SUM(D21:D23) | E24: =SUM(E21:E23) | F24: =SUM(F21:F23) | G24: =SUM(G21:G23) | H24: =SUM(H21:H23) | I24: =SUM(I21:I23) | J24: =SUM(J21:J23) | K24: =SUM(K21:K23) | ... W24: =SUM(W21:W23)
C25: 保險 | D25: 2023 | E25: 2024 | F25: 2025 | G25: 2026 | H25: 2027 | I25: 2028 | J25: 2029 | K25: 2030 | L25: 2031 | M25: 2032 | N25: 2033 | O25: 2034 | P25: 2035 | Q25: 2036 | R25: 2037 | S25: 2038 | T25: 2039 | U25: 2040 | V25: 2041 | W25: 2042
B26: 表 105 | D26: =ABS('表 105_滾算紀錄1'!D49) | E26: =ABS('表 105_滾算紀錄1'!E49) | F26: =ABS('表 105_滾算紀錄1'!F49) | G26: =ABS('表 105_滾算紀錄1'!G49) | H26: =ABS('表 105_滾算紀錄1'!H49) | I26: =ABS('表 105_滾算紀錄1'!I49) | J26: =ABS('表 105_滾算紀錄1'!J49) | K26: =ABS('表 105_滾算紀錄1'!K49) | ... W26: =ABS('表 105_滾算紀錄1'!W49)
B27: 表 105 | D27: =ABS('表 105_滾算紀錄2'!D49) | E27: =ABS('表 105_滾算紀錄2'!E49) | F27: =ABS('表 105_滾算紀錄2'!F49) | G27: =ABS('表 105_滾算紀錄2'!G49) | H27: =ABS('表 105_滾算紀錄2'!H49) | I27: =ABS('表 105_滾算紀錄2'!I49) | J27: =ABS('表 105_滾算紀錄2'!J49) | K27: =ABS('表 105_滾算紀錄2'!K49) | ... W27: =ABS('表 105_滾算紀錄2'!W49)
B28: 表 105 | D28: =ABS('表 105_滾算紀錄3'!D49) | E28: =ABS('表 105_滾算紀錄3'!E49) | F28: =ABS('表 105_滾算紀錄3'!F49) | G28: =ABS('表 105_滾算紀錄3'!G49) | H28: =ABS('表 105_滾算紀錄3'!H49) | I28: =ABS('表 105_滾算紀錄3'!I49) | J28: =ABS('表 105_滾算紀錄3'!J49) | K28: =ABS('表 105_滾算紀錄3'!K49) | ... W28: =ABS('表 105_滾算紀錄3'!W49)
C29: 保險/年總計 | D29: =SUM(D26:D28) | E29: =SUM(E26:E28) | F29: =SUM(F26:F28) | G29: =SUM(G26:G28) | H29: =SUM(H26:H28) | I29: =SUM(I26:I28) | J29: =SUM(J26:J28) | K29: =SUM(K26:K28) | ... W29: =SUM(W26:W28)
C30: 模組回收費 | D30: 2023 | E30: 2024 | F30: 2025 | G30: 2026 | H30: 2027 | I30: 2028 | J30: 2029 | K30: 2030 | L30: 2031 | M30: 2032 | N30: 2033 | O30: 2034 | P30: 2035 | Q30: 2036 | R30: 2037 | S30: 2038 | T30: 2039 | U30: 2040 | V30: 2041 | W30: 2042
B31: 表 105 | D31: =ABS('表 105_滾算紀錄1'!D50) | E31: =ABS('表 105_滾算紀錄1'!E50) | F31: =ABS('表 105_滾算紀錄1'!F50) | G31: =ABS('表 105_滾算紀錄1'!G50) | H31: =ABS('表 105_滾算紀錄1'!H50) | I31: =ABS('表 105_滾算紀錄1'!I50) | J31: =ABS('表 105_滾算紀錄1'!J50) | K31: =ABS('表 105_滾算紀錄1'!K50) | ... W31: =ABS('表 105_滾算紀錄1'!W50)
B32: 表 105 | D32: =ABS('表 105_滾算紀錄2'!D50) | E32: =ABS('表 105_滾算紀錄2'!E50) | F32: =ABS('表 105_滾算紀錄2'!F50) | G32: =ABS('表 105_滾算紀錄2'!G50) | H32: =ABS('表 105_滾算紀錄2'!H50) | I32: =ABS('表 105_滾算紀錄2'!I50) | J32: =ABS('表 105_滾算紀錄2'!J50) | K32: =ABS('表 105_滾算紀錄2'!K50) | ... W32: =ABS('表 105_滾算紀錄2'!W50)
B33: 表 105 | D33: =ABS('表 105_滾算紀錄3'!D50) | E33: =ABS('表 105_滾算紀錄3'!E50) | F33: =ABS('表 105_滾算紀錄3'!F50) | G33: =ABS('表 105_滾算紀錄3'!G50) | H33: =ABS('表 105_滾算紀錄3'!H50) | I33: =ABS('表 105_滾算紀錄3'!I50) | J33: =ABS('表 105_滾算紀錄3'!J50) | K33: =ABS('表 105_滾算紀錄3'!K50) | ... W33: =ABS('表 105_滾算紀錄3'!W50)
C34: 模組回收費/年總計 | D34: =SUM(D31:D33) | E34: =SUM(E31:E33) | F34: =SUM(F31:F33) | G34: =SUM(G31:G33) | H34: =SUM(H31:H33) | I34: =SUM(I31:I33) | J34: =SUM(J31:J33) | K34: =SUM(K31:K33) | ... W34: =SUM(W31:W33)
C35: 所得稅 | D35: 2023 | E35: 2024 | F35: 2025 | G35: 2026 | H35: 2027 | I35: 2028 | J35: 2029 | K35: 2030 | L35: 2031 | M35: 2032 | N35: 2033 | O35: 2034 | P35: 2035 | Q35: 2036 | R35: 2037 | S35: 2038 | T35: 2039 | U35: 2040 | V35: 2041 | W35: 2042
B36: 表 105 | D36: =ABS('表 105_滾算紀錄1'!D54) | E36: =ABS('表 105_滾算紀錄1'!E54) | F36: =ABS('表 105_滾算紀錄1'!F54) | G36: =ABS('表 105_滾算紀錄1'!G54) | H36: =ABS('表 105_滾算紀錄1'!H54) | I36: =ABS('表 105_滾算紀錄1'!I54) | J36: =ABS('表 105_滾算紀錄1'!J54) | K36: =ABS('表 105_滾算紀錄1'!K54) | ... W36: =ABS('表 105_滾算紀錄1'!W54)
B37: 表 105 | D37: =ABS('表 105_滾算紀錄2'!D54) | E37: =ABS('表 105_滾算紀錄2'!E54) | F37: =ABS('表 105_滾算紀錄2'!F54) | G37: =ABS('表 105_滾算紀錄2'!G54) | H37: =ABS('表 105_滾算紀錄2'!H54) | I37: =ABS('表 105_滾算紀錄2'!I54) | J37: =ABS('表 105_滾算紀錄2'!J54) | K37: =ABS('表 105_滾算紀錄2'!K54) | ... W37: =ABS('表 105_滾算紀錄2'!W54)
B38: 表 105 | D38: =ABS('表 105_滾算紀錄3'!D54) | E38: =ABS('表 105_滾算紀錄3'!E54) | F38: =ABS('表 105_滾算紀錄3'!F54) | G38: =ABS('表 105_滾算紀錄3'!G54) | H38: =ABS('表 105_滾算紀錄3'!H54) | I38: =ABS('表 105_滾算紀錄3'!I54) | J38: =ABS('表 105_滾算紀錄3'!J54) | K38: =ABS('表 105_滾算紀錄3'!K54) | ... W38: =ABS('表 105_滾算紀錄3'!W54)
C39: 所得稅/年總計 | D39: =SUM(D36:D38) | E39: =SUM(E36:E38) | F39: =SUM(F36:F38) | G39: =SUM(G36:G38) | H39: =SUM(H36:H38) | I39: =SUM(I36:I38) | J39: =SUM(J36:J38) | K39: =SUM(K36:K38) | ... W39: =SUM(W36:W38)
C40: 設備折舊 | D40: 2023 | E40: 2024 | F40: 2025 | G40: 2026 | H40: 2027 | I40: 2028 | J40: 2029 | K40: 2030 | L40: 2031 | M40: 2032 | N40: 2033 | O40: 2034 | P40: 2035 | Q40: 2036 | R40: 2037 | S40: 2038 | T40: 2039 | U40: 2040 | V40: 2041 | W40: 2042
B41: 表 105 | D41: =ABS('表 105_滾算紀錄1'!D67) | E41: =ABS('表 105_滾算紀錄1'!E67) | F41: =ABS('表 105_滾算紀錄1'!F67) | G41: =ABS('表 105_滾算紀錄1'!G67) | H41: =ABS('表 105_滾算紀錄1'!H67) | I41: =ABS('表 105_滾算紀錄1'!I67) | J41: =ABS('表 105_滾算紀錄1'!J67) | K41: =ABS('表 105_滾算紀錄1'!K67) | ... W41: =ABS('表 105_滾算紀錄1'!W67)
B42: 表 105 | D42: =ABS('表 105_滾算紀錄2'!D67) | E42: =ABS('表 105_滾算紀錄2'!E67) | F42: =ABS('表 105_滾算紀錄2'!F67) | G42: =ABS('表 105_滾算紀錄2'!G67) | H42: =ABS('表 105_滾算紀錄2'!H67) | I42: =ABS('表 105_滾算紀錄2'!I67) | J42: =ABS('表 105_滾算紀錄2'!J67) | K42: =ABS('表 105_滾算紀錄2'!K67) | ... W42: =ABS('表 105_滾算紀錄2'!W67)
B43: 表 105 | D43: =ABS('表 105_滾算紀錄3'!D67) | E43: =ABS('表 105_滾算紀錄3'!E67) | F43: =ABS('表 105_滾算紀錄3'!F67) | G43: =ABS('表 105_滾算紀錄3'!G67) | H43: =ABS('表 105_滾算紀錄3'!H67) | I43: =ABS('表 105_滾算紀錄3'!I67) | J43: =ABS('表 105_滾算紀錄3'!J67) | K43: =ABS('表 105_滾算紀錄3'!K67) | ... W43: =ABS('表 105_滾算紀錄3'!W67)
C44: 設備折舊/年總計 | D44: =SUM(D41:D43) | E44: =SUM(E41:E43) | F44: =SUM(F41:F43) | G44: =SUM(G41:G43) | H44: =SUM(H41:H43) | I44: =SUM(I41:I43) | J44: =SUM(J41:J43) | K44: =SUM(K41:K43) | ... W44: =SUM(W41:W43)
B46: 貸款成數(%) | C46: 80
B47: 還款期數 | C47: 15
B48: 股利比率(%) | C48: 90
B49: 年底減資攤還期數 | C49: 4
B50: 銀行利率(%) | C50: 2.5595
C51: 年份 | D51: 2023 | E51: 2024 | F51: 2025 | G51: 2026 | H51: 2027 | I51: 2028 | J51: 2029 | K51: 2030 | L51: 2031 | M51: 2032 | N51: 2033 | O51: 2034 | P51: 2035 | Q51: 2036 | R51: 2037 | S51: 2038 | T51: 2039 | U51: 2040 | V51: 2041 | W51: 2042
B52: 0
B53: (Unit : Currency) | C53: 0 | D53: 1 | E53: 2 | F53: 3 | G53: 4 | H53: 5 | I53: 6 | J53: 7 | K53: 8 | L53: 9 | M53: 10 | N53: 11 | O53: 12 | P53: 13 | Q53: 14 | R53: 15 | S53: 16 | T53: 17 | U53: 18 | V53: 19 | W53: 20
B54: 發電度數(KWH) | C54: 0 | D54: =D9 | E54: =E9 | F54: =F9 | G54: =G9 | H54: =H9 | I54: =I9 | J54: =J9 | K54: =K9 | ... W54: =W9
B55: Inflow : 電費收入 | C55: - | D55: =D14 | E55: =E14 | F55: =F14 | G55: =G14 | H55: =H14 | I55: =I14 | J55: =J14 | K55: =K14 | ... W55: =W14
B56: Inflow : 政府補助 | C56: - | G56: - | H56: - | I56: - | J56: - | K56: - | L56: - | M56: - | N56: - | O56: - | P56: - | Q56: - | R56: - | S56: - | T56: - | U56: - | V56: - | W56: -
B57: Inflow : 銀行借款
B58: Outflow : 設備費用 | C58: =-SUM(D44:W44)
B59: Outflow : 設備放置區域租金 | C59: - | D59: =-D19 | E59: =-E19 | F59: =-F19 | G59: =-G19 | H59: =-H19 | I59: =-I19 | J59: =-J19 | K59: =-K19 | ... W59: =-W19
B60: Outflow : 返還借款
B61: Outflow : 利息費用 | C61: -
B62: Outflow : 維運費 | C62: - | D62: =-D24 | E62: =-E24 | F62: =-F24 | G62: =-G24 | H62: =-H24 | I62: =-I24 | J62: =-J24 | K62: =-K24 | ... W62: =-W24
B63: Outflow : 保險費 | C63: - | D63: =-D29 | E63: =-E29 | F63: =-F29 | G63: =-G29 | H63: =-H29 | I63: =-I29 | J63: =-J29 | K63: =-K29 | ... W63: =-W29
B64: Outflow : 模組回收費 | D64: =-D34 | E64: =-E34 | F64: =-F34 | G64: =-G34 | H64: =-H34 | I64: =-I34 | J64: =-J34 | K64: =-K34 | ... W64: =-W34
B65: Outflow : 其它費用(人事薪資…等)
B66: 1%管理費
B67: 績效獎金
B68: 所得稅20% | D68: =-D91 | E68: =-E91 | F68: =-F91 | G68: =-G91 | H68: =-H91 | I68: =-I91 | J68: =-J91 | K68: =-K91 | ... W68: =-W91
B69: 現金流 | C69: =C58 | D69: =SUM(D55:D68) | E69: =SUM(E55:E68) | F69: =SUM(F55:F68) | G69: =SUM(G55:G68) | H69: =SUM(H55:H68) | I69: =SUM(I55:I68) | J69: =SUM(J55:J68) | K69: =SUM(K55:K68) | ... W69: =SUM(W55:W68)
B70: 累計現金流 | D70: =C55+D55 | E70: =D56+E55 | F70: =E56+F55 | G70: =F56+G55 | H70: =G56+H55 | I70: =H56+I55 | J70: =I56+J55 | K70: =J56+K55 | L70: =K56+L55 | ... W70: =V56+W55
B71: 回收年限評估 | D71: =IF((D56)>0,"回收","未回收") | E71: =IF((E56)>0,"回收","未回收") | F71: =IF((F56)>0,"回收","未回收") | G71: =IF((G56)>0,"回收","未回收") | H71: =IF((H56)>0,"回收","未回收") | I71: =IF((I56)>0,"回收","未回收") | J71: =IF((J56)>0,"回收","未回收") | K71: =IF((K56)>0,"回收","未回收") | ... W71: =IF((W56)>0,"回收","未回收")
B72: 專案法IRR | C72: =IRR(C69:W69)
C74: 年份 | D74: 2023 | E74: 2024 | F74: 2025 | G74: 2026 | H74: 2027 | I74: 2028 | J74: 2029 | K74: 2030 | L74: 2031 | M74: 2032 | N74: 2033 | O74: 2034 | P74: 2035 | Q74: 2036 | R74: 2037 | S74: 2038 | T74: 2039 | U74: 2040 | V74: 2041 | W74: 2042
B75: 0 | T75: 償還年限
B76: (Unit : Currency) | C76: 0 | D76: 1 | E76: 2 | F76: 3 | G76: 4 | H76: 5 | I76: 6 | J76: 7 | K76: 8 | L76: 9 | M76: 10 | N76: 11 | O76: 12 | P76: 13 | Q76: 14 | R76: 15 | S76: 16 | T76: 17 | U76: 18 | V76: 19 | W76: 20
B77: 發電度數(KWH) | C77: 0 | D77: =D9 | E77: =E9 | F77: =F9 | G77: =G9 | H77: =H9 | I77: =I9 | J77: =J9 | K77: =K9 | ... W77: =W9
B78: Inflow : 電費收入 | C78: - | D78: =D14 | E78: =E14 | F78: =F14 | G78: =G14 | H78: =H14 | I78: =I14 | J78: =J14 | K78: =K14 | ... W78: =W14
B79: Inflow : 政府補助 | C79: - | G79: - | H79: - | I79: - | J79: - | K79: - | L79: - | M79: - | N79: - | O79: - | P79: - | Q79: - | R79: - | S79: - | T79: - | U79: - | V79: - | W79: -
B80: Inflow : 銀行借款
B81: Outflow : 設備折舊 | D81: =-D44 | E81: =-E44 | F81: =-F44 | G81: =-G44 | H81: =-H44 | I81: =-I44 | J81: =-J44 | K81: =-K44 | ... W81: =-W44
B82: Outflow : 設備放置區域租金 | C82: - | D82: =-D19 | E82: =-E19 | F82: =-F19 | G82: =-G19 | H82: =-H19 | I82: =-I19 | J82: =-J19 | K82: =-K19 | ... W82: =-W19
B83: Outflow : 返還借款
B84: Outflow : 利息費用 | C84: - | D84: =-D122*C50/100 | E84: =-E122*C50/100 | F84: =-F122*C50/100 | G84: =-G122*C50/100 | H84: =-H122*C50/100 | I84: =-I122*C50/100 | J84: =-J122*C50/100 | K84: =-K122*C50/100 | L84: =-L122*C50/100 | M84: =-M122*C50/100 | N84: =-N122*C50/100 | O84: =-O122*C50/100 | P84: =-P122*C50/100 | Q84: =-Q122*C50/100 | R84: =-R122*C50/100 | S84: =-S122*C50/100 | T84: =-T122*C50/100 | U84: =-U122*C50/100 | V84: =-V122*C50/100 | W84: =-W122*C50/100
B85: Outflow : 維運費 | C85: - | D85: =-D24 | E85: =-E24 | F85: =-F24 | G85: =-G24 | H85: =-H24 | I85: =-I24 | J85: =-J24 | K85: =-K24 | ... W85: =-W24
B86: Outflow : 保險費 | C86: - | D86: =-D29 | E86: =-E29 | F86: =-F29 | G86: =-G29 | H86: =-H29 | I86: =-I29 | J86: =-J29 | K86: =-K29 | ... W86: =-W29
B87: Outflow : 模組回收費 | D87: =-D34 | E87: =-E34 | F87: =-F34 | G87: =-G34 | H87: =-H34 | I87: =-I34 | J87: =-J34 | K87: =-K34 | ... W87: =-W34
B88: Outflow : 其它費用(人事薪資…等)
B89: 1%管理費
B90: 稅前淨利 | D90: =SUM(D78:D89) | E90: =SUM(E78:E89) | F90: =SUM(F78:F89) | G90: =SUM(G78:G89) | H90: =SUM(H78:H89) | I90: =SUM(I78:I89) | J90: =SUM(J78:J89) | K90: =SUM(K78:K89) | ... W90: =SUM(W78:W89)
B91: 所得稅20% | D91: =D90*0.2 | E91: =E90*0.2 | F91: =F90*0.2 | G91: =G90*0.2 | H91: =H90*0.2 | I91: =I90*0.2 | J91: =J90*0.2 | K91: =K90*0.2 | ... W91: =W90*0.2
B92: 稅後淨利 | D92: =D90-D91 | E92: =E90-E91 | F92: =F90-F91 | G92: =G90-G91 | H92: =H90-H91 | I92: =I90-I91 | J92: =J90-J91 | K92: =K90-K91 | ... W92: =W90-W91
B93: 累計現金流
B94: 回收年限評估
C95: 年份 | D95: 2023 | E95: 2024 | F95: 2025 | G95: 2026 | H95: 2027 | I95: 2028 | J95: 2029 | K95: 2030 | L95: 2031 | M95: 2032 | N95: 2033 | O95: 2034 | P95: 2035 | Q95: 2036 | R95: 2037 | S95: 2038 | T95: 2039 | U95: 2040 | V95: 2041 | W95: 2042
B97: (Unit : Currency) | C97: 0 | D97: 1 | E97: 2 | F97: 3 | G97: 4 | H97: 5 | I97: 6 | J97: 7 | K97: 8 | L97: 9 | M97: 10 | N97: 11 | O97: 12 | P97: 13 | Q97: 14 | R97: 15 | S97: 16 | T97: 17 | U97: 18 | V97: 19 | W97: 20
B98: 稅後淨利 | D98: =D92 | E98: =E92 | F98: =F92 | G98: =G92 | H98: =H92 | I98: =I92 | J98: =J92 | K98: =K92 | ... W98: =W92
B99: 設備折舊 | D99: =D44 | E99: =E44 | F99: =F44 | G99: =G44 | H99: =H44 | I99: =I44 | J99: =J44 | K99: =K44 | ... W99: =W44
B100: 營運活動現金流量 | D100: =D98+D99 | E100: =E98+E99 | F100: =F98+F99 | G100: =G98+G99 | H100: =H98+H99 | I100: =I98+I99 | J100: =J98+J99 | K100: =K98+K99 | ... W100: =W98+W99
B102: 投資活動-設備支出 | D102: =C58
B105: 理財活動-借款 | D105: =-ABS(D102)*C46/100
B106: 理財活動-還款 | E106: =-D105/C47 | F106: =-D105/C47 | G106: =-D105/C47 | H106: =-D105/C47 | I106: =-D105/C47 | J106: =-D105/C47 | K106: =-D105/C47 | L106: =-D105/C47 | M106: =-D105/C47 | N106: =-D105/C47 | O106: =-D105/C47 | P106: =-D105/C47 | Q106: =-D105/C47 | R106: =-D105/C47 | S106: =-D105/C47
B107: 理財活動-現金增資 | D107: =-ABS(D102)*(1-C46/100)
B108: 現金股利 | E108: =-D98*C48/100 | F108: =-E98*C48/100 | G108: =-F98*C48/100 | H108: =-G98*C48/100 | I108: =-H98*C48/100 | J108: =-I98*C48/100 | K108: =-J98*C48/100 | L108: =-K98*C48/100 | M108: =-L98*C48/100 | N108: =-M98*C48/100 | O108: =-N98*C48/100 | P108: =-O98*C48/100 | Q108: =-P98*C48/100 | R108: =-Q98*C48/100 | S108: =-R98*C48/100 | T108: =-S98*C48/100 | U108: =-T98*C48/100 | V108: =-U98*C48/100 | W108: =-V98*C48/100
B109: 年底減資 | T109: =-D107/C49 | U109: =-D107/C49 | V109: =-D107/C49 | W109: =-D107/C49
...

Sheet 表 105_滾算紀錄1
B1: 電站基本資料 | P1: =1-D11 | Q1: =P1-$D12 | R1: =Q1-$D12 | S1: =R1-$D12 | T1: =S1-$D12 | U1: =T1-$D12 | V1: =U1-$D12 | W1: =V1-$D12 | X1: =W1-$D12 | ... AI1: =AH1-$D12
B2: 電站名稱 | C2: 淡江大學-財務模擬案場 | D2: - | E2: -
B3: 電站壽命 | C3: 20 | D3: - | E3: -
B4: 建置量(kWp) | C4: 436.1 | D4: - | E4: - | M4: 滾算紀錄編號: 1
B5: 起始年度 | C5: 2023 | D5: 結束年度 | E5: 2042 | M5: 初始價金摘要
M6: 價金: 35000
B7: 綜合損益表 | M7: 專案IRR: 1.54
B8: 收入 | M8: 權益法IRR: 1.27
B9: 收支項目 | C9: 相關參數 | D9: 參數數值 | E9: 年限 | M9: 利潤率: 30.00%
B10: 電費收入 | C10: 年度AC併網總發電量 | D10: 547002 | E10: 20 | M10: 初始價金 - 現金模式，每次減少 1000 元
C11: 首年衰退率 | D11: 0.01
C12: 次年衰退率 | D12: 0.004
C13: 躉售費率(FIT) | D13: 3.7152
B14: 支出
B15: 收支項目 | C15: 相關參數 | D15: 參數數值 | E15: 攤提年限
B16: 設備費用(價金) | C16: 每kWp設備成本 | D16: 35000 | E16: 20
C17: 信邦利潤率 | D17: 0.3
C18: 開發費 | D18: 3000
B19: 租金費用 | C19: 租金計算方式 (1=固定攤提/2=電費抽成) | D19: 1 | E19: 0
C20: 【方式1參數】租金總額 | D20: 290201 | E20: 20
C21: 【方式2參數】抽成比率 | D21: 0 | E21: 0
B22: 運維費用 | C22: 每kw運維成本 | D22: 400 | E22: 20
B23: 保險費用 | C23: 占整體設備費用比例 | D23: 0.003 | E23: 20
B24: 模組回收費用 | C24: 每kw模組回收成本 | D24: 1000 | E24: 10
B25: 利息費用 | C25: 銀行利率 | D25: 0.025595 | E25: 0
B26: 所得稅 | C26: 所得稅率 | D26: 0.2 | E26: 0
B29: 現金流量表
B30: 金流項目 | C30: 相關參數 | D30: 參數數值
B31: 貸款成數 | C31: 占總設備費用比例 | D31: 0.8
B32: 貸款還款 | C32: 攤還期數 | D32: 15
B33: 現金股利 | C33: 股利比率 | D33: 0.9
B34: 年底減資 | C34: 攤還期數 | D34: 4
C37: 年份 | D37: 2023 | E37: 2024 | F37: 2025 | G37: 2026 | H37: 2027 | I37: 2028 | J37: 2029 | K37: 2030 | L37: 2031 | M37: 2032 | N37: 2033 | O37: 2034 | P37: 2035 | Q37: 2036 | R37: 2037 | S37: 2038 | T37: 2039 | U37: 2040 | V37: 2041 | W37: 2042
B38: 0
B39: (Unit : Currency) | C39: 0 | D39: 1 | E39: 2 | F39: 3 | G39: 4 | H39: 5 | I39: 6 | J39: 7 | K39: 8 | L39: 9 | M39: 10 | N39: 11 | O39: 12 | P39: 13 | Q39: 14 | R39: 15 | S39: 16 | T39: 17 | U39: 18 | V39: 19 | W39: 20
B40: 發電度數(KWH) | C40: 0 | D40: =$D$10*P1 | E40: =$D$10*Q1 | F40: =$D$10*R1 | G40: =$D$10*S1 | H40: =$D$10*T1 | I40: =$D$10*U1 | J40: =$D$10*V1 | K40: =$D$10*W1 | ... W40: =$D$10*AI1
B41: Inflow : 電費收入 | C41: - | D41: =D40*$D$13 | E41: =E40*$D$13 | F41: =F40*$D$13 | G41: =G40*$D$13 | H41: =H40*$D$13 | I41: =I40*$D$13 | J41: =J40*$D$13 | K41: =K40*$D$13 | ... W41: =W40*$D$13
B42: Inflow : 政府補助 | C42: - | G42: - | H42: - | I42: - | J42: - | K42: - | L42: - | M42: - | N42: - | O42: - | P42: - | Q42: - | R42: - | S42: - | T42: - | U42: - | V42: - | W42: -
B43: Inflow : 銀行借款
B44: Outflow : 設備費用 | C44: =-(D16/(1-D17)+D18)*C4
B45: Outflow : 設備放置區域租金 | C45: - | D45: 0 | E45: -290201 | F45: -290201 | G45: -290201 | H45: -290201 | I45: -290201 | J45: -290201 | K45: -290201 | L45: -290201 | M45: -290201 | N45: -290201 | O45: -290201 | P45: -290201 | Q45: -290201 | R45: -290201 | S45: -290201 | T45: -290201 | U45: -290201 | V45: -290201 | W45: -290201
B46: Outflow : 返還借款
B47: Outflow : 利息費用 | C47: -
B48: Outflow : 維運費 | C48: - | D48: -174440 | E48: -174440 | F48: -174440 | G48: -174440 | H48: -174440 | I48: -174440 | J48: -174440 | K48: -174440 | L48: -174440 | M48: -174440 | N48: -174440 | O48: -174440 | P48: -174440 | Q48: -174440 | R48: -174440 | S48: -174440 | T48: -174440 | U48: -174440 | V48: -174440 | W48: -174440
B49: Outflow : 保險費 | C49: - | D49: -45790.5 | E49: -45790.5 | F49: -45790.5 | G49: -45790.5 | H49: -45790.5 | I49: -45790.5 | J49: -45790.5 | K49: -45790.5 | L49: -45790.5 | M49: -45790.5 | N49: -45790.5 | O49: -45790.5 | P49: -45790.5 | Q49: -45790.5 | R49: -45790.5 | S49: -45790.5 | T49: -45790.5 | U49: -45790.5 | V49: -45790.5 | W49: -45790.5
B50: Outflow : 模組回收費 | D50: -43610 | E50: -43610 | F50: -43610 | G50: -43610 | H50: -43610 | I50: -43610 | J50: -43610 | K50: -43610 | L50: -43610 | M50: -43610 | N50: 0 | O50: 0 | P50: 0 | Q50: 0 | R50: 0 | S50: 0 | T50: 0 | U50: 0 | V50: 0 | W50: 0
B51: Outflow : 其它費用(人事薪資…等)
B52: 1%管理費
B53: 績效獎金
B54: 所得稅20% | D54: =D77 | E54: =E77 | F54: =F77 | G54: =G77 | H54: =H77 | I54: =I77 | J54: =J77 | K54: =K77 | ... W54: =W77
B55: 現金流 | C55: =C44 | D55: =SUM(D41:D54) | E55: =SUM(E41:E54) | F55: =SUM(F41:F54) | G55: =SUM(G41:G54) | H55: =SUM(H41:H54) | I55: =SUM(I41:I54) | J55: =SUM(J41:J54) | K55: =SUM(K41:K54) | ... W55: =SUM(W41:W54)
B56: 累計現金流 | D56: =C55+D55 | E56: =D56+E55 | F56: =E56+F55 | G56: =F56+G55 | H56: =G56+H55 | I56: =H56+I55 | J56: =I56+J55 | K56: =J56+K55 | L56: =K56+L55 | ... X56: =W56+X55
B57: 回收年限評估 | D57: =IF((D56)>0,"回收","未回收") | E57: =IF((E56)>0,"回收","未回收") | F57: =IF((F56)>0,"回收","未回收") | G57: =IF((G56)>0,"回收","未回收") | H57: =IF((H56)>0,"回收","未回收") | I57: =IF((I56)>0,"回收","未回收") | J57: =IF((J56)>0,"回收","未回收") | K57: =IF((K56)>0,"回收","未回收") | ... X57: =IF((X56)>0,"回收","未回收")
B58: 專案法IRR | C58: =IRR(C55:W55)
C60: 年份 | D60: =D37 | E60: =E37 | F60: =F37 | G60: =G37 | H60: =H37 | I60: =I37 | J60: =J37 | K60: =K37 | ... W60: =W37
B61: 0 | T61: 償還年限
B62: (Unit : Currency) | C62: 0 | D62: 1 | E62: 2 | F62: 3 | G62: 4 | H62: 5 | I62: 6 | J62: 7 | K62: 8 | L62: 9 | M62: 10 | N62: 11 | O62: 12 | P62: 13 | Q62: 14 | R62: 15 | S62: 16 | T62: 17 | U62: 18 | V62: 19 | W62: 20
B63: 發電度數(KWH) | C63: 0 | D63: =D40 | E63: =E40 | F63: =F40 | G63: =G40 | H63: =H40 | I63: =I40 | J63: =J40 | K63: =K40 | ... W63: =W40
B64: Inflow : 電費收入 | C64: - | D64: =D41 | E64: =E41 | F64: =F41 | G64: =G41 | H64: =H41 | I64: =I41 | J64: =J41 | K64: =K41 | ... W64: =W41
B65: Inflow : 政府補助 | C65: - | G65: - | H65: - | I65: - | J65: - | K65: - | L65: - | M65: - | N65: - | O65: - | P65: - | Q65: - | R65: - | S65: - | T65: - | U65: - | V65: - | W65: -
B66: Inflow : 銀行借款
B67: Outflow : 設備折舊 | D67: =$C$44/$E$16 | E67: =$C$44/$E$16 | F67: =$C$44/$E$16 | G67: =$C$44/$E$16 | H67: =$C$44/$E$16 | I67: =$C$44/$E$16 | J67: =$C$44/$E$16 | K67: =$C$44/$E$16 | ... W67: =$C$44/$E$16
B68: Outflow : 設備放置區域租金 | C68: - | D68: =D44 | E68: =E44 | F68: =F44 | G68: =G44 | H68: =H44 | I68: =I44 | J68: =J44 | K68: =K44 | ... W68: =W44
B69: Outflow : 返還借款
B70: Outflow : 利息費用 | C70: - | D70: 0 | E70: 0 | F70: 0 | G70: 0 | H70: 0 | I70: 0 | J70: 0 | K70: 0 | L70: 0 | M70: 0 | N70: 0 | O70: 0 | P70: 0 | Q70: 0 | R70: 0 | S70: 0 | T70: 0 | U70: 0 | V70: 0 | W70: 0
B71: Outflow : 維運費 | C71: - | D71: =D48 | E71: =E48 | F71: =F48 | G71: =G48 | H71: =H48 | I71: =I48 | J71: =J48 | K71: =K48 | ... W71: =W48
B72: Outflow : 保險費 | C72: - | D72: =D49 | E72: =E49 | F72: =F49 | G72: =G49 | H72: =H49 | I72: =I49 | J72: =J49 | K72: =K49 | ... W72: =W49
B73: Outflow : 模組回收費 | D73: =D50 | E73: =E50 | F73: =F50 | G73: =G50 | H73: =H50 | I73: =I50 | J73: =J50 | K73: =K50 | ... W73: =W50
B74: Outflow : 其它費用(人事薪資…等)
B75: 1%管理費
B76: 稅前淨利 | D76: =SUM(D64:D75) | E76: =SUM(E64:E75) | F76: =SUM(F64:F75) | G76: =SUM(G64:G75) | H76: =SUM(H64:H75) | I76: =SUM(I64:I75) | J76: =SUM(J64:J75) | K76: =SUM(K64:K75) | ... X76: =SUM(X64:X75)
B77: 所得稅20% | D77: =-D76*0.2 | E77: =-E76*0.2 | F77: =-F76*0.2 | G77: =-G76*0.2 | H77: =-H76*0.2 | I77: =-I76*0.2 | J77: =-J76*0.2 | K77: =-K76*0.2 | ... X77: =-X76*0.2
B78: 稅後淨利 | D78: =SUM(D76:D77) | E78: =SUM(E76:E77) | F78: =SUM(F76:F77) | G78: =SUM(G76:G77) | H78: =SUM(H76:H77) | I78: =SUM(I76:I77) | J78: =SUM(J76:J77) | K78: =SUM(K76:K77) | ... X78: =SUM(X76:X77)
B79: 累計現金流
B80: 回收年限評估

Sheet 表 105_滾算紀錄2
B1: 電站基本資料 | P1: =1-D11 | Q1: =P1-$D12 | R1: =Q1-$D12 | S1: =R1-$D12 | T1: =S1-$D12 | U1: =T1-$D12 | V1: =U1-$D12 | W1: =V1-$D12 | X1: =W1-$D12 | ... AI1: =AH1-$D12
B2: 電站名稱 | C2: 淡江大學-財務模擬案場 | D2: - | E2: -
B3: 電站壽命 | C3: 20 | D3: - | E3: -
B4: 建置量(kWp) | C4: 436.1 | D4: - | E4: - | M4: 滾算紀錄編號: 2
B5: 起始年度 | C5: 2023 | D5: 結束年度 | E5: 2042 | M5: 第1次滾算摘要
M6: 價金: 34000
B7: 綜合損益表 | M7: 專案IRR: 1.78
B8: 收入 | M8: 權益法IRR: 1.99
B9: 收支項目 | C9: 相關參數 | D9: 參數數值 | E9: 年限 | M9: 利潤率: 30.00%
B10: 電費收入 | C10: 年度AC併網總發電量 | D10: 547002 | E10: 20 | M10: 第1次滾算，減少 1000 元 - 現金模式，每次減少 1000 元
C11: 首年衰退率 | D11: 0.01
C12: 次年衰退率 | D12: 0.004
C13: 躉售費率(FIT) | D13: 3.7152
B14: 支出
B15: 收支項目 | C15: 相關參數 | D15: 參數數值 | E15: 攤提年限
B16: 設備費用(價金) | C16: 每kWp設備成本 | D16: 34000 | E16: 20
C17: 信邦利潤率 | D17: 0.3
C18: 開發費 | D18: 3000
B19: 租金費用 | C19: 租金計算方式 (1=固定攤提/2=電費抽成) | D19: 1 | E19: 0
C20: 【方式1參數】租金總額 | D20: 290201 | E20: 20
C21: 【方式2參數】抽成比率 | D21: 0 | E21: 0
B22: 運維費用 | C22: 每kw運維成本 | D22: 400 | E22: 20
B23: 保險費用 | C23: 占整體設備費用比例 | D23: 0.003 | E23: 20
B24: 模組回收費用 | C24: 每kw模組回收成本 | D24: 1000 | E24: 10
B25: 利息費用 | C25: 銀行利率 | D25: 0.025595 | E25: 0
B26: 所得稅 | C26: 所得稅率 | D26: 0.2 | E26: 0
B29: 現金流量表
B30: 金流項目 | C30: 相關參數 | D30: 參數數值
B31: 貸款成數 | C31: 占總設備費用比例 | D31: 0.8
B32: 貸款還款 | C32: 攤還期數 | D32: 15
B33: 現金股利 | C33: 股利比率 | D33: 0.9
B34: 年底減資 | C34: 攤還期數 | D34: 4
C37: 年份 | D37: 2023 | E37: 2024 | F37: 2025 | G37: 2026 | H37: 2027 | I37: 2028 | J37: 2029 | K37: 2030 | L37: 2031 | M37: 2032 | N37: 2033 | O37: 2034 | P37: 2035 | Q37: 2036 | R37: 2037 | S37: 2038 | T37: 2039 | U37: 2040 | V37: 2041 | W37: 2042
B38: 0
B39: (Unit : Currency) | C39: 0 | D39: 1 | E39: 2 | F39: 3 | G39: 4 | H39: 5 | I39: 6 | J39: 7 | K39: 8 | L39: 9 | M39: 10 | N39: 11 | O39: 12 | P39: 13 | Q39: 14 | R39: 15 | S39: 16 | T39: 17 | U39: 18 | V39: 19 | W39: 20
B40: 發電度數(KWH) | C40: 0 | D40: =$D$10*P1 | E40: =$D$10*Q1 | F40: =$D$10*R1 | G40: =$D$10*S1 | H40: =$D$10*T1 | I40: =$D$10*U1 | J40: =$D$10*V1 | K40: =$D$10*W1 | ... W40: =$D$10*AI1
B41: Inflow : 電費收入 | C41: - | D41: =D40*$D$13 | E41: =E40*$D$13 | F41: =F40*$D$13 | G41: =G40*$D$13 | H41: =H40*$D$13 | I41: =I40*$D$13 | J41: =J40*$D$13 | K41: =K40*$D$13 | ... W41: =W40*$D$13
B42: Inflow : 政府補助 | C42: - | G42: - | H42: - | I42: - | J42: - | K42: - | L42: - | M42: - | N42: - | O42: - | P42: - | Q42: - | R42: - | S42: - | T42: - | U42: - | V42: - | W42: -
B43: Inflow : 銀行借款
B44: Outflow : 設備費用 | C44: =-(D16/(1-D17)+D18)*C4
B45: Outflow : 設備放置區域租金 | C45: - | D45: 0 | E45: -290201 | F45: -290201 | G45: -290201 | H45: -290201 | I45: -290201 | J45: -290201 | K45: -290201 | L45: -290201 | M45: -290201 | N45: -290201 | O45: -290201 | P45: -290201 | Q45: -290201 | R45: -290201 | S45: -290201 | T45: -290201 | U45: -290201 | V45: -290201 | W45: -290201
B46: Outflow : 返還借款
B47: Outflow : 利息費用 | C47: -
B48: Outflow : 維運費 | C48: - | D48: -174440 | E48: -174440 | F48: -174440 | G48: -174440 | H48: -174440 | I48: -174440 | J48: -174440 | K48: -174440 | L48: -174440 | M48: -174440 | N48: -174440 | O48: -174440 | P48: -174440 | Q48: -174440 | R48: -174440 | S48: -174440 | T48: -174440 | U48: -174440 | V48: -174440 | W48: -174440
B49: Outflow : 保險費 | C49: - | D49: -44482.2 | E49: -44482.2 | F49: -44482.2 | G49: -44482.2 | H49: -44482.2 | I49: -44482.2 | J49: -44482.2 | K49: -44482.2 | L49: -44482.2 | M49: -44482.2 | N49: -44482.2 | O49: -44482.2 | P49: -44482.2 | Q49: -44482.2 | R49: -44482.2 | S49: -44482.2 | T49: -44482.2 | U49: -44482.2 | V49: -44482.2 | W49: -44482.2
B50: Outflow : 模組回收費 | D50: -43610 | E50: -43610 | F50: -43610 | G50: -43610 | H50: -43610 | I50: -43610 | J50: -43610 | K50: -43610 | L50: -43610 | M50: -43610 | N50: 0 | O50: 0 | P50: 0 | Q50: 0 | R50: 0 | S50: 0 | T50: 0 | U50: 0 | V50: 0 | W50: 0
B51: Outflow : 其它費用(人事薪資…等)
B52: 1%管理費
B53: 績效獎金
B54: 所得稅20% | D54: =D77 | E54: =E77 | F54: =F77 | G54: =G77 | H54: =H77 | I54: =I77 | J54: =J77 | K54: =K77 | ... W54: =W77
B55: 現金流 | C55: =C44 | D55: =SUM(D41:D54) | E55: =SUM(E41:E54) | F55: =SUM(F41:F54) | G55: =SUM(G41:G54) | H55: =SUM(H41:H54) | I55: =SUM(I41:I54) | J55: =SUM(J41:J54) | K55: =SUM(K41:K54) | ... W55: =SUM(W41:W54)
B56: 累計現金流 | D56: =C55+D55 | E56: =D56+E55 | F56: =E56+F55 | G56: =F56+G55 | H56: =G56+H55 | I56: =H56+I55 | J56: =I56+J55 | K56: =J56+K55 | L56: =K56+L55 | ... X56: =W56+X55
B57: 回收年限評估 | D57: =IF((D56)>0,"回收","未回收") | E57: =IF((E56)>0,"回收","未回收") | F57: =IF((F56)>0,"回收","未回收") | G57: =IF((G56)>0,"回收","未回收") | H57: =IF((H56)>0,"回收","未回收") | I57: =IF((I56)>0,"回收","未回收") | J57: =IF((J56)>0,"回收","未回收") | K57: =IF((K56)>0,"回收","未回收") | ... X57: =IF((X56)>0,"回收","未回收")
B58: 專案法IRR | C58: =IRR(C55:W55)
C60: 年份 | D60: =D37 | E60: =E37 | F60: =F37 | G60: =G37 | H60: =H37 | I60: =I37 | J60: =J37 | K60: =K37 | ... W60: =W37
B61: 0 | T61: 償還年限
B62: (Unit : Currency) | C62: 0 | D62: 1 | E62: 2 | F62: 3 | G62: 4 | H62: 5 | I62: 6 | J62: 7 | K62: 8 | L62: 9 | M62: 10 | N62: 11 | O62: 12 | P62: 13 | Q62: 14 | R62: 15 | S62: 16 | T62: 17 | U62: 18 | V62: 19 | W62: 20
B63: 發電度數(KWH) | C63: 0 | D63: =D40 | E63: =E40 | F63: =F40 | G63: =G40 | H63: =H40 | I63: =I40 | J63: =J40 | K63: =K40 | ... W63: =W40
B64: Inflow : 電費收入 | C64: - | D64: =D41 | E64: =E41 | F64: =F41 | G64: =G41 | H64: =H41 | I64: =I41 | J64: =J41 | K64: =K41 | ... W64: =W41
B65: Inflow : 政府補助 | C65: - | G65: - | H65: - | I65: - | J65: - | K65: - | L65: - | M65: - | N65: - | O65: - | P65: - | Q65: - | R65: - | S65: - | T65: - | U65: - | V65: - | W65: -
B66: Inflow : 銀行借款
B67: Outflow : 設備折舊 | D67: =$C$44/$E$16 | E67: =$C$44/$E$16 | F67: =$C$44/$E$16 | G67: =$C$44/$E$16 | H67: =$C$44/$E$16 | I67: =$C$44/$E$16 | J67: =$C$44/$E$16 | K67: =$C$44/$E$16 | ... W67: =$C$44/$E$16
B68: Outflow : 設備放置區域租金 | C68: - | D68: =D44 | E68: =E44 | F68: =F44 | G68: =G44 | H68: =H44 | I68: =I44 | J68: =J44 | K68: =K44 | ... W68: =W44
B69: Outflow : 返還借款
B70: Outflow : 利息費用 | C70: - | D70: 0 | E70: 0 | F70: 0 | G70: 0 | H70: 0 | I70: 0 | J70: 0 | K70: 0 | L70: 0 | M70: 0 | N70: 0 | O70: 0 | P70: 0 | Q70: 0 | R70: 0 | S70: 0 | T70: 0 | U70: 0 | V70: 0 | W70: 0
B71: Outflow : 維運費 | C71: - | D71: =D48 | E71: =E48 | F71: =F48 | G71: =G48 | H71: =H48 | I71: =I48 | J71: =J48 | K71: =K48 | ... W71: =W48
B72: Outflow : 保險費 | C72: - | D72: =D49 | E72: =E49 | F72: =F49 | G72: =G49 | H72: =H49 | I72: =I49 | J72: =J49 | K72: =K49 | ... W72: =W49
B73: Outflow : 模組回收費 | D73: =D50 | E73: =E50 | F73: =F50 | G73: =G50 | H73: =H50 | I73: =I50 | J73: =J50 | K73: =K50 | ... W73: =W50
B74: Outflow : 其它費用(人事薪資…等)
B75: 1%管理費
B76: 稅前淨利 | D76: =SUM(D64:D75) | E76: =SUM(E64:E75) | F76: =SUM(F64:F75) | G76: =SUM(G64:G75) | H76: =SUM(H64:H75) | I76: =SUM(I64:I75) | J76: =SUM(J64:J75) | K76: =SUM(K64:K75) | ... X76: =SUM(X64:X75)
B77: 所得稅20% | D77: =-D76*0.2 | E77: =-E76*0.2 | F77: =-F76*0.2 | G77: =-G76*0.2 | H77: =-H76*0.2 | I77: =-I76*0.2 | J77: =-J76*0.2 | K77: =-K76*0.2 | ... X77: =-X76*0.2
B78: 稅後淨利 | D78: =SUM(D76:D77) | E78: =SUM(E76:E77) | F78: =SUM(F76:F77) | G78: =SUM(G76:G77) | H78: =SUM(H76:H77) | I78: =SUM(I76:I77) | J78: =SUM(J76:J77) | K78: =SUM(K76:K77) | ... X78: =SUM(X76:X77)
B79: 累計現金流
B80: 回收年限評估

Sheet 表 105_滾算紀錄3
B1: 電站基本資料 | P1: =1-D11 | Q1: =P1-$D12 | R1: =Q1-$D12 | S1: =R1-$D12 | T1: =S1-$D12 | U1: =T1-$D12 | V1: =U1-$D12 | W1: =V1-$D12 | X1: =W1-$D12 | ... AI1: =AH1-$D12
B2: 電站名稱 | C2: 淡江大學-財務模擬案場 | D2: - | E2: -
B3: 電站壽命 | C3: 20 | D3: - | E3: -
B4: 建置量(kWp) | C4: 436.1 | D4: - | E4: - | M4: 滾算紀錄編號: 3
B5: 起始年度 | C5: 2023 | D5: 結束年度 | E5: 2042 | M5: 第2次滾算摘要
M6: 價金: 33000
B7: 綜合損益表 | M7: 專案IRR: 2.03
B8: 收入 | M8: 權益法IRR: 2.75
B9: 收支項目 | C9: 相關參數 | D9: 參數數值 | E9: 年限 | M9: 利潤率: 30.00%
B10: 電費收入 | C10: 年度AC併網總發電量 | D10: 547002 | E10: 20 | M10: 第2次滾算，減少 1000 元 - 現金模式，每次減少 1000 元
C11: 首年衰退率 | D11: 0.01
C12: 次年衰退率 | D12: 0.004
C13: 躉售費率(FIT) | D13: 3.7152
B14: 支出
B15: 收支項目 | C15: 相關參數 | D15: 參數數值 | E15: 攤提年限
B16: 設備費用(價金) | C16: 每kWp設備成本 | D16: 33000 | E16: 20
C17: 信邦利潤率 | D17: 0.3
C18: 開發費 | D18: 3000
B19: 租金費用 | C19: 租金計算方式 (1=固定攤提/2=電費抽成) | D19: 1 | E19: 0
C20: 【方式1參數】租金總額 | D20: 290201 | E20: 20
C21: 【方式2參數】抽成比率 | D21: 0 | E21: 0
B22: 運維費用 | C22: 每kw運維成本 | D22: 400 | E22: 20
B23: 保險費用 | C23: 占整體設備費用比例 | D23: 0.003 | E23: 20
B24: 模組回收費用 | C24: 每kw模組回收成本 | D24: 1000 | E24: 10
B25: 利息費用 | C25: 銀行利率 | D25: 0.025595 | E25: 0
B26: 所得稅 | C26: 所得稅率 | D26: 0.2 | E26: 0
B29: 現金流量表
B30: 金流項目 | C30: 相關參數 | D30: 參數數值
B31: 貸款成數 | C31: 占總設備費用比例 | D31: 0.8
B32: 貸款還款 | C32: 攤還期數 | D32: 15
B33: 現金股利 | C33: 股利比率 | D33: 0.9
B34: 年底減資 | C34: 攤還期數 | D34: 4
C37: 年份 | D37: 2023 | E37: 2024 | F37: 2025 | G37: 2026 | H37: 2027 | I37: 2028 | J37: 2029 | K37: 2030 | L37: 2031 | M37: 2032 | N37: 2033 | O37: 2034 | P37: 2035 | Q37: 2036 | R37: 2037 | S37: 2038 | T37: 2039 | U37: 2040 | V37: 2041 | W37: 2042
B38: 0
B39: (Unit : Currency) | C39: 0 | D39: 1 | E39: 2 | F39: 3 | G39: 4 | H39: 5 | I39: 6 | J39: 7 | K39: 8 | L39: 9 | M39: 10 | N39: 11 | O39: 12 | P39: 13 | Q39: 14 | R39: 15 | S39: 16 | T39: 17 | U39: 18 | V39: 19 | W39: 20
B40: 發電度數(KWH) | C40: 0 | D40: =$D$10*P1 | E40: =$D$10*Q1 | F40: =$D$10*R1 | G40: =$D$10*S1 | H40: =$D$10*T1 | I40: =$D$10*U1 | J40: =$D$10*V1 | K40: =$D$10*W1 | ... W40: =$D$10*AI1
B41: Inflow : 電費收入 | C41: - | D41: =D40*$D$13 | E41: =E40*$D$13 | F41: =F40*$D$13 | G41: =G40*$D$13 | H41: =H40*$D$13 | I41: =I40*$D$13 | J41: =J40*$D$13 | K41: =K40*$D$13 | ... W41: =W40*$D$13
B42: Inflow : 政府補助 | C42: - | G42: - | H42: - | I42: - | J42: - | K42: - | L42: - | M42: - | N42: - | O42: - | P42: - | Q42: - | R42: - | S42: - | T42: - | U42: - | V42: - | W42: -
B43: Inflow : 銀行借款
B44: Outflow : 設備費用 | C44: =-(D16/(1-D17)+D18)*C4
B45: Outflow : 設備放置區域租金 | C45: - | D45: 0 | E45: -290201 | F45: -290201 | G45: -290201 | H45: -290201 | I45: -290201 | J45: -290201 | K45: -290201 | L45: -290201 | M45: -290201 | N45: -290201 | O45: -290201 | P45: -290201 | Q45: -290201 | R45: -290201 | S45: -290201 | T45: -290201 | U45: -290201 | V45: -290201 | W45: -290201
B46: Outflow : 返還借款
B47: Outflow : 利息費用 | C47: -
B48: Outflow : 維運費 | C48: - | D48: -174440 | E48: -174440 | F48: -174440 | G48: -174440 | H48: -174440 | I48: -174440 | J48: -174440 | K48: -174440 | L48: -174440 | M48: -174440 | N48: -174440 | O48: -174440 | P48: -174440 | Q48: -174440 | R48: -174440 | S48: -174440 | T48: -174440 | U48: -174440 | V48: -174440 | W48: -174440
B49: Outflow : 保險費 | C49: - | D49: -43173.9 | E49: -43173.9 | F49: -43173.9 | G49: -43173.9 | H49: -43173.9 | I49: -43173.9 | J49: -43173.9 | K49: -43173.9 | L49: -43173.9 | M49: -43173.9 | N49: -43173.9 | O49: -43173.9 | P49: -43173.9 | Q49: -43173.9 | R49: -43173.9 | S49: -43173.9 | T49: -43173.9 | U49: -43173.9 | V49: -43173.9 | W49: -43173.9
B50: Outflow : 模組回收費 | D50: -43610 | E50: -43610 | F50: -43610 | G50: -43610 | H50: -43610 | I50: -43610 | J50: -43610 | K50: -43610 | L50: -43610 | M50: -43610 | N50: 0 | O50: 0 | P50: 0 | Q50: 0 | R50: 0 | S50: 0 | T50: 0 | U50: 0 | V50: 0 | W50: 0
B51: Outflow : 其它費用(人事薪資…等)
B52: 1%管理費
B53: 績效獎金
B54: 所得稅20% | D54: =D77 | E54: =E77 | F54: =F77 | G54: =G77 | H54: =H77 | I54: =I77 | J54: =J77 | K54: =K77 | ... W54: =W77
B55: 現金流 | C55: =C44 | D55: =SUM(D41:D54) | E55: =SUM(E41:E54) | F55: =SUM(F41:F54) | G55: =SUM(G41:G54) | H55: =SUM(H41:H54) | I55: =SUM(I41:I54) | J55: =SUM(J41:J54) | K55: =SUM(K41:K54) | ... W55: =SUM(W41:W54)
B56: 累計現金流 | D56: =C55+D55 | E56: =D56+E55 | F56: =E56+F55 | G56: =F56+G55 | H56: =G56+H55 | I56: =H56+I55 | J56: =I56+J55 | K56: =J56+K55 | L56: =K56+L55 | ... X56: =W56+X55
B57: 回收年限評估 | D57: =IF((D56)>0,"回收","未回收") | E57: =IF((E56)>0,"回收","未回收") | F57: =IF((F56)>0,"回收","未回收") | G57: =IF((G56)>0,"回收","未回收") | H57: =IF((H56)>0,"回收","未回收") | I57: =IF((I56)>0,"回收","未回收") | J57: =IF((J56)>0,"回收","未回收") | K57: =IF((K56)>0,"回收","未回收") | ... X57: =IF((X56)>0,"回收","未回收")
B58: 專案法IRR | C58: =IRR(C55:W55)
C60: 年份 | D60: =D37 | E60: =E37 | F60: =F37 | G60: =G37 | H60: =H37 | I60: =I37 | J60: =J37 | K60: =K37 | ... W60: =W37
B61: 0 | T61: 償還年限
B62: (Unit : Currency) | C62: 0 | D62: 1 | E62: 2 | F62: 3 | G62: 4 | H62: 5 | I62: 6 | J62: 7 | K62: 8 | L62: 9 | M62: 10 | N62: 11 | O62: 12 | P62: 13 | Q62: 14 | R62: 15 | S62: 16 | T62: 17 | U62: 18 | V62: 19 | W62: 20
B63: 發電度數(KWH) | C63: 0 | D63: =D40 | E63: =E40 | F63: =F40 | G63: =G40 | H63: =H40 | I63: =I40 | J63: =J40 | K63: =K40 | ... W63: =W40
B64: Inflow : 電費收入 | C64: - | D64: =D41 | E64: =E41 | F64: =F41 | G64: =G41 | H64: =H41 | I64: =I41 | J64: =J41 | K64: =K41 | ... W64: =W41
B65: Inflow : 政府補助 | C65: - | G65: - | H65: - | I65: - | J65: - | K65: - | L65: - | M65: - | N65: - | O65: - | P65: - | Q65: - | R65: - | S65: - | T65: - | U65: - | V65: - | W65: -
B66: Inflow : 銀行借款
B67: Outflow : 設備折舊 | D67: =$C$44/$E$16 | E67: =$C$44/$E$16 | F67: =$C$44/$E$16 | G67: =$C$44/$E$16 | H67: =$C$44/$E$16 | I67: =$C$44/$E$16 | J67: =$C$44/$E$16 | K67: =$C$44/$E$16 | ... W67: =$C$44/$E$16
B68: Outflow : 設備放置區域租金 | C68: - | D68: =D44 | E68: =E44 | F68: =F44 | G68: =G44 | H68: =H44 | I68: =I44 | J68: =J44 | K68: =K44 | ... W68: =W44
B69: Outflow : 返還借款
B70: Outflow : 利息費用 | C70: - | D70: 0 | E70: 0 | F70: 0 | G70: 0 | H70: 0 | I70: 0 | J70: 0 | K70: 0 | L70: 0 | M70: 0 | N70: 0 | O70: 0 | P70: 0 | Q70: 0 | R70: 0 | S70: 0 | T70: 0 | U70: 0 | V70: 0 | W70: 0
B71: Outflow : 維運費 | C71: - | D71: =D48 | E71: =E48 | F71: =F48 | G71: =G48 | H71: =H48 | I71: =I48 | J71: =J48 | K71: =K48 | ... W71: =W48
B72: Outflow : 保險費 | C72: - | D72: =D49 | E72: =E49 | F72: =F49 | G72: =G49 | H72: =H49 | I72: =I49 | J72: =J49 | K72: =K49 | ... W72: =W49
B73: Outflow : 模組回收費 | D73: =D50 | E73: =E50 | F73: =F50 | G73: =G50 | H73: =H50 | I73: =I50 | J73: =J50 | K73: =K50 | ... W73: =W50
B74: Outflow : 其它費用(人事薪資…等)
B75: 1%管理費
B76: 稅前淨利 | D76: =SUM(D64:D75) | E76: =SUM(E64:E75) | F76: =SUM(F64:F75) | G76: =SUM(G64:G75) | H76: =SUM(H64:H75) | I76: =SUM(I64:I75) | J76: =SUM(J64:J75) | K76: =SUM(K64:K75) | ... X76: =SUM(X64:X75)
B77: 所得稅20% | D77: =-D76*0.2 | E77: =-E76*0.2 | F77: =-F76*0.2 | G77: =-G76*0.2 | H77: =-H76*0.2 | I77: =-I76*0.2 | J77: =-J76*0.2 | K77: =-K76*0.2 | ... X77: =-X76*0.2
B78: 稅後淨利 | D78: =SUM(D76:D77) | E78: =SUM(E76:E77) | F78: =SUM(F76:F77) | G78: =SUM(G76:G77) | H78: =SUM(H76:H77) | I78: =SUM(I76:I77) | J78: =SUM(J76:J77) | K78: =SUM(K76:K77) | ... X78: =SUM(X76:X77)
B79: 累計現金流
B80: 回收年限評估
