Workbook

Sheet 彙整總表
C4: 年份 | D4: 2023 | E4: 2024 | F4: 2025 | G4: 2026 | H4: 2027 | I4: 2028 | J4: 2029 | K4: 2030 | L4: 2031 | M4: 2032 | N4: 2033 | O4: 2034 | P4: 2035 | Q4: 2036 | R4: 2037 | S4: 2038 | T4: 2039 | U4: 2040 | V4: 2041 | W4: 2042
C5: 預估發電度數
B6: 表 62 | D6: =ABS('表 62_滾算紀錄3'!D40) | E6: =ABS('表 62_滾算紀錄3'!E40) | F6: =ABS('表 62_滾算紀錄3'!F40) | G6: =ABS('表 62_滾算紀錄3'!G40) | H6: =ABS('表 62_滾算紀錄3'!H40) | I6: =ABS('表 62_滾算紀錄3'!I40) | J6: =ABS('表 62_滾算紀錄3'!J40) | K6: =ABS('表 62_滾算紀錄3'!K40) | ... W6: =ABS('表 62_滾算紀錄3'!W40)
B7: 表 62 | D7: =ABS('表 62_滾算紀錄2'!D40) | E7: =ABS('表 62_滾算紀錄2'!E40) | F7: =ABS('表 62_滾算紀錄2'!F40) | G7: =ABS('表 62_滾算紀錄2'!G40) | H7: =ABS('表 62_滾算紀錄2'!H40) | I7: =ABS('表 62_滾算紀錄2'!I40) | J7: =ABS('表 62_滾算紀錄2'!J40) | K7: =ABS('表 62_滾算紀錄2'!K40) | ... W7: =ABS('表 62_滾算紀錄2'!W40)
B8: 表 62 | D8: =ABS('表 62_滾算紀錄4'!D40) | E8: =ABS('表 62_滾算紀錄4'!E40) | F8: =ABS('表 62_滾算紀錄4'!F40) | G8: =ABS('表 62_滾算紀錄4'!G40) | H8: =ABS('表 62_滾算紀錄4'!H40) | I8: =ABS('表 62_滾算紀錄4'!I40) | J8: =ABS('表 62_滾算紀錄4'!J40) | K8: =ABS('表 62_滾算紀錄4'!K40) | ... W8: =ABS('表 62_滾算紀錄4'!W40)
B9: 表 62 | D9: =ABS('表 62_滾算紀錄6'!D40) | E9: =ABS('表 62_滾算紀錄6'!E40) | F9: =ABS('表 62_滾算紀錄6'!F40) | G9: =ABS('表 62_滾算紀錄6'!G40) | H9: =ABS('表 62_滾算紀錄6'!H40) | I9: =ABS('表 62_滾算紀錄6'!I40) | J9: =ABS('表 62_滾算紀錄6'!J40) | K9: =ABS('表 62_滾算紀錄6'!K40) | ... W9: =ABS('表 62_滾算紀錄6'!W40)
C10: 預估發電度數/年總計 | D10: =SUM(D6:D9) | E10: =SUM(E6:E9) | F10: =SUM(F6:F9) | G10: =SUM(G6:G9) | H10: =SUM(H6:H9) | I10: =SUM(I6:I9) | J10: =SUM(J6:J9) | K10: =SUM(K6:K9) | ... W10: =SUM(W6:W9)
C11: 預估收入 | D11: 2023 | E11: 2024 | F11: 2025 | G11: 2026 | H11: 2027 | I11: 2028 | J11: 2029 | K11: 2030 | L11: 2031 | M11: 2032 | N11: 2033 | O11: 2034 | P11: 2035 | Q11: 2036 | R11: 2037 | S11: 2038 | T11: 2039 | U11: 2040 | V11: 2041 | W11: 2042
B12: 表 62 | D12: =ABS('表 62_滾算紀錄3'!D41) | E12: =ABS('表 62_滾算紀錄3'!E41) | F12: =ABS('表 62_滾算紀錄3'!F41) | G12: =ABS('表 62_滾算紀錄3'!G41) | H12: =ABS('表 62_滾算紀錄3'!H41) | I12: =ABS('表 62_滾算紀錄3'!I41) | J12: =ABS('表 62_滾算紀錄3'!J41) | K12: =ABS('表 62_滾算紀錄3'!K41) | ... W12: =ABS('表 62_滾算紀錄3'!W41)
B13: 表 62 | D13: =ABS('表 62_滾算紀錄2'!D41) | E13: =ABS('表 62_滾算紀錄2'!E41) | F13: =ABS('表 62_滾算紀錄2'!F41) | G13: =ABS('表 62_滾算紀錄2'!G41) | H13: =ABS('表 62_滾算紀錄2'!H41) | I13: =ABS('表 62_滾算紀錄2'!I41) | J13: =ABS('表 62_滾算紀錄2'!J41) | K13: =ABS('表 62_滾算紀錄2'!K41) | ... W13: =ABS('表 62_滾算紀錄2'!W41)
B14: 表 62 | D14: =ABS('表 62_滾算紀錄4'!D41) | E14: =ABS('表 62_滾算紀錄4'!E41) | F14: =ABS('表 62_滾算紀錄4'!F41) | G14: =ABS('表 62_滾算紀錄4'!G41) | H14: =ABS('表 62_滾算紀錄4'!H41) | I14: =ABS('表 62_滾算紀錄4'!I41) | J14: =ABS('表 62_滾算紀錄4'!J41) | K14: =ABS('表 62_滾算紀錄4'!K41) | ... W14: =ABS('表 62_滾算紀錄4'!W41)
B15: 表 62 | D15: =ABS('表 62_滾算紀錄6'!D41) | E15: =ABS('表 62_滾算紀錄6'!E41) | F15: =ABS('表 62_滾算紀錄6'!F41) | G15: =ABS('表 62_滾算紀錄6'!G41) | H15: =ABS('表 62_滾算紀錄6'!H41) | I15: =ABS('表 62_滾算紀錄6'!I41) | J15: =ABS('表 62_滾算紀錄6'!J41) | K15: =ABS('表 62_滾算紀錄6'!K41) | ... W15: =ABS('表 62_滾算紀錄6'!W41)
C16: 預估收入/年總計 | D16: =SUM(D12:D15) | E16: =SUM(E12:E15) | F16: =SUM(F12:F15) | G16: =SUM(G12:G15) | H16: =SUM(H12:H15) | I16: =SUM(I12:I15) | J16: =SUM(J12:J15) | K16: =SUM(K12:K15) | ... W16: =SUM(W12:W15)
C17: 租金 | D17: 2023 | E17: 2024 | F17: 2025 | G17: 2026 | H17: 2027 | I17: 2028 | J17: 2029 | K17: 2030 | L17: 2031 | M17: 2032 | N17: 2033 | O17: 2034 | P17: 2035 | Q17: 2036 | R17: 2037 | S17: 2038 | T17: 2039 | U17: 2040 | V17: 2041 | W17: 2042
B18: 表 62 | D18: =ABS('表 62_滾算紀錄3'!D45) | E18: =ABS('表 62_滾算紀錄3'!E45) | F18: =ABS('表 62_滾算紀錄3'!F45) | G18: =ABS('表 62_滾算紀錄3'!G45) | H18: =ABS('表 62_滾算紀錄3'!H45) | I18: =ABS('表 62_滾算紀錄3'!I45) | J18: =ABS('表 62_滾算紀錄3'!J45) | K18: =ABS('表 62_滾算紀錄3'!K45) | ... W18: =ABS('表 62_滾算紀錄3'!W45)
B19: 表 62 | D19: =ABS('表 62_滾算紀錄2'!D45) | E19: =ABS('表 62_滾算紀錄2'!E45) | F19: =ABS('表 62_滾算紀錄2'!F45) | G19: =ABS('表 62_滾算紀錄2'!G45) | H19: =ABS('表 62_滾算紀錄2'!H45) | I19: =ABS('表 62_滾算紀錄2'!I45) | J19: =ABS('表 62_滾算紀錄2'!J45) | K19: =ABS('表 62_滾算紀錄2'!K45) | ... W19: =ABS('表 62_滾算紀錄2'!W45)
B20: 表 62 | D20: =ABS('表 62_滾算紀錄4'!D45) | E20: =ABS('表 62_滾算紀錄4'!E45) | F20: =ABS('表 62_滾算紀錄4'!F45) | G20: =ABS('表 62_滾算紀錄4'!G45) | H20: =ABS('表 62_滾算紀錄4'!H45) | I20: =ABS('表 62_滾算紀錄4'!I45) | J20: =ABS('表 62_滾算紀錄4'!J45) | K20: =ABS('表 62_滾算紀錄4'!K45) | ... W20: =ABS('表 62_滾算紀錄4'!W45)
B21: 表 62 | D21: =ABS('表 62_滾算紀錄6'!D45) | E21: =ABS('表 62_滾算紀錄6'!E45) | F21: =ABS('表 62_滾算紀錄6'!F45) | G21: =ABS('表 62_滾算紀錄6'!G45) | H21: =ABS('表 62_滾算紀錄6'!H45) | I21: =ABS('表 62_滾算紀錄6'!I45) | J21: =ABS('表 62_滾算紀錄6'!J45) | K21: =ABS('表 62_滾算紀錄6'!K45) | ... W21: =ABS('表 62_滾算紀錄6'!W45)
C22: 租金/年總計 | D22: =SUM(D18:D21) | E22: =SUM(E18:E21) | F22: =SUM(F18:F21) | G22: =SUM(G18:G21) | H22: =SUM(H18:H21) | I22: =SUM(I18:I21) | J22: =SUM(J18:J21) | K22: =SUM(K18:K21) | ... W22: =SUM(W18:W21)
C23: 運維 | D23: 2023 | E23: 2024 | F23: 2025 | G23: 2026 | H23: 2027 | I23: 2028 | J23: 2029 | K23: 2030 | L23: 2031 | M23: 2032 | N23: 2033 | O23: 2034 | P23: 2035 | Q23: 2036 | R23: 2037 | S23: 2038 | T23: 2039 | U23: 2040 | V23: 2041 | W23: 2042
B24: 表 62 | D24: =ABS('表 62_滾算紀錄3'!D48) | E24: =ABS('表 62_滾算紀錄3'!E48) | F24: =ABS('表 62_滾算紀錄3'!F48) | G24: =ABS('表 62_滾算紀錄3'!G48) | H24: =ABS('表 62_滾算紀錄3'!H48) | I24: =ABS('表 62_滾算紀錄3'!I48) | J24: =ABS('表 62_滾算紀錄3'!J48) | K24: =ABS('表 62_滾算紀錄3'!K48) | ... W24: =ABS('表 62_滾算紀錄3'!W48)
B25: 表 62 | D25: =ABS('表 62_滾算紀錄2'!D48) | E25: =ABS('表 62_滾算紀錄2'!E48) | F25: =ABS('表 62_滾算紀錄2'!F48) | G25: =ABS('表 62_滾算紀錄2'!G48) | H25: =ABS('表 62_滾算紀錄2'!H48) | I25: =ABS('表 62_滾算紀錄2'!I48) | J25: =ABS('表 62_滾算紀錄2'!J48) | K25: =ABS('表 62_滾算紀錄2'!K48) | ... W25: =ABS('表 62_滾算紀錄2'!W48)
B26: 表 62 | D26: =ABS('表 62_滾算紀錄4'!D48) | E26: =ABS('表 62_滾算紀錄4'!E48) | F26: =ABS('表 62_滾算紀錄4'!F48) | G26: =ABS('表 62_滾算紀錄4'!G48) | H26: =ABS('表 62_滾算紀錄4'!H48) | I26: =ABS('表 62_滾算紀錄4'!I48) | J26: =ABS('表 62_滾算紀錄4'!J48) | K26: =ABS('表 62_滾算紀錄4'!K48) | ... W26: =ABS('表 62_滾算紀錄4'!W48)
B27: 表 62 | D27: =ABS('表 62_滾算紀錄6'!D48) | E27: =ABS('表 62_滾算紀錄6'!E48) | F27: =ABS('表 62_滾算紀錄6'!F48) | G27: =ABS('表 62_滾算紀錄6'!G48) | H27: =ABS('表 62_滾算紀錄6'!H48) | I27: =ABS('表 62_滾算紀錄6'!I48) | J27: =ABS('表 62_滾算紀錄6'!J48) | K27: =ABS('表 62_滾算紀錄6'!K48) | ... W27: =ABS('表 62_滾算紀錄6'!W48)
C28: 運維/年總計 | D28: =SUM(D24:D27) | E28: =SUM(E24:E27) | F28: =SUM(F24:F27) | G28: =SUM(G24:G27) | H28: =SUM(H24:H27) | I28: =SUM(I24:I27) | J28: =SUM(J24:J27) | K28: =SUM(K24:K27) | ... W28: =SUM(W24:W27)
C29: 保險 | D29: 2023 | E29: 2024 | F29: 2025 | G29: 2026 | H29: 2027 | I29: 2028 | J29: 2029 | K29: 2030 | L29: 2031 | M29: 2032 | N29: 2033 | O29: 2034 | P29: 2035 | Q29: 2036 | R29: 2037 | S29: 2038 | T29: 2039 | U29: 2040 | V29: 2041 | W29: 2042
B30: 表 62 | D30: =ABS('表 62_滾算紀錄3'!D49) | E30: =ABS('表 62_滾算紀錄3'!E49) | F30: =ABS('表 62_滾算紀錄3'!F49) | G30: =ABS('表 62_滾算紀錄3'!G49) | H30: =ABS('表 62_滾算紀錄3'!H49) | I30: =ABS('表 62_滾算紀錄3'!I49) | J30: =ABS('表 62_滾算紀錄3'!J49) | K30: =ABS('表 62_滾算紀錄3'!K49) | ... W30: =ABS('表 62_滾算紀錄3'!W49)
B31: 表 62 | D31: =ABS('表 62_滾算紀錄2'!D49) | E31: =ABS('表 62_滾算紀錄2'!E49) | F31: =ABS('表 62_滾算紀錄2'!F49) | G31: =ABS('表 62_滾算紀錄2'!G49) | H31: =ABS('表 62_滾算紀錄2'!H49) | I31: =ABS('表 62_滾算紀錄2'!I49) | J31: =ABS('表 62_滾算紀錄2'!J49) | K31: =ABS('表 62_滾算紀錄2'!K49) | ... W31: =ABS('表 62_滾算紀錄2'!W49)
B32: 表 62 | D32: =ABS('表 62_滾算紀錄4'!D49) | E32: =ABS('表 62_滾算紀錄4'!E49) | F32: =ABS('表 62_滾算紀錄4'!F49) | G32: =ABS('表 62_滾算紀錄4'!G49) | H32: =ABS('表 62_滾算紀錄4'!H49) | I32: =ABS('表 62_滾算紀錄4'!I49) | J32: =ABS('表 62_滾算紀錄4'!J49) | K32: =ABS('表 62_滾算紀錄4'!K49) | ... W32: =ABS('表 62_滾算紀錄4'!W49)
B33: 表 62 | D33: =ABS('表 62_滾算紀錄6'!D49) | E33: =ABS('表 62_滾算紀錄6'!E49) | F33: =ABS('表 62_滾算紀錄6'!F49) | G33: =ABS('表 62_滾算紀錄6'!G49) | H33: =ABS('表 62_滾算紀錄6'!H49) | I33: =ABS('表 62_滾算紀錄6'!I49) | J33: =ABS('表 62_滾算紀錄6'!J49) | K33: =ABS('表 62_滾算紀錄6'!K49) | ... W33: =ABS('表 62_滾算紀錄6'!W49)
C34: 保險/年總計 | D34: =SUM(D30:D33) | E34: =SUM(E30:E33) | F34: =SUM(F30:F33) | G34: =SUM(G30:G33) | H34: =SUM(H30:H33) | I34: =SUM(I30:I33) | J34: =SUM(J30:J33) | K34: =SUM(K30:K33) | ... W34: =SUM(W30:W33)
C35: 模組回收費 | D35: 2023 | E35: 2024 | F35: 2025 | G35: 2026 | H35: 2027 | I35: 2028 | J35: 2029 | K35: 2030 | L35: 2031 | M35: 2032 | N35: 2033 | O35: 2034 | P35: 2035 | Q35: 2036 | R35: 2037 | S35: 2038 | T35: 2039 | U35: 2040 | V35: 2041 | W35: 2042
B36: 表 62 | D36: =ABS('表 62_滾算紀錄3'!D50) | E36: =ABS('表 62_滾算紀錄3'!E50) | F36: =ABS('表 62_滾算紀錄3'!F50) | G36: =ABS('表 62_滾算紀錄3'!G50) | H36: =ABS('表 62_滾算紀錄3'!H50) | I36: =ABS('表 62_滾算紀錄3'!I50) | J36: =ABS('表 62_滾算紀錄3'!J50) | K36: =ABS('表 62_滾算紀錄3'!K50) | ... W36: =ABS('表 62_滾算紀錄3'!W50)
B37: 表 62 | D37: =ABS('表 62_滾算紀錄2'!D50) | E37: =ABS('表 62_滾算紀錄2'!E50) | F37: =ABS('表 62_滾算紀錄2'!F50) | G37: =ABS('表 62_滾算紀錄2'!G50) | H37: =ABS('表 62_滾算紀錄2'!H50) | I37: =ABS('表 62_滾算紀錄2'!I50) | J37: =ABS('表 62_滾算紀錄2'!J50) | K37: =ABS('表 62_滾算紀錄2'!K50) | ... W37: =ABS('表 62_滾算紀錄2'!W50)
B38: 表 62 | D38: =ABS('表 62_滾算紀錄4'!D50) | E38: =ABS('表 62_滾算紀錄4'!E50) | F38: =ABS('表 62_滾算紀錄4'!F50) | G38: =ABS('表 62_滾算紀錄4'!G50) | H38: =ABS('表 62_滾算紀錄4'!H50) | I38: =ABS('表 62_滾算紀錄4'!I50) | J38: =ABS('表 62_滾算紀錄4'!J50) | K38: =ABS('表 62_滾算紀錄4'!K50) | ... W38: =ABS('表 62_滾算紀錄4'!W50)
B39: 表 62 | D39: =ABS('表 62_滾算紀錄6'!D50) | E39: =ABS('表 62_滾算紀錄6'!E50) | F39: =ABS('表 62_滾算紀錄6'!F50) | G39: =ABS('表 62_滾算紀錄6'!G50) | H39: =ABS('表 62_滾算紀錄6'!H50) | I39: =ABS('表 62_滾算紀錄6'!I50) | J39: =ABS('表 62_滾算紀錄6'!J50) | K39: =ABS('表 62_滾算紀錄6'!K50) | ... W39: =ABS('表 62_滾算紀錄6'!W50)
C40: 模組回收費/年總計 | D40: =SUM(D36:D39) | E40: =SUM(E36:E39) | F40: =SUM(F36:F39) | G40: =SUM(G36:G39) | H40: =SUM(H36:H39) | I40: =SUM(I36:I39) | J40: =SUM(J36:J39) | K40: =SUM(K36:K39) | ... W40: =SUM(W36:W39)
C41: 所得稅 | D41: 2023 | E41: 2024 | F41: 2025 | G41: 2026 | H41: 2027 | I41: 2028 | J41: 2029 | K41: 2030 | L41: 2031 | M41: 2032 | N41: 2033 | O41: 2034 | P41: 2035 | Q41: 2036 | R41: 2037 | S41: 2038 | T41: 2039 | U41: 2040 | V41: 2041 | W41: 2042
B42: 表 62 | D42: =ABS('表 62_滾算紀錄3'!D54) | E42: =ABS('表 62_滾算紀錄3'!E54) | F42: =ABS('表 62_滾算紀錄3'!F54) | G42: =ABS('表 62_滾算紀錄3'!G54) | H42: =ABS('表 62_滾算紀錄3'!H54) | I42: =ABS('表 62_滾算紀錄3'!I54) | J42: =ABS('表 62_滾算紀錄3'!J54) | K42: =ABS('表 62_滾算紀錄3'!K54) | ... W42: =ABS('表 62_滾算紀錄3'!W54)
B43: 表 62 | D43: =ABS('表 62_滾算紀錄2'!D54) | E43: =ABS('表 62_滾算紀錄2'!E54) | F43: =ABS('表 62_滾算紀錄2'!F54) | G43: =ABS('表 62_滾算紀錄2'!G54) | H43: =ABS('表 62_滾算紀錄2'!H54) | I43: =ABS('表 62_滾算紀錄2'!I54) | J43: =ABS('表 62_滾算紀錄2'!J54) | K43: =ABS('表 62_滾算紀錄2'!K54) | ... W43: =ABS('表 62_滾算紀錄2'!W54)
B44: 表 62 | D44: =ABS('表 62_滾算紀錄4'!D54) | E44: =ABS('表 62_滾算紀錄4'!E54) | F44: =ABS('表 62_滾算紀錄4'!F54) | G44: =ABS('表 62_滾算紀錄4'!G54) | H44: =ABS('表 62_滾算紀錄4'!H54) | I44: =ABS('表 62_滾算紀錄4'!I54) | J44: =ABS('表 62_滾算紀錄4'!J54) | K44: =ABS('表 62_滾算紀錄4'!K54) | ... W44: =ABS('表 62_滾算紀錄4'!W54)
B45: 表 62 | D45: =ABS('表 62_滾算紀錄6'!D54) | E45: =ABS('表 62_滾算紀錄6'!E54) | F45: =ABS('表 62_滾算紀錄6'!F54) | G45: =ABS('表 62_滾算紀錄6'!G54) | H45: =ABS('表 62_滾算紀錄6'!H54) | I45: =ABS('表 62_滾算紀錄6'!I54) | J45: =ABS('表 62_滾算紀錄6'!J54) | K45: =ABS('表 62_滾算紀錄6'!K54) | ... W45: =ABS('表 62_滾算紀錄6'!W54)
C46: 所得稅/年總計 | D46: =SUM(D42:D45) | E46: =SUM(E42:E45) | F46: =SUM(F42:F45) | G46: =SUM(G42:G45) | H46: =SUM(H42:H45) | I46: =SUM(I42:I45) | J46: =SUM(J42:J45) | K46: =SUM(K42:K45) | ... W46: =SUM(W42:W45)
C47: 設備折舊 | D47: 2023 | E47: 2024 | F47: 2025 | G47: 2026 | H47: 2027 | I47: 2028 | J47: 2029 | K47: 2030 | L47: 2031 | M47: 2032 | N47: 2033 | O47: 2034 | P47: 2035 | Q47: 2036 | R47: 2037 | S47: 2038 | T47: 2039 | U47: 2040 | V47: 2041 | W47: 2042
B48: 表 62 | D48: =ABS('表 62_滾算紀錄3'!D67) | E48: =ABS('表 62_滾算紀錄3'!E67) | F48: =ABS('表 62_滾算紀錄3'!F67) | G48: =ABS('表 62_滾算紀錄3'!G67) | H48: =ABS('表 62_滾算紀錄3'!H67) | I48: =ABS('表 62_滾算紀錄3'!I67) | J48: =ABS('表 62_滾算紀錄3'!J67) | K48: =ABS('表 62_滾算紀錄3'!K67) | ... W48: =ABS('表 62_滾算紀錄3'!W67)
B49: 表 62 | D49: =ABS('表 62_滾算紀錄2'!D67) | E49: =ABS('表 62_滾算紀錄2'!E67) | F49: =ABS('表 62_滾算紀錄2'!F67) | G49: =ABS('表 62_滾算紀錄2'!G67) | H49: =ABS('表 62_滾算紀錄2'!H67) | I49: =ABS('表 62_滾算紀錄2'!I67) | J49: =ABS('表 62_滾算紀錄2'!J67) | K49: =ABS('表 62_滾算紀錄2'!K67) | ... W49: =ABS('表 62_滾算紀錄2'!W67)
B50: 表 62 | D50: =ABS('表 62_滾算紀錄4'!D67) | E50: =ABS('表 62_滾算紀錄4'!E67) | F50: =ABS('表 62_滾算紀錄4'!F67) | G50: =ABS('表 62_滾算紀錄4'!G67) | H50: =ABS('表 62_滾算紀錄4'!H67) | I50: =ABS('表 62_滾算紀錄4'!I67) | J50: =ABS('表 62_滾算紀錄4'!J67) | K50: =ABS('表 62_滾算紀錄4'!K67) | ... W50: =ABS('表 62_滾算紀錄4'!W67)
B51: 表 62 | D51: =ABS('表 62_滾算紀錄6'!D67) | E51: =ABS('表 62_滾算紀錄6'!E67) | F51: =ABS('表 62_滾算紀錄6'!F67) | G51: =ABS('表 62_滾算紀錄6'!G67) | H51: =ABS('表 62_滾算紀錄6'!H67) | I51: =ABS('表 62_滾算紀錄6'!I67) | J51: =ABS('表 62_滾算紀錄6'!J67) | K51: =ABS('表 62_滾算紀錄6'!K67) | ... W51: =ABS('表 62_滾算紀錄6'!W67)
C52: 設備折舊/年總計 | D52: =SUM(D48:D51) | E52: =SUM(E48:E51) | F52: =SUM(F48:F51) | G52: =SUM(G48:G51) | H52: =SUM(H48:H51) | I52: =SUM(I48:I51) | J52: =SUM(J48:J51) | K52: =SUM(K48:K51) | ... W52: =SUM(W48:W51)
C59: 年份 | D59: 2023 | E59: 2024 | F59: 2025 | G59: 2026 | H59: 2027 | I59: 2028 | J59: 2029 | K59: 2030 | L59: 2031 | M59: 2032 | N59: 2033 | O59: 2034 | P59: 2035 | Q59: 2036 | R59: 2037 | S59: 2038 | T59: 2039 | U59: 2040 | V59: 2041 | W59: 2042
B60: 0
B61: (Unit : Currency) | C61: 0 | D61: 1 | E61: 2 | F61: 3 | G61: 4 | H61: 5 | I61: 6 | J61: 7 | K61: 8 | L61: 9 | M61: 10 | N61: 11 | O61: 12 | P61: 13 | Q61: 14 | R61: 15 | S61: 16 | T61: 17 | U61: 18 | V61: 19 | W61: 20
B62: 發電度數(KWH) | C62: 0 | D62: =D10 | E62: =E10 | F62: =F10 | G62: =G10 | H62: =H10 | I62: =I10 | J62: =J10 | K62: =K10 | ... W62: =W10
B63: Inflow : 電費收入 | C63: - | D63: =D16 | E63: =E16 | F63: =F16 | G63: =G16 | H63: =H16 | I63: =I16 | J63: =J16 | K63: =K16 | ... W63: =W16
B64: Inflow : 政府補助 | C64: - | G64: - | H64: - | I64: - | J64: - | K64: - | L64: - | M64: - | N64: - | O64: - | P64: - | Q64: - | R64: - | S64: - | T64: - | U64: - | V64: - | W64: -
B65: Inflow : 銀行借款
B66: Outflow : 設備費用 | C66: =-(D16/(1-D17)+D18)*C4
B67: Outflow : 設備放置區域租金 | C67: - | D67: =D22 | E67: =E22 | F67: =F22 | G67: =G22 | H67: =H22 | I67: =I22 | J67: =J22 | K67: =K22 | ... W67: =W22
B68: Outflow : 返還借款
B69: Outflow : 利息費用 | C69: -
B70: Outflow : 維運費 | C70: - | D70: =D28 | E70: =E28 | F70: =F28 | G70: =G28 | H70: =H28 | I70: =I28 | J70: =J28 | K70: =K28 | ... W70: =W28
B71: Outflow : 保險費 | C71: - | D71: =D34 | E71: =E34 | F71: =F34 | G71: =G34 | H71: =H34 | I71: =I34 | J71: =J34 | K71: =K34 | ... W71: =W34
B72: Outflow : 模組回收費 | D72: =D40 | E72: =E40 | F72: =F40 | G72: =G40 | H72: =H40 | I72: =I40 | J72: =J40 | K72: =K40 | ... W72: =W40
B73: Outflow : 其它費用(人事薪資…等)
B74: 1%管理費
B75: 績效獎金
B76: 所得稅20% | D76: =D46 | E76: =E46 | F76: =F46 | G76: =G46 | H76: =H46 | I76: =I46 | J76: =J46 | K76: =K46 | ... W76: =W46
B77: 現金流 | C77: =C44 | D77: =SUM(D41:D54) | E77: =SUM(E41:E54) | F77: =SUM(F41:F54) | G77: =SUM(G41:G54) | H77: =SUM(H41:H54) | I77: =SUM(I41:I54) | J77: =SUM(J41:J54) | K77: =SUM(K41:K54) | ... W77: =SUM(W41:W54)
B78: 累計現金流 | D78: =C55+D55 | E78: =D56+E55 | F78: =E56+F55 | G78: =F56+G55 | H78: =G56+H55 | I78: =H56+I55 | J78: =I56+J55 | K78: =J56+K55 | L78: =K56+L55 | ... W78: =V56+W55
B79: 回收年限評估 | D79: =IF((D56)>0,"回收","未回收") | E79: =IF((E56)>0,"回收","未回收") | F79: =IF((F56)>0,"回收","未回收") | G79: =IF((G56)>0,"回收","未回收") | H79: =IF((H56)>0,"回收","未回收") | I79: =IF((I56)>0,"回收","未回收") | J79: =IF((J56)>0,"回收","未回收") | K79: =IF((K56)>0,"回收","未回收") | ... W79: =IF((W56)>0,"回收","未回收")
B80: 專案法IRR | C80: =IRR(C55:W55)
C82: 年份 | D82: 2023 | E82: 2024 | F82: 2025 | G82: 2026 | H82: 2027 | I82: 2028 | J82: 2029 | K82: 2030 | L82: 2031 | M82: 2032 | N82: 2033 | O82: 2034 | P82: 2035 | Q82: 2036 | R82: 2037 | S82: 2038 | T82: 2039 | U82: 2040 | V82: 2041 | W82: 2042
B83: 0 | T83: 償還年限
B84: (Unit : Currency) | C84: 0 | D84: 1 | E84: 2 | F84: 3 | G84: 4 | H84: 5 | I84: 6 | J84: 7 | K84: 8 | L84: 9 | M84: 10 | N84: 11 | O84: 12 | P84: 13 | Q84: 14 | R84: 15 | S84: 16 | T84: 17 | U84: 18 | V84: 19 | W84: 20
B85: 發電度數(KWH) | C85: 0 | D85: =D40 | E85: =E40 | F85: =F40 | G85: =G40 | H85: =H40 | I85: =I40 | J85: =J40 | K85: =K40 | ... W85: =W40
B86: Inflow : 電費收入 | C86: - | D86: =D41 | E86: =E41 | F86: =F41 | G86: =G41 | H86: =H41 | I86: =I41 | J86: =J41 | K86: =K41 | ... W86: =W41
B87: Inflow : 政府補助 | C87: - | G87: - | H87: - | I87: - | J87: - | K87: - | L87: - | M87: - | N87: - | O87: - | P87: - | Q87: - | R87: - | S87: - | T87: - | U87: - | V87: - | W87: -
B88: Inflow : 銀行借款
B89: Outflow : 設備折舊 | D89: =D52 | E89: =E52 | F89: =F52 | G89: =G52 | H89: =H52 | I89: =I52 | J89: =J52 | K89: =K52 | ... W89: =W52
B90: Outflow : 設備放置區域租金 | C90: - | D90: =D45 | E90: =E45 | F90: =F45 | G90: =G45 | H90: =H45 | I90: =I45 | J90: =J45 | K90: =K45 | ... W90: =W45
B91: Outflow : 返還借款
B92: Outflow : 利息費用 | C92: -
B93: Outflow : 維運費 | C93: - | D93: =D48 | E93: =E48 | F93: =F48 | G93: =G48 | H93: =H48 | I93: =I48 | J93: =J48 | K93: =K48 | ... W93: =W48
B94: Outflow : 保險費 | C94: - | D94: =D49 | E94: =E49 | F94: =F49 | G94: =G49 | H94: =H49 | I94: =I49 | J94: =J49 | K94: =K49 | ... W94: =W49
B95: Outflow : 模組回收費 | D95: =D50 | E95: =E50 | F95: =F50 | G95: =G50 | H95: =H50 | I95: =I50 | J95: =J50 | K95: =K50 | ... W95: =W50
B96: Outflow : 其它費用(人事薪資…等)
B97: 1%管理費
B98: 稅前淨利 | D98: =SUM(D64:D75) | E98: =SUM(E64:E75) | F98: =SUM(F64:F75) | G98: =SUM(G64:G75) | H98: =SUM(H64:H75) | I98: =SUM(I64:I75) | J98: =SUM(J64:J75) | K98: =SUM(K64:K75) | ... W98: =SUM(W64:W75)
B99: 所得稅20% | D99: =-D76*0.2 | E99: =-E76*0.2 | F99: =-F76*0.2 | G99: =-G76*0.2 | H99: =-H76*0.2 | I99: =-I76*0.2 | J99: =-J76*0.2 | K99: =-K76*0.2 | ... W99: =-W76*0.2
B100: 稅後淨利 | D100: =SUM(D76:D77) | E100: =SUM(E76:E77) | F100: =SUM(F76:F77) | G100: =SUM(G76:G77) | H100: =SUM(H76:H77) | I100: =SUM(I76:I77) | J100: =SUM(J76:J77) | K100: =SUM(K76:K77) | ... W100: =SUM(W76:W77)
B101: 累計現金流
B102: 回收年限評估
C103: 年份 | D103: 2023 | E103: 2024 | F103: 2025 | G103: 2026 | H103: 2027 | I103: 2028 | J103: 2029 | K103: 2030 | L103: 2031 | M103: 2032 | N103: 2033 | O103: 2034 | P103: 2035 | Q103: 2036 | R103: 2037 | S103: 2038 | T103: 2039 | U103: 2040 | V103: 2041 | W103: 2042
B105: (Unit : Currency) | C105: 0 | D105: 1 | E105: 2 | F105: 3 | G105: 4 | H105: 5 | I105: 6 | J105: 7 | K105: 8 | L105: 9 | M105: 10 | N105: 11 | O105: 12 | P105: 13 | Q105: 14 | R105: 15 | S105: 16 | T105: 17 | U105: 18 | V105: 19 | W105: 20
B106: 稅後淨利 | D106: =D78 | E106: =E78 | F106: =F78 | G106: =G78 | H106: =H78 | I106: =I78 | J106: =J78 | K106: =K78 | ... W106: =W78
B107: 設備折舊 | D107: =-D67 | E107: =-E67 | F107: =-F67 | G107: =-G67 | H107: =-H67 | I107: =-I67 | J107: =-J67 | K107: =-K67 | ... W107: =-W67
B108: 營運活動現金流量 | D108: =SUM(D85:D86) | E108: =SUM(E85:E86) | F108: =SUM(F85:F86) | G108: =SUM(G85:G86) | H108: =SUM(H85:H86) | I108: =SUM(I85:I86) | J108: =SUM(J85:J86) | K108: =SUM(K85:K86) | ... W108: =SUM(W85:W86)
B110: 投資活動-設備支出 | D110: =C44
B113: 理財活動-借款 | D113: =-D89*D31
B114: 理財活動-還款
...

Sheet 表 62_滾算紀錄3
B1: 電站基本資料
B2: 電站名稱 | C2: 淡江大學-財務模擬案場 | D2: - | E2: -
B3: 電站壽命 | C3: 20 | D3: - | E3: -
B4: 建置量(kWp) | C4: 436.1 | D4: - | E4: - | M4: 滾算紀錄編號: 3
B5: 起始年度 | C5: 2023 | D5: 結束年度 | E5: 2042 | M5: 第2次滾算摘要
M6: 價金: 28000
B7: 綜合損益表 | M7: 專案IRR: 4.98
B8: 收入 | M8: 權益法IRR: 13.18
B9: 收支項目 | C9: 相關參數 | D9: 參數數值 | E9: 年限 | M9: 利潤率: 20.00%
B10: 電費收入 | C10: 年度AC併網總發電量 | D10: 547002 | E10: 20 | M10: 第2次滾算，減少 1000 元 - 現金模式，每次減少 1000 元
C11: 首年衰退率 | D11: 0.01
C12: 次年衰退率 | D12: 0.004
C13: 躉售費率(FIT) | D13: 3.7152
B14: 支出
B15: 收支項目 | C15: 相關參數 | D15: 參數數值 | E15: 攤提年限
B16: 設備費用(價金) | C16: 每kWp設備成本 | D16: 28000 | E16: 20
C17: 信邦利潤率 | D17: 0.2
C18: 開發費 | D18: 2000
B19: 租金費用 | C19: 租金計算方式 (1=固定攤提/2=電費抽成) | D19: 1 | E19: 0
C20: 【方式1參數】租金總額 | D20: 5804025 | E20: 20
C21: 【方式2參數】抽成比率 | D21: 0 | E21: 0
B22: 運維費用 | C22: 每kw運維成本 | D22: 400 | E22: 20
B23: 保險費用 | C23: 占整體設備費用比例 | D23: 0.003 | E23: 20
B24: 模組回收費用 | C24: 每kw模組回收成本 | D24: 1000 | E24: 10
B25: 利息費用 | C25: 銀行利率 | D25: 0.025595 | E25: 0
B26: 所得稅 | C26: 所得稅率 | D26: 0.2 | E26: 0
B29: 現金流量表
B30: 金流項目 | C30: 相關參數 | D30: 參數數值
B31: 貸款成數 | C31: 占總設備費用比例 | D31: 0.8
B32: 貸款還款 | C32: 攤還期數 | D32: 15
B33: 現金股利 | C33: 股利比率 | D33: 0.9
B34: 年底減資 | C34: 攤還期數 | D34: 4
C37: 年份 | D37: 2023 | E37: 2024 | F37: 2025 | G37: 2026 | H37: 2027 | I37: 2028 | J37: 2029 | K37: 2030 | L37: 2031 | M37: 2032 | N37: 2033 | O37: 2034 | P37: 2035 | Q37: 2036 | R37: 2037 | S37: 2038 | T37: 2039 | U37: 2040 | V37: 2041 | W37: 2042
B38: 0
B39: (Unit : Currency) | C39: 0 | D39: 1 | E39: 2 | F39: 3 | G39: 4 | H39: 5 | I39: 6 | J39: 7 | K39: 8 | L39: 9 | M39: 10 | N39: 11 | O39: 12 | P39: 13 | Q39: 14 | R39: 15 | S39: 16 | T39: 17 | U39: 18 | V39: 19 | W39: 20
B40: 發電度數(KWH) | C40: 0 | D40: =$D$10*0.99 | E40: =$D$10*0.986 | F40: =$D$10*0.982 | G40: =$D$10*0.978 | H40: =$D$10*0.974 | I40: =$D$10*0.97 | J40: =$D$10*0.966 | K40: =$D$10*0.962 | L40: =$D$10*0.958 | M40: =$D$10*0.954 | N40: =$D$10*0.95 | O40: =$D$10*0.946 | P40: =$D$10*0.942 | Q40: =$D$10*0.938 | R40: =$D$10*0.934 | S40: =$D$10*0.93 | T40: =$D$10*0.926 | U40: =$D$10*0.922 | V40: =$D$10*0.918 | W40: =$D$10*0.914
B41: Inflow : 電費收入 | C41: - | D41: =D40*$D$13 | E41: =E40*$D$13 | F41: =F40*$D$13 | G41: =G40*$D$13 | H41: =H40*$D$13 | I41: =I40*$D$13 | J41: =J40*$D$13 | K41: =K40*$D$13 | ... W41: =W40*$D$13
B42: Inflow : 政府補助 | C42: - | G42: - | H42: - | I42: - | J42: - | K42: - | L42: - | M42: - | N42: - | O42: - | P42: - | Q42: - | R42: - | S42: - | T42: - | U42: - | V42: - | W42: -
B43: Inflow : 銀行借款
B44: Outflow : 設備費用 | C44: =-(D16/(1-D17)+D18)*C4
B45: Outflow : 設備放置區域租金 | C45: - | D45: 0 | E45: -290201.25 | F45: -290201.25 | G45: -290201.25 | H45: -290201.25 | I45: -290201.25 | J45: -290201.25 | K45: -290201.25 | L45: -290201.25 | M45: -290201.25 | N45: -290201.25 | O45: -290201.25 | P45: -290201.25 | Q45: -290201.25 | R45: -290201.25 | S45: -290201.25 | T45: -290201.25 | U45: -290201.25 | V45: -290201.25 | W45: -290201.25
B46: Outflow : 返還借款
B47: Outflow : 利息費用 | C47: -
B48: Outflow : 維運費 | C48: - | D48: -174440 | E48: -174440 | F48: -174440 | G48: -174440 | H48: -174440 | I48: -174440 | J48: -174440 | K48: -174440 | L48: -174440 | M48: -174440 | N48: -174440 | O48: -174440 | P48: -174440 | Q48: -174440 | R48: -174440 | S48: -174440 | T48: -174440 | U48: -174440 | V48: -174440 | W48: -174440
B49: Outflow : 保險費 | C49: - | D49: -36632.4 | E49: -36632.4 | F49: -36632.4 | G49: -36632.4 | H49: -36632.4 | I49: -36632.4 | J49: -36632.4 | K49: -36632.4 | L49: -36632.4 | M49: -36632.4 | N49: -36632.4 | O49: -36632.4 | P49: -36632.4 | Q49: -36632.4 | R49: -36632.4 | S49: -36632.4 | T49: -36632.4 | U49: -36632.4 | V49: -36632.4 | W49: -36632.4
B50: Outflow : 模組回收費 | D50: -43610 | E50: -43610 | F50: -43610 | G50: -43610 | H50: -43610 | I50: -43610 | J50: -43610 | K50: -43610 | L50: -43610 | M50: -43610 | N50: 0 | O50: 0 | P50: 0 | Q50: 0 | R50: 0 | S50: 0 | T50: 0 | U50: 0 | V50: 0 | W50: 0
B51: Outflow : 其它費用(人事薪資…等)
B52: 1%管理費
B53: 績效獎金
B54: 所得稅20% | D54: =D77 | E54: =E77 | F54: =F77 | G54: =G77 | H54: =H77 | I54: =I77 | J54: =J77 | K54: =K77 | ... W54: =W77
B55: 現金流 | C55: =C44 | D55: =SUM(D41:D54) | E55: =SUM(E41:E54) | F55: =SUM(F41:F54) | G55: =SUM(G41:G54) | H55: =SUM(H41:H54) | I55: =SUM(I41:I54) | J55: =SUM(J41:J54) | K55: =SUM(K41:K54) | ... W55: =SUM(W41:W54)
B56: 累計現金流 | D56: =C55+D55 | E56: =D56+E55 | F56: =E56+F55 | G56: =F56+G55 | H56: =G56+H55 | I56: =H56+I55 | J56: =I56+J55 | K56: =J56+K55 | L56: =K56+L55 | ... X56: =W56+X55
B57: 回收年限評估 | D57: =IF((D56)>0,"回收","未回收") | E57: =IF((E56)>0,"回收","未回收") | F57: =IF((F56)>0,"回收","未回收") | G57: =IF((G56)>0,"回收","未回收") | H57: =IF((H56)>0,"回收","未回收") | I57: =IF((I56)>0,"回收","未回收") | J57: =IF((J56)>0,"回收","未回收") | K57: =IF((K56)>0,"回收","未回收") | ... X57: =IF((X56)>0,"回收","未回收")
B58: 專案法IRR | C58: =IRR(C55:W55)
C60: 年份 | D60: =D37 | E60: =E37 | F60: =F37 | G60: =G37 | H60: =H37 | I60: =I37 | J60: =J37 | K60: =K37 | ... W60: =W37
B61: 0 | T61: 償還年限
B62: (Unit : Currency) | C62: 0 | D62: 1 | E62: 2 | F62: 3 | G62: 4 | H62: 5 | I62: 6 | J62: 7 | K62: 8 | L62: 9 | M62: 10 | N62: 11 | O62: 12 | P62: 13 | Q62: 14 | R62: 15 | S62: 16 | T62: 17 | U62: 18 | V62: 19 | W62: 20
B63: 發電度數(KWH) | C63: 0 | D63: =D40 | E63: =E40 | F63: =F40 | G63: =G40 | H63: =H40 | I63: =I40 | J63: =J40 | K63: =K40 | ... W63: =W40
B64: Inflow : 電費收入 | C64: - | D64: =D41 | E64: =E41 | F64: =F41 | G64: =G41 | H64: =H41 | I64: =I41 | J64: =J41 | K64: =K41 | ... W64: =W41
B65: Inflow : 政府補助 | C65: - | G65: - | H65: - | I65: - | J65: - | K65: - | L65: - | M65: - | N65: - | O65: - | P65: - | Q65: - | R65: - | S65: - | T65: - | U65: - | V65: - | W65: -
B66: Inflow : 銀行借款
B67: Outflow : 設備折舊 | D67: =$C$44/$E$16 | E67: =$C$44/$E$16 | F67: =$C$44/$E$16 | G67: =$C$44/$E$16 | H67: =$C$44/$E$16 | I67: =$C$44/$E$16 | J67: =$C$44/$E$16 | K67: =$C$44/$E$16 | ... W67: =$C$44/$E$16
B68: Outflow : 設備放置區域租金 | C68: - | D68: =D45 | E68: =E45 | F68: =F45 | G68: =G45 | H68: =H45 | I68: =I45 | J68: =J45 | K68: =K45 | ... W68: =W45
B69: Outflow : 返還借款
B70: Outflow : 利息費用 | C70: - | D70: 0 | E70: 0 | F70: 0 | G70: 0 | H70: 0 | I70: 0 | J70: 0 | K70: 0 | L70: 0 | M70: 0 | N70: 0 | O70: 0 | P70: 0 | Q70: 0 | R70: 0 | S70: 0 | T70: 0 | U70: 0 | V70: 0 | W70: 0
B71: Outflow : 維運費 | C71: - | D71: =D48 | E71: =E48 | F71: =F48 | G71: =G48 | H71: =H48 | I71: =I48 | J71: =J48 | K71: =K48 | ... W71: =W48
B72: Outflow : 保險費 | C72: - | D72: =D49 | E72: =E49 | F72: =F49 | G72: =G49 | H72: =H49 | I72: =I49 | J72: =J49 | K72: =K49 | ... W72: =W49
B73: Outflow : 模組回收費 | D73: =D50 | E73: =E50 | F73: =F50 | G73: =G50 | H73: =H50 | I73: =I50 | J73: =J50 | K73: =K50 | ... W73: =W50
B74: Outflow : 其它費用(人事薪資…等)
B75: 1%管理費
B76: 稅前淨利 | D76: =SUM(D64:D75) | E76: =SUM(E64:E75) | F76: =SUM(F64:F75) | G76: =SUM(G64:G75) | H76: =SUM(H64:H75) | I76: =SUM(I64:I75) | J76: =SUM(J64:J75) | K76: =SUM(K64:K75) | ... X76: =SUM(X64:X75)
B77: 所得稅20% | D77: =-D76*0.2 | E77: =-E76*0.2 | F77: =-F76*0.2 | G77: =-G76*0.2 | H77: =-H76*0.2 | I77: =-I76*0.2 | J77: =-J76*0.2 | K77: =-K76*0.2 | ... X77: =-X76*0.2
B78: 稅後淨利 | D78: =SUM(D76:D77) | E78: =SUM(E76:E77) | F78: =SUM(F76:F77) | G78: =SUM(G76:G77) | H78: =SUM(H76:H77) | I78: =SUM(I76:I77) | J78: =SUM(J76:J77) | K78: =SUM(K76:K77) | ... X78: =SUM(X76:X77)
B79: 累計現金流
B80: 回收年限評估

Sheet 表 62_滾算紀錄2
B1: 電站基本資料
B2: 電站名稱 | C2: 淡江大學-財務模擬案場 | D2: - | E2: -
B3: 電站壽命 | C3: 20 | D3: - | E3: -
B4: 建置量(kWp) | C4: 436.1 | D4: - | E4: - | M4: 滾算紀錄編號: 2
B5: 起始年度 | C5: 2023 | D5: 結束年度 | E5: 2042 | M5: 第1次滾算摘要
M6: 價金: 29000
B7: 綜合損益表 | M7: 專案IRR: 4.63
B8: 收入 | M8: 權益法IRR: 11.74
B9: 收支項目 | C9: 相關參數 | D9: 參數數值 | E9: 年限 | M9: 利潤率: 20.00%
B10: 電費收入 | C10: 年度AC併網總發電量 | D10: 547002 | E10: 20 | M10: 第1次滾算，減少 1000 元 - 現金模式，每次減少 1000 元
C11: 首年衰退率 | D11: 0.01
C12: 次年衰退率 | D12: 0.004
C13: 躉售費率(FIT) | D13: 3.7152
B14: 支出
B15: 收支項目 | C15: 相關參數 | D15: 參數數值 | E15: 攤提年限
B16: 設備費用(價金) | C16: 每kWp設備成本 | D16: 29000 | E16: 20
C17: 信邦利潤率 | D17: 0.2
C18: 開發費 | D18: 2000
B19: 租金費用 | C19: 租金計算方式 (1=固定攤提/2=電費抽成) | D19: 1 | E19: 0
C20: 【方式1參數】租金總額 | D20: 5804025 | E20: 20
C21: 【方式2參數】抽成比率 | D21: 0 | E21: 0
B22: 運維費用 | C22: 每kw運維成本 | D22: 400 | E22: 20
B23: 保險費用 | C23: 占整體設備費用比例 | D23: 0.003 | E23: 20
B24: 模組回收費用 | C24: 每kw模組回收成本 | D24: 1000 | E24: 10
B25: 利息費用 | C25: 銀行利率 | D25: 0.025595 | E25: 0
B26: 所得稅 | C26: 所得稅率 | D26: 0.2 | E26: 0
B29: 現金流量表
B30: 金流項目 | C30: 相關參數 | D30: 參數數值
B31: 貸款成數 | C31: 占總設備費用比例 | D31: 0.8
B32: 貸款還款 | C32: 攤還期數 | D32: 15
B33: 現金股利 | C33: 股利比率 | D33: 0.9
B34: 年底減資 | C34: 攤還期數 | D34: 4
C37: 年份 | D37: 2023 | E37: 2024 | F37: 2025 | G37: 2026 | H37: 2027 | I37: 2028 | J37: 2029 | K37: 2030 | L37: 2031 | M37: 2032 | N37: 2033 | O37: 2034 | P37: 2035 | Q37: 2036 | R37: 2037 | S37: 2038 | T37: 2039 | U37: 2040 | V37: 2041 | W37: 2042
B38: 0
B39: (Unit : Currency) | C39: 0 | D39: 1 | E39: 2 | F39: 3 | G39: 4 | H39: 5 | I39: 6 | J39: 7 | K39: 8 | L39: 9 | M39: 10 | N39: 11 | O39: 12 | P39: 13 | Q39: 14 | R39: 15 | S39: 16 | T39: 17 | U39: 18 | V39: 19 | W39: 20
B40: 發電度數(KWH) | C40: 0 | D40: =$D$10*0.99 | E40: =$D$10*0.986 | F40: =$D$10*0.982 | G40: =$D$10*0.978 | H40: =$D$10*0.974 | I40: =$D$10*0.97 | J40: =$D$10*0.966 | K40: =$D$10*0.962 | L40: =$D$10*0.958 | M40: =$D$10*0.954 | N40: =$D$10*0.95 | O40: =$D$10*0.946 | P40: =$D$10*0.942 | Q40: =$D$10*0.938 | R40: =$D$10*0.934 | S40: =$D$10*0.93 | T40: =$D$10*0.926 | U40: =$D$10*0.922 | V40: =$D$10*0.918 | W40: =$D$10*0.914
B41: Inflow : 電費收入 | C41: - | D41: =D40*$D$13 | E41: =E40*$D$13 | F41: =F40*$D$13 | G41: =G40*$D$13 | H41: =H40*$D$13 | I41: =I40*$D$13 | J41: =J40*$D$13 | K41: =K40*$D$13 | ... W41: =W40*$D$13
B42: Inflow : 政府補助 | C42: - | G42: - | H42: - | I42: - | J42: - | K42: - | L42: - | M42: - | N42: - | O42: - | P42: - | Q42: - | R42: - | S42: - | T42: - | U42: - | V42: - | W42: -
B43: Inflow : 銀行借款
B44: Outflow : 設備費用 | C44: =-(D16/(1-D17)+D18)*C4
B45: Outflow : 設備放置區域租金 | C45: - | D45: 0 | E45: -290201.25 | F45: -290201.25 | G45: -290201.25 | H45: -290201.25 | I45: -290201.25 | J45: -290201.25 | K45: -290201.25 | L45: -290201.25 | M45: -290201.25 | N45: -290201.25 | O45: -290201.25 | P45: -290201.25 | Q45: -290201.25 | R45: -290201.25 | S45: -290201.25 | T45: -290201.25 | U45: -290201.25 | V45: -290201.25 | W45: -290201.25
B46: Outflow : 返還借款
B47: Outflow : 利息費用 | C47: -
B48: Outflow : 維運費 | C48: - | D48: -174440 | E48: -174440 | F48: -174440 | G48: -174440 | H48: -174440 | I48: -174440 | J48: -174440 | K48: -174440 | L48: -174440 | M48: -174440 | N48: -174440 | O48: -174440 | P48: -174440 | Q48: -174440 | R48: -174440 | S48: -174440 | T48: -174440 | U48: -174440 | V48: -174440 | W48: -174440
B49: Outflow : 保險費 | C49: - | D49: -37940.7 | E49: -37940.7 | F49: -37940.7 | G49: -37940.7 | H49: -37940.7 | I49: -37940.7 | J49: -37940.7 | K49: -37940.7 | L49: -37940.7 | M49: -37940.7 | N49: -37940.7 | O49: -37940.7 | P49: -37940.7 | Q49: -37940.7 | R49: -37940.7 | S49: -37940.7 | T49: -37940.7 | U49: -37940.7 | V49: -37940.7 | W49: -37940.7
B50: Outflow : 模組回收費 | D50: -43610 | E50: -43610 | F50: -43610 | G50: -43610 | H50: -43610 | I50: -43610 | J50: -43610 | K50: -43610 | L50: -43610 | M50: -43610 | N50: 0 | O50: 0 | P50: 0 | Q50: 0 | R50: 0 | S50: 0 | T50: 0 | U50: 0 | V50: 0 | W50: 0
B51: Outflow : 其它費用(人事薪資…等)
B52: 1%管理費
B53: 績效獎金
B54: 所得稅20% | D54: =D77 | E54: =E77 | F54: =F77 | G54: =G77 | H54: =H77 | I54: =I77 | J54: =J77 | K54: =K77 | ... W54: =W77
B55: 現金流 | C55: =C44 | D55: =SUM(D41:D54) | E55: =SUM(E41:E54) | F55: =SUM(F41:F54) | G55: =SUM(G41:G54) | H55: =SUM(H41:H54) | I55: =SUM(I41:I54) | J55: =SUM(J41:J54) | K55: =SUM(K41:K54) | ... W55: =SUM(W41:W54)
B56: 累計現金流 | D56: =C55+D55 | E56: =D56+E55 | F56: =E56+F55 | G56: =F56+G55 | H56: =G56+H55 | I56: =H56+I55 | J56: =I56+J55 | K56: =J56+K55 | L56: =K56+L55 | ... X56: =W56+X55
B57: 回收年限評估 | D57: =IF((D56)>0,"回收","未回收") | E57: =IF((E56)>0,"回收","未回收") | F57: =IF((F56)>0,"回收","未回收") | G57: =IF((G56)>0,"回收","未回收") | H57: =IF((H56)>0,"回收","未回收") | I57: =IF((I56)>0,"回收","未回收") | J57: =IF((J56)>0,"回收","未回收") | K57: =IF((K56)>0,"回收","未回收") | ... X57: =IF((X56)>0,"回收","未回收")
B58: 專案法IRR | C58: =IRR(C55:W55)
C60: 年份 | D60: =D37 | E60: =E37 | F60: =F37 | G60: =G37 | H60: =H37 | I60: =I37 | J60: =J37 | K60: =K37 | ... W60: =W37
B61: 0 | T61: 償還年限
B62: (Unit : Currency) | C62: 0 | D62: 1 | E62: 2 | F62: 3 | G62: 4 | H62: 5 | I62: 6 | J62: 7 | K62: 8 | L62: 9 | M62: 10 | N62: 11 | O62: 12 | P62: 13 | Q62: 14 | R62: 15 | S62: 16 | T62: 17 | U62: 18 | V62: 19 | W62: 20
B63: 發電度數(KWH) | C63: 0 | D63: =D40 | E63: =E40 | F63: =F40 | G63: =G40 | H63: =H40 | I63: =I40 | J63: =J40 | K63: =K40 | ... W63: =W40
B64: Inflow : 電費收入 | C64: - | D64: =D41 | E64: =E41 | F64: =F41 | G64: =G41 | H64: =H41 | I64: =I41 | J64: =J41 | K64: =K41 | ... W64: =W41
B65: Inflow : 政府補助 | C65: - | G65: - | H65: - | I65: - | J65: - | K65: - | L65: - | M65: - | N65: - | O65: - | P65: - | Q65: - | R65: - | S65: - | T65: - | U65: - | V65: - | W65: -
B66: Inflow : 銀行借款
B67: Outflow : 設備折舊 | D67: =$C$44/$E$16 | E67: =$C$44/$E$16 | F67: =$C$44/$E$16 | G67: =$C$44/$E$16 | H67: =$C$44/$E$16 | I67: =$C$44/$E$16 | J67: =$C$44/$E$16 | K67: =$C$44/$E$16 | ... W67: =$C$44/$E$16
B68: Outflow : 設備放置區域租金 | C68: - | D68: =D45 | E68: =E45 | F68: =F45 | G68: =G45 | H68: =H45 | I68: =I45 | J68: =J45 | K68: =K45 | ... W68: =W45
B69: Outflow : 返還借款
B70: Outflow : 利息費用 | C70: - | D70: 0 | E70: 0 | F70: 0 | G70: 0 | H70: 0 | I70: 0 | J70: 0 | K70: 0 | L70: 0 | M70: 0 | N70: 0 | O70: 0 | P70: 0 | Q70: 0 | R70: 0 | S70: 0 | T70: 0 | U70: 0 | V70: 0 | W70: 0
B71: Outflow : 維運費 | C71: - | D71: =D48 | E71: =E48 | F71: =F48 | G71: =G48 | H71: =H48 | I71: =I48 | J71: =J48 | K71: =K48 | ... W71: =W48
B72: Outflow : 保險費 | C72: - | D72: =D49 | E72: =E49 | F72: =F49 | G72: =G49 | H72: =H49 | I72: =I49 | J72: =J49 | K72: =K49 | ... W72: =W49
B73: Outflow : 模組回收費 | D73: =D50 | E73: =E50 | F73: =F50 | G73: =G50 | H73: =H50 | I73: =I50 | J73: =J50 | K73: =K50 | ... W73: =W50
B74: Outflow : 其它費用(人事薪資…等)
B75: 1%管理費
B76: 稅前淨利 | D76: =SUM(D64:D75) | E76: =SUM(E64:E75) | F76: =SUM(F64:F75) | G76: =SUM(G64:G75) | H76: =SUM(H64:H75) | I76: =SUM(I64:I75) | J76: =SUM(J64:J75) | K76: =SUM(K64:K75) | ... X76: =SUM(X64:X75)
B77: 所得稅20% | D77: =-D76*0.2 | E77: =-E76*0.2 | F77: =-F76*0.2 | G77: =-G76*0.2 | H77: =-H76*0.2 | I77: =-I76*0.2 | J77: =-J76*0.2 | K77: =-K76*0.2 | ... X77: =-X76*0.2
B78: 稅後淨利 | D78: =SUM(D76:D77) | E78: =SUM(E76:E77) | F78: =SUM(F76:F77) | G78: =SUM(G76:G77) | H78: =SUM(H76:H77) | I78: =SUM(I76:I77) | J78: =SUM(J76:J77) | K78: =SUM(K76:K77) | ... X78: =SUM(X76:X77)
B79: 累計現金流
B80: 回收年限評估

Sheet 表 62_滾算紀錄4
B1: 電站基本資料
B2: 電站名稱 | C2: 淡江大學-財務模擬案場 | D2: - | E2: -
B3: 電站壽命 | C3: 20 | D3: - | E3: -
B4: 建置量(kWp) | C4: 436.1 | D4: - | E4: - | M4: 滾算紀錄編號: 4
B5: 起始年度 | C5: 2023 | D5: 結束年度 | E5: 2042 | M5: 第3次滾算摘要
M6: 價金: 27000
B7: 綜合損益表 | M7: 專案IRR: 5.35
B8: 收入 | M8: 權益法IRR: 14.77
B9: 收支項目 | C9: 相關參數 | D9: 參數數值 | E9: 年限 | M9: 利潤率: 20.00%
B10: 電費收入 | C10: 年度AC併網總發電量 | D10: 547002 | E10: 20 | M10: 第3次滾算，減少 1000 元 - 現金模式，每次減少 1000 元
C11: 首年衰退率 | D11: 0.01
C12: 次年衰退率 | D12: 0.004
C13: 躉售費率(FIT) | D13: 3.7152
B14: 支出
B15: 收支項目 | C15: 相關參數 | D15: 參數數值 | E15: 攤提年限
B16: 設備費用(價金) | C16: 每kWp設備成本 | D16: 27000 | E16: 20
C17: 信邦利潤率 | D17: 0.2
C18: 開發費 | D18: 2000
B19: 租金費用 | C19: 租金計算方式 (1=固定攤提/2=電費抽成) | D19: 1 | E19: 0
C20: 【方式1參數】租金總額 | D20: 5804025 | E20: 20
C21: 【方式2參數】抽成比率 | D21: 0 | E21: 0
B22: 運維費用 | C22: 每kw運維成本 | D22: 400 | E22: 20
B23: 保險費用 | C23: 占整體設備費用比例 | D23: 0.003 | E23: 20
B24: 模組回收費用 | C24: 每kw模組回收成本 | D24: 1000 | E24: 10
B25: 利息費用 | C25: 銀行利率 | D25: 0.025595 | E25: 0
B26: 所得稅 | C26: 所得稅率 | D26: 0.2 | E26: 0
B29: 現金流量表
B30: 金流項目 | C30: 相關參數 | D30: 參數數值
B31: 貸款成數 | C31: 占總設備費用比例 | D31: 0.8
B32: 貸款還款 | C32: 攤還期數 | D32: 15
B33: 現金股利 | C33: 股利比率 | D33: 0.9
B34: 年底減資 | C34: 攤還期數 | D34: 4
C37: 年份 | D37: 2023 | E37: 2024 | F37: 2025 | G37: 2026 | H37: 2027 | I37: 2028 | J37: 2029 | K37: 2030 | L37: 2031 | M37: 2032 | N37: 2033 | O37: 2034 | P37: 2035 | Q37: 2036 | R37: 2037 | S37: 2038 | T37: 2039 | U37: 2040 | V37: 2041 | W37: 2042
B38: 0
B39: (Unit : Currency) | C39: 0 | D39: 1 | E39: 2 | F39: 3 | G39: 4 | H39: 5 | I39: 6 | J39: 7 | K39: 8 | L39: 9 | M39: 10 | N39: 11 | O39: 12 | P39: 13 | Q39: 14 | R39: 15 | S39: 16 | T39: 17 | U39: 18 | V39: 19 | W39: 20
B40: 發電度數(KWH) | C40: 0 | D40: =$D$10*0.99 | E40: =$D$10*0.986 | F40: =$D$10*0.982 | G40: =$D$10*0.978 | H40: =$D$10*0.974 | I40: =$D$10*0.97 | J40: =$D$10*0.966 | K40: =$D$10*0.962 | L40: =$D$10*0.958 | M40: =$D$10*0.954 | N40: =$D$10*0.95 | O40: =$D$10*0.946 | P40: =$D$10*0.942 | Q40: =$D$10*0.938 | R40: =$D$10*0.934 | S40: =$D$10*0.93 | T40: =$D$10*0.926 | U40: =$D$10*0.922 | V40: =$D$10*0.918 | W40: =$D$10*0.914
B41: Inflow : 電費收入 | C41: - | D41: =D40*$D$13 | E41: =E40*$D$13 | F41: =F40*$D$13 | G41: =G40*$D$13 | H41: =H40*$D$13 | I41: =I40*$D$13 | J41: =J40*$D$13 | K41: =K40*$D$13 | ... W41: =W40*$D$13
B42: Inflow : 政府補助 | C42: - | G42: - | H42: - | I42: - | J42: - | K42: - | L42: - | M42: - | N42: - | O42: - | P42: - | Q42: - | R42: - | S42: - | T42: - | U42: - | V42: - | W42: -
B43: Inflow : 銀行借款
B44: Outflow : 設備費用 | C44: =-(D16/(1-D17)+D18)*C4
B45: Outflow : 設備放置區域租金 | C45: - | D45: 0 | E45: -290201.25 | F45: -290201.25 | G45: -290201.25 | H45: -290201.25 | I45: -290201.25 | J45: -290201.25 | K45: -290201.25 | L45: -290201.25 | M45: -290201.25 | N45: -290201.25 | O45: -290201.25 | P45: -290201.25 | Q45: -290201.25 | R45: -290201.25 | S45: -290201.25 | T45: -290201.25 | U45: -290201.25 | V45: -290201.25 | W45: -290201.25
B46: Outflow : 返還借款
B47: Outflow : 利息費用 | C47: -
B48: Outflow : 維運費 | C48: - | D48: -174440 | E48: -174440 | F48: -174440 | G48: -174440 | H48: -174440 | I48: -174440 | J48: -174440 | K48: -174440 | L48: -174440 | M48: -174440 | N48: -174440 | O48: -174440 | P48: -174440 | Q48: -174440 | R48: -174440 | S48: -174440 | T48: -174440 | U48: -174440 | V48: -174440 | W48: -174440
B49: Outflow : 保險費 | C49: - | D49: -35324.1 | E49: -35324.1 | F49: -35324.1 | G49: -35324.1 | H49: -35324.1 | I49: -35324.1 | J49: -35324.1 | K49: -35324.1 | L49: -35324.1 | M49: -35324.1 | N49: -35324.1 | O49: -35324.1 | P49: -35324.1 | Q49: -35324.1 | R49: -35324.1 | S49: -35324.1 | T49: -35324.1 | U49: -35324.1 | V49: -35324.1 | W49: -35324.1
B50: Outflow : 模組回收費 | D50: -43610 | E50: -43610 | F50: -43610 | G50: -43610 | H50: -43610 | I50: -43610 | J50: -43610 | K50: -43610 | L50: -43610 | M50: -43610 | N50: 0 | O50: 0 | P50: 0 | Q50: 0 | R50: 0 | S50: 0 | T50: 0 | U50: 0 | V50: 0 | W50: 0
B51: Outflow : 其它費用(人事薪資…等)
B52: 1%管理費
B53: 績效獎金
B54: 所得稅20% | D54: =D77 | E54: =E77 | F54: =F77 | G54: =G77 | H54: =H77 | I54: =I77 | J54: =J77 | K54: =K77 | ... W54: =W77
B55: 現金流 | C55: =C44 | D55: =SUM(D41:D54) | E55: =SUM(E41:E54) | F55: =SUM(F41:F54) | G55: =SUM(G41:G54) | H55: =SUM(H41:H54) | I55: =SUM(I41:I54) | J55: =SUM(J41:J54) | K55: =SUM(K41:K54) | ... W55: =SUM(W41:W54)
B56: 累計現金流 | D56: =C55+D55 | E56: =D56+E55 | F56: =E56+F55 | G56: =F56+G55 | H56: =G56+H55 | I56: =H56+I55 | J56: =I56+J55 | K56: =J56+K55 | L56: =K56+L55 | ... X56: =W56+X55
B57: 回收年限評估 | D57: =IF((D56)>0,"回收","未回收") | E57: =IF((E56)>0,"回收","未回收") | F57: =IF((F56)>0,"回收","未回收") | G57: =IF((G56)>0,"回收","未回收") | H57: =IF((H56)>0,"回收","未回收") | I57: =IF((I56)>0,"回收","未回收") | J57: =IF((J56)>0,"回收","未回收") | K57: =IF((K56)>0,"回收","未回收") | ... X57: =IF((X56)>0,"回收","未回收")
B58: 專案法IRR | C58: =IRR(C55:W55)
C60: 年份 | D60: =D37 | E60: =E37 | F60: =F37 | G60: =G37 | H60: =H37 | I60: =I37 | J60: =J37 | K60: =K37 | ... W60: =W37
B61: 0 | T61: 償還年限
B62: (Unit : Currency) | C62: 0 | D62: 1 | E62: 2 | F62: 3 | G62: 4 | H62: 5 | I62: 6 | J62: 7 | K62: 8 | L62: 9 | M62: 10 | N62: 11 | O62: 12 | P62: 13 | Q62: 14 | R62: 15 | S62: 16 | T62: 17 | U62: 18 | V62: 19 | W62: 20
B63: 發電度數(KWH) | C63: 0 | D63: =D40 | E63: =E40 | F63: =F40 | G63: =G40 | H63: =H40 | I63: =I40 | J63: =J40 | K63: =K40 | ... W63: =W40
B64: Inflow : 電費收入 | C64: - | D64: =D41 | E64: =E41 | F64: =F41 | G64: =G41 | H64: =H41 | I64: =I41 | J64: =J41 | K64: =K41 | ... W64: =W41
B65: Inflow : 政府補助 | C65: - | G65: - | H65: - | I65: - | J65: - | K65: - | L65: - | M65: - | N65: - | O65: - | P65: - | Q65: - | R65: - | S65: - | T65: - | U65: - | V65: - | W65: -
B66: Inflow : 銀行借款
B67: Outflow : 設備折舊 | D67: =$C$44/$E$16 | E67: =$C$44/$E$16 | F67: =$C$44/$E$16 | G67: =$C$44/$E$16 | H67: =$C$44/$E$16 | I67: =$C$44/$E$16 | J67: =$C$44/$E$16 | K67: =$C$44/$E$16 | ... W67: =$C$44/$E$16
B68: Outflow : 設備放置區域租金 | C68: - | D68: =D45 | E68: =E45 | F68: =F45 | G68: =G45 | H68: =H45 | I68: =I45 | J68: =J45 | K68: =K45 | ... W68: =W45
B69: Outflow : 返還借款
B70: Outflow : 利息費用 | C70: - | D70: 0 | E70: 0 | F70: 0 | G70: 0 | H70: 0 | I70: 0 | J70: 0 | K70: 0 | L70: 0 | M70: 0 | N70: 0 | O70: 0 | P70: 0 | Q70: 0 | R70: 0 | S70: 0 | T70: 0 | U70: 0 | V70: 0 | W70: 0
B71: Outflow : 維運費 | C71: - | D71: =D48 | E71: =E48 | F71: =F48 | G71: =G48 | H71: =H48 | I71: =I48 | J71: =J48 | K71: =K48 | ... W71: =W48
B72: Outflow : 保險費 | C72: - | D72: =D49 | E72: =E49 | F72: =F49 | G72: =G49 | H72: =H49 | I72: =I49 | J72: =J49 | K72: =K49 | ... W72: =W49
B73: Outflow : 模組回收費 | D73: =D50 | E73: =E50 | F73: =F50 | G73: =G50 | H73: =H50 | I73: =I50 | J73: =J50 | K73: =K50 | ... W73: =W50
B74: Outflow : 其它費用(人事薪資…等)
B75: 1%管理費
B76: 稅前淨利 | D76: =SUM(D64:D75) | E76: =SUM(E64:E75) | F76: =SUM(F64:F75) | G76: =SUM(G64:G75) | H76: =SUM(H64:H75) | I76: =SUM(I64:I75) | J76: =SUM(J64:J75) | K76: =SUM(K64:K75) | ... X76: =SUM(X64:X75)
B77: 所得稅20% | D77: =-D76*0.2 | E77: =-E76*0.2 | F77: =-F76*0.2 | G77: =-G76*0.2 | H77: =-H76*0.2 | I77: =-I76*0.2 | J77: =-J76*0.2 | K77: =-K76*0.2 | ... X77: =-X76*0.2
B78: 稅後淨利 | D78: =SUM(D76:D77) | E78: =SUM(E76:E77) | F78: =SUM(F76:F77) | G78: =SUM(G76:G77) | H78: =SUM(H76:H77) | I78: =SUM(I76:I77) | J78: =SUM(J76:J77) | K78: =SUM(K76:K77) | ... X78: =SUM(X76:X77)
B79: 累計現金流
B80: 回收年限評估

Sheet 表 62_滾算紀錄6
B1: 電站基本資料
B2: 電站名稱 | C2: 淡江大學-財務模擬案場 | D2: - | E2: -
B3: 電站壽命 | C3: 20 | D3: - | E3: -
B4: 建置量(kWp) | C4: 436.1 | D4: - | E4: - | M4: 滾算紀錄編號: 6
B5: 起始年度 | C5: 2023 | D5: 結束年度 | E5: 2042 | M5: 第5次滾算摘要
M6: 價金: 25000
B7: 綜合損益表 | M7: 專案IRR: 6.15
B8: 收入 | M8: 權益法IRR: 18.54
B9: 收支項目 | C9: 相關參數 | D9: 參數數值 | E9: 年限 | M9: 利潤率: 20.00%
B10: 電費收入 | C10: 年度AC併網總發電量 | D10: 547002 | E10: 20 | M10: 第5次滾算，減少 1000 元 - 現金模式，每次減少 1000 元
C11: 首年衰退率 | D11: 0.01
C12: 次年衰退率 | D12: 0.004
C13: 躉售費率(FIT) | D13: 3.7152
B14: 支出
B15: 收支項目 | C15: 相關參數 | D15: 參數數值 | E15: 攤提年限
B16: 設備費用(價金) | C16: 每kWp設備成本 | D16: 25000 | E16: 20
C17: 信邦利潤率 | D17: 0.2
C18: 開發費 | D18: 2000
B19: 租金費用 | C19: 租金計算方式 (1=固定攤提/2=電費抽成) | D19: 1 | E19: 0
C20: 【方式1參數】租金總額 | D20: 5804025 | E20: 20
C21: 【方式2參數】抽成比率 | D21: 0 | E21: 0
B22: 運維費用 | C22: 每kw運維成本 | D22: 400 | E22: 20
B23: 保險費用 | C23: 占整體設備費用比例 | D23: 0.003 | E23: 20
B24: 模組回收費用 | C24: 每kw模組回收成本 | D24: 1000 | E24: 10
B25: 利息費用 | C25: 銀行利率 | D25: 0.025595 | E25: 0
B26: 所得稅 | C26: 所得稅率 | D26: 0.2 | E26: 0
B29: 現金流量表
B30: 金流項目 | C30: 相關參數 | D30: 參數數值
B31: 貸款成數 | C31: 占總設備費用比例 | D31: 0.8
B32: 貸款還款 | C32: 攤還期數 | D32: 15
B33: 現金股利 | C33: 股利比率 | D33: 0.9
B34: 年底減資 | C34: 攤還期數 | D34: 4
C37: 年份 | D37: 2023 | E37: 2024 | F37: 2025 | G37: 2026 | H37: 2027 | I37: 2028 | J37: 2029 | K37: 2030 | L37: 2031 | M37: 2032 | N37: 2033 | O37: 2034 | P37: 2035 | Q37: 2036 | R37: 2037 | S37: 2038 | T37: 2039 | U37: 2040 | V37: 2041 | W37: 2042
B38: 0
B39: (Unit : Currency) | C39: 0 | D39: 1 | E39: 2 | F39: 3 | G39: 4 | H39: 5 | I39: 6 | J39: 7 | K39: 8 | L39: 9 | M39: 10 | N39: 11 | O39: 12 | P39: 13 | Q39: 14 | R39: 15 | S39: 16 | T39: 17 | U39: 18 | V39: 19 | W39: 20
B40: 發電度數(KWH) | C40: 0 | D40: =$D$10*0.99 | E40: =$D$10*0.986 | F40: =$D$10*0.982 | G40: =$D$10*0.978 | H40: =$D$10*0.974 | I40: =$D$10*0.97 | J40: =$D$10*0.966 | K40: =$D$10*0.962 | L40: =$D$10*0.958 | M40: =$D$10*0.954 | N40: =$D$10*0.95 | O40: =$D$10*0.946 | P40: =$D$10*0.942 | Q40: =$D$10*0.938 | R40: =$D$10*0.934 | S40: =$D$10*0.93 | T40: =$D$10*0.926 | U40: =$D$10*0.922 | V40: =$D$10*0.918 | W40: =$D$10*0.914
B41: Inflow : 電費收入 | C41: - | D41: =D40*$D$13 | E41: =E40*$D$13 | F41: =F40*$D$13 | G41: =G40*$D$13 | H41: =H40*$D$13 | I41: =I40*$D$13 | J41: =J40*$D$13 | K41: =K40*$D$13 | ... W41: =W40*$D$13
B42: Inflow : 政府補助 | C42: - | G42: - | H42: - | I42: - | J42: - | K42: - | L42: - | M42: - | N42: - | O42: - | P42: - | Q42: - | R42: - | S42: - | T42: - | U42: - | V42: - | W42: -
B43: Inflow : 銀行借款
B44: Outflow : 設備費用 | C44: =-(D16/(1-D17)+D18)*C4
B45: Outflow : 設備放置區域租金 | C45: - | D45: 0 | E45: -290201.25 | F45: -290201.25 | G45: -290201.25 | H45: -290201.25 | I45: -290201.25 | J45: -290201.25 | K45: -290201.25 | L45: -290201.25 | M45: -290201.25 | N45: -290201.25 | O45: -290201.25 | P45: -290201.25 | Q45: -290201.25 | R45: -290201.25 | S45: -290201.25 | T45: -290201.25 | U45: -290201.25 | V45: -290201.25 | W45: -290201.25
B46: Outflow : 返還借款
B47: Outflow : 利息費用 | C47: -
B48: Outflow : 維運費 | C48: - | D48: -174440 | E48: -174440 | F48: -174440 | G48: -174440 | H48: -174440 | I48: -174440 | J48: -174440 | K48: -174440 | L48: -174440 | M48: -174440 | N48: -174440 | O48: -174440 | P48: -174440 | Q48: -174440 | R48: -174440 | S48: -174440 | T48: -174440 | U48: -174440 | V48: -174440 | W48: -174440
B49: Outflow : 保險費 | C49: - | D49: -32707.5 | E49: -32707.5 | F49: -32707.5 | G49: -32707.5 | H49: -32707.5 | I49: -32707.5 | J49: -32707.5 | K49: -32707.5 | L49: -32707.5 | M49: -32707.5 | N49: -32707.5 | O49: -32707.5 | P49: -32707.5 | Q49: -32707.5 | R49: -32707.5 | S49: -32707.5 | T49: -32707.5 | U49: -32707.5 | V49: -32707.5 | W49: -32707.5
B50: Outflow : 模組回收費 | D50: -43610 | E50: -43610 | F50: -43610 | G50: -43610 | H50: -43610 | I50: -43610 | J50: -43610 | K50: -43610 | L50: -43610 | M50: -43610 | N50: 0 | O50: 0 | P50: 0 | Q50: 0 | R50: 0 | S50: 0 | T50: 0 | U50: 0 | V50: 0 | W50: 0
B51: Outflow : 其它費用(人事薪資…等)
B52: 1%管理費
B53: 績效獎金
B54: 所得稅20% | D54: =D77 | E54: =E77 | F54: =F77 | G54: =G77 | H54: =H77 | I54: =I77 | J54: =J77 | K54: =K77 | ... W54: =W77
B55: 現金流 | C55: =C44 | D55: =SUM(D41:D54) | E55: =SUM(E41:E54) | F55: =SUM(F41:F54) | G55: =SUM(G41:G54) | H55: =SUM(H41:H54) | I55: =SUM(I41:I54) | J55: =SUM(J41:J54) | K55: =SUM(K41:K54) | ... W55: =SUM(W41:W54)
B56: 累計現金流 | D56: =C55+D55 | E56: =D56+E55 | F56: =E56+F55 | G56: =F56+G55 | H56: =G56+H55 | I56: =H56+I55 | J56: =I56+J55 | K56: =J56+K55 | L56: =K56+L55 | ... X56: =W56+X55
B57: 回收年限評估 | D57: =IF((D56)>0,"回收","未回收") | E57: =IF((E56)>0,"回收","未回收") | F57: =IF((F56)>0,"回收","未回收") | G57: =IF((G56)>0,"回收","未回收") | H57: =IF((H56)>0,"回收","未回收") | I57: =IF((I56)>0,"回收","未回收") | J57: =IF((J56)>0,"回收","未回收") | K57: =IF((K56)>0,"回收","未回收") | ... X57: =IF((X56)>0,"回收","未回收")
B58: 專案法IRR | C58: =IRR(C55:W55)
C60: 年份 | D60: =D37 | E60: =E37 | F60: =F37 | G60: =G37 | H60: =H37 | I60: =I37 | J60: =J37 | K60: =K37 | ... W60: =W37
B61: 0 | T61: 償還年限
B62: (Unit : Currency) | C62: 0 | D62: 1 | E62: 2 | F62: 3 | G62: 4 | H62: 5 | I62: 6 | J62: 7 | K62: 8 | L62: 9 | M62: 10 | N62: 11 | O62: 12 | P62: 13 | Q62: 14 | R62: 15 | S62: 16 | T62: 17 | U62: 18 | V62: 19 | W62: 20
B63: 發電度數(KWH) | C63: 0 | D63: =D40 | E63: =E40 | F63: =F40 | G63: =G40 | H63: =H40 | I63: =I40 | J63: =J40 | K63: =K40 | ... W63: =W40
B64: Inflow : 電費收入 | C64: - | D64: =D41 | E64: =E41 | F64: =F41 | G64: =G41 | H64: =H41 | I64: =I41 | J64: =J41 | K64: =K41 | ... W64: =W41
B65: Inflow : 政府補助 | C65: - | G65: - | H65: - | I65: - | J65: - | K65: - | L65: - | M65: - | N65: - | O65: - | P65: - | Q65: - | R65: - | S65: - | T65: - | U65: - | V65: - | W65: -
B66: Inflow : 銀行借款
B67: Outflow : 設備折舊 | D67: =$C$44/$E$16 | E67: =$C$44/$E$16 | F67: =$C$44/$E$16 | G67: =$C$44/$E$16 | H67: =$C$44/$E$16 | I67: =$C$44/$E$16 | J67: =$C$44/$E$16 | K67: =$C$44/$E$16 | ... W67: =$C$44/$E$16
B68: Outflow : 設備放置區域租金 | C68: - | D68: =D45 | E68: =E45 | F68: =F45 | G68: =G45 | H68: =H45 | I68: =I45 | J68: =J45 | K68: =K45 | ... W68: =W45
B69: Outflow : 返還借款
B70: Outflow : 利息費用 | C70: - | D70: 0 | E70: 0 | F70: 0 | G70: 0 | H70: 0 | I70: 0 | J70: 0 | K70: 0 | L70: 0 | M70: 0 | N70: 0 | O70: 0 | P70: 0 | Q70: 0 | R70: 0 | S70: 0 | T70: 0 | U70: 0 | V70: 0 | W70: 0
B71: Outflow : 維運費 | C71: - | D71: =D48 | E71: =E48 | F71: =F48 | G71: =G48 | H71: =H48 | I71: =I48 | J71: =J48 | K71: =K48 | ... W71: =W48
B72: Outflow : 保險費 | C72: - | D72: =D49 | E72: =E49 | F72: =F49 | G72: =G49 | H72: =H49 | I72: =I49 | J72: =J49 | K72: =K49 | ... W72: =W49
B73: Outflow : 模組回收費 | D73: =D50 | E73: =E50 | F73: =F50 | G73: =G50 | H73: =H50 | I73: =I50 | J73: =J50 | K73: =K50 | ... W73: =W50
B74: Outflow : 其它費用(人事薪資…等)
B75: 1%管理費
B76: 稅前淨利 | D76: =SUM(D64:D75) | E76: =SUM(E64:E75) | F76: =SUM(F64:F75) | G76: =SUM(G64:G75) | H76: =SUM(H64:H75) | I76: =SUM(I64:I75) | J76: =SUM(J64:J75) | K76: =SUM(K64:K75) | ... X76: =SUM(X64:X75)
B77: 所得稅20% | D77: =-D76*0.2 | E77: =-E76*0.2 | F77: =-F76*0.2 | G77: =-G76*0.2 | H77: =-H76*0.2 | I77: =-I76*0.2 | J77: =-J76*0.2 | K77: =-K76*0.2 | ... X77: =-X76*0.2
B78: 稅後淨利 | D78: =SUM(D76:D77) | E78: =SUM(E76:E77) | F78: =SUM(F76:F77) | G78: =SUM(G76:G77) | H78: =SUM(H76:H77) | I78: =SUM(I76:I77) | J78: =SUM(J76:J77) | K78: =SUM(K76:K77) | ... X78: =SUM(X76:X77)
B79: 累計現金流
B80: 回收年限評估
