Workbook
Name ret_tlt0: #REF!
Name ss: #REF!
Name Table0: 發電!$U$7:$AE$23
Name ret_tlt0: #REF!
Name ss: #REF!
Name ret_tlt0: #REF!
Name ss: #REF!
Name ret_tlt0: #REF!
Name ss: #REF!
Name ret_tlt0: #REF!
Name ss: #REF!
Name ret_tlt0: #REF!
Name ss: #REF!
Name ret_tlt0: #REF!
Name ss: #REF!
Name ret_tlt0: #REF!
Name ss: #REF!
Name ret_tlt0: #REF!
Name ss: #REF!
Name ret_tlt0: #REF!
Name ss: #REF!
Name ret_tlt0: #REF!
Name ret_tlt0: #REF!
Name ss: #REF!
Name ret_tlt0: #REF!
Name ret_tlt0: #REF!
Name ret_tlt0: #REF!
Name ss: #REF!
Name ret_tlt0: #REF!
Name ss: #REF!
Name ret_tlt0: #REF!

Sheet 等效
A1: Parameters for Tilted Solar Panels:
A3: =Q5 | B3: Jan | C3: Feb | D3: Mar | E3: Apr | F3: May | G3: Jun | H3: Jul | I3: Aug | J3: Sep | K3: Oct | L3: Nov | M3: Dec | N3: Annual | Q3: 請貼這→
A4: =R5 | N4: Average | Q4: LAT | R4: LON | S4: PARAMETER | T4: JAN | U4: FEB | V4: MAR | W4: APR | X4: MAY | Y4: JUN | Z4: JUL | AA4: AUG | AB4: SEP | AC4: OCT | AD4: NOV | AE4: DEC | AF4: ANN
A5: =SUBSTITUTE(S5,P5,"") | B5: =T5 | C5: =U5 | D5: =V5 | E5: =W5 | F5: =X5 | G5: =Y5 | H5: =Z5 | I5: =AA5 | ... N5: =AF5 | P5: ALLSKY_SFC_ | S5: ALLSKY_SFC_SW_DNI
A6: =SUBSTITUTE(S6,P6,"") | B6: =T6 | C6: =U6 | D6: =V6 | E6: =W6 | F6: =X6 | G6: =Y6 | H6: =Z6 | I6: =AA6 | ... N6: =AF6 | P6: ALLSKY_SFC_ | S6: ALLSKY_SFC_SW_DWN
A7: =SUBSTITUTE(S7,P7,"") | B7: =T7 | C7: =U7 | D7: =V7 | E7: =W7 | F7: =X7 | G7: =Y7 | H7: =Z7 | I7: =AA7 | ... N7: =AF7 | P7: ALLSKY_SFC_ | S7: ALLSKY_SFC_SW_DIFF
A8: =SUBSTITUTE(S8,P8,"") | B8: =T8 | C8: =U8 | D8: =V8 | E8: =W8 | F8: =X8 | G8: =Y8 | H8: =Z8 | I8: =AA8 | ... N8: =AF8 | P8: SI_EF_TILTED_SURFACE_ | S8: SI_EF_TILTED_SURFACE_HORIZONTAL
A9: =SUBSTITUTE(S9,P9,"") | B9: =T9 | C9: =U9 | D9: =V9 | E9: =W9 | F9: =X9 | G9: =Y9 | H9: =Z9 | I9: =AA9 | ... N9: =AF9 | P9: SI_EF_TILTED_SURFACE_ | S9: SI_EF_TILTED_SURFACE_LAT_MINUS15
A10: =SUBSTITUTE(S10,P10,"") | B10: =T10 | C10: =U10 | D10: =V10 | E10: =W10 | F10: =X10 | G10: =Y10 | H10: =Z10 | I10: =AA10 | ... N10: =AF10 | P10: SI_EF_TILTED_SURFACE_ | S10: SI_EF_TILTED_SURFACE_LATITUDE
A11: =SUBSTITUTE(S11,P11,"") | B11: =T11 | C11: =U11 | D11: =V11 | E11: =W11 | F11: =X11 | G11: =Y11 | H11: =Z11 | I11: =AA11 | ... N11: =AF11 | P11: SI_EF_TILTED_SURFACE_ | S11: SI_EF_TILTED_SURFACE_LAT_PLUS15
A12: =SUBSTITUTE(S12,P12,"") | B12: =T12 | C12: =U12 | D12: =V12 | E12: =W12 | F12: =X12 | G12: =Y12 | H12: =Z12 | I12: =AA12 | ... N12: =AF12 | P12: SI_EF_TILTED_SURFACE_ | S12: SI_EF_TILTED_SURFACE_VERTICAL
A13: =SUBSTITUTE(S13,P13,"") | B13: =T13 | C13: =U13 | D13: =V13 | E13: =W13 | F13: =X13 | G13: =Y13 | H13: =Z13 | I13: =AA13 | ... N13: =AF13 | P13: SI_EF_TILTED_SURFACE_ | S13: SI_EF_TILTED_SURFACE_OPTIMAL
A14: =SUBSTITUTE(S14,P14,"") | B14: =T14 | C14: =U14 | D14: =V14 | E14: =W14 | F14: =X14 | G14: =Y14 | H14: =Z14 | I14: =AA14 | ... N14: =AF14 | P14: SI_EF_TILTED_SURFACE_ | S14: SI_EF_TILTED_SURFACE_OPTIMAL_ANG
A15: =SUBSTITUTE(S15,P15,"") | B15: =T15 | C15: =U15 | D15: =V15 | E15: =W15 | F15: =X15 | G15: =Y15 | H15: =Z15 | I15: =AA15 | ... N15: =AF15 | P15: SI_EF_TILTED_SURFACE_ | S15: SI_EF_TILTED_SURFACE_OPTIMAL_ANG_ORT
A16: NOTE: Diffuse radiation, direct normal radiation and tilted surface radiation are not calculated when the clearness index (K) is below 0.3 or above 0.8.
P17: Location: Latitude | S17: Parameter(s):
A18: https://eosweb.larc.nasa.gov/cgi-bin/sse/grid.cgi?email=skip@larc.nasa.gov | P18: Longitude 120.8254 | S18: ALLSKY_SFC_SW_DNI | T18: 全天面短波向下直接法向輻照度 (kW-hr/m^2/day)
P19: Location: Latitude 24.5648 Longitude | S19: ALLSKY_SFC_SW_DWN | T19: 全天面短波下行輻照度 (kW-hr/m^2/day)
A20: https://power.larc.nasa.gov/data-access-viewer/ | E20: NEW | P20: =SUBSTITUTE(S3,P17,"") | S20: ALLSKY_SFC_SW_DIFF | T20: 全天表面短波漫射輻照度 (kW-hr/m^2/day)
S21: SI_EF_TILTED_SURFACE_HORIZONTAL | T21: 赤道面向水平面的太陽輻照度（kW-hr/m^2/day）
S22: SI_EF_TILTED_SURFACE_LAT_MINUS15 | T22: 赤道面向緯度減 15 傾斜的太陽輻照度 (kW-hr/m^2/day)
S23: SI_EF_TILTED_SURFACE_LATITUDE | T23: 赤道面向緯度傾斜的太陽輻照度（kW-hr/m^2/day）
S24: SI_EF_TILTED_SURFACE_LAT_PLUS15 | T24: 面向赤道緯度加上 15 傾斜度的太陽輻照度（kW-hr/m^2/day）
S25: SI_EF_TILTED_SURFACE_VERTICAL | T25: 面向赤道垂直表面的太陽輻照度（kW-hr/m^2/day）
S26: SI_EF_TILTED_SURFACE_OPTIMAL | T26: 太陽輻照度最佳 (kW-hr/m^2/day)
S27: SI_EF_TILTED_SURFACE_OPTIMAL_ANG | T27: 太陽輻照度最佳角度（度）
S28: SI_EF_TILTED_SURFACE_OPTIMAL_ANG_ORT | T28: 太陽輻照度傾斜表面方向（N/S 方向）

Sheet 費率
C2: 苗栗為分界
B3: 屋 | C3: 北 | D3: 111年 | E3: 上 | F3: 下 | H3: 躉售費率 | L3: 本案適用級距 | M3: 本案適用費率欄位(行) | P3: 本案適用級距欄位(列)
B4: 頂 | D4: 1-<20 kW | E4: =E10*1.15 | F4: =F10*1.15 | H4: =INDEX(D3:F6,P4,M4) | L4: =IF(#REF!="屋頂",IF(#REF!<20,費率!D4,IF(#REF!<100,費率!D5,費率!D6)),0) | M4: =MATCH(#REF!,費率!D3:F3,0) | P4: =MATCH(L4,D3:D6,0)
B5: 型 | D5: 20-<100 kW | E5: =E11*1.15 | F5: =F11*1.15 | J5: 合併計算
D6: 100-<500kW | E6: =E12*1.15 | F6: =F12*1.15 | J6: =IF(#REF!="屋頂",IF(#REF!="否",IF(L11=7,H10,IF(L11=1,H4)),IF(L11=7,H20,IF(L11=1,H17))),IF(L11=7,H27,IF(L11=1,H24)))
L7: 本案適用級距 | M7: 本案適用費率欄位(行) | P7: 本案適用級距欄位(列)
C8: 苗栗為分界 | J8: 實際費率看回收頁 | L8: =IF(#REF!="屋頂",IF(#REF!<20,費率!D10,IF(#REF!<100,費率!D11,費率!D12)),0) | M8: =MATCH(#REF!,費率!D9:F9,0) | P8: =MATCH(L8,D9:D12,0)
B9: 屋 | C9: 南 | D9: 111年 | E9: 上 | F9: 下 | H9: 躉售費率
B10: 頂 | D10: 1-<20 kW | E10: 5.8952 | F10: 5.7848 | H10: =INDEX(D9:F12,P8,M8) | L10: 選用費率
B11: 型 | D11: 20-<100 kW | E11: 4.5549 | F11: 4.4538 | L11: =MATCH(#REF!,費率!C3:C19,0)
D12: 100-<500kW | E12: 4.097 | F12: 3.9666
J13: 無合併計算
J14: =IF(L11=7,H10,IF(L11=1,H4))
C15: 苗栗為分界
B16: 屋 | C16: 北 | D16: 111年 | E16: 上 | F16: 下 | H16: 躉售費率 | L16: 本案適用級距 | M16: 本案適用費率欄位(行) | P16: 本案適用級距欄位(列)
B17: 頂 | D17: 500 kW↑ | E17: =E19*1.15 | F17: =F19*1.15 | H17: =INDEX(D16:F17,P17,M17) | L17: =IF(#REF!="屋頂",IF(#REF!="是",D17,0),0) | M17: =MATCH(#REF!,費率!D16:F16,0) | P17: =MATCH(L17,D16:D17,0)
B18: 型 | C18: 南 | D18: 111年 | E18: 上 | F18: 下 | L18: 本案適用級距 | M18: 本案適用費率欄位(行) | P18: 本案適用級距欄位(列)
D19: 500 kW↑ | E19: 4.1122 | F19: 3.9727 | H19: 躉售費率 | L19: =IF(#REF!="屋頂",IF(#REF!="是",D19,0),0) | M19: =MATCH(#REF!,費率!D18:F18,0) | P19: =MATCH(L19,D18:D19,0)
D20: 合併 | H20: =INDEX(D18:F19,P19,M19)
C22: 苗栗為分界
B23: 地 | C23: 北 | D23: 111年 | E23: 上 | F23: 下 | H23: 躉售費率 | L23: 本案適用級距 | M23: 本案適用費率欄位(行) | P23: 本案適用級距欄位(列)
B24: 面 | D24: 1 kW↑ | E24: =E26*1.15 | F24: =F26*1.15 | H24: =INDEX(D23:F24,P24,M24) | L24: =IF(#REF!="屋頂",0,D24) | M24: =MATCH(#REF!,費率!D23:F23,0) | P24: =MATCH(L24,D23:D24,0)
B25: 型 | C25: 南 | D25: 111年 | E25: 上 | F25: 下 | L25: 本案適用級距 | M25: 本案適用費率欄位(行) | P25: 本案適用級距欄位(列)
D26: 1 kW↑ | E26: 4.0031 | F26: 3.868 | H26: 躉售費率 | L26: =IF(#REF!="屋頂",0,D26) | M26: =MATCH(#REF!,費率!D25:F25,0) | P26: =MATCH(L26,D25:D26,0)
H27: =INDEX(D25:F26,P26,M26)
C31: 高效能模組(元/度)
C32: 屋頂型 | D32: 1-<20 kW | E32: 0.3471
D33: 20-<100 kW | E33: 0.2672
D34: 100-<500kW | E34: 0.238
D35: 500 kW↑ | E35: 0.2384
C37: 地面型 | D37: 1 kW↑ | E37: 0.2321

Sheet 發電
C2: 安裝總容量 | D2: =#REF! | E2: kW
C3: 設計傾角 | D3: SW_DWN | E3: 度
U4: 說明 | V4: 水平面總輻射量 | W4: 水平面散射輻射量 | X4: 環境溫度 | Y4: 入射採光面上 的總輻射量 | Z4: 陣列輸出的 有效能量 | AA4: 併網電量 | AB4: 系統效率PR值 | AC4: 等效日照 | AD4: 有效日照
C5: 1 | D5: 2 | E5: 3 | F5: 4 | G5: 5 | H5: 6 | I5: 7 | J5: 8 | K5: 9 | L5: 10 | M5: 11 | N5: 12 | O5: 13 | P5: 14
C6: 系統PR值 | D6: =AB22
C8: 發電量評估 | D8: 一月 | E8: 二月 | F8: 三月 | G8: 四月 | H8: 五月 | I8: 六月 | J8: 七月 | K8: 八月 | L8: 九月 | M8: 十月 | N8: 十一月 | O8: 十二月 | P8: 每年 總發電量 (度/每年) | Q8: 每年 每KW總發電量 (度/KW/每年) | S8: 有效日照 | V8: GlobHor | W8: DiffHor | X8: T_Amb | Y8: GlobInc | Z8: EArray | AA8: E_Grid | AB8: PR | AC8: Yr | AD8: Yf
C9: AC 併網總發電量 (度/月) | S9: =Q9/365 | V9: kWh/m² | W9: kWh/m² | X9: °C | Y9: kWh/m² | Z9: kWh | AA9: kWh | AB9: ratio | AC9: kWh/m²/day | AD9: kWh/kWp/day
U10: 1月
U11: 2月
L12: 衰退率 | M12: 首年 | N12: 0.01 | U12: 3月
C13: 手動計算值 | M13: 第2-25年 | N13: 0.004 | U13: 4月
U14: 5月
C15: 模組衰減率(年) | D15: 0.004 | L15: 衰退率 | M15: 年 | N15: 遞減% | O15: 模組瓦數(W) | U15: 6月
C16: 發電量計算 | D16: 年發電量(KWH) | F16: 年躉電收入(NTD) | H16: 累計躉電收入(NTD) | L16: 0 | M16: 0 | N16: 1 | O16: 550 | U16: 7月
C17: 第1年 | J17: =N17 | L17: =$N$12 | M17: 1 | N17: =N16-L17 | O17: =$O$16*N17 | U17: 8月
C18: 第2年 | J18: =N18 | L18: =$N$13 | M18: 2 | N18: =N17-L18 | O18: =$O$16*N18 | U18: 9月
C19: 第3年 | J19: =N19 | L19: =$N$13 | M19: 3 | N19: =N18-L19 | O19: =$O$16*N19 | U19: 10月
C20: 第4年 | J20: =N20 | L20: =$N$13 | M20: 4 | N20: =N19-L20 | O20: =$O$16*N20 | U20: 11月
C21: 第5年 | J21: =N21 | L21: =$N$13 | M21: 5 | N21: =N20-L21 | O21: =$O$16*N21 | U21: 12月
C22: 第6年 | J22: =N22 | L22: =$N$13 | M22: 6 | N22: =N21-L22 | O22: =$O$16*N22 | U22: 年
C23: 第7年 | J23: =N23 | L23: =$N$13 | M23: 7 | N23: =N22-L23 | O23: =$O$16*N23
C24: 第8年 | J24: =N24 | L24: =$N$13 | M24: 8 | N24: =N23-L24 | O24: =$O$16*N24
C25: 第9年 | J25: =N25 | L25: =$N$13 | M25: 9 | N25: =N24-L25 | O25: =$O$16*N25
C26: 第10年 | J26: =N26 | L26: =$N$13 | M26: 10 | N26: =N25-L26 | O26: =$O$16*N26
C27: 第11年 | J27: =N27 | L27: =$N$13 | M27: 11 | N27: =N26-L27 | O27: =$O$16*N27
C28: 第12年 | J28: =N28 | L28: =$N$13 | M28: 12 | N28: =N27-L28 | O28: =$O$16*N28
C29: 第13年 | J29: =N29 | L29: =$N$13 | M29: 13 | N29: =N28-L29 | O29: =$O$16*N29
C30: 第14年 | J30: =N30 | L30: =$N$13 | M30: 14 | N30: =N29-L30 | O30: =$O$16*N30
C31: 第15年 | J31: =N31 | L31: =$N$13 | M31: 15 | N31: =N30-L31 | O31: =$O$16*N31
C32: 第16年 | J32: =N32 | L32: =$N$13 | M32: 16 | N32: =N31-L32 | O32: =$O$16*N32
C33: 第17年 | J33: =N33 | L33: =$N$13 | M33: 17 | N33: =N32-L33 | O33: =$O$16*N33
C34: 第18年 | J34: =N34 | L34: =$N$13 | M34: 18 | N34: =N33-L34 | O34: =$O$16*N34
... C36: 第20年 | J36: =N36 | L36: =$N$13 | M36: 20 | N36: =N35-L36 | O36: =$O$16*N36
L37: =$N$13 | M37: 21 | N37: =N36-L37 | O37: =$O$16*N37
C38: 平均值 | L38: =$N$13 | M38: 22 | N38: =N37-L38 | O38: =$O$16*N38
L39: =$N$13 | M39: 23 | N39: =N38-L39 | O39: =$O$16*N39
L40: =$N$13 | M40: 24 | N40: =N39-L40 | O40: =$O$16*N40
L41: =$N$13 | M41: 25 | N41: =N40-L41 | O41: =$O$16*N41

Sheet 成本
B2: =#REF! | D2: =#REF! | E2: kW系統設置成本分析 | F2: 工程利潤 (未稅售價-未稅成本) /未稅售價 | H2: =($M$175-$O$175)/$M$175 | J2: 實際利潤 (未稅售價-未稅成本) /未稅售價 | L2: =($M$175-$P$175)/$M$175
B4: 編號 | C4: 名 稱 | F4: 業務報價用 (單價NTD) | G4: 業務 倍率 | H4: PM buffer (單價NTD) | I4: PM 倍率 | J4: 實際單價 (NTD) | K4: 數量 | L4: 單位 | M4: 業務報價 (NTD) | N4: PM buffer (NTD) | O4: 預估成本 (NTD) | P4: 實際報價 | Q4: 備 註
B5: 模組及逆變器
B6: 1 | C6: DCPV | F6: =H6*G6 | G6: 1.2 | H6: =I6*J6 | I6: 1.05 | J6: =模組!E3*模組!D3*#REF! | K6: =#REF! | L6: 片 | M6: =F6*K6 | N6: =H6*K6 | O6: =J6*K6
B7: 2 | C7: Micro Inverter | F7: =H7*G7 | G7: 1.7 | H7: =I7*J7 | I7: 1.05 | J7: =微逆變!E3*#REF! | K7: 0 | L7: 台 | M7: =F7*K7 | N7: =H7*K7 | O7: =J7*K7 | T7: 含inverter加工及配件
B8: 3 | C8: String Iinverter | F8: =H8*G8 | G8: 1.2 | H8: =I8*J8 | I8: 1.05 | J8: =逆變!F8 | K8: 0 | L8: 式 | M8: =F8*K8 | N8: =H8*K8 | O8: =J8*K8 | T8: x 牌 x 台 x KW; x 牌 x 台 x KW
B9: 4 | C9: 獨立Iinverter | F9: =H9*G9 | G9: 1.05 | H9: =I9*J9 | I9: 1.05 | J9: ='(獨)逆變'!F3 | K9: 0 | L9: 台 | M9: =F9*K9 | N9: =H9*K9 | O9: =J9*K9 | T9: x 牌 x 台 x KW; x 牌 x 台 x KW
L10: 小計 | M10: =SUM(M6:M9) | N10: =SUM(N6:N9) | O10: =SUM(O6:O9)
L11: 平均1KW(未稅) | M11: =M10/$D$2 | N11: =N10/$D$2 | O11: =O10/$D$2
B12: 文件&行政
B13: 1 | C13: 市電躉售併聯申請 | F13: =H13*G13 | G13: 1.2 | H13: =I13*J13 | I13: 1.05 | J13: =IF(D2<100,行政!D20,行政!D3)*0+行政!D3 | L13: 式 | M13: =F13*K13 | N13: =H13*K13 | O13: =J13*K13 | Q13: 單期500~2MW $86000/式 | T13: 工程圖說需有甲級蓋章
B14: 2 | C14: 結構技師簽證 | F14: =H14*G14 | G14: 1.2 | H14: =I14*J14 | I14: 1.05 | J14: =行政!D7*0+D2*80 | L14: 式 | M14: =F14*K14 | N14: =H14*K14 | O14: =J14*K14 | Q14: 80/kW | T14: 含結構計算及完竣表
B15: 3 | C15: 電機技師簽證費(100KW以上需要) | F15: =H15*G15 | G15: 1.2 | H15: =I15*J15 | I15: 1.05 | J15: =IF(D2<500,行政!D54,行政!D54+IF((D2-500)<500,行政!D54,IF((D2-500)<=1000,行政!D56,IF((D2-500)<=1500,行政!D57,IF((D2-500)<=2000,行政!D58)))))*0+行政!D11 | L15: 式 | M15: =F15*K15 | N15: =H15*K15 | O15: =J15*K15
B16: 4 | C16: 電機技師簽證費(APS簽證) | F16: =H16*G16 | G16: 1.05 | H16: =I16*J16 | I16: 1.05 | J16: =行政!D55 | L16: 式 | M16: =F16*K16 | N16: =H16*K16 | O16: =J16*K16 | T16: 100kW↓
B17: 5 | C17: 太陽光電乙級技術士簽證 | F17: =H17*G17 | G17: 1.2 | H17: =I17*J17 | I17: 1.05 | J17: =行政!D65 | L17: 式 | M17: =F17*K17 | N17: =H17*K17 | O17: =J17*K17 | T17: 100kW↓
F18: =H18*G18 | G18: 1.05 | H18: =I18*J18 | I18: 1.05 | L18: 式 | M18: =F18*K18 | N18: =H18*K18 | O18: =J18*K18
L19: 小計 | M19: =SUM(M13:M17) | N19: =SUM(N13:N17) | O19: =SUM(O13:O18)
L20: 平均1KW(未稅) | M20: =M19/$D$2 | N20: =N19/$D$2 | O20: =O19/$D$2
B21: 設計監造
B22: 1 | C22: 系統設計監造及設計費 | F22: =H22*G22 | G22: 1.05 | H22: =I22*J22 | I22: 1.05 | J22: 50000 | K22: 0 | L22: 式 | M22: =F22*K22 | N22: =H22*K22 | O22: 0 | T22: sinbon監造, sinbon設計電力系統(結構圖繪製,電力圖繪製)
B23: 2 | C23: 開發費 | F23: =H23*G23 | G23: 1 | H23: =I23*J23 | I23: 1 | J23: 3000 | K23: 0 | L23: KW | M23: =F23*K23 | N23: =H23*K23 | O23: =J23*K23
L24: 小計 | M24: =SUM(M22:M23) | N24: =SUM(N22:N23) | O24: =SUM(O22:O23)
L25: 平均1KW(未稅) | M25: =M24/$D$2 | N25: =N24/$D$2 | O25: =O24/$D$2
B26: 鋼料結構工程
B27: 1 | C27: 材料費用: H型鋼 | F27: =H27*G27 | G27: 1.05 | H27: =I27*J27 | I27: 1.05 | J27: =鋼構!D3*1.4*1.4*1.1 | K27: 0 | L27: KG | M27: =F27*K27 | N27: =H27*K27 | O27: =J27*K27 | P27: 1.4*1.4*1.1 | T27: (規格)
B28: 2 | C28: 材料費用: C型鋼 | F28: =H28*G28 | G28: 1.05 | H28: =I28*J28 | I28: 1.05 | J28: =鋼構!F3*1.4*1.4*1.1 | K28: 0 | L28: KG | M28: =F28*K28 | N28: =H28*K28 | O28: =J28*K28 | P28: 1.4*1.4*1.1 | T28: (規格)
B29: 3 | C29: 材料費用: 熱浸鍍鋅費用 | F29: =H29*G29 | G29: 1.05 | H29: =I29*J29 | I29: 1.05 | J29: =鋼構!H3*1.1 | K29: 0 | L29: KG | M29: =F29*K29 | N29: =H29*K29 | O29: =J29*K29 | P29: *1.1 | T29: 噴砂噴漆 $8/kg
B30: 4 | C30: 材料費用: 五金配件+人工 | F30: =H30*G30 | G30: 1.05 | H30: =I30*J30 | I30: 1.05 | J30: =鋼構!J3 | K30: 0 | L30: KG | M30: =F30*K30 | N30: =H30*K30 | O30: =J30*K30 | T30: 葉23，尚25；耐17
B31: 5 | C31: 材料費用: 水泥基礎 | F31: =H31*G31 | G31: 1.05 | H31: =I31*J31 | I31: 1.05 | J31: =鋼構!L3 | L31: 柱 | M31: =F31*K31 | N31: =H31*K31 | O31: =J31*K31 | T31: 葉老闆
B32: 6 | C32: 材料費用: 吊運費 | F32: =H32*G32 | G32: 1.05 | H32: =I32*J32 | I32: 1.05 | J32: =鋼構!N3 | K32: 0 | L32: KG | M32: =F32*K32 | N32: =H32*K32 | O32: =J32*K32
B33: 7 | C33: 材料費用: 管理費 | F33: =H33*G33 | G33: 1.05 | H33: =I33*J33 | I33: 1.05 | J33: =(O27+O28+O29+O30+O31+O32)*0.08 | K33: 1 | L33: 式 | M33: =F33*K33 | N33: =H33*K33 | O33: =J33*K33
B34: 8 | C34: 材料費用: 膨脹螺栓(與樓板結合) | F34: =H34*G34 | G34: 1.05 | H34: =I34*J34 | I34: 1.05 | J34: 0 | K34: 0 | L34: 式 | M34: =F34*K34 | N34: =H34*K34 | O34: =J34*K34
B35: 9 | C35: 材料費用: 白鐵花紋板 | F35: =H35*G35 | G35: 1.05 | H35: =I35*J35 | I35: 1.05 | J35: 0 | K35: 0 | L35: 式 | M35: =F35*K35 | N35: =H35*K35 | O35: =J35*K35
B36: 10 | C36: 材料費用: 維修走道 (鋼構用) | F36: =H36*G36 | G36: 1.05 | H36: =I36*J36 | I36: 1.05 | J36: =500*1.2 | K36: 0 | L36: 張 | M36: =F36*K36 | N36: =H36*K36 | O36: =J36*K36 | P36: 1.2 | T36: 400x2400mm/張 $500
B37: 11 | C37: 爬梯+護籠 | F37: =H37*G37 | G37: 1.05 | H37: =I37*J37 | I37: 1.05 | J37: =材料!E32*1.2 | K37: 0 | L37: 米 | M37: =F37*K37 | N37: =H37*K37 | O37: =J37*K37 | P37: 1.2 | T37: 中苗，金明案發包價
B38: 12 | C38: 既設烤漆_清板 0.52T(盛餘) | F38: =H38*G38 | G38: 1.05 | H38: =I38*J38 | I38: 1.05 | J38: =材料!E15*1.15*1.2 | K38: 0 | L38: 坪 | M38: =F38*K38 | N38: =H38*K38 | O38: =J38*K38 | P38: 1.2 | T38: 1坪=3.3平方公尺，含Z或口型鋼
B39: 13 | C39: 新設烤漆_清板 0.52T(盛餘) | F39: =H39*G39 | G39: 1.05 | H39: =I39*J39 | I39: 1.05 | J39: =材料!E14*1.2 | K39: 0 | L39: 坪 | M39: =F39*K39 | N39: =H39*K39 | O39: =J39*K39 | P39: 1.2 | T39: 1坪=3.3平方公尺
B40: 14 | C40: 新設烤漆_雙層鋼板 0.52T(盛餘) | F40: =H40*G40 | G40: 1.05 | H40: =I40*J40 | I40: 1.05 | J40: =材料!E16*1.2 | K40: 0 | L40: 坪 | M40: =F40*K40 | N40: =H40*K40 | O40: =J40*K40 | P40: 1.2 | T40: 業界也稱「三明治板」
B41: 15 | C41: 不鏽鋼水槽(0.4T) | F41: =H41*G41 | G41: 1.05 | H41: =I41*J41 | I41: 1.05 | J41: =材料!E37*1.2 | K41: 0 | L41: 米 | M41: =F41*K41 | N41: =H41*K41 | O41: =J41*K41 | P41: 1.2
B42: 16 | C42: 收邊 烤漆鋁鋅板 | F42: =H42*G42 | G42: 1.05 | H42: =I42*J42 | I42: 1.05 | J42: =材料!E41*1.2 | K42: 0 | L42: 米 | M42: =F42*K42 | N42: =H42*K42 | O42: =J42*K42 | P42: 1.2
L43: 小計 | M43: =(SUM(M27:M42))*0 | N43: =SUM(N27:N42) | O43: =SUM(O27:O42)
B44: 統包 | L44: 平均1KW(未稅) | M44: =M43/$D$2 | N44: =N43/$D$2 | O44: =O43/$D$2
B45: 1 | C45: 鋼構搭設工程 | F45: =H45*G45 | G45: 1.05 | H45: =I45*J45 | I45: 1.05 | J45: 12000 | K45: 0 | L45: KW | M45: =F45*K45 | N45: =H45*K45 | O45: =J45*K45 | T45: 魚鱗12k,棚架16k；宇軒10k(HC、熱浸)，掛基礎座13k
B46: 1 | C46: 地面型搭設工程 | F46: =H46*G46 | G46: 1.05 | H46: =I46*J46 | I46: 1.05 | J46: 13000 | K46: 0 | L46: KW | M46: =F46*K46 | N46: =H46*K46 | O46: =J46*K46 | R46: 除整地外 | T46: (包含地質探堪、基礎座、支架安裝含料、模組安裝)
L47: 小計 | M47: =SUM(M45:M46) | N47: =SUM(N45:N46) | O47: =SUM(O45:O46)
L48: 平均1KW(未稅) | M48: =M47/$D$2 | N48: =N47/$D$2 | O48: =O47/$D$2
B49: 鋁合金結構工程
B50: 1 | C50: 材料費用: 平貼支架 | F50: =H50*G50 | G50: 1.05 | H50: =I50*J50 | I50: 1.05 | J50: =鋁支架!E3*1.2 | K50: =K6*0 | L50: 片 | M50: =F50*K50 | N50: =H50*K50 | O50: =J50*K50 | P50: 1.2 | Q50: C間距<90→730/片 | T50: 鋁鎂鋅k27：平鋪2700/KW(映發)、2600/kW(石中劍)
B51: 2 | C51: 材料費用: 仰角支架 | F51: =H51*G51 | G51: 1.05 | H51: =I51*J51 | I51: 1.05 | J51: =鋁支架!E5 | K51: 0 | L51: 片 | M51: =F51*K51 | N51: =H51*K51 | O51: =J51*K51 | P51: 1.2 | T51: 鋁鎂鋅k27：架高3500/KW(映發)
B52: 3 | C52: 材料費用: 棚架支架 | F52: =H52*G52 | G52: 1.05 | H52: =I52*J52 | I52: 1.05 | J52: =鋁支架!P4*1.2 | K52: 0 | L52: kW | M52: =F52*K52 | N52: =H52*K52 | O52: =J52*K52 | P52: 1.2
B53: 4 | C53: 材料費用: 豐菱鎖片(防鬆脫螺絲) | F53: =H53*G53 | G53: 1.05 | H53: =I53*J53 | I53: 1.05 | J53: 10 | K53: =K6*4*0 | L53: 片 | M53: =F53*K53 | N53: =H53*K53 | O53: =J53*K53 | T53: 模組下鎖用
B54: 5 | C54: 材料費用: 膨脹螺栓(與樓板結合) | F54: =H54*G54 | G54: 1.05 | H54: =I54*J54 | I54: 1.05 | J54: 12 | K54: 0 | L54: 支 | M54: =F54*K54 | N54: =H54*K54 | O54: =J54*K54
B55: 6 | C55: 材料費用: 植筋劑 | F55: =H55*G55 | G55: 1.05 | H55: =I55*J55 | I55: 1.05 | J55: 350 | K55: 0 | L55: 支 | M55: =F55*K55 | N55: =H55*K55 | O55: =J55*K55
B56: 7 | C56: 材料費用: 其它材料 | F56: =H56*G56 | G56: 1.05 | H56: =I56*J56 | I56: 1.05 | J56: 0 | K56: 0 | L56: 式 | M56: =F56*K56 | N56: =H56*K56 | O56: =J56*K56
B57: 8 | C57: 安全母索(主幹) | F57: =H57*G57 | G57: 1.05 | H57: =I57*J57 | I57: 1.05 | J57: =200*1.2 | K57: 0 | L57: 米 | M57: =F57*K57 | N57: =H57*K57 | O57: =J57*K57 | P57: 1.2
B58: 9 | C58: 安全圍籬 | F58: =H58*G58 | G58: 1.05 | H58: =I58*J58 | I58: 1.05 | J58: =550*1.2 | K58: 0 | L58: 米 | M58: =F58*K58 | N58: =H58*K58 | O58: =J58*K58 | P58: 1.2 | T58: 詠發報價
B59: 10 | C59: 維修走道 | F59: =H59*G59 | G59: 1.05 | H59: =I59*J59 | I59: 1.05 | J59: =500*1.2 | K59: =D2*0 | L59: KW | M59: =F59*K59 | N59: =H59*K59 | O59: =J59*K59 | P59: 1.2 | T59: 主幹(500)+分路(500)為四片一組(寬40CM)=1000
B60: 11 | C60: 材料升級: 鍍膜25u↑ | F60: =H60*G60 | G60: 1.05 | H60: =I60*J60 | I60: 1.05 | J60: 100 | K60: 0 | L60: KW | M60: =F60*K60 | N60: =H60*K60 | O60: =J60*K60 | P60: 1.2 | T60: 鹽灘
B61: 12 | C61: 材料升級: 螺絲316 | F61: =H61*G61 | G61: 1.05 | H61: =I61*J61 | I61: 1.05 | J61: 100 | K61: 0 | L61: KW | M61: =F61*K61 | N61: =H61*K61 | O61: =J61*K61 | P61: 1.2 | T61: 鹽灘
B62: 13 | C62: 材料升級: 撐高座30cm | F62: =H62*G62 | G62: 1.05 | H62: =I62*J62 | I62: 1.05 | J62: 200 | K62: =D4 | L62: KW | M62: =F62*K62 | N62: =H62*K62 | O62: =J62*K62 | P62: 1.2 | T62: 鹽灘 散熱
B63: 14 | C63: 防水支架 (璟元) | F63: =H63*G63 | G63: 1.05 | H63: =I63*J63 | I63: 1.05 | J63: 4800 | K63: 0 | L63: KW | M63: =F63*K63 | N63: =H63*K63 | O63: =J63*K63 | P63: 1.2 | T63: 二代版(含短邊接水槽)
B64: 15 | C64: 防水支架 (雅唐) | F64: =H64*G64 | G64: 1 | H64: =I64*J64 | I64: 1.05 | J64: =鋁支架!J5 | K64: 0 | L64: 坪 | M64: =F64*K64 | N64: =H64*K64 | O64: =J64*K64 | P64: 1.2 | T64: 1坪=3.3平方公尺
L65: 小計 | M65: =SUM(M50:M64) | N65: =SUM(N50:N64) | O65: =SUM(O50:O64)
B66: 統包 | L66: 平均1KW(未稅) | M66: =M65/$D$2 | N66: =N65/$D$2 | O66: =O65/$D$2
B67: 1 | C67: 平鋪式組裝工程 (鎖附於鋼棚上or 鐵皮浪板) | F67: =H67*G67 | G67: 1.3 | H67: =I67*J67 | I67: 1.05 | J67: 3800 | L67: kW | M67: =F67*K67 | N67: =H67*K67 | O67: =J67*K67 | T67: 組裝支架 (2人/天); 每人2500
B68: 2 | C68: 棚架式組裝工程 | F68: =H68*G68 | G68: 1 | H68: =I68*J68 | I68: 1.05 | J68: 0 | L68: 式 | M68: =F68*K68 | N68: =H68*K68 | O68: =J68*K68
B69: 3 | C69: 魚鱗式組裝工程 | F69: =H69*G69 | G69: 1.3 | H69: =I69*J69 | I69: 1.05 | J69: 14000 | L69: kW | M69: =F69*K69 | N69: =H69*K69 | O69: =J69*K69
L70: 小計 | M70: =SUM(M67:M69) | N70: =SUM(N67:N69) | O70: =SUM(O67:O69)
L71: 平均1KW(未稅) | M71: =M70/$D$2 | N71: =N70/$D$2 | O71: =O70/$D$2
B72: 水泥基座工程
B73: 1 | F73: =H73*G73 | G73: 1 | H73: =I73*J73 | I73: 1.05 | J73: 0 | K73: 0 | L73: 式
B74: 2 | F74: =H74*G74 | G74: 1 | H74: =I74*J74 | I74: 1.05 | J74: 0 | K74: 0 | L74: 式
B75: 3 | C75: 技術指導費 | F75: =H75*G75 | G75: 1 | H75: =I75*J75 | I75: 1.05 | J75: 0 | K75: 0 | L75: 式 | M75: =F75*K75 | N75: =H75*K75 | O75: =J75*K75
L76: 小計 | M76: =SUM(M73:M75) | N76: =SUM(N73:N75) | O76: =SUM(O73:O75)
B77: 統包 | L77: 平均1KW(未稅) | M77: =M76/$D$2 | N77: =N76/$D$2 | O77: =O76/$D$2
B78: 1 | C78: 水泥基座工程 | F78: =H78*G78 | G78: 1.25 | H78: =I78*J78 | I78: 1.05 | J78: 2500 | K78: =K69 | L78: kW | M78: =F78*K78 | N78: =H78*K78 | O78: =J78*K78
L79: 小計 | M79: =SUM(M78) | N79: =SUM(N78) | O79: =SUM(O78)
L80: 平均1KW(未稅) | M80: =M79/$D$2 | N80: =N79/$D$2 | O80: =O79/$D$2
B81: 防水工程
B82: 1 | C82: =材料!B27 | F82: =H82*G82 | G82: 1.05 | H82: =I82*J82 | I82: 1.05 | J82: =材料!E27 | K82: 0 | L82: 米 | M82: =F82*K82 | N82: =H82*K82 | O82: =J82*K82
B83: 2 | C83: =材料!B28 | F83: =H83*G83 | G83: 1.05 | H83: =I83*J83 | I83: 1.05 | J83: =材料!E28 | K83: 0 | L83: 米 | M83: =F83*K83 | N83: =H83*K83 | O83: =J83*K83 | T83: 銀色(貼表面)
B84: 3 | C84: 材料費用: 一般防水膠 | F84: =H84*G84 | G84: 1.05 | H84: =I84*J84 | I84: 1.05 | J84: 200 | K84: 0 | L84: 支 | M84: =F84*K84 | N84: =H84*K84 | O84: =J84*K84 | T84: (道康寧817(600cc)) 總接縫長度1287m*4cm*2cm
B85: 4 | C85: 防水工程：舊有水泥刨除 | F85: =H85*G85 | G85: 1.05 | H85: =I85*J85 | I85: 1.05 | J85: 1000 | K85: 0 | L85: 坪 | M85: =F85*K85 | N85: =H85*K85 | O85: =J85*K85 | T85: (凡平企業社)
B86: 5 | C86: 防水工程：水泥(粉光) | F86: =H86*G86 | G86: 1.05 | H86: =I86*J86 | I86: 1.05 | J86: 2000 | K86: 0 | L86: 坪 | M86: =F86*K86 | N86: =H86*K86 | O86: =J86*K86
B87: 6 | C87: 防水工程：PU防水層 | F87: =H87*G87 | G87: 1.05 | H87: =I87*J87 | I87: 1.05 | J87: 1500 | K87: 0 | L87: 坪 | M87: =F87*K87 | N87: =H87*K87 | O87: =J87*K87 | T87: 地坪PU施作(3層)曾宅
B88: 7 | C88: 防水工程：清洗 | F88: =H88*G88 | G88: 1.05 | H88: =I88*J88 | I88: 1.05 | J88: 215 | K88: 0 | L88: 坪 | M88: =F88*K88 | N88: =H88*K88 | O88: =J88*K88 | T88: 洗地機+高壓沖洗 (鴻業國際工程)
B89: 8 | C89: 防水工程：防水漆 | F89: =H89*G89 | G89: 1.05 | H89: =I89*J89 | I89: 1.05 | J89: 840 | K89: 0 | L89: 坪 | M89: =F89*K89 | N89: =H89*K89 | O89: =J89*K89 | T89: 一底漆+二面漆(金絲猴)
B90: 9 | C90: 防水工程：隔熱漆 | F90: =H90*G90 | G90: 1.05 | H90: =I90*J90 | I90: 1.05 | J90: 745 | K90: 0 | L90: 坪 | M90: =F90*K90 | N90: =H90*K90 | O90: =J90*K90 | T90: 底漆一道(金絲猴)
B91: 10 | C91: 材料費用: 其它 | F91: =H91*G91 | G91: 1.05 | H91: =I91*J91 | I91: 1.05 | J91: 0 | K91: 0 | L91: 式 | M91: =F91*K91 | N91: =H91*K91 | O91: =J91*K91
B92: 11 | C92: 人力: 點工人力 | F92: =H92*G92 | G92: 1.05 | H92: =I92*J92 | I92: 1.05 | J92: 0 | K92: 0 | L92: 式 | M92: =F92*K92 | N92: =H92*K92 | O92: =J92*K92
B93: 12 | C93: 技術指導費 | F93: =H93*G93 | G93: 1.05 | H93: =I93*J93 | I93: 1.05 | J93: 0 | K93: 0 | L93: 式 | M93: =F93*K93 | N93: =H93*K93 | O93: =J93*K93
L94: 小計 | M94: =SUM(M82:M93) | N94: =SUM(N82:N93) | O94: =SUM(O82:O93)
B95: 統包 | L95: 平均1KW(未稅) | M95: =M94/$D$2 | N95: =N94/$D$2 | O95: =O94/$D$2
B96: 1 | C96: 模組間防水塗佈工程 | F96: =H96*G96 | G96: 1 | H96: =I96*J96 | I96: 1.05 | J96: 0 | K96: 0 | L96: 式 | M96: =F96*K96 | N96: =H96*K96 | O96: =J96*K96
B97: 2 | C97: 聯美營造防水系統總工程 | F97: =H97*G97 | G97: 1 | H97: =I97*J97 | I97: 1.05 | J97: =鋁支架!J7 | K97: 0 | L97: KW | M97: =F97*K97 | N97: =H97*K97 | O97: =J97*K97
L98: 小計 | M98: =SUM(M96:M97) | N98: =SUM(N96:N97) | O98: =SUM(O96:O97)
L99: 平均1KW(未稅) | M99: =M98/$D$2 | N99: =N98/$D$2 | O99: =O98/$D$2
B100: 系統監控工程
B101: 1 | C101: 材料費用: 監控收集器 | F101: =H101*G101 | G101: 1.05 | H101: =I101*J101 | I101: 1.05 | J101: =監控!D3 | K101: 0 | L101: 台 | M101: =F101*K101 | N101: =H101*K101 | O101: =J101*K101 | Q101: 保固3年/台 | T101: ECU-R
B102: 2 | C102: 材料費用: 數據收集盒 | F102: =H102*G102 | G102: 1.15 | H102: =I102*J102 | I102: 1.05 | J102: =監控!D7 | L102: 台 | M102: =F102*K102 | N102: =H102*K102 | O102: =J102*K102 | Q102: 保固1年/台
...

Sheet 報價
C2: =成本!D2 | D2: KW交流太陽能光電板發電系統 | L2: =C2 | M2: KW交流太陽能光電板發電系統
B3: 編號 | C3: 名稱 | D3: 數量 | E3: 單位 | F3: 小計 | G3: 備註 | K3: 編號 | L3: 名稱 | M3: 數量 | N3: 單位 | O3: 小計 | P3: 備註
B4: 1 | C4: 太陽能模組 | D4: =成本!K6 | E4: 片 | F4: =成本!M6 | K4: 1 | L4: =C4 | M4: =D4 | N4: 片 | O4: 9168000 | P4: 20年保固
B5: 2 | C5: 逆變器 | D5: 1 | E5: 式 | F5: =成本!M8 | K5: 2 | L5: =C5 | M5: =D5 | N5: 式 | O5: 2375000 | P5: 20年保固
B6: 3 | C6: 市電躉售併聯申請 | D6: 1 | E6: 式 | F6: =成本!M13 | K6: 3 | L6: =C6 | M6: =D6 | N6: 式 | O6: 168000 | P6: 台電、能源局、建管。
B7: 4 | C7: 結構技師簽證 | D7: 1 | E7: 式 | F7: =成本!M14 | K7: 4 | L7: =C7 | M7: =D7 | N7: 式 | O7: 80000
B8: 5 | C8: 電機技師簽證費 | D8: 1 | E8: 式 | F8: =成本!M15 | K8: 5 | L8: =C8 | M8: =D8 | N8: 式 | O8: =F8 | P8: 100kW以上，含系統衝擊分析。
B9: 6 | C9: 太陽光電乙級技術士簽證 | D9: 1 | E9: 式 | F9: =成本!M17 | K9: 6 | L9: =C9 | M9: =D9 | N9: 式 | O9: 8000 | P9: 100kW以下。
B10: 7 | C10: 太陽能系統監造及設計費用 | D10: 1 | E10: 式 | F10: =成本!M23 | K10: 7 | L10: =C10 | M10: =D10 | N10: 式 | O10: =F10
B11: 8 | C11: 鋼料結構工程 | D11: 1 | E11: 式 | F11: =成本!M43+成本!M47 | K11: 8 | L11: =C11 | M11: =D11 | N11: 式 | O11: =F11
B12: 9 | C12: 鋁合金結構工程 | D12: 1 | E12: 式 | F12: =成本!M65+成本!M70 | K12: 9 | L12: =C12 | M12: =D12 | N12: 式 | O12: 8816000 | P12: 含支架以及維修步道。
B13: 10 | C13: 水泥基座工程 | D13: 1 | E13: 式 | F13: =成本!M76+成本!M79 | K13: 10 | L13: =C13 | M13: =D13 | N13: 式 | O13: 1152000
B14: 11 | C14: 防水工程 | D14: 1 | E14: 式 | F14: =成本!M94+成本!M98 | K14: 11 | L14: =C14 | M14: =D14 | N14: 式 | O14: =F14
B15: 12 | C15: 系統監控工程 | D15: 1 | E15: 式 | F15: =成本!M115+成本!M118 | K15: 12 | L15: =C15 | M15: =D15 | N15: 式 | O15: 450000 | P15: 含監控箱體、錶頭、⽇照計、模組溫度計。
B16: 13 | C16: 太陽能系統配線工程 | D16: 1 | E16: 式 | F16: =成本!M137+成本!M147+成本!M152 | K16: 13 | L16: =C16 | M16: =D16 | N16: 式 | O16: 13380000 | P16: 含工帶料。 交流電纜線(太平洋/華新麗華)、太陽能專用直流線、金屬軟管、RSG管、PVC管、網路線、太陽能鋁線槽。 管線配置工程、動力管配線工程、配電盤設備安裝工程、監控安裝工程、太陽能系統測試工程。
B17: 14 | C17: 運輸及吊掛工程 | D17: 1 | E17: 式 | F17: =成本!M167 | K17: 14 | L17: =C17 | M17: =D17 | N17: 式 | O17: 80000
B18: 15 | C18: 台電審查作業費、線補費 | D18: 1 | E18: 式 | F18: =成本!M172 | K18: 15 | L18: =C18 | M18: =D18 | N18: 式 | O18: =F18 | P18: 實質審查後，實支實付。
B20: 小計 | F20: =SUM(F4:F19) | K20: 小計 | O20: =SUM(O4:O19) | Q20: =IF(O20<F20,"錯誤","OK") | R20: 調整後利潤 | S20: =(O20-成本!O175)/O20
B21: 稅金5％ | F21: =F20*0.05 | K21: 稅金5％ | O21: =O20*0.05
B22: 總計 | F22: =F21+F20 | K22: 總計 | O22: =SUM(O20:O21)
B23: 平均1kw（未稅） | F23: =F20/#REF! | K23: 平均1kW（未稅） | O23: =O20/#REF!
B24: 平均1kw（含稅） | F24: =F22/#REF! | K24: 平均1kW（含稅） | O24: =O22/#REF!
B25: 運維 | K25: 運維
B26: 1 | C26: 系統維運 | D26: =C2 | E26: kW | F26: =D26*400*20 | K26: 1 | L26: 系統維運 | M26: =D26 | N26: kW | O26: =F26 | P26: 400kW/年，共計20年。 含清洗巡檢線上監控等運維服務。
B27: 其他 | K27: 其他
B28: 1 | C28: 保險費 | D28: 參考: 造價0.3% 由業主自行投保。 | K28: 1 | L28: 保險費 | M28: =D28
B29: 2 | C29: 模組回收費 | D29: =C2 | E29: kW | F29: =D29*1000 | K29: 2 | L29: 模組回收費 | M29: =D29 | N29: kW | O29: =F29 | P29: 1000kW/元，由環保署分10年徵收。

Sheet IRR (樂觀2%)
B2: 重資打包賣價 | C2: =Z28
C4: 年份 | D4: 2020 | E4: 2021 | F4: 2022 | G4: 2023 | H4: 2024 | I4: 2025 | J4: 2026 | K4: 2027 | L4: 2028 | M4: 2029 | N4: 2030 | O4: 2031 | P4: 2032 | Q4: 2033 | R4: 2034 | S4: 2035 | T4: 2036 | U4: 2037 | V4: 2038 | W4: 2039
B5: 案場名 | C5: 預估發電度數 | AD5: 發電度數
B6: =#REF! | D6: =#REF! | E6: =#REF! | F6: =#REF! | G6: =#REF! | H6: =#REF! | I6: =#REF! | J6: =#REF! | K6: =#REF! | ... W6: =#REF! | Z6: =SUM(D6:Y6) | AD6: 賣價
C7: 發電度數 總計 | D7: =SUM(D6:D6) | E7: =SUM(E6:E6) | F7: =SUM(F6:F6) | G7: =SUM(G6:G6) | H7: =SUM(H6:H6) | I7: =SUM(I6:I6) | J7: =SUM(J6:J6) | K7: =SUM(K6:K6) | ... X7: =SUM(X6:X6) | Z7: =SUM(D7:Y7) | AA7: =IF(ROUND((#REF!-'IRR (樂觀2%)'!Z7),0)=0,"correct", "error")
B8: 案場名 | C8: 預估收入 | D8: 2020 | E8: 2021 | F8: 2022 | G8: 2023 | H8: 2024 | I8: 2025 | J8: 2026 | K8: 2027 | L8: 2028 | M8: 2029 | N8: 2030 | O8: 2031 | P8: 2032 | Q8: 2033 | R8: 2034 | S8: 2035 | T8: 2036 | U8: 2037 | V8: 2038 | W8: 2039 | X8: 2040
B9: =#REF! | D9: =#REF! | E9: =#REF! | F9: =#REF! | G9: =#REF! | H9: =#REF! | I9: =#REF! | J9: =#REF! | K9: =#REF! | ... W9: =#REF! | Z9: =SUM(D9:Y9)
C10: 預估收入 總計 | D10: =SUM(D9:D9) | E10: =SUM(E9:E9) | F10: =SUM(F9:F9) | G10: =SUM(G9:G9) | H10: =SUM(H9:H9) | I10: =SUM(I9:I9) | J10: =SUM(J9:J9) | K10: =SUM(K9:K9) | ... X10: =SUM(X9:X9) | Z10: =SUM(D10:Y10) | AA10: =IF(ROUND((#REF!-'IRR (樂觀2%)'!Z10),0)=0,"correct", "error")
B11: 案場名 | C11: 租金/年 | D11: 2020 | E11: 2021 | F11: 2022 | G11: 2023 | H11: 2024 | I11: 2025 | J11: 2026 | K11: 2027 | L11: 2028 | M11: 2029 | N11: 2030 | O11: 2031 | P11: 2032 | Q11: 2033 | R11: 2034 | S11: 2035 | T11: 2036 | U11: 2037 | V11: 2038 | W11: 2039 | X11: 2040
B12: =#REF! | D12: =#REF! | E12: =#REF! | F12: =#REF! | G12: =#REF! | H12: =#REF! | I12: =#REF! | J12: =#REF! | K12: =#REF! | ... W12: =#REF! | Z12: =SUM(D12:Y12)
C13: 租金/年 總計 | D13: =SUM(D12:D12) | E13: =SUM(E12:E12) | F13: =SUM(F12:F12) | G13: =SUM(G12:G12) | H13: =SUM(H12:H12) | I13: =SUM(I12:I12) | J13: =SUM(J12:J12) | K13: =SUM(K12:K12) | ... X13: =SUM(X12:X12) | Z13: =SUM(D13:Y13) | AA13: =IF(ROUND((#REF!-'IRR (樂觀2%)'!Z13),0)=0,"correct", "error")
B14: 案場名 | C14: 運維/年 | D14: 2020 | E14: 2021 | F14: 2022 | G14: 2023 | H14: 2024 | I14: 2025 | J14: 2026 | K14: 2027 | L14: 2028 | M14: 2029 | N14: 2030 | O14: 2031 | P14: 2032 | Q14: 2033 | R14: 2034 | S14: 2035 | T14: 2036 | U14: 2037 | V14: 2038 | W14: 2039 | X14: 2040
B15: =#REF! | D15: =#REF! | E15: =#REF! | F15: =#REF! | G15: =#REF! | H15: =#REF! | I15: =#REF! | J15: =#REF! | K15: =#REF! | ... W15: =#REF! | Z15: =SUM(D15:Y15)
C16: 運維/年 總計 | D16: =SUM(D15:D15) | E16: =SUM(E15:E15) | F16: =SUM(F15:F15) | G16: =SUM(G15:G15) | H16: =SUM(H15:H15) | I16: =SUM(I15:I15) | J16: =SUM(J15:J15) | K16: =SUM(K15:K15) | ... X16: =SUM(X15:X15) | Z16: =SUM(D16:Y16) | AA16: =IF(ROUND((#REF!-'IRR (樂觀2%)'!Z16),0)=0,"correct", "error")
B17: 案場名 | C17: 保險/年 | D17: 2020 | E17: 2021 | F17: 2022 | G17: 2023 | H17: 2024 | I17: 2025 | J17: 2026 | K17: 2027 | L17: 2028 | M17: 2029 | N17: 2030 | O17: 2031 | P17: 2032 | Q17: 2033 | R17: 2034 | S17: 2035 | T17: 2036 | U17: 2037 | V17: 2038 | W17: 2039 | X17: 2040
B18: =#REF! | D18: =#REF! | E18: =#REF! | F18: =#REF! | G18: =#REF! | H18: =#REF! | I18: =#REF! | J18: =#REF! | K18: =#REF! | ... W18: =#REF! | Z18: =SUM(D18:Y18)
C19: 保險/年 總計 | D19: =SUM(D18:D18) | E19: =SUM(E18:E18) | F19: =SUM(F18:F18) | G19: =SUM(G18:G18) | H19: =SUM(H18:H18) | I19: =SUM(I18:I18) | J19: =SUM(J18:J18) | K19: =SUM(K18:K18) | ... X19: =SUM(X18:X18) | Z19: =SUM(D19:Y19) | AA19: =IF(ROUND((#REF!-'IRR (樂觀2%)'!Z19),0)=0,"correct", "error")
B20: 案場名 | C20: 模組回收費/年 | D20: 2020 | E20: 2021 | F20: 2022 | G20: 2023 | H20: 2024 | I20: 2025 | J20: 2026 | K20: 2027 | L20: 2028 | M20: 2029 | N20: 2030 | O20: 2031 | P20: 2032 | Q20: 2033 | R20: 2034 | S20: 2035 | T20: 2036 | U20: 2037 | V20: 2038 | W20: 2039 | X20: 2040
B21: =#REF! | D21: =#REF! | E21: =#REF! | F21: =#REF! | G21: =#REF! | H21: =#REF! | I21: =#REF! | J21: =#REF! | K21: =#REF! | ... W21: =#REF! | Z21: =SUM(D21:Y21)
C22: 模組回收費/年 總計 | D22: =SUM(D21:D21) | E22: =SUM(E21:E21) | F22: =SUM(F21:F21) | G22: =SUM(G21:G21) | H22: =SUM(H21:H21) | I22: =SUM(I21:I21) | J22: =SUM(J21:J21) | K22: =SUM(K21:K21) | ... X22: =SUM(X21:X21) | Z22: =SUM(D22:Y22) | AA22: =IF(ROUND((#REF!-'IRR (樂觀2%)'!Z22),0)=0,"correct", "error")
B23: 案場名 | C23: 所得稅/年 | D23: 2020 | E23: 2021 | F23: 2022 | G23: 2023 | H23: 2024 | I23: 2025 | J23: 2026 | K23: 2027 | L23: 2028 | M23: 2029 | N23: 2030 | O23: 2031 | P23: 2032 | Q23: 2033 | R23: 2034 | S23: 2035 | T23: 2036 | U23: 2037 | V23: 2038 | W23: 2039 | X23: 2040
B24: =#REF! | D24: =#REF! | E24: =#REF! | F24: =#REF! | G24: =#REF! | H24: =#REF! | I24: =#REF! | J24: =#REF! | K24: =#REF! | ... W24: =#REF! | Z24: =SUM(D24:Y24)
C25: 所得稅/年 總計 | D25: =SUM(D24:D24) | E25: =SUM(E24:E24) | F25: =SUM(F24:F24) | G25: =SUM(G24:G24) | H25: =SUM(H24:H24) | I25: =SUM(I24:I24) | J25: =SUM(J24:J24) | K25: =SUM(K24:K24) | ... X25: =SUM(X24:X24) | Z25: =SUM(D25:Y25) | AA25: =IF(ROUND((#REF!-'IRR (樂觀2%)'!Z25),0)=0,"correct", "error")
B26: 案場名 | C26: 設備折舊/年 | D26: 2020 | E26: 2021 | F26: 2022 | G26: 2023 | H26: 2024 | I26: 2025 | J26: 2026 | K26: 2027 | L26: 2028 | M26: 2029 | N26: 2030 | O26: 2031 | P26: 2032 | Q26: 2033 | R26: 2034 | S26: 2035 | T26: 2036 | U26: 2037 | V26: 2038 | W26: 2039 | X26: 2040
B27: =#REF! | D27: =#REF! | E27: =#REF! | F27: =#REF! | G27: =#REF! | H27: =#REF! | I27: =#REF! | J27: =#REF! | K27: =#REF! | ... W27: =#REF! | Z27: =SUM(D27:Y27) | AA27: =IF(ROUND((Z27-#REF!),0)=0,"correct", "error")
C28: 設備折舊/年 總計 | D28: =SUM(D27:D27) | E28: =SUM(E27:E27) | F28: =SUM(F27:F27) | G28: =SUM(G27:G27) | H28: =SUM(H27:H27) | I28: =SUM(I27:I27) | J28: =SUM(J27:J27) | K28: =SUM(K27:K27) | ... X28: =SUM(X27:X27) | Z28: =SUM(D28:Y28) | AA28: =IF(ROUND((#REF!-'IRR (樂觀2%)'!Z28),0)=0,"correct", "error")
C30: 年份 | D30: 2020 | E30: 2021 | F30: 2022 | G30: 2023 | H30: 2024 | I30: 2025 | J30: 2026 | K30: 2027 | L30: 2028 | M30: 2029 | N30: 2030 | O30: 2031 | P30: 2032 | Q30: 2033 | R30: 2034 | S30: 2035 | T30: 2036 | U30: 2037 | V30: 2038 | W30: 2039
B31: 0 | F31: 手動計算值 | T31: 償還年限
B32: (Unit : Currency) | C32: 0 | D32: 1 | E32: 2 | F32: 3 | G32: 4 | H32: 5 | I32: 6 | J32: 7 | K32: 8 | L32: 9 | M32: 10 | N32: 11 | O32: 12 | P32: 13 | Q32: 14 | R32: 15 | S32: 16 | T32: 17 | U32: 18 | V32: 19 | W32: 20
B33: 發電度數(KWH) | C33: 0 | D33: =D7 | E33: =E7 | F33: =F7 | G33: =G7 | H33: =H7 | I33: =I7 | J33: =J7 | K33: =K7 | ... X33: =X7 | Z33: =SUM(D33:Y33) | AA33: =IF(ROUND((Z33-Z7),0)=0,"correct", "error")
B34: Inflow : 電費收入 | C34: - | D34: =D10 | E34: =E10 | F34: =F10 | G34: =G10 | H34: =H10 | I34: =I10 | J34: =J10 | K34: =K10 | ... X34: =X10 | Z34: =SUM(D34:Y34) | AA34: =IF(ROUND((Z34-Z10),0)=0,"correct", "error")
B35: Inflow : 政府補助 | C35: - | F35: 0 | G35: - | H35: - | I35: - | J35: - | K35: - | L35: - | M35: - | N35: - | O35: - | P35: - | Q35: - | R35: - | S35: - | T35: - | U35: - | V35: - | W35: -
B36: Inflow : 銀行借款
B37: Outflow : 設備費用 | C37: =-C2 | F37: - | G37: - | H37: - | I37: - | J37: - | K37: - | L37: - | M37: - | N37: - | O37: - | P37: - | Q37: - | R37: - | S37: - | T37: - | U37: - | V37: - | W37: -
B38: Outflow : 設備放置區域租金 | C38: - | D38: =-D13 | E38: =-E13 | F38: =-F13 | G38: =-G13 | H38: =-H13 | I38: =-I13 | J38: =-J13 | K38: =-K13 | ... X38: =-X13 | Z38: =SUM(D38:Y38) | AA38: =IF(ROUND((Z38+Z13),0)=0,"correct", "error")
B39: Outflow : 返還借款 | C39: 0 | V39: 0 | W39: 0 | Z39: =SUM(D39:Y39)
B40: Outflow : 利息費用 | C40: - | Z40: =SUM(D40:Y40)
B41: Outflow : 維運費 | C41: - | D41: =-D16 | E41: =-E16 | F41: =-F16 | G41: =-G16 | H41: =-H16 | I41: =-I16 | J41: =-J16 | K41: =-K16 | ... X41: =-X16 | Z41: =SUM(D41:Y41) | AA41: =IF(ROUND((Z41+Z16),0)=0,"correct", "error")
B42: Outflow : 保險費 | C42: - | D42: =-D19 | E42: =-E19 | F42: =-F19 | G42: =-G19 | H42: =-H19 | I42: =-I19 | J42: =-J19 | K42: =-K19 | ... X42: =-X19 | Z42: =SUM(D42:Y42) | AA42: =IF(ROUND((Z42+Z19),0)=0,"correct", "error")
B43: Outflow : 模組回收費 | D43: =-D22 | E43: =-E22 | F43: =-F22 | G43: =-G22 | H43: =-H22 | I43: =-I22 | J43: =-J22 | K43: =-K22 | ... X43: =-X22 | Z43: =SUM(D43:Y43) | AA43: =IF(ROUND((Z22+Z43),0)=0,"correct", "error")
B44: Outflow : 其它費用(人事薪資…等) | F44: =-(F34*$D$131) | G44: =-(G34*$D$131) | H44: =-(H34*$D$131) | I44: =-(I34*$D$131) | J44: =-(J34*$D$131) | K44: =-(K34*$D$131) | L44: =-(L34*$D$131) | M44: =-(M34*$D$131) | ... X44: =-(X34*$D$131) | Z44: =SUM(D44:Y44)
B45: 1%管理費 | Z45: =SUM(D45:Y45)
B46: 績效獎金 | Z46: =SUM(D46:Y46)
B47: 所得稅20% | D47: =IF((D88+SUM(D90+D91+D94+D95+D96+D97))>0,-(D88+SUM(D90+D91+D94+D95+D96+D97))*0.2,0) | E47: =IF((E88+SUM(E90+E91+E94+E95+E96+E97))>0,-(E88+SUM(E90+E91+E94+E95+E96+E97))*0.2,0) | F47: =IF((F88+SUM(F90+F91+F94+F95+F96+F97))>0,-(F88+SUM(F90+F91+F94+F95+F96+F97))*0.2,0) | G47: =IF((G88+SUM(G90+G91+G94+G95+G96+G97))>0,-(G88+SUM(G90+G91+G94+G95+G96+G97))*0.2,0) | H47: =IF((H88+SUM(H90+H91+H94+H95+H96+H97))>0,-(H88+SUM(H90+H91+H94+H95+H96+H97))*0.2,0) | I47: =IF((I88+SUM(I90+I91+I94+I95+I96+I97))>0,-(I88+SUM(I90+I91+I94+I95+I96+I97))*0.2,0) | J47: =IF((J88+SUM(J90+J91+J94+J95+J96+J97))>0,-(J88+SUM(J90+J91+J94+J95+J96+J97))*0.2,0) | K47: =IF((K88+SUM(K90+K91+K94+K95+K96+K97))>0,-(K88+SUM(K90+K91+K94+K95+K96+K97))*0.2,0) | ... X47: =IF((X88+SUM(X90+X91+X94+X95+X96+X97))>0,-(X88+SUM(X90+X91+X94+X95+X96+X97))*0.2,0) | Z47: =SUM(D47:Y47) | AA47: =IF(ROUND((Z47+Z25),0)=0,"correct", "error")
Z48: =SUM(D48:Y48)
B49: 現金流 | C49: =C37 | D49: =SUM(D34:D47) | E49: =SUM(E34:E47) | F49: =SUM(F34:F47) | G49: =SUM(G34:G47) | H49: =SUM(H34:H47) | I49: =SUM(I34:I47) | J49: =SUM(J34:J47) | K49: =SUM(K34:K47) | ... X49: =SUM(X34:X47) | Z49: =SUM(C49:Y49)
B50: 累計現金流 | D50: =D49+C49 | E50: =E49+D50 | F50: =F49+E50 | G50: =G49+F50 | H50: =H49+G50 | I50: =I49+H50 | J50: =J49+I50 | K50: =K49+J50 | L50: =L49+K50 | ... W50: =W49+V50 | Z50: =IF(ROUND((Z49-W50),0)=0,"correct", "error")
B51: Discounted cash flow | C51: -37721416 | F51: 4765724.1 | G51: 4715578.7 | H51: 4665433.3 | I51: 4615287.9 | J51: 4565142.4 | K51: 4517504.3 | L51: 4469866.2 | M51: 4422228 | N51: 4374589.9 | O51: 4326951.7 | P51: 4284954.9 | Q51: 4242958.2 | R51: 4200961.4 | S51: 4158964.6 | T51: 4116967.8 | U51: 4074971 | V51: 4032974.2 | W51: 3990977.4
B52: Minus : Depreciation | F52: 1886070.8 | G52: 1886070.8 | H52: 1886070.8 | I52: 1886070.8 | J52: 1886070.8 | K52: 1886070.8 | L52: 1886070.8 | M52: 1886070.8 | N52: 1886070.8 | O52: 1886070.8 | P52: 1886070.8 | Q52: 1886070.8 | R52: 1886070.8 | S52: 1886070.8 | T52: 1886070.8 | U52: 1886070.8 | V52: 1886070.8 | W52: 1886070.8
B53: Plus : Principle payment | F53: 0 | G53: 0 | H53: 0 | I53: 0 | J53: 0 | K53: 0 | L53: 0 | M53: 0 | N53: 0 | O53: 0 | P53: 0 | Q53: 0 | R53: 0 | S53: 0 | T53: 0 | U53: 0 | V53: 0 | W53: 0
B54: Profit | F54: 2879653.3 | G54: 2829507.9 | H54: 2779362.5 | I54: 2729217 | J54: 2679071.6 | K54: 2631433.5 | L54: 2583795.3 | M54: 2536157.2 | N54: 2488519 | O54: 2440880.9 | P54: 2398884.1 | Q54: 2356887.3 | R54: 2314890.5 | S54: 2272893.8 | T54: 2230897 | U54: 2188900.2 | V54: 2146903.4 | W54: 2104906.6
B55: EPS | F55: 0.76340009 | G55: 0.75010647 | H55: 0.73681286 | I55: 0.72351924 | J55: 0.71022562 | K55: 0.69759668 | L55: 0.68496774 | M55: 0.6723388 | N55: 0.65970986 | O55: 0.64708093 | P55: 0.63594752 | Q55: 0.62481411 | R55: 0.61368071 | S55: 0.6025473 | T55: 0.59141389 | U55: 0.58028049 | V55: 0.56914708 | W55: 0.55801368
B56: 回收年限評估 | D56: =IF((D50)>0,"回收","未回收") | E56: =IF((E50)>0,"回收","未回收") | F56: =IF((F50)>0,"回收","未回收") | G56: =IF((G50)>0,"回收","未回收") | H56: =IF((H50)>0,"回收","未回收") | I56: =IF((I50)>0,"回收","未回收") | J56: =IF((J50)>0,"回收","未回收") | K56: =IF((K50)>0,"回收","未回收") | ... W56: =IF((W50)>0,"回收","未回收")
L58: 預估可建置量 | M58: 0
L59: 預估可建置量 | M59: 0
L60: 總計 | M60: =M58+M59
B62: Assumption | D62: NOTE | J62: 管理費，1%of 股本 | L62: 假設自有資本(億) | N62: =D159/100000000 | AC62: 申辦期間一甲地租金 | AG62: 100000
B63: 預計系統完工年限 | C63: 109年 | D63: #REF! | J63: 績效獎金 | L63: 貸款(億) | N63: =D157/100000000 | AH63: 申辦期預抓2年土租 | AK63: 20
B64: 政府每度收購價格 | C64: 4.1733 | D64: 109下半年 地面型併高壓費率(高效模組) | J64: 權益法下IRR | L64: XX年攤還 (有錢就還) | AC64: 平方公尺 | AD64: 甲 | AE64: 公頃 | AF64: 分 | AG64: 申辦期 租金/甲/年 | AH64: 2 | AI64: 每年租金/分 (單價) | AJ64: 掛錶後 每年租金/分 | AK64: 20年土地租金 | AL64: 饋線 途經 國有財產地20年租金預抓
B65: 安裝容量(KW) | C65: =#REF! | J65: 現金流IRR | AB65: 地號學甲寮 283,82-83-84 三筆 | AC65: 10259 | AD65: 1.05668 | AE65: 1.0259 | AF65: 10.56677 | AG65: 105668 | AH65: 211336 | AI65: 35000 | AJ65: 369836.95 | AK65: 7396739
B66: 每KW系統價格(NTD/KW) -未稅 | C66: 0 | D66: 調整前價格 (恆映 開發費用4000/kW 測算) | AB66: 地號學甲寮 283,40-55-58 三筆 | AC66: 11113 | AD66: 1.14464 | AE66: 1.1113 | AF66: 11.44639 | AG66: 114464 | AH66: 228928 | AI66: 30000 | AJ66: 343391.7 | AK66: 6867834
B67: 總建構成本(NTD) | C67: 0 | AB67: 其餘地號都屬 翁秀正, 李雅婷 | AC67: 154742 | AD67: 15.93843 | AE67: 15.4742 | AF67: 159.38426 | AG67: 1593843 | AH67: 3187686 | AI67: 40000 | AJ67: 6375370.4 | AK67: 127507408 | AM67: 20年土地總租金(含國有財產地)
B68: 政府補助(NTD/案) | C68: 0 | AB68: 總計 | AC68: 176114 | AD68: 18.13975 | AE68: 17.6114 | AG68: 1813975 | AH68: 3627950 | AJ68: 7088599.1 | AK68: 141771981 | AL68: 2000000
B69: 貸款金額(NTD) | C69: 0 | D69: 0 | E69: 貸款成數 | K69: 20年 | L69: 前2年 開發期 每年租金 | AH69: 土地界址鑑定合計
B70: 償還年限 | C70: 15 | D70: (本息平均)償還法 | H70: 有錢就還 | J70: 租金(依各地主條件) | K70: - | AB70: a.土地界址鑑定規費 : 17公頃 *$ 4,000 + 0.6114公頃 - 以 $2,000計 , 合計: $70,000元 | AH70: 75000
B71: 銀行利率(%) | C71: 0.02 | J71: 保險 | K71: 0 | AB71: b.地政事務所陪同鑑界費用 : 因土地面積龐大 , 每筆土地收費$5,000元(初估)
B72: 設備放置區域年租金(NTD) | C72: 0 | D72: 各地主租金總合+饋線途經國有財產地6公里租金 | E72: ; 租 | F72: 20 | G72: 年
B73: 維運費(NTD) | C73: 0 | D73: 400/kw | E73: ; 保固共 | F73: 20 | G73: 年 | I73: 1KW | J73: 運維20年 | N73: 金額 | O73: 備註
B74: 保險費(NTD) | C74: 0 | D74: 0.003 | E74: ; 保險共 | F74: 20 | G74: 年 | I74: 400 | J74: 0 | M74: 模組回收(kw) | N74: 1000 | O74: 分10年攤提
B75: 模組回收費(NTD) | C75: 0 | D75: 分10年攤提 | E75: ; 攤提共 | F75: 10 | G75: 年 | I75: 300 | J75: 0 | M75: 0
B76: 初始資金需求 | C76: 0 | D76: 原始資金需求 | I76: 200 | J76: 0
B77: 折扣率(%) | C77: 0 | D77: 競標型 | I77: 100 | J77: 0
B78: 高效加成%
B79: 最終躉售費率
B80: Internal Rate of Return; IRR (%) | C80: =IRR(C49:X49)
C84: 年份 | D84: 2020 | E84: 2021 | F84: 2022 | G84: 2023 | H84: 2024 | I84: 2025 | J84: 2026 | K84: 2027 | L84: 2028 | M84: 2029 | N84: 2030 | O84: 2031 | P84: 2032 | Q84: 2033 | R84: 2034 | S84: 2035 | T84: 2036 | U84: 2037 | V84: 2038 | W84: 2039
B85: =C120 | F85: 手動計算值 | T85: 償還年限
B86: (Unit : Currency) | C86: 0 | D86: 1 | E86: 2 | F86: 3 | G86: 4 | H86: 5 | I86: 6 | J86: 7 | K86: 8 | L86: 9 | M86: 10 | N86: 11 | O86: 12 | P86: 13 | Q86: 14 | R86: 15 | S86: 16 | T86: 17 | U86: 18 | V86: 19 | W86: 20
B87: 發電度數(KWH) | C87: 0 | D87: =D33 | E87: =E33 | F87: =F33 | G87: =G33 | H87: =H33 | I87: =I33 | J87: =J33 | K87: =K33 | ... X87: =X33 | Z87: =SUM(D87:Y87)
B88: 電費收入 | C88: - | D88: =D10 | E88: =E10 | F88: =F10 | G88: =G10 | H88: =H10 | I88: =I10 | J88: =J10 | K88: =K10 | ... X88: =X10 | Z88: =SUM(D88:Y88)
B89: 政府補助 | C89: - | Z89: =SUM(D89:Y89)
B90: : 設備折舊 | C90: - | D90: =-D28 | E90: =-E28 | F90: =-F28 | G90: =-G28 | H90: =-H28 | I90: =-I28 | J90: =-J28 | K90: =-K28 | ... X90: =-X28 | Z90: =SUM(D90:Y90)
B91: : 設備放置區域租金 | C91: - | D91: =D38 | E91: =E38 | F91: =F38 | G91: =G38 | H91: =H38 | I91: =I38 | J91: =J38 | K91: =K38 | ... X91: =X38 | Z91: =SUM(D91:Y91)
C92: - | F92: - | G92: - | H92: - | I92: - | J92: - | K92: - | L92: - | M92: - | N92: - | O92: - | P92: - | Q92: - | R92: - | S92: - | T92: - | U92: - | V92: - | W92: - | Z92: =SUM(D92:Y92)
B93: : 利息費用 | C93: - | D93: =-D174*$C$126 | E93: =-E174*$C$126 | F93: =-F174*$C$126 | G93: =-G174*$C$126 | H93: =-H174*$C$126 | I93: =-I174*$C$126 | J93: =-J174*$C$126 | K93: =-K174*$C$126 | ... X93: =-X174*$C$126 | Z93: =SUM(D93:Y93)
B94: : 維運費 | C94: - | D94: =D41 | E94: =E41 | F94: =F41 | G94: =G41 | H94: =H41 | I94: =I41 | J94: =J41 | K94: =K41 | ... X94: =X41 | Z94: =SUM(D94:Y94)
B95: : 保險費 | C95: - | D95: =D42 | E95: =E42 | F95: =F42 | G95: =G42 | H95: =H42 | I95: =I42 | J95: =J42 | K95: =K42 | ... X95: =X42 | Z95: =SUM(D95:Y95)
B96: : 模組回收費 | D96: =D43 | E96: =E43 | F96: =F43 | G96: =G43 | H96: =H43 | I96: =I43 | J96: =J43 | K96: =K43 | ... X96: =X43 | Z96: =SUM(D96:Y96)
B97: : 其它費用(人事薪資…等) | C97: - | F97: =-(F88*$D$131) | G97: =-(G88*$D$131) | H97: =-(H88*$D$131) | I97: =-(I88*$D$131) | J97: =-(J88*$D$131) | K97: =-(K88*$D$131) | L97: =-(L88*$D$131) | M97: =-(M88*$D$131) | ... W97: =-(W88*$D$131) | Z97: =SUM(D97:Y97)
B98: 1%管理費 | D98: =-D159*0.01 | E98: =(D98/0.01-D161)*0.01 | F98: =(E98/0.01-E161)*0.01 | G98: =(F98/0.01-F161)*0.01 | H98: =(G98/0.01-G161)*0.01 | I98: =(H98/0.01-H161)*0.01 | J98: =(I98/0.01-I161)*0.01 | K98: =(J98/0.01-J161)*0.01 | L98: =(K98/0.01-K161)*0.01 | ... W98: =(V98/0.01-V161)*0.01 | Z98: =SUM(D98:Y98)
B99: 績效獎金 | E99: =-IF((SUM(E88:E98)/(-D98/0.1))>0.5,(SUM(E88:E98)*0.8+((D98/0.01-D161)*0.05))*0.2, 0) | F99: =-IF((SUM(F88:F98)/(-E98/0.1))>0.5,(SUM(F88:F98)*0.8+((E98/0.01-E161)*0.05))*0.2, 0) | G99: =-IF((SUM(G88:G98)/(-F98/0.1))>0.5,(SUM(G88:G98)*0.8+((F98/0.01-F161)*0.05))*0.2, 0) | H99: =-IF((SUM(H88:H98)/(-G98/0.1))>0.5,(SUM(H88:H98)*0.8+((G98/0.01-G161)*0.05))*0.2, 0) | I99: =-IF((SUM(I88:I98)/(-H98/0.1))>0.5,(SUM(I88:I98)*0.8+((H98/0.01-H161)*0.05))*0.2, 0) | J99: =-IF((SUM(J88:J98)/(-I98/0.1))>0.5,(SUM(J88:J98)*0.8+((I98/0.01-I161)*0.05))*0.2, 0) | K99: =-IF((SUM(K88:K98)/(-J98/0.1))>0.5,(SUM(K88:K98)*0.8+((J98/0.01-J161)*0.05))*0.2, 0) | L99: =-IF((SUM(L88:L98)/(-K98/0.1))>0.5,(SUM(L88:L98)*0.8+((K98/0.01-K161)*0.05))*0.2, 0) | ... X99: =-IF((SUM(X88:X98)/(-W98/0.1))>0.5,(SUM(X88:X98)*0.8+((W98/0.01-W161)*0.05))*0.2, 0) | Z99: =SUM(D99:Y99)
B100: 稅前淨利 | C100: 0 | D100: =SUM(D88:D99) | E100: =SUM(E88:E99) | F100: =SUM(F88:F99) | G100: =SUM(G88:G99) | H100: =SUM(H88:H99) | I100: =SUM(I88:I99) | J100: =SUM(J88:J99) | K100: =SUM(K88:K99) | ... X100: =SUM(X88:X99) | Z100: =SUM(D100:Y100)
B101: Outflow : 所得稅(20%) | C101: - | D101: =-D100*0.2 | E101: =-E100*0.2 | F101: =-F100*0.2 | G101: =-(G100*$D$132) | H101: =-(H100*$D$132) | I101: =-(I100*$D$132) | J101: =-(J100*$D$132) | K101: =-(K100*$D$132) | L101: =-(L100*$D$132) | M101: =-(M100*$D$132) | N101: =-(N100*$D$132) | ... X101: =-(X100*$D$132) | Z101: =SUM(F101:Y101)
B102: 稅後淨利 | D102: =SUM(D100:D101) | E102: =SUM(E100:E101) | F102: =SUM(F100:F101) | G102: =SUM(G100:G101) | H102: =SUM(H100:H101) | I102: =SUM(I100:I101) | J102: =SUM(J100:J101) | K102: =SUM(K100:K101) | ... X102: =SUM(X100:X101) | Z102: =SUM(D102:Y102) | AA102: =IF(ROUND((Z102-Y169),0)=0,"correct", "error")
B103: 每股盈餘 | D103: =D102/($N$62*10000000) | E103: =E102/($N$62*10000000) | F103: =F102/-(E98/0.01-E161)*10 | G103: =G102/-(F98/0.01-F161)*10 | H103: =H102/-(G98/0.01-G161)*10 | I103: =I102/-(H98/0.01-H161)*10 | J103: =J102/-(I98/0.01-I161)*10 | K103: =K102/-(J98/0.01-J161)*10 | L103: =L102/-(K98/0.01-K161)*10 | M103: =M102/-(L98/0.01-L161)*10 | ... W103: =W102/-(V98/0.01-V161)*10
B106: 設備折舊 | D106: =-D90 | E106: =-E90 | F106: =-F90 | G106: =-G90 | H106: =-H90 | I106: =-I90 | J106: =-J90 | K106: =-K90 | ... X106: =-X90 | Z106: =SUM(D106:Y106) | AA106: =IF(ROUND((Z106-C122-C2),0)=0,"correct", "error")
B107: 累計現金流 | C107: 0 | D107: =C37+D102+D106 | E107: =E102+E106+D107 | F107: =F102+F106+E107 | G107: =G102+G106+F107 | H107: =H102+H106+G107 | I107: =I102+I106+H107 | J107: =J102+J106+I107 | K107: =K102+K106+J107 | L107: =L102+L106+K107 | ... W107: =W102+W106+V107 | Z107: =IF(ROUND((W107-Z102),0)=0,"correct", "error")
B108: Discounted cash flow | C108: 0 | F108: 1983135.6 | G108: 1938004.7 | H108: 1892873.8 | I108: 1847742.9 | J108: 1802612.1 | K108: 1759737.7 | L108: 1716863.4 | M108: 1673989.1 | N108: 1631114.8 | O108: 1588240.4 | P108: 1550443.3 | Q108: 1512646.2 | R108: 1474849.1 | S108: 1437052 | T108: 1399254.9 | U108: 1361457.8 | V108: 1323660.7 | W108: 1285863.6
B109: Minus : Depreciation | F109: 0 | G109: 0 | H109: 0 | I109: 0 | J109: 0 | K109: 0 | L109: 0 | M109: 0 | N109: 0 | O109: 0 | P109: 0 | Q109: 0 | R109: 0 | S109: 0 | T109: 0 | U109: 0 | V109: 0 | W109: 0
B110: Plus : Principle payment | F110: 0 | G110: 0 | H110: 0 | I110: 0 | J110: 0 | K110: 0 | L110: 0 | M110: 0 | N110: 0 | O110: 0 | P110: 0 | Q110: 0 | R110: 0 | S110: 0 | T110: 0 | U110: 0 | V110: 0 | W110: 0
...

Sheet 滾算紀錄單(總紀錄)
A1: 價金每KW | B1: 專案法IRR | C1: 權益法IRR | D1: 信邦利潤率 | E1: 信邦利潤 | F1: 每kw信邦利潤 | G1: 開發費 | H1: 備註
A2: 30000 | B2: 4.29 | C2: 10.43 | D2: 0.2 | E2: 2398550 | F2: 5500 | G2: 2000 | H2: 初始價金 - 現金模式，每次減少 500 元，邊界值 25000 元
A3: 29500 | B3: 4.46 | C3: 11.07 | D3: 0.2 | E3: 2344037.5 | F3: 5375 | G3: 2000 | H3: 第1次滾算，減少 500 元 - 現金模式，每次減少 500 元
A4: 29000 | B4: 4.63 | C4: 11.74 | D4: 0.2 | E4: 2289525 | F4: 5250 | G4: 2000 | H4: 第2次滾算，減少 500 元 - 現金模式，每次減少 500 元
A5: 28500 | B5: 4.8 | C5: 12.44 | D5: 0.2 | E5: 2235012.5 | F5: 5125 | G5: 2000 | H5: 第3次滾算，減少 500 元 - 現金模式，每次減少 500 元
A6: 28000 | B6: 4.98 | C6: 13.18 | D6: 0.2 | E6: 2180500 | F6: 5000 | G6: 2000 | H6: 第4次滾算，減少 500 元 - 現金模式，每次減少 500 元
A7: 27500 | B7: 5.16 | C7: 13.95 | D7: 0.2 | E7: 2125987.5 | F7: 4875 | G7: 2000 | H7: 第5次滾算，減少 500 元 - 現金模式，每次減少 500 元
A8: 27000 | B8: 5.35 | C8: 14.77 | D8: 0.2 | E8: 2071475 | F8: 4750 | G8: 2000 | H8: 第6次滾算，減少 500 元 - 現金模式，每次減少 500 元
A9: 26500 | B9: 5.54 | C9: 15.63 | D9: 0.2 | E9: 2016962.5 | F9: 4625 | G9: 2000 | H9: 第7次滾算，減少 500 元 - 現金模式，每次減少 500 元
A10: 26000 | B10: 5.74 | C10: 16.54 | D10: 0.2 | E10: 1962450 | F10: 4500 | G10: 2000 | H10: 第8次滾算，減少 500 元 - 現金模式，每次減少 500 元
A11: 25500 | B11: 5.94 | C11: 17.51 | D11: 0.2 | E11: 1907937.5 | F11: 4375 | G11: 2000 | H11: 第9次滾算，減少 500 元 - 現金模式，每次減少 500 元
A12: 25000 | B12: 6.15 | C12: 18.54 | D12: 0.2 | E12: 1853425 | F12: 4250 | G12: 2000 | H12: 第10次滾算，減少 500 元 - 現金模式，每次減少 500 元

Sheet 滾算紀錄單(使用者記錄)
A1: 價金每KW | B1: 專案法IRR | C1: 權益法IRR | D1: 信邦利潤率 | E1: 信邦利潤 | F1: 每kw信邦利潤 | G1: 開發費 | H1: 備註

Sheet 滾算紀錄1
B1: 電站基本資料
B2: 電站名稱 | C2: 淡江大學-財務模擬案場 | D2: - | E2: -
B3: 電站壽命 | C3: 20 | D3: - | E3: -
B4: 建置量(kWp) | C4: 436.1 | D4: - | E4: -
B5: 起始年度 | C5: 2020 | D5: 結束年度 | E5: 2039 | M5: 初始價金摘要
M6: 初始價金: 30000
B7: 綜合損益表 | M7: 專案IRR: 4.29
B8: 收入 | M8: 權益法IRR: 10.43
B9: 收支項目 | C9: 相關參數 | D9: 參數數值 | E9: 年限 | M9: 利潤率: 20.00%
B10: 電費收入 | C10: 年度AC併網總發電量 | D10: 547002 | E10: 20 | M10: 基準價金 - 滾算起始點
C11: 首年衰退率 | D11: 0.01
C12: 次年衰退率 | D12: 0.004
C13: 躉售費率(FIT) | D13: 3.7152
B14: 支出
B15: 收支項目 | C15: 相關參數 | D15: 參數數值 | E15: 攤提年限
B16: 設備費用(價金) | C16: 每kWp設備成本 | D16: 30000 | E16: 20
C17: 信邦利潤率 | D17: 0.2
C18: 開發費 | D18: 2000
B19: 租金費用 | C19: 租金計算方式 (1=固定攤提/2=電費抽成) | D19: 1 | E19: 0
C20: 【方式1參數】租金總額 | D20: 5804025 | E20: 20
C21: 【方式2參數】抽成比率 | D21: 0 | E21: 0
B22: 運維費用 | C22: 每kw運維成本 | D22: 400 | E22: 20
B23: 保險費用 | C23: 占整體設備費用比例 | D23: 0.003 | E23: 20
B24: 模組回收費用 | C24: 每kw模組回收成本 | D24: 1000 | E24: 10
B25: 利息費用 | C25: 銀行利率 | D25: 0.025595 | E25: 0
B26: 所得稅 | C26: 所得稅率 | D26: 0.2 | E26: 0
B29: 現金流量表
B30: 金流項目 | C30: 相關參數 | D30: 參數數值
B31: 貸款成數 | C31: 占總設備費用比例 | D31: 0.8
B32: 貸款還款 | C32: 攤還期數 | D32: 15
B33: 現金股利 | C33: 股利比率 | D33: 0.9
B34: 年底減資 | C34: 攤還期數 | D34: 4
C37: 年份 | D37: 2020 | E37: 2021 | F37: 2022 | G37: 2023 | H37: 2024 | I37: 2025 | J37: 2026 | K37: 2027 | L37: 2028 | M37: 2029 | N37: 2030 | O37: 2031 | P37: 2032 | Q37: 2033 | R37: 2034 | S37: 2035 | T37: 2036 | U37: 2037 | V37: 2038 | W37: 2039
B38: 0 | F38: 手動計算值 | T38: 償還年限
B39: (Unit : Currency) | C39: 0 | D39: 1 | E39: 2 | F39: 3 | G39: 4 | H39: 5 | I39: 6 | J39: 7 | K39: 8 | L39: 9 | M39: 10 | N39: 11 | O39: 12 | P39: 13 | Q39: 14 | R39: 15 | S39: 16 | T39: 17 | U39: 18 | V39: 19 | W39: 20
B40: 發電度數(KWH) | C40: 0 | D40: =#REF! | E40: =#REF! | F40: =#REF! | G40: =#REF! | H40: =#REF! | I40: =#REF! | J40: =#REF! | K40: =#REF! | ... W40: =#REF!
B41: Inflow : 電費收入 | C41: - | D41: =#REF! | E41: =#REF! | F41: =#REF! | G41: =#REF! | H41: =#REF! | I41: =#REF! | J41: =#REF! | K41: =#REF! | ... W41: =#REF!
B42: Inflow : 政府補助 | C42: - | F42: 0 | G42: - | H42: - | I42: - | J42: - | K42: - | L42: - | M42: - | N42: - | O42: - | P42: - | Q42: - | R42: - | S42: - | T42: - | U42: - | V42: - | W42: -
B43: Inflow : 銀行借款
B44: Outflow : 設備費用 | C44: =-#REF! | F44: - | G44: - | H44: - | I44: - | J44: - | K44: - | L44: - | M44: - | N44: - | O44: - | P44: - | Q44: - | R44: - | S44: - | T44: - | U44: - | V44: - | W44: -
B45: Outflow : 設備放置區域租金 | C45: - | D45: =-#REF! | E45: =-#REF! | F45: =-#REF! | G45: =-#REF! | H45: =-#REF! | I45: =-#REF! | J45: =-#REF! | K45: =-#REF! | ... W45: =-#REF!
B46: Outflow : 返還借款 | C46: 0 | V46: 0 | W46: 0
B47: Outflow : 利息費用 | C47: -
B48: Outflow : 維運費 | C48: - | D48: =-#REF! | E48: =-#REF! | F48: =-#REF! | G48: =-#REF! | H48: =-#REF! | I48: =-#REF! | J48: =-#REF! | K48: =-#REF! | ... W48: =-#REF!
B49: Outflow : 保險費 | C49: - | D49: =-#REF! | E49: =-#REF! | F49: =-#REF! | G49: =-#REF! | H49: =-#REF! | I49: =-#REF! | J49: =-#REF! | K49: =-#REF! | ... W49: =-#REF!
B50: Outflow : 模組回收費 | D50: =-#REF! | E50: =-#REF! | F50: =-#REF! | G50: =-#REF! | H50: =-#REF! | I50: =-#REF! | J50: =-#REF! | K50: =-#REF! | ... W50: =-#REF!
B51: Outflow : 其它費用(人事薪資…等) | F51: =-(F41*#REF!) | G51: =-(G41*#REF!) | H51: =-(H41*#REF!) | I51: =-(I41*#REF!) | J51: =-(J41*#REF!) | K51: =-(K41*#REF!) | L51: =-(L41*#REF!) | M51: =-(M41*#REF!) | ... W51: =-(W41*#REF!)
B52: 1%管理費
B53: 績效獎金
B54: 所得稅20% | D54: =IF((#REF!+SUM(#REF!+#REF!+#REF!+#REF!+#REF!+#REF!))>0,-(#REF!+SUM(#REF!+#REF!+#REF!+#REF!+#REF!+#REF!))*0.2,0) | E54: =IF((#REF!+SUM(#REF!+#REF!+#REF!+#REF!+#REF!+#REF!))>0,-(#REF!+SUM(#REF!+#REF!+#REF!+#REF!+#REF!+#REF!))*0.2,0) | F54: =IF((#REF!+SUM(#REF!+#REF!+#REF!+#REF!+#REF!+#REF!))>0,-(#REF!+SUM(#REF!+#REF!+#REF!+#REF!+#REF!+#REF!))*0.2,0) | G54: =IF((#REF!+SUM(#REF!+#REF!+#REF!+#REF!+#REF!+#REF!))>0,-(#REF!+SUM(#REF!+#REF!+#REF!+#REF!+#REF!+#REF!))*0.2,0) | H54: =IF((#REF!+SUM(#REF!+#REF!+#REF!+#REF!+#REF!+#REF!))>0,-(#REF!+SUM(#REF!+#REF!+#REF!+#REF!+#REF!+#REF!))*0.2,0) | I54: =IF((#REF!+SUM(#REF!+#REF!+#REF!+#REF!+#REF!+#REF!))>0,-(#REF!+SUM(#REF!+#REF!+#REF!+#REF!+#REF!+#REF!))*0.2,0) | J54: =IF((#REF!+SUM(#REF!+#REF!+#REF!+#REF!+#REF!+#REF!))>0,-(#REF!+SUM(#REF!+#REF!+#REF!+#REF!+#REF!+#REF!))*0.2,0) | K54: =IF((#REF!+SUM(#REF!+#REF!+#REF!+#REF!+#REF!+#REF!))>0,-(#REF!+SUM(#REF!+#REF!+#REF!+#REF!+#REF!+#REF!))*0.2,0) | ... W54: =IF((#REF!+SUM(#REF!+#REF!+#REF!+#REF!+#REF!+#REF!))>0,-(#REF!+SUM(#REF!+#REF!+#REF!+#REF!+#REF!+#REF!))*0.2,0)
B56: 現金流 | C56: =C44 | D56: =SUM(D41:D54) | E56: =SUM(E41:E54) | F56: =SUM(F41:F54) | G56: =SUM(G41:G54) | H56: =SUM(H41:H54) | I56: =SUM(I41:I54) | J56: =SUM(J41:J54) | K56: =SUM(K41:K54) | ... W56: =SUM(W41:W54)
B57: 累計現金流 | D57: =D56+C56 | E57: =E56+D57 | F57: =F56+E57 | G57: =G56+F57 | H57: =H56+G57 | I57: =I56+H57 | J57: =J56+I57 | K57: =K56+J57 | L57: =L56+K57 | ... W57: =W56+V57
B58: Discounted cash flow | C58: -37721416 | F58: 4765724.1 | G58: 4715578.7 | H58: 4665433.3 | I58: 4615287.9 | J58: 4565142.4 | K58: 4517504.3 | L58: 4469866.2 | M58: 4422228 | N58: 4374589.9 | O58: 4326951.7 | P58: 4284954.9 | Q58: 4242958.2 | R58: 4200961.4 | S58: 4158964.6 | T58: 4116967.8 | U58: 4074971 | V58: 4032974.2 | W58: 3990977.4
B59: Minus : Depreciation | F59: 1886070.8 | G59: 1886070.8 | H59: 1886070.8 | I59: 1886070.8 | J59: 1886070.8 | K59: 1886070.8 | L59: 1886070.8 | M59: 1886070.8 | N59: 1886070.8 | O59: 1886070.8 | P59: 1886070.8 | Q59: 1886070.8 | R59: 1886070.8 | S59: 1886070.8 | T59: 1886070.8 | U59: 1886070.8 | V59: 1886070.8 | W59: 1886070.8
B60: Plus : Principle payment | F60: 0 | G60: 0 | H60: 0 | I60: 0 | J60: 0 | K60: 0 | L60: 0 | M60: 0 | N60: 0 | O60: 0 | P60: 0 | Q60: 0 | R60: 0 | S60: 0 | T60: 0 | U60: 0 | V60: 0 | W60: 0
B61: Profit | F61: 2879653.3 | G61: 2829507.9 | H61: 2779362.5 | I61: 2729217 | J61: 2679071.6 | K61: 2631433.5 | L61: 2583795.3 | M61: 2536157.2 | N61: 2488519 | O61: 2440880.9 | P61: 2398884.1 | Q61: 2356887.3 | R61: 2314890.5 | S61: 2272893.8 | T61: 2230897 | U61: 2188900.2 | V61: 2146903.4 | W61: 2104906.6
B62: EPS | F62: 0.76340009 | G62: 0.75010647 | H62: 0.73681286 | I62: 0.72351924 | J62: 0.71022562 | K62: 0.69759668 | L62: 0.68496774 | M62: 0.6723388 | N62: 0.65970986 | O62: 0.64708093 | P62: 0.63594752 | Q62: 0.62481411 | R62: 0.61368071 | S62: 0.6025473 | T62: 0.59141389 | U62: 0.58028049 | V62: 0.56914708 | W62: 0.55801368
B63: 回收年限評估 | D63: =IF((D57)>0,"回收","未回收") | E63: =IF((E57)>0,"回收","未回收") | F63: =IF((F57)>0,"回收","未回收") | G63: =IF((G57)>0,"回收","未回收") | H63: =IF((H57)>0,"回收","未回收") | I63: =IF((I57)>0,"回收","未回收") | J63: =IF((J57)>0,"回收","未回收") | K63: =IF((K57)>0,"回收","未回收") | ... W63: =IF((W57)>0,"回收","未回收")
L65: 預估可建置量 | M65: 0
L66: 預估可建置量 | M66: 0
C67: 年份 | D67: 2020 | E67: 2021 | F67: 2022 | G67: 2023 | H67: 2024 | I67: 2025 | J67: 2026 | K67: 2027 | L67: 2028 | M67: 2029 | N67: 2030 | O67: 2031 | P67: 2032 | Q67: 2033 | R67: 2034 | S67: 2035 | T67: 2036 | U67: 2037 | V67: 2038 | W67: 2039
B69: (Unit : Currency) | C69: 0 | D69: 1 | E69: 2 | F69: 3 | G69: 4 | H69: 5 | I69: 6 | J69: 7 | K69: 8 | L69: 9 | M69: 10 | N69: 11 | O69: 12 | P69: 13 | Q69: 14 | R69: 15 | S69: 16 | T69: 17 | U69: 18 | V69: 19 | W69: 20
B70: 稅後淨利 | D70: =#REF! | E70: =#REF! | F70: =#REF! | G70: =#REF! | H70: =#REF! | I70: =#REF! | J70: =#REF! | K70: =#REF! | ... W70: =#REF!
B71: 設備折舊 | D71: =-#REF! | E71: =-#REF! | F71: =-#REF! | G71: =-#REF! | H71: =-#REF! | I71: =-#REF! | J71: =-#REF! | K71: =-#REF! | ... W71: =-#REF!
B72: 營運活動現金流量 | D72: =SUM(D70:D71) | E72: =SUM(E70:E71) | F72: =SUM(F70:F71) | G72: =SUM(G70:G71) | H72: =SUM(H70:H71) | I72: =SUM(I70:I71) | J72: =SUM(J70:J71) | K72: =SUM(K70:K71) | ... W72: =SUM(W70:W71)
B74: 投資活動-設備支出 | D74: =C44 | E74: 0 | G74: 0 | H74: 0 | I74: 0 | J74: 0 | K74: 0 | L74: 0 | M74: 0 | N74: 0 | O74: 0 | P74: 0 | Q74: 0 | R74: 0 | S74: 0 | T74: 0 | U74: 0 | V74: 0 | W74: 0
B77: 理財活動-借款 | D77: =#REF!*0.8 | G77: 0 | H77: 0 | I77: 0 | J77: 0 | K77: 0 | L77: 0 | M77: 0 | N77: 0 | O77: 0 | P77: 0 | Q77: 0 | R77: 0 | S77: 0 | T77: 0 | U77: 0 | V77: 0 | W77: 0
B78: 理財活動-還款 | E78: =-#REF! | F78: =-#REF! | G78: =-#REF! | H78: =-#REF! | I78: =-#REF! | J78: =-#REF! | K78: =-#REF! | L78: =-#REF! | ... S78: =-#REF!
B79: 理財活動-現金增資 | D79: =#REF!*0.2
B80: 現金股利 | E80: =-D70*0.9 | F80: =-E70*0.9 | G80: =-F70*0.9 | H80: =-G70*0.9 | I80: =-H70*0.9 | J80: =-I70*0.9 | K80: =-J70*0.9 | L80: =-K70*0.9 | ... U80: =-T70*0.9 | W80: =-V70*0.9
B81: 年底減資 | R81: =-$D$79/4 | S81: =-$D$79/4 | T81: =-$D$79/4 | U81: =-$D$79/4
B84: 現金淨流入(出 ) | C84: =SUM(C74:C83) | D84: =SUM(D72:D83) | E84: =SUM(E72:E83) | F84: =SUM(F72:F83) | G84: =SUM(G72:G83) | H84: =SUM(H72:H83) | I84: =SUM(I72:I83) | J84: =SUM(J72:J83) | K84: =SUM(K72:K83) | ... W84: =SUM(W72:W83)
B85: 期初淨現金 | C85: 0 | D85: =C86 | E85: =D86 | F85: =E86 | G85: =F86 | H85: =G86 | I85: =H86 | J85: =I86 | K85: =J86 | ... U85: =T86
B86: 期未淨現金 | C86: =C84 | D86: =D84+D85 | E86: =E84+E85 | F86: =F84+F85 | G86: =G84+G85 | H86: =H84+H85 | I86: =I84+I85 | J86: =J84+J85 | K86: =K84+K85 | ... U86: =U84+U85
B89: 成本法實際現金流 | D89: =-D79 | E89: =-E80-E81 | F89: =-F80-F81 | G89: =-G80-G81 | H89: =-H80-H81 | I89: =-I80-I81 | J89: =-J80-J81 | K89: =-K80-K81 | L89: =-L80-L81 | ... W89: =-W80-W81
B90: 成本法IRR | C90: =IRR(D89:W89)
B91: 權益法實際現金流 | D91: =#REF!-D79 | E91: =#REF! | F91: =#REF!-F81 | G91: =#REF!-G81 | H91: =#REF!-H81 | I91: =#REF!-I81 | J91: =#REF!-J81 | K91: =#REF!-K81 | L91: =#REF!-L81 | M91: =#REF!-M81 | ... W91: =#REF!-W81
B92: 權益法IRR | C92: =IRR(D91:W91)
B94: 借款餘額 | C94: 0 | D94: =D77 | E94: =D94+E77+E78 | F94: =E94+F77+F78 | G94: =F94+G77+G78 | H94: =G94+H77+H78 | I94: =H94+I77+I78 | J94: =I94+J77+J78 | K94: =J94+K77+K78 | L94: =K94+L77+L78 | ... S94: =R94+S77+S78

Sheet IRR (保守3%)
B2: 重資打包賣價 | C2: =Z28
C4: 年份 | D4: 2020 | E4: 2021 | F4: 2022 | G4: 2023 | H4: 2024 | I4: 2025 | J4: 2026 | K4: 2027 | L4: 2028 | M4: 2029 | N4: 2030 | O4: 2031 | P4: 2032 | Q4: 2033 | R4: 2034 | S4: 2035 | T4: 2036 | U4: 2037 | V4: 2038 | W4: 2039
B5: 案場名 | C5: 預估發電度數 | AD5: 發電度數
B6: =#REF! | D6: =#REF! | E6: =#REF! | F6: =#REF! | G6: =#REF! | H6: =#REF! | I6: =#REF! | J6: =#REF! | K6: =#REF! | ... W6: =#REF! | Z6: =SUM(D6:Y6) | AD6: 賣價
C7: 發電度數 總計 | D7: =SUM(D6:D6) | E7: =SUM(E6:E6) | F7: =SUM(F6:F6) | G7: =SUM(G6:G6) | H7: =SUM(H6:H6) | I7: =SUM(I6:I6) | J7: =SUM(J6:J6) | K7: =SUM(K6:K6) | ... X7: =SUM(X6:X6) | Z7: =SUM(D7:Y7) | AA7: =IF(ROUND((#REF!-'IRR (保守3%)'!Z7),0)=0,"correct", "error")
B8: 案場名 | C8: 預估收入 | D8: 2020 | E8: 2021 | F8: 2022 | G8: 2023 | H8: 2024 | I8: 2025 | J8: 2026 | K8: 2027 | L8: 2028 | M8: 2029 | N8: 2030 | O8: 2031 | P8: 2032 | Q8: 2033 | R8: 2034 | S8: 2035 | T8: 2036 | U8: 2037 | V8: 2038 | W8: 2039 | X8: 2040
B9: =#REF! | D9: =#REF! | E9: =#REF! | F9: =#REF! | G9: =#REF! | H9: =#REF! | I9: =#REF! | J9: =#REF! | K9: =#REF! | ... W9: =#REF! | Z9: =SUM(D9:Y9)
C10: 預估收入 總計 | D10: =SUM(D9:D9) | E10: =SUM(E9:E9) | F10: =SUM(F9:F9) | G10: =SUM(G9:G9) | H10: =SUM(H9:H9) | I10: =SUM(I9:I9) | J10: =SUM(J9:J9) | K10: =SUM(K9:K9) | ... X10: =SUM(X9:X9) | Z10: =SUM(D10:Y10) | AA10: =IF(ROUND((#REF!-'IRR (保守3%)'!Z10),0)=0,"correct", "error")
B11: 案場名 | C11: 租金/年 | D11: 2020 | E11: 2021 | F11: 2022 | G11: 2023 | H11: 2024 | I11: 2025 | J11: 2026 | K11: 2027 | L11: 2028 | M11: 2029 | N11: 2030 | O11: 2031 | P11: 2032 | Q11: 2033 | R11: 2034 | S11: 2035 | T11: 2036 | U11: 2037 | V11: 2038 | W11: 2039 | X11: 2040
B12: =#REF! | D12: =#REF! | E12: =#REF! | F12: =#REF! | G12: =#REF! | H12: =#REF! | I12: =#REF! | J12: =#REF! | K12: =#REF! | ... W12: =#REF! | Z12: =SUM(D12:Y12)
C13: 租金/年 總計 | D13: =SUM(D12:D12) | E13: =SUM(E12:E12) | F13: =SUM(F12:F12) | G13: =SUM(G12:G12) | H13: =SUM(H12:H12) | I13: =SUM(I12:I12) | J13: =SUM(J12:J12) | K13: =SUM(K12:K12) | ... X13: =SUM(X12:X12) | Z13: =SUM(D13:Y13) | AA13: =IF(ROUND((#REF!-'IRR (保守3%)'!Z13),0)=0,"correct", "error")
B14: 案場名 | C14: 運維/年 | D14: 2020 | E14: 2021 | F14: 2022 | G14: 2023 | H14: 2024 | I14: 2025 | J14: 2026 | K14: 2027 | L14: 2028 | M14: 2029 | N14: 2030 | O14: 2031 | P14: 2032 | Q14: 2033 | R14: 2034 | S14: 2035 | T14: 2036 | U14: 2037 | V14: 2038 | W14: 2039 | X14: 2040
B15: =#REF! | D15: =#REF! | E15: =#REF! | F15: =#REF! | G15: =#REF! | H15: =#REF! | I15: =#REF! | J15: =#REF! | K15: =#REF! | ... W15: =#REF! | Z15: =SUM(D15:Y15)
C16: 運維/年 總計 | D16: =SUM(D15:D15) | E16: =SUM(E15:E15) | F16: =SUM(F15:F15) | G16: =SUM(G15:G15) | H16: =SUM(H15:H15) | I16: =SUM(I15:I15) | J16: =SUM(J15:J15) | K16: =SUM(K15:K15) | ... X16: =SUM(X15:X15) | Z16: =SUM(D16:Y16) | AA16: =IF(ROUND((#REF!-'IRR (保守3%)'!Z16),0)=0,"correct", "error")
B17: 案場名 | C17: 保險/年 | D17: 2020 | E17: 2021 | F17: 2022 | G17: 2023 | H17: 2024 | I17: 2025 | J17: 2026 | K17: 2027 | L17: 2028 | M17: 2029 | N17: 2030 | O17: 2031 | P17: 2032 | Q17: 2033 | R17: 2034 | S17: 2035 | T17: 2036 | U17: 2037 | V17: 2038 | W17: 2039 | X17: 2040
B18: =#REF! | D18: =#REF! | E18: =#REF! | F18: =#REF! | G18: =#REF! | H18: =#REF! | I18: =#REF! | J18: =#REF! | K18: =#REF! | ... W18: =#REF! | Z18: =SUM(D18:Y18)
C19: 保險/年 總計 | D19: =SUM(D18:D18) | E19: =SUM(E18:E18) | F19: =SUM(F18:F18) | G19: =SUM(G18:G18) | H19: =SUM(H18:H18) | I19: =SUM(I18:I18) | J19: =SUM(J18:J18) | K19: =SUM(K18:K18) | ... X19: =SUM(X18:X18) | Z19: =SUM(D19:Y19) | AA19: =IF(ROUND((#REF!-'IRR (保守3%)'!Z19),0)=0,"correct", "error")
B20: 案場名 | C20: 模組回收費/年 | D20: 2020 | E20: 2021 | F20: 2022 | G20: 2023 | H20: 2024 | I20: 2025 | J20: 2026 | K20: 2027 | L20: 2028 | M20: 2029 | N20: 2030 | O20: 2031 | P20: 2032 | Q20: 2033 | R20: 2034 | S20: 2035 | T20: 2036 | U20: 2037 | V20: 2038 | W20: 2039 | X20: 2040
B21: =#REF! | D21: =#REF! | E21: =#REF! | F21: =#REF! | G21: =#REF! | H21: =#REF! | I21: =#REF! | J21: =#REF! | K21: =#REF! | ... W21: =#REF! | Z21: =SUM(D21:Y21)
C22: 模組回收費/年 總計 | D22: =SUM(D21:D21) | E22: =SUM(E21:E21) | F22: =SUM(F21:F21) | G22: =SUM(G21:G21) | H22: =SUM(H21:H21) | I22: =SUM(I21:I21) | J22: =SUM(J21:J21) | K22: =SUM(K21:K21) | ... X22: =SUM(X21:X21) | Z22: =SUM(D22:Y22) | AA22: =IF(ROUND((#REF!-'IRR (保守3%)'!Z22),0)=0,"correct", "error")
B23: 案場名 | C23: 所得稅/年 | D23: 2020 | E23: 2021 | F23: 2022 | G23: 2023 | H23: 2024 | I23: 2025 | J23: 2026 | K23: 2027 | L23: 2028 | M23: 2029 | N23: 2030 | O23: 2031 | P23: 2032 | Q23: 2033 | R23: 2034 | S23: 2035 | T23: 2036 | U23: 2037 | V23: 2038 | W23: 2039 | X23: 2040
B24: =#REF! | D24: =#REF! | E24: =#REF! | F24: =#REF! | G24: =#REF! | H24: =#REF! | I24: =#REF! | J24: =#REF! | K24: =#REF! | ... W24: =#REF! | Z24: =SUM(D24:Y24)
C25: 所得稅/年 總計 | D25: =SUM(D24:D24) | E25: =SUM(E24:E24) | F25: =SUM(F24:F24) | G25: =SUM(G24:G24) | H25: =SUM(H24:H24) | I25: =SUM(I24:I24) | J25: =SUM(J24:J24) | K25: =SUM(K24:K24) | ... X25: =SUM(X24:X24) | Z25: =SUM(D25:Y25) | AA25: =IF(ROUND((#REF!-'IRR (保守3%)'!Z25),0)=0,"correct", "error")
B26: 案場名 | C26: 設備折舊/年 | D26: 2020 | E26: 2021 | F26: 2022 | G26: 2023 | H26: 2024 | I26: 2025 | J26: 2026 | K26: 2027 | L26: 2028 | M26: 2029 | N26: 2030 | O26: 2031 | P26: 2032 | Q26: 2033 | R26: 2034 | S26: 2035 | T26: 2036 | U26: 2037 | V26: 2038 | W26: 2039 | X26: 2040
B27: =#REF! | D27: =#REF! | E27: =#REF! | F27: =#REF! | G27: =#REF! | H27: =#REF! | I27: =#REF! | J27: =#REF! | K27: =#REF! | ... W27: =#REF! | Z27: =SUM(D27:Y27) | AA27: =IF(ROUND((Z27-#REF!),0)=0,"correct", "error")
C28: 設備折舊/年 總計 | D28: =SUM(D27:D27) | E28: =SUM(E27:E27) | F28: =SUM(F27:F27) | G28: =SUM(G27:G27) | H28: =SUM(H27:H27) | I28: =SUM(I27:I27) | J28: =SUM(J27:J27) | K28: =SUM(K27:K27) | ... X28: =SUM(X27:X27) | Z28: =SUM(D28:Y28) | AA28: =IF(ROUND((#REF!-'IRR (保守3%)'!Z28),0)=0,"correct", "error")
C30: 年份 | D30: 2020 | E30: 2021 | F30: 2022 | G30: 2023 | H30: 2024 | I30: 2025 | J30: 2026 | K30: 2027 | L30: 2028 | M30: 2029 | N30: 2030 | O30: 2031 | P30: 2032 | Q30: 2033 | R30: 2034 | S30: 2035 | T30: 2036 | U30: 2037 | V30: 2038 | W30: 2039
B31: 0 | F31: 手動計算值 | T31: 償還年限
B32: (Unit : Currency) | C32: 0 | D32: 1 | E32: 2 | F32: 3 | G32: 4 | H32: 5 | I32: 6 | J32: 7 | K32: 8 | L32: 9 | M32: 10 | N32: 11 | O32: 12 | P32: 13 | Q32: 14 | R32: 15 | S32: 16 | T32: 17 | U32: 18 | V32: 19 | W32: 20
B33: 發電度數(KWH) | C33: 0 | D33: =D7 | E33: =E7 | F33: =F7 | G33: =G7 | H33: =H7 | I33: =I7 | J33: =J7 | K33: =K7 | ... X33: =X7 | Z33: =SUM(D33:Y33) | AA33: =IF(ROUND((Z33-Z7),0)=0,"correct", "error")
B34: Inflow : 電費收入 | C34: - | D34: =D10 | E34: =E10 | F34: =F10 | G34: =G10 | H34: =H10 | I34: =I10 | J34: =J10 | K34: =K10 | ... X34: =X10 | Z34: =SUM(D34:Y34) | AA34: =IF(ROUND((Z34-Z10),0)=0,"correct", "error")
B35: Inflow : 政府補助 | C35: - | F35: 0 | G35: - | H35: - | I35: - | J35: - | K35: - | L35: - | M35: - | N35: - | O35: - | P35: - | Q35: - | R35: - | S35: - | T35: - | U35: - | V35: - | W35: -
B36: Inflow : 銀行借款
B37: Outflow : 設備費用 | C37: =-C2 | F37: - | G37: - | H37: - | I37: - | J37: - | K37: - | L37: - | M37: - | N37: - | O37: - | P37: - | Q37: - | R37: - | S37: - | T37: - | U37: - | V37: - | W37: -
B38: Outflow : 設備放置區域租金 | C38: - | D38: =-D13 | E38: =-E13 | F38: =-F13 | G38: =-G13 | H38: =-H13 | I38: =-I13 | J38: =-J13 | K38: =-K13 | ... X38: =-X13 | Z38: =SUM(D38:Y38) | AA38: =IF(ROUND((Z38+Z13),0)=0,"correct", "error")
B39: Outflow : 返還借款 | C39: 0 | V39: 0 | W39: 0 | Z39: =SUM(D39:Y39)
B40: Outflow : 利息費用 | C40: - | Z40: =SUM(D40:Y40)
B41: Outflow : 維運費 | C41: - | D41: =-D16 | E41: =-E16 | F41: =-F16 | G41: =-G16 | H41: =-H16 | I41: =-I16 | J41: =-J16 | K41: =-K16 | ... X41: =-X16 | Z41: =SUM(D41:Y41) | AA41: =IF(ROUND((Z41+Z16),0)=0,"correct", "error")
B42: Outflow : 保險費 | C42: - | D42: =-D19 | E42: =-E19 | F42: =-F19 | G42: =-G19 | H42: =-H19 | I42: =-I19 | J42: =-J19 | K42: =-K19 | ... X42: =-X19 | Z42: =SUM(D42:Y42) | AA42: =IF(ROUND((Z42+Z19),0)=0,"correct", "error")
B43: Outflow : 模組回收費 | D43: =-D22 | E43: =-E22 | F43: =-F22 | G43: =-G22 | H43: =-H22 | I43: =-I22 | J43: =-J22 | K43: =-K22 | ... X43: =-X22 | Z43: =SUM(D43:Y43) | AA43: =IF(ROUND((Z22+Z43),0)=0,"correct", "error")
B44: Outflow : 其它費用(人事薪資…等) | F44: =-(F34*$D$131) | G44: =-(G34*$D$131) | H44: =-(H34*$D$131) | I44: =-(I34*$D$131) | J44: =-(J34*$D$131) | K44: =-(K34*$D$131) | L44: =-(L34*$D$131) | M44: =-(M34*$D$131) | ... X44: =-(X34*$D$131) | Z44: =SUM(D44:Y44)
B45: 1%管理費 | Z45: =SUM(D45:Y45)
B46: 績效獎金 | Z46: =SUM(D46:Y46)
B47: 所得稅20% | D47: =IF((D88+SUM(D90+D91+D94+D95+D96+D97))>0,-(D88+SUM(D90+D91+D94+D95+D96+D97))*0.2,0) | E47: =IF((E88+SUM(E90+E91+E94+E95+E96+E97))>0,-(E88+SUM(E90+E91+E94+E95+E96+E97))*0.2,0) | F47: =IF((F88+SUM(F90+F91+F94+F95+F96+F97))>0,-(F88+SUM(F90+F91+F94+F95+F96+F97))*0.2,0) | G47: =IF((G88+SUM(G90+G91+G94+G95+G96+G97))>0,-(G88+SUM(G90+G91+G94+G95+G96+G97))*0.2,0) | H47: =IF((H88+SUM(H90+H91+H94+H95+H96+H97))>0,-(H88+SUM(H90+H91+H94+H95+H96+H97))*0.2,0) | I47: =IF((I88+SUM(I90+I91+I94+I95+I96+I97))>0,-(I88+SUM(I90+I91+I94+I95+I96+I97))*0.2,0) | J47: =IF((J88+SUM(J90+J91+J94+J95+J96+J97))>0,-(J88+SUM(J90+J91+J94+J95+J96+J97))*0.2,0) | K47: =IF((K88+SUM(K90+K91+K94+K95+K96+K97))>0,-(K88+SUM(K90+K91+K94+K95+K96+K97))*0.2,0) | ... X47: =IF((X88+SUM(X90+X91+X94+X95+X96+X97))>0,-(X88+SUM(X90+X91+X94+X95+X96+X97))*0.2,0) | Z47: =SUM(D47:Y47) | AA47: =IF(ROUND((Z47+Z25),0)=0,"correct", "error")
Z48: =SUM(D48:Y48)
B49: 現金流 | C49: =C37 | D49: =SUM(D34:D47) | E49: =SUM(E34:E47) | F49: =SUM(F34:F47) | G49: =SUM(G34:G47) | H49: =SUM(H34:H47) | I49: =SUM(I34:I47) | J49: =SUM(J34:J47) | K49: =SUM(K34:K47) | ... X49: =SUM(X34:X47) | Z49: =SUM(C49:Y49)
B50: 累計現金流 | D50: =D49+C49 | E50: =E49+D50 | F50: =F49+E50 | G50: =G49+F50 | H50: =H49+G50 | I50: =I49+H50 | J50: =J49+I50 | K50: =K49+J50 | L50: =L49+K50 | ... W50: =W49+V50 | Z50: =IF(ROUND((Z49-W50),0)=0,"correct", "error")
B51: Discounted cash flow | C51: -37721416 | F51: 4765724.1 | G51: 4715578.7 | H51: 4665433.3 | I51: 4615287.9 | J51: 4565142.4 | K51: 4517504.3 | L51: 4469866.2 | M51: 4422228 | N51: 4374589.9 | O51: 4326951.7 | P51: 4284954.9 | Q51: 4242958.2 | R51: 4200961.4 | S51: 4158964.6 | T51: 4116967.8 | U51: 4074971 | V51: 4032974.2 | W51: 3990977.4
B52: Minus : Depreciation | F52: 1886070.8 | G52: 1886070.8 | H52: 1886070.8 | I52: 1886070.8 | J52: 1886070.8 | K52: 1886070.8 | L52: 1886070.8 | M52: 1886070.8 | N52: 1886070.8 | O52: 1886070.8 | P52: 1886070.8 | Q52: 1886070.8 | R52: 1886070.8 | S52: 1886070.8 | T52: 1886070.8 | U52: 1886070.8 | V52: 1886070.8 | W52: 1886070.8
B53: Plus : Principle payment | F53: 0 | G53: 0 | H53: 0 | I53: 0 | J53: 0 | K53: 0 | L53: 0 | M53: 0 | N53: 0 | O53: 0 | P53: 0 | Q53: 0 | R53: 0 | S53: 0 | T53: 0 | U53: 0 | V53: 0 | W53: 0
B54: Profit | F54: 2879653.3 | G54: 2829507.9 | H54: 2779362.5 | I54: 2729217 | J54: 2679071.6 | K54: 2631433.5 | L54: 2583795.3 | M54: 2536157.2 | N54: 2488519 | O54: 2440880.9 | P54: 2398884.1 | Q54: 2356887.3 | R54: 2314890.5 | S54: 2272893.8 | T54: 2230897 | U54: 2188900.2 | V54: 2146903.4 | W54: 2104906.6
B55: EPS | F55: 0.76340009 | G55: 0.75010647 | H55: 0.73681286 | I55: 0.72351924 | J55: 0.71022562 | K55: 0.69759668 | L55: 0.68496774 | M55: 0.6723388 | N55: 0.65970986 | O55: 0.64708093 | P55: 0.63594752 | Q55: 0.62481411 | R55: 0.61368071 | S55: 0.6025473 | T55: 0.59141389 | U55: 0.58028049 | V55: 0.56914708 | W55: 0.55801368
B56: 回收年限評估 | D56: =IF((D50)>0,"回收","未回收") | E56: =IF((E50)>0,"回收","未回收") | F56: =IF((F50)>0,"回收","未回收") | G56: =IF((G50)>0,"回收","未回收") | H56: =IF((H50)>0,"回收","未回收") | I56: =IF((I50)>0,"回收","未回收") | J56: =IF((J50)>0,"回收","未回收") | K56: =IF((K50)>0,"回收","未回收") | ... W56: =IF((W50)>0,"回收","未回收")
L58: 預估可建置量 | M58: 0
L59: 預估可建置量 | M59: 0
L60: 總計 | M60: =M58+M59
B62: Assumption | D62: NOTE | J62: 管理費，1%of 股本 | L62: 假設自有資本(億) | N62: =D159/100000000 | AC62: 申辦期間一甲地租金 | AG62: 100000
B63: 預計系統完工年限 | C63: 109年 | D63: #REF! | J63: 績效獎金 | L63: 貸款(億) | N63: =D157/100000000 | AH63: 申辦期預抓2年土租 | AK63: 20
B64: 政府每度收購價格 | C64: 4.1733 | D64: 109下半年 地面型併高壓費率(高效模組) | J64: 權益法下IRR | L64: XX年攤還 (有錢就還) | AC64: 平方公尺 | AD64: 甲 | AE64: 公頃 | AF64: 分 | AG64: 申辦期 租金/甲/年 | AH64: 2 | AI64: 每年租金/分 (單價) | AJ64: 掛錶後 每年租金/分 | AK64: 20年土地租金 | AL64: 饋線 途經 國有財產地20年租金預抓
B65: 安裝容量(KW) | C65: =#REF! | J65: 現金流IRR | AB65: 地號學甲寮 283,82-83-84 三筆 | AC65: 10259 | AD65: 1.05668 | AE65: 1.0259 | AF65: 10.56677 | AG65: 105668 | AH65: 211336 | AI65: 35000 | AJ65: 369836.95 | AK65: 7396739
B66: 每KW系統價格(NTD/KW) -未稅 | C66: 0 | D66: 調整前價格 (恆映 開發費用4000/kW 測算) | AB66: 地號學甲寮 283,40-55-58 三筆 | AC66: 11113 | AD66: 1.14464 | AE66: 1.1113 | AF66: 11.44639 | AG66: 114464 | AH66: 228928 | AI66: 30000 | AJ66: 343391.7 | AK66: 6867834
B67: 總建構成本(NTD) | C67: 0 | AB67: 其餘地號都屬 翁秀正, 李雅婷 | AC67: 154742 | AD67: 15.93843 | AE67: 15.4742 | AF67: 159.38426 | AG67: 1593843 | AH67: 3187686 | AI67: 40000 | AJ67: 6375370.4 | AK67: 127507408 | AM67: 20年土地總租金(含國有財產地)
B68: 政府補助(NTD/案) | C68: 0 | AB68: 總計 | AC68: 176114 | AD68: 18.13975 | AE68: 17.6114 | AG68: 1813975 | AH68: 3627950 | AJ68: 7088599.1 | AK68: 141771981 | AL68: 2000000
B69: 貸款金額(NTD) | C69: 0 | D69: 0 | E69: 貸款成數 | K69: 20年 | L69: 前2年 開發期 每年租金 | AH69: 土地界址鑑定合計
B70: 償還年限 | C70: 15 | D70: (本息平均)償還法 | H70: 有錢就還 | J70: 租金(依各地主條件) | K70: - | AB70: a.土地界址鑑定規費 : 17公頃 *$ 4,000 + 0.6114公頃 - 以 $2,000計 , 合計: $70,000元 | AH70: 75000
B71: 銀行利率(%) | C71: 0.03 | J71: 保險 | K71: 0 | AB71: b.地政事務所陪同鑑界費用 : 因土地面積龐大 , 每筆土地收費$5,000元(初估)
B72: 設備放置區域年租金(NTD) | C72: 0 | D72: 各地主租金總合+饋線途經國有財產地6公里租金 | E72: ; 租 | F72: 20 | G72: 年
B73: 維運費(NTD) | C73: 0 | D73: 400/kw | E73: ; 保固共 | F73: 20 | G73: 年 | I73: 1KW | J73: 運維20年 | N73: 金額 | O73: 備註
B74: 保險費(NTD) | C74: 0 | D74: 0.003 | E74: ; 保險共 | F74: 20 | G74: 年 | I74: 400 | J74: 0 | M74: 模組回收(kw) | N74: 1000 | O74: 分10年攤提
B75: 模組回收費(NTD) | C75: 0 | D75: 分10年攤提 | E75: ; 攤提共 | F75: 10 | G75: 年 | I75: 300 | J75: 0 | M75: 0
B76: 初始資金需求 | C76: 0 | D76: 原始資金需求 | I76: 200 | J76: 0
B77: 折扣率(%) | C77: 0 | D77: 競標型 | I77: 100 | J77: 0
B78: 高效加成%
B79: 最終躉售費率
B80: Internal Rate of Return; IRR (%) | C80: =IRR(C49:X49)
C84: 年份 | D84: 2020 | E84: 2021 | F84: 2022 | G84: 2023 | H84: 2024 | I84: 2025 | J84: 2026 | K84: 2027 | L84: 2028 | M84: 2029 | N84: 2030 | O84: 2031 | P84: 2032 | Q84: 2033 | R84: 2034 | S84: 2035 | T84: 2036 | U84: 2037 | V84: 2038 | W84: 2039
B85: =C120 | F85: 手動計算值 | T85: 償還年限
B86: (Unit : Currency) | C86: 0 | D86: 1 | E86: 2 | F86: 3 | G86: 4 | H86: 5 | I86: 6 | J86: 7 | K86: 8 | L86: 9 | M86: 10 | N86: 11 | O86: 12 | P86: 13 | Q86: 14 | R86: 15 | S86: 16 | T86: 17 | U86: 18 | V86: 19 | W86: 20
B87: 發電度數(KWH) | C87: 0 | D87: =D33 | E87: =E33 | F87: =F33 | G87: =G33 | H87: =H33 | I87: =I33 | J87: =J33 | K87: =K33 | ... X87: =X33 | Z87: =SUM(D87:Y87)
B88: 電費收入 | C88: - | D88: =D10 | E88: =E10 | F88: =F10 | G88: =G10 | H88: =H10 | I88: =I10 | J88: =J10 | K88: =K10 | ... X88: =X10 | Z88: =SUM(D88:Y88)
B89: 政府補助 | C89: - | Z89: =SUM(D89:Y89)
B90: : 設備折舊 | C90: - | D90: =-D28 | E90: =-E28 | F90: =-F28 | G90: =-G28 | H90: =-H28 | I90: =-I28 | J90: =-J28 | K90: =-K28 | ... X90: =-X28 | Z90: =SUM(D90:Y90)
B91: : 設備放置區域租金 | C91: - | D91: =D38 | E91: =E38 | F91: =F38 | G91: =G38 | H91: =H38 | I91: =I38 | J91: =J38 | K91: =K38 | ... X91: =X38 | Z91: =SUM(D91:Y91)
C92: - | F92: - | G92: - | H92: - | I92: - | J92: - | K92: - | L92: - | M92: - | N92: - | O92: - | P92: - | Q92: - | R92: - | S92: - | T92: - | U92: - | V92: - | W92: - | Z92: =SUM(D92:Y92)
B93: : 利息費用 | C93: - | D93: =-D174*$C$126 | E93: =-E174*$C$126 | F93: =-F174*$C$126 | G93: =-G174*$C$126 | H93: =-H174*$C$126 | I93: =-I174*$C$126 | J93: =-J174*$C$126 | K93: =-K174*$C$126 | ... X93: =-X174*$C$126 | Z93: =SUM(D93:Y93)
B94: : 維運費 | C94: - | D94: =D41 | E94: =E41 | F94: =F41 | G94: =G41 | H94: =H41 | I94: =I41 | J94: =J41 | K94: =K41 | ... X94: =X41 | Z94: =SUM(D94:Y94)
B95: : 保險費 | C95: - | D95: =D42 | E95: =E42 | F95: =F42 | G95: =G42 | H95: =H42 | I95: =I42 | J95: =J42 | K95: =K42 | ... X95: =X42 | Z95: =SUM(D95:Y95)
B96: : 模組回收費 | D96: =D43 | E96: =E43 | F96: =F43 | G96: =G43 | H96: =H43 | I96: =I43 | J96: =J43 | K96: =K43 | ... X96: =X43 | Z96: =SUM(D96:Y96)
B97: : 其它費用(人事薪資…等) | C97: - | F97: =-(F88*$D$131) | G97: =-(G88*$D$131) | H97: =-(H88*$D$131) | I97: =-(I88*$D$131) | J97: =-(J88*$D$131) | K97: =-(K88*$D$131) | L97: =-(L88*$D$131) | M97: =-(M88*$D$131) | ... W97: =-(W88*$D$131) | Z97: =SUM(D97:Y97)
B98: 1%管理費 | D98: =-D159*0.01 | E98: =(D98/0.01-D161)*0.01 | F98: =(E98/0.01-E161)*0.01 | G98: =(F98/0.01-F161)*0.01 | H98: =(G98/0.01-G161)*0.01 | I98: =(H98/0.01-H161)*0.01 | J98: =(I98/0.01-I161)*0.01 | K98: =(J98/0.01-J161)*0.01 | L98: =(K98/0.01-K161)*0.01 | ... W98: =(V98/0.01-V161)*0.01 | Z98: =SUM(D98:Y98)
B99: 績效獎金 | E99: =-IF((SUM(E88:E98)/(-D98/0.1))>0.5,(SUM(E88:E98)*0.8+((D98/0.01-D161)*0.05))*0.2, 0) | F99: =-IF((SUM(F88:F98)/(-E98/0.1))>0.5,(SUM(F88:F98)*0.8+((E98/0.01-E161)*0.05))*0.2, 0) | G99: =-IF((SUM(G88:G98)/(-F98/0.1))>0.5,(SUM(G88:G98)*0.8+((F98/0.01-F161)*0.05))*0.2, 0) | H99: =-IF((SUM(H88:H98)/(-G98/0.1))>0.5,(SUM(H88:H98)*0.8+((G98/0.01-G161)*0.05))*0.2, 0) | I99: =-IF((SUM(I88:I98)/(-H98/0.1))>0.5,(SUM(I88:I98)*0.8+((H98/0.01-H161)*0.05))*0.2, 0) | J99: =-IF((SUM(J88:J98)/(-I98/0.1))>0.5,(SUM(J88:J98)*0.8+((I98/0.01-I161)*0.05))*0.2, 0) | K99: =-IF((SUM(K88:K98)/(-J98/0.1))>0.5,(SUM(K88:K98)*0.8+((J98/0.01-J161)*0.05))*0.2, 0) | L99: =-IF((SUM(L88:L98)/(-K98/0.1))>0.5,(SUM(L88:L98)*0.8+((K98/0.01-K161)*0.05))*0.2, 0) | ... X99: =-IF((SUM(X88:X98)/(-W98/0.1))>0.5,(SUM(X88:X98)*0.8+((W98/0.01-W161)*0.05))*0.2, 0) | Z99: =SUM(D99:Y99)
B100: 稅前淨利 | C100: 0 | D100: =SUM(D88:D99) | E100: =SUM(E88:E99) | F100: =SUM(F88:F99) | G100: =SUM(G88:G99) | H100: =SUM(H88:H99) | I100: =SUM(I88:I99) | J100: =SUM(J88:J99) | K100: =SUM(K88:K99) | ... X100: =SUM(X88:X99) | Z100: =SUM(D100:Y100)
B101: Outflow : 所得稅(20%) | C101: - | D101: =-D100*0.2 | E101: =-E100*0.2 | F101: =-F100*0.2 | G101: =-(G100*$D$132) | H101: =-(H100*$D$132) | I101: =-(I100*$D$132) | J101: =-(J100*$D$132) | K101: =-(K100*$D$132) | L101: =-(L100*$D$132) | M101: =-(M100*$D$132) | N101: =-(N100*$D$132) | ... X101: =-(X100*$D$132) | Z101: =SUM(F101:Y101)
B102: 稅後淨利 | D102: =SUM(D100:D101) | E102: =SUM(E100:E101) | F102: =SUM(F100:F101) | G102: =SUM(G100:G101) | H102: =SUM(H100:H101) | I102: =SUM(I100:I101) | J102: =SUM(J100:J101) | K102: =SUM(K100:K101) | ... X102: =SUM(X100:X101) | Z102: =SUM(D102:Y102) | AA102: =IF(ROUND((Z102-Y169),0)=0,"correct", "error")
B103: 每股盈餘 | D103: =D102/($N$62*10000000) | E103: =E102/($N$62*10000000) | F103: =F102/-(E98/0.01-E161)*10 | G103: =G102/-(F98/0.01-F161)*10 | H103: =H102/-(G98/0.01-G161)*10 | I103: =I102/-(H98/0.01-H161)*10 | J103: =J102/-(I98/0.01-I161)*10 | K103: =K102/-(J98/0.01-J161)*10 | L103: =L102/-(K98/0.01-K161)*10 | M103: =M102/-(L98/0.01-L161)*10 | ... W103: =W102/-(V98/0.01-V161)*10
B106: 設備折舊 | D106: =-D90 | E106: =-E90 | F106: =-F90 | G106: =-G90 | H106: =-H90 | I106: =-I90 | J106: =-J90 | K106: =-K90 | ... X106: =-X90 | Z106: =SUM(D106:Y106) | AA106: =IF(ROUND((Z106-C122-C2),0)=0,"correct", "error")
B107: 累計現金流 | C107: 0 | D107: =C37+D102+D106 | E107: =E102+E106+D107 | F107: =F102+F106+E107 | G107: =G102+G106+F107 | H107: =H102+H106+G107 | I107: =I102+I106+H107 | J107: =J102+J106+I107 | K107: =K102+K106+J107 | L107: =L102+L106+K107 | ... W107: =W102+W106+V107 | Z107: =IF(ROUND((W107-Z102),0)=0,"correct", "error")
B108: Discounted cash flow | C108: 0 | F108: 1983135.6 | G108: 1938004.7 | H108: 1892873.8 | I108: 1847742.9 | J108: 1802612.1 | K108: 1759737.7 | L108: 1716863.4 | M108: 1673989.1 | N108: 1631114.8 | O108: 1588240.4 | P108: 1550443.3 | Q108: 1512646.2 | R108: 1474849.1 | S108: 1437052 | T108: 1399254.9 | U108: 1361457.8 | V108: 1323660.7 | W108: 1285863.6
B109: Minus : Depreciation | F109: 0 | G109: 0 | H109: 0 | I109: 0 | J109: 0 | K109: 0 | L109: 0 | M109: 0 | N109: 0 | O109: 0 | P109: 0 | Q109: 0 | R109: 0 | S109: 0 | T109: 0 | U109: 0 | V109: 0 | W109: 0
B110: Plus : Principle payment | F110: 0 | G110: 0 | H110: 0 | I110: 0 | J110: 0 | K110: 0 | L110: 0 | M110: 0 | N110: 0 | O110: 0 | P110: 0 | Q110: 0 | R110: 0 | S110: 0 | T110: 0 | U110: 0 | V110: 0 | W110: 0
...

Sheet 比例
B2: 工程項目圓餅圖
Q4: =SUM(Q6:Q15)
B5: 項目 | C5: 成本比例 | I5: 項目 | J5: 業務報價比例 | P5: 項目 | Q5: 利潤比例
B6: =#REF! | C6: =#REF!/#REF! | I6: =#REF! | J6: =#REF!/#REF! | P6: =#REF! | Q6: =(#REF!-#REF!)/#REF!
B7: =#REF! | C7: =#REF!/#REF! | I7: =#REF! | J7: =#REF!/#REF! | P7: =#REF! | Q7: =(#REF!-#REF!)/#REF!
B8: =#REF! | C8: =(#REF!+#REF!+#REF!+#REF!)/#REF! | I8: =#REF! | J8: =(#REF!+#REF!+#REF!+#REF!)/#REF! | P8: =#REF! | Q8: =((#REF!-#REF!)+(#REF!-#REF!)+(#REF!-#REF!)+(#REF!-#REF!))/#REF!
B9: =#REF! | C9: =(#REF!+#REF!)/#REF! | I9: =#REF! | J9: =(#REF!+#REF!)/#REF! | P9: =#REF! | Q9: =((#REF!-#REF!)+(#REF!-#REF!))/#REF!
B10: =#REF! | C10: =(#REF!+#REF!)/#REF! | I10: =#REF! | J10: =(#REF!+#REF!)/#REF! | P10: =#REF! | Q10: =((#REF!-#REF!)+(#REF!-#REF!))/#REF!
B11: =#REF! | C11: =(#REF!+#REF!+#REF!)/#REF! | I11: =#REF! | J11: =(#REF!+#REF!+#REF!)/#REF! | P11: =#REF! | Q11: =((#REF!-#REF!)+(#REF!-#REF!)+(#REF!-#REF!))/#REF!
B12: =#REF! | C12: =(#REF!+#REF!)/#REF! | I12: =#REF! | J12: =(#REF!+#REF!)/#REF! | P12: =#REF! | Q12: =((#REF!-#REF!)+(#REF!-#REF!))/#REF!
B13: =#REF! | C13: =(#REF!)/#REF! | I13: =#REF! | J13: =(#REF!)/#REF! | P13: =#REF! | Q13: =(#REF!-#REF!)/#REF!
B14: =#REF! | C14: =(#REF!)/#REF! | I14: =#REF! | J14: =(#REF!)/#REF! | P14: =#REF! | Q14: =(#REF!-#REF!)/#REF!
B15: =#REF! | C15: =#REF!/#REF! | I15: =#REF! | J15: =#REF!/#REF! | P15: =#REF! | Q15: =(#REF!-#REF!)/#REF!

Sheet 台電
B1: =B11
B2: 選用廠商 | C2: 規格 | D2: 報價(台幣/KW)
B3: =B14 | C3: =C14 | D3: =D14
B5: =B19
B6: 選用廠商 | C6: 規格 | D6: 報價(台幣/案) | F6: 選用廠商 | G6: 規格 | H6: 報價(台幣/KW)
B7: =B23 | C7: =C23 | D7: =D23 | F7: - | G7: 內線 | H7: 0
B11: 併網工程費用
B12: 廠商 | C12: 規格 | D12: 報價(台幣/KW) | E12: 報價時間 | F12: NOTE | G12: 聯絡人 | H12: 聯絡方式 | I12: Email
B13: 台電 | C13: 50-100 | D13: 1050 | F13: 50KW以下免費(屋頂型)
B14: 台電 | C14: 100-500 | D14: 1470 | F14: 50KW以下免費(屋頂型)
B15: 台電 | C15: 50-2000 | D15: 630 | F15: 50KW以下免費，高壓線補費(屋頂型)；110/03/29內線須確認既有線路是否需加強電力網(該電號併接的台電線路為分界，3年↑X、3年↓O、須實質審查)
B16: 台電 | C16: 地面型 | D16: 2100 | F16: 22.8kV↓配電、110.05.06 草案
B17: 台電 | D17: 1400 | F17: 69kV↑配電、110.05.06 草案
B19: 併網審查作業費
B20: 廠商 | C20: 規格 | D20: 報價(台幣/案) | E20: 報價時間 | F20: NOTE | G20: 聯絡人 | H20: 聯絡方式 | I20: Email
B21: 台電 | C21: 併接外線69KV以上 | D21: 340000 | F21: 中華民國99年1/18日,經授能字09920080510
B22: 台電 | C22: 併接外線22.8KV | D22: 85000 | F22: 中華民國99年1/18日,經授能字09920080510
B23: 台電 | C23: 併接外線11.4KV | D23: 85000 | F23: 中華民國99年1/18日,經授能字09920080510
B24: 台電 | C24: 併接低壓 | D24: 18000 | F24: 中華民國109年4/6日,電輸供部規字第10980340751號 惟辦理第一次展延時收取
B28: 代辦升壓設備(1+2或1+3)
B29: 廠商 | C29: 規格 | D29: 報價(台幣/kW/km) | E29: 報價時間 | F29: NOTE | G29: 聯絡人 | H29: 聯絡方式 | I29: Email
B30: 台電 | C30: 升壓設備 | D30: 2880元/kw*裝置容量 | E30: 1 | F30: 中華民國107年7月2日電配售部配字第1078066359
B31: 台電 | C31: 配電線路(架空) | D31: 803元/Kw*km | E31: 2 | F31: 中華民國107年7月2日電配售部配字第1078066359
B32: 台電 | C32: 配電線路(地下) | D32: 2484元/kW*km | E32: 3 | F32: 中華民國107年7月2日電配售部配字第1078066359

Sheet 行政
B1: 市電躉售併聯申請
B2: 選用廠商 | C2: 規格 | D2: 報價(台幣/案)
B3: =B42 | C3: 1-99kWp *1案 100-499kWp *2案 | D3: =D41+D42*2
B5: 結構技師
B6: 選用廠商 | C6: 規格 | D6: 報價(台幣/案)
B7: =B50 | C7: =C50 | D7: =80*#REF! | E7: 80/kW
B9: 電機技師(100KW以上案件需要)
B10: 選用廠商 | C10: 規格(KW) | D10: 報價(台幣/案)
B11: =B54 | C11: =C54 | D11: =D54
B14: 市電躉售併聯申請
B15: 廠商 | C15: 規格 | D15: 報價(台幣/案) | E15: 報價時間 | F15: NOTE | G15: 聯絡人 | H15: 聯絡方式 | I15: Email | J15: 備註
B16: 原生 | C16: 10kW左右 | D16: 20000 | E16: 2020/4月 | F16: 所有公家文件申請行政流程 (特別價) | G16: 湯學薇 | J16: 第三型
B17: 原生 | C17: 100kW以下 | D17: 30000 | E17: 2018/5月 | F17: 所有公家文件申請行政流程
B18: 原生 | C18: 100kW以上 | D18: 33000 | E18: 2018/5月 | F18: 所有公家文件申請行政流程
B19: 原生 | C19: 500-2MW | D19: 86000 | E19: 2020/8月 | F19: 所有公家文件申請行政流程 (特別價)
B20: 辰欣豪亦 | C20: 20kW以下 | D20: 40000 | E20: 2021/8月 | F20: 所有公家文件申請行政流程 *台電審查 *縣市政府 *顧問服務 | G20: 李佳玲 | I20: 自用不躉售案件 以9折計算
B21: 辰欣豪亦 | C21: 21-99kW | E21: 2021/8月 | G21: 李佳玲
B22: 辰欣豪亦 | C22: 100-199kW | D22: 45000 | E22: 2021/8月 | G22: 李佳玲
B23: 辰欣豪亦 | C23: 200-299kW | E23: 2021/8月 | G23: 李佳玲
B24: 辰欣豪亦 | C24: 300-399kW | E24: 2021/8月 | G24: 李佳玲
B25: 辰欣豪亦 | C25: 400-499kW | E25: 2021/8月 | G25: 李佳玲
B26: 辰欣豪亦 | C26: 500-999kW | D26: 70000 | E26: 2021/8月 | G26: 李佳玲
B27: 辰欣豪亦 | C27: 1000-1499kW | D27: 95000 | E27: 2021/8月 | G27: 李佳玲
B28: 辰欣豪亦 | C28: 1500-1999kW | D28: 150000 | E28: 2021/8月 | G28: 李佳玲
B29: 辰欣豪亦 | C29: 10MW以下 | D29: 500000 | E29: 2021/8月 | F29: 所有公家文件申請行政流程 *籌設前置 *電業籌設 *施工許可 *免雜項執照 *設備認定 *電業執照 | G29: 李佳玲 | I29: 每案籌設以一期為限， 施工許可申請依據籌設許可函核定內容為準 | J29: 第二型
B30: 辰欣豪亦 | C30: 11-30MW | D30: 800000 | E30: 2021/8月 | G30: 李佳玲
B31: 辰欣豪亦 | C31: 31-50MW | D31: 1000000 | E31: 2021/8月 | G31: 李佳玲
B32: 辰欣豪亦 | C32: 51MW以上 | D32: 另行報價 | E32: 2021/8月 | G32: 李佳玲
B33: 辰欣豪亦 | C33: 10MW以下 | D33: 750000 | E33: 2021/8月 | G33: 李佳玲 | J33: 第一型
B34: 辰欣豪亦 | C34: 11-20MW | D34: 850000 | E34: 2021/8月 | G34: 李佳玲
B35: 辰欣豪亦 | C35: 21-40MW | D35: 1050000 | E35: 2021/8月 | G35: 李佳玲
B36: 辰欣豪亦 | C36: 41-60MW | D36: 1250000 | E36: 2021/8月 | G36: 李佳玲
B37: 辰欣豪亦 | C37: 61-80MW | D37: 1450000 | E37: 2021/8月 | G37: 李佳玲
B38: 辰欣豪亦 | C38: 81-100MW | D38: 1650000 | E38: 2021/8月 | G38: 李佳玲
B39: 辰欣豪亦 | C39: 101MW以上 | D39: 另行報價 | E39: 2021/8月 | G39: 李佳玲
B40: 日鴻 | C40: 20kW以下 | D40: 45000 | E40: 2022/4月 | F40: 所有公家文件申請行政流程 *台電審查(含台電送審四大圖說繪製) *縣市政府 | G40: 黃永政 | J40: 第三型
B41: 友樂晴 | C41: 1-99kWp | D41: 35000 | E41: 20221109 | F41: 所有公家文件申請行政流程 *同一場址分多期送件，視為多案，依各案容量所屬級距分別報價 *同一場址分兩期以上送件，可折扣 *報價包含電器承裝業及太陽光電乙級技術士簽證 *不含圖說修正及設備修改 *不含任何技師簽證費用及政府規費 | G41: 湯學薇 | H41: 02-23038861 | I41: neomy@yolothink.com | J41: 第三型
B42: 友樂晴 | C42: 100-499kWp | D42: 45000 | E42: 2221109
C43: 500-999kWp | D43: 55000 | E43: 20221109
C44: 1000-1999kWp | D44: 75000 | E44: 20221109
B46: 結構技師
B47: 廠商 | C47: 規格 | D47: 報價(台幣/案) | E47: 報價時間 | F47: NOTE | G47: 聯絡人 | H47: 聯絡方式 | I47: Email
B48: 吳技師 | C48: 無 | D48: 13000 | E48: 2016/3月 | F48: 含結構計算(15級風),免雜照簽證表,結構技師簽證,完竣證明 | G48: 吳技師 | H48: 989574616
B49: 吳技師 | C49: 10kW | D49: 8000 | E49: 2020/4月 | F49: 含結構計算(15級風),免雜照簽證表,結構技師簽證,完竣證明(特別價) | G49: 吳技師 | H49: 989574616
B50: 吳技師 | C50: 163kW↑ | D50: 80/kW | G50: 吳技師 | H50: 989574616
B52: 電機技師(100KW以上案件需要)
B53: 廠商 | C53: 規格(KW) | D53: 報價(台幣/案) | E53: 報價時間 | F53: NOTE | G53: 聯絡人 | H53: 聯絡方式 | I53: Email
B54: 莫技師 | C54: 100-500 | D54: 150000 | E54: 2016/3月 | F54: (併接600V以上外線需要系統衝擊分析,價格已含); 含台電協商; 系統廠拿到8萬價格 | G54: 莫技師 | H54: 0936290428 / 0422210296
B55: 莫技師 | C55: 100以下 | D55: 5000 | E55: 2017/3月 | F55: APS連接器簽證 | G55: 莫技師 | H55: 0936290428 / 0422210296
B56: 莫技師 | C56: 500-1000 | D56: =150000+75000 | E56: 2020/8月 | F56: (併接600V以上外線需要系統衝擊分析,價格已含); 含台電協商; 系統廠拿到8萬價格 | G56: 莫技師 | H56: 0936290428 / 0422210296
B57: 莫技師 | C57: 1000-1500 | D57: =150000+75000+75000 | E57: 2020/8月 | F57: (併接600V以上外線需要系統衝擊分析,價格已含); 含台電協商; 系統廠拿到8萬價格 | G57: 莫技師 | H57: 0936290428 / 0422210296
B58: 莫技師 | C58: 1500-2000 | D58: =150000+75000+75000+75000 | E58: 2020/8月 | F58: (併接600V以上外線需要系統衝擊分析,價格已含); 含台電協商; 系統廠拿到8萬價格 | G58: 莫技師 | H58: 0936290428 / 0422210296
C59: 500~1M：15+7.5=22.5w | F59: 系統衝擊報告費用 ($7萬)
C60: 1M~1.5M：22.5+7.5=30w
C61: 1.5~2M：30+7.5=37.5w
B63: 太陽光電乙級技術士簽證(100KW以下案件需要)
B64: 廠商 | C64: 規格 | D64: 報價(台幣/案) | E64: 報價時間 | F64: NOTE | G64: 聯絡人 | H64: 聯絡方式 | I64: Email
C65: 100以下 | D65: 5000 | E65: 2020/8月 | F65: 100KW以內 設備登記需要檢附
B66: 友樂晴 | D66: 3000 | E66: 20221109 | G66: 湯學薇 | H66: 02-23038861 | I66: neomy@yolothink.com
B68: 三轉一行政申請
B69: 廠商 | C69: 規格 | D69: 報價(台幣/案) | E69: 報價時間 | F69: NOTE | G69: 聯絡人 | H69: 聯絡方式 | I69: Email
B70: 友樂晴 | C70: 第三型再生能源發電設備轉第一型電業 | D70: 330000 | E70: 20221109 | F70: *此項目為一案第三型轉第一型電業 *若為多案第三型轉一案第一型電業，每增加一案第三型加收工本費15,000元 | G70: 湯學薇 | H70: 02-23038861 | I70: neomy@yolothink.com
B72: 申請項目
B73: 廠商 | C73: 規格 | D73: 報價(台幣/案) | E73: 報價時間 | F73: NOTE | G73: 聯絡人 | H73: 聯絡方式 | I73: Email
B74: 友樂晴 | C74: 電能轉供申請 | D74: 120000 | E74: 20221109 | G74: 湯學薇 | H74: 02-23038861 | I74: neomy@yolothink.com
C75: 再生能源憑證申請 | D75: 10000 | F75: 不含後續數據回傳、憑證管理

Sheet 材料
B2: 品名 | C2: 廠商 | D2: 規格 | E2: 報價(台幣/pc) | F2: 報價時間 | G2: NOTE | H2: 聯絡人 | I2: 聯絡方式
B3: 花紋鐵板 | C3: 唐絹 | D3: 白鐵 4呎 x 8呎 t=3mm | E3: 5600 | F3: 2016/3月 | G3: 報價未含材切費用(120 x 243cm)，材切每刀500元 | H3: 彭小姐 | I3: 037230032
B4: 菱型網 | C4: 久恩 | D4: 熱浸 4呎 x 8呎 t=6mm | E4: 1620 | F4: 2017/5月 | G4: 報價未含材切費用(120 x 243cm)，材切每刀60元 | H4: 劉經理 | I4: 073737800
B5: 菱型網 | C5: 久恩 | D5: 白鐵 4呎 x 8呎 t=6mm | E5: 4800 | F5: 2017/5月 | G5: 報價未含材切費用(120 x 243cm)，材切每刀60元 | H5: 劉經理 | I5: 073737800
B7: 品名 | C7: 廠商 | D7: 規格 | E7: 報價(台幣/坪) | F7: 報價時間 | G7: NOTE | H7: 聯絡人 | I7: 聯絡方式
B8: 鐵皮浪板 | C8: 尚鴻 | D8: 不銹鋼+烤漆_清板 0.47 | E8: 3200 | F8: 2020/4月 | G8: 不銹鋼(白鐵)清板0.47+烤漆 (含工帶料) | H8: 黃世昕 | I8: 0916107569
B9: 鐵皮浪板 | C9: 盛貿 | D9: 不銹鋼_清板 | E9: 2500 | F9: 2020/4月 | G9: 不銹鋼(白鐵)清板 (含工帶料) | H9: 林浩興 | I9: 0933526557
B10: 鐵皮浪板 | C10: 龍耀 | D10: 不銹鋼_清板 0.5 | E10: 2500 | F10: 2020/4月 | G10: 不銹鋼(白鐵)清板0.5 (含工帶料) | H10: 邱耀德 | I10: 0912607906
B11: 鐵皮浪板 | C11: 尚鴻 | D11: 不銹鋼_清板 0.47 | E11: 2800 | F11: 2020/4月 | G11: 不銹鋼(白鐵)清板0.47 (含工帶料) | H11: 黃世昕 | I11: 0916107569
B12: 鐵皮浪板 | C12: 志貿 | D12: 不銹鋼_清板 0.5 | E12: 2800 | F12: 2019/6月 | G12: 不銹鋼(白鐵)清板0.5 (含工帶料) | H12: 廖彥傑 | I12: 0958159909
B13: 鐵皮浪板 | C13: 志貿 | D13: 烤漆_清板0.6 | E13: 1900 | F13: 2019/6月 | G13: 清板0.6 (含工帶料) 盛餘清板0.5(1200)、三明治0.5(2500)→華鋼 | H13: 廖彥傑 | I13: 0958159909
B14: 鐵皮浪板 | C14: 宏勝 | D14: 烤漆_清板 0.52(盛餘) | E14: 1600 | F14: 2018/1月 | G14: 盛餘清板0.52 (含工帶料) | H14: 葉老闆 | I14: 0973124524
B15: 鐵皮浪板 | C15: 宏勝 | D15: 烤漆_清板 0.52(盛餘) + Z或口型鋼 | E15: 1800 | F15: 2018/1月 | G15: 盛餘清板0.52+Z或口型鋼 (含工帶料) | H15: 葉老闆 | I15: 0973124524
B16: 鐵皮浪板 | C16: 宏勝 | D16: 烤漆_雙層鋼板 0.5(盛餘) | E16: 1850 | F16: 2019/10月 | G16: 0.5商標雙層盛於浪板 (含工帶料) | H16: 葉老闆 | I16: 0973124524
B17: 鐵皮浪板 | C17: 尚鴻 | D17: 烤漆_雙層鋼板 0.5 | E17: 1980 | F17: 2019/10月 | G17: 750五溝雙層鋼板 (含工帶料) | H17: 黃世昕 | I17: 0916107569
B18: 鐵皮浪板 | C18: 盛貿 | D18: 烤漆_雙層鋼板 | E18: 2000 | F18: 2019/10月 | G18: 三合一浪板 (含工帶料) | H18: 林浩興 | I18: 0933526557
B19: 鐵皮浪板 | C19: 門泰 | D19: 烤漆_雙層鋼板 | E19: 1800 | F19: 2019/10月 | G19: 烤漆四合一 (含工帶料) | H19: 范光星 | I19: 0937020326
... B21: 鐵皮浪板 | C21: 立岑 | D21: 烤漆_三明治板 0.52(燁輝) | E21: 3250 | F21: 2018/1月 | G21: 外層板:燁輝0.52PE烤漆 中層:5cm玻璃棉+1.6mmZ型鐵 內層:凱景0.42PE烤漆美式板 含工帶料，不含清運(清板:170/坪、防火板620/坪) | H21: 楊文雄 | I21: 0955788037
B22: 鐵皮浪板 | C22: 華鋼 | D22: 盛餘清板0.5 | F22: 2018/6月 | G22: 盛餘清板0.5 (含工帶料，修邊280(米/元)，美福介紹) | H22: 李天助 | I22: 0932399844
B23: 鐵皮浪板 | C23: 華鋼 | D23: 三明治0.5 | F23: 2018/6月 | G23: 三明治0.5 (含工帶料，修邊280(米/元)，美福介紹) | H23: 李天助 | I23: 0932399844
B25: 品名 | C25: 廠商 | D25: 規格 | E25: 報價(台幣/米) | F25: 報價時間 | G25: NOTE | H25: 聯絡人 | I25: 聯絡方式
B26: 防水膠帶 | C26: 3M | D26: 寬3cm | E26: 100 | F26: 2018/7月 | G26: 寬3cm x 長1600cm一捲，原材料 寬60cm x 長1600cm一捲
B27: 防水膠帶412 | C27: 金勇貿 | D27: 厚0.5mmx寬3cm | E27: 18 | F27: 2018/7月 | G27: 厚0.5mmx寬3cm x 長20m，每寬120元，可客製化裁切 | H27: 李先生 | I27: 0980111379
B28: 防水膠帶5032 | C28: 金勇貿 | D28: 厚2mmx寬3cm | E28: 33 | F28: 2018/7月 | G28: 厚2mmx寬3cm x 長10m，每寬110元，可客製化裁切 | H28: 李先生 | I28: 0980111379
B29: 結構膠帶2204 | C29: 3M | D29: 寬4cm | E29: 38 | G29: 寬4cm x 長2500cm一捲 | H29: 邱先生 | I29: 0935052022
B31: 品名 | C31: 廠商 | D31: 規格 | E31: 報價(台幣/米) | F31: 報價時間 | G31: NOTE | H31: 聯絡人 | I31: 聯絡方式
B32: 爬梯 | C32: 中苗鐵工廠 | D32: 不鏽鋼爬梯+護籠 | E32: 3500 | F32: 2018/12月 | G32: 含工帶料 | H32: 羅老闆 | I32: 0932617006
B34: 品名 | C34: 廠商 | D34: 規格 | E34: 報價(台幣/米) | F34: 報價時間 | G34: NOTE | H34: 聯絡人 | I34: 聯絡方式
B35: 不鏽鋼水槽 | C35: 華鋼 | D35: 0.5t | E35: 700 | F35: 2018/6月 | G35: 含工帶料，美福介紹 | H35: 李天助 | I35: 0932399844
B36: 不鏽鋼水槽 | C36: 華鋼 | D36: 1t | E36: 1600 | F36: 2018/6月 | G36: 含工帶料，美福介紹 | H36: 李天助 | I36: 0932399844
B37: 不鏽鋼水槽 | C37: 宏勝 | D37: 0.4t | E37: 1000 | F37: 2019/10月 | G37: 含工帶料 | H37: 葉老闆 | I37: 0973124524
B38: 不鏽鋼水槽 | C38: 尚鴻 | D38: 0.5t | E38: 1000 | F38: 2019/10月 | G38: 含工帶料 | H38: 黃世昕 | I38: 0916107569
B40: 品名 | C40: 廠商 | D40: 規格 | E40: 報價(台幣/米) | F40: 報價時間 | G40: NOTE | H40: 聯絡人 | I40: 聯絡方式
B41: 收邊 烤漆鋁鋅板 | C41: 宏勝 | D41: 0.5 | E41: 300 | F41: 2019/10月 | G41: 含工帶料 | H41: 葉老闆 | I41: 0973124524
B42: 收邊 烤漆鋁鋅板 | C42: 尚鴻 | D42: 0.5 | E42: 300 | F42: 2019/10月 | G42: 含工帶料 | H42: 黃世昕 | I42: 0916107569
B43: 收邊 烤漆鋁鋅板 | C43: 門泰 | E43: 300 | F43: 2019/10月 | G43: 含工帶料 | H43: 范光星 | I43: 0937020326
B44: 收邊 烤漆鋁鋅板 | C44: 聖貿 | E44: 300 | F44: 2019/10月 | G44: 含工帶料 | H44: 林浩興 | I44: 0933526557
B45: 收邊 不鏽鋼板 | C45: 聖貿 | E45: 700 | F45: 2020/4月 | G45: 含工帶料 | H45: 林浩興 | I45: 0933526557
B46: 收邊 烤漆不鏽鋼板 | C46: 聖貿 | E46: 800 | F46: 2020/4月 | G46: 含工帶料 | H46: 林浩興 | I46: 0933526557

Sheet 監控
B1: 監控收集器 | F1: 環控設備
B2: 選用廠商 | C2: 規格 | D2: 報價(台幣/台) | F2: 選用廠商 | G2: 規格 | H2: 報價(台幣/式)
B3: =B14 | C3: =C14 | D3: =D14 | F3: =IF(成本!D2<=100,B29,IF(成本!D2>100,B30,)) | G3: =IF(成本!D2<=100,C29,IF(成本!D2>100,C30,)) | H3: =IF(成本!D2<=100,D29,IF(成本!D2>100,D30))*0+D29+D30*2
B5: 數據收集盒 | F5: 雲端系統
B6: 選用廠商 | C6: 規格 | D6: 報價(台幣/台) | F6: 選用廠商 | G6: 規格 | H6: 報價(台幣/年)
B7: =B22 | C7: =C22 | D7: =D22 | F7: =B45 | G7: =C45 | H7: =D43+D44+D45
B10: 監控收集器
B11: 廠商 | C11: 規格 | D11: 報價(台幣/台) | E11: KW | F11: 報價時間 | G11: NOTE | H11: 聯絡人 | I11: 聯絡方式 | J11: Email
B12: Solarbridge | C12: PowerManerger | D12: 12000 | G12: 含雲端系統,無專人監控(由Sinbon專人監控) | H12: 蘇育志 | I12: 0936-185841 / 03-5980288-1370 | J12: jeffery.su@bigsun-energy.com
B13: APS | C13: ECU | D13: 7500 | H13: 業務
B14: APS | C14: ECUR | D14: =100*#REF! | F14: 2020/1月 | G14: 100/USD，保固3年，90台QS1用一台ECU-R | H14: 麗芳
B15: 古瑞瓦特 | C15: 監控模組 | D15: 1500 | F15: 2021/10月 | G15: 7台以內INV，(一支對一台INV) | H15: 郭曜誠 | I15: 0975-515-112
B16: 古瑞瓦特 | C16: 數據收集器 | D16: 15000 | F16: 2021/10月 | G16: 32台INV，拉RS-485線路 | H16: 郭曜誠 | I16: 0975-515-112
B17: 新望 | C17: V1000+ | D17: 5000 | F17: 2022/3月 | G17: 外接資料蒐集器-含電源組，一年保固 / 無延保方案 | H17: 郭曜誠 | I17: 0975-515-112
B18: 新望 | C18: V1000L | D18: 8000 | F18: 2022/3月 | G18: 外接資料蒐集器-含電源組，一年保固 / 無延保方案 | H18: 郭曜誠 | I18: 0975-515-112
B20: 數據收集盒
B21: BIG SUN | C21: iPVBox智慧盒 | D21: 15800 | F21: 2018/4月 | G21: iPVBox-2102 智慧盒 (5年保固) | H21: 蘇育志 | I21: 0936-185841 / 03-5980288-1370 | J21: jeffery.su@bigsun-energy.com
B22: 沅碁雲 | C22: Logger | D22: 35000 | E22: 2MW以下 | F22: 2020/10月 | G22: logger保固一年含現場安裝費(線材不含)；Logger $14000/台；雲端系統 | H22: 王振城 | I22: 0928-225-333 | J22: max@sunedge.com.tw
B23: 沅碁雲 | C23: Logger | D23: 25000 | E23: 2MW以下 | F23: 2020/10月 | G23: logger保固一年含現場安裝費(線材不含)；Logger $14000/台；雲端系統+Dreams系統 | H23: 王振城 | I23: 0928-225-333 | J23: max@sunedge.com.tw
B24: 三惟 | C24: Logger | D24: 31500 | E24: 499kW以下 | F24: 2020/4月 | G24: logger保固一年不含現場安裝費(線材不含) | H24: 朱育龍 | I24: 02-6620-8358 / 0928-765206 | J24: Adam-chew@sunware.com.tw
B25: 慧景 | C25: Logger | D25: 25000 | E25: - | F25: 2022/3月 | G25: logger保固五年(工業等級)；範圍25~40台裝置(基本30台)；型號：pt-2020 (2port) | H25: 詹前鋒 | I25: 0989-434-128 | J25: max@thingnario.com
B26: 慧景 | C26: Logger | D26: 28000 | E26: - | F26: 2022/3月 | G26: logger保固五年(工業等級)；範圍25~40台裝置(基本30台)；型號：pt-4020 (4port) | H26: 詹前鋒 | I26: 0989-434-128 | J26: max@thingnario.com
B28: 環控設備
B29: 沅碁 | C29: 環控設備 | D29: 52300 | E29: 100KW以下 | F29: 2018/2月 | G29: 含溫度(5300)+日照(28500)+CT、交流錶頭(18500) | H29: 王振城 | I29: 0928-225-333 | J29: max@sunedge.com.tw
B30: 沅碁 | C30: 環控設備 | D30: 55000 | E30: 499KW | F30: 2018/7月 | G30: 含溫度、日照(43000)+CT、交流錶頭(12000) | H30: 王振城 | I30: 0928-225-333 | J30: max@sunedge.com.tw
B31: 綠世界 | C31: 環控設備 | D31: 44600 | E31: 100KW以下 | F31: 2018/2月 | G31: 含溫度(4900)+日照(19400)+CT(600*3)+交流錶頭(6600)+安裝費(2500)+箱體(9400) | H31: 蘇育志 | I31: 0936-185841 / 03-5980288-1370
B32: 綠世界 | C32: 環控設備 | D32: 51200 | E32: 100KW以上 | F32: 2018/2月 | G32: 含溫度(4900)+日照(19400)+CT(2800*3)+交流錶頭(6600)+安裝費(2500)+箱體(9400) | H32: 蘇育志 | I32: 0936-185841 / 03-5980288-1370
B33: 三惟 | C33: 環控設備 | D33: 43500 | E33: 499KW | F33: 2020/4月 | G33: 含溫度(1500)+日照(22000)+CT(2800*3)+交流錶頭(6600)+箱體(8000) | H33: 朱育龍 | I33: 02-6620-8358 / 0928-765206 | J33: Adam-chew@sunware.com.tw
B34: 三惟 | C34: 環控設備 | D34: 40900 | E34: 100KW | F34: 2021/8月 | G34: 含溫度(2000)+日照(19500)+CT(2800*3)+交流錶頭(5000)+箱體(6000) | H34: 朱育龍 | I34: 02-6620-8358 / 0928-765206 | J34: Adam-chew@sunware.com.tw
B35: 慧景(紘銘) | C35: 環控設備 | D35: 40700 | E35: - | F35: 2022/4月 | G35: 含溫度(5150)+日照(22350)+箱體(13200) | H35: 詹前鋒 | I35: 0989-434-128 | J35: max@thingnario.com
B37: 雲端系統
B38: 廠商 | C38: 規格 | D38: 報價(台幣/年) | E38: KW | F38: 報價時間 | G38: NOTE | H38: 聯絡人 | I38: 聯絡方式 | J38: Email | K38: 報價(台幣)
B39: BIG SUN | C39: 雲端IPV系統 | D39: 900 | E39: 20KW以下 | F39: 2018/4月 | G39: 5年期滿後每案每年1000元 | H39: 蘇育志 | I39: 0936-185841 / 03-5980288-1370 | J39: jeffery.su@bigsun-energy.com | K39: 25000
B40: BIG SUN | C40: 雲端IPV系統 | D40: 1600 | E40: 21-100KW | F40: 2018/4月 | G40: 5年期滿後每案每年1000元 | H40: 蘇育志 | I40: 0936-185841 / 03-5980288-1370 | J40: jeffery.su@bigsun-energy.com
B41: BIG SUN | C41: 雲端IPV系統 | D41: 2000 | E41: 101-499KW | F41: 2018/4月 | G41: 5年期滿後每案每年1000元 | H41: 蘇育志 | I41: 0936-185841 / 03-5980288-1370 | J41: jeffery.su@bigsun-energy.com
B42: BIG SUN | C42: 雲端IPV系統 | D42: 3000 | E42: 499-999KW | F42: 2018/4月 | G42: 5年期滿後每案每年1000元 | H42: 蘇育志 | I42: 0936-185841 / 03-5980288-1370 | J42: jeffery.su@bigsun-energy.com
B43: 沅碁 | C43: 沅碁網站監控 | D43: 4000 | E43: 100KW以下 | F43: 2020/10月 | G43: 含專人監控,五年一個package | H43: 王振城 | I43: 0928-225-333 | J43: max@sunedge.com.tw
B44: 沅碁 | C44: 沅碁網站監控 | D44: 7000 | E44: 101-300KW | F44: 2020/10月 | H44: 王振城 | I44: 0928-225-333 | J44: max@sunedge.com.tw
B45: 沅碁 | C45: 沅碁網站監控 | D45: 12000 | E45: 301-499KW | F45: 2020/10月 | H45: 王振城 | I45: 0928-225-333 | J45: max@sunedge.com.tw
B46: 沅碁 | C46: 沅碁網站監控 | D46: 16000 | E46: 500~1MW | F46: 2020/10月 | H46: 王振城 | I46: 0928-225-333 | J46: max@sunedge.com.tw
B47: 沅碁 | C47: 沅碁網站監控 | D47: 24000 | E47: 1~2MW | F47: 2020/10月 | H47: 王振城 | I47: 0928-225-333 | J47: max@sunedge.com.tw
B48: 沅碁 | C48: 沅碁網站監控 | D48: 39000 | E48: 2~4MW | F48: 2020/10月 | H48: 王振城 | I48: 0928-225-333 | J48: max@sunedge.com.tw
B49: 沅碁 | C49: 沅碁網站監控 | D49: 4000 | E49: 99KW以下 | F49: 2021/9月 | G49: 含智慧盒，含專人監控,五年一個package，5年 | H49: 王振城 | I49: 0928-225-333 | J49: max@sunedge.com.tw | K49: =D49*5
B50: 沅碁 | C50: 沅碁網站監控 | D50: 9000 | E50: 100-299KW | F50: 2021/9月 | H50: 王振城 | I50: 0928-225-333 | J50: max@sunedge.com.tw | K50: =D50*5
B51: 沅碁 | C51: 沅碁網站監控 | D51: 10000 | E51: 300-499KW | F51: 2021/9月 | H51: 王振城 | I51: 0928-225-333 | J51: max@sunedge.com.tw | K51: =D51*5
B52: 沅碁 | C52: 沅碁網站監控 | D52: 16000 | E52: 500~1MW | F52: 2021/9月 | H52: 王振城 | I52: 0928-225-333 | J52: max@sunedge.com.tw | K52: =D52*5
B53: 沅碁 | C53: 沅碁網站監控 | D53: 30000 | E53: 1~2MW | F53: 2021/9月 | H53: 王振城 | I53: 0928-225-333 | J53: max@sunedge.com.tw | K53: =D53*5
B54: 沅碁 | C54: 沅碁網站監控 | D54: 4000 | E54: 99KW以下 | F54: 2021/9月 | G54: 含智慧盒，含專人監控,五年一個package，20年 | H54: 王振城 | I54: 0928-225-333 | J54: max@sunedge.com.tw | K54: =D54*20*$L$54 | L54: 0.8
B55: 沅碁 | C55: 沅碁網站監控 | D55: 9000 | E55: 100-299KW | F55: 2021/9月 | H55: 王振城 | I55: 0928-225-333 | J55: max@sunedge.com.tw | K55: =D55*20*$L$54
B56: 沅碁 | C56: 沅碁網站監控 | D56: 10000 | E56: 300-499KW | F56: 2021/9月 | H56: 王振城 | I56: 0928-225-333 | J56: max@sunedge.com.tw | K56: =D56*20*$L$54
B57: 沅碁 | C57: 沅碁網站監控 | D57: 16000 | E57: 500~1MW | F57: 2021/9月 | H57: 王振城 | I57: 0928-225-333 | J57: max@sunedge.com.tw | K57: =D57*20*$L$54
B58: 沅碁 | C58: 沅碁網站監控 | D58: 30000 | E58: 1~2MW | F58: 2021/9月 | H58: 王振城 | I58: 0928-225-333 | J58: max@sunedge.com.tw | K58: =D58*20*$L$54
B60: 廠商 | C60: 規格 | D60: 報價(台幣/年) | E60: KW | F60: 報價時間 | G60: NOTE | H60: 聯絡人 | I60: 聯絡方式 | J60: Email
B61: 三惟 | C61: 三惟網站監控 | D61: 1500 | E61: 1-99kW | F61: 2021/8月 | G61: 含專人監控,五年一個package | H61: 朱育龍 | I61: 02-6620-8358 / 0928-765206 | J61: Adam-chew@sunware.com.tw | K61: 2020/4月
B62: 三惟 | C62: 三惟網站監控 | D62: 3000 | E62: 100-299kW | F62: 2021/8月 | H62: 朱育龍 | I62: 02-6620-8358 / 0928-765206 | J62: Adam-chew@sunware.com.tw
B63: 三惟 | C63: 三惟網站監控 | D63: 5000 | E63: 300-499kW | F63: 2021/8月 | H63: 朱育龍 | I63: 02-6620-8358 / 0928-765206 | J63: Adam-chew@sunware.com.tw
B64: 三惟 | C64: 三惟網站監控 | D64: 7500 | E64: 500-999kW | F64: 2021/8月 | H64: 朱育龍 | I64: 02-6620-8358 / 0928-765206 | J64: Adam-chew@sunware.com.tw
B65: 三惟 | C65: 三惟網站監控 | D65: 10000 | E65: 1MW | F65: 2021/8月 | G65: 含專人監控,五年一個package；多1MW加$5000/年 | H65: 朱育龍 | I65: 02-6620-8358 / 0928-765206 | J65: Adam-chew@sunware.com.tw
B66: 三惟 | C66: 現場軟體安裝、 系統上線測試費 | D66: 15,000 (總價) | E66: 1式 | F66: 2021/8月 | G66: Inverter、日照計、溫度計、網路通訊測試設定，能源管理系統安裝設定 | H66: 朱育龍 | I66: 02-6620-8358 / 0928-765206 | J66: Adam-chew@sunware.com.tw
B68: 廠商 | C68: 規格 | D68: 報價(台幣/年) | E68: KW | F68: 報價時間 | G68: NOTE | H68: 聯絡人 | I68: 聯絡方式 | J68: Email | K68: 報價(台幣)
B69: 慧景 | C69: 慧景網站監控 | D69: =K69/5 | E69: 100kW以下 | F69: 2022/3月 | G69: 五年一個package，共5年 (無專人監控，提供一套系統平臺，供維運及管理電站) | H69: 詹前鋒 | I69: 0989-434-128 | J69: max@thingnario.com | K69: 25000
B70: 慧景 | C70: 慧景網站監控 | D70: =K70/5 | E70: 99~249kW | F70: 2022/3月 | H70: 詹前鋒 | I70: 0989-434-128 | J70: max@thingnario.com | K70: 35000
B71: 慧景 | C71: 慧景網站監控 | D71: =K71/5 | E71: 249~499kW | F71: 2022/3月 | H71: 詹前鋒 | I71: 0989-434-128 | J71: max@thingnario.com | K71: 45000
B72: 慧景 | C72: 慧景網站監控 | D72: =K72/5 | E72: 499~999kW | F72: 2022/3月 | H72: 詹前鋒 | I72: 0989-434-128 | J72: max@thingnario.com | K72: 60000
B73: 慧景 | C73: 慧景網站監控 | D73: =K73/20 | E73: 99kW以下 | F73: 2022/3月 | G73: 五年一個package，共20年 (無專人監控，提供一套系統平臺，供維運及管理電站) | H73: 詹前鋒 | I73: 0989-434-128 | J73: max@thingnario.com | K73: =K69*4
B74: 慧景 | C74: 慧景網站監控 | D74: =K74/20 | E74: 99~249kW | F74: 2022/3月 | H74: 詹前鋒 | I74: 0989-434-128 | J74: max@thingnario.com | K74: =K70*4
B75: 慧景 | C75: 慧景網站監控 | D75: =K75/20 | E75: 249~499kW | F75: 2022/3月 | H75: 詹前鋒 | I75: 0989-434-128 | J75: max@thingnario.com | K75: =K71*4
B76: 慧景 | C76: 慧景網站監控 | D76: =K76/20 | E76: 499~999kW | F76: 2022/3月 | H76: 詹前鋒 | I76: 0989-434-128 | J76: max@thingnario.com | K76: =K72*4
B77: 慧景 | C77: 慧景網站監控 | D77: =K77/20 | E77: 99kW以下 | F77: 2022/3月 | G77: 二十年一個package，共20年 (無專人監控，提供一套系統平臺，供維運及管理電站) | H77: 詹前鋒 | I77: 0989-434-128 | J77: max@thingnario.com | K77: =K73*L77 | L77: 0.95
B78: 慧景 | C78: 慧景網站監控 | D78: =K78/20 | E78: 99~249kW | F78: 2022/3月 | H78: 詹前鋒 | I78: 0989-434-128 | J78: max@thingnario.com | K78: =K74*L77 | L78: 0.95
B79: 慧景 | C79: 慧景網站監控 | D79: =K79/20 | E79: 249~499kW | F79: 2022/3月 | H79: 詹前鋒 | I79: 0989-434-128 | J79: max@thingnario.com | K79: =K75*L77 | L79: 0.95
B80: 慧景 | C80: 慧景網站監控 | D80: =K80/20 | E80: 499~999kW | F80: 2022/3月 | H80: 詹前鋒 | I80: 0989-434-128 | J80: max@thingnario.com | K80: =K76*L77 | L80: 0.95
B82: Dreams系統 | C82: 同一廠址總裝置容量500kW以上時，須裝設遙控監視設備並接受台電安全調度(110.08.05)
B83: 廠商 | C83: 規格 | D83: 報價(台幣) | E83: KW | F83: 報價時間 | G83: NOTE | H83: 聯絡人 | I83: 聯絡方式 | J83: Email | K83: 報價(台幣/年)
B84: 沅碁 | C84: 沅碁網站監控 | D84: =K84*20 | E84: - | F84: 2021/8月 | G84: 5年一個package，年繳，無SIM卡，無KW級距，含logger，不含施工 | H84: 王振城 | I84: 0928-225-333 | J84: max@sunedge.com.tw | K84: 1200
B85: 沅碁 | C85: 沅碁網站監控 | D85: =K85*20 | E85: - | F85: 2021/8月 | G85: 20年一個package，年繳，無SIM卡，無KW級距，含logger，不含施工 | H85: 王振城 | I85: 0928-225-333 | J85: max@sunedge.com.tw | K85: 1050
B86: 沅碁 | C86: 沅碁網站監控 | D86: 28000 | E86: 500~1MW | F86: 2021/9月 | G86: 5年 | H86: 王振城 | I86: 0928-225-333 | J86: max@sunedge.com.tw
B87: 沅碁 | C87: 沅碁網站監控 | D87: 35000 | E87: 500~1MW | F87: 2021/9月 | G87: 5年+4G SIM卡 | H87: 王振城 | I87: 0928-225-333 | J87: max@sunedge.com.tw
B88: 沅碁 | C88: 沅碁網站監控 | D88: 102000 | E88: 500~1MW | F88: 2021/9月 | G88: 20年 | H88: 王振城 | I88: 0928-225-333 | J88: max@sunedge.com.tw
B89: 沅碁 | C89: 沅碁網站監控 | D89: 130000 | E89: 500~1MW | F89: 2021/9月 | G89: 20年+4G SIM卡 | H89: 王振城 | I89: 0928-225-333 | J89: max@sunedge.com.tw
B90: 沅碁 | C90: 沅碁網站監控 | D90: 68000 | E90: 1MW以上 | F90: 2021/9月 | G90: 5年 | H90: 王振城 | I90: 0928-225-333 | J90: max@sunedge.com.tw
B91: 沅碁 | C91: 沅碁網站監控 | D91: 75000 | E91: 1MW以上 | F91: 2021/9月 | G91: 5年+4G SIM卡 | H91: 王振城 | I91: 0928-225-333 | J91: max@sunedge.com.tw
B92: 沅碁 | C92: 沅碁網站監控 | D92: 222000 | E92: 1MW以上 | F92: 2021/9月 | G92: 20年 | H92: 王振城 | I92: 0928-225-333 | J92: max@sunedge.com.tw
B93: 沅碁 | C93: 沅碁網站監控 | D93: 250000 | E93: 1MW以上 | F93: 2021/9月 | G93: 20年+4G SIM卡 | H93: 王振城 | I93: 0928-225-333 | J93: max@sunedge.com.tw
B95: 廠商 | C95: 規格 | D95: 報價(台幣) | E95: KW | F95: 報價時間 | G95: NOTE | H95: 聯絡人 | I95: 聯絡方式 | J95: Email | K95: 報價(台幣/年)
B96: 三惟 | C96: 三惟網站監控 | D96: =K96*20 | E96: - | F96: 2021/8月 | G96: 20年，年繳，無SIM卡，無KW級距 | H96: 詹前鋒 | I96: 0937-099-803 | J96: max@thingnario.com | K96: 3000
B97: 三惟 | C97: 台電Dreams系統 上線設定 | D97: 55000 | E97: 1式 | F97: 2021/8月 | G97: 含雲端Gateway+電源供應器(保固一年，延保5年一次 $10,000 未稅)， 台電Dreams申請跑件、雲端上線，Dreams VPN訊號測試 | H97: 詹前鋒 | I97: 0937-099-803 | J97: max@thingnario.com | K97: 3000
B99: 廠商 | C99: 規格 | D99: 報價(台幣) | E99: KW | F99: 報價時間 | G99: NOTE | H99: 聯絡人 | I99: 聯絡方式 | J99: Email | K99: 備註
B100: 慧景 | C100: 慧景網站監控 | D100: 35000 | E100: 500~1MW | F100: 2021/8月 | G100: 5年 | H100: 詹前鋒 | I100: 0937-099-803 | J100: max@thingnario.com | K100: 1.SIM卡 $6000(5年)=$1200(1年)=$100(1個月)
B101: 慧景 | C101: 慧景網站監控 | D101: 41000 | E101: 500~1MW | F101: 2021/8月 | G101: 5年+SIM卡 | H101: 詹前鋒 | I101: 0937-099-803 | J101: max@thingnario.com | K101: 2.報價內含了logger (軟硬體皆含)
B102: 慧景 | C102: 慧景網站監控 | D102: 200000 | E102: 500~1MW | F102: 2021/8月 | G102: 20年 | H102: 詹前鋒 | I102: 0937-099-803 | J102: max@thingnario.com | K102: 3.買監控20年一次付清送Dreams
B103: 慧景 | C103: 慧景網站監控 | D103: 224000 | E103: 500~1MW | F103: 2021/8月 | G103: 20年+SIM卡 | H103: 詹前鋒 | I103: 0937-099-803 | J103: max@thingnario.com | K103: 4.不含環控設備(日照計、溫度計)
B104: 慧景 | C104: 慧景網站監控 | D104: 72000 | E104: 1~2MW | F104: 2021/8月 | G104: 5年+SIM卡 | H104: 詹前鋒 | I104: 0937-099-803 | J104: max@thingnario.com | K104: 5.硬體設備保固同軟體年限(雷擊不保固)
B105: 慧景 | C105: 慧景網站監控 | D105: 288000 | E105: 1~2MW | F105: 2021/8月 | G105: 20年+SIM卡 | H105: 詹前鋒 | I105: 0937-099-803 | J105: max@thingnario.com
B107: 雲端系統+Dreams系統
B108: 廠商 | C108: 規格 | D108: 報價(台幣) | E108: KW | F108: 報價時間 | G108: NOTE | H108: 聯絡人 | I108: 聯絡方式 | J108: Email
B109: 沅碁 | C109: 沅碁網站監控 | E109: 500~1MW | F109: 2021/9月 | G109: 5年 | H109: 王振城 | I109: 0928-225-333 | J109: max@sunedge.com.tw
B110: 沅碁 | C110: 沅碁網站監控 | D110: 92000 | E110: 500~1MW | F110: 2021/9月 | G110: 5年+4G SIM卡 | H110: 王振城 | I110: 0928-225-333 | J110: max@sunedge.com.tw
B111: 沅碁 | C111: 沅碁網站監控 | E111: 500~1MW | F111: 2021/9月 | G111: 20年 | H111: 王振城 | I111: 0928-225-333 | J111: max@sunedge.com.tw
B112: 沅碁 | C112: 沅碁網站監控 | D112: 308800 | E112: 500~1MW | F112: 2021/9月 | G112: 20年+4G SIM卡 | H112: 王振城 | I112: 0928-225-333 | J112: max@sunedge.com.tw
...

Sheet 監控 (2)
B1: 數據收集盒
B2: 慧景 | C2: Logger | D2: 25000 | E2: - | F2: 2022/3月 | G2: logger保固五年(工業等級)；範圍25~40台裝置(基本30台)；型號：pt-2020 (2port) | H2: 詹前鋒 | I2: 0989-434-128 | J2: max@thingnario.com
B3: 慧景 | C3: Logger | D3: 28000 | E3: - | F3: 2022/3月 | G3: logger保固五年(工業等級)；範圍25~40台裝置(基本30台)；型號：pt-4020 (4port) | H3: 詹前鋒 | I3: 0989-434-128 | J3: max@thingnario.com
B5: 環控設備
B6: 慧景(紘銘) | C6: 環控設備 | D6: 38100 | E6: - | F6: 2022/3月 | G6: 含溫度(2300)+日照(19500)+交流錶頭(5700)+箱體(10600)、不含CT | H6: 詹前鋒 | I6: 0989-434-128 | J6: max@thingnario.com
B7: 慧景(紘銘) | C7: 環控設備 | D7: 40700 | E7: - | F7: 2022/4月 | G7: 含溫度(5150)+日照(22350)+箱體(13200) | H7: 詹前鋒 | I7: 0989-434-128 | J7: max@thingnario.com
B9: 雲端系統
B10: 廠商 | C10: 規格 | D10: 報價(台幣/年) | E10: KW | F10: 報價時間 | G10: NOTE | H10: 聯絡人 | I10: 聯絡方式 | J10: Email | K10: 報價(台幣)
B11: 慧景 | C11: 慧景網站監控 | D11: =K11/5 | E11: 100kW以下 | F11: 2022/3月 | G11: 五年一個package，共5年 (無專人監控，提供一套系統平臺，供維運及管理電站) | H11: 詹前鋒 | I11: 0989-434-128 | J11: max@thingnario.com | K11: 25000
B12: 慧景 | C12: 慧景網站監控 | D12: =K12/5 | E12: 99~249kW | F12: 2022/3月 | H12: 詹前鋒 | I12: 0989-434-128 | J12: max@thingnario.com | K12: 35000
B13: 慧景 | C13: 慧景網站監控 | D13: =K13/5 | E13: 249~499kW | F13: 2022/3月 | H13: 詹前鋒 | I13: 0989-434-128 | J13: max@thingnario.com | K13: 45000
B14: 慧景 | C14: 慧景網站監控 | D14: =K14/5 | E14: 499~999kW | F14: 2022/3月 | H14: 詹前鋒 | I14: 0989-434-128 | J14: max@thingnario.com | K14: 60000
B15: 慧景 | C15: 慧景網站監控 | D15: =K15/20 | E15: 99kW以下 | F15: 2022/3月 | G15: 五年一個package，共20年 (無專人監控，提供一套系統平臺，供維運及管理電站) | H15: 詹前鋒 | I15: 0989-434-128 | J15: max@thingnario.com | K15: =K11*4
B16: 慧景 | C16: 慧景網站監控 | D16: =K16/20 | E16: 99~249kW | F16: 2022/3月 | H16: 詹前鋒 | I16: 0989-434-128 | J16: max@thingnario.com | K16: =K12*4
B17: 慧景 | C17: 慧景網站監控 | D17: =K17/20 | E17: 249~499kW | F17: 2022/3月 | H17: 詹前鋒 | I17: 0989-434-128 | J17: max@thingnario.com | K17: =K13*4
B18: 慧景 | C18: 慧景網站監控 | D18: =K18/20 | E18: 499~999kW | F18: 2022/3月 | H18: 詹前鋒 | I18: 0989-434-128 | J18: max@thingnario.com | K18: =K14*4
B19: 慧景 | C19: 慧景網站監控 | D19: =K19/20 | E19: 99kW以下 | F19: 2022/3月 | G19: 二十年一個package，共20年 (無專人監控，提供一套系統平臺，供維運及管理電站) | H19: 詹前鋒 | I19: 0989-434-128 | J19: max@thingnario.com | K19: =K15*L19 | L19: 0.95
B20: 慧景 | C20: 慧景網站監控 | D20: =K20/20 | E20: 99~249kW | F20: 2022/3月 | H20: 詹前鋒 | I20: 0989-434-128 | J20: max@thingnario.com | K20: =K16*L19 | L20: 0.95
B21: 慧景 | C21: 慧景網站監控 | D21: =K21/20 | E21: 249~499kW | F21: 2022/3月 | H21: 詹前鋒 | I21: 0989-434-128 | J21: max@thingnario.com | K21: =K17*L19 | L21: 0.95
B22: 慧景 | C22: 慧景網站監控 | D22: =K22/20 | E22: 499~999kW | F22: 2022/3月 | H22: 詹前鋒 | I22: 0989-434-128 | J22: max@thingnario.com | K22: =K18*L19 | L22: 0.95
B24: Dreams系統 | C24: 同一廠址總裝置容量500kW以上時，須裝設遙控監視設備並接受台電安全調度(110.08.05)
B25: 廠商 | C25: 規格 | D25: 報價(台幣) | E25: KW | F25: 報價時間 | G25: NOTE | H25: 聯絡人 | I25: 聯絡方式 | J25: Email
B26: 慧景 | C26: 慧景網站監控 | D26: 35000 | E26: 500~1MW | F26: 2021/8月 | G26: 5年 | H26: 詹前鋒 | I26: 0937-099-803 | J26: max@thingnario.com
B27: 慧景 | C27: 慧景網站監控 | D27: 41000 | E27: 500~1MW | F27: 2021/8月 | G27: 5年+SIM卡 | H27: 詹前鋒 | I27: 0937-099-803 | J27: max@thingnario.com
B28: 慧景 | C28: 慧景網站監控 | D28: 200000 | E28: 500~1MW | F28: 2021/8月 | G28: 20年 | H28: 詹前鋒 | I28: 0937-099-803 | J28: max@thingnario.com
B29: 慧景 | C29: 慧景網站監控 | D29: 224000 | E29: 500~1MW | F29: 2021/8月 | G29: 20年+SIM卡 | H29: 詹前鋒 | I29: 0937-099-803 | J29: max@thingnario.com
B30: 慧景 | C30: 慧景網站監控 | D30: 72000 | E30: 1~2MW | F30: 2021/8月 | G30: 5年+SIM卡 | H30: 詹前鋒 | I30: 0937-099-803 | J30: max@thingnario.com
B31: 慧景 | C31: 慧景網站監控 | D31: 288000 | E31: 1~2MW | F31: 2021/8月 | G31: 20年+SIM卡 | H31: 詹前鋒 | I31: 0937-099-803 | J31: max@thingnario.com
B33: 雲端系統+Dreams系統 | D33: 同一廠址總裝置容量500kW以上時，須裝設遙控監視設備並接受台電安全調度(110.08.05)
B34: 廠商 | C34: 規格 | D34: 報價(台幣/年)*20年 | E34: KW | F34: 報價時間 | G34: NOTE | H34: 聯絡人 | I34: 聯絡方式 | J34: Email | K34: 報價(台幣)
B35: 慧景 | C35: 慧景網站監控 | D35: =D22 | E35: 499~999kW | F35: 2022/3月 | G35: 二十年一個package；無SIM卡；含硬體(logger) | H35: 詹前鋒 | I35: 0989-434-128 | J35: max@thingnario.com | K35: =K22
B36: 慧景 | C36: 慧景網站監控 | D36: 224000 | E36: 500~1MW | F36: 2021/8月 | G36: 20年+SIM卡 | H36: 詹前鋒 | I36: 0989-434-128 | J36: max@thingnario.com | K36: =R23
B37: 慧景 | C37: 慧景網站監控 | D37: 10 / kW | E37: 1~80MW | F37: 2022/3月 | G37: 二十年一個package；無SIM卡；純軟體不含硬體(logger)，1MW->$10,000/年(1/kw->$10/年) | H37: 詹前鋒 | I37: 0989-434-128 | J37: max@thingnario.com | K37: -
B38: 慧景 | C38: 慧景網站監控 | D38: 288000 | E38: 1~2MW | F38: 2021/8月 | G38: 20年+SIM卡 | H38: 詹前鋒 | I38: 0937-099-803 | J38: max@thingnario.com
D40: 一電站拆一二期，且總建置超過500kW
D41: ～ 499kW 採級距報價 ， 二期 就採用每kW 純軟體的收費 1.2NT /每月 ； kW*1.2*單月；前提一二期INV位置相同，可共用Logger；如INV不同區域，無法共用Logger，則須額外加購Logger
D42: (二十年一個package)
D45: 備註
D46: 1.SIM卡 $6000(5年)=$1200(1年)=$100(1個月) for Dreams(1G)
D47: 2.報價內含了logger (軟硬體皆含)
D48: 3.買監控20年一次付清送Dreams
D49: 4.不含環控設備(日照計、溫度計)
D50: 5.硬體設備保固同軟體年限(雷擊不保固)
D51: 6.API提供：
D52: 1.一天100次(15分鐘一筆):一站1萬，軟體使用年限間可撈
D53: 2.一天2000次(15分鐘一筆):一站總價10%，軟體使用年限間可撈

Sheet 監控 (3)
B1: 監控收集器 | F1: 環控設備
B2: 選用廠商 | C2: 規格 | D2: 報價(台幣/台) | F2: 選用廠商 | G2: 規格 | H2: 報價(台幣/式)
B3: =B14 | C3: =C14 | D3: =D14 | F3: =IF(#REF!<=100,B24,IF(#REF!>100,B25,)) | G3: =IF(#REF!<=100,C24,IF(#REF!>100,C25,)) | H3: =IF(#REF!<=100,D24,IF(#REF!>100,D25))
B5: 數據收集盒 | F5: 雲端系統
B6: 選用廠商 | C6: 規格 | D6: 報價(台幣/台) | F6: 選用廠商 | G6: 規格 | H6: 報價(台幣/年)
B7: =B18 | C7: =C18 | D7: =D18 | F7: =B39 | G7: =C39 | H7: =D39
B10: 監控收集器
B11: 廠商 | C11: 規格 | D11: 報價(台幣/台) | E11: KW | F11: 報價時間 | G11: NOTE | H11: 聯絡人 | I11: 聯絡方式 | J11: Email
B12: Solarbridge | C12: PowerManerger | D12: 12000 | G12: 含雲端系統,無專人監控(由Sinbon專人監控) | H12: 蘇育志 | I12: 0936-185841 / 03-5980288-1370 | J12: jeffery.su@bigsun-energy.com
B13: APS | C13: ECU | D13: 7500 | H13: 業務
B14: APS | C14: ECUR | D14: =100*#REF! | F14: 2020/1月 | G14: 100/USD，保固3年，90台QS1用一台ECU-R | H14: 麗芳
B16: 數據收集盒
B17: BIG SUN | C17: iPVBox智慧盒 | D17: 15800 | F17: 2018/4月 | G17: iPVBox-2102 智慧盒 (5年保固) | H17: 蘇育志 | I17: 0936-185841 / 03-5980288-1370 | J17: jeffery.su@bigsun-energy.com
B18: 沅碁雲 | C18: Logger | D18: 35000 | E18: 2MW以下 | F18: 2020/10月 | G18: logger保固一年含現場安裝費(線材不含)；Logger $14000/台；雲端系統 | H18: 王振城 | I18: 0928-225-333 | J18: max@sunedge.com.tw
B19: 沅碁雲 | C19: Logger | D19: 25000 | E19: 2MW以下 | F19: 2020/10月 | G19: logger保固一年含現場安裝費(線材不含)；Logger $14000/台；雲端系統+Dreams系統 | H19: 王振城 | I19: 0928-225-333 | J19: max@sunedge.com.tw
B20: 三惟 | C20: Logger | D20: 31500 | E20: 499kW以下 | F20: 2020/4月 | G20: logger保固一年不含現場安裝費(線材不含) | H20: 朱育龍 | I20: 02-6620-8358 / 0928-765206 | J20: Adam-chew@sunware.com.tw
B21: 慧景 | C21: Logger | D21: 25000 | E21: - | F21: 2021/10月 | G21: logger保固五年(工業等級)；範圍25~40台裝置 | H21: 詹前鋒 | I21: 0937-099-803 | J21: max@thingnario.com
B23: 環控設備
B24: 沅碁 | C24: 環控設備 | D24: 52300 | E24: 100KW以下 | F24: 2018/2月 | G24: 含溫度(5300)+日照(28500)+CT、交流錶頭(18500) | H24: 王振城 | I24: 0928-225-333 | J24: max@sunedge.com.tw
B25: 沅碁 | C25: 環控設備 | D25: 55000 | E25: 499KW | F25: 2018/7月 | G25: 含溫度、日照(43000)+CT、交流錶頭(12000) | H25: 王振城 | I25: 0928-225-333 | J25: max@sunedge.com.tw
B26: 綠世界 | C26: 環控設備 | D26: 44600 | E26: 100KW以下 | F26: 2018/2月 | G26: 含溫度(4900)+日照(19400)+CT(600*3)+交流錶頭(6600)+安裝費(2500)+箱體(9400) | H26: 蘇育志 | I26: 0936-185841 / 03-5980288-1370
B27: 綠世界 | C27: 環控設備 | D27: 51200 | E27: 100KW以上 | F27: 2018/2月 | G27: 含溫度(4900)+日照(19400)+CT(2800*3)+交流錶頭(6600)+安裝費(2500)+箱體(9400) | H27: 蘇育志 | I27: 0936-185841 / 03-5980288-1370
B28: 三惟 | C28: 環控設備 | D28: 43500 | E28: 499KW | F28: 2020/4月 | G28: 含溫度(1500)+日照(22000)+CT(2800*3)+交流錶頭(6600)+箱體(8000) | H28: 朱育龍 | I28: 02-6620-8358 / 0928-765206 | J28: Adam-chew@sunware.com.tw
B29: 三惟 | C29: 環控設備 | D29: 40900 | E29: 100KW | F29: 2021/8月 | G29: 含溫度(2000)+日照(19500)+CT(2800*3)+交流錶頭(5000)+箱體(6000) | H29: 朱育龍 | I29: 02-6620-8358 / 0928-765206 | J29: Adam-chew@sunware.com.tw
B31: 雲端系統
B32: 廠商 | C32: 規格 | D32: 報價(台幣/年) | E32: KW | F32: 報價時間 | G32: NOTE | H32: 聯絡人 | I32: 聯絡方式 | J32: Email | K32: 報價(台幣)
B33: BIG SUN | C33: 雲端IPV系統 | D33: 900 | E33: 20KW以下 | F33: 2018/4月 | G33: 5年期滿後每案每年1000元 | H33: 蘇育志 | I33: 0936-185841 / 03-5980288-1370 | J33: jeffery.su@bigsun-energy.com | K33: 25000
B34: BIG SUN | C34: 雲端IPV系統 | D34: 1600 | E34: 21-100KW | F34: 2018/4月 | G34: 5年期滿後每案每年1000元 | H34: 蘇育志 | I34: 0936-185841 / 03-5980288-1370 | J34: jeffery.su@bigsun-energy.com
B35: BIG SUN | C35: 雲端IPV系統 | D35: 2000 | E35: 101-499KW | F35: 2018/4月 | G35: 5年期滿後每案每年1000元 | H35: 蘇育志 | I35: 0936-185841 / 03-5980288-1370 | J35: jeffery.su@bigsun-energy.com
B36: BIG SUN | C36: 雲端IPV系統 | D36: 3000 | E36: 499-999KW | F36: 2018/4月 | G36: 5年期滿後每案每年1000元 | H36: 蘇育志 | I36: 0936-185841 / 03-5980288-1370 | J36: jeffery.su@bigsun-energy.com
B37: 沅碁 | C37: 沅碁網站監控 | D37: 4000 | E37: 100KW以下 | F37: 2020/10月 | G37: 含專人監控,五年一個package | H37: 王振城 | I37: 0928-225-333 | J37: max@sunedge.com.tw
B38: 沅碁 | C38: 沅碁網站監控 | D38: 7000 | E38: 101-300KW | F38: 2020/10月 | H38: 王振城 | I38: 0928-225-333 | J38: max@sunedge.com.tw
B39: 沅碁 | C39: 沅碁網站監控 | D39: 12000 | E39: 301-499KW | F39: 2020/10月 | H39: 王振城 | I39: 0928-225-333 | J39: max@sunedge.com.tw
B40: 沅碁 | C40: 沅碁網站監控 | D40: 16000 | E40: 500~1MW | F40: 2020/10月 | H40: 王振城 | I40: 0928-225-333 | J40: max@sunedge.com.tw
B41: 沅碁 | C41: 沅碁網站監控 | D41: 24000 | E41: 1~2MW | F41: 2020/10月 | H41: 王振城 | I41: 0928-225-333 | J41: max@sunedge.com.tw
B42: 沅碁 | C42: 沅碁網站監控 | D42: 39000 | E42: 2~4MW | F42: 2020/10月 | H42: 王振城 | I42: 0928-225-333 | J42: max@sunedge.com.tw
B43: 沅碁 | C43: 沅碁網站監控 | D43: 4000 | E43: 99KW以下 | F43: 2021/9月 | G43: 含智慧盒，含專人監控,五年一個package，5年 | H43: 王振城 | I43: 0928-225-333 | J43: max@sunedge.com.tw | K43: =D43*5
B44: 沅碁 | C44: 沅碁網站監控 | D44: 9000 | E44: 100-299KW | F44: 2021/9月 | H44: 王振城 | I44: 0928-225-333 | J44: max@sunedge.com.tw | K44: =D44*5
B45: 沅碁 | C45: 沅碁網站監控 | D45: 10000 | E45: 300-499KW | F45: 2021/9月 | H45: 王振城 | I45: 0928-225-333 | J45: max@sunedge.com.tw | K45: =D45*5
B46: 沅碁 | C46: 沅碁網站監控 | D46: 16000 | E46: 500~1MW | F46: 2021/9月 | H46: 王振城 | I46: 0928-225-333 | J46: max@sunedge.com.tw | K46: =D46*5
B47: 沅碁 | C47: 沅碁網站監控 | D47: 30000 | E47: 1~2MW | F47: 2021/9月 | H47: 王振城 | I47: 0928-225-333 | J47: max@sunedge.com.tw | K47: =D47*5
B48: 沅碁 | C48: 沅碁網站監控 | D48: 4000 | E48: 99KW以下 | F48: 2021/9月 | G48: 含智慧盒，含專人監控,五年一個package，20年 | H48: 王振城 | I48: 0928-225-333 | J48: max@sunedge.com.tw | K48: =D48*20*$L$48 | L48: 0.8
B49: 沅碁 | C49: 沅碁網站監控 | D49: 9000 | E49: 100-299KW | F49: 2021/9月 | H49: 王振城 | I49: 0928-225-333 | J49: max@sunedge.com.tw | K49: =D49*20*$L$48
B50: 沅碁 | C50: 沅碁網站監控 | D50: 10000 | E50: 300-499KW | F50: 2021/9月 | H50: 王振城 | I50: 0928-225-333 | J50: max@sunedge.com.tw | K50: =D50*20*$L$48
B51: 沅碁 | C51: 沅碁網站監控 | D51: 16000 | E51: 500~1MW | F51: 2021/9月 | H51: 王振城 | I51: 0928-225-333 | J51: max@sunedge.com.tw | K51: =D51*20*$L$48
B52: 沅碁 | C52: 沅碁網站監控 | D52: 30000 | E52: 1~2MW | F52: 2021/9月 | H52: 王振城 | I52: 0928-225-333 | J52: max@sunedge.com.tw | K52: =D52*20*$L$48
B54: 廠商 | C54: 規格 | D54: 報價(台幣/年) | E54: KW | F54: 報價時間 | G54: NOTE | H54: 聯絡人 | I54: 聯絡方式 | J54: Email
B55: 三惟 | C55: 三惟網站監控 | D55: 1500 | E55: 1-99kW | F55: 2021/8月 | G55: 含專人監控,五年一個package | H55: 朱育龍 | I55: 02-6620-8358 / 0928-765206 | J55: Adam-chew@sunware.com.tw | K55: 2020/4月
B56: 三惟 | C56: 三惟網站監控 | D56: 3000 | E56: 100-299kW | F56: 2021/8月 | H56: 朱育龍 | I56: 02-6620-8358 / 0928-765206 | J56: Adam-chew@sunware.com.tw
B57: 三惟 | C57: 三惟網站監控 | D57: 5000 | E57: 300-499kW | F57: 2021/8月 | H57: 朱育龍 | I57: 02-6620-8358 / 0928-765206 | J57: Adam-chew@sunware.com.tw
B58: 三惟 | C58: 三惟網站監控 | D58: 7500 | E58: 500-999kW | F58: 2021/8月 | H58: 朱育龍 | I58: 02-6620-8358 / 0928-765206 | J58: Adam-chew@sunware.com.tw
B59: 三惟 | C59: 三惟網站監控 | D59: 10000 | E59: 1MW | F59: 2021/8月 | G59: 含專人監控,五年一個package；多1MW加$5000/年 | H59: 朱育龍 | I59: 02-6620-8358 / 0928-765206 | J59: Adam-chew@sunware.com.tw
B60: 三惟 | C60: 現場軟體安裝、 系統上線測試費 | D60: 15,000 (總價) | E60: 1式 | F60: 2021/8月 | G60: Inverter、日照計、溫度計、網路通訊測試設定，能源管理系統安裝設定 | H60: 朱育龍 | I60: 02-6620-8358 / 0928-765206 | J60: Adam-chew@sunware.com.tw
B62: 廠商 | C62: 規格 | D62: 報價(台幣/年) | E62: KW | F62: 報價時間 | G62: NOTE | H62: 聯絡人 | I62: 聯絡方式 | J62: Email | K62: 報價(台幣)
B63: 慧景 | C63: 慧景網站監控 | D63: =K63/5 | E63: 100kW以下 | F63: 2021/8月 | G63: 五年一個package，共5年 (無專人監控，提供一套系統平臺，供維運及管理電站) | H63: 詹前鋒 | I63: 0937-099-803 | J63: max@thingnario.com | K63: 25000
B64: 慧景 | C64: 慧景網站監控 | D64: =K64/5 | E64: 99~249kW | F64: 2021/8月 | H64: 詹前鋒 | I64: 0937-099-803 | J64: max@thingnario.com | K64: 35000
B65: 慧景 | C65: 慧景網站監控 | D65: =K65/5 | E65: 249~499kW | F65: 2021/8月 | H65: 詹前鋒 | I65: 0937-099-803 | J65: max@thingnario.com | K65: 45000
B66: 慧景 | C66: 慧景網站監控 | D66: =K66/5 | E66: 499~999kW | F66: 2021/8月 | H66: 詹前鋒 | I66: 0937-099-803 | J66: max@thingnario.com | K66: 65000
B67: 慧景 | C67: 慧景網站監控 | D67: =K67/20 | E67: 99kW以下 | F67: 2021/8月 | G67: 五年一個package，共20年 (無專人監控，提供一套系統平臺，供維運及管理電站) | H67: 詹前鋒 | I67: 0937-099-803 | J67: max@thingnario.com | K67: =K63*4
B68: 慧景 | C68: 慧景網站監控 | D68: =K68/20 | E68: 99~249kW | F68: 2021/8月 | H68: 詹前鋒 | I68: 0937-099-803 | J68: max@thingnario.com | K68: =K64*4
B69: 慧景 | C69: 慧景網站監控 | D69: =K69/20 | E69: 249~499kW | F69: 2021/8月 | H69: 詹前鋒 | I69: 0937-099-803 | J69: max@thingnario.com | K69: =K65*4
B70: 慧景 | C70: 慧景網站監控 | D70: =K70/20 | E70: 499~999kW | F70: 2021/8月 | H70: 詹前鋒 | I70: 0937-099-803 | J70: max@thingnario.com | K70: =K66*4
B71: 慧景 | C71: 慧景網站監控 | D71: =K71/20 | E71: 99kW以下 | F71: 2021/8月 | G71: 二十年一個package，共20年 (無專人監控，提供一套系統平臺，供維運及管理電站) | H71: 詹前鋒 | I71: 0937-099-803 | J71: max@thingnario.com | K71: =K67*L71 | L71: 0.95
B72: 慧景 | C72: 慧景網站監控 | D72: =K72/20 | E72: 99~249kW | F72: 2021/8月 | H72: 詹前鋒 | I72: 0937-099-803 | J72: max@thingnario.com | K72: =K68*L71
B73: 慧景 | C73: 慧景網站監控 | D73: =K73/20 | E73: 249~499kW | F73: 2021/8月 | H73: 詹前鋒 | I73: 0937-099-803 | J73: max@thingnario.com | K73: =K69*L71
B74: 慧景 | C74: 慧景網站監控 | D74: =K74/20 | E74: 499~999kW | F74: 2021/8月 | H74: 詹前鋒 | I74: 0937-099-803 | J74: max@thingnario.com | K74: =K70*L71
B76: Dreams系統 | C76: 同一廠址總裝置容量500kW以上時，須裝設遙控監視設備並接受台電安全調度(110.08.05)
B77: 廠商 | C77: 規格 | D77: 報價(台幣) | E77: KW | F77: 報價時間 | G77: NOTE | H77: 聯絡人 | I77: 聯絡方式 | J77: Email | K77: 報價(台幣/年)
B78: 沅碁 | C78: 沅碁網站監控 | D78: =K78*20 | E78: - | F78: 2021/8月 | G78: 5年一個package，年繳，無SIM卡，無KW級距，含logger，不含施工 | H78: 王振城 | I78: 0928-225-333 | J78: max@sunedge.com.tw | K78: 1200
B79: 沅碁 | C79: 沅碁網站監控 | D79: =K79*20 | E79: - | F79: 2021/8月 | G79: 20年一個package，年繳，無SIM卡，無KW級距，含logger，不含施工 | H79: 王振城 | I79: 0928-225-333 | J79: max@sunedge.com.tw | K79: 1050
B80: 沅碁 | C80: 沅碁網站監控 | D80: 28000 | E80: 500~1MW | F80: 2021/9月 | G80: 5年 | H80: 王振城 | I80: 0928-225-333 | J80: max@sunedge.com.tw
B81: 沅碁 | C81: 沅碁網站監控 | D81: 35000 | E81: 500~1MW | F81: 2021/9月 | G81: 5年+4G SIM卡 | H81: 王振城 | I81: 0928-225-333 | J81: max@sunedge.com.tw
B82: 沅碁 | C82: 沅碁網站監控 | D82: 102000 | E82: 500~1MW | F82: 2021/9月 | G82: 20年 | H82: 王振城 | I82: 0928-225-333 | J82: max@sunedge.com.tw
B83: 沅碁 | C83: 沅碁網站監控 | D83: 130000 | E83: 500~1MW | F83: 2021/9月 | G83: 20年+4G SIM卡 | H83: 王振城 | I83: 0928-225-333 | J83: max@sunedge.com.tw
B84: 沅碁 | C84: 沅碁網站監控 | D84: 68000 | E84: 1MW以上 | F84: 2021/9月 | G84: 5年 | H84: 王振城 | I84: 0928-225-333 | J84: max@sunedge.com.tw
B85: 沅碁 | C85: 沅碁網站監控 | D85: 75000 | E85: 1MW以上 | F85: 2021/9月 | G85: 5年+4G SIM卡 | H85: 王振城 | I85: 0928-225-333 | J85: max@sunedge.com.tw
B86: 沅碁 | C86: 沅碁網站監控 | D86: 222000 | E86: 1MW以上 | F86: 2021/9月 | G86: 20年 | H86: 王振城 | I86: 0928-225-333 | J86: max@sunedge.com.tw
B87: 沅碁 | C87: 沅碁網站監控 | D87: 250000 | E87: 1MW以上 | F87: 2021/9月 | G87: 20年+4G SIM卡 | H87: 王振城 | I87: 0928-225-333 | J87: max@sunedge.com.tw
B89: 廠商 | C89: 規格 | D89: 報價(台幣) | E89: KW | F89: 報價時間 | G89: NOTE | H89: 聯絡人 | I89: 聯絡方式 | J89: Email | K89: 報價(台幣/年)
B90: 三惟 | C90: 三惟網站監控 | D90: =K90*20 | E90: - | F90: 2021/8月 | G90: 20年，年繳，無SIM卡，無KW級距 | H90: 詹前鋒 | I90: 0937-099-803 | J90: max@thingnario.com | K90: 3000
B91: 三惟 | C91: 台電Dreams系統 上線設定 | D91: 55000 | E91: 1式 | F91: 2021/8月 | G91: 含雲端Gateway+電源供應器(保固一年，延保5年一次 $10,000 未稅)， 台電Dreams申請跑件、雲端上線，Dreams VPN訊號測試 | H91: 詹前鋒 | I91: 0937-099-803 | J91: max@thingnario.com | K91: 3000
B93: 廠商 | C93: 規格 | D93: 報價(台幣) | E93: KW | F93: 報價時間 | G93: NOTE | H93: 聯絡人 | I93: 聯絡方式 | J93: Email | K93: 備註
B94: 慧景 | C94: 慧景網站監控 | D94: 35000 | E94: 500~1MW | F94: 2021/8月 | G94: 5年 | H94: 詹前鋒 | I94: 0937-099-803 | J94: max@thingnario.com | K94: 1.SIM卡 $6000(5年)=$1200(1年)=$100(1個月)
B95: 慧景 | C95: 慧景網站監控 | D95: 41000 | E95: 500~1MW | F95: 2021/8月 | G95: 5年+SIM卡 | H95: 詹前鋒 | I95: 0937-099-803 | J95: max@thingnario.com | K95: 2.報價內含了logger (軟硬體皆含)
B96: 慧景 | C96: 慧景網站監控 | D96: 200000 | E96: 500~1MW | F96: 2021/8月 | G96: 20年 | H96: 詹前鋒 | I96: 0937-099-803 | J96: max@thingnario.com | K96: 3.買監控20年一次付清送Dreams
B97: 慧景 | C97: 慧景網站監控 | D97: 224000 | E97: 500~1MW | F97: 2021/8月 | G97: 20年+SIM卡 | H97: 詹前鋒 | I97: 0937-099-803 | J97: max@thingnario.com | K97: 4.不含環控設備(日照計、溫度計)
B98: 慧景 | C98: 慧景網站監控 | D98: 72000 | E98: 1~2MW | F98: 2021/8月 | G98: 5年+SIM卡 | H98: 詹前鋒 | I98: 0937-099-803 | J98: max@thingnario.com | K98: 5.硬體設備保固同軟體年限(雷擊不保固)
B99: 慧景 | C99: 慧景網站監控 | D99: 288000 | E99: 1~2MW | F99: 2021/8月 | G99: 20年+SIM卡 | H99: 詹前鋒 | I99: 0937-099-803 | J99: max@thingnario.com
B101: 雲端系統+Dreams系統
B102: 廠商 | C102: 規格 | D102: 報價(台幣) | E102: KW | F102: 報價時間 | G102: NOTE | H102: 聯絡人 | I102: 聯絡方式 | J102: Email
B103: 沅碁 | C103: 沅碁網站監控 | E103: 500~1MW | F103: 2021/9月 | G103: 5年 | H103: 王振城 | I103: 0928-225-333 | J103: max@sunedge.com.tw
B104: 沅碁 | C104: 沅碁網站監控 | D104: 92000 | E104: 500~1MW | F104: 2021/9月 | G104: 5年+4G SIM卡 | H104: 王振城 | I104: 0928-225-333 | J104: max@sunedge.com.tw
B105: 沅碁 | C105: 沅碁網站監控 | E105: 500~1MW | F105: 2021/9月 | G105: 20年 | H105: 王振城 | I105: 0928-225-333 | J105: max@sunedge.com.tw
B106: 沅碁 | C106: 沅碁網站監控 | D106: 308800 | E106: 500~1MW | F106: 2021/9月 | G106: 20年+4G SIM卡 | H106: 王振城 | I106: 0928-225-333 | J106: max@sunedge.com.tw
B107: 沅碁 | C107: 沅碁網站監控 | E107: 1~2MW | F107: 2021/9月 | G107: 5年 | H107: 王振城 | I107: 0928-225-333 | J107: max@sunedge.com.tw
B108: 沅碁 | C108: 沅碁網站監控 | D108: 180000 | E108: 1~2MW | F108: 2021/9月 | G108: 5年+4G SIM卡 | H108: 王振城 | I108: 0928-225-333 | J108: max@sunedge.com.tw
B109: 沅碁 | C109: 沅碁網站監控 | E109: 1~2MW | F109: 2021/9月 | G109: 20年 | H109: 王振城 | I109: 0928-225-333 | J109: max@sunedge.com.tw
B110: 沅碁 | C110: 沅碁網站監控 | D110: 584000 | E110: 1~2MW | F110: 2021/9月 | G110: 20年+4G SIM卡 | H110: 王振城 | I110: 0928-225-333 | J110: max@sunedge.com.tw
B112: 廠商 | C112: 規格 | D112: 報價(台幣) | E112: KW | F112: 報價時間 | G112: NOTE | H112: 聯絡人 | I112: 聯絡方式 | J112: Email
B113: 慧景 | C113: 慧景網站監控 | D113: 200000 | E113: 500~1MW | F113: 2021/8月 | G113: 20年 | H113: 詹前鋒 | I113: 0937-099-803 | J113: max@thingnario.com
...

Sheet 模組
B2: 選用廠商 | C2: 型號 | D2: 瓦數/片 | E2: 報價(USD/W) | G2: 模組型號 | H2: XS54-CH410 | I2: *美金利率
B3: 晶科 | D3: 550 | E3: 0.3 | G3: 模組價格(元/片) | H3: =156.57*32 | I3: 156.57x32
B6: 廠商 | C6: 型號 | D6: 瓦數/片 | E6: 報價(USD/W) | F6: 報價時間 | G6: USD/PCS | H6: 交期 | I6: 範圍 | J6: 備註 | K6: 聯絡人 | L6: 信箱 | M6: 電話
B7: 錸德 | C7: 多晶 | D7: 245 | E7: 0.57
B8: 錸德 | C8: 多晶 | D8: 245 | E8: 0.58
B9: 安集 | C9: 多晶 | D9: 250 | E9: 0.61
B10: 安集 | C10: 多晶 | D10: 270 | E10: 0.64 | F10: 20160317 | H10: 06-5105988 | K10: 張小姐
B11: 安集 | C11: 單晶 | D11: 285 | E11: 0.59 | F11: 20160322 | H11: 06-5105988 | K11: 張小姐
B12: AUO | C12: 單晶 | D12: 320 | E12: 0.92 | F12: 20160114 | G12: 翰可經銷商 | H12: 0922774818 | I12: wen.pan@skwentex.net | K12: 潘先生
B13: AUO | C13: 單晶 | D13: 325 | E13: 0.94 | F13: 20160114 | G13: 翰可經銷商 | H13: 0922774818 | I13: wen.pan@skwentex.net | K13: 潘先生
B14: AUO | C14: 單晶 | D14: 327 | E14: 0.94 | F14: 20160114 | G14: 翰可經銷商 | H14: 0922774818 | K14: 潘先生
B15: AUO | C15: 單晶 | D15: 330 | E15: 0.95 | F15: 20160114 | G15: 翰可經銷商 | H15: 0922774818 | K15: 潘先生
B16: 元晶 | C16: 單晶 | D16: 285 | E16: 0.59 | F16: 20160512 | H16: 0905058123 | J16: 499KWbase; 單晶模組; 金能獎 | K16: 游先生
B17: 元晶 | C17: 單晶 | D17: 285 | E17: 0.52 | F17: 20161006 | H17: 0905058123 | J17: 499KWbase; 單晶模組; 金能獎 | K17: 游先生
B18: 元晶 | C18: 單晶 | D18: 290 | E18: 0.56 | F18: 20161106 | H18: 0905058123 | J18: 499KWbase; 單晶模組; 標檢 | K18: 游先生
B19: 元晶 | C19: 單晶 | D19: 290 | E19: 0.52 | F19: 20170209 | J19: 1000片 / 290W/片 | K19: Alex
B20: 元晶 | C20: 單晶 | D20: 290 | E20: 0.505 | F20: 20180101 | J20: 2M / 290W/片 | K20: 游先生
B21: 新日光 | C21: 單晶 | D21: 310 | E21: 0.5 | F21: 20180101 | K21: Josh
B22: AUO | C22: 單晶 | D22: 295 | E22: 0.5 | F22: 20180205 | K22: Alan
B23: AUO | C23: 單晶 | D23: 300 | E23: 0.5 | F23: 20180205 | K23: Alan
B24: 元晶 | C24: 單晶 | D24: 295 | E24: 0.46 | F24: 20180515 | K24: 范小姐
B25: 元晶 | C25: 單晶 | D25: 300 | E25: 0.465 | F25: 20180515 | K25: 范小姐
B26: 昇陽 | C26: 單晶 | D26: 300 | E26: 0.47 | F26: 20180515 | H26: 0958230080 | I26: joshchiu@solartech-energy.com | K26: 邱宗譽
B27: 元晶 | C27: 單晶 | D27: 300 | E27: 0.46 | F27: 20180605 | K27: 范小姐
B28: 新日光 | C28: 單晶 | D28: 310 | E28: 0.47 | F28: 20180615 | K28: Josh
B29: 元晶 | C29: 單晶 | D29: 300 | E29: 0.43 | F29: 20180709 | K29: 范小姐
B30: 安集 | C30: 多晶雙玻 | D30: 275 | E30: 0.53 | F30: 20180625 | K30: 張小姐
B31: 綠能 | C31: 多晶輕量化 | D31: 280 | E31: 0.61 | F31: 20180629 | J31: 高效 | K31: 彭小姐
B32: 元晶 | C32: 單晶 | D32: 300 | E32: 0.395 | F32: 20181024 | K32: 施小姐
B33: 元晶 | C33: 單晶 | D33: 305 | E33: 0.38 | F33: 20190321 | K33: 施小姐
B34: 元晶 | C34: 單晶 | D34: 310 | E34: 0.38 | F34: 20190321 | K34: 施小姐
B35: 新日光 | C35: 單晶 | D35: 310 | E35: 0.37 | F35: 20190515 | K35: Josh
B36: 元晶 | C36: 單晶 | D36: 305 | E36: 0.365 | F36: 20190523 | K36: 施小姐
B37: 元晶 | C37: 單晶 | D37: 305 | E37: 0.36 | F37: 20190523 | K37: 施小姐
B38: 元晶 | C38: 單晶 | D38: 305 | E38: 0.35 | F38: 20191017 | I38: 305310315 | J38: 1.2m加價0.015USD/W | K38: 施小姐
B39: 元晶 | C39: 單晶 | D39: 310 | E39: 0.35 | F39: 20191017 | I39: 305310315 | J39: 一個月前告知 | K39: 施小姐
B40: 元晶 | C40: 單晶 | D40: 315 | E40: 0.35 | F40: 20191017 | I40: 305310315 | K40: 施小姐
B41: 有成 | C41: 單晶 | D41: 310 | E41: 0.35 | F41: 20191031 | I41: 300305310 | K41: 陳思豪
B42: 有成 | C42: 單晶 | D42: 330 | E42: 0.37 | F42: 20191031 | I42: 330340 | K42: 陳思豪
B43: 元晶 | C43: 單晶 | D43: 315 | E43: 0.34 | F43: 20200114 | I43: 305310315320 | J43: M2電池片，MC4 | K43: 施小姐
B44: 元晶 | C44: 單晶 | D44: 320 | E44: 0.34 | F44: 20200114 | I44: 305310315320 | J44: M2電池片，MC4 | K44: 施小姐
B45: 聯合(全片) | C45: 單晶 | D45: 310 | E45: 0.345 | F45: 20200114 | I45: 310315 | J45: M2電池片，MC4 | K45: Josh
B46: 聯合(半切) | C46: 單晶 | D46: 320 | E46: 0.34 | F46: 20200114 | I46: 320325 | J46: M2電池片，MC4 | K46: Josh
B47: 友達(半切) | C47: 單晶 | D47: 350 | E47: 0.35 | F47: 20200113 | G47: 翰可經銷商 | H47: 難產中 | I47: 340345350 | J47: M4電池片 | K47: 徐珮甄
B48: 有成 | C48: 單晶 | D48: 340 | E48: 0.35 | F48: 20200114 | I48: 330340 | J48: M4電池片，MC4 | K48: 陳思豪
B49: 有成 | C49: 單晶 | D49: 330 | E49: 0.33 | F49: 20201120 | G49: 33 | I49: 325330 | J49: G1電池片，MC4 | K49: 陳思豪
B50: 元晶 | C50: 單晶 | D50: 330 | E50: 0.33 | F50: 20201026 | G50: 32 | I50: 325330 | J50: G1電池片，MC4(一般型R) | K50: 施小姐
B51: 元晶(M) | C51: 單晶 | D51: 330 | E51: 0.33 | F51: 20201026 | G51: 325 | I51: 325330 | J51: G1電池片，MC4(鹽灘型M) | K51: 施小姐
B52: 元晶(半切) | C52: 單晶 | D52: 335 | E52: 0.33 | F52: 20201201 | G52: 32 | I52: 330335 | J52: G1電池片，MC4(一般型R) | K52: 施小姐
B53: 聯合(全片) | C53: 單晶 | D53: 330 | E53: 0.33 | F53: 20201023 | I53: 350 | J53: G1電池片，MC4 | K53: Josh
B54: 聯合(半切) | C54: 單晶 | D54: 340 | E54: 0.33 | F54: 20201023 | G54: 32 | I54: 350 | J54: G1電池片，MC4 | K54: Josh
B55: 有成 | C55: 單晶 | D55: 340 | E55: 0.44 | F55: 20210609 | I55: 330340 | J55: M4電池片，MC4 | K55: 陳思豪
B56: 元晶 | C56: 單晶 | D56: 330 | E56: 0.41 | F56: 20210609 | I56: 325330 | J56: G1電池片，MC4(一般型R) | K56: 施小姐
B57: 元晶 | C57: 單晶 | D57: 330 | E57: 0.407 | F57: 20210726 | I57: 325330 | J57: G1電池片，EVO2(一般型R) | K57: 施小姐
B58: 元晶(半切) | C58: 單晶 | D58: 340 | E58: 0.41 | F58: 20210726 | I58: 335340 | J58: G1電池片，EVO2(一般型R) | K58: 施小姐
B59: 元晶(半切) | C59: 單晶 | D59: 360 | E59: =G59/D59/#REF! | F59: 20211217 | G59: 4792 | I59: 360365370375 | J59: M6電池片，佳明(一般型R) | K59: 施小姐
B60: 元晶(半切) | C60: 單晶 | D60: 365 | E60: =G60/D60/#REF! | F60: 20211217 | G60: 4810 | I60: 360365370375 | J60: M6電池片，佳明(一般型R) | K60: 施小姐
B61: 元晶(半切) | C61: 單晶 | D61: 370 | E61: =G61/D61/#REF! | F61: 20211217 | G61: 4928 | I61: 360365370375 | J61: M6電池片，佳明(一般型R) | K61: 施小姐
B62: 有成(半切) | C62: 單晶 | D62: 375 | E62: 0.49 | F62: 20211231 | G62: 4928 | I62: 375 | J62: M6電池片，QC4 | K62: 陳思豪
B63: 同昱(半切) | C63: 單晶 | D63: 370 | E63: =G63/D63/#REF! | F63: 20220302 | G63: 5000 | I63: 370375380 | J63: M6電池片，PV-CO02 | K63: 唐先生
B64: 茂迪(半切) | C64: 單晶 | D64: 370 | E64: =G64/D64/#REF! | F64: 20220324 | G64: 5112 | H64: 雙面 | I64: 370375380 | J64: M6電池片，輝朗 | K64: 劉小姐
B65: 茂迪(半切) | C65: 單晶 | D65: 370 | E65: =G65/D65/#REF! | F65: 20220324 | G65: 5006 | H65: 單面 | I65: 370375380 | J65: M6電池片，輝朗 | K65: 劉小姐
B66: 元晶(半切) | C66: 單晶 | D66: 370 | E66: =G66/D66/#REF! | F66: 20220622 | G66: 5300 | I66: 360365370375 | J66: M6電池片，佳明(一般型R) | K66: 施小姐
B67: 有成(半切) | C67: 單晶 | D67: 375 | E67: 0.5 | F67: 20220621 | G67: =E67*29.72*375 | H67: WSP(抗颱框) | I67: 375 | J67: M6電池片，QC4 | K67: 陳思豪
B68: 有成(半切) | C68: 單晶 | D68: 375 | E68: 0.49 | F68: 20220621 | G68: =E68*29.72*375 | H68: WST(一般框) | I68: 375 | J68: M6電池片，QC4 | K68: 陳思豪
B69: 有成(半切) | C69: 單晶 | D69: 375 | E69: 0.49 | F69: 20220621 | G69: =E69*29.72*375 | H69: WST(一般框) | I69: 376 | J69: M6電池片，QC5 | K69: 陳思豪
B70: 有成(半切) | C70: 單晶 | D70: 375 | E70: 0.49 | F70: 20220621 | G70: =E70*29.72*375 | H70: WST(一般框) | I70: 377 | J70: M6電池片，QC6 | K70: 陳思豪
B71: 有成(半切) | C71: 單晶 | D71: 375 | E71: 0.49 | F71: 20220621 | G71: =E71*29.72*375 | H71: WST(一般框) | I71: 378 | J71: M6電池片，QC7 | K71: 陳思豪
B72: 有成(半切) | C72: 單晶 | D72: 375 | E72: 0.49 | F72: 20220621 | G72: =E72*29.72*375 | H72: WST(一般框) | I72: 379 | J72: M6電池片，QC8 | K72: 陳思豪
B73: 有成(半切) | C73: 單晶 | D73: 375 | E73: 0.49 | F73: 20220621 | G73: =E73*29.72*375 | H73: WST(一般框) | I73: 380 | J73: M6電池片，QC9 | K73: 陳思豪
B74: 有成(半切) | C74: 單晶 | D74: 375 | E74: 0.49 | F74: 20220621 | G74: =E74*29.72*375 | H74: WST(一般框) | I74: 381 | J74: M6電池片，QC10 | K74: 陳思豪
B75: 茂迪 | C75: XS60CD | D75: 380 | E75: =184.3/D75 | F75: 44889 | G75: =E75*D75 | H75: 2023年Q2 | I75: 370375380385 | J75: M6電池片 | K75: 鄭雅君 | L75: ann_cheng@motech.com.tw | M75: 06-505-0789#0452
B76: 茂迪 | C76: XN60CD-B | D76: 390 | E76: =210.6/D76 | F76: 44889 | G76: =E76*D76 | H76: 2023年Q2 | I76: 370375380386 | J76: M6電池片，雙面(TOPCon) | K76: 鄭雅君 | L76: ann_cheng@motech.com.tw | M76: 06-505-0789#0452
B77: 元晶 | C77: TS54-BMH-*** H1 | D77: 405 | H77: 2023年Q1 | I77: 390395400405410 | J77: M10電池片，108P | K77: 施旭芳 | L77: suifang.shih@tsecpv.com | M77: 0928-810-056
B78: 元晶 | C78: TS60-BMH-*** H1 | D78: 455 | H78: 2023年Q2 | I78: 435,440,445,450,455 ,460 | J78: M10電池片，120P | K78: 施旭芳 | L78: suifang.shih@tsecpv.com | M78: 0928-810-056
B79: 有成 | C79: WST-375MGL | D79: 375 | E79: 0.475 | F79: 44893 | G79: =E79*D79 | H79: 2023年Q1 | I79: 375 | J79: M6電池片，120P | K79: 陳思豪 | L79: j.chen@winaico.com | M79: 0921-756-757

Sheet 微逆變
B2: 選用廠商 | C2: 型號 | D2: 規格(W) | E2: 報價(USD/台)
B3: =B13 | C3: =C13 | D3: =D13 | E3: =E13
B6: 廠商 | C6: 型號 | D6: 規格(W) | E6: 報價(USD/台) | F6: 報價時間 | G6: NOTE | H6: 聯絡人 | I6: 聯絡方式 | J6: Email
B7: SolarBridge | C7: P250LV-208/240 | D7: 250 | E7: 135 | F7: 2014 | G7: 1DC in; 含運+廠商組裝
B8: APS | D8: 500 | E8: 190 | F8: 2015 | G8: 2DC in; 含運+廠商組裝
B9: APS | C9: YC500 | D9: 500 | E9: 155 | F9: 2017 | H9: Charles更正
B10: APS | C10: YC1000 | D10: 1000 | E10: 252 | F10: 2018 | G10: 一台220+4mT接頭32 | H10: Charles
B11: APS | C11: QS1 | D11: 1200 | E11: 222 | F11: 2019 | G11: 一台189+總線1T1012.5/150=6.75+1.02+2.33+2.93 | H11: 麗芳
B12: APS | C12: QS1 | D12: 1200 | E12: 210 | F12: 2019 | G12: 一台199+總線1T1012.5/150=6.75+1.02+((2.33+2.93)/3) | H12: 麗芳
B13: APS | C13: QS1 | D13: 1200 | E13: 233 | F13: 2023 | G13: 一台222+總線1T1120/150=7.47+1.02+((2.33+2.93)/3) | H13: 麗芳
C20: 更新
D21: 199/台(2020/1)
C22: =6.75+1.02+((2.33+2.93)/3)+199
D23: =1012.5/150
H26: 202.03
H27: 一台189+總線1T1012.5/150=6.75+1.02+2.33+2.93
D35: 44944
C36: =7.47+1.02+((2.33+2.93)/3)+222
D37: =1120/150

Sheet 逆變
B2: 選用廠商 | C2: 型號 | D2: 規格(KW) | E2: 報價(台幣/KW) | F2: 總報價 (台幣/台) | G2: 台 | I2: 選用廠商 | J2: 型號 | K2: 規格(KW) | L2: 報價(台幣/KW) | M2: 總報價 (台幣/台) | N2: 台
B3: =B168 | C3: =C168 | D3: =D168 | E3: =E168 | F3: =F168 | G3: 1 | I3: 碩天 | J3: CPSPV120KETL | K3: 120 | L3: =M3/K3 | M3: 130800 | N3: 3
B4: =B176 | C4: =C176 | D4: =D176 | E4: =E176 | F4: =F176 | G4: =4+7 | I4: 碩天 | J4: CPSPV22000ETLA | K4: 22 | L4: =M4/K4 | M4: 48720 | N4: 2
B8: 總價 | F8: =(F3*G3)+(F4*G4)+(F5*G5)+(F6*G6)+(F7*G7) | I8: 總價 | M8: =(M3*N3)+(M4*N4)+(M5*N5)+(M6*N6)+(M7*N7)
B11: 廠商 | C11: 型號 | D11: 規格(KW) | E11: 報價(台幣/KW) | F11: 總報價 (台幣/台) | G11: 報價時間 | H11: NOTE | I11: 聯絡人 | J11: 聯絡方式 | K11: Email
B12: 碩天 | C12: CPSPV10000ETL-S | D12: 10 | E12: =F12/D12 | F12: 29650 | G12: 20200116 | H12: 5年保固 | I12: 許照陽 Aaron Hsu | J12: 0972-981383 | K12: Aaron.Hsu@cyberpower.com
B13: 碩天 | C13: CPSPV10000ETL-S | D13: 10 | E13: =F13/D13 | F13: 37063 | G13: 20200116 | H13: 10年保固 | I13: 許照陽 Aaron Hsu | J13: 0972-981383 | K13: Aaron.Hsu@cyberpower.com
B14: 碩天 | C14: CPSPV10000ETL-S | D14: 10 | E14: =F14/D14 | F14: 59300 | G14: 20200116 | H14: 20年保固 | I14: 許照陽 Aaron Hsu | J14: 0972-981383 | K14: Aaron.Hsu@cyberpower.com
B15: 碩天 | C15: CPSPV20000ETL | D15: 20 | E15: =F15/D15 | F15: 52100 | G15: 20200116 | H15: 5年保固 | I15: 許照陽 Aaron Hsu | J15: 0972-981383 | K15: Aaron.Hsu@cyberpower.com
B16: 碩天 | C16: CPSPV20000ETL | D16: 20 | E16: =F16/D16 | F16: 65125 | G16: 20200116 | H16: 10年保固 | I16: 許照陽 Aaron Hsu | J16: 0972-981383 | K16: Aaron.Hsu@cyberpower.com
B17: 碩天 | C17: CPSPV20000ETL | D17: 20 | E17: =F17/D17 | F17: 104200 | G17: 20200116 | H17: 20年保固 | I17: 許照陽 Aaron Hsu | J17: 0972-981383 | K17: Aaron.Hsu@cyberpower.com
B18: 碩天 | C18: CPSPV30000ETL | D18: 30 | E18: =F18/D18 | F18: 59550 | G18: 20200116 | H18: 5年保固 | I18: 許照陽 Aaron Hsu | J18: 0972-981383 | K18: Aaron.Hsu@cyberpower.com
B19: 碩天 | C19: CPSPV30000ETL | D19: 30 | E19: =F19/D19 | F19: 74438 | G19: 20200116 | H19: 10年保固 | I19: 許照陽 Aaron Hsu | J19: 0972-981383 | K19: Aaron.Hsu@cyberpower.com
B20: 碩天 | C20: CPSPV30000ETL | D20: 30 | E20: =F20/D20 | F20: 119100 | G20: 20200116 | H20: 20年保固 | I20: 許照陽 Aaron Hsu | J20: 0972-981383 | K20: Aaron.Hsu@cyberpower.com
B21: 碩天 | C21: CPSPV33000ETL | D21: 33 | E21: =F21/D21 | F21: 63855 | G21: 20200116 | H21: 5年保固 | I21: 許照陽 Aaron Hsu | J21: 0972-981383 | K21: Aaron.Hsu@cyberpower.com
B22: 碩天 | C22: CPSPV33000ETL | D22: 33 | E22: =F22/D22 | F22: 79819 | G22: 20200116 | H22: 10年保固 | I22: 許照陽 Aaron Hsu | J22: 0972-981383 | K22: Aaron.Hsu@cyberpower.com
B23: 碩天 | C23: CPSPV33000ETL | D23: 33 | E23: =F23/D23 | F23: 127710 | G23: 20200116 | H23: 20年保固 | I23: 許照陽 Aaron Hsu | J23: 0972-981383 | K23: Aaron.Hsu@cyberpower.com
... B26: 碩天 | C26: CPSPV50000ETL-WB | D26: 50 | E26: =F26/D26 | F26: 172500 | G26: 20200116 | H26: 20年保固 (3Φ220/380V) | I26: 李旻珊 Vivi | J26: 0972-981383 | K26: Aaron.Hsu@cyberpower.com
B27: 碩天 | C27: CPSPV66000ETL-WB | D27: 66 | E27: =F27/66 | F27: 94710 | G27: 20200116 | H27: 5年保固 (3Φ277/480V) | I27: 李旻珊 Vivi | J27: 0972-981383 | K27: Aaron.Hsu@cyberpower.com
B28: 碩天 | C28: CPSPV66000ETL-WB | D28: 66 | E28: =F28/66 | F28: 118388 | G28: 20200116 | H28: 10年保固 (3Φ277/480V) | I28: 李旻珊 Vivi | J28: 0972-981383 | K28: Aaron.Hsu@cyberpower.com
B29: 碩天 | C29: CPSPV66000ETL-WB | D29: 66 | E29: =F29/66 | F29: 189420 | G29: 20200116 | H29: 20年保固 (3Φ277/480V) | I29: 李旻珊 Vivi | J29: 0972-981383 | K29: Aaron.Hsu@cyberpower.com
B30: 碩天 | C30: CPSPV50000ETL-WB | D30: 50 | E30: =F30/D30 | F30: 82500 | G30: 20200116 | H30: 5年保固(200M) | I30: 李旻珊 Vivi | J30: 0972-981383 | K30: Aaron.Hsu@cyberpower.com
B31: 碩天 | C31: CPSPV50000ETL-WB | D31: 50 | E31: =F31/D31 | F31: 165000 | G31: 20200116 | H31: 20年保固(200M) | I31: 李旻珊 Vivi | J31: 0972-981383 | K31: Aaron.Hsu@cyberpower.com
B32: 碩天 | C32: CPSPV66000-WB | D32: 66 | E32: =F32/D32 | F32: 92334 | G32: 20200116 | H32: 5年保固(200M) | I32: 李旻珊 Vivi | J32: 0956-805-911 | K32: Aaron.Hsu@cyberpower.com
B33: 碩天 | C33: CPSPV66000-WB | D33: 66 | E33: =F33/D33 | F33: 184668 | G33: 20200116 | H33: 20年保固(200M) | I33: 李旻珊 Vivi | J33: 0956-805-911 | K33: Aaron.Hsu@cyberpower.com
B34: 碩天 | C34: CPSPV3000ETLA | D34: 3 | E34: =F34/D34 | F34: 14400 | G34: 20210628 | H34: 5年保固 (1Φ) | I34: 李旻珊 Vivi | J34: 0972-981383 | K34: Vivi.Li@cyberpower.com
B35: 碩天 | C35: CPSPV3000ETLA | D35: 3 | E35: =F35/D35 | F35: 18000 | G35: 20210628 | H35: 10年保固 (1Φ) | I35: 李旻珊 Vivi | J35: 0972-981383 | K35: Vivi.Li@cyberpower.com
B36: 碩天 | C36: CPSPV3600ETLA | D36: 3.6 | E36: =F36/D36 | F36: 15840 | G36: 20210628 | H36: 5年保固 (1Φ) | I36: 李旻珊 Vivi | J36: 0972-981383 | K36: Vivi.Li@cyberpower.com
B37: 碩天 | C37: CPSPV3600ETLA | D37: 3.6 | E37: =F37/D37 | F37: 19800 | G37: 20210628 | H37: 10年保固 (1Φ) | I37: 李旻珊 Vivi | J37: 0972-981383 | K37: Vivi.Li@cyberpower.com
B38: 碩天 | C38: CPSPV6000ETLA | D38: 6 | E38: =F38/D38 | F38: 19800 | G38: 20210628 | H38: 5年保固 (1Φ) | I38: 李旻珊 Vivi | J38: 0972-981383 | K38: Vivi.Li@cyberpower.com
B39: 碩天 | C39: CPSPV6000ETLA | D39: 6 | E39: =F39/D39 | F39: 24750 | G39: 20210628 | H39: 10年保固 (1Φ) | I39: 李旻珊 Vivi | J39: 0972-981383 | K39: Vivi.Li@cyberpower.com
B40: 碩天 | C40: CPSPV20000ETL | D40: 20 | E40: =F40/D40 | F40: 51600 | G40: 20210628 | H40: 5年保固 (3Φ220/380V) | I40: 李旻珊 Vivi | J40: 0972-981383 | K40: Vivi.Li@cyberpower.com
B41: 碩天 | C41: CPSPV20000ETL | D41: 20 | E41: =F41/D41 | F41: 64500 | G41: 20210628 | H41: 10年保固 (3Φ220/380V) | I41: 李旻珊 Vivi | J41: 0972-981383 | K41: Vivi.Li@cyberpower.com
... B55: 碩天 | C55: CPSPV22000ETLA-WB | D55: 22 | E55: =F55/D55 | F55: 113520 | G55: 20210628 | H55: 20年保固 (3Φ220/380V) | I55: 李旻珊 Vivi | J55: 0972-981383 | K55: Vivi.Li@cyberpower.com
B56: 碩天 | C56: CPSPV22000ETLA-WB | D56: 22 | E56: 2580 | F56: 56760 | G56: 20220930 | H56: 5年保固 (3Φ220/380V) | I56: 李旻珊 Vivi | J56: 0956-805911 | K56: Vivi.Li@cyberpower.com
B57: 碩天 | C57: CPSPV22000ETLA-WB | D57: 22 | E57: 5418.1818 | F57: 119200 | G57: 20220930 | H57: 20年保固 (3Φ220/380V) | I57: 李旻珊 Vivi | J57: 0956-805911 | K57: Vivi.Li@cyberpower.com
B58: 碩天 | C58: CPSPV30000ETLA-WB | D58: 30 | E58: =F58/D58 | F58: 61500 | G58: 20210628 | H58: 5年保固 (3Φ220/380V) | I58: 李旻珊 Vivi | J58: 0972-981383 | K58: Vivi.Li@cyberpower.com
B59: 碩天 | C59: CPSPV30000ETLA-WB | D59: 30 | E59: =F59/D59 | F59: 123000 | G59: 20210628 | H59: 20年保固 (3Φ220/380V) | I59: 李旻珊 Vivi | J59: 0972-981383 | K59: Vivi.Li@cyberpower.com
B60: 碩天 | C60: CPSPV30000ETLA-WB | D60: 30 | E60: 2050 | F60: 61500 | G60: 20220930 | H60: 5年保固 (3Φ220/380V) | I60: 李旻珊 Vivi | J60: 0956-805911 | K60: Vivi.Li@cyberpower.com
B61: 碩天 | C61: CPSPV30000ETLA-WB | D61: 30 | E61: 4306.6667 | F61: 129200 | G61: 20220930 | H61: 20年保固 (3Φ220/380V) | I61: 李旻珊 Vivi | J61: 0956-805911 | K61: Vivi.Li@cyberpower.com
B62: 碩天 | C62: CPSPV33000ETLA-WB | D62: 33 | E62: =F62/D62 | F62: 66000 | G62: 20210628 | H62: 5年保固 (3Φ220/380V) | I62: 李旻珊 Vivi | J62: 0972-981383 | K62: Vivi.Li@cyberpower.com
B63: 碩天 | C63: CPSPV33000ETLA-WB | D63: 33 | E63: =F63/D63 | F63: 132000 | G63: 20210628 | H63: 20年保固 (3Φ220/380V) | I63: 李旻珊 Vivi | J63: 0972-981383 | K63: Vivi.Li@cyberpower.com
B64: 碩天 | C64: CPSPV33000ETLA-WB | D64: 33 | E64: 2000 | F64: 66000 | G64: 20220930 | H64: 5年保固 (3Φ220/380V) | I64: 李旻珊 Vivi | J64: 0956-805911 | K64: Vivi.Li@cyberpower.com
B65: 碩天 | C65: CPSPV33000ETLA-WB | D65: 33 | E65: 4200 | F65: 138600 | G65: 20220930 | H65: 20年保固 (3Φ220/380V) | I65: 李旻珊 Vivi | J65: 0956-805911 | K65: Vivi.Li@cyberpower.com
B66: 碩天 | C66: CPSPV36000ETLA-WB | D66: 36 | E66: =F66/D66 | F66: 67680 | G66: 20210628 | H66: 5年保固 (3Φ220/380V) | I66: 李旻珊 Vivi | J66: 0972-981383 | K66: Vivi.Li@cyberpower.com
B67: 碩天 | C67: CPSPV36000ETLA-WB | D67: 36 | E67: =F67/D67 | F67: 135360 | G67: 20210628 | H67: 20年保固 (3Φ220/380V) | I67: 李旻珊 Vivi | J67: 0972-981383 | K67: Vivi.Li@cyberpower.com
B68: 碩天 | C68: CPSPV36000ETLA-WB | D68: 36 | E68: 1880 | F68: 67680 | G68: 20220930 | H68: 5年保固 (3Φ220/380V) | I68: 李旻珊 Vivi | J68: 0956-805911 | K68: Vivi.Li@cyberpower.com
B69: 碩天 | C69: CPSPV36000ETLA-WB | D69: 36 | E69: 3950 | F69: 142200 | G69: 20220930 | H69: 20年保固 (3Φ220/380V) | I69: 李旻珊 Vivi | J69: 0956-805911 | K69: Vivi.Li@cyberpower.com
B70: 碩天 | C70: CPSPV50000ETL-WB | D70: 50 | E70: =F70/D70 | F70: 79000 | G70: 20210628 | H70: 5年保固 (3Φ220/380V) | I70: 李旻珊 Vivi | J70: 0972-981383 | K70: Vivi.Li@cyberpower.com
B71: 碩天 | C71: CPSPV50000ETL-WB | D71: 50 | E71: =F71/D71 | F71: 158000 | G71: 20210628 | H71: 20年保固 (3Φ220/380V) | I71: 李旻珊 Vivi | J71: 0972-981383 | K71: Vivi.Li@cyberpower.com
B72: 碩天 | C72: CPSPV50000ETL-WB | D72: 50 | E72: 1710 | F72: 85500 | G72: 20220930 | H72: 5年保固 (3Φ220/380V) | I72: 李旻珊 Vivi | J72: 0956-805911 | K72: Vivi.Li@cyberpower.com
B73: 碩天 | C73: CPSPV50000ETL-WB | D73: 50 | E73: 3591 | F73: 179550 | G73: 20220930 | H73: 20年保固 (3Φ220/380V) | I73: 李旻珊 Vivi | J73: 0956-805911 | K73: Vivi.Li@cyberpower.com
B74: 碩天 | C74: CPSPV55000ETL-WB | D74: 55 | E74: =F74/D74 | F74: 81400 | G74: 20210628 | H74: 5年保固 (3Φ220/380V) | I74: 李旻珊 Vivi | J74: 0972-981383 | K74: Vivi.Li@cyberpower.com
B75: 碩天 | C75: CPSPV55000ETL-WB | D75: 55 | E75: =F75/D75 | F75: 162800 | G75: 20210628 | H75: 20年保固 (3Φ220/380V) | I75: 李旻珊 Vivi | J75: 0972-981383 | K75: Vivi.Li@cyberpower.com | L75: 12input、3MPPT(4/4/4)
B76: 台達電 | C76: H3_210 | D76: 3 | E76: =F76/D76 | F76: 42550 | G76: 20200130 | H76: 5年保固 | I76: 阿潘Chamber | J76: 0938-300-828 | K76: chamber@skwentex.net
B77: 台達電 | C77: H5A_220 | D77: 5 | E77: =F77/D77 | F77: 48100 | G77: 20200130 | H77: 5年保固 | I77: 阿潘Chamber | J77: 0938-300-828 | K77: chamber@skwentex.net
B78: 台達電 | C78: RPI-H5 | D78: 5 | E78: =F78/D78 | F78: 27000 | G78: 20200130 | H78: 5年保固 | I78: 阿潘Chamber | J78: 0938-300-828 | K78: chamber@skwentex.net
B79: 台達電 | C79: RPI-M10 | D79: 10.5 | E79: =F79/D79 | F79: 50000 | G79: 20200130 | H79: 5年保固 | I79: 阿潘Chamber | J79: 0938-300-828 | K79: chamber@skwentex.net
B80: 台達電 | C80: RPI-M10 | D80: 10.5 | E80: =F80/D80 | F80: 65000 | G80: 20200130 | H80: 10年保固 | I80: 阿潘Chamber | J80: 0938-300-828 | K80: chamber@skwentex.net
B81: 台達電 | C81: RPI-M10 | D81: 10.5 | E81: =F81/D81 | F81: 102500 | G81: 20200130 | H81: 20年保固 | I81: 阿潘Chamber | J81: 0938-300-828 | K81: chamber@skwentex.net
B82: 台達電 | C82: RPI-M20 | D82: 21 | E82: =F82/D82 | F82: 64000 | G82: 20200130 | H82: 5年保固 | I82: 阿潘Chamber | J82: 0938-300-828 | K82: chamber@skwentex.net
B83: 台達電 | C83: RPI-M20 | D83: 21 | E83: =F83/D83 | F83: 83200 | G83: 20200130 | H83: 10年保固 | I83: 阿潘Chamber | J83: 0938-300-828 | K83: chamber@skwentex.net
B84: 台達電 | C84: RPI-M20 | D84: 21 | E84: =F84/D84 | F84: =F82*2.05 | G84: 20200130 | H84: 20年保固 | I84: 阿潘Chamber | J84: 0938-300-828 | K84: chamber@skwentex.net
B85: 台達電 | C85: RPI-M30_121 | D85: 33 | E85: =F85/D85 | F85: 72000 | G85: 20200130 | H85: 5年保固 | I85: 阿潘Chamber | J85: 0938-300-828 | K85: chamber@skwentex.net
B86: 台達電 | C86: RPI-M30_121 | D86: 33 | E86: =F86/D86 | F86: 93600 | G86: 20200130 | H86: 10年保固 | I86: 阿潘Chamber | J86: 0938-300-828 | K86: chamber@skwentex.net
B87: 台達電 | C87: RPI-M30_121 | D87: 33 | E87: =F87/D87 | F87: =F85*2.05 | G87: 20200130 | H87: 20年保固 | I87: 阿潘Chamber | J87: 0938-300-828 | K87: chamber@skwentex.net
B88: 台達電 | C88: M70A_262 | D88: 70 | E88: =F88/D88 | F88: 150000 | G88: 20200917 | H88: 5年保固 (3Φ220/380V) | I88: 阿潘Chamber | J88: 0938-300-828 | K88: chamber@skwentex.net
B89: 台達電 | C89: M70A_262 | D89: 70 | E89: =F89/D89 | F89: =F88*1.95 | G89: 20200917 | H89: 20年保固 (3Φ220/380V) | I89: 阿潘Chamber | J89: 0938-300-828 | K89: chamber@skwentex.net
B90: 台達電 | C90: RPI-M88_122 | D90: 88 | E90: =F90/D90 | F90: 155000 | G90: 20200107 | H90: 5年保固(1~200M) | I90: 阿潘Chamber | J90: 0938-300-828 | K90: chamber@skwentex.net
B91: 台達電 | C91: RPI-M88_122 | D91: 88 | E91: =F91/D91 | F91: =F90*2 | G91: 20200107 | H91: 20年保固(1~200M) | I91: 阿潘Chamber | J91: 0938-300-828 | K91: chamber@skwentex.net
B92: 台達電 | C92: RPI-M100 | D92: 100 | E92: =F92/D92 | F92: 160000 | G92: 20200107 | H92: 5年保固(1~200M) | I92: 阿潘Chamber | J92: 0938-300-828 | K92: chamber@skwentex.net
B93: 台達電 | C93: RPI-M100 | D93: 100 | E93: =F93/D93 | F93: =F92*2 | G93: 20200107 | H93: 20年保固(1~200M) | I93: 阿潘Chamber | J93: 0938-300-828 | K93: chamber@skwentex.net
B94: 碩天 | C94: CPSPV55000ETL-WB | D94: 55 | E94: 1614.5455 | F94: 88800 | G94: 20220930 | H94: 5年保固 (3Φ220/380V) | I94: 李旻珊 Vivi | J94: 0956-805911 | K94: Vivi.Li@cyberpower.com
B95: 碩天 | C95: CPSPV55000ETL-WB | D95: 55 | E95: 3390.9091 | F95: 186500 | G95: 20220930 | H95: 20年保固 (3Φ220/380V) | I95: 李旻珊 Vivi | J95: 0956-805911 | K95: Vivi.Li@cyberpower.com
B96: 碩天 | C96: CPSPV66000ETL-WB | D96: 66 | E96: =F96/D96 | F96: 89100 | G96: 20210628 | H96: 5年保固 (3Φ277/480V) | I96: 李旻珊 Vivi | J96: 0972-981383 | K96: Vivi.Li@cyberpower.com
B97: 碩天 | C97: CPSPV66000ETL-WB | D97: 66 | E97: =F97/D97 | F97: 178200 | G97: 20210628 | H97: 20年保固 (3Φ277/480V) | I97: 李旻珊 Vivi | J97: 0972-981383 | K97: Vivi.Li@cyberpower.com | L97: 12input、3MPPT(4/4/4)
B98: 碩天 | C98: CPSPV66000ETL-WB | D98: 66 | E98: 1457.5758 | F98: 96200 | G98: 20220930 | H98: 5年保固 (3Φ277/480V) | I98: 李旻珊 Vivi | J98: 0956-805911 | K98: Vivi.Li@cyberpower.com
B99: 碩天 | C99: CPSPV66000ETL-WB | D99: 66 | E99: 3062.1212 | F99: 202100 | G99: 20220930 | H99: 20年保固 (3Φ277/480V) | I99: 李旻珊 Vivi | J99: 0956-805911 | K99: Vivi.Li@cyberpower.com
B100: 台達電 | C100: H3_210 | D100: 3 | E100: =F100/D100 | F100: 23000 | G100: 20210625 | H100: 5年保固 (1Φ220V) | I100: 阿潘Chamber | J100: 0938-300-828 | K100: chamber@skwentex.net
B101: 台達電 | C101: H3_210 | D101: 3 | E101: =F101/D101 | F101: 42550 | G101: 20210625 | H101: 20年保固 (1Φ220V) | I101: 阿潘Chamber | J101: 0938-300-828 | K101: chamber@skwentex.net
B102: 台達電 | C102: H5A_220 | D102: 5 | E102: =F102/D102 | F102: 26000 | G102: 20210625 | H102: 5年保固 (1Φ220V) | I102: 阿潘Chamber | J102: 0938-300-828 | K102: chamber@skwentex.net
B103: 台達電 | C103: H5A_220 | D103: 5 | E103: =F103/D103 | F103: 48100 | G103: 20210625 | H103: 20年保固 (1Φ220V) | I103: 阿潘Chamber | J103: 0938-300-828 | K103: chamber@skwentex.net
B104: 台達電 | C104: RPI-M10A | D104: 10 | E104: =F104/D104 | F104: 48000 | G104: 20210625 | H104: 5年保固 (3Φ220/380V) | I104: 阿潘Chamber | J104: 0938-300-828 | K104: chamber@skwentex.net
B105: 台達電 | C105: RPI-M10A | D105: 10 | E105: =F105/D105 | F105: 88800 | G105: 20210625 | H105: 20年保固 (3Φ220/380V) | I105: 阿潘Chamber | J105: 0938-300-828 | K105: chamber@skwentex.net
B106: 台達電 | C106: M20A_220 | D106: 20 | E106: =F106/D106 | F106: 58000 | G106: 20210625 | H106: 5年保固 (3Φ220/380V) | I106: 阿潘Chamber | J106: 0938-300-828 | K106: chamber@skwentex.net
B107: 台達電 | C107: M20A_220 | D107: 20 | E107: =F107/D107 | F107: 107300 | G107: 20210625 | H107: 20年保固 (3Φ220/380V) | I107: 阿潘Chamber | J107: 0938-300-828 | K107: chamber@skwentex.net
B108: 台達電 | C108: M20A_220 | D108: 20 | E108: 3400 | F108: 68000 | G108: 20220927 | H108: 5年保固 (3Φ220/380V) | I108: 阿潘Chamber | J108: 0938-300-828 | K108: chamber@skwentex.net
B109: 台達電 | C109: M20A_220 | D109: 20 | E109: 6800 | F109: 136000 | G109: 20220927 | H109: 20年保固 (3Φ220/380V) | I109: 阿潘Chamber | J109: 0938-300-828 | K109: chamber@skwentex.net
B110: 台達電 | C110: M30A_230 | D110: 30 | E110: =F110/D110 | F110: 64000 | G110: 20210625 | H110: 5年保固 (3Φ220/380V) | I110: 阿潘Chamber | J110: 0938-300-828 | K110: chamber@skwentex.net
B111: 台達電 | C111: M30A_230 | D111: 30 | E111: =F111/D111 | F111: 118400 | G111: 20210625 | H111: 20年保固 (3Φ220/380V) | I111: 阿潘Chamber | J111: 0938-300-828 | K111: chamber@skwentex.net
B112: 台達電 | C112: M30A_230 | D112: 30 | E112: 2466.6667 | F112: 74000 | G112: 20220927 | H112: 5年保固 (3Φ220/380V) | I112: 阿潘Chamber | J112: 0938-300-828 | K112: chamber@skwentex.net
B113: 台達電 | C113: M30A_230 | D113: 30 | E113: 4933.3333 | F113: 148000 | G113: 20220927 | H113: 20年保固 (3Φ220/380V) | I113: 阿潘Chamber | J113: 0938-300-828 | K113: chamber@skwentex.net
B114: 台達電 | C114: M70A_262 | D114: 70 | E114: =F114/D114 | F114: 140000 | G114: 20210625 | H114: 5年保固 (3Φ220/380V) | I114: 阿潘Chamber | J114: 0938-300-828 | K114: chamber@skwentex.net
B115: 台達電 | C115: M70A_262 | D115: 70 | E115: =F115/D115 | F115: =F114*1.85 | G115: 20210625 | H115: 20年保固 (3Φ220/380V) | I115: 阿潘Chamber | J115: 0938-300-828 | K115: chamber@skwentex.net
B116: 台達電 | C116: M70A_263 | D116: 70 | E116: 2142.8571 | F116: 150000 | G116: 20220927 | H116: 5年保固 (3Φ220/380V) | I116: 阿潘Chamber | J116: 0938-300-828 | K116: chamber@skwentex.net
B117: 台達電 | C117: M70A_263 | D117: 70 | E117: 4285.7143 | F117: 300000 | G117: 20220927 | H117: 20年保固 (3Φ220/380V) | I117: 阿潘Chamber | J117: 0938-300-828 | K117: chamber@skwentex.net
B118: 台達電 | C118: M100_210 | D118: 100 | E118: =F118/D118 | F118: 145000 | G118: 20210625 | H118: 5年保固 (3Φ380V) | I118: 阿潘Chamber | J118: 0938-300-828 | K118: chamber@skwentex.net
B119: 台達電 | C119: M100_210 | D119: 100 | E119: =F119/D119 | F119: 268250 | G119: 20210625 | H119: 20年保固 (3Φ380V) | I119: 阿潘Chamber | J119: 0938-300-828 | K119: chamber@skwentex.net
B120: ABB | C120: TRIO.27.6 | D120: 27.6 | E120: =F120/D120 | F120: 120000 | G120: 20180403 | H120: 5年保固 | I120: 黃俐瑋rebecca | J120: 0939-880-771 | K120: rebecca@kysolar.com.tw
B121: ABB | C121: TRIO.27.6 | D121: 27.6 | E121: =F121/D121 | F121: 126000 | G121: 20180403 | H121: 10年保固 | I121: 黃俐瑋rebecca | J121: 0939-880-771 | K121: rebecca@kysolar.com.tw
...

Sheet (獨)逆變
B2: 選用廠商 | C2: 型號 | D2: 規格(KW) | E2: 報價(台幣/W) | F2: 總報價 (台幣)
B3: =B7 | C3: =C7 | D3: =D7 | E3: =E7 | F3: =F7
B6: 廠商 | C6: 型號 | D6: 規格(KW) | E6: 報價(台幣/W) | F6: 總報價 (台幣) | G6: 報價時間 | H6: NOTE | I6: 聯絡人 | J6: 聯絡方式 | K6: Email
B7: 先啟 | C7: SP-10000 | D7: 10 | E7: =F7/D7/1000 | F7: 95000 | G7: 2016/2月 | H7: 1.SP-10000 premium hybrid inverter 220vac 3P 2.產品保固2年 | I7: 蘇子雲 | J7: 0930-599834 | K7: soeasy@prospect-technology.com
B8: 先啟 | C8: SP3000-Brilliant | D8: 3 | E8: =F8/D8/1000 | F8: 30000 | G8: 2016/4月 | H8: 1.220V負載 2.無市電混合
B9: 先啟 | C9: Pxxx | D9: 3 | E9: =F9/D9/1000 | F9: 38000 | G9: 2016/4月 | H9: 1.220V負載 2.市電混合 3.待確定規格
B10: 盈正 | C10: ESS-5000 | D10: 5 | E10: =F10/D10/1000 | F10: 260000 | G10: 2019/5月 | H10: 使用6度電 48Vdc 鋰三元電池 | I10: 林岱明 | J10: 916877705
C32: (電池) | D32: (放電深度) | E32: (價格) | F32: (壽命)
C33: 鋰鐵 | D33: 放淺10~20%
C35: 鉛酸 | D35: 放50% | E35: 4000 | F35: 2年
B36: (進階) | C36: 深循環 | D36: 放50% | E36: 7000 | F36: 4年
C38: 鋰酸鋰鐵 | D38: 放80% | E38: 20000 | F38: 5~8年
C40: 三鋰元 | D40: 很容易燒(活性大)、不建議
C42: ◎感性負載=負載x3

Sheet 鋁支架
B2: 選用廠商 | C2: 型號 | D2: 平貼-規格(KW) | E2: 報價(台幣/片) | G2: 選用廠商 | H2: 型號 | I2: 平貼 | J2: 報價 | M2: 選用廠商 | N2: 型號 | O2: 規格 | P2: 報價
B3: =B35 | C3: =C35 | D3: =D35 | E3: =E35 | G3: 璟元 | H3: 防水支架(一代) | I3: (台幣/KW) | J3: 4000~4300 | K3: 不含鋼骨，實際報價依圖面；跨距2m | M3: 璟元 | N3: 魚鱗式(40*40) | O3: (台幣/KW) | P3: 5000 | Q3: 高點1米，斜度10度；支架含螺絲(不含牙條)
B4: 選用廠商 | C4: 型號 | D4: 仰角-規格(KW) | E4: 報價(台幣/片) | G4: 璟元 | H4: 防水支架(二代) | I4: (台幣/KW) | J4: 4600~4800 | K4: 不含鋼骨，實際報價依圖面；跨距3.8m~4m | M4: 璟元 | N4: 魚鱗式(80*80) | O4: (台幣/KW) | P4: 5300 | Q4: 高點1米，斜度10度；支架含螺絲(不含牙條)
B5: =B32 | C5: =C32 | D5: =D32 | E5: =E32 | G5: 雅唐 | H5: 防水支架 | I5: (台幣/坪) | J5: 14000 | K5: 不含鋼骨，含工帶料 | M5: 璟元 | N5: 矮棚(100*100) | O5: (台幣/KW) | P5: 6000-6500 | Q5: 高點2米，跨距3.5米；支架含螺絲(不含牙條)
B6: 選用廠商 | C6: 型號 | D6: 棚架-規格(KW) | E6: 報價(台幣/片) | G6: 選用廠商 | H6: 型號 | I6: 棚架 | J6: 報價(台幣/KW) | M6: 選用廠商 | N6: 型號 | O6: 規格 | P6: 報價(台幣/KW)
B7: =B24 | C7: =C24 | D7: =D24 | E7: =E24 | G7: 聯美營造 | H7: 防水系統總工程 | I7: 套餐 | J7: 75000 | K7: 總工程造價 套餐1KW 7~8萬，防水保固3年，H沒熱浸 | M7: 旭東 | N7: 浮筒 | O7: 一島(12片) | P7: 3850 | Q7: 含浮台、支架鐵件，不含安裝及固定方式
B9: 廠商 | C9: 型號 | D9: 規格(KW) | E9: 報價(台幣/片) | F9: 總報價 (台幣) | G9: 總片數 | H9: 報價時間 | I9: 案件 | J9: 案場概述 | K9: 詳細規格
B10: 推進 | C10: 50 x 25mm | D10: 平貼 | E10: =ROUNDUP((F10/G10),0) | F10: 107000 | G10: 172 | I10: 唐絹案 | K10: 1.含壓塊及封口蓋 2.搭配配彈簧華司及自攻螺絲 3.單孔L KEY 4.表面處理10um陽極+10um壓克力
B11: 推進 | C11: 50 x 25mm | D11: 平貼 | E11: =ROUNDUP((F11/G11),0) | F11: 130000 | G11: 200 | I11: 偉昌案 | K11: 1.含壓塊及封口蓋 2.搭配配彈簧華司及自攻螺絲 3.單孔L KEY 4.表面處理10um陽極+10um壓克力
B12: 推進 | C12: 50 x 25mm | D12: 平貼 | E12: =ROUNDUP((F12/G12),0) | F12: 76000 | G12: 122 | I12: 振邦案 | K12: 1.含壓塊及封口蓋 2.搭配配彈簧華司及自攻螺絲 3.單孔L KEY 4.表面處理10um陽極+10um壓克力
B13: 推進 | C13: 50 x 25mm | D13: 平貼 | E13: =ROUNDUP((F13/G13),0) | F13: 114450 | G13: 190 | I13: 苗強案 | K13: 1.含壓塊及封口蓋 2.搭配配彈簧華司及自攻螺絲 3.單孔L KEY 4.表面處理10um陽極+10um壓克力
B14: 推進 | C14: 50 x 25mm | D14: 平貼 | E14: =ROUNDUP((F14/G14),0) | F14: 79000 | G14: 122 | I14: 優群案 | K14: 1.含壓塊及封口蓋 2.搭配配彈簧華司及自攻螺絲 3.單孔L KEY 4.表面處理10um陽極+10um壓克力
B15: 推進 | C15: 50 x 25mm | D15: 平貼 | E15: =ROUNDUP((F15/G15),0) | F15: 197000 | G15: 200 | I15: 昱盛案 | K15: 1.含壓塊及封口蓋 2.搭配配彈簧華司及自攻螺絲 3.扣件夾具 4.表面處理10um陽極+10um壓克力
B16: 推進 | C16: 50 x 25mm | D16: 平貼 | E16: =ROUNDUP((F16/G16),0) | F16: 80300 | G16: 80 | I16: 西拉雅案 | K16: 1.含壓塊及封口蓋 2.搭配配彈簧華司及自攻螺絲 3.扣件夾具 4.表面處理10um陽極+10um壓克力
B17: 推進 | C17: 70 x 40mm | D17: 平貼 | E17: =ROUNDUP((F17/G17),0) | F17: 52800 | G17: 80 | I17: 長榮商標案 | K17: 1.含壓塊及封口蓋 2.搭配配彈簧華司及自攻螺絲 3.單孔L KEY 4.表面處理10um陽極+10um壓克力
B18: 推進 | C18: 80 x 40mm | D18: 平貼 | E18: =ROUNDUP((F18/G18),0) | F18: 19950 | G18: 30 | I18: 葉月菊案 | K18: 1.含壓塊及封口蓋 2.搭配配彈簧華司及自攻螺絲 3.單孔L KEY 4.表面處理10um陽極+10um壓克力
B19: 推進 | C19: 50 x 25mm | D19: 平貼 | E19: =ROUNDUP((F19/G19),0) | F19: 107000 | G19: 172 | I19: 梁仁勳案 | K19: 1.含壓塊及封口蓋 2.搭配配彈簧華司及自攻螺絲 3.單孔L KEY 4.表面處理10um陽極+10um壓克力
B20: 模冠 | C20: 80 x 40mm | D20: 平貼 | E20: - | F20: 570/m | G20: - | K20: 1.結構鋁擠
B21: 推進 | C21: 50 x 50mm+5025 | D21: 仰角 | E21: =ROUNDUP((F21/G21),0) | F21: 47000 | G21: 40 | I21: 謝志堅案 | K21: 1.含壓塊及封口蓋 2.搭配配彈簧華司及自攻螺絲 3.單孔L KEY 4.表面處理10um陽極+10um壓克力
B22: 推進 | C22: 50 x 50mm+5025 | D22: 仰角 | E22: =ROUNDUP((F22/G22),0) | F22: 42400 | G22: 28 | I22: 唐絹案 | K22: 1.含壓塊及封口蓋 2.搭配配彈簧華司及自攻螺絲 3.單孔L KEY 4.表面處理10um陽極+10um壓克力
B23: 推進 | C23: 70 x 70mm-4080 | D23: 棚架 | E23: =ROUNDUP((F23/G23),0) | F23: 55650 | G23: 24 | I23: 網語案 | K23: 1.含壓塊及封口蓋 2.搭配配彈簧華司及自攻螺絲 3.單孔L KEY 4.表面處理10um陽極+10um壓克力
B24: 推進 | C24: 70 x 70mm-4080 | D24: 棚架 | E24: =ROUNDUP((F24/G24),0) | F24: 206000 | G24: 80 | I24: 長榮商標案 | K24: 1.含壓塊及封口蓋 2.搭配配彈簧華司及自攻螺絲 3.單孔L KEY 4.表面處理10um陽極+10um壓克力
B25: 受興 | C25: 40 x 70mm-4080 | D25: 平鋪 | E25: =ROUNDUP((F25/G25),0) | F25: 383205 | G25: 300 | I25: 信邦工廠案 | J25: 三支鋁擠 | K25: 1.含壓塊及封口蓋 2.搭配配彈簧華司及自攻螺絲 3.單孔L KEY 4.表面處理10um陽極+10um壓克力
B26: 受興 | C26: 40 x 70mm-4080 | D26: 平鋪 | E26: =ROUNDUP((F26/G26),0) | F26: 396256 | G26: 448 | I26: 美福案 | J26: 兩支鋁擠 | K26: 1.含壓塊及封口蓋 2.搭配配彈簧華司及自攻螺絲 3.單孔L KEY 4.表面處理10um陽極+10um壓克力
B27: 受興 | C27: 40 x 70mm-4080 | D27: 仰角 | E27: =ROUNDUP((F27/G27),0) | F27: 2261130 | G27: 1130 | I27: 美福案 | J27: 每跨距都有斜撐 | K27: 1.含壓塊及封口蓋 2.搭配配彈簧華司及自攻螺絲 3.單孔L KEY 4.表面處理10um陽極+10um壓克力
B28: 推進 | C28: 50 x 25mm | D28: 平貼 | E28: =ROUNDUP((F28/G28),0) | F28: 785000 | G28: 1204 | I28: 大宇紗筒案 | K28: 1.含壓塊及封口蓋 2.搭配配彈簧華司及自攻螺絲 3.雙孔H KEY 4.表面處理10um陽極+10um壓克力
B29: 推進 | C29: 50 x 25mm | D29: 仰角 | E29: =ROUNDUP((F29/G29),0) | F29: 892000 | G29: 550 | I29: 大宇紗筒案 | K29: 1.含壓塊及封口蓋 2.搭配配彈簧華司及自攻螺絲 3.雙孔H KEY 4.表面處理10um陽極+10um壓克力
B30: 培興 | C30: 40 x 60mm | D30: 平貼 | E30: =ROUNDUP((F30/G30),0) | F30: 485000 | G30: 837 | I30: 振邦二期案 | J30: 兩支鋁擠 | K30: 1.含壓塊及封口蓋 2.搭配配彈簧華司及自攻螺絲 3.雙孔H KEY 4.表面處理15um陽極+10um壓克力
B31: 璟元 | C31: 40 x 40mm | D31: 平貼 | E31: =ROUNDUP((F31/G31),0) | F31: 2224735 | G31: 3332 | H31: 43460 | I31: 金明玻璃案 | J31: 兩支鋁擠 | K31: 1.含壓塊及封口蓋 2.搭配配彈簧華司及自攻螺絲 3.架高20CM 4.表面處理10um陽極+10um壓克力
B32: 璟元 | C32: 40 x 40mm | D32: 仰角 | E32: 1500 | H32: 43425 | K32: 1.含壓塊及封口蓋 2.搭配配彈簧華司及自攻螺絲 3.架高100CM以下 4.表面處理10um陽極+10um壓克力
B33: 璟元 | C33: 40 x 40mm | D33: 平貼 | E33: =ROUNDUP((F33/G33),0) | F33: 771424 | G33: 1051 | H33: 43240 | I33: 銘誠水電案 | J33: 三支鋁擠 腳座式 (未議價) | K33: 1.不含自攻牙及封口蓋 2.搭配平彈簧華司及壓塊 3.架高20CM 4.表面處理10um陽極+10um壓克力
B34: 培興 | C34: 40 x 60mm | D34: 平貼 | E34: 1000 | H34: 預抓 | J34: 三支鋁擠 夾具式 | K34: 1.含壓塊及封口蓋 2.搭配配彈簧華司及自攻螺絲 3.雙孔H KEY 4.表面處理15um陽極+10um壓克力
B35: 璟元 | C35: 40 x 40mm | D35: 平貼(100kW↑) | E35: 700 | H35: 預抓 | J35: 兩支鋁擠(C=85) | K35: 1.含壓塊及封口蓋 2.搭配配彈簧華司及自攻螺絲 3.架高20CM 4.表面處理10um陽極+10um壓克力
B36: 璟元 | C36: 40 x 40mm | D36: 平貼(100kW↓) | E36: 730 | H36: 預抓 | J36: 兩支鋁擠(C=80) | K36: 1.含壓塊及封口蓋 2.搭配配彈簧華司及自攻螺絲 3.架高20CM 4.表面處理10um陽極+11um壓克力
C39: 腳座 | D39: 兩鋁擠
C40: 夾具 | D40: 三鋁擠
D41: 棚架 | E41: 6500 | F41: x1.2

Sheet 鋁線槽
B2: 選用廠商 | C2: 規格(KW) | D2: 報價(台幣/米)
B3: =B7 | C3: =C7 | D3: =D7
B6: 廠商 | C6: 規格(KW) | D6: 報價(台幣/米) | E6: 總報價 (台幣) | F6: 報價時間 | G6: NOTE | H6: 聯絡人 | I6: 聯絡方式 | J6: Email
B7: 推進 | C7: 50x50mm | D7: 160 | E7: 480 | F7: 2016/2月 | G7: 3米為一單位
B8: 推進 | C8: 100*100mm | D8: 297 | E8: 890 | G8: 3米 | H8: 6063
B9: 推進 | C9: 100*100mm | D9: 330 | E9: 930 | G9: 3米 | H9: 6005 | I9: 3週下單 | J9: 耐鹼耐酸之電著塗料ED
B10: 推進 | C10: 100*100mm | D10: 326 | E10: 980 | G10: 3米 | H10: 6005 | I10: 3週下單 | J10: 耐鹼耐酸之電著塗料ED(壓克力樹脂)
B13: 廠商 | C13: 規格(KW) | D13: 報價(台幣/米) | E13: 總報價 (台幣) | F13: 報價時間 | G13: NOTE | H13: 聯絡人 | I13: 聯絡方式 | J13: Email
B14: 受興 | C14: 中壓(FV347-70) | E14: 30 | F14: 2018/3月 | G14: 平平彈 | J14: 陽極10u
B15: 受興 | C15: 側壓(FJ507-70) | E15: 30 | F15: 2018/3月 | G15: 平平彈 | J15: 陽極10u
B16: 東野精機 | C16: 4080A | D16: 534
B17: 東野精機 | C17: 4080A連結片 | D17: 106

Sheet 變壓器
B2: 低壓
B3: 容量kVA | C3: 一次側電壓 | D3: 二次側電壓 | E3: 士林電機 | H3: 大同 | I3: 巧力
F4: 2021.10.06 | G4: 2022.02.24
B5: 10 | C5: 3相4線380V (巧力為3相3線380V) | D5: 3相3線220V | E5: 26500 | F5: =E5*1.775 | G5: 33000 | H5: 30000 | I5: 28500
B6: 20 | E6: 35000 | F6: =E6*1.775 | G6: 45000 | H6: 36000 | I6: 43100
B7: 30 | E7: 40000 | F7: =E7*1.775 | G7: 51000 | H7: 40000 | I7: 55400
B8: 37.5 | E8: 44000 | F8: =E8*1.775 | G8: 53000 | H8: 44000 | I8: 66800
B9: 40 | E9: X | F9: X | G9: X | H9: X | I9: X
B10: 50 | E10: 48000 | F10: =E10*1.775 | G10: 61000 | H10: 52000 | I10: 87000
B11: 60 | E11: X | F11: X | G11: X | H11: 60000 | I11: X
B12: 70 | E12: X | F12: X | G12: X | H12: 68800 | I12: X
B13: 75 | E13: 62000 | F13: =E13*1.775 | G13: 78000 | H13: X | I13: 116700
B14: 80 | E14: X | F14: X | G14: X | H14: 78000 | I14: X
B15: 90 | E15: X | F15: X | G15: X | H15: 88000 | I15: X
B16: 100 | E16: 80000 | F16: =E16*1.775 | G16: 96500 | H16: 98000 | I16: 134000
B17: 200 | E17: 125000 | F17: =E17*1.775 | G17: 155000 | H17: 140000 | I17: 237000
B18: 300 | E18: 165000 | F18: =E18*1.775 | G18: 188000 | H18: 190000 | I18: 331200
B19: 400 | E19: 200000 | F19: 355000 | G19: 315000 | H19: 230000 | I19: 455700
B20: 500 | E20: 250000 | F20: =E20*1.775 | G20: 360000 | H20: 270000 | I20: 537500
B21: 600 | E21: X | F21: X | G21: X | H21: 340000 | I21: 584500
B22: 付款條件 | E22: 訂金30%(票期15天)， 交貨70%(票期60天) | H22: 發票日90天兌現貨款 | I22: 首次交易須先付款才出貨
B23: 交期 | E23: 60天 | H23: 30~60天 | I23: 30天
B26: 高壓
B27: 容量kVA | C27: 一次側電壓 | D27: 二次側電壓 | E27: 華城電機
B28: 6000 | C28: 22.8kV | D28: 380V | E28: 4714300
B29: 5000 | C29: 22.8KV | D29: 380V | E29: 4003900

Sheet 鋼構
B2: =B9 | C2: =C9 | D2: =D9 | E2: =E9 | F2: =F9 | G2: =G9 | H2: =H9 | I2: =I9 | ... P2: =P9
B3: =B12 | C3: =C12 | D3: =D12 | E3: =E12 | F3: =F12 | G3: =G12 | H3: =H12 | I3: =I12 | ... P3: =P12
B4: =B9 | C4: =C9 | D4: =D9 | E4: =E9 | F4: =F9 | G4: =G9 | H4: =H9 | I4: =I9 | ... P4: =P9
P5: =#REF!
B6: =B9 | C6: =C9 | D6: =D9 | E6: =E9 | F6: =F9 | G6: =G9 | H6: =H9 | I6: =I9 | ... P6: =P9
P7: =#REF!
B9: 廠商 | C9: 型號 | D9: 報價(台幣/kg) | E9: 型號 | F9: 報價(台幣/kg) | G9: 型號 | H9: 報價(台幣/kg) | I9: 型號 | J9: 報價(台幣/kg) | K9: 型號 | L9: 報價(台幣/柱) | M9: 型號 | N9: 報價(台幣/柱) | O9: 型號 | P9: 報價(台幣)
B10: 宏勝工程行 | C10: H型鋼 | D10: =45-22 | E10: C型鋼 | F10: =50-23 | G10: 熱浸鍍鋅 | H10: 15 | I10: 五金另料+人工 | J10: 40 | K10: 水泥基礎 | L10: 2220 | M10: 吊運費 | N10: 4 | O10: 管理費 | P10: 總造價10% | Q10: 107/03
B11: 伍陽鋼構 | C11: H型鋼 | D11: 23 | E11: C型鋼 | F11: 27 | G11: 熱浸鍍鋅 | H11: 15 | I11: 五金另料+人工 | J11: 29 | K11: 水泥基座 | L11: 1200 | M11: 吊運費 | N11: 4 | O11: 管理費 | P11: 總造價10% | Q11: 107/11
B12: 尚鴻工程 | C12: H型鋼 | D12: =45-22 | E12: C型鋼 | F12: =50-23 | G12: 熱浸鍍鋅 | H12: 15 | I12: 五金另料+人工 | J12: 30 | K12: 水泥基礎 | L12: 2220 | M12: 吊運費 | N12: 4 | O12: 管理費 | P12: 總造價10% | Q12: 108/10
C13: H型鋼 | E13: C型鋼 | G13: 熱浸鍍鋅 | I13: 五金另料+人工 | K13: 水泥基礎 | M13: 吊運費 | O13: 管理費
C14: H型鋼 | E14: C型鋼 | G14: 熱浸鍍鋅 | I14: 五金另料+人工 | K14: 水泥基礎 | M14: 吊運費 | O14: 管理費
C15: H型鋼 | E15: C型鋼 | G15: 熱浸鍍鋅 | I15: 五金另料+人工 | K15: 水泥基礎 | M15: 吊運費 | O15: 管理費
C16: H型鋼 | E16: C型鋼 | G16: 熱浸鍍鋅 | I16: 五金另料+人工 | K16: 水泥基礎 | M16: 吊運費 | O16: 管理費
B20: 創炘工業 | C20: H型鋼 | D20: 72.9 | E20: C型鋼 | F20: 58.05 | G20: 熱浸鍍鋅 | I20: 五金另料+人工 | K20: 水泥基礎 | M20: 吊運費 | O20: 管理費
B24: 石中劍 | C24: 方管 | D24: $3800 /kW
C25: HC型鋼 | D25: $4800 /kW
D26: (高度1.5m內，4x3片)
B28: 尚鴻 | F28: (未稅)
B29: 鋼構工程 H型鋼(鍍鋅)工料 | F29: 54/kg
B30: 鋼構工程 H型鋼(噴砂+一底一度漆)工料 | F30: 48/kg
B31: 土+點銲鋼絲網(1層)+水泥(3000psi、厚10~12cm)+表面粉光 | F31: $1000~1100/m2 | G31: § 重車經過：點銲鋼絲網(2層)+水泥(4000psi、20cm)
B32: 土+夯實+AC(厚5~8cm) | F32: $800/m2
B33: RC | C33: 3000psi | D33: 輸送 | F33: $3000/m3
B34: RC | C34: 4000psi | F34: $3200/m3
B36: 地面型PC樁 | C36: 6米/支 | D36: 3000
C37: 9米/支 | D37: 4500
B39: 2甲地
B40: 地貌改變 44萬+修整 5萬

Sheet 雜項
B3: 品名 | C3: 單位 | D3: 費用 | E3: 規格
B4: 監控電腦含22吋以上螢幕 | C4: 式 | D4: 22990
B5: 75"以上LCD螢幕4K | C5: 式 | D5: 79900
B6: 不銹鋼車牙管清洗管線含施工/配電/加壓馬達 | C6: m | D6: 500
B7: PVC管清洗管線含施工/配電/加壓馬達 | C7: m | D7: 200
B8: 採光罩防墜安全網 | C8: 元/m2 | D8: 400
B9: 箱體掛牆(含安裝鋼構材料) | C9: 組 | D9: 3000
B10: 高壓設備增設圍籬 | C10: m | D10: 5000
B11: 滅火器(環保) | C11: 支 | D11: 3200 | E11: 保固10年 | F11: https://24h.pchome.com.tw/prod/QFAP18-A900AF8MO
B12: 滅火器(乾粉) | C12: 支 | D12: 800
B17: 結構技師現勘費 | C17: 次 | D17: 8000 | E17: 苗栗
B18: 超音波測量廠商 | C18: 出一次 | D18: 20000-30000 | E18: 未含後續分析

Sheet 線材
B2: DC線廠商 | C2: 型號 | D2: 規格 | E2: 報價(台幣/M) | F2: 報價時間 | G2: NOTE | H2: 聯絡人 | I2: 聯絡方式 | J2: Email
B3: 適發工業科技 | C3: LEON_ STUDER 2248U3 | D3: 4mm2(TUV) | E3: 23.5 | F3: 2013/10月 | G3: 外徑6.05 | H3: 適發工業科技 | I3: 0227924360
B4: 華新 | C4: OD(完成外徑)7.5mm | D4: 4mm2(UL) | E4: 21.2 | F4: 2018/6月 | G4: 外徑7.5mm2
B5: 華新 | C5: OD(完成外徑)6.4mm | D5: 4mm2(TUV) | E5: 20.2 | F5: 2018/6月 | G5: 外徑6.4mm2
B6: 華新 | C6: OD(完成外徑)5.8mm | D6: 4mm2(EN) | E6: 18.9 | F6: 2018/6月 | G6: 外徑5.8mm2
B7: 經緯 | C7: OD(完成外徑)5.9mm | D7: 4mm2(TUV) | E7: 19.3 | F7: 2018/6月 | G7: 外徑5.9mm2
B8: 泰科 | C8: OD(完成外徑)6.35mm | D8: 4mm2(TUV&UL) | E8: 20 | F8: 2018/6月 | G8: 外徑6.35mm2
B10: AC線廠商 | C10: 型號 | D10: 規格 | E10: 報價(台幣/M) | F10: 報價時間 | G10: NOTE | H10: 聯絡人 | I10: 聯絡方式 | J10: Email
B11: 太平洋 | C11: PVC3.5mm2 | E11: 8
B12: 太平洋 | C12: PVC5.5mm2 | E12: 12
B13: 太平洋 | C13: PVC8mm2 | E13: 17
B14: 太平洋 | C14: PVC14mm2 | E14: 30
B15: 華新 | C15: XPVC5.5mm2 | E15: 19
B16: 華新 | C16: XPVC22mm2 | E16: 62
B17: 華新 | C17: XPVC50mm2 | E17: 130
B18: 華新 | C18: XPVC250mm2 | E18: 640
B20: DC接頭廠商 | C20: 型號 | D20: 規格 | E20: 報價(台幣/組) | F20: 報價時間 | G20: NOTE | H20: 聯絡人 | I20: 聯絡方式 | J20: Email
B21: MC4 | C21: PV-KBT4/6II-UR | D21: A:5.9-8.8 | E21: 58元 | F21: 2018/6月 | G21: 塑膠尖的
B22: MC4 | C22: PV-KST4/6II-UR | D22: A:5.9-8.8 | F22: 2018/6月 | G22: 塑膠凹的

Sheet 箱體
B2: DC箱 | H2: AC箱 | N2: 躉售電錶箱
B4: 廠商 | C4: 規格 | D4: 單位報價 | E4: 數量 | F4: 小計 | H4: 廠商 | I4: 規格 | J4: 單位報價 | K4: 數量 | L4: 小計 | N4: 廠商 | O4: 規格 | P4: 單位報價 | Q4: 數量 | R4: 小計
B5: 立駱 | C5: Fuse 15A 2個 | D5: 185 | E5: 2 | F5: =D5*E5 | H5: 立駱 | I5: Breaker 1組 2P 30AT/100AF | J5: 190 | K5: 1 | L5: =J5*K5 | N5: 立駱 | O5: KS 1組 2P 100A | P5: 650 | Q5: 1 | R5: =P5*Q5
C6: 突波吸收器 2個 | D6: 180 | E6: 2 | F6: =D6*E6 | I6: Case 250x300x150 1.2t sus304 | J6: 2200 | K6: 1 | L6: =J6*K6 | O6: Breaker 1組 2P 50AT/100AF 10KA | P6: 200 | Q6: 1 | R6: =P6*Q6
C7: Case 250x350x150 IP66 | D7: 2130 | E7: 1 | F7: =D7*E7 | I7: 另料 | J7: 710 | K7: 1 | L7: =J7*K7 | O7: Case 1050x350x250 1.5t | P7: 11213 | Q7: 1 | R7: =P7*Q7
C8: 直流開關 16A | D8: 950 | E8: 1 | F8: =D8*E8 | I8: 組立工資 | J8: 800 | K8: 1 | L8: =J8*K8 | O8: 另料 | P8: 700 | Q8: 1 | R8: =P8*Q8
C9: 組立工資 | D9: 1550 | E9: 1 | F9: =D9*E9 | O9: 組立工資 | P9: 700 | Q9: 1 | R9: =P9*Q9
B11: 總報價 | F11: =SUM(F5:F9) | H11: 總報價 | L11: =SUM(L5:L8) | N11: 總報價 | R11: =SUM(R5:R9)
H13: 廠商 | I13: 規格 | J13: 單位報價 | K13: 數量 | L13: 小計 | N13: 廠商 | O13: 規格 | P13: 單位報價 | Q13: 數量 | R13: 小計
H14: 立駱 | I14: Breaker 3組 2P 20AT/100AF | J14: 200 | K14: 3 | L14: =J14*K14 | N14: 立駱 | O14: KS 1組 2P 100A | P14: 680 | Q14: 1 | R14: =P14*Q14
I15: 總Breaker 1組 2P 50AT/100AF | J15: 200 | K15: 1 | L15: =J15*K15 | O15: Breaker 1組 2P 30AT/100AF 10KA | P15: 190 | Q15: 1 | R15: =P15*Q15
I16: Case 550x500x200 1.2t sus304 | J16: 7450 | K16: 1 | L16: =J16*K16 | O16: Case 1050x350x300 1.5t | P16: 11996 | Q16: 1 | R16: =P16*Q16
I17: 另料 | J17: 710 | K17: 1 | L17: =J17*K17 | O17: 另料 | P17: 750 | Q17: 1 | R17: =P17*Q17
I18: 組立工資 | J18: 1550 | K18: 1 | L18: =J18*K18 | O18: 組立工資 | P18: 750 | Q18: 1 | R18: =P18*Q18
H20: 總報價 | L20: =SUM(L14:L18) | N20: 總報價 | R20: =SUM(R14:R18)

Sheet 高空作業車
B2: 廠商名稱:浤大企業有限公司 | J2: 廠商名稱:大友高空實業股份有限公司 | Q2: 廠商名稱:磐石企業有限公司
B3: 地址:台中市烏日區溪南路三段418巷251號 | J3: 地址:嘉義縣太保市埤鄉里埤麻腳29-2號 | Q3: 地址:高雄市岡山區聖森路168號對面(工礦技師公會對面)
B4: 電話:04-23358655/傳真:04-23351978 | J4: 電話:05-2385797/傳真:05-2385795 | Q4: 電話:07-6235799/傳真:07-2635139
B5: 報價日期:110/06/16 報價有效期限:15天 | J5: 報價日期:110/06/17 | Q5: 報價日期:110/06/23
B6: 業務人員:蘇小姐 | J6: 業務人員:施雅珠，電話:05-2385797#211 | Q6: 業務人員:joel
B8: 項目名稱 | C8: 數量 | D8: 單位 | E8: 天數 | F8: 單價 | G8: 總價 | H8: 備註 | J8: 項目名稱 | K8: 數量 | L8: 單位 | M8: 單價 | N8: 總價 | O8: 備註 | Q8: 項目名稱 | R8: 數量 | S8: 單位 | T8: 單價 | U8: 總價 | V8: 備註
B9: 26米-直臂式高空作業車"S85 | C9: 1 | D9: 台 | E9: 30日/月 | F9: 73000 | G9: 73000 | H9: 月租含運費 | J9: 24米高空作業車輪胎直臂式"S80 | K9: 1 | L9: 台 | Q9: 21米輪胎式高空車JLG 660SJ 21M | R9: 1 | S9: 月 | T9: 55000 | U9: 55000 | V9: 含運費
B10: 26米-直臂式高空作業車"S85 | C10: 2 | D10: 台 | E10: 30日/月 | F10: 70000 | G10: 70000 | J10: 起重工程款_日 | K10: 1 | L10: 日 | M10: 6000 | N10: 6000 | Q10: 21米輪胎式高空車JLG 660SJ 21M | R10: 1 | S10: 天 | T10: 3500 | U10: 3500 | V10: 運費7000元(來回)
B11: 26米-直臂式高空作業車"S85 | C11: 1 | D11: 台 | E11: 1日 | F11: 5500 | G11: 5500 | H11: 運費另計，看地點 | J11: 運費(來回) | K11: 2 | L11: 趟 | M11: 2500 | N11: 5000 | O11: 運台南，其他地方另計 | Q11: 1.未稅價格
B12: 1.以上報價不含5%營業稅。 | J12: 起重工程款_日 | K12: 15 | L12: 日 | M12: 3800 | N12: 57000 | O12: 含運費 | Q12: 2.租車流程：完成合約—預收款項（匯款或收現）--預約司機--巡檢車輛—出車
B13: 2.月租機種來回運費由本公司負責。 | J13: 起重工程款_月 | K13: 1 | L13: 月 | M13: 80000 | N13: 80000 | O13: 含運費 | Q13: 3.另車輛流動不一定有現車，若有確定租期，請提前預訂，以備留車
B14: 3.若未滿月租之計價方式：日租金*天數*數量+運費。 | J14: 1.報價有效期限：自報價日起算 15天
B15: 4.若未滿月租之計價超過月租金，則個別以月租金計價。 | J15: 2.報價未稅 | Q15: 商品名稱:
B16: 5.本公司月租以每月30日為基準，滿月租之超租日租金計算方式：月租金/30日。 | Q16: JLG 660SJ 21M 輪胎直臂式高空作業車
B17: 6.日租價格會隨日租天數增加做調整。 | J17: 主要規格 | Q17: 規格介紹:
B18: 7.首次交易，需預收訂金。煩請傳真基本資料，以利後續作業。 | J18: 工作高度： | K18: 平台高度： | L18: D-貯藏長度： | M18: E-貯藏寬度： | N18: C-貯藏高度： | Q18: 高空作業車規格:
B19: 備 註:付款辦法-匯款或支票 -月結30天 | J19: 26.38 m | K19: 24.38 m | L19: 11.23 m | M19: 2.49 m | N19: 2.80 m | Q19: 平台高度:20.3M(含人員工作高度:22M)
J20: A x B-平台尺寸： | K20: 作業半徑： | L20: 平台轉向： | M20: 平台載重： | N20: 爬坡能力(貯藏)： | Q20: 工作半徑:17.3M
B21: 主要規格 | J21: 0.91 m x 2.44 m | K21: 21.79 m | L21: 160° | M21: 227 kg | N21: 30% / 45% | Q21: 最高載重:230kg
B22: 工作高度：27.9m | J22: 車身重量： | K22: 動力來源： | Q22: 高空作業車重量:13,550kg
B23: 平台高度：25.9m | J23: 16,103 kg | K23: 柴油引擎 | Q23: 車身尺寸:長10.21M*寬2.56M*高2.4M
B24: 機器長度：12.2m | Q24: 工作台尺寸:長2.44M*寬0.91M*高1.83M
B25: 機器寬度：2.5m | Q25: 動力來源:柴油引擎
B26: 機器高度：2.8m | Q26: 使用燃料:高級柴油(油量:147L)
B27: 平台載重：227公斤 | Q27: 規格明細:
B28: 機具總重量：17300公斤 | Q28: https://s3-ap-northeast-1.amazonaws.com/static.iyp.tw/22019/files/6ba43200-45b2-4e37-b6db-8ab12d9e23cb.pdf

Sheet 統包價
G2: 唐絹 | H2: 長榮商標 | I2: 中興管理中心 | J2: 偉昌
B3: kW | G3: 49.995 | H3: 19.6 | I3: 19.6 | J3: 49.995
B4: 業務報價 | G4: 3250000 | H4: =2030000/1.05 | I4: 1723570 | J4: 3500000
B5: 實際總成本 | G5: =[1]報價及成本分析!$M$73 | H5: =[2]成本分析!$J$43 | I5: =[3]報價及成本分析!$M$73 | J5: =[4]報價及成本分析!$M$73
B6: 利潤% | G6: =(G4-G5)/G4 | H6: =(H4-H5)/H4 | I6: =(I4-I5)/I4 | J6: =(J4-J5)/J4
B7: 差值 | G7: =G4-G5 | H7: =H4-H5 | I7: =I4-I5 | J7: =J4-J5
B9: 電力系統配線 | G9: 案件/報價(未稅)
B10: 公司名稱 | C10: 聯絡人 | D10: 聯絡方式 | E10: 備註 | G10: 唐絹 | H10: 長榮商標 | I10: 中興管理中心 | J10: 偉昌
G11: 49.995 | H11: 19.6 | I11: 19.6 | J11: 49.995
B12: 山毅科技有限公司 | C12: 江進通 | D12: 0923-182970 juddy.jim@gmail.com | E12: *未稅 | F12: 第一次 | G12: 798921 | H12: 323400 | I12: 未寄資料 | J12: 未寄資料
F13: 議價1
F14: 議價2
B15: 瑞發水電行 | C15: 謝先生 | D15: 0972-739372(謝先生) 04-7552226(張小姐 議價) rf.n410924@msa.hinet.net | E15: *未稅 | F15: 第一次 | G15: =(714972/1.05)+20000 | H15: =330666/1.05 | I15: =353919/1.05 | J15: =(780830+4200)/1.05
F16: 議價1 | G16: =G15-10000 | H16: 供應商無法一次承接四案 | I16: 供應商無法一次承接四案 | J16: =J15-10000
F17: 議價2 | G17: 670000
B18: 網語 | C18: 謝志堅 | D18: 0933151699 calvin.mcse@msa.hinet.net | F18: 第一次 | G18: 無法施作 | H18: 145060 | I18: 235410 | J18: 無法施作
F19: 議價1 | I19: 190000
F20: 議價2
B21: 凱文光電科技有限公司 | C21: 陳先生 | D21: 0933541037 kevin@kevin-solar.com | E21: *~2萬/KW | F21: 第一次 | G21: 已寄資料,尚未取得報價 | H21: 已寄資料,尚未取得報價 | I21: 已寄資料,尚未取得報價 | J21: 已寄資料,尚未取得報價
F22: 議價1
F23: 議價2
B24: 翌順水電工程 | C24: 賴先生 | D24: 1. yi.shun@hotmail.com.tw 2. 0937729287 | E24: *到12月中都無法施作 | F24: 第一次 | G24: 已寄資料,尚未取得報價 | H24: 已寄資料,尚未取得報價 | I24: 已寄資料,尚未取得報價 | J24: 已寄資料,尚未取得報價
F25: 議價1
F26: 議價2
B27: 預估機電成本 | G27: 760000 | H27: 245900 | I27: =216200 | J27: 750000
B29: 鋁料結構 | G29: 案件/報價(未稅)
B30: 公司名稱 | C30: 聯絡人 | D30: 聯絡方式 | E30: 備註 | G30: 唐絹 | H30: 長榮商標 | I30: 中興管理中心 | J30: 偉昌
G31: 49.995 | H31: 19.6 | I31: 19.6 | J31: 49.995
B32: 推進工業有限公司 | C32: Winnie 許瀞云 | D32: 0921096621 03 656-3996 winnie@acceloronline.com | F32: 第一次 | G32: 149400 | H32: 52800 | I32: 158000 | J32: 130000
F33: 議價1 | G33: 130000 | H33: 49000 | I33: 143000 | J33: 114000
F34: 議價2
B35: 法隆企業有限公司 | C35: 翁小姐 | D35: 06-2736755 #204 falon.co@gmail.com | F35: 第一次 | G35: 已寄資料,尚未取得報價 | H35: 192000 | I35: 未寄資料
F36: 議價1
F37: 議價2
B38: 預估鋁料成本 | G38: 195720 | H38: 64288 | I38: 178688 | J38: 160720
B40: 箱體 | G40: 案件/報價(未稅)
B41: 公司名稱 | C41: 聯絡人 | D41: 聯絡方式 | E41: 備註 | G41: 唐絹 | H41: 長榮商標 | I41: 中興管理中心 | J41: 偉昌
G42: 49.995 | H42: 19.6 | I42: 19.6 | J42: 49.995
B43: 立駱 | C43: 陳彥儒 | D43: 0915522403 0915522403@puffer.tw | E43: *RD | F43: AC BOX | H43: =11105+1096+2400+1800+2000 | I43: =12520+1096+3000+2000+3000
F44: 躉售錶箱 | H44: =14000+750+1096+750+750 | I44: =14000+750+1096+750+750
F45: 變壓器 | H45: 26000 | I45: 26000
F46: 運費 | H46: 1300 | I46: 1300
F47: 小計(第一次) | H47: =SUM(H43:H46) | I47: =SUM(I43:I46)
F48: 議價1 | H48: 62000 | I48: 65500
F49: 議價2
B50: 預估箱體成本 | H50: 70753 | I50: 93000
B52: 鋼構結構 | G52: 案件/報價(未稅)
B53: 公司名稱 | C53: 聯絡人 | D53: 聯絡方式 | E53: 備註 | G53: 唐絹 | H53: 長榮商標 | I53: 中興管理中心 | J53: 偉昌
G54: 49.995 | H54: 19.6 | I54: 19.6 | J54: 49.995
C55: 陳大哥 | D55: 0955100968 | E55: *鋼構+鋼浪板 *鋼構材料費(鋼料原物料-得泰鋼鐵, 唐絹) *含運輸吊掛 | F55: 鋼構 | G55: 鋁擠 | H55: 317240 | I55: 鋁擠 | J55: 鋁擠
F56: 二次施工 | H56: 113356
F57: 小計(第一次) | H57: =SUM(H55:H56)
F58: 議價1 | H58: =430000/1.05
F59: 議價2
F60: 第一次 | G60: 鋁擠 | I60: 鋁擠 | J60: 鋁擠
F61: 議價1
F62: 議價2
B63: 預估鋼構成本 | H63: 336000
B64: 預估二次施工成本 | H64: 120000
B66: DC BOX箱+配件 | G66: 案件/報價(未稅)
B67: 公司名稱 | C67: 聯絡人 | D67: 聯絡方式 | E67: 備註 | G67: 澎湖獨立型
B69: 日煬 | C69: 沈小姐 | D69: 02-2595-9780 #15 claire@jdauspice.com | F69: 第一次 | G69: 12780
F70: 議價1
F71: 議價2
B73: 電池 | G73: 案件/報價
B74: 公司名稱 | C74: 聯絡人 | D74: 聯絡方式 | E74: 備註 | G74: 澎湖獨立型/顆
B76: 蘭陽能源 | C76: 林淑玲 | D76: 03-2706565#222 0915-991883 sales@lynopower.com | E76: 250AH 48V | F76: 第一次 | G76: 395000
F77: 議價1
F78: 議價2
B79: 進翔科技 股份有限公司 | C79: 桂慧齡 | D79: 03-2631212 #135 0939-007908 veronique.kuei@amitatech.com | E79: 250AH 48V | F79: 第一次 | G79: 已寄資料,尚未取得報價
F80: 議價1
F81: 議價2
B83: 獨立型逆變器 | G83: 案件/報價
B84: 公司名稱 | C84: 聯絡人 | D84: 聯絡方式 | E84: 備註 | G84: 澎湖獨立型
G85: 10KW-3台
B86: 先啟科技 | C86: 蘇子雲 | D86: 0930-599834 soeasy@prospect-technology.com | F86: 第一次 | G86: 285000
F87: 議價1
F88: 議價2

Sheet 鋼構長度重量計算
A1: 尺寸 | B1: kg/m
A2: H200*100 | B2: 20.9
A3: H150*75 | B3: 14
A4: C150*65*3.2t | B4: 7.51
A5: C150*65*2.3t | B5: 5.5
A7: H鋼 | B7: =A3 | H7: C鋼 | I7: =A5 | O7: 水泥墩 | R7: 菱形網 | W7: 400*2400
B8: 長度 | C8: 數量 | D8: 單位重量 | E8: 總重量 | F8: 全部總和(重量) | I8: 長度 | J8: 數量 | K8: 單位重量 | L8: 總重量 | M8: 全部總和(重量) | P8: 數量 | S8: 長度 | T8: 數量 | U8: 總數長度 | V8: 總和 | W8: 張數
A9: #001 | B9: 3.5 | C9: 258 | D9: 14 | E9: =B9*C9*D9 | F9: =SUM(E9:E28) | H9: #001 | I9: 8.3 | J9: 586 | K9: 5.5 | L9: =I9*J9*K9 | M9: =SUM(L9:L12) | O9: #001 | P9: =SUM(C9:C11) | R9: #001 | S9: 32.2 | T9: 1 | U9: =S9*T9 | V9: =SUM(U9:U19) | W9: =ROUNDUP(U9/2.4,0)+1
A10: #002 | B10: 3.9 | C10: 356 | D10: 14 | E10: =B10*C10*D10 | H10: #002 | I10: 7.8 | J10: 518 | K10: 5.5 | L10: =I10*J10*K10 | R10: #002 | S10: 12 | T10: 1 | U10: =S10*T10 | W10: =ROUNDUP(U10/2.4,0)+1
A11: #003 | B11: 4.2 | C11: 196 | D11: 14 | E11: =B11*C11*D11 | H11: #003 | I11: 4.5 | J11: 12 | K11: 5.5 | L11: =I11*J11*K11 | R11: #003 | S11: 73.6 | T11: 1 | U11: =S11*T11 | W11: =ROUNDUP(U11/2.4,0)+1
A12: #004 | B12: 31.7 | C12: 6 | D12: 14 | E12: =B12*C12*D12 | H12: #004 | I12: 9.5 | J12: 39 | K12: 5.5 | L12: =I12*J12*K12 | R12: #004 | S12: 57.5 | T12: 1 | U12: =S12*T12 | W12: =ROUNDUP(U12/2.4,0)+1
A13: #005 | B13: 15.7 | C13: 3 | D13: 14 | E13: =B13*C13*D13 | R13: #005 | S13: 13.8 | T13: 1 | U13: =S13*T13 | W13: =ROUNDUP(U13/2.4,0)+1
A14: #006 | B14: 12.1 | C14: 1 | D14: 14 | E14: =B14*C14*D14 | R14: #006 | S14: 34.5 | T14: 1 | U14: =S14*T14 | W14: =ROUNDUP(U14/2.4,0)+1
A15: #007 | B15: 43.1 | C15: 2 | D15: 14 | E15: =B15*C15*D15 | R15: #007 | S15: 97.9 | T15: 1 | U15: =S15*T15 | W15: =ROUNDUP(U15/2.4,0)+1
A16: #008 | B16: 97.9 | C16: 1 | D16: 14 | E16: =B16*C16*D16 | R16: #008 | S16: 107.1 | T16: 3 | U16: =S16*T16 | W16: =ROUNDUP(U16/2.4,0)+1
A17: #009 | B17: 73.9 | C17: 3 | D17: 14 | E17: =B17*C17*D17 | R17: #009 | S17: 63.4 | T17: 1 | U17: =S17*T17 | W17: =ROUNDUP(U17/2.4,0)+1
A18: #010 | B18: 58.3 | C18: 6 | D18: 14 | E18: =B18*C18*D18 | R18: #010 | S18: 8.1 | T18: 8 | U18: =S18*T18 | W18: =ROUNDUP(U18/2.4,0)+1
A19: #011 | B19: 58.3 | C19: 2 | D19: 14 | E19: =B19*C19*D19 | R19: #011 | S19: 7.3 | T19: 7 | U19: =S19*T19 | W19: =ROUNDUP(U19/2.4,0)+1
A20: #012 | B20: 46.5 | C20: 1 | D20: 14 | E20: =B20*C20*D20 | V20: 總和 | W20: =SUM(W9:W19)
A21: #013 | B21: 36.5 | C21: 3 | D21: 14 | E21: =B21*C21*D21
A22: #014 | B22: 99.1 | C22: 6 | D22: 14 | E22: =B22*C22*D22
A23: #015 | B23: 108.1 | C23: 18 | D23: 14 | E23: =B23*C23*D23
A24: #016 | B24: 64.1 | C24: 3 | D24: 14 | E24: =B24*C24*D24
A25: #017 | B25: 8.1 | C25: 314 | D25: 14 | E25: =B25*C25*D25
A26: #018 | B26: 9.7 | C26: 13 | D26: 14 | E26: =B26*C26*D26
A27: #019 | B27: 8.3 | C27: 20 | D27: 14 | E27: =B27*C27*D27
A28: #020 | B28: 4.3 | C28: 4 | D28: 14 | E28: =B28*C28*D28

Sheet XLPE牌價
B1: 華新麗華股份有限公司 | F1: 報價日 | G1: 20220930
B2: 600V XLP (交連PE)電力電纜 | F2: CNS 2655
F3: JISC 3606
A4: 規格 | B4: 構成 | C4: 單位 | D4: 一芯 | E4: 二芯 | F4: 三芯 | G4: 四芯
D5: 牌價 | E5: 牌價 | F5: 牌價 | G5: 牌價
A6: 2.0 mm2 | B6: 7/0.6 mm | C6: 公尺 | D6: 8.7 | E6: 20.5 | F6: 26.5 | G6: 33.7
A7: 3.5 mm2 | B7: 7/0.8 mm | C7: " | D7: 12.5 | E7: 28.5 | F7: 39.5 | G7: 48.5
A8: 5.5 mm2 | B8: 7/1.0 mm | C8: " | D8: 18.3 | E8: 42.5 | F8: 57.5 | G8: 73.5
A9: 8 mm2 | B9: 7/1.2 mm | C9: " | D9: 24.2 | E9: 56 | F9: 76.5 | G9: 98.5
A10: 14 mm2 | B10: 7/1.6 mm | C10: " | D10: 38.8 | E10: 86.2 | F10: 121.5 | G10: 159
A11: 22 mm2 | B11: 7/2.0 mm | C11: " | D11: 58.6 | E11: 131.7 | F11: 185.3 | G11: 243
A12: 30 mm2 | B12: 7/2.3 mm | C12: " | D12: 75.6 | E12: 168.9 | F12: 240.3 | G12: 315.5
A13: 38 mm2 | B13: 7/2.6 mm | C13: " | D13: 94.6 | E13: 211.2 | F13: 301.3 | G13: 395.8
A14: 50 mm2 | B14: 19/1.8 mm | C14: " | D14: 123.5 | E14: 273.1 | F14: 390.3 | G14: 512.7
A15: 60 mm2 | B15: 19/2.0 mm | C15: " | D15: 149.5 | E15: 329.9 | F15: 474.5 | G15: 622.3
A16: 80 mm2 | B16: 19/2.3 mm | C16: " | D16: 194.8 | E16: 431.8 | F16: 607.2 | G16: 812.1
A17: 100 mm2 | B17: 19/2.6 mm | C17: " | D17: 249.4 | E17: 554.9 | F17: 793.4 | G17: 1047.7
... A21: 250 mm2 | B21: 61/2.3 mm | C21: " | D21: 608.8 | E21: 1356.1 | F21: 1947 | G21: 2580.6
A22: 325 mm2 | B22: 61/2.6 mm | C22: " | D22: 769.6 | E22: 1711.8 | F22: 2464.9
A23: 400 mm2 | B23: 61/2.9 mm | C23: " | D23: 958.2
A24: 500 mm2 | B24: 61/3.2 mm | C24: " | D24: 1168.7
A25: 600 mm2 | B25: 91/2.9 mm | C25: " | D25: 1427.4
A26: 725 mm2 | B26: 91/3.2 mm | C26: " | D26: 1728.6
A27: 850 mm2 | B27: 127/2.9 mm | C27: " | D27: 1987.1
A28: 1000 mm2 | B28: 127/3.2 mm | C28: " | D28: 2405.7

Sheet 開始滾算紀錄1
B1: 電站基本資料
B2: 電站名稱 | C2: 淡江大學-財務模擬案場 | D2: - | E2: -
B3: 電站壽命 | C3: 20 | D3: - | E3: -
B4: 建置量(kWp) | C4: 436.1 | D4: - | E4: -
B5: 起始年度 | C5: 2020 | D5: 結束年度 | E5: 2039 | M5: 第1次滾算摘要
M6: 價金: 29500
B7: 綜合損益表 | M7: 專案IRR: 4.46
B8: 收入 | M8: 權益法IRR: 11.07
B9: 收支項目 | C9: 相關參數 | D9: 參數數值 | E9: 年限 | M9: 利潤率: 20.00%
B10: 電費收入 | C10: 年度AC併網總發電量 | D10: 547002 | E10: 20 | M10: 第1次滾算，減少 500 元 - 現金模式，每次減少 500 元
C11: 首年衰退率 | D11: 0.01
C12: 次年衰退率 | D12: 0.004
C13: 躉售費率(FIT) | D13: 3.7152
B14: 支出
B15: 收支項目 | C15: 相關參數 | D15: 參數數值 | E15: 攤提年限
B16: 設備費用(價金) | C16: 每kWp設備成本 | D16: 29500 | E16: 20
C17: 信邦利潤率 | D17: 0.2
C18: 開發費 | D18: 2000
B19: 租金費用 | C19: 租金計算方式 (1=固定攤提/2=電費抽成) | D19: 1 | E19: 0
C20: 【方式1參數】租金總額 | D20: 5804025 | E20: 20
C21: 【方式2參數】抽成比率 | D21: 0 | E21: 0
B22: 運維費用 | C22: 每kw運維成本 | D22: 400 | E22: 20
B23: 保險費用 | C23: 占整體設備費用比例 | D23: 0.003 | E23: 20
B24: 模組回收費用 | C24: 每kw模組回收成本 | D24: 1000 | E24: 10
B25: 利息費用 | C25: 銀行利率 | D25: 0.025595 | E25: 0
B26: 所得稅 | C26: 所得稅率 | D26: 0.2 | E26: 0
B29: 現金流量表
B30: 金流項目 | C30: 相關參數 | D30: 參數數值
B31: 貸款成數 | C31: 占總設備費用比例 | D31: 0.8
B32: 貸款還款 | C32: 攤還期數 | D32: 15
B33: 現金股利 | C33: 股利比率 | D33: 0.9
B34: 年底減資 | C34: 攤還期數 | D34: 4
C37: 年份 | D37: 2020 | E37: 2021 | F37: 2022 | G37: 2023 | H37: 2024 | I37: 2025 | J37: 2026 | K37: 2027 | L37: 2028 | M37: 2029 | N37: 2030 | O37: 2031 | P37: 2032 | Q37: 2033 | R37: 2034 | S37: 2035 | T37: 2036 | U37: 2037 | V37: 2038 | W37: 2039
B38: 0 | F38: 手動計算值 | T38: 償還年限
B39: (Unit : Currency) | C39: 0 | D39: 1 | E39: 2 | F39: 3 | G39: 4 | H39: 5 | I39: 6 | J39: 7 | K39: 8 | L39: 9 | M39: 10 | N39: 11 | O39: 12 | P39: 13 | Q39: 14 | R39: 15 | S39: 16 | T39: 17 | U39: 18 | V39: 19 | W39: 20
B40: 發電度數(KWH) | C40: 0 | D40: =#REF! | E40: =#REF! | F40: =#REF! | G40: =#REF! | H40: =#REF! | I40: =#REF! | J40: =#REF! | K40: =#REF! | ... W40: =#REF!
B41: Inflow : 電費收入 | C41: - | D41: =#REF! | E41: =#REF! | F41: =#REF! | G41: =#REF! | H41: =#REF! | I41: =#REF! | J41: =#REF! | K41: =#REF! | ... W41: =#REF!
B42: Inflow : 政府補助 | C42: - | F42: 0 | G42: - | H42: - | I42: - | J42: - | K42: - | L42: - | M42: - | N42: - | O42: - | P42: - | Q42: - | R42: - | S42: - | T42: - | U42: - | V42: - | W42: -
B43: Inflow : 銀行借款
B44: Outflow : 設備費用 | C44: =-#REF! | F44: - | G44: - | H44: - | I44: - | J44: - | K44: - | L44: - | M44: - | N44: - | O44: - | P44: - | Q44: - | R44: - | S44: - | T44: - | U44: - | V44: - | W44: -
B45: Outflow : 設備放置區域租金 | C45: - | D45: =-#REF! | E45: =-#REF! | F45: =-#REF! | G45: =-#REF! | H45: =-#REF! | I45: =-#REF! | J45: =-#REF! | K45: =-#REF! | ... W45: =-#REF!
B46: Outflow : 返還借款 | C46: 0 | V46: 0 | W46: 0
B47: Outflow : 利息費用 | C47: -
B48: Outflow : 維運費 | C48: - | D48: =-#REF! | E48: =-#REF! | F48: =-#REF! | G48: =-#REF! | H48: =-#REF! | I48: =-#REF! | J48: =-#REF! | K48: =-#REF! | ... W48: =-#REF!
B49: Outflow : 保險費 | C49: - | D49: =-#REF! | E49: =-#REF! | F49: =-#REF! | G49: =-#REF! | H49: =-#REF! | I49: =-#REF! | J49: =-#REF! | K49: =-#REF! | ... W49: =-#REF!
B50: Outflow : 模組回收費 | D50: =-#REF! | E50: =-#REF! | F50: =-#REF! | G50: =-#REF! | H50: =-#REF! | I50: =-#REF! | J50: =-#REF! | K50: =-#REF! | ... W50: =-#REF!
B51: Outflow : 其它費用(人事薪資…等) | F51: =-(F41*#REF!) | G51: =-(G41*#REF!) | H51: =-(H41*#REF!) | I51: =-(I41*#REF!) | J51: =-(J41*#REF!) | K51: =-(K41*#REF!) | L51: =-(L41*#REF!) | M51: =-(M41*#REF!) | ... W51: =-(W41*#REF!)
B52: 1%管理費
B53: 績效獎金
B54: 所得稅20% | D54: =IF((#REF!+SUM(#REF!+#REF!+#REF!+#REF!+#REF!+#REF!))>0,-(#REF!+SUM(#REF!+#REF!+#REF!+#REF!+#REF!+#REF!))*0.2,0) | E54: =IF((#REF!+SUM(#REF!+#REF!+#REF!+#REF!+#REF!+#REF!))>0,-(#REF!+SUM(#REF!+#REF!+#REF!+#REF!+#REF!+#REF!))*0.2,0) | F54: =IF((#REF!+SUM(#REF!+#REF!+#REF!+#REF!+#REF!+#REF!))>0,-(#REF!+SUM(#REF!+#REF!+#REF!+#REF!+#REF!+#REF!))*0.2,0) | G54: =IF((#REF!+SUM(#REF!+#REF!+#REF!+#REF!+#REF!+#REF!))>0,-(#REF!+SUM(#REF!+#REF!+#REF!+#REF!+#REF!+#REF!))*0.2,0) | H54: =IF((#REF!+SUM(#REF!+#REF!+#REF!+#REF!+#REF!+#REF!))>0,-(#REF!+SUM(#REF!+#REF!+#REF!+#REF!+#REF!+#REF!))*0.2,0) | I54: =IF((#REF!+SUM(#REF!+#REF!+#REF!+#REF!+#REF!+#REF!))>0,-(#REF!+SUM(#REF!+#REF!+#REF!+#REF!+#REF!+#REF!))*0.2,0) | J54: =IF((#REF!+SUM(#REF!+#REF!+#REF!+#REF!+#REF!+#REF!))>0,-(#REF!+SUM(#REF!+#REF!+#REF!+#REF!+#REF!+#REF!))*0.2,0) | K54: =IF((#REF!+SUM(#REF!+#REF!+#REF!+#REF!+#REF!+#REF!))>0,-(#REF!+SUM(#REF!+#REF!+#REF!+#REF!+#REF!+#REF!))*0.2,0) | ... W54: =IF((#REF!+SUM(#REF!+#REF!+#REF!+#REF!+#REF!+#REF!))>0,-(#REF!+SUM(#REF!+#REF!+#REF!+#REF!+#REF!+#REF!))*0.2,0)
B56: 現金流 | C56: =C44 | D56: =SUM(D41:D54) | E56: =SUM(E41:E54) | F56: =SUM(F41:F54) | G56: =SUM(G41:G54) | H56: =SUM(H41:H54) | I56: =SUM(I41:I54) | J56: =SUM(J41:J54) | K56: =SUM(K41:K54) | ... W56: =SUM(W41:W54)
B57: 累計現金流 | D57: =D56+C56 | E57: =E56+D57 | F57: =F56+E57 | G57: =G56+F57 | H57: =H56+G57 | I57: =I56+H57 | J57: =J56+I57 | K57: =K56+J57 | L57: =L56+K57 | ... W57: =W56+V57
B58: Discounted cash flow | C58: -37721416 | F58: 4765724.1 | G58: 4715578.7 | H58: 4665433.3 | I58: 4615287.9 | J58: 4565142.4 | K58: 4517504.3 | L58: 4469866.2 | M58: 4422228 | N58: 4374589.9 | O58: 4326951.7 | P58: 4284954.9 | Q58: 4242958.2 | R58: 4200961.4 | S58: 4158964.6 | T58: 4116967.8 | U58: 4074971 | V58: 4032974.2 | W58: 3990977.4
B59: Minus : Depreciation | F59: 1886070.8 | G59: 1886070.8 | H59: 1886070.8 | I59: 1886070.8 | J59: 1886070.8 | K59: 1886070.8 | L59: 1886070.8 | M59: 1886070.8 | N59: 1886070.8 | O59: 1886070.8 | P59: 1886070.8 | Q59: 1886070.8 | R59: 1886070.8 | S59: 1886070.8 | T59: 1886070.8 | U59: 1886070.8 | V59: 1886070.8 | W59: 1886070.8
B60: Plus : Principle payment | F60: 0 | G60: 0 | H60: 0 | I60: 0 | J60: 0 | K60: 0 | L60: 0 | M60: 0 | N60: 0 | O60: 0 | P60: 0 | Q60: 0 | R60: 0 | S60: 0 | T60: 0 | U60: 0 | V60: 0 | W60: 0
B61: Profit | F61: 2879653.3 | G61: 2829507.9 | H61: 2779362.5 | I61: 2729217 | J61: 2679071.6 | K61: 2631433.5 | L61: 2583795.3 | M61: 2536157.2 | N61: 2488519 | O61: 2440880.9 | P61: 2398884.1 | Q61: 2356887.3 | R61: 2314890.5 | S61: 2272893.8 | T61: 2230897 | U61: 2188900.2 | V61: 2146903.4 | W61: 2104906.6
B62: EPS | F62: 0.76340009 | G62: 0.75010647 | H62: 0.73681286 | I62: 0.72351924 | J62: 0.71022562 | K62: 0.69759668 | L62: 0.68496774 | M62: 0.6723388 | N62: 0.65970986 | O62: 0.64708093 | P62: 0.63594752 | Q62: 0.62481411 | R62: 0.61368071 | S62: 0.6025473 | T62: 0.59141389 | U62: 0.58028049 | V62: 0.56914708 | W62: 0.55801368
B63: 回收年限評估 | D63: =IF((D57)>0,"回收","未回收") | E63: =IF((E57)>0,"回收","未回收") | F63: =IF((F57)>0,"回收","未回收") | G63: =IF((G57)>0,"回收","未回收") | H63: =IF((H57)>0,"回收","未回收") | I63: =IF((I57)>0,"回收","未回收") | J63: =IF((J57)>0,"回收","未回收") | K63: =IF((K57)>0,"回收","未回收") | ... W63: =IF((W57)>0,"回收","未回收")
L65: 預估可建置量 | M65: 0
L66: 預估可建置量 | M66: 0
C67: 年份 | D67: 2020 | E67: 2021 | F67: 2022 | G67: 2023 | H67: 2024 | I67: 2025 | J67: 2026 | K67: 2027 | L67: 2028 | M67: 2029 | N67: 2030 | O67: 2031 | P67: 2032 | Q67: 2033 | R67: 2034 | S67: 2035 | T67: 2036 | U67: 2037 | V67: 2038 | W67: 2039
B69: (Unit : Currency) | C69: 0 | D69: 1 | E69: 2 | F69: 3 | G69: 4 | H69: 5 | I69: 6 | J69: 7 | K69: 8 | L69: 9 | M69: 10 | N69: 11 | O69: 12 | P69: 13 | Q69: 14 | R69: 15 | S69: 16 | T69: 17 | U69: 18 | V69: 19 | W69: 20
B70: 稅後淨利 | D70: =#REF! | E70: =#REF! | F70: =#REF! | G70: =#REF! | H70: =#REF! | I70: =#REF! | J70: =#REF! | K70: =#REF! | ... W70: =#REF!
B71: 設備折舊 | D71: =-#REF! | E71: =-#REF! | F71: =-#REF! | G71: =-#REF! | H71: =-#REF! | I71: =-#REF! | J71: =-#REF! | K71: =-#REF! | ... W71: =-#REF!
B72: 營運活動現金流量 | D72: =SUM(D70:D71) | E72: =SUM(E70:E71) | F72: =SUM(F70:F71) | G72: =SUM(G70:G71) | H72: =SUM(H70:H71) | I72: =SUM(I70:I71) | J72: =SUM(J70:J71) | K72: =SUM(K70:K71) | ... W72: =SUM(W70:W71)
B74: 投資活動-設備支出 | D74: =C44 | E74: 0 | G74: 0 | H74: 0 | I74: 0 | J74: 0 | K74: 0 | L74: 0 | M74: 0 | N74: 0 | O74: 0 | P74: 0 | Q74: 0 | R74: 0 | S74: 0 | T74: 0 | U74: 0 | V74: 0 | W74: 0
B77: 理財活動-借款 | D77: =#REF!*0.8 | G77: 0 | H77: 0 | I77: 0 | J77: 0 | K77: 0 | L77: 0 | M77: 0 | N77: 0 | O77: 0 | P77: 0 | Q77: 0 | R77: 0 | S77: 0 | T77: 0 | U77: 0 | V77: 0 | W77: 0
B78: 理財活動-還款 | E78: =-#REF! | F78: =-#REF! | G78: =-#REF! | H78: =-#REF! | I78: =-#REF! | J78: =-#REF! | K78: =-#REF! | L78: =-#REF! | ... S78: =-#REF!
B79: 理財活動-現金增資 | D79: =#REF!*0.2
B80: 現金股利 | E80: =-D70*0.9 | F80: =-E70*0.9 | G80: =-F70*0.9 | H80: =-G70*0.9 | I80: =-H70*0.9 | J80: =-I70*0.9 | K80: =-J70*0.9 | L80: =-K70*0.9 | ... U80: =-T70*0.9 | W80: =-V70*0.9
B81: 年底減資 | R81: =-$D$79/4 | S81: =-$D$79/4 | T81: =-$D$79/4 | U81: =-$D$79/4
B84: 現金淨流入(出 ) | C84: =SUM(C74:C83) | D84: =SUM(D72:D83) | E84: =SUM(E72:E83) | F84: =SUM(F72:F83) | G84: =SUM(G72:G83) | H84: =SUM(H72:H83) | I84: =SUM(I72:I83) | J84: =SUM(J72:J83) | K84: =SUM(K72:K83) | ... W84: =SUM(W72:W83)
B85: 期初淨現金 | C85: 0 | D85: =C86 | E85: =D86 | F85: =E86 | G85: =F86 | H85: =G86 | I85: =H86 | J85: =I86 | K85: =J86 | ... U85: =T86
B86: 期未淨現金 | C86: =C84 | D86: =D84+D85 | E86: =E84+E85 | F86: =F84+F85 | G86: =G84+G85 | H86: =H84+H85 | I86: =I84+I85 | J86: =J84+J85 | K86: =K84+K85 | ... U86: =U84+U85
B89: 成本法實際現金流 | D89: =-D79 | E89: =-E80-E81 | F89: =-F80-F81 | G89: =-G80-G81 | H89: =-H80-H81 | I89: =-I80-I81 | J89: =-J80-J81 | K89: =-K80-K81 | L89: =-L80-L81 | ... W89: =-W80-W81
B90: 成本法IRR | C90: =IRR(D89:W89)
B91: 權益法實際現金流 | D91: =#REF!-D79 | E91: =#REF! | F91: =#REF!-F81 | G91: =#REF!-G81 | H91: =#REF!-H81 | I91: =#REF!-I81 | J91: =#REF!-J81 | K91: =#REF!-K81 | L91: =#REF!-L81 | M91: =#REF!-M81 | ... W91: =#REF!-W81
B92: 權益法IRR | C92: =IRR(D91:W91)
B94: 借款餘額 | C94: 0 | D94: =D77 | E94: =D94+E77+E78 | F94: =E94+F77+F78 | G94: =F94+G77+G78 | H94: =G94+H77+H78 | I94: =H94+I77+I78 | J94: =I94+J77+J78 | K94: =J94+K77+K78 | L94: =K94+L77+L78 | ... S94: =R94+S77+S78

Sheet 開始滾算紀錄2
B1: 電站基本資料
B2: 電站名稱 | C2: 淡江大學-財務模擬案場 | D2: - | E2: -
B3: 電站壽命 | C3: 20 | D3: - | E3: -
B4: 建置量(kWp) | C4: 436.1 | D4: - | E4: -
B5: 起始年度 | C5: 2020 | D5: 結束年度 | E5: 2039 | M5: 第2次滾算摘要
M6: 價金: 29000
B7: 綜合損益表 | M7: 專案IRR: 4.63
B8: 收入 | M8: 權益法IRR: 11.74
B9: 收支項目 | C9: 相關參數 | D9: 參數數值 | E9: 年限 | M9: 利潤率: 20.00%
B10: 電費收入 | C10: 年度AC併網總發電量 | D10: 547002 | E10: 20 | M10: 第2次滾算，減少 500 元 - 現金模式，每次減少 500 元
C11: 首年衰退率 | D11: 0.01
C12: 次年衰退率 | D12: 0.004
C13: 躉售費率(FIT) | D13: 3.7152
B14: 支出
B15: 收支項目 | C15: 相關參數 | D15: 參數數值 | E15: 攤提年限
B16: 設備費用(價金) | C16: 每kWp設備成本 | D16: 29000 | E16: 20
C17: 信邦利潤率 | D17: 0.2
C18: 開發費 | D18: 2000
B19: 租金費用 | C19: 租金計算方式 (1=固定攤提/2=電費抽成) | D19: 1 | E19: 0
C20: 【方式1參數】租金總額 | D20: 5804025 | E20: 20
C21: 【方式2參數】抽成比率 | D21: 0 | E21: 0
B22: 運維費用 | C22: 每kw運維成本 | D22: 400 | E22: 20
B23: 保險費用 | C23: 占整體設備費用比例 | D23: 0.003 | E23: 20
B24: 模組回收費用 | C24: 每kw模組回收成本 | D24: 1000 | E24: 10
B25: 利息費用 | C25: 銀行利率 | D25: 0.025595 | E25: 0
B26: 所得稅 | C26: 所得稅率 | D26: 0.2 | E26: 0
B29: 現金流量表
B30: 金流項目 | C30: 相關參數 | D30: 參數數值
B31: 貸款成數 | C31: 占總設備費用比例 | D31: 0.8
B32: 貸款還款 | C32: 攤還期數 | D32: 15
B33: 現金股利 | C33: 股利比率 | D33: 0.9
B34: 年底減資 | C34: 攤還期數 | D34: 4
C37: 年份 | D37: 2020 | E37: 2021 | F37: 2022 | G37: 2023 | H37: 2024 | I37: 2025 | J37: 2026 | K37: 2027 | L37: 2028 | M37: 2029 | N37: 2030 | O37: 2031 | P37: 2032 | Q37: 2033 | R37: 2034 | S37: 2035 | T37: 2036 | U37: 2037 | V37: 2038 | W37: 2039
B38: 0 | F38: 手動計算值 | T38: 償還年限
B39: (Unit : Currency) | C39: 0 | D39: 1 | E39: 2 | F39: 3 | G39: 4 | H39: 5 | I39: 6 | J39: 7 | K39: 8 | L39: 9 | M39: 10 | N39: 11 | O39: 12 | P39: 13 | Q39: 14 | R39: 15 | S39: 16 | T39: 17 | U39: 18 | V39: 19 | W39: 20
B40: 發電度數(KWH) | C40: 0 | D40: =#REF! | E40: =#REF! | F40: =#REF! | G40: =#REF! | H40: =#REF! | I40: =#REF! | J40: =#REF! | K40: =#REF! | ... W40: =#REF!
B41: Inflow : 電費收入 | C41: - | D41: =#REF! | E41: =#REF! | F41: =#REF! | G41: =#REF! | H41: =#REF! | I41: =#REF! | J41: =#REF! | K41: =#REF! | ... W41: =#REF!
B42: Inflow : 政府補助 | C42: - | F42: 0 | G42: - | H42: - | I42: - | J42: - | K42: - | L42: - | M42: - | N42: - | O42: - | P42: - | Q42: - | R42: - | S42: - | T42: - | U42: - | V42: - | W42: -
B43: Inflow : 銀行借款
B44: Outflow : 設備費用 | C44: =-#REF! | F44: - | G44: - | H44: - | I44: - | J44: - | K44: - | L44: - | M44: - | N44: - | O44: - | P44: - | Q44: - | R44: - | S44: - | T44: - | U44: - | V44: - | W44: -
B45: Outflow : 設備放置區域租金 | C45: - | D45: =-#REF! | E45: =-#REF! | F45: =-#REF! | G45: =-#REF! | H45: =-#REF! | I45: =-#REF! | J45: =-#REF! | K45: =-#REF! | ... W45: =-#REF!
B46: Outflow : 返還借款 | C46: 0 | V46: 0 | W46: 0
B47: Outflow : 利息費用 | C47: -
B48: Outflow : 維運費 | C48: - | D48: =-#REF! | E48: =-#REF! | F48: =-#REF! | G48: =-#REF! | H48: =-#REF! | I48: =-#REF! | J48: =-#REF! | K48: =-#REF! | ... W48: =-#REF!
B49: Outflow : 保險費 | C49: - | D49: =-#REF! | E49: =-#REF! | F49: =-#REF! | G49: =-#REF! | H49: =-#REF! | I49: =-#REF! | J49: =-#REF! | K49: =-#REF! | ... W49: =-#REF!
B50: Outflow : 模組回收費 | D50: =-#REF! | E50: =-#REF! | F50: =-#REF! | G50: =-#REF! | H50: =-#REF! | I50: =-#REF! | J50: =-#REF! | K50: =-#REF! | ... W50: =-#REF!
B51: Outflow : 其它費用(人事薪資…等) | F51: =-(F41*#REF!) | G51: =-(G41*#REF!) | H51: =-(H41*#REF!) | I51: =-(I41*#REF!) | J51: =-(J41*#REF!) | K51: =-(K41*#REF!) | L51: =-(L41*#REF!) | M51: =-(M41*#REF!) | ... W51: =-(W41*#REF!)
B52: 1%管理費
B53: 績效獎金
B54: 所得稅20% | D54: =IF((#REF!+SUM(#REF!+#REF!+#REF!+#REF!+#REF!+#REF!))>0,-(#REF!+SUM(#REF!+#REF!+#REF!+#REF!+#REF!+#REF!))*0.2,0) | E54: =IF((#REF!+SUM(#REF!+#REF!+#REF!+#REF!+#REF!+#REF!))>0,-(#REF!+SUM(#REF!+#REF!+#REF!+#REF!+#REF!+#REF!))*0.2,0) | F54: =IF((#REF!+SUM(#REF!+#REF!+#REF!+#REF!+#REF!+#REF!))>0,-(#REF!+SUM(#REF!+#REF!+#REF!+#REF!+#REF!+#REF!))*0.2,0) | G54: =IF((#REF!+SUM(#REF!+#REF!+#REF!+#REF!+#REF!+#REF!))>0,-(#REF!+SUM(#REF!+#REF!+#REF!+#REF!+#REF!+#REF!))*0.2,0) | H54: =IF((#REF!+SUM(#REF!+#REF!+#REF!+#REF!+#REF!+#REF!))>0,-(#REF!+SUM(#REF!+#REF!+#REF!+#REF!+#REF!+#REF!))*0.2,0) | I54: =IF((#REF!+SUM(#REF!+#REF!+#REF!+#REF!+#REF!+#REF!))>0,-(#REF!+SUM(#REF!+#REF!+#REF!+#REF!+#REF!+#REF!))*0.2,0) | J54: =IF((#REF!+SUM(#REF!+#REF!+#REF!+#REF!+#REF!+#REF!))>0,-(#REF!+SUM(#REF!+#REF!+#REF!+#REF!+#REF!+#REF!))*0.2,0) | K54: =IF((#REF!+SUM(#REF!+#REF!+#REF!+#REF!+#REF!+#REF!))>0,-(#REF!+SUM(#REF!+#REF!+#REF!+#REF!+#REF!+#REF!))*0.2,0) | ... W54: =IF((#REF!+SUM(#REF!+#REF!+#REF!+#REF!+#REF!+#REF!))>0,-(#REF!+SUM(#REF!+#REF!+#REF!+#REF!+#REF!+#REF!))*0.2,0)
B56: 現金流 | C56: =C44 | D56: =SUM(D41:D54) | E56: =SUM(E41:E54) | F56: =SUM(F41:F54) | G56: =SUM(G41:G54) | H56: =SUM(H41:H54) | I56: =SUM(I41:I54) | J56: =SUM(J41:J54) | K56: =SUM(K41:K54) | ... W56: =SUM(W41:W54)
B57: 累計現金流 | D57: =D56+C56 | E57: =E56+D57 | F57: =F56+E57 | G57: =G56+F57 | H57: =H56+G57 | I57: =I56+H57 | J57: =J56+I57 | K57: =K56+J57 | L57: =L56+K57 | ... W57: =W56+V57
B58: Discounted cash flow | C58: -37721416 | F58: 4765724.1 | G58: 4715578.7 | H58: 4665433.3 | I58: 4615287.9 | J58: 4565142.4 | K58: 4517504.3 | L58: 4469866.2 | M58: 4422228 | N58: 4374589.9 | O58: 4326951.7 | P58: 4284954.9 | Q58: 4242958.2 | R58: 4200961.4 | S58: 4158964.6 | T58: 4116967.8 | U58: 4074971 | V58: 4032974.2 | W58: 3990977.4
B59: Minus : Depreciation | F59: 1886070.8 | G59: 1886070.8 | H59: 1886070.8 | I59: 1886070.8 | J59: 1886070.8 | K59: 1886070.8 | L59: 1886070.8 | M59: 1886070.8 | N59: 1886070.8 | O59: 1886070.8 | P59: 1886070.8 | Q59: 1886070.8 | R59: 1886070.8 | S59: 1886070.8 | T59: 1886070.8 | U59: 1886070.8 | V59: 1886070.8 | W59: 1886070.8
B60: Plus : Principle payment | F60: 0 | G60: 0 | H60: 0 | I60: 0 | J60: 0 | K60: 0 | L60: 0 | M60: 0 | N60: 0 | O60: 0 | P60: 0 | Q60: 0 | R60: 0 | S60: 0 | T60: 0 | U60: 0 | V60: 0 | W60: 0
B61: Profit | F61: 2879653.3 | G61: 2829507.9 | H61: 2779362.5 | I61: 2729217 | J61: 2679071.6 | K61: 2631433.5 | L61: 2583795.3 | M61: 2536157.2 | N61: 2488519 | O61: 2440880.9 | P61: 2398884.1 | Q61: 2356887.3 | R61: 2314890.5 | S61: 2272893.8 | T61: 2230897 | U61: 2188900.2 | V61: 2146903.4 | W61: 2104906.6
B62: EPS | F62: 0.76340009 | G62: 0.75010647 | H62: 0.73681286 | I62: 0.72351924 | J62: 0.71022562 | K62: 0.69759668 | L62: 0.68496774 | M62: 0.6723388 | N62: 0.65970986 | O62: 0.64708093 | P62: 0.63594752 | Q62: 0.62481411 | R62: 0.61368071 | S62: 0.6025473 | T62: 0.59141389 | U62: 0.58028049 | V62: 0.56914708 | W62: 0.55801368
B63: 回收年限評估 | D63: =IF((D57)>0,"回收","未回收") | E63: =IF((E57)>0,"回收","未回收") | F63: =IF((F57)>0,"回收","未回收") | G63: =IF((G57)>0,"回收","未回收") | H63: =IF((H57)>0,"回收","未回收") | I63: =IF((I57)>0,"回收","未回收") | J63: =IF((J57)>0,"回收","未回收") | K63: =IF((K57)>0,"回收","未回收") | ... W63: =IF((W57)>0,"回收","未回收")
L65: 預估可建置量 | M65: 0
L66: 預估可建置量 | M66: 0
C67: 年份 | D67: 2020 | E67: 2021 | F67: 2022 | G67: 2023 | H67: 2024 | I67: 2025 | J67: 2026 | K67: 2027 | L67: 2028 | M67: 2029 | N67: 2030 | O67: 2031 | P67: 2032 | Q67: 2033 | R67: 2034 | S67: 2035 | T67: 2036 | U67: 2037 | V67: 2038 | W67: 2039
B69: (Unit : Currency) | C69: 0 | D69: 1 | E69: 2 | F69: 3 | G69: 4 | H69: 5 | I69: 6 | J69: 7 | K69: 8 | L69: 9 | M69: 10 | N69: 11 | O69: 12 | P69: 13 | Q69: 14 | R69: 15 | S69: 16 | T69: 17 | U69: 18 | V69: 19 | W69: 20
B70: 稅後淨利 | D70: =#REF! | E70: =#REF! | F70: =#REF! | G70: =#REF! | H70: =#REF! | I70: =#REF! | J70: =#REF! | K70: =#REF! | ... W70: =#REF!
B71: 設備折舊 | D71: =-#REF! | E71: =-#REF! | F71: =-#REF! | G71: =-#REF! | H71: =-#REF! | I71: =-#REF! | J71: =-#REF! | K71: =-#REF! | ... W71: =-#REF!
B72: 營運活動現金流量 | D72: =SUM(D70:D71) | E72: =SUM(E70:E71) | F72: =SUM(F70:F71) | G72: =SUM(G70:G71) | H72: =SUM(H70:H71) | I72: =SUM(I70:I71) | J72: =SUM(J70:J71) | K72: =SUM(K70:K71) | ... W72: =SUM(W70:W71)
B74: 投資活動-設備支出 | D74: =C44 | E74: 0 | G74: 0 | H74: 0 | I74: 0 | J74: 0 | K74: 0 | L74: 0 | M74: 0 | N74: 0 | O74: 0 | P74: 0 | Q74: 0 | R74: 0 | S74: 0 | T74: 0 | U74: 0 | V74: 0 | W74: 0
B77: 理財活動-借款 | D77: =#REF!*0.8 | G77: 0 | H77: 0 | I77: 0 | J77: 0 | K77: 0 | L77: 0 | M77: 0 | N77: 0 | O77: 0 | P77: 0 | Q77: 0 | R77: 0 | S77: 0 | T77: 0 | U77: 0 | V77: 0 | W77: 0
B78: 理財活動-還款 | E78: =-#REF! | F78: =-#REF! | G78: =-#REF! | H78: =-#REF! | I78: =-#REF! | J78: =-#REF! | K78: =-#REF! | L78: =-#REF! | ... S78: =-#REF!
B79: 理財活動-現金增資 | D79: =#REF!*0.2
B80: 現金股利 | E80: =-D70*0.9 | F80: =-E70*0.9 | G80: =-F70*0.9 | H80: =-G70*0.9 | I80: =-H70*0.9 | J80: =-I70*0.9 | K80: =-J70*0.9 | L80: =-K70*0.9 | ... U80: =-T70*0.9 | W80: =-V70*0.9
B81: 年底減資 | R81: =-$D$79/4 | S81: =-$D$79/4 | T81: =-$D$79/4 | U81: =-$D$79/4
B84: 現金淨流入(出 ) | C84: =SUM(C74:C83) | D84: =SUM(D72:D83) | E84: =SUM(E72:E83) | F84: =SUM(F72:F83) | G84: =SUM(G72:G83) | H84: =SUM(H72:H83) | I84: =SUM(I72:I83) | J84: =SUM(J72:J83) | K84: =SUM(K72:K83) | ... W84: =SUM(W72:W83)
B85: 期初淨現金 | C85: 0 | D85: =C86 | E85: =D86 | F85: =E86 | G85: =F86 | H85: =G86 | I85: =H86 | J85: =I86 | K85: =J86 | ... U85: =T86
B86: 期未淨現金 | C86: =C84 | D86: =D84+D85 | E86: =E84+E85 | F86: =F84+F85 | G86: =G84+G85 | H86: =H84+H85 | I86: =I84+I85 | J86: =J84+J85 | K86: =K84+K85 | ... U86: =U84+U85
B89: 成本法實際現金流 | D89: =-D79 | E89: =-E80-E81 | F89: =-F80-F81 | G89: =-G80-G81 | H89: =-H80-H81 | I89: =-I80-I81 | J89: =-J80-J81 | K89: =-K80-K81 | L89: =-L80-L81 | ... W89: =-W80-W81
B90: 成本法IRR | C90: =IRR(D89:W89)
B91: 權益法實際現金流 | D91: =#REF!-D79 | E91: =#REF! | F91: =#REF!-F81 | G91: =#REF!-G81 | H91: =#REF!-H81 | I91: =#REF!-I81 | J91: =#REF!-J81 | K91: =#REF!-K81 | L91: =#REF!-L81 | M91: =#REF!-M81 | ... W91: =#REF!-W81
B92: 權益法IRR | C92: =IRR(D91:W91)
B94: 借款餘額 | C94: 0 | D94: =D77 | E94: =D94+E77+E78 | F94: =E94+F77+F78 | G94: =F94+G77+G78 | H94: =G94+H77+H78 | I94: =H94+I77+I78 | J94: =I94+J77+J78 | K94: =J94+K77+K78 | L94: =K94+L77+L78 | ... S94: =R94+S77+S78

Sheet 開始滾算紀錄3
B1: 電站基本資料
B2: 電站名稱 | C2: 淡江大學-財務模擬案場 | D2: - | E2: -
B3: 電站壽命 | C3: 20 | D3: - | E3: -
B4: 建置量(kWp) | C4: 436.1 | D4: - | E4: -
B5: 起始年度 | C5: 2020 | D5: 結束年度 | E5: 2039 | M5: 第3次滾算摘要
M6: 價金: 28500
B7: 綜合損益表 | M7: 專案IRR: 4.8
B8: 收入 | M8: 權益法IRR: 12.44
B9: 收支項目 | C9: 相關參數 | D9: 參數數值 | E9: 年限 | M9: 利潤率: 20.00%
B10: 電費收入 | C10: 年度AC併網總發電量 | D10: 547002 | E10: 20 | M10: 第3次滾算，減少 500 元 - 現金模式，每次減少 500 元
C11: 首年衰退率 | D11: 0.01
C12: 次年衰退率 | D12: 0.004
C13: 躉售費率(FIT) | D13: 3.7152
B14: 支出
B15: 收支項目 | C15: 相關參數 | D15: 參數數值 | E15: 攤提年限
B16: 設備費用(價金) | C16: 每kWp設備成本 | D16: 28500 | E16: 20
C17: 信邦利潤率 | D17: 0.2
C18: 開發費 | D18: 2000
B19: 租金費用 | C19: 租金計算方式 (1=固定攤提/2=電費抽成) | D19: 1 | E19: 0
C20: 【方式1參數】租金總額 | D20: 5804025 | E20: 20
C21: 【方式2參數】抽成比率 | D21: 0 | E21: 0
B22: 運維費用 | C22: 每kw運維成本 | D22: 400 | E22: 20
B23: 保險費用 | C23: 占整體設備費用比例 | D23: 0.003 | E23: 20
B24: 模組回收費用 | C24: 每kw模組回收成本 | D24: 1000 | E24: 10
B25: 利息費用 | C25: 銀行利率 | D25: 0.025595 | E25: 0
B26: 所得稅 | C26: 所得稅率 | D26: 0.2 | E26: 0
B29: 現金流量表
B30: 金流項目 | C30: 相關參數 | D30: 參數數值
B31: 貸款成數 | C31: 占總設備費用比例 | D31: 0.8
B32: 貸款還款 | C32: 攤還期數 | D32: 15
B33: 現金股利 | C33: 股利比率 | D33: 0.9
B34: 年底減資 | C34: 攤還期數 | D34: 4
C37: 年份 | D37: 2020 | E37: 2021 | F37: 2022 | G37: 2023 | H37: 2024 | I37: 2025 | J37: 2026 | K37: 2027 | L37: 2028 | M37: 2029 | N37: 2030 | O37: 2031 | P37: 2032 | Q37: 2033 | R37: 2034 | S37: 2035 | T37: 2036 | U37: 2037 | V37: 2038 | W37: 2039
B38: 0 | F38: 手動計算值 | T38: 償還年限
B39: (Unit : Currency) | C39: 0 | D39: 1 | E39: 2 | F39: 3 | G39: 4 | H39: 5 | I39: 6 | J39: 7 | K39: 8 | L39: 9 | M39: 10 | N39: 11 | O39: 12 | P39: 13 | Q39: 14 | R39: 15 | S39: 16 | T39: 17 | U39: 18 | V39: 19 | W39: 20
B40: 發電度數(KWH) | C40: 0 | D40: =#REF! | E40: =#REF! | F40: =#REF! | G40: =#REF! | H40: =#REF! | I40: =#REF! | J40: =#REF! | K40: =#REF! | ... W40: =#REF!
B41: Inflow : 電費收入 | C41: - | D41: =#REF! | E41: =#REF! | F41: =#REF! | G41: =#REF! | H41: =#REF! | I41: =#REF! | J41: =#REF! | K41: =#REF! | ... W41: =#REF!
B42: Inflow : 政府補助 | C42: - | F42: 0 | G42: - | H42: - | I42: - | J42: - | K42: - | L42: - | M42: - | N42: - | O42: - | P42: - | Q42: - | R42: - | S42: - | T42: - | U42: - | V42: - | W42: -
B43: Inflow : 銀行借款
B44: Outflow : 設備費用 | C44: =-#REF! | F44: - | G44: - | H44: - | I44: - | J44: - | K44: - | L44: - | M44: - | N44: - | O44: - | P44: - | Q44: - | R44: - | S44: - | T44: - | U44: - | V44: - | W44: -
B45: Outflow : 設備放置區域租金 | C45: - | D45: =-#REF! | E45: =-#REF! | F45: =-#REF! | G45: =-#REF! | H45: =-#REF! | I45: =-#REF! | J45: =-#REF! | K45: =-#REF! | ... W45: =-#REF!
B46: Outflow : 返還借款 | C46: 0 | V46: 0 | W46: 0
B47: Outflow : 利息費用 | C47: -
B48: Outflow : 維運費 | C48: - | D48: =-#REF! | E48: =-#REF! | F48: =-#REF! | G48: =-#REF! | H48: =-#REF! | I48: =-#REF! | J48: =-#REF! | K48: =-#REF! | ... W48: =-#REF!
B49: Outflow : 保險費 | C49: - | D49: =-#REF! | E49: =-#REF! | F49: =-#REF! | G49: =-#REF! | H49: =-#REF! | I49: =-#REF! | J49: =-#REF! | K49: =-#REF! | ... W49: =-#REF!
B50: Outflow : 模組回收費 | D50: =-#REF! | E50: =-#REF! | F50: =-#REF! | G50: =-#REF! | H50: =-#REF! | I50: =-#REF! | J50: =-#REF! | K50: =-#REF! | ... W50: =-#REF!
B51: Outflow : 其它費用(人事薪資…等) | F51: =-(F41*#REF!) | G51: =-(G41*#REF!) | H51: =-(H41*#REF!) | I51: =-(I41*#REF!) | J51: =-(J41*#REF!) | K51: =-(K41*#REF!) | L51: =-(L41*#REF!) | M51: =-(M41*#REF!) | ... W51: =-(W41*#REF!)
B52: 1%管理費
B53: 績效獎金
B54: 所得稅20% | D54: =IF((#REF!+SUM(#REF!+#REF!+#REF!+#REF!+#REF!+#REF!))>0,-(#REF!+SUM(#REF!+#REF!+#REF!+#REF!+#REF!+#REF!))*0.2,0) | E54: =IF((#REF!+SUM(#REF!+#REF!+#REF!+#REF!+#REF!+#REF!))>0,-(#REF!+SUM(#REF!+#REF!+#REF!+#REF!+#REF!+#REF!))*0.2,0) | F54: =IF((#REF!+SUM(#REF!+#REF!+#REF!+#REF!+#REF!+#REF!))>0,-(#REF!+SUM(#REF!+#REF!+#REF!+#REF!+#REF!+#REF!))*0.2,0) | G54: =IF((#REF!+SUM(#REF!+#REF!+#REF!+#REF!+#REF!+#REF!))>0,-(#REF!+SUM(#REF!+#REF!+#REF!+#REF!+#REF!+#REF!))*0.2,0) | H54: =IF((#REF!+SUM(#REF!+#REF!+#REF!+#REF!+#REF!+#REF!))>0,-(#REF!+SUM(#REF!+#REF!+#REF!+#REF!+#REF!+#REF!))*0.2,0) | I54: =IF((#REF!+SUM(#REF!+#REF!+#REF!+#REF!+#REF!+#REF!))>0,-(#REF!+SUM(#REF!+#REF!+#REF!+#REF!+#REF!+#REF!))*0.2,0) | J54: =IF((#REF!+SUM(#REF!+#REF!+#REF!+#REF!+#REF!+#REF!))>0,-(#REF!+SUM(#REF!+#REF!+#REF!+#REF!+#REF!+#REF!))*0.2,0) | K54: =IF((#REF!+SUM(#REF!+#REF!+#REF!+#REF!+#REF!+#REF!))>0,-(#REF!+SUM(#REF!+#REF!+#REF!+#REF!+#REF!+#REF!))*0.2,0) | ... W54: =IF((#REF!+SUM(#REF!+#REF!+#REF!+#REF!+#REF!+#REF!))>0,-(#REF!+SUM(#REF!+#REF!+#REF!+#REF!+#REF!+#REF!))*0.2,0)
B56: 現金流 | C56: =C44 | D56: =SUM(D41:D54) | E56: =SUM(E41:E54) | F56: =SUM(F41:F54) | G56: =SUM(G41:G54) | H56: =SUM(H41:H54) | I56: =SUM(I41:I54) | J56: =SUM(J41:J54) | K56: =SUM(K41:K54) | ... W56: =SUM(W41:W54)
B57: 累計現金流 | D57: =D56+C56 | E57: =E56+D57 | F57: =F56+E57 | G57: =G56+F57 | H57: =H56+G57 | I57: =I56+H57 | J57: =J56+I57 | K57: =K56+J57 | L57: =L56+K57 | ... W57: =W56+V57
B58: Discounted cash flow | C58: -37721416 | F58: 4765724.1 | G58: 4715578.7 | H58: 4665433.3 | I58: 4615287.9 | J58: 4565142.4 | K58: 4517504.3 | L58: 4469866.2 | M58: 4422228 | N58: 4374589.9 | O58: 4326951.7 | P58: 4284954.9 | Q58: 4242958.2 | R58: 4200961.4 | S58: 4158964.6 | T58: 4116967.8 | U58: 4074971 | V58: 4032974.2 | W58: 3990977.4
B59: Minus : Depreciation | F59: 1886070.8 | G59: 1886070.8 | H59: 1886070.8 | I59: 1886070.8 | J59: 1886070.8 | K59: 1886070.8 | L59: 1886070.8 | M59: 1886070.8 | N59: 1886070.8 | O59: 1886070.8 | P59: 1886070.8 | Q59: 1886070.8 | R59: 1886070.8 | S59: 1886070.8 | T59: 1886070.8 | U59: 1886070.8 | V59: 1886070.8 | W59: 1886070.8
