Workbook

Sheet 多站彙整
C4: 年份 | D4: 2020 | E4: 2021 | F4: 2022 | G4: 2023 | H4: 2024 | I4: 2025 | J4: 2026 | K4: 2027 | L4: 2028 | M4: 2029 | N4: 2030 | O4: 2031 | P4: 2032 | Q4: 2033 | R4: 2034 | S4: 2035 | T4: 2036 | U4: 2037 | V4: 2038 | W4: 2039
C5: 預估發電度數
B6: 淡江大學 | D6: =ROUND(ABS(淡江大學_p3!D40),0) -> 541532 | E6: =ROUND(ABS(淡江大學_p3!E40),0) -> 539344 | F6: =ROUND(ABS(淡江大學_p3!F40),0) -> 537156 | G6: =ROUND(ABS(淡江大學_p3!G40),0) -> 534968 | H6: =ROUND(ABS(淡江大學_p3!H40),0) -> 532780 | I6: =ROUND(ABS(淡江大學_p3!I40),0) -> 530592 | J6: =ROUND(ABS(淡江大學_p3!J40),0) -> 528404 | K6: =ROUND(ABS(淡江大學_p3!K40),0) -> 526216 | ... W6: =ROUND(ABS(淡江大學_p3!W40),0) -> 499960
B7: 淡江大學 | D7: =ROUND(ABS(淡江大學_p4!D40),0) -> 541532 | E7: =ROUND(ABS(淡江大學_p4!E40),0) -> 539344 | F7: =ROUND(ABS(淡江大學_p4!F40),0) -> 537156 | G7: =ROUND(ABS(淡江大學_p4!G40),0) -> 534968 | H7: =ROUND(ABS(淡江大學_p4!H40),0) -> 532780 | I7: =ROUND(ABS(淡江大學_p4!I40),0) -> 530592 | J7: =ROUND(ABS(淡江大學_p4!J40),0) -> 528404 | K7: =ROUND(ABS(淡江大學_p4!K40),0) -> 526216 | ... W7: =ROUND(ABS(淡江大學_p4!W40),0) -> 499960
B8: 淡江大學 | D8: =ROUND(ABS(淡江大學_p5!D40),0) -> 541532 | E8: =ROUND(ABS(淡江大學_p5!E40),0) -> 539344 | F8: =ROUND(ABS(淡江大學_p5!F40),0) -> 537156 | G8: =ROUND(ABS(淡江大學_p5!G40),0) -> 534968 | H8: =ROUND(ABS(淡江大學_p5!H40),0) -> 532780 | I8: =ROUND(ABS(淡江大學_p5!I40),0) -> 530592 | J8: =ROUND(ABS(淡江大學_p5!J40),0) -> 528404 | K8: =ROUND(ABS(淡江大學_p5!K40),0) -> 526216 | ... W8: =ROUND(ABS(淡江大學_p5!W40),0) -> 499960
C9: 預估發電度數/年總計 | D9: =SUM(D6:D8) -> 1624596 | E9: =SUM(E6:E8) -> 1618032 | F9: =SUM(F6:F8) -> 1611468 | G9: =SUM(G6:G8) -> 1604904 | H9: =SUM(H6:H8) -> 1598340 | I9: =SUM(I6:I8) -> 1591776 | J9: =SUM(J6:J8) -> 1585212 | K9: =SUM(K6:K8) -> 1578648 | ... W9: =SUM(W6:W8) -> 1499880
C10: 年份 | D10: 2020 | E10: 2021 | F10: 2022 | G10: 2023 | H10: 2024 | I10: 2025 | J10: 2026 | K10: 2027 | L10: 2028 | M10: 2029 | N10: 2030 | O10: 2031 | P10: 2032 | Q10: 2033 | R10: 2034 | S10: 2035 | T10: 2036 | U10: 2037 | V10: 2038 | W10: 2039
C11: 預估收入
B12: 淡江大學 | D12: =ROUND(ABS(淡江大學_p3!D41),0) -> 2166128 | E12: =ROUND(ABS(淡江大學_p3!E41),0) -> 2157376 | F12: =ROUND(ABS(淡江大學_p3!F41),0) -> 2148624 | G12: =ROUND(ABS(淡江大學_p3!G41),0) -> 2139872 | H12: =ROUND(ABS(淡江大學_p3!H41),0) -> 2131120 | I12: =ROUND(ABS(淡江大學_p3!I41),0) -> 2122368 | J12: =ROUND(ABS(淡江大學_p3!J41),0) -> 2113616 | K12: =ROUND(ABS(淡江大學_p3!K41),0) -> 2104864 | ... W12: =ROUND(ABS(淡江大學_p3!W41),0) -> 1999839
B13: 淡江大學 | D13: =ROUND(ABS(淡江大學_p4!D41),0) -> 2166128 | E13: =ROUND(ABS(淡江大學_p4!E41),0) -> 2157376 | F13: =ROUND(ABS(淡江大學_p4!F41),0) -> 2148624 | G13: =ROUND(ABS(淡江大學_p4!G41),0) -> 2139872 | H13: =ROUND(ABS(淡江大學_p4!H41),0) -> 2131120 | I13: =ROUND(ABS(淡江大學_p4!I41),0) -> 2122368 | J13: =ROUND(ABS(淡江大學_p4!J41),0) -> 2113616 | K13: =ROUND(ABS(淡江大學_p4!K41),0) -> 2104864 | ... W13: =ROUND(ABS(淡江大學_p4!W41),0) -> 1999839
B14: 淡江大學 | D14: =ROUND(ABS(淡江大學_p5!D41),0) -> 2166128 | E14: =ROUND(ABS(淡江大學_p5!E41),0) -> 2157376 | F14: =ROUND(ABS(淡江大學_p5!F41),0) -> 2148624 | G14: =ROUND(ABS(淡江大學_p5!G41),0) -> 2139872 | H14: =ROUND(ABS(淡江大學_p5!H41),0) -> 2131120 | I14: =ROUND(ABS(淡江大學_p5!I41),0) -> 2122368 | J14: =ROUND(ABS(淡江大學_p5!J41),0) -> 2113616 | K14: =ROUND(ABS(淡江大學_p5!K41),0) -> 2104864 | ... W14: =ROUND(ABS(淡江大學_p5!W41),0) -> 1999839
C15: 預估收入/年總計 | D15: =SUM(D12:D14) -> 6498384 | E15: =SUM(E12:E14) -> 6472128 | F15: =SUM(F12:F14) -> 6445872 | G15: =SUM(G12:G14) -> 6419616 | H15: =SUM(H12:H14) -> 6393360 | I15: =SUM(I12:I14) -> 6367104 | J15: =SUM(J12:J14) -> 6340848 | K15: =SUM(K12:K14) -> 6314592 | ... W15: =SUM(W12:W14) -> 5999517
C16: 年份 | D16: 2020 | E16: 2021 | F16: 2022 | G16: 2023 | H16: 2024 | I16: 2025 | J16: 2026 | K16: 2027 | L16: 2028 | M16: 2029 | N16: 2030 | O16: 2031 | P16: 2032 | Q16: 2033 | R16: 2034 | S16: 2035 | T16: 2036 | U16: 2037 | V16: 2038 | W16: 2039
C17: 租金
B18: 淡江大學 | D18: =ROUND(ABS(淡江大學_p3!D45),0) -> 290201 | E18: =ROUND(ABS(淡江大學_p3!E45),0) -> 290201 | F18: =ROUND(ABS(淡江大學_p3!F45),0) -> 290201 | G18: =ROUND(ABS(淡江大學_p3!G45),0) -> 290201 | H18: =ROUND(ABS(淡江大學_p3!H45),0) -> 290201 | I18: =ROUND(ABS(淡江大學_p3!I45),0) -> 290201 | J18: =ROUND(ABS(淡江大學_p3!J45),0) -> 290201 | K18: =ROUND(ABS(淡江大學_p3!K45),0) -> 290201 | ... W18: =ROUND(ABS(淡江大學_p3!W45),0) -> 290201
B19: 淡江大學 | D19: =ROUND(ABS(淡江大學_p4!D45),0) -> 290201 | E19: =ROUND(ABS(淡江大學_p4!E45),0) -> 290201 | F19: =ROUND(ABS(淡江大學_p4!F45),0) -> 290201 | G19: =ROUND(ABS(淡江大學_p4!G45),0) -> 290201 | H19: =ROUND(ABS(淡江大學_p4!H45),0) -> 290201 | I19: =ROUND(ABS(淡江大學_p4!I45),0) -> 290201 | J19: =ROUND(ABS(淡江大學_p4!J45),0) -> 290201 | K19: =ROUND(ABS(淡江大學_p4!K45),0) -> 290201 | ... W19: =ROUND(ABS(淡江大學_p4!W45),0) -> 290201
B20: 淡江大學 | D20: =ROUND(ABS(淡江大學_p5!D45),0) -> 290201 | E20: =ROUND(ABS(淡江大學_p5!E45),0) -> 290201 | F20: =ROUND(ABS(淡江大學_p5!F45),0) -> 290201 | G20: =ROUND(ABS(淡江大學_p5!G45),0) -> 290201 | H20: =ROUND(ABS(淡江大學_p5!H45),0) -> 290201 | I20: =ROUND(ABS(淡江大學_p5!I45),0) -> 290201 | J20: =ROUND(ABS(淡江大學_p5!J45),0) -> 290201 | K20: =ROUND(ABS(淡江大學_p5!K45),0) -> 290201 | ... W20: =ROUND(ABS(淡江大學_p5!W45),0) -> 290201
C21: 租金/年總計 | D21: =SUM(D18:D20) -> 870603 | E21: =SUM(E18:E20) -> 870603 | F21: =SUM(F18:F20) -> 870603 | G21: =SUM(G18:G20) -> 870603 | H21: =SUM(H18:H20) -> 870603 | I21: =SUM(I18:I20) -> 870603 | J21: =SUM(J18:J20) -> 870603 | K21: =SUM(K18:K20) -> 870603 | ... W21: =SUM(W18:W20) -> 870603
C22: 年份 | D22: 2020 | E22: 2021 | F22: 2022 | G22: 2023 | H22: 2024 | I22: 2025 | J22: 2026 | K22: 2027 | L22: 2028 | M22: 2029 | N22: 2030 | O22: 2031 | P22: 2032 | Q22: 2033 | R22: 2034 | S22: 2035 | T22: 2036 | U22: 2037 | V22: 2038 | W22: 2039
C23: 運維
B24: 淡江大學 | D24: =ROUND(ABS(淡江大學_p3!D48),0) -> 174440 | E24: =ROUND(ABS(淡江大學_p3!E48),0) -> 174440 | F24: =ROUND(ABS(淡江大學_p3!F48),0) -> 174440 | G24: =ROUND(ABS(淡江大學_p3!G48),0) -> 174440 | H24: =ROUND(ABS(淡江大學_p3!H48),0) -> 174440 | I24: =ROUND(ABS(淡江大學_p3!I48),0) -> 174440 | J24: =ROUND(ABS(淡江大學_p3!J48),0) -> 174440 | K24: =ROUND(ABS(淡江大學_p3!K48),0) -> 174440 | ... W24: =ROUND(ABS(淡江大學_p3!W48),0) -> 174440
B25: 淡江大學 | D25: =ROUND(ABS(淡江大學_p4!D48),0) -> 174440 | E25: =ROUND(ABS(淡江大學_p4!E48),0) -> 174440 | F25: =ROUND(ABS(淡江大學_p4!F48),0) -> 174440 | G25: =ROUND(ABS(淡江大學_p4!G48),0) -> 174440 | H25: =ROUND(ABS(淡江大學_p4!H48),0) -> 174440 | I25: =ROUND(ABS(淡江大學_p4!I48),0) -> 174440 | J25: =ROUND(ABS(淡江大學_p4!J48),0) -> 174440 | K25: =ROUND(ABS(淡江大學_p4!K48),0) -> 174440 | ... W25: =ROUND(ABS(淡江大學_p4!W48),0) -> 174440
B26: 淡江大學 | D26: =ROUND(ABS(淡江大學_p5!D48),0) -> 174440 | E26: =ROUND(ABS(淡江大學_p5!E48),0) -> 174440 | F26: =ROUND(ABS(淡江大學_p5!F48),0) -> 174440 | G26: =ROUND(ABS(淡江大學_p5!G48),0) -> 174440 | H26: =ROUND(ABS(淡江大學_p5!H48),0) -> 174440 | I26: =ROUND(ABS(淡江大學_p5!I48),0) -> 174440 | J26: =ROUND(ABS(淡江大學_p5!J48),0) -> 174440 | K26: =ROUND(ABS(淡江大學_p5!K48),0) -> 174440 | ... W26: =ROUND(ABS(淡江大學_p5!W48),0) -> 174440
C27: 運維/年總計 | D27: =SUM(D24:D26) -> 523320 | E27: =SUM(E24:E26) -> 523320 | F27: =SUM(F24:F26) -> 523320 | G27: =SUM(G24:G26) -> 523320 | H27: =SUM(H24:H26) -> 523320 | I27: =SUM(I24:I26) -> 523320 | J27: =SUM(J24:J26) -> 523320 | K27: =SUM(K24:K26) -> 523320 | ... W27: =SUM(W24:W26) -> 523320
C28: 年份 | D28: 2020 | E28: 2021 | F28: 2022 | G28: 2023 | H28: 2024 | I28: 2025 | J28: 2026 | K28: 2027 | L28: 2028 | M28: 2029 | N28: 2030 | O28: 2031 | P28: 2032 | Q28: 2033 | R28: 2034 | S28: 2035 | T28: 2036 | U28: 2037 | V28: 2038 | W28: 2039
C29: 保險
B30: 淡江大學 | D30: =ROUND(ABS(淡江大學_p3!D49),0) -> 40000 | E30: =ROUND(ABS(淡江大學_p3!E49),0) -> 40000 | F30: =ROUND(ABS(淡江大學_p3!F49),0) -> 40000 | G30: =ROUND(ABS(淡江大學_p3!G49),0) -> 40000 | H30: =ROUND(ABS(淡江大學_p3!H49),0) -> 40000 | I30: =ROUND(ABS(淡江大學_p3!I49),0) -> 40000 | J30: =ROUND(ABS(淡江大學_p3!J49),0) -> 40000 | K30: =ROUND(ABS(淡江大學_p3!K49),0) -> 40000 | ... W30: =ROUND(ABS(淡江大學_p3!W49),0) -> 40000
B31: 淡江大學 | D31: =ROUND(ABS(淡江大學_p4!D49),0) -> 37941 | E31: =ROUND(ABS(淡江大學_p4!E49),0) -> 37941 | F31: =ROUND(ABS(淡江大學_p4!F49),0) -> 37941 | G31: =ROUND(ABS(淡江大學_p4!G49),0) -> 37941 | H31: =ROUND(ABS(淡江大學_p4!H49),0) -> 37941 | I31: =ROUND(ABS(淡江大學_p4!I49),0) -> 37941 | J31: =ROUND(ABS(淡江大學_p4!J49),0) -> 37941 | K31: =ROUND(ABS(淡江大學_p4!K49),0) -> 37941 | ... W31: =ROUND(ABS(淡江大學_p4!W49),0) -> 37941
B32: 淡江大學 | D32: =ROUND(ABS(淡江大學_p5!D49),0) -> 35324 | E32: =ROUND(ABS(淡江大學_p5!E49),0) -> 35324 | F32: =ROUND(ABS(淡江大學_p5!F49),0) -> 35324 | G32: =ROUND(ABS(淡江大學_p5!G49),0) -> 35324 | H32: =ROUND(ABS(淡江大學_p5!H49),0) -> 35324 | I32: =ROUND(ABS(淡江大學_p5!I49),0) -> 35324 | J32: =ROUND(ABS(淡江大學_p5!J49),0) -> 35324 | K32: =ROUND(ABS(淡江大學_p5!K49),0) -> 35324 | ... W32: =ROUND(ABS(淡江大學_p5!W49),0) -> 35324
C33: 保險/年總計 | D33: =SUM(D30:D32) -> 113265 | E33: =SUM(E30:E32) -> 113265 | F33: =SUM(F30:F32) -> 113265 | G33: =SUM(G30:G32) -> 113265 | H33: =SUM(H30:H32) -> 113265 | I33: =SUM(I30:I32) -> 113265 | J33: =SUM(J30:J32) -> 113265 | K33: =SUM(K30:K32) -> 113265 | ... W33: =SUM(W30:W32) -> 113265
C34: 年份 | D34: 2020 | E34: 2021 | F34: 2022 | G34: 2023 | H34: 2024 | I34: 2025 | J34: 2026 | K34: 2027 | L34: 2028 | M34: 2029 | N34: 2030 | O34: 2031 | P34: 2032 | Q34: 2033 | R34: 2034 | S34: 2035 | T34: 2036 | U34: 2037 | V34: 2038 | W34: 2039
C35: 模組回收費
B36: 淡江大學 | D36: =ROUND(ABS(淡江大學_p3!D50),0) -> 43610 | E36: =ROUND(ABS(淡江大學_p3!E50),0) -> 43610 | F36: =ROUND(ABS(淡江大學_p3!F50),0) -> 43610 | G36: =ROUND(ABS(淡江大學_p3!G50),0) -> 43610 | H36: =ROUND(ABS(淡江大學_p3!H50),0) -> 43610 | I36: =ROUND(ABS(淡江大學_p3!I50),0) -> 43610 | J36: =ROUND(ABS(淡江大學_p3!J50),0) -> 43610 | K36: =ROUND(ABS(淡江大學_p3!K50),0) -> 43610 | ... W36: =ROUND(ABS(淡江大學_p3!W50),0) -> 0
B37: 淡江大學 | D37: =ROUND(ABS(淡江大學_p4!D50),0) -> 43610 | E37: =ROUND(ABS(淡江大學_p4!E50),0) -> 43610 | F37: =ROUND(ABS(淡江大學_p4!F50),0) -> 43610 | G37: =ROUND(ABS(淡江大學_p4!G50),0) -> 43610 | H37: =ROUND(ABS(淡江大學_p4!H50),0) -> 43610 | I37: =ROUND(ABS(淡江大學_p4!I50),0) -> 43610 | J37: =ROUND(ABS(淡江大學_p4!J50),0) -> 43610 | K37: =ROUND(ABS(淡江大學_p4!K50),0) -> 43610 | ... W37: =ROUND(ABS(淡江大學_p4!W50),0) -> 0
B38: 淡江大學 | D38: =ROUND(ABS(淡江大學_p5!D50),0) -> 43610 | E38: =ROUND(ABS(淡江大學_p5!E50),0) -> 43610 | F38: =ROUND(ABS(淡江大學_p5!F50),0) -> 43610 | G38: =ROUND(ABS(淡江大學_p5!G50),0) -> 43610 | H38: =ROUND(ABS(淡江大學_p5!H50),0) -> 43610 | I38: =ROUND(ABS(淡江大學_p5!I50),0) -> 43610 | J38: =ROUND(ABS(淡江大學_p5!J50),0) -> 43610 | K38: =ROUND(ABS(淡江大學_p5!K50),0) -> 43610 | ... W38: =ROUND(ABS(淡江大學_p5!W50),0) -> 0
C39: 模組回收費/年總計 | D39: =SUM(D36:D38) -> 130830 | E39: =SUM(E36:E38) -> 130830 | F39: =SUM(F36:F38) -> 130830 | G39: =SUM(G36:G38) -> 130830 | H39: =SUM(H36:H38) -> 130830 | I39: =SUM(I36:I38) -> 130830 | J39: =SUM(J36:J38) -> 130830 | K39: =SUM(K36:K38) -> 130830 | ... W39: =SUM(W36:W38) -> 0
C40: 年份 | D40: 2020 | E40: 2021 | F40: 2022 | G40: 2023 | H40: 2024 | I40: 2025 | J40: 2026 | K40: 2027 | L40: 2028 | M40: 2029 | N40: 2030 | O40: 2031 | P40: 2032 | Q40: 2033 | R40: 2034 | S40: 2035 | T40: 2036 | U40: 2037 | V40: 2038 | W40: 2039
C41: 所得稅
B42: 淡江大學 | D42: =ROUND(ABS(淡江大學_p3!D54),0) -> 179764 | E42: =ROUND(ABS(淡江大學_p3!E54),0) -> 119973 | F42: =ROUND(ABS(淡江大學_p3!F54),0) -> 118223 | G42: =ROUND(ABS(淡江大學_p3!G54),0) -> 116472 | H42: =ROUND(ABS(淡江大學_p3!H54),0) -> 114722 | I42: =ROUND(ABS(淡江大學_p3!I54),0) -> 112971 | J42: =ROUND(ABS(淡江大學_p3!J54),0) -> 111221 | K42: =ROUND(ABS(淡江大學_p3!K54),0) -> 109471 | ... W42: =ROUND(ABS(淡江大學_p3!W54),0) -> 97188
B43: 淡江大學 | D43: =ROUND(ABS(淡江大學_p4!D54),0) -> 192635 | E43: =ROUND(ABS(淡江大學_p4!E54),0) -> 132845 | F43: =ROUND(ABS(淡江大學_p4!F54),0) -> 131094 | G43: =ROUND(ABS(淡江大學_p4!G54),0) -> 129344 | H43: =ROUND(ABS(淡江大學_p4!H54),0) -> 127594 | I43: =ROUND(ABS(淡江大學_p4!I54),0) -> 125843 | J43: =ROUND(ABS(淡江大學_p4!J54),0) -> 124093 | K43: =ROUND(ABS(淡江大學_p4!K54),0) -> 122342 | ... W43: =ROUND(ABS(淡江大學_p4!W54),0) -> 110060
B44: 淡江大學 | D44: =ROUND(ABS(淡江大學_p5!D54),0) -> 205619 | E44: =ROUND(ABS(淡江大學_p5!E54),0) -> 145828 | F44: =ROUND(ABS(淡江大學_p5!F54),0) -> 144078 | G44: =ROUND(ABS(淡江大學_p5!G54),0) -> 142327 | H44: =ROUND(ABS(淡江大學_p5!H54),0) -> 140577 | I44: =ROUND(ABS(淡江大學_p5!I54),0) -> 138827 | J44: =ROUND(ABS(淡江大學_p5!J54),0) -> 137076 | K44: =ROUND(ABS(淡江大學_p5!K54),0) -> 135326 | ... W44: =ROUND(ABS(淡江大學_p5!W54),0) -> 123043
C45: 所得稅/年總計 | D45: =SUM(D42:D44) -> 578018 | E45: =SUM(E42:E44) -> 398646 | F45: =SUM(F42:F44) -> 393395 | G45: =SUM(G42:G44) -> 388143 | H45: =SUM(H42:H44) -> 382893 | I45: =SUM(I42:I44) -> 377641 | J45: =SUM(J42:J44) -> 372390 | K45: =SUM(K42:K44) -> 367139 | ... W45: =SUM(W42:W44) -> 330291
C46: 年份 | D46: 2020 | E46: 2021 | F46: 2022 | G46: 2023 | H46: 2024 | I46: 2025 | J46: 2026 | K46: 2027 | L46: 2028 | M46: 2029 | N46: 2030 | O46: 2031 | P46: 2032 | Q46: 2033 | R46: 2034 | S46: 2035 | T46: 2036 | U46: 2037 | V46: 2038 | W46: 2039
C47: 設備折舊
B48: 淡江大學 | D48: =ROUND(ABS(淡江大學_p3!D67),0) -> 1009260 | E48: =ROUND(ABS(淡江大學_p3!E67),0) -> 1009260 | F48: =ROUND(ABS(淡江大學_p3!F67),0) -> 1009260 | G48: =ROUND(ABS(淡江大學_p3!G67),0) -> 1009260 | H48: =ROUND(ABS(淡江大學_p3!H67),0) -> 1009260 | I48: =ROUND(ABS(淡江大學_p3!I67),0) -> 1009260 | J48: =ROUND(ABS(淡江大學_p3!J67),0) -> 1009260 | K48: =ROUND(ABS(淡江大學_p3!K67),0) -> 1009260 | ... W48: =ROUND(ABS(淡江大學_p3!W67),0) -> 1009260
B49: 淡江大學 | D49: =ROUND(ABS(淡江大學_p4!D67),0) -> 946960 | E49: =ROUND(ABS(淡江大學_p4!E67),0) -> 946960 | F49: =ROUND(ABS(淡江大學_p4!F67),0) -> 946960 | G49: =ROUND(ABS(淡江大學_p4!G67),0) -> 946960 | H49: =ROUND(ABS(淡江大學_p4!H67),0) -> 946960 | I49: =ROUND(ABS(淡江大學_p4!I67),0) -> 946960 | J49: =ROUND(ABS(淡江大學_p4!J67),0) -> 946960 | K49: =ROUND(ABS(淡江大學_p4!K67),0) -> 946960 | ... W49: =ROUND(ABS(淡江大學_p4!W67),0) -> 946960
B50: 淡江大學 | D50: =ROUND(ABS(淡江大學_p5!D67),0) -> 884660 | E50: =ROUND(ABS(淡江大學_p5!E67),0) -> 884660 | F50: =ROUND(ABS(淡江大學_p5!F67),0) -> 884660 | G50: =ROUND(ABS(淡江大學_p5!G67),0) -> 884660 | H50: =ROUND(ABS(淡江大學_p5!H67),0) -> 884660 | I50: =ROUND(ABS(淡江大學_p5!I67),0) -> 884660 | J50: =ROUND(ABS(淡江大學_p5!J67),0) -> 884660 | K50: =ROUND(ABS(淡江大學_p5!K67),0) -> 884660 | ... W50: =ROUND(ABS(淡江大學_p5!W67),0) -> 884660
C51: 設備折舊/年總計 | D51: =SUM(D48:D50) -> 2840880 | E51: =SUM(E48:E50) -> 2840880 | F51: =SUM(F48:F50) -> 2840880 | G51: =SUM(G48:G50) -> 2840880 | H51: =SUM(H48:H50) -> 2840880 | I51: =SUM(I48:I50) -> 2840880 | J51: =SUM(J48:J50) -> 2840880 | K51: =SUM(K48:K50) -> 2840880 | ... W51: =SUM(W48:W50) -> 2840880
B53: 貸款成數(%) | C53: 0.8
B54: 還款期數 | C54: 14
B55: 股利比率(%) | C55: 0.9
B56: 年底減資攤還期數 | C56: 4
B57: 銀行利率(%) | C57: 0.03
C58: 年份 | D58: 2020 | E58: 2021 | F58: 2022 | G58: 2023 | H58: 2024 | I58: 2025 | J58: 2026 | K58: 2027 | L58: 2028 | M58: 2029 | N58: 2030 | O58: 2031 | P58: 2032 | Q58: 2033 | R58: 2034 | S58: 2035 | T58: 2036 | U58: 2037 | V58: 2038 | W58: 2039
B59: 0
B60: (Unit : Currency) | C60: 0 | D60: 1 | E60: 2 | F60: 3 | G60: 4 | H60: 5 | I60: 6 | J60: 7 | K60: 8 | L60: 9 | M60: 10 | N60: 11 | O60: 12 | P60: 13 | Q60: 14 | R60: 15 | S60: 16 | T60: 17 | U60: 18 | V60: 19 | W60: 20
B61: 發電度數(KWH) | C61: 0 | D61: =D9 -> 1624596 | E61: =E9 -> 1618032 | F61: =F9 -> 1611468 | G61: =G9 -> 1604904 | H61: =H9 -> 1598340 | I61: =I9 -> 1591776 | J61: =J9 -> 1585212 | K61: =K9 -> 1578648 | ... W61: =W9 -> 1499880
B62: Inflow : 電費收入 | C62: - | D62: =D15 -> 6498384 | E62: =E15 -> 6472128 | F62: =F15 -> 6445872 | G62: =G15 -> 6419616 | H62: =H15 -> 6393360 | I62: =I15 -> 6367104 | J62: =J15 -> 6340848 | K62: =K15 -> 6314592 | ... W62: =W15 -> 5999517
B63: Inflow : 政府補助 | C63: - | G63: - | H63: - | I63: - | J63: - | K63: - | L63: - | M63: - | N63: - | O63: - | P63: - | Q63: - | R63: - | S63: - | T63: - | U63: - | V63: - | W63: -
B64: Inflow : 銀行借款
B65: Outflow : 設備費用 | C65: =-SUM(D51:W51) -> -56817600
B66: Outflow : 設備放置區域租金 | C66: - | D66: =-D21 -> -870603 | E66: =-E21 -> -870603 | F66: =-F21 -> -870603 | G66: =-G21 -> -870603 | H66: =-H21 -> -870603 | I66: =-I21 -> -870603 | J66: =-J21 -> -870603 | K66: =-K21 -> -870603 | ... W66: =-W21 -> -870603
B67: Outflow : 返還借款
B68: Outflow : 利息費用 | C68: -
B69: Outflow : 維運費 | C69: - | D69: =-D27 -> -523320 | E69: =-E27 -> -523320 | F69: =-F27 -> -523320 | G69: =-G27 -> -523320 | H69: =-H27 -> -523320 | I69: =-I27 -> -523320 | J69: =-J27 -> -523320 | K69: =-K27 -> -523320 | ... W69: =-W27 -> -523320
B70: Outflow : 保險費 | C70: - | D70: =-D33 -> -113265 | E70: =-E33 -> -113265 | F70: =-F33 -> -113265 | G70: =-G33 -> -113265 | H70: =-H33 -> -113265 | I70: =-I33 -> -113265 | J70: =-J33 -> -113265 | K70: =-K33 -> -113265 | ... W70: =-W33 -> -113265
B71: Outflow : 模組回收費 | D71: =-D39 -> -130830 | E71: =-E39 -> -130830 | F71: =-F39 -> -130830 | G71: =-G39 -> -130830 | H71: =-H39 -> -130830 | I71: =-I39 -> -130830 | J71: =-J39 -> -130830 | K71: =-K39 -> -130830 | ... W71: =-W39 -> 0
B72: Outflow : 其它費用(人事薪資…等)
B73: 1%管理費
B74: 績效獎金
B75: 所得稅20% | D75: =-D98 -> -131172.72 | E75: =-E98 -> -145401.84 | F75: =-F98 -> -159630.96 | G75: =-G98 -> -173860.08 | H75: =-H98 -> -188089.2 | I75: =-I98 -> -202318.32 | J75: =-J98 -> -216547.44 | K75: =-K98 -> -230776.56 | ... W75: =-W98 -> -330289.8
B76: 現金流 | C76: =C65 -> -56817600 | D76: =SUM(D62:D75) -> 4729193.3 | E76: =SUM(E62:E75) -> 4688708.2 | F76: =SUM(F62:F75) -> 4648223 | G76: =SUM(G62:G75) -> 4607737.9 | H76: =SUM(H62:H75) -> 4567252.8 | I76: =SUM(I62:I75) -> 4526767.7 | J76: =SUM(J62:J75) -> 4486282.6 | K76: =SUM(K62:K75) -> 4445797.4 | ... W76: =SUM(W62:W75) -> 4162039.2
B77: 累計現金流 | D77: =C55+D55 -> 0.9 | E77: =D56+E55 -> 0 | F77: =E56+F55 -> 0 | G77: =F56+G55 -> 0 | H77: =G56+H55 -> 0 | I77: =H56+I55 -> 0 | J77: =I56+J55 -> 0 | K77: =J56+K55 -> 0 | L77: =K56+L55 -> 0 | ... W77: =V56+W55 -> 0
B78: 回收年限評估 | D78: =IF((D56)>0,"回收","未回收") -> 未回收 | E78: =IF((E56)>0,"回收","未回收") -> 未回收 | F78: =IF((F56)>0,"回收","未回收") -> 未回收 | G78: =IF((G56)>0,"回收","未回收") -> 未回收 | H78: =IF((H56)>0,"回收","未回收") -> 未回收 | I78: =IF((I56)>0,"回收","未回收") -> 未回收 | J78: =IF((J56)>0,"回收","未回收") -> 未回收 | K78: =IF((K56)>0,"回收","未回收") -> 未回收 | ... W78: =IF((W56)>0,"回收","未回收") -> 未回收
B79: 專案法IRR | C79: =IRR(C76:W76) -> 0.047317711
C81: 年份 | D81: 2020 | E81: 2021 | F81: 2022 | G81: 2023 | H81: 2024 | I81: 2025 | J81: 2026 | K81: 2027 | L81: 2028 | M81: 2029 | N81: 2030 | O81: 2031 | P81: 2032 | Q81: 2033 | R81: 2034 | S81: 2035 | T81: 2036 | U81: 2037 | V81: 2038 | W81: 2039
B82: 0 | T82: 償還年限
B83: (Unit : Currency) | C83: 0 | D83: 1 | E83: 2 | F83: 3 | G83: 4 | H83: 5 | I83: 6 | J83: 7 | K83: 8 | L83: 9 | M83: 10 | N83: 11 | O83: 12 | P83: 13 | Q83: 14 | R83: 15 | S83: 16 | T83: 17 | U83: 18 | V83: 19 | W83: 20
B84: 發電度數(KWH) | C84: 0 | D84: =D9 -> 1624596 | E84: =E9 -> 1618032 | F84: =F9 -> 1611468 | G84: =G9 -> 1604904 | H84: =H9 -> 1598340 | I84: =I9 -> 1591776 | J84: =J9 -> 1585212 | K84: =K9 -> 1578648 | ... W84: =W9 -> 1499880
B85: Inflow : 電費收入 | C85: - | D85: =D15 -> 6498384 | E85: =E15 -> 6472128 | F85: =F15 -> 6445872 | G85: =G15 -> 6419616 | H85: =H15 -> 6393360 | I85: =I15 -> 6367104 | J85: =J15 -> 6340848 | K85: =K15 -> 6314592 | ... W85: =W15 -> 5999517
B86: Inflow : 政府補助 | C86: - | G86: - | H86: - | I86: - | J86: - | K86: - | L86: - | M86: - | N86: - | O86: - | P86: - | Q86: - | R86: - | S86: - | T86: - | U86: - | V86: - | W86: -
B87: Inflow : 銀行借款
B88: Outflow : 設備折舊 | D88: =-D51 -> -2840880 | E88: =-E51 -> -2840880 | F88: =-F51 -> -2840880 | G88: =-G51 -> -2840880 | H88: =-H51 -> -2840880 | I88: =-I51 -> -2840880 | J88: =-J51 -> -2840880 | K88: =-K51 -> -2840880 | ... W88: =-W51 -> -2840880
B89: Outflow : 設備放置區域租金 | C89: - | D89: =-D21 -> -870603 | E89: =-E21 -> -870603 | F89: =-F21 -> -870603 | G89: =-G21 -> -870603 | H89: =-H21 -> -870603 | I89: =-I21 -> -870603 | J89: =-J21 -> -870603 | K89: =-K21 -> -870603 | ... W89: =-W21 -> -870603
B90: Outflow : 返還借款
B91: Outflow : 利息費用 | C91: - | D91: =-D129*C57 -> -1363622.4 | E91: =-E129*C57 -> -1266220.8 | F91: =-F129*C57 -> -1168819.2 | G91: =-G129*C57 -> -1071417.6 | H91: =-H129*C57 -> -974016 | I91: =-I129*C57 -> -876614.4 | J91: =-J129*C57 -> -779212.8 | K91: =-K129*C57 -> -681811.2 | L91: =-L129*C57 -> -584409.6 | M91: =-M129*C57 -> -487008 | N91: =-N129*C57 -> -389606.4 | O91: =-O129*C57 -> -292204.8 | P91: =-P129*C57 -> -194803.2 | Q91: =-Q129*C57 -> -97401.6 | R91: =-R129*C57 -> 0 | S91: =-S129*C57 -> 0 | T91: =-T129*C57 -> 0 | U91: =-U129*C57 -> 0 | V91: =-V129*C57 -> 0 | W91: =-W129*C57 -> 0
B92: Outflow : 維運費 | C92: - | D92: =-D27 -> -523320 | E92: =-E27 -> -523320 | F92: =-F27 -> -523320 | G92: =-G27 -> -523320 | H92: =-H27 -> -523320 | I92: =-I27 -> -523320 | J92: =-J27 -> -523320 | K92: =-K27 -> -523320 | ... W92: =-W27 -> -523320
B93: Outflow : 保險費 | C93: - | D93: =-D33 -> -113265 | E93: =-E33 -> -113265 | F93: =-F33 -> -113265 | G93: =-G33 -> -113265 | H93: =-H33 -> -113265 | I93: =-I33 -> -113265 | J93: =-J33 -> -113265 | K93: =-K33 -> -113265 | ... W93: =-W33 -> -113265
B94: Outflow : 模組回收費 | D94: =-D39 -> -130830 | E94: =-E39 -> -130830 | F94: =-F39 -> -130830 | G94: =-G39 -> -130830 | H94: =-H39 -> -130830 | I94: =-I39 -> -130830 | J94: =-J39 -> -130830 | K94: =-K39 -> -130830 | ... W94: =-W39 -> 0
B95: Outflow : 其它費用(人事薪資…等)
B96: 1%管理費
B97: 稅前淨利 | D97: =SUM(D85:D96) -> 655863.6 | E97: =SUM(E85:E96) -> 727009.2 | F97: =SUM(F85:F96) -> 798154.8 | G97: =SUM(G85:G96) -> 869300.4 | H97: =SUM(H85:H96) -> 940446 | I97: =SUM(I85:I96) -> 1011591.6 | J97: =SUM(J85:J96) -> 1082737.2 | K97: =SUM(K85:K96) -> 1153882.8 | ... W97: =SUM(W85:W96) -> 1651449
B98: 所得稅20% | D98: =D97*0.2 -> 131172.72 | E98: =E97*0.2 -> 145401.84 | F98: =F97*0.2 -> 159630.96 | G98: =G97*0.2 -> 173860.08 | H98: =H97*0.2 -> 188089.2 | I98: =I97*0.2 -> 202318.32 | J98: =J97*0.2 -> 216547.44 | K98: =K97*0.2 -> 230776.56 | ... W98: =W97*0.2 -> 330289.8
B99: 稅後淨利 | D99: =D97-D98 -> 524690.88 | E99: =E97-E98 -> 581607.36 | F99: =F97-F98 -> 638523.84 | G99: =G97-G98 -> 695440.32 | H99: =H97-H98 -> 752356.8 | I99: =I97-I98 -> 809273.28 | J99: =J97-J98 -> 866189.76 | K99: =K97-K98 -> 923106.24 | ... W99: =W97-W98 -> 1321159.2
B100: 累計現金流
B101: 回收年限評估
C102: 年份 | D102: 2020 | E102: 2021 | F102: 2022 | G102: 2023 | H102: 2024 | I102: 2025 | J102: 2026 | K102: 2027 | L102: 2028 | M102: 2029 | N102: 2030 | O102: 2031 | P102: 2032 | Q102: 2033 | R102: 2034 | S102: 2035 | T102: 2036 | U102: 2037 | V102: 2038 | W102: 2039
B104: (Unit : Currency) | C104: 0 | D104: 1 | E104: 2 | F104: 3 | G104: 4 | H104: 5 | I104: 6 | J104: 7 | K104: 8 | L104: 9 | M104: 10 | N104: 11 | O104: 12 | P104: 13 | Q104: 14 | R104: 15 | S104: 16 | T104: 17 | U104: 18 | V104: 19 | W104: 20
B105: 稅後淨利 | D105: =D99 -> 524690.88 | E105: =E99 -> 581607.36 | F105: =F99 -> 638523.84 | G105: =G99 -> 695440.32 | H105: =H99 -> 752356.8 | I105: =I99 -> 809273.28 | J105: =J99 -> 866189.76 | K105: =K99 -> 923106.24 | ... W105: =W99 -> 1321159.2
B106: 設備折舊 | D106: =D51 -> 2840880 | E106: =E51 -> 2840880 | F106: =F51 -> 2840880 | G106: =G51 -> 2840880 | H106: =H51 -> 2840880 | I106: =I51 -> 2840880 | J106: =J51 -> 2840880 | K106: =K51 -> 2840880 | ... W106: =W51 -> 2840880
...

Sheet 淡江大學_p3
B1: 電站基本資料 | F1: 說明 | P1: =1-D11 -> 0.99 | Q1: =P1-$D12 -> 0.986 | R1: =Q1-$D12 -> 0.982 | S1: =R1-$D12 -> 0.978 | T1: =S1-$D12 -> 0.974 | U1: =T1-$D12 -> 0.97 | V1: =U1-$D12 -> 0.966 | W1: =V1-$D12 -> 0.962 | X1: =W1-$D12 -> 0.958 | ... AI1: =AH1-$D12 -> 0.914
B2: 電站名稱 | C2: 淡江大學 | D2: - | E2: - | F2: 填入本案場名稱
B3: 電站壽命 | C3: 20 | D3: - | E3: - | F3: 預設 20 年，代表財務評估年期。若合約年限不同可依實際情況修改
B4: 建置量(kWp) | C4: 436.1 | D4: - | E4: - | F4: 填入裝置容量（kWp），通常由設計圖面或報價書取得 | M4: 情境編號: 3
B5: 起始年度 | C5: 2020 | D5: 結束年度 | E5: 2039 | F5: 填入電站預計掛表的西元年份（例：2025）。結束年度會自動計算 | M5: 第2次滾算摘要
M6: 價金: 31000
B7: 綜合損益表 | M7: 專案IRR: 3.75
B8: 收入 | M8: 權益法IRR: 8.21
B9: 收支項目 | C9: 相關參數 | D9: 參數數值 | E9: 年限 | F9: 說明 | M9: 利潤率: 30.00%
B10: 電費收入 | C10: 年度AC併網總發電量 | D10: 547002 | E10: 20 | F10: 預估年發電量（kWh），通常來自 PVsyst 模擬或估算：裝置容量 × 年日照時數 × 系統效率 | M10: 第2次滾算，減少 2000 元 - 現金模式，每次減少 2000 元
C11: 首年衰退率 | D11: 0.01 | F11: 第一年發電衰退比率，請填小數（例：1% → 填 0.01）。一般首年衰退約 1~2%(請參考模組規格書)
C12: 次年衰退率 | D12: 0.004 | F12: 第二年起每年固定衰退比率，請填小數（例：0.4% → 填 0.004）。一般約 0.4~0.7%(請參考模組規格書)
C13: 躉售費率(FIT) / 綠電費率 | D13: 4 | F13: 與台電簽訂的躉購費率或綠電合約費率，單位：元/度。請參考台電公告或合約內容
B14: 支出
B15: 收支項目 | C15: 相關參數 | D15: 參數數值 | E15: 攤提年限 | F15: 說明
B16: 設備費用(價金) | C16: 每kWp設備成本 | D16: 31000 | E16: 20 | F16: 每峰瓩設備成本（元/kWp），包含模組、逆變器、支架等硬體，不含工程施工費
C17: 信邦利潤率(ex:20%填0.2) | D17: 0.3 | F17: 公司在設備費用上加計的利潤比率，請填小數（例：20% → 填 0.2）
C18: 開發費 | D18: 2000 | F18: 前期開發費用（元），含可行性評估、申請規費、地主溝通等。若無則填 0
B19: 租金費用 | C19: 租金計算方式 | D19: 1 | E19: 20 | F19: 填 1 = 固定年租金（需填方式1參數）；填 2 = 依電費收入抽成（需填方式2參數）
C20: 【方式1參數】每年相同價格 | D20: 290201 | E20: 20 | F20: 租金計算方式選「1」時填寫，固定年租金金額（元/年），套用至整個電站壽命期
C21: 【方式2參數】抽成比率 | D21: 0 | E21: 20 | F21: 租金計算方式選「2」時填寫，請填小數（例：10% → 填 0.1）。租金 = 當年電費收入 × 抽成比率
B22: 運維費用 | C22: 每kw運維成本 | D22: 400 | E22: 20 | F22: 每峰瓩每年運維費用（元/kWp/年），含清洗、巡檢、維修等。
B23: 保險費用 | C23: 占整體設備費用比例 | D23: 0.003 | E23: 20 | F23: 保險費佔設備總費用比率，填小數（例：0.3% → 填 0.003）。預設 0.003，可依投保條件調整
B24: 模組回收費用 | C24: 每kw模組回收成本 | D24: 1000 | E24: 10 | F24: 每峰瓩模組廢棄回收費用（元/kWp），於第 1~10 年計提（攤提 10 年）。
B25: 利息費用 | C25: 銀行利率 | D25: 0.0256 | E25: 20 | F25: 向銀行貸款的年利率，填小數（例：2.56% → 填 0.0256）。請依銀行核准利率填入
B26: 所得稅 | C26: 所得稅率 | D26: 0.2 | E26: 20 | F26: 公司所得稅率，填小數（例：20% → 填 0.2）。預設 0.2，通常不需更改
B29: 現金流量表
B30: 金流項目 | C30: 相關參數 | D30: 參數數值 | F30: 說明
B31: 貸款成數 | C31: 占總設備費用比例 | D31: 0.8 | F31: 貸款佔設備總費用比例，填小數（例：80% → 填 0.8）。預設 0.8 代表貸八成、自備二成
B32: 貸款還款 | C32: 攤還期數 | D32: 15 | F32: 貸款還款年數（年）。預設 15 年，代表分 15 年平均攤還本金
B33: 現金股利 | C33: 股利比率 | D33: 0.9 | F33: 稅後現金流中分配給股東的比例，填小數（例：90% → 填 0.9）
B34: 年底減資 | C34: 攤還期數 | D34: 4 | F34: 年底減資返還股東的年數。預設 4 年，代表 倒數 4 年進行減資，加速資金返還
C37: 年份 | D37: 2020 | E37: 2021 | F37: 2022 | G37: 2023 | H37: 2024 | I37: 2025 | J37: 2026 | K37: 2027 | L37: 2028 | M37: 2029 | N37: 2030 | O37: 2031 | P37: 2032 | Q37: 2033 | R37: 2034 | S37: 2035 | T37: 2036 | U37: 2037 | V37: 2038 | W37: 2039
B38: 0
B39: (Unit : Currency) | C39: 0 | D39: 1 | E39: 2 | F39: 3 | G39: 4 | H39: 5 | I39: 6 | J39: 7 | K39: 8 | L39: 9 | M39: 10 | N39: 11 | O39: 12 | P39: 13 | Q39: 14 | R39: 15 | S39: 16 | T39: 17 | U39: 18 | V39: 19 | W39: 20
B40: 發電度數(KWH) | C40: 0 | D40: =$D$10*P1 -> 541531.98 | E40: =$D$10*Q1 -> 539343.97 | F40: =$D$10*R1 -> 537155.96 | G40: =$D$10*S1 -> 534967.96 | H40: =$D$10*T1 -> 532779.95 | I40: =$D$10*U1 -> 530591.94 | J40: =$D$10*V1 -> 528403.93 | K40: =$D$10*W1 -> 526215.92 | ... W40: =$D$10*AI1 -> 499959.83
B41: Inflow : 電費收入 | C41: - | D41: =D40*$D$13 -> 2166127.9 | E41: =E40*$D$13 -> 2157375.9 | F41: =F40*$D$13 -> 2148623.9 | G41: =G40*$D$13 -> 2139871.8 | H41: =H40*$D$13 -> 2131119.8 | I41: =I40*$D$13 -> 2122367.8 | J41: =J40*$D$13 -> 2113615.7 | K41: =K40*$D$13 -> 2104863.7 | ... W41: =W40*$D$13 -> 1999839.3
B42: Inflow : 政府補助 | C42: - | G42: - | H42: - | I42: - | J42: - | K42: - | L42: - | M42: - | N42: - | O42: - | P42: - | Q42: - | R42: - | S42: - | T42: - | U42: - | V42: - | W42: -
B43: Inflow : 銀行借款
B44: Outflow : 設備費用 | C44: =-(D16/(1-D17)+D18)*C4 -> -20185200
B45: Outflow : 設備放置區域租金 | C45: - | D45: -290201 | E45: -290201 | F45: -290201 | G45: -290201 | H45: -290201 | I45: -290201 | J45: -290201 | K45: -290201 | L45: -290201 | M45: -290201 | N45: -290201 | O45: -290201 | P45: -290201 | Q45: -290201 | R45: -290201 | S45: -290201 | T45: -290201 | U45: -290201 | V45: -290201 | W45: -290201
B46: Outflow : 返還借款
B47: Outflow : 利息費用 | C47: -
B48: Outflow : 維運費 | C48: - | D48: -174440 | E48: -174440 | F48: -174440 | G48: -174440 | H48: -174440 | I48: -174440 | J48: -174440 | K48: -174440 | L48: -174440 | M48: -174440 | N48: -174440 | O48: -174440 | P48: -174440 | Q48: -174440 | R48: -174440 | S48: -174440 | T48: -174440 | U48: -174440 | V48: -174440 | W48: -174440
B49: Outflow : 保險費 | C49: - | D49: -40000 | E49: -40000 | F49: -40000 | G49: -40000 | H49: -40000 | I49: -40000 | J49: -40000 | K49: -40000 | L49: -40000 | M49: -40000 | N49: -40000 | O49: -40000 | P49: -40000 | Q49: -40000 | R49: -40000 | S49: -40000 | T49: -40000 | U49: -40000 | V49: -40000 | W49: -40000
B50: Outflow : 模組回收費 | D50: -43610 | E50: -43610 | F50: -43610 | G50: -43610 | H50: -43610 | I50: -43610 | J50: -43610 | K50: -43610 | L50: -43610 | M50: -43610 | N50: 0 | O50: 0 | P50: 0 | Q50: 0 | R50: 0 | S50: 0 | T50: 0 | U50: 0 | V50: 0 | W50: 0
B51: Outflow : 其它費用(人事薪資…等)
B52: 1%管理費
B53: 績效獎金
B54: 所得稅20% | D54: =D77 -> -179763.58 | E54: =E77 -> -119972.98 | F54: =F77 -> -118222.57 | G54: =G77 -> -116472.16 | H54: =H77 -> -114721.76 | I54: =I77 -> -112971.35 | J54: =J77 -> -111220.95 | K54: =K77 -> -109470.54 | ... W54: =W77 -> -97187.662
B55: 現金流 | C55: =C44 -> -20185200 | D55: =SUM(D41:D54) -> 1438113.3 | E55: =SUM(E41:E54) -> 1489151.9 | F55: =SUM(F41:F54) -> 1482150.3 | G55: =SUM(G41:G54) -> 1475148.7 | H55: =SUM(H41:H54) -> 1468147 | I55: =SUM(I41:I54) -> 1461145.4 | J55: =SUM(J41:J54) -> 1454143.8 | K55: =SUM(K41:K54) -> 1447142.2 | ... W55: =SUM(W41:W54) -> 1398010.6
B56: 累計現金流 | D56: =C55+D55 -> -18747087 | E56: =D56+E55 -> -17257935 | F56: =E56+F55 -> -15775784 | G56: =F56+G55 -> -14300636 | H56: =G56+H55 -> -12832489 | I56: =H56+I55 -> -11371343 | J56: =I56+J55 -> -9917199.6 | K56: =J56+K55 -> -8470057.4 | L56: =K56+L55 -> -7029916.9 | ... X56: =W56+X55 -> 8698401.7
B57: 回收年限評估 | D57: =IF((D56)>0,"回收","未回收") -> 未回收 | E57: =IF((E56)>0,"回收","未回收") -> 未回收 | F57: =IF((F56)>0,"回收","未回收") -> 未回收 | G57: =IF((G56)>0,"回收","未回收") -> 未回收 | H57: =IF((H56)>0,"回收","未回收") -> 未回收 | I57: =IF((I56)>0,"回收","未回收") -> 未回收 | J57: =IF((J56)>0,"回收","未回收") -> 未回收 | K57: =IF((K56)>0,"回收","未回收") -> 未回收 | ... X57: =IF((X56)>0,"回收","未回收") -> 回收
B58: 專案法IRR | C58: =IRR(C55:W55) -> 0.037174543
C60: 年份 | D60: =D37 -> 2020 | E60: =E37 -> 2021 | F60: =F37 -> 2022 | G60: =G37 -> 2023 | H60: =H37 -> 2024 | I60: =I37 -> 2025 | J60: =J37 -> 2026 | K60: =K37 -> 2027 | ... W60: =W37 -> 2039
B61: 0 | T61: 償還年限
B62: (Unit : Currency) | C62: 0 | D62: 1 | E62: 2 | F62: 3 | G62: 4 | H62: 5 | I62: 6 | J62: 7 | K62: 8 | L62: 9 | M62: 10 | N62: 11 | O62: 12 | P62: 13 | Q62: 14 | R62: 15 | S62: 16 | T62: 17 | U62: 18 | V62: 19 | W62: 20
B63: 發電度數(KWH) | C63: 0 | D63: =D40 -> 541531.98 | E63: =E40 -> 539343.97 | F63: =F40 -> 537155.96 | G63: =G40 -> 534967.96 | H63: =H40 -> 532779.95 | I63: =I40 -> 530591.94 | J63: =J40 -> 528403.93 | K63: =K40 -> 526215.92 | ... W63: =W40 -> 499959.83
B64: Inflow : 電費收入 | C64: - | D64: =D41 -> 2166127.9 | E64: =E41 -> 2157375.9 | F64: =F41 -> 2148623.9 | G64: =G41 -> 2139871.8 | H64: =H41 -> 2131119.8 | I64: =I41 -> 2122367.8 | J64: =J41 -> 2113615.7 | K64: =K41 -> 2104863.7 | ... W64: =W41 -> 1999839.3
B65: Inflow : 政府補助 | C65: - | G65: - | H65: - | I65: - | J65: - | K65: - | L65: - | M65: - | N65: - | O65: - | P65: - | Q65: - | R65: - | S65: - | T65: - | U65: - | V65: - | W65: -
B66: Inflow : 銀行借款
B67: Outflow : 設備折舊 | D67: =$C$44/$E$16 -> -1009260 | E67: =$C$44/$E$16 -> -1009260 | F67: =$C$44/$E$16 -> -1009260 | G67: =$C$44/$E$16 -> -1009260 | H67: =$C$44/$E$16 -> -1009260 | I67: =$C$44/$E$16 -> -1009260 | J67: =$C$44/$E$16 -> -1009260 | K67: =$C$44/$E$16 -> -1009260 | ... W67: =$C$44/$E$16 -> -1009260
B68: Outflow : 設備放置區域租金 | C68: - | D68: =D44 -> 0 | E68: =E45 -> -290201 | F68: =F45 -> -290201 | G68: =G45 -> -290201 | H68: =H45 -> -290201 | I68: =I45 -> -290201 | J68: =J45 -> -290201 | K68: =K45 -> -290201 | L68: =L45 -> -290201 | ... W68: =W45 -> -290201
B69: Outflow : 返還借款
B70: Outflow : 利息費用 | C70: - | D70: 0 | E70: 0 | F70: 0 | G70: 0 | H70: 0 | I70: 0 | J70: 0 | K70: 0 | L70: 0 | M70: 0 | N70: 0 | O70: 0 | P70: 0 | Q70: 0 | R70: 0 | S70: 0 | T70: 0 | U70: 0 | V70: 0 | W70: 0
B71: Outflow : 維運費 | C71: - | D71: =D48 -> -174440 | E71: =E48 -> -174440 | F71: =F48 -> -174440 | G71: =G48 -> -174440 | H71: =H48 -> -174440 | I71: =I48 -> -174440 | J71: =J48 -> -174440 | K71: =K48 -> -174440 | ... W71: =W48 -> -174440
B72: Outflow : 保險費 | C72: - | D72: =D49 -> -40000 | E72: =E49 -> -40000 | F72: =F49 -> -40000 | G72: =G49 -> -40000 | H72: =H49 -> -40000 | I72: =I49 -> -40000 | J72: =J49 -> -40000 | K72: =K49 -> -40000 | ... W72: =W49 -> -40000
B73: Outflow : 模組回收費 | D73: =D50 -> -43610 | E73: =E50 -> -43610 | F73: =F50 -> -43610 | G73: =G50 -> -43610 | H73: =H50 -> -43610 | I73: =I50 -> -43610 | J73: =J50 -> -43610 | K73: =K50 -> -43610 | ... W73: =W50 -> 0
B74: Outflow : 其它費用(人事薪資…等)
B75: 1%管理費
B76: 稅前淨利 | D76: =SUM(D64:D75) -> 898817.92 | E76: =SUM(E64:E75) -> 599864.89 | F76: =SUM(F64:F75) -> 591112.86 | G76: =SUM(G64:G75) -> 582360.82 | H76: =SUM(H64:H75) -> 573608.79 | I76: =SUM(I64:I75) -> 564856.76 | J76: =SUM(J64:J75) -> 556104.73 | K76: =SUM(K64:K75) -> 547352.7 | ... X76: =SUM(X64:X75) -> 0
B77: 所得稅20% | D77: =-D76*0.2 -> -179763.58 | E77: =-E76*0.2 -> -119972.98 | F77: =-F76*0.2 -> -118222.57 | G77: =-G76*0.2 -> -116472.16 | H77: =-H76*0.2 -> -114721.76 | I77: =-I76*0.2 -> -112971.35 | J77: =-J76*0.2 -> -111220.95 | K77: =-K76*0.2 -> -109470.54 | ... X77: =-X76*0.2 -> 0
B78: 稅後淨利 | D78: =SUM(D76:D77) -> 719054.34 | E78: =SUM(E76:E77) -> 479891.91 | F78: =SUM(F76:F77) -> 472890.28 | G78: =SUM(G76:G77) -> 465888.66 | H78: =SUM(H76:H77) -> 458887.03 | I78: =SUM(I76:I77) -> 451885.41 | J78: =SUM(J76:J77) -> 444883.78 | K78: =SUM(K76:K77) -> 437882.16 | ... X78: =SUM(X76:X77) -> 0
B79: 累計現金流
B80: 回收年限評估

Sheet 淡江大學_p4
B1: 電站基本資料 | F1: 說明 | P1: =1-D11 -> 0.99 | Q1: =P1-$D12 -> 0.986 | R1: =Q1-$D12 -> 0.982 | S1: =R1-$D12 -> 0.978 | T1: =S1-$D12 -> 0.974 | U1: =T1-$D12 -> 0.97 | V1: =U1-$D12 -> 0.966 | W1: =V1-$D12 -> 0.962 | X1: =W1-$D12 -> 0.958 | ... AI1: =AH1-$D12 -> 0.914
B2: 電站名稱 | C2: 淡江大學 | D2: - | E2: - | F2: 填入本案場名稱
B3: 電站壽命 | C3: 20 | D3: - | E3: - | F3: 預設 20 年，代表財務評估年期。若合約年限不同可依實際情況修改
B4: 建置量(kWp) | C4: 436.1 | D4: - | E4: - | F4: 填入裝置容量（kWp），通常由設計圖面或報價書取得 | M4: 情境編號: 4
B5: 起始年度 | C5: 2020 | D5: 結束年度 | E5: 2039 | F5: 填入電站預計掛表的西元年份（例：2025）。結束年度會自動計算 | M5: 第3次滾算摘要
M6: 價金: 29000
B7: 綜合損益表 | M7: 專案IRR: 4.39
B8: 收入 | M8: 權益法IRR: 10.59
B9: 收支項目 | C9: 相關參數 | D9: 參數數值 | E9: 年限 | F9: 說明 | M9: 利潤率: 30.00%
B10: 電費收入 | C10: 年度AC併網總發電量 | D10: 547002 | E10: 20 | F10: 預估年發電量（kWh），通常來自 PVsyst 模擬或估算：裝置容量 × 年日照時數 × 系統效率 | M10: 第3次滾算，減少 2000 元 - 現金模式，每次減少 2000 元
C11: 首年衰退率 | D11: 0.01 | F11: 第一年發電衰退比率，請填小數（例：1% → 填 0.01）。一般首年衰退約 1~2%(請參考模組規格書)
C12: 次年衰退率 | D12: 0.004 | F12: 第二年起每年固定衰退比率，請填小數（例：0.4% → 填 0.004）。一般約 0.4~0.7%(請參考模組規格書)
C13: 躉售費率(FIT) / 綠電費率 | D13: 4 | F13: 與台電簽訂的躉購費率或綠電合約費率，單位：元/度。請參考台電公告或合約內容
B14: 支出
B15: 收支項目 | C15: 相關參數 | D15: 參數數值 | E15: 攤提年限 | F15: 說明
B16: 設備費用(價金) | C16: 每kWp設備成本 | D16: 29000 | E16: 20 | F16: 每峰瓩設備成本（元/kWp），包含模組、逆變器、支架等硬體，不含工程施工費
C17: 信邦利潤率(ex:20%填0.2) | D17: 0.3 | F17: 公司在設備費用上加計的利潤比率，請填小數（例：20% → 填 0.2）
C18: 開發費 | D18: 2000 | F18: 前期開發費用（元），含可行性評估、申請規費、地主溝通等。若無則填 0
B19: 租金費用 | C19: 租金計算方式 | D19: 1 | E19: 20 | F19: 填 1 = 固定年租金（需填方式1參數）；填 2 = 依電費收入抽成（需填方式2參數）
C20: 【方式1參數】每年相同價格 | D20: 290201 | E20: 20 | F20: 租金計算方式選「1」時填寫，固定年租金金額（元/年），套用至整個電站壽命期
C21: 【方式2參數】抽成比率 | D21: 0 | E21: 20 | F21: 租金計算方式選「2」時填寫，請填小數（例：10% → 填 0.1）。租金 = 當年電費收入 × 抽成比率
B22: 運維費用 | C22: 每kw運維成本 | D22: 400 | E22: 20 | F22: 每峰瓩每年運維費用（元/kWp/年），含清洗、巡檢、維修等。
B23: 保險費用 | C23: 占整體設備費用比例 | D23: 0.003 | E23: 20 | F23: 保險費佔設備總費用比率，填小數（例：0.3% → 填 0.003）。預設 0.003，可依投保條件調整
B24: 模組回收費用 | C24: 每kw模組回收成本 | D24: 1000 | E24: 10 | F24: 每峰瓩模組廢棄回收費用（元/kWp），於第 1~10 年計提（攤提 10 年）。
B25: 利息費用 | C25: 銀行利率 | D25: 0.0256 | E25: 20 | F25: 向銀行貸款的年利率，填小數（例：2.56% → 填 0.0256）。請依銀行核准利率填入
B26: 所得稅 | C26: 所得稅率 | D26: 0.2 | E26: 20 | F26: 公司所得稅率，填小數（例：20% → 填 0.2）。預設 0.2，通常不需更改
B29: 現金流量表
B30: 金流項目 | C30: 相關參數 | D30: 參數數值 | F30: 說明
B31: 貸款成數 | C31: 占總設備費用比例 | D31: 0.8 | F31: 貸款佔設備總費用比例，填小數（例：80% → 填 0.8）。預設 0.8 代表貸八成、自備二成
B32: 貸款還款 | C32: 攤還期數 | D32: 15 | F32: 貸款還款年數（年）。預設 15 年，代表分 15 年平均攤還本金
B33: 現金股利 | C33: 股利比率 | D33: 0.9 | F33: 稅後現金流中分配給股東的比例，填小數（例：90% → 填 0.9）
B34: 年底減資 | C34: 攤還期數 | D34: 4 | F34: 年底減資返還股東的年數。預設 4 年，代表 倒數 4 年進行減資，加速資金返還
C37: 年份 | D37: 2020 | E37: 2021 | F37: 2022 | G37: 2023 | H37: 2024 | I37: 2025 | J37: 2026 | K37: 2027 | L37: 2028 | M37: 2029 | N37: 2030 | O37: 2031 | P37: 2032 | Q37: 2033 | R37: 2034 | S37: 2035 | T37: 2036 | U37: 2037 | V37: 2038 | W37: 2039
B38: 0
B39: (Unit : Currency) | C39: 0 | D39: 1 | E39: 2 | F39: 3 | G39: 4 | H39: 5 | I39: 6 | J39: 7 | K39: 8 | L39: 9 | M39: 10 | N39: 11 | O39: 12 | P39: 13 | Q39: 14 | R39: 15 | S39: 16 | T39: 17 | U39: 18 | V39: 19 | W39: 20
B40: 發電度數(KWH) | C40: 0 | D40: =$D$10*P1 -> 541531.98 | E40: =$D$10*Q1 -> 539343.97 | F40: =$D$10*R1 -> 537155.96 | G40: =$D$10*S1 -> 534967.96 | H40: =$D$10*T1 -> 532779.95 | I40: =$D$10*U1 -> 530591.94 | J40: =$D$10*V1 -> 528403.93 | K40: =$D$10*W1 -> 526215.92 | ... W40: =$D$10*AI1 -> 499959.83
B41: Inflow : 電費收入 | C41: - | D41: =D40*$D$13 -> 2166127.9 | E41: =E40*$D$13 -> 2157375.9 | F41: =F40*$D$13 -> 2148623.9 | G41: =G40*$D$13 -> 2139871.8 | H41: =H40*$D$13 -> 2131119.8 | I41: =I40*$D$13 -> 2122367.8 | J41: =J40*$D$13 -> 2113615.7 | K41: =K40*$D$13 -> 2104863.7 | ... W41: =W40*$D$13 -> 1999839.3
B42: Inflow : 政府補助 | C42: - | G42: - | H42: - | I42: - | J42: - | K42: - | L42: - | M42: - | N42: - | O42: - | P42: - | Q42: - | R42: - | S42: - | T42: - | U42: - | V42: - | W42: -
B43: Inflow : 銀行借款
B44: Outflow : 設備費用 | C44: =-(D16/(1-D17)+D18)*C4 -> -18939200
B45: Outflow : 設備放置區域租金 | C45: - | D45: -290201 | E45: -290201 | F45: -290201 | G45: -290201 | H45: -290201 | I45: -290201 | J45: -290201 | K45: -290201 | L45: -290201 | M45: -290201 | N45: -290201 | O45: -290201 | P45: -290201 | Q45: -290201 | R45: -290201 | S45: -290201 | T45: -290201 | U45: -290201 | V45: -290201 | W45: -290201
B46: Outflow : 返還借款
B47: Outflow : 利息費用 | C47: -
B48: Outflow : 維運費 | C48: - | D48: -174440 | E48: -174440 | F48: -174440 | G48: -174440 | H48: -174440 | I48: -174440 | J48: -174440 | K48: -174440 | L48: -174440 | M48: -174440 | N48: -174440 | O48: -174440 | P48: -174440 | Q48: -174440 | R48: -174440 | S48: -174440 | T48: -174440 | U48: -174440 | V48: -174440 | W48: -174440
B49: Outflow : 保險費 | C49: - | D49: -37940.7 | E49: -37940.7 | F49: -37940.7 | G49: -37940.7 | H49: -37940.7 | I49: -37940.7 | J49: -37940.7 | K49: -37940.7 | L49: -37940.7 | M49: -37940.7 | N49: -37940.7 | O49: -37940.7 | P49: -37940.7 | Q49: -37940.7 | R49: -37940.7 | S49: -37940.7 | T49: -37940.7 | U49: -37940.7 | V49: -37940.7 | W49: -37940.7
B50: Outflow : 模組回收費 | D50: -43610 | E50: -43610 | F50: -43610 | G50: -43610 | H50: -43610 | I50: -43610 | J50: -43610 | K50: -43610 | L50: -43610 | M50: -43610 | N50: 0 | O50: 0 | P50: 0 | Q50: 0 | R50: 0 | S50: 0 | T50: 0 | U50: 0 | V50: 0 | W50: 0
B51: Outflow : 其它費用(人事薪資…等)
B52: 1%管理費
B53: 績效獎金
B54: 所得稅20% | D54: =D77 -> -192635.44 | E54: =E77 -> -132844.84 | F54: =F77 -> -131094.43 | G54: =G77 -> -129344.02 | H54: =H77 -> -127593.62 | I54: =I77 -> -125843.21 | J54: =J77 -> -124092.81 | K54: =K77 -> -122342.4 | ... W54: =W77 -> -110059.52
B55: 現金流 | C55: =C44 -> -18939200 | D55: =SUM(D41:D54) -> 1427300.8 | E55: =SUM(E41:E54) -> 1478339.4 | F55: =SUM(F41:F54) -> 1471337.7 | G55: =SUM(G41:G54) -> 1464336.1 | H55: =SUM(H41:H54) -> 1457334.5 | I55: =SUM(I41:I54) -> 1450332.8 | J55: =SUM(J41:J54) -> 1443331.2 | K55: =SUM(K41:K54) -> 1436329.6 | ... W55: =SUM(W41:W54) -> 1387198.1
B56: 累計現金流 | D56: =C55+D55 -> -17511899 | E56: =D56+E55 -> -16033560 | F56: =E56+F55 -> -14562222 | G56: =F56+G55 -> -13097886 | H56: =G56+H55 -> -11640552 | I56: =H56+I55 -> -10190219 | J56: =I56+J55 -> -8746887.5 | K56: =J56+K55 -> -7310557.9 | L56: =K56+L55 -> -5881229.9 | ... X56: =W56+X55 -> 9728150.5
B57: 回收年限評估 | D57: =IF((D56)>0,"回收","未回收") -> 未回收 | E57: =IF((E56)>0,"回收","未回收") -> 未回收 | F57: =IF((F56)>0,"回收","未回收") -> 未回收 | G57: =IF((G56)>0,"回收","未回收") -> 未回收 | H57: =IF((H56)>0,"回收","未回收") -> 未回收 | I57: =IF((I56)>0,"回收","未回收") -> 未回收 | J57: =IF((J56)>0,"回收","未回收") -> 未回收 | K57: =IF((K56)>0,"回收","未回收") -> 未回收 | ... X57: =IF((X56)>0,"回收","未回收") -> 回收
B58: 專案法IRR | C58: =IRR(C55:W55) -> 0.043586467
C60: 年份 | D60: =D37 -> 2020 | E60: =E37 -> 2021 | F60: =F37 -> 2022 | G60: =G37 -> 2023 | H60: =H37 -> 2024 | I60: =I37 -> 2025 | J60: =J37 -> 2026 | K60: =K37 -> 2027 | ... W60: =W37 -> 2039
B61: 0 | T61: 償還年限
B62: (Unit : Currency) | C62: 0 | D62: 1 | E62: 2 | F62: 3 | G62: 4 | H62: 5 | I62: 6 | J62: 7 | K62: 8 | L62: 9 | M62: 10 | N62: 11 | O62: 12 | P62: 13 | Q62: 14 | R62: 15 | S62: 16 | T62: 17 | U62: 18 | V62: 19 | W62: 20
B63: 發電度數(KWH) | C63: 0 | D63: =D40 -> 541531.98 | E63: =E40 -> 539343.97 | F63: =F40 -> 537155.96 | G63: =G40 -> 534967.96 | H63: =H40 -> 532779.95 | I63: =I40 -> 530591.94 | J63: =J40 -> 528403.93 | K63: =K40 -> 526215.92 | ... W63: =W40 -> 499959.83
B64: Inflow : 電費收入 | C64: - | D64: =D41 -> 2166127.9 | E64: =E41 -> 2157375.9 | F64: =F41 -> 2148623.9 | G64: =G41 -> 2139871.8 | H64: =H41 -> 2131119.8 | I64: =I41 -> 2122367.8 | J64: =J41 -> 2113615.7 | K64: =K41 -> 2104863.7 | ... W64: =W41 -> 1999839.3
B65: Inflow : 政府補助 | C65: - | G65: - | H65: - | I65: - | J65: - | K65: - | L65: - | M65: - | N65: - | O65: - | P65: - | Q65: - | R65: - | S65: - | T65: - | U65: - | V65: - | W65: -
B66: Inflow : 銀行借款
B67: Outflow : 設備折舊 | D67: =$C$44/$E$16 -> -946960 | E67: =$C$44/$E$16 -> -946960 | F67: =$C$44/$E$16 -> -946960 | G67: =$C$44/$E$16 -> -946960 | H67: =$C$44/$E$16 -> -946960 | I67: =$C$44/$E$16 -> -946960 | J67: =$C$44/$E$16 -> -946960 | K67: =$C$44/$E$16 -> -946960 | ... W67: =$C$44/$E$16 -> -946960
B68: Outflow : 設備放置區域租金 | C68: - | D68: =D44 -> 0 | E68: =E45 -> -290201 | F68: =F45 -> -290201 | G68: =G45 -> -290201 | H68: =H45 -> -290201 | I68: =I45 -> -290201 | J68: =J45 -> -290201 | K68: =K45 -> -290201 | L68: =L45 -> -290201 | ... W68: =W45 -> -290201
B69: Outflow : 返還借款
B70: Outflow : 利息費用 | C70: - | D70: 0 | E70: 0 | F70: 0 | G70: 0 | H70: 0 | I70: 0 | J70: 0 | K70: 0 | L70: 0 | M70: 0 | N70: 0 | O70: 0 | P70: 0 | Q70: 0 | R70: 0 | S70: 0 | T70: 0 | U70: 0 | V70: 0 | W70: 0
B71: Outflow : 維運費 | C71: - | D71: =D48 -> -174440 | E71: =E48 -> -174440 | F71: =F48 -> -174440 | G71: =G48 -> -174440 | H71: =H48 -> -174440 | I71: =I48 -> -174440 | J71: =J48 -> -174440 | K71: =K48 -> -174440 | ... W71: =W48 -> -174440
B72: Outflow : 保險費 | C72: - | D72: =D49 -> -37940.7 | E72: =E49 -> -37940.7 | F72: =F49 -> -37940.7 | G72: =G49 -> -37940.7 | H72: =H49 -> -37940.7 | I72: =I49 -> -37940.7 | J72: =J49 -> -37940.7 | K72: =K49 -> -37940.7 | ... W72: =W49 -> -37940.7
B73: Outflow : 模組回收費 | D73: =D50 -> -43610 | E73: =E50 -> -43610 | F73: =F50 -> -43610 | G73: =G50 -> -43610 | H73: =H50 -> -43610 | I73: =I50 -> -43610 | J73: =J50 -> -43610 | K73: =K50 -> -43610 | ... W73: =W50 -> 0
B74: Outflow : 其它費用(人事薪資…等)
B75: 1%管理費
B76: 稅前淨利 | D76: =SUM(D64:D75) -> 963177.22 | E76: =SUM(E64:E75) -> 664224.19 | F76: =SUM(F64:F75) -> 655472.16 | G76: =SUM(G64:G75) -> 646720.12 | H76: =SUM(H64:H75) -> 637968.09 | I76: =SUM(I64:I75) -> 629216.06 | J76: =SUM(J64:J75) -> 620464.03 | K76: =SUM(K64:K75) -> 611712 | ... X76: =SUM(X64:X75) -> 0
B77: 所得稅20% | D77: =-D76*0.2 -> -192635.44 | E77: =-E76*0.2 -> -132844.84 | F77: =-F76*0.2 -> -131094.43 | G77: =-G76*0.2 -> -129344.02 | H77: =-H76*0.2 -> -127593.62 | I77: =-I76*0.2 -> -125843.21 | J77: =-J76*0.2 -> -124092.81 | K77: =-K76*0.2 -> -122342.4 | ... X77: =-X76*0.2 -> 0
B78: 稅後淨利 | D78: =SUM(D76:D77) -> 770541.78 | E78: =SUM(E76:E77) -> 531379.35 | F78: =SUM(F76:F77) -> 524377.72 | G78: =SUM(G76:G77) -> 517376.1 | H78: =SUM(H76:H77) -> 510374.47 | I78: =SUM(I76:I77) -> 503372.85 | J78: =SUM(J76:J77) -> 496371.22 | K78: =SUM(K76:K77) -> 489369.6 | ... X78: =SUM(X76:X77) -> 0
B79: 累計現金流
B80: 回收年限評估

Sheet 淡江大學_p5
B1: 電站基本資料 | F1: 說明 | P1: =1-D11 -> 0.99 | Q1: =P1-$D12 -> 0.986 | R1: =Q1-$D12 -> 0.982 | S1: =R1-$D12 -> 0.978 | T1: =S1-$D12 -> 0.974 | U1: =T1-$D12 -> 0.97 | V1: =U1-$D12 -> 0.966 | W1: =V1-$D12 -> 0.962 | X1: =W1-$D12 -> 0.958 | ... AI1: =AH1-$D12 -> 0.914
B2: 電站名稱 | C2: 淡江大學 | D2: - | E2: - | F2: 填入本案場名稱
B3: 電站壽命 | C3: 20 | D3: - | E3: - | F3: 預設 20 年，代表財務評估年期。若合約年限不同可依實際情況修改
B4: 建置量(kWp) | C4: 436.1 | D4: - | E4: - | F4: 填入裝置容量（kWp），通常由設計圖面或報價書取得 | M4: 情境編號: 5
B5: 起始年度 | C5: 2020 | D5: 結束年度 | E5: 2039 | F5: 填入電站預計掛表的西元年份（例：2025）。結束年度會自動計算 | M5: 第4次滾算摘要
M6: 價金: 27000
B7: 綜合損益表 | M7: 專案IRR: 5.11
B8: 收入 | M8: 權益法IRR: 13.45
B9: 收支項目 | C9: 相關參數 | D9: 參數數值 | E9: 年限 | F9: 說明 | M9: 利潤率: 30.00%
B10: 電費收入 | C10: 年度AC併網總發電量 | D10: 547002 | E10: 20 | F10: 預估年發電量（kWh），通常來自 PVsyst 模擬或估算：裝置容量 × 年日照時數 × 系統效率 | M10: 第4次滾算，減少 2000 元 - 現金模式，每次減少 2000 元
C11: 首年衰退率 | D11: 0.01 | F11: 第一年發電衰退比率，請填小數（例：1% → 填 0.01）。一般首年衰退約 1~2%(請參考模組規格書)
C12: 次年衰退率 | D12: 0.004 | F12: 第二年起每年固定衰退比率，請填小數（例：0.4% → 填 0.004）。一般約 0.4~0.7%(請參考模組規格書)
C13: 躉售費率(FIT) / 綠電費率 | D13: 4 | F13: 與台電簽訂的躉購費率或綠電合約費率，單位：元/度。請參考台電公告或合約內容
B14: 支出
B15: 收支項目 | C15: 相關參數 | D15: 參數數值 | E15: 攤提年限 | F15: 說明
B16: 設備費用(價金) | C16: 每kWp設備成本 | D16: 27000 | E16: 20 | F16: 每峰瓩設備成本（元/kWp），包含模組、逆變器、支架等硬體，不含工程施工費
C17: 信邦利潤率(ex:20%填0.2) | D17: 0.3 | F17: 公司在設備費用上加計的利潤比率，請填小數（例：20% → 填 0.2）
C18: 開發費 | D18: 2000 | F18: 前期開發費用（元），含可行性評估、申請規費、地主溝通等。若無則填 0
B19: 租金費用 | C19: 租金計算方式 | D19: 1 | E19: 20 | F19: 填 1 = 固定年租金（需填方式1參數）；填 2 = 依電費收入抽成（需填方式2參數）
C20: 【方式1參數】每年相同價格 | D20: 290201 | E20: 20 | F20: 租金計算方式選「1」時填寫，固定年租金金額（元/年），套用至整個電站壽命期
C21: 【方式2參數】抽成比率 | D21: 0 | E21: 20 | F21: 租金計算方式選「2」時填寫，請填小數（例：10% → 填 0.1）。租金 = 當年電費收入 × 抽成比率
B22: 運維費用 | C22: 每kw運維成本 | D22: 400 | E22: 20 | F22: 每峰瓩每年運維費用（元/kWp/年），含清洗、巡檢、維修等。
B23: 保險費用 | C23: 占整體設備費用比例 | D23: 0.003 | E23: 20 | F23: 保險費佔設備總費用比率，填小數（例：0.3% → 填 0.003）。預設 0.003，可依投保條件調整
B24: 模組回收費用 | C24: 每kw模組回收成本 | D24: 1000 | E24: 10 | F24: 每峰瓩模組廢棄回收費用（元/kWp），於第 1~10 年計提（攤提 10 年）。
B25: 利息費用 | C25: 銀行利率 | D25: 0.0256 | E25: 20 | F25: 向銀行貸款的年利率，填小數（例：2.56% → 填 0.0256）。請依銀行核准利率填入
B26: 所得稅 | C26: 所得稅率 | D26: 0.2 | E26: 20 | F26: 公司所得稅率，填小數（例：20% → 填 0.2）。預設 0.2，通常不需更改
B29: 現金流量表
B30: 金流項目 | C30: 相關參數 | D30: 參數數值 | F30: 說明
B31: 貸款成數 | C31: 占總設備費用比例 | D31: 0.8 | F31: 貸款佔設備總費用比例，填小數（例：80% → 填 0.8）。預設 0.8 代表貸八成、自備二成
B32: 貸款還款 | C32: 攤還期數 | D32: 15 | F32: 貸款還款年數（年）。預設 15 年，代表分 15 年平均攤還本金
B33: 現金股利 | C33: 股利比率 | D33: 0.9 | F33: 稅後現金流中分配給股東的比例，填小數（例：90% → 填 0.9）
B34: 年底減資 | C34: 攤還期數 | D34: 4 | F34: 年底減資返還股東的年數。預設 4 年，代表 倒數 4 年進行減資，加速資金返還
C37: 年份 | D37: 2020 | E37: 2021 | F37: 2022 | G37: 2023 | H37: 2024 | I37: 2025 | J37: 2026 | K37: 2027 | L37: 2028 | M37: 2029 | N37: 2030 | O37: 2031 | P37: 2032 | Q37: 2033 | R37: 2034 | S37: 2035 | T37: 2036 | U37: 2037 | V37: 2038 | W37: 2039
B38: 0
B39: (Unit : Currency) | C39: 0 | D39: 1 | E39: 2 | F39: 3 | G39: 4 | H39: 5 | I39: 6 | J39: 7 | K39: 8 | L39: 9 | M39: 10 | N39: 11 | O39: 12 | P39: 13 | Q39: 14 | R39: 15 | S39: 16 | T39: 17 | U39: 18 | V39: 19 | W39: 20
B40: 發電度數(KWH) | C40: 0 | D40: =$D$10*P1 -> 541531.98 | E40: =$D$10*Q1 -> 539343.97 | F40: =$D$10*R1 -> 537155.96 | G40: =$D$10*S1 -> 534967.96 | H40: =$D$10*T1 -> 532779.95 | I40: =$D$10*U1 -> 530591.94 | J40: =$D$10*V1 -> 528403.93 | K40: =$D$10*W1 -> 526215.92 | ... W40: =$D$10*AI1 -> 499959.83
B41: Inflow : 電費收入 | C41: - | D41: =D40*$D$13 -> 2166127.9 | E41: =E40*$D$13 -> 2157375.9 | F41: =F40*$D$13 -> 2148623.9 | G41: =G40*$D$13 -> 2139871.8 | H41: =H40*$D$13 -> 2131119.8 | I41: =I40*$D$13 -> 2122367.8 | J41: =J40*$D$13 -> 2113615.7 | K41: =K40*$D$13 -> 2104863.7 | ... W41: =W40*$D$13 -> 1999839.3
B42: Inflow : 政府補助 | C42: - | G42: - | H42: - | I42: - | J42: - | K42: - | L42: - | M42: - | N42: - | O42: - | P42: - | Q42: - | R42: - | S42: - | T42: - | U42: - | V42: - | W42: -
B43: Inflow : 銀行借款
B44: Outflow : 設備費用 | C44: =-(D16/(1-D17)+D18)*C4 -> -17693200
B45: Outflow : 設備放置區域租金 | C45: - | D45: -290201 | E45: -290201 | F45: -290201 | G45: -290201 | H45: -290201 | I45: -290201 | J45: -290201 | K45: -290201 | L45: -290201 | M45: -290201 | N45: -290201 | O45: -290201 | P45: -290201 | Q45: -290201 | R45: -290201 | S45: -290201 | T45: -290201 | U45: -290201 | V45: -290201 | W45: -290201
B46: Outflow : 返還借款
B47: Outflow : 利息費用 | C47: -
B48: Outflow : 維運費 | C48: - | D48: -174440 | E48: -174440 | F48: -174440 | G48: -174440 | H48: -174440 | I48: -174440 | J48: -174440 | K48: -174440 | L48: -174440 | M48: -174440 | N48: -174440 | O48: -174440 | P48: -174440 | Q48: -174440 | R48: -174440 | S48: -174440 | T48: -174440 | U48: -174440 | V48: -174440 | W48: -174440
B49: Outflow : 保險費 | C49: - | D49: -35324.1 | E49: -35324.1 | F49: -35324.1 | G49: -35324.1 | H49: -35324.1 | I49: -35324.1 | J49: -35324.1 | K49: -35324.1 | L49: -35324.1 | M49: -35324.1 | N49: -35324.1 | O49: -35324.1 | P49: -35324.1 | Q49: -35324.1 | R49: -35324.1 | S49: -35324.1 | T49: -35324.1 | U49: -35324.1 | V49: -35324.1 | W49: -35324.1
B50: Outflow : 模組回收費 | D50: -43610 | E50: -43610 | F50: -43610 | G50: -43610 | H50: -43610 | I50: -43610 | J50: -43610 | K50: -43610 | L50: -43610 | M50: -43610 | N50: 0 | O50: 0 | P50: 0 | Q50: 0 | R50: 0 | S50: 0 | T50: 0 | U50: 0 | V50: 0 | W50: 0
B51: Outflow : 其它費用(人事薪資…等)
B52: 1%管理費
B53: 績效獎金
B54: 所得稅20% | D54: =D77 -> -205618.76 | E54: =E77 -> -145828.16 | F54: =F77 -> -144077.75 | G54: =G77 -> -142327.34 | H54: =H77 -> -140576.94 | I54: =I77 -> -138826.53 | J54: =J77 -> -137076.13 | K54: =K77 -> -135325.72 | ... W54: =W77 -> -123042.84
B55: 現金流 | C55: =C44 -> -17693200 | D55: =SUM(D41:D54) -> 1416934.1 | E55: =SUM(E41:E54) -> 1467972.6 | F55: =SUM(F41:F54) -> 1460971 | G55: =SUM(G41:G54) -> 1453969.4 | H55: =SUM(H41:H54) -> 1446967.8 | I55: =SUM(I41:I54) -> 1439966.1 | J55: =SUM(J41:J54) -> 1432964.5 | K55: =SUM(K41:K54) -> 1425962.9 | ... W55: =SUM(W41:W54) -> 1376831.4
B56: 累計現金流 | D56: =C55+D55 -> -16276266 | E56: =D56+E55 -> -14808293 | F56: =E56+F55 -> -13347322 | G56: =F56+G55 -> -11893353 | H56: =G56+H55 -> -10446385 | I56: =H56+I55 -> -9006419 | J56: =I56+J55 -> -7573454.5 | K56: =J56+K55 -> -6147491.7 | L56: =K56+L55 -> -4728530.4 | ... X56: =W56+X55 -> 10766816
B57: 回收年限評估 | D57: =IF((D56)>0,"回收","未回收") -> 未回收 | E57: =IF((E56)>0,"回收","未回收") -> 未回收 | F57: =IF((F56)>0,"回收","未回收") -> 未回收 | G57: =IF((G56)>0,"回收","未回收") -> 未回收 | H57: =IF((H56)>0,"回收","未回收") -> 未回收 | I57: =IF((I56)>0,"回收","未回收") -> 未回收 | J57: =IF((J56)>0,"回收","未回收") -> 未回收 | K57: =IF((K56)>0,"回收","未回收") -> 未回收 | ... X57: =IF((X56)>0,"回收","未回收") -> 回收
B58: 專案法IRR | C58: =IRR(C55:W55) -> 0.050729975
C60: 年份 | D60: =D37 -> 2020 | E60: =E37 -> 2021 | F60: =F37 -> 2022 | G60: =G37 -> 2023 | H60: =H37 -> 2024 | I60: =I37 -> 2025 | J60: =J37 -> 2026 | K60: =K37 -> 2027 | ... W60: =W37 -> 2039
B61: 0 | T61: 償還年限
B62: (Unit : Currency) | C62: 0 | D62: 1 | E62: 2 | F62: 3 | G62: 4 | H62: 5 | I62: 6 | J62: 7 | K62: 8 | L62: 9 | M62: 10 | N62: 11 | O62: 12 | P62: 13 | Q62: 14 | R62: 15 | S62: 16 | T62: 17 | U62: 18 | V62: 19 | W62: 20
B63: 發電度數(KWH) | C63: 0 | D63: =D40 -> 541531.98 | E63: =E40 -> 539343.97 | F63: =F40 -> 537155.96 | G63: =G40 -> 534967.96 | H63: =H40 -> 532779.95 | I63: =I40 -> 530591.94 | J63: =J40 -> 528403.93 | K63: =K40 -> 526215.92 | ... W63: =W40 -> 499959.83
B64: Inflow : 電費收入 | C64: - | D64: =D41 -> 2166127.9 | E64: =E41 -> 2157375.9 | F64: =F41 -> 2148623.9 | G64: =G41 -> 2139871.8 | H64: =H41 -> 2131119.8 | I64: =I41 -> 2122367.8 | J64: =J41 -> 2113615.7 | K64: =K41 -> 2104863.7 | ... W64: =W41 -> 1999839.3
B65: Inflow : 政府補助 | C65: - | G65: - | H65: - | I65: - | J65: - | K65: - | L65: - | M65: - | N65: - | O65: - | P65: - | Q65: - | R65: - | S65: - | T65: - | U65: - | V65: - | W65: -
B66: Inflow : 銀行借款
B67: Outflow : 設備折舊 | D67: =$C$44/$E$16 -> -884660 | E67: =$C$44/$E$16 -> -884660 | F67: =$C$44/$E$16 -> -884660 | G67: =$C$44/$E$16 -> -884660 | H67: =$C$44/$E$16 -> -884660 | I67: =$C$44/$E$16 -> -884660 | J67: =$C$44/$E$16 -> -884660 | K67: =$C$44/$E$16 -> -884660 | ... W67: =$C$44/$E$16 -> -884660
B68: Outflow : 設備放置區域租金 | C68: - | D68: =D44 -> 0 | E68: =E45 -> -290201 | F68: =F45 -> -290201 | G68: =G45 -> -290201 | H68: =H45 -> -290201 | I68: =I45 -> -290201 | J68: =J45 -> -290201 | K68: =K45 -> -290201 | L68: =L45 -> -290201 | ... W68: =W45 -> -290201
B69: Outflow : 返還借款
B70: Outflow : 利息費用 | C70: - | D70: 0 | E70: 0 | F70: 0 | G70: 0 | H70: 0 | I70: 0 | J70: 0 | K70: 0 | L70: 0 | M70: 0 | N70: 0 | O70: 0 | P70: 0 | Q70: 0 | R70: 0 | S70: 0 | T70: 0 | U70: 0 | V70: 0 | W70: 0
B71: Outflow : 維運費 | C71: - | D71: =D48 -> -174440 | E71: =E48 -> -174440 | F71: =F48 -> -174440 | G71: =G48 -> -174440 | H71: =H48 -> -174440 | I71: =I48 -> -174440 | J71: =J48 -> -174440 | K71: =K48 -> -174440 | ... W71: =W48 -> -174440
B72: Outflow : 保險費 | C72: - | D72: =D49 -> -35324.1 | E72: =E49 -> -35324.1 | F72: =F49 -> -35324.1 | G72: =G49 -> -35324.1 | H72: =H49 -> -35324.1 | I72: =I49 -> -35324.1 | J72: =J49 -> -35324.1 | K72: =K49 -> -35324.1 | ... W72: =W49 -> -35324.1
B73: Outflow : 模組回收費 | D73: =D50 -> -43610 | E73: =E50 -> -43610 | F73: =F50 -> -43610 | G73: =G50 -> -43610 | H73: =H50 -> -43610 | I73: =I50 -> -43610 | J73: =J50 -> -43610 | K73: =K50 -> -43610 | ... W73: =W50 -> 0
B74: Outflow : 其它費用(人事薪資…等)
B75: 1%管理費
B76: 稅前淨利 | D76: =SUM(D64:D75) -> 1028093.8 | E76: =SUM(E64:E75) -> 729140.79 | F76: =SUM(F64:F75) -> 720388.76 | G76: =SUM(G64:G75) -> 711636.72 | H76: =SUM(H64:H75) -> 702884.69 | I76: =SUM(I64:I75) -> 694132.66 | J76: =SUM(J64:J75) -> 685380.63 | K76: =SUM(K64:K75) -> 676628.6 | ... X76: =SUM(X64:X75) -> 0
B77: 所得稅20% | D77: =-D76*0.2 -> -205618.76 | E77: =-E76*0.2 -> -145828.16 | F77: =-F76*0.2 -> -144077.75 | G77: =-G76*0.2 -> -142327.34 | H77: =-H76*0.2 -> -140576.94 | I77: =-I76*0.2 -> -138826.53 | J77: =-J76*0.2 -> -137076.13 | K77: =-K76*0.2 -> -135325.72 | ... X77: =-X76*0.2 -> 0
B78: 稅後淨利 | D78: =SUM(D76:D77) -> 822475.06 | E78: =SUM(E76:E77) -> 583312.63 | F78: =SUM(F76:F77) -> 576311 | G78: =SUM(G76:G77) -> 569309.38 | H78: =SUM(H76:H77) -> 562307.75 | I78: =SUM(I76:I77) -> 555306.13 | J78: =SUM(J76:J77) -> 548304.5 | K78: =SUM(K76:K77) -> 541302.88 | ... X78: =SUM(X76:X77) -> 0
B79: 累計現金流
B80: 回收年限評估
