Workbook

Sheet 多站彙整
C4: 年份 | D4: 2020 | E4: 2021 | F4: 2022 | G4: 2023 | H4: 2024 | I4: 2025 | J4: 2026 | K4: 2027 | L4: 2028 | M4: 2029 | N4: 2030 | O4: 2031 | P4: 2032 | Q4: 2033 | R4: 2034 | S4: 2035 | T4: 2036 | U4: 2037 | V4: 2038 | W4: 2039
C5: 預估發電度數
B6: 淡江大學 | D6: =ROUND(ABS(淡江大學_p8!D40),0) -> 541532 | E6: =ROUND(ABS(淡江大學_p8!E40),0) -> 539344 | F6: =ROUND(ABS(淡江大學_p8!F40),0) -> 537156 | G6: =ROUND(ABS(淡江大學_p8!G40),0) -> 534968 | H6: =ROUND(ABS(淡江大學_p8!H40),0) -> 532780 | I6: =ROUND(ABS(淡江大學_p8!I40),0) -> 530592 | J6: =ROUND(ABS(淡江大學_p8!J40),0) -> 528404 | K6: =ROUND(ABS(淡江大學_p8!K40),0) -> 526216 | ... W6: =ROUND(ABS(淡江大學_p8!W40),0) -> 499960
B7: 淡江大學 | D7: =ROUND(ABS(淡江大學_p7!D40),0) -> 541532 | E7: =ROUND(ABS(淡江大學_p7!E40),0) -> 539344 | F7: =ROUND(ABS(淡江大學_p7!F40),0) -> 537156 | G7: =ROUND(ABS(淡江大學_p7!G40),0) -> 534968 | H7: =ROUND(ABS(淡江大學_p7!H40),0) -> 532780 | I7: =ROUND(ABS(淡江大學_p7!I40),0) -> 530592 | J7: =ROUND(ABS(淡江大學_p7!J40),0) -> 528404 | K7: =ROUND(ABS(淡江大學_p7!K40),0) -> 526216 | ... W7: =ROUND(ABS(淡江大學_p7!W40),0) -> 499960
B8: 淡江大學 | D8: =ROUND(ABS(淡江大學_p5!D40),0) -> 541532 | E8: =ROUND(ABS(淡江大學_p5!E40),0) -> 539344 | F8: =ROUND(ABS(淡江大學_p5!F40),0) -> 537156 | G8: =ROUND(ABS(淡江大學_p5!G40),0) -> 534968 | H8: =ROUND(ABS(淡江大學_p5!H40),0) -> 532780 | I8: =ROUND(ABS(淡江大學_p5!I40),0) -> 530592 | J8: =ROUND(ABS(淡江大學_p5!J40),0) -> 528404 | K8: =ROUND(ABS(淡江大學_p5!K40),0) -> 526216 | ... W8: =ROUND(ABS(淡江大學_p5!W40),0) -> 499960
B9: 淡江大學 | D9: =ROUND(ABS(淡江大學_p4!D40),0) -> 541532 | E9: =ROUND(ABS(淡江大學_p4!E40),0) -> 539344 | F9: =ROUND(ABS(淡江大學_p4!F40),0) -> 537156 | G9: =ROUND(ABS(淡江大學_p4!G40),0) -> 534968 | H9: =ROUND(ABS(淡江大學_p4!H40),0) -> 532780 | I9: =ROUND(ABS(淡江大學_p4!I40),0) -> 530592 | J9: =ROUND(ABS(淡江大學_p4!J40),0) -> 528404 | K9: =ROUND(ABS(淡江大學_p4!K40),0) -> 526216 | ... W9: =ROUND(ABS(淡江大學_p4!W40),0) -> 499960
B10: 淡江大學 | D10: =ROUND(ABS(淡江大學_p3!D40),0) -> 541532 | E10: =ROUND(ABS(淡江大學_p3!E40),0) -> 539344 | F10: =ROUND(ABS(淡江大學_p3!F40),0) -> 537156 | G10: =ROUND(ABS(淡江大學_p3!G40),0) -> 534968 | H10: =ROUND(ABS(淡江大學_p3!H40),0) -> 532780 | I10: =ROUND(ABS(淡江大學_p3!I40),0) -> 530592 | J10: =ROUND(ABS(淡江大學_p3!J40),0) -> 528404 | K10: =ROUND(ABS(淡江大學_p3!K40),0) -> 526216 | ... W10: =ROUND(ABS(淡江大學_p3!W40),0) -> 499960
B11: 淡江大學 | D11: =ROUND(ABS(淡江大學_p6!D40),0) -> 541532 | E11: =ROUND(ABS(淡江大學_p6!E40),0) -> 539344 | F11: =ROUND(ABS(淡江大學_p6!F40),0) -> 537156 | G11: =ROUND(ABS(淡江大學_p6!G40),0) -> 534968 | H11: =ROUND(ABS(淡江大學_p6!H40),0) -> 532780 | I11: =ROUND(ABS(淡江大學_p6!I40),0) -> 530592 | J11: =ROUND(ABS(淡江大學_p6!J40),0) -> 528404 | K11: =ROUND(ABS(淡江大學_p6!K40),0) -> 526216 | ... W11: =ROUND(ABS(淡江大學_p6!W40),0) -> 499960
C12: 預估發電度數/年總計 | D12: =SUM(D6:D11) -> 3249192 | E12: =SUM(E6:E11) -> 3236064 | F12: =SUM(F6:F11) -> 3222936 | G12: =SUM(G6:G11) -> 3209808 | H12: =SUM(H6:H11) -> 3196680 | I12: =SUM(I6:I11) -> 3183552 | J12: =SUM(J6:J11) -> 3170424 | K12: =SUM(K6:K11) -> 3157296 | ... W12: =SUM(W6:W11) -> 2999760
C13: 年份 | D13: 2020 | E13: 2021 | F13: 2022 | G13: 2023 | H13: 2024 | I13: 2025 | J13: 2026 | K13: 2027 | L13: 2028 | M13: 2029 | N13: 2030 | O13: 2031 | P13: 2032 | Q13: 2033 | R13: 2034 | S13: 2035 | T13: 2036 | U13: 2037 | V13: 2038 | W13: 2039
C14: 預估收入
B15: 淡江大學 | D15: =ROUND(ABS(淡江大學_p8!D41),0) -> 2166128 | E15: =ROUND(ABS(淡江大學_p8!E41),0) -> 2157376 | F15: =ROUND(ABS(淡江大學_p8!F41),0) -> 2148624 | G15: =ROUND(ABS(淡江大學_p8!G41),0) -> 2139872 | H15: =ROUND(ABS(淡江大學_p8!H41),0) -> 2131120 | I15: =ROUND(ABS(淡江大學_p8!I41),0) -> 2122368 | J15: =ROUND(ABS(淡江大學_p8!J41),0) -> 2113616 | K15: =ROUND(ABS(淡江大學_p8!K41),0) -> 2104864 | ... W15: =ROUND(ABS(淡江大學_p8!W41),0) -> 1999839
B16: 淡江大學 | D16: =ROUND(ABS(淡江大學_p7!D41),0) -> 2166128 | E16: =ROUND(ABS(淡江大學_p7!E41),0) -> 2157376 | F16: =ROUND(ABS(淡江大學_p7!F41),0) -> 2148624 | G16: =ROUND(ABS(淡江大學_p7!G41),0) -> 2139872 | H16: =ROUND(ABS(淡江大學_p7!H41),0) -> 2131120 | I16: =ROUND(ABS(淡江大學_p7!I41),0) -> 2122368 | J16: =ROUND(ABS(淡江大學_p7!J41),0) -> 2113616 | K16: =ROUND(ABS(淡江大學_p7!K41),0) -> 2104864 | ... W16: =ROUND(ABS(淡江大學_p7!W41),0) -> 1999839
B17: 淡江大學 | D17: =ROUND(ABS(淡江大學_p5!D41),0) -> 2166128 | E17: =ROUND(ABS(淡江大學_p5!E41),0) -> 2157376 | F17: =ROUND(ABS(淡江大學_p5!F41),0) -> 2148624 | G17: =ROUND(ABS(淡江大學_p5!G41),0) -> 2139872 | H17: =ROUND(ABS(淡江大學_p5!H41),0) -> 2131120 | I17: =ROUND(ABS(淡江大學_p5!I41),0) -> 2122368 | J17: =ROUND(ABS(淡江大學_p5!J41),0) -> 2113616 | K17: =ROUND(ABS(淡江大學_p5!K41),0) -> 2104864 | ... W17: =ROUND(ABS(淡江大學_p5!W41),0) -> 1999839
B18: 淡江大學 | D18: =ROUND(ABS(淡江大學_p4!D41),0) -> 2166128 | E18: =ROUND(ABS(淡江大學_p4!E41),0) -> 2157376 | F18: =ROUND(ABS(淡江大學_p4!F41),0) -> 2148624 | G18: =ROUND(ABS(淡江大學_p4!G41),0) -> 2139872 | H18: =ROUND(ABS(淡江大學_p4!H41),0) -> 2131120 | I18: =ROUND(ABS(淡江大學_p4!I41),0) -> 2122368 | J18: =ROUND(ABS(淡江大學_p4!J41),0) -> 2113616 | K18: =ROUND(ABS(淡江大學_p4!K41),0) -> 2104864 | ... W18: =ROUND(ABS(淡江大學_p4!W41),0) -> 1999839
B19: 淡江大學 | D19: =ROUND(ABS(淡江大學_p3!D41),0) -> 2166128 | E19: =ROUND(ABS(淡江大學_p3!E41),0) -> 2157376 | F19: =ROUND(ABS(淡江大學_p3!F41),0) -> 2148624 | G19: =ROUND(ABS(淡江大學_p3!G41),0) -> 2139872 | H19: =ROUND(ABS(淡江大學_p3!H41),0) -> 2131120 | I19: =ROUND(ABS(淡江大學_p3!I41),0) -> 2122368 | J19: =ROUND(ABS(淡江大學_p3!J41),0) -> 2113616 | K19: =ROUND(ABS(淡江大學_p3!K41),0) -> 2104864 | ... W19: =ROUND(ABS(淡江大學_p3!W41),0) -> 1999839
B20: 淡江大學 | D20: =ROUND(ABS(淡江大學_p6!D41),0) -> 2166128 | E20: =ROUND(ABS(淡江大學_p6!E41),0) -> 2157376 | F20: =ROUND(ABS(淡江大學_p6!F41),0) -> 2148624 | G20: =ROUND(ABS(淡江大學_p6!G41),0) -> 2139872 | H20: =ROUND(ABS(淡江大學_p6!H41),0) -> 2131120 | I20: =ROUND(ABS(淡江大學_p6!I41),0) -> 2122368 | J20: =ROUND(ABS(淡江大學_p6!J41),0) -> 2113616 | K20: =ROUND(ABS(淡江大學_p6!K41),0) -> 2104864 | ... W20: =ROUND(ABS(淡江大學_p6!W41),0) -> 1999839
C21: 預估收入/年總計 | D21: =SUM(D15:D20) -> 12996768 | E21: =SUM(E15:E20) -> 12944256 | F21: =SUM(F15:F20) -> 12891744 | G21: =SUM(G15:G20) -> 12839232 | H21: =SUM(H15:H20) -> 12786720 | I21: =SUM(I15:I20) -> 12734208 | J21: =SUM(J15:J20) -> 12681696 | K21: =SUM(K15:K20) -> 12629184 | ... W21: =SUM(W15:W20) -> 11999034
C22: 年份 | D22: 2020 | E22: 2021 | F22: 2022 | G22: 2023 | H22: 2024 | I22: 2025 | J22: 2026 | K22: 2027 | L22: 2028 | M22: 2029 | N22: 2030 | O22: 2031 | P22: 2032 | Q22: 2033 | R22: 2034 | S22: 2035 | T22: 2036 | U22: 2037 | V22: 2038 | W22: 2039
C23: 租金
B24: 淡江大學 | D24: =ROUND(ABS(淡江大學_p8!D45),0) -> 290201 | E24: =ROUND(ABS(淡江大學_p8!E45),0) -> 290201 | F24: =ROUND(ABS(淡江大學_p8!F45),0) -> 290201 | G24: =ROUND(ABS(淡江大學_p8!G45),0) -> 290201 | H24: =ROUND(ABS(淡江大學_p8!H45),0) -> 290201 | I24: =ROUND(ABS(淡江大學_p8!I45),0) -> 290201 | J24: =ROUND(ABS(淡江大學_p8!J45),0) -> 290201 | K24: =ROUND(ABS(淡江大學_p8!K45),0) -> 290201 | ... W24: =ROUND(ABS(淡江大學_p8!W45),0) -> 290201
B25: 淡江大學 | D25: =ROUND(ABS(淡江大學_p7!D45),0) -> 290201 | E25: =ROUND(ABS(淡江大學_p7!E45),0) -> 290201 | F25: =ROUND(ABS(淡江大學_p7!F45),0) -> 290201 | G25: =ROUND(ABS(淡江大學_p7!G45),0) -> 290201 | H25: =ROUND(ABS(淡江大學_p7!H45),0) -> 290201 | I25: =ROUND(ABS(淡江大學_p7!I45),0) -> 290201 | J25: =ROUND(ABS(淡江大學_p7!J45),0) -> 290201 | K25: =ROUND(ABS(淡江大學_p7!K45),0) -> 290201 | ... W25: =ROUND(ABS(淡江大學_p7!W45),0) -> 290201
B26: 淡江大學 | D26: =ROUND(ABS(淡江大學_p5!D45),0) -> 290201 | E26: =ROUND(ABS(淡江大學_p5!E45),0) -> 290201 | F26: =ROUND(ABS(淡江大學_p5!F45),0) -> 290201 | G26: =ROUND(ABS(淡江大學_p5!G45),0) -> 290201 | H26: =ROUND(ABS(淡江大學_p5!H45),0) -> 290201 | I26: =ROUND(ABS(淡江大學_p5!I45),0) -> 290201 | J26: =ROUND(ABS(淡江大學_p5!J45),0) -> 290201 | K26: =ROUND(ABS(淡江大學_p5!K45),0) -> 290201 | ... W26: =ROUND(ABS(淡江大學_p5!W45),0) -> 290201
B27: 淡江大學 | D27: =ROUND(ABS(淡江大學_p4!D45),0) -> 290201 | E27: =ROUND(ABS(淡江大學_p4!E45),0) -> 290201 | F27: =ROUND(ABS(淡江大學_p4!F45),0) -> 290201 | G27: =ROUND(ABS(淡江大學_p4!G45),0) -> 290201 | H27: =ROUND(ABS(淡江大學_p4!H45),0) -> 290201 | I27: =ROUND(ABS(淡江大學_p4!I45),0) -> 290201 | J27: =ROUND(ABS(淡江大學_p4!J45),0) -> 290201 | K27: =ROUND(ABS(淡江大學_p4!K45),0) -> 290201 | ... W27: =ROUND(ABS(淡江大學_p4!W45),0) -> 290201
B28: 淡江大學 | D28: =ROUND(ABS(淡江大學_p3!D45),0) -> 290201 | E28: =ROUND(ABS(淡江大學_p3!E45),0) -> 290201 | F28: =ROUND(ABS(淡江大學_p3!F45),0) -> 290201 | G28: =ROUND(ABS(淡江大學_p3!G45),0) -> 290201 | H28: =ROUND(ABS(淡江大學_p3!H45),0) -> 290201 | I28: =ROUND(ABS(淡江大學_p3!I45),0) -> 290201 | J28: =ROUND(ABS(淡江大學_p3!J45),0) -> 290201 | K28: =ROUND(ABS(淡江大學_p3!K45),0) -> 290201 | ... W28: =ROUND(ABS(淡江大學_p3!W45),0) -> 290201
B29: 淡江大學 | D29: =ROUND(ABS(淡江大學_p6!D45),0) -> 290201 | E29: =ROUND(ABS(淡江大學_p6!E45),0) -> 290201 | F29: =ROUND(ABS(淡江大學_p6!F45),0) -> 290201 | G29: =ROUND(ABS(淡江大學_p6!G45),0) -> 290201 | H29: =ROUND(ABS(淡江大學_p6!H45),0) -> 290201 | I29: =ROUND(ABS(淡江大學_p6!I45),0) -> 290201 | J29: =ROUND(ABS(淡江大學_p6!J45),0) -> 290201 | K29: =ROUND(ABS(淡江大學_p6!K45),0) -> 290201 | ... W29: =ROUND(ABS(淡江大學_p6!W45),0) -> 290201
C30: 租金/年總計 | D30: =SUM(D24:D29) -> 1741206 | E30: =SUM(E24:E29) -> 1741206 | F30: =SUM(F24:F29) -> 1741206 | G30: =SUM(G24:G29) -> 1741206 | H30: =SUM(H24:H29) -> 1741206 | I30: =SUM(I24:I29) -> 1741206 | J30: =SUM(J24:J29) -> 1741206 | K30: =SUM(K24:K29) -> 1741206 | ... W30: =SUM(W24:W29) -> 1741206
C31: 年份 | D31: 2020 | E31: 2021 | F31: 2022 | G31: 2023 | H31: 2024 | I31: 2025 | J31: 2026 | K31: 2027 | L31: 2028 | M31: 2029 | N31: 2030 | O31: 2031 | P31: 2032 | Q31: 2033 | R31: 2034 | S31: 2035 | T31: 2036 | U31: 2037 | V31: 2038 | W31: 2039
C32: 運維
B33: 淡江大學 | D33: =ROUND(ABS(淡江大學_p8!D48),0) -> 174440 | E33: =ROUND(ABS(淡江大學_p8!E48),0) -> 174440 | F33: =ROUND(ABS(淡江大學_p8!F48),0) -> 174440 | G33: =ROUND(ABS(淡江大學_p8!G48),0) -> 174440 | H33: =ROUND(ABS(淡江大學_p8!H48),0) -> 174440 | I33: =ROUND(ABS(淡江大學_p8!I48),0) -> 174440 | J33: =ROUND(ABS(淡江大學_p8!J48),0) -> 174440 | K33: =ROUND(ABS(淡江大學_p8!K48),0) -> 174440 | ... W33: =ROUND(ABS(淡江大學_p8!W48),0) -> 174440
B34: 淡江大學 | D34: =ROUND(ABS(淡江大學_p7!D48),0) -> 174440 | E34: =ROUND(ABS(淡江大學_p7!E48),0) -> 174440 | F34: =ROUND(ABS(淡江大學_p7!F48),0) -> 174440 | G34: =ROUND(ABS(淡江大學_p7!G48),0) -> 174440 | H34: =ROUND(ABS(淡江大學_p7!H48),0) -> 174440 | I34: =ROUND(ABS(淡江大學_p7!I48),0) -> 174440 | J34: =ROUND(ABS(淡江大學_p7!J48),0) -> 174440 | K34: =ROUND(ABS(淡江大學_p7!K48),0) -> 174440 | ... W34: =ROUND(ABS(淡江大學_p7!W48),0) -> 174440
B35: 淡江大學 | D35: =ROUND(ABS(淡江大學_p5!D48),0) -> 174440 | E35: =ROUND(ABS(淡江大學_p5!E48),0) -> 174440 | F35: =ROUND(ABS(淡江大學_p5!F48),0) -> 174440 | G35: =ROUND(ABS(淡江大學_p5!G48),0) -> 174440 | H35: =ROUND(ABS(淡江大學_p5!H48),0) -> 174440 | I35: =ROUND(ABS(淡江大學_p5!I48),0) -> 174440 | J35: =ROUND(ABS(淡江大學_p5!J48),0) -> 174440 | K35: =ROUND(ABS(淡江大學_p5!K48),0) -> 174440 | ... W35: =ROUND(ABS(淡江大學_p5!W48),0) -> 174440
B36: 淡江大學 | D36: =ROUND(ABS(淡江大學_p4!D48),0) -> 174440 | E36: =ROUND(ABS(淡江大學_p4!E48),0) -> 174440 | F36: =ROUND(ABS(淡江大學_p4!F48),0) -> 174440 | G36: =ROUND(ABS(淡江大學_p4!G48),0) -> 174440 | H36: =ROUND(ABS(淡江大學_p4!H48),0) -> 174440 | I36: =ROUND(ABS(淡江大學_p4!I48),0) -> 174440 | J36: =ROUND(ABS(淡江大學_p4!J48),0) -> 174440 | K36: =ROUND(ABS(淡江大學_p4!K48),0) -> 174440 | ... W36: =ROUND(ABS(淡江大學_p4!W48),0) -> 174440
B37: 淡江大學 | D37: =ROUND(ABS(淡江大學_p3!D48),0) -> 174440 | E37: =ROUND(ABS(淡江大學_p3!E48),0) -> 174440 | F37: =ROUND(ABS(淡江大學_p3!F48),0) -> 174440 | G37: =ROUND(ABS(淡江大學_p3!G48),0) -> 174440 | H37: =ROUND(ABS(淡江大學_p3!H48),0) -> 174440 | I37: =ROUND(ABS(淡江大學_p3!I48),0) -> 174440 | J37: =ROUND(ABS(淡江大學_p3!J48),0) -> 174440 | K37: =ROUND(ABS(淡江大學_p3!K48),0) -> 174440 | ... W37: =ROUND(ABS(淡江大學_p3!W48),0) -> 174440
B38: 淡江大學 | D38: =ROUND(ABS(淡江大學_p6!D48),0) -> 174440 | E38: =ROUND(ABS(淡江大學_p6!E48),0) -> 174440 | F38: =ROUND(ABS(淡江大學_p6!F48),0) -> 174440 | G38: =ROUND(ABS(淡江大學_p6!G48),0) -> 174440 | H38: =ROUND(ABS(淡江大學_p6!H48),0) -> 174440 | I38: =ROUND(ABS(淡江大學_p6!I48),0) -> 174440 | J38: =ROUND(ABS(淡江大學_p6!J48),0) -> 174440 | K38: =ROUND(ABS(淡江大學_p6!K48),0) -> 174440 | ... W38: =ROUND(ABS(淡江大學_p6!W48),0) -> 174440
C39: 運維/年總計 | D39: =SUM(D33:D38) -> 1046640 | E39: =SUM(E33:E38) -> 1046640 | F39: =SUM(F33:F38) -> 1046640 | G39: =SUM(G33:G38) -> 1046640 | H39: =SUM(H33:H38) -> 1046640 | I39: =SUM(I33:I38) -> 1046640 | J39: =SUM(J33:J38) -> 1046640 | K39: =SUM(K33:K38) -> 1046640 | ... W39: =SUM(W33:W38) -> 1046640
C40: 年份 | D40: 2020 | E40: 2021 | F40: 2022 | G40: 2023 | H40: 2024 | I40: 2025 | J40: 2026 | K40: 2027 | L40: 2028 | M40: 2029 | N40: 2030 | O40: 2031 | P40: 2032 | Q40: 2033 | R40: 2034 | S40: 2035 | T40: 2036 | U40: 2037 | V40: 2038 | W40: 2039
C41: 保險
B42: 淡江大學 | D42: =ROUND(ABS(淡江大學_p8!D49),0) -> 27474 | E42: =ROUND(ABS(淡江大學_p8!E49),0) -> 27474 | F42: =ROUND(ABS(淡江大學_p8!F49),0) -> 27474 | G42: =ROUND(ABS(淡江大學_p8!G49),0) -> 27474 | H42: =ROUND(ABS(淡江大學_p8!H49),0) -> 27474 | I42: =ROUND(ABS(淡江大學_p8!I49),0) -> 27474 | J42: =ROUND(ABS(淡江大學_p8!J49),0) -> 27474 | K42: =ROUND(ABS(淡江大學_p8!K49),0) -> 27474 | ... W42: =ROUND(ABS(淡江大學_p8!W49),0) -> 27474
B43: 淡江大學 | D43: =ROUND(ABS(淡江大學_p7!D49),0) -> 30091 | E43: =ROUND(ABS(淡江大學_p7!E49),0) -> 30091 | F43: =ROUND(ABS(淡江大學_p7!F49),0) -> 30091 | G43: =ROUND(ABS(淡江大學_p7!G49),0) -> 30091 | H43: =ROUND(ABS(淡江大學_p7!H49),0) -> 30091 | I43: =ROUND(ABS(淡江大學_p7!I49),0) -> 30091 | J43: =ROUND(ABS(淡江大學_p7!J49),0) -> 30091 | K43: =ROUND(ABS(淡江大學_p7!K49),0) -> 30091 | ... W43: =ROUND(ABS(淡江大學_p7!W49),0) -> 30091
B44: 淡江大學 | D44: =ROUND(ABS(淡江大學_p5!D49),0) -> 35324 | E44: =ROUND(ABS(淡江大學_p5!E49),0) -> 35324 | F44: =ROUND(ABS(淡江大學_p5!F49),0) -> 35324 | G44: =ROUND(ABS(淡江大學_p5!G49),0) -> 35324 | H44: =ROUND(ABS(淡江大學_p5!H49),0) -> 35324 | I44: =ROUND(ABS(淡江大學_p5!I49),0) -> 35324 | J44: =ROUND(ABS(淡江大學_p5!J49),0) -> 35324 | K44: =ROUND(ABS(淡江大學_p5!K49),0) -> 35324 | ... W44: =ROUND(ABS(淡江大學_p5!W49),0) -> 35324
B45: 淡江大學 | D45: =ROUND(ABS(淡江大學_p4!D49),0) -> 37941 | E45: =ROUND(ABS(淡江大學_p4!E49),0) -> 37941 | F45: =ROUND(ABS(淡江大學_p4!F49),0) -> 37941 | G45: =ROUND(ABS(淡江大學_p4!G49),0) -> 37941 | H45: =ROUND(ABS(淡江大學_p4!H49),0) -> 37941 | I45: =ROUND(ABS(淡江大學_p4!I49),0) -> 37941 | J45: =ROUND(ABS(淡江大學_p4!J49),0) -> 37941 | K45: =ROUND(ABS(淡江大學_p4!K49),0) -> 37941 | ... W45: =ROUND(ABS(淡江大學_p4!W49),0) -> 37941
B46: 淡江大學 | D46: =ROUND(ABS(淡江大學_p3!D49),0) -> 40557 | E46: =ROUND(ABS(淡江大學_p3!E49),0) -> 40557 | F46: =ROUND(ABS(淡江大學_p3!F49),0) -> 40557 | G46: =ROUND(ABS(淡江大學_p3!G49),0) -> 40557 | H46: =ROUND(ABS(淡江大學_p3!H49),0) -> 40557 | I46: =ROUND(ABS(淡江大學_p3!I49),0) -> 40557 | J46: =ROUND(ABS(淡江大學_p3!J49),0) -> 40557 | K46: =ROUND(ABS(淡江大學_p3!K49),0) -> 40557 | ... W46: =ROUND(ABS(淡江大學_p3!W49),0) -> 40557
B47: 淡江大學 | D47: =ROUND(ABS(淡江大學_p6!D49),0) -> 32708 | E47: =ROUND(ABS(淡江大學_p6!E49),0) -> 32708 | F47: =ROUND(ABS(淡江大學_p6!F49),0) -> 32708 | G47: =ROUND(ABS(淡江大學_p6!G49),0) -> 32708 | H47: =ROUND(ABS(淡江大學_p6!H49),0) -> 32708 | I47: =ROUND(ABS(淡江大學_p6!I49),0) -> 32708 | J47: =ROUND(ABS(淡江大學_p6!J49),0) -> 32708 | K47: =ROUND(ABS(淡江大學_p6!K49),0) -> 32708 | ... W47: =ROUND(ABS(淡江大學_p6!W49),0) -> 32708
C48: 保險/年總計 | D48: =SUM(D42:D47) -> 204095 | E48: =SUM(E42:E47) -> 204095 | F48: =SUM(F42:F47) -> 204095 | G48: =SUM(G42:G47) -> 204095 | H48: =SUM(H42:H47) -> 204095 | I48: =SUM(I42:I47) -> 204095 | J48: =SUM(J42:J47) -> 204095 | K48: =SUM(K42:K47) -> 204095 | ... W48: =SUM(W42:W47) -> 204095
C49: 年份 | D49: 2020 | E49: 2021 | F49: 2022 | G49: 2023 | H49: 2024 | I49: 2025 | J49: 2026 | K49: 2027 | L49: 2028 | M49: 2029 | N49: 2030 | O49: 2031 | P49: 2032 | Q49: 2033 | R49: 2034 | S49: 2035 | T49: 2036 | U49: 2037 | V49: 2038 | W49: 2039
C50: 模組回收費
B51: 淡江大學 | D51: =ROUND(ABS(淡江大學_p8!D50),0) -> 43610 | E51: =ROUND(ABS(淡江大學_p8!E50),0) -> 43610 | F51: =ROUND(ABS(淡江大學_p8!F50),0) -> 43610 | G51: =ROUND(ABS(淡江大學_p8!G50),0) -> 43610 | H51: =ROUND(ABS(淡江大學_p8!H50),0) -> 43610 | I51: =ROUND(ABS(淡江大學_p8!I50),0) -> 43610 | J51: =ROUND(ABS(淡江大學_p8!J50),0) -> 43610 | K51: =ROUND(ABS(淡江大學_p8!K50),0) -> 43610 | ... W51: =ROUND(ABS(淡江大學_p8!W50),0) -> 0
B52: 淡江大學 | D52: =ROUND(ABS(淡江大學_p7!D50),0) -> 43610 | E52: =ROUND(ABS(淡江大學_p7!E50),0) -> 43610 | F52: =ROUND(ABS(淡江大學_p7!F50),0) -> 43610 | G52: =ROUND(ABS(淡江大學_p7!G50),0) -> 43610 | H52: =ROUND(ABS(淡江大學_p7!H50),0) -> 43610 | I52: =ROUND(ABS(淡江大學_p7!I50),0) -> 43610 | J52: =ROUND(ABS(淡江大學_p7!J50),0) -> 43610 | K52: =ROUND(ABS(淡江大學_p7!K50),0) -> 43610 | ... W52: =ROUND(ABS(淡江大學_p7!W50),0) -> 0
B53: 淡江大學 | D53: =ROUND(ABS(淡江大學_p5!D50),0) -> 43610 | E53: =ROUND(ABS(淡江大學_p5!E50),0) -> 43610 | F53: =ROUND(ABS(淡江大學_p5!F50),0) -> 43610 | G53: =ROUND(ABS(淡江大學_p5!G50),0) -> 43610 | H53: =ROUND(ABS(淡江大學_p5!H50),0) -> 43610 | I53: =ROUND(ABS(淡江大學_p5!I50),0) -> 43610 | J53: =ROUND(ABS(淡江大學_p5!J50),0) -> 43610 | K53: =ROUND(ABS(淡江大學_p5!K50),0) -> 43610 | ... W53: =ROUND(ABS(淡江大學_p5!W50),0) -> 0
B54: 淡江大學 | D54: =ROUND(ABS(淡江大學_p4!D50),0) -> 43610 | E54: =ROUND(ABS(淡江大學_p4!E50),0) -> 43610 | F54: =ROUND(ABS(淡江大學_p4!F50),0) -> 43610 | G54: =ROUND(ABS(淡江大學_p4!G50),0) -> 43610 | H54: =ROUND(ABS(淡江大學_p4!H50),0) -> 43610 | I54: =ROUND(ABS(淡江大學_p4!I50),0) -> 43610 | J54: =ROUND(ABS(淡江大學_p4!J50),0) -> 43610 | K54: =ROUND(ABS(淡江大學_p4!K50),0) -> 43610 | ... W54: =ROUND(ABS(淡江大學_p4!W50),0) -> 0
B55: 淡江大學 | D55: =ROUND(ABS(淡江大學_p3!D50),0) -> 43610 | E55: =ROUND(ABS(淡江大學_p3!E50),0) -> 43610 | F55: =ROUND(ABS(淡江大學_p3!F50),0) -> 43610 | G55: =ROUND(ABS(淡江大學_p3!G50),0) -> 43610 | H55: =ROUND(ABS(淡江大學_p3!H50),0) -> 43610 | I55: =ROUND(ABS(淡江大學_p3!I50),0) -> 43610 | J55: =ROUND(ABS(淡江大學_p3!J50),0) -> 43610 | K55: =ROUND(ABS(淡江大學_p3!K50),0) -> 43610 | ... W55: =ROUND(ABS(淡江大學_p3!W50),0) -> 0
B56: 淡江大學 | D56: =ROUND(ABS(淡江大學_p6!D50),0) -> 43610 | E56: =ROUND(ABS(淡江大學_p6!E50),0) -> 43610 | F56: =ROUND(ABS(淡江大學_p6!F50),0) -> 43610 | G56: =ROUND(ABS(淡江大學_p6!G50),0) -> 43610 | H56: =ROUND(ABS(淡江大學_p6!H50),0) -> 43610 | I56: =ROUND(ABS(淡江大學_p6!I50),0) -> 43610 | J56: =ROUND(ABS(淡江大學_p6!J50),0) -> 43610 | K56: =ROUND(ABS(淡江大學_p6!K50),0) -> 43610 | ... W56: =ROUND(ABS(淡江大學_p6!W50),0) -> 0
C57: 模組回收費/年總計 | D57: =SUM(D51:D56) -> 261660 | E57: =SUM(E51:E56) -> 261660 | F57: =SUM(F51:F56) -> 261660 | G57: =SUM(G51:G56) -> 261660 | H57: =SUM(H51:H56) -> 261660 | I57: =SUM(I51:I56) -> 261660 | J57: =SUM(J51:J56) -> 261660 | K57: =SUM(K51:K56) -> 261660 | ... W57: =SUM(W51:W56) -> 0
C58: 年份 | D58: 2020 | E58: 2021 | F58: 2022 | G58: 2023 | H58: 2024 | I58: 2025 | J58: 2026 | K58: 2027 | L58: 2028 | M58: 2029 | N58: 2030 | O58: 2031 | P58: 2032 | Q58: 2033 | R58: 2034 | S58: 2035 | T58: 2036 | U58: 2037 | V58: 2038 | W58: 2039
C59: 所得稅
B60: 淡江大學 | D60: =ROUND(ABS(淡江大學_p8!D54),0) -> 244569 | E60: =ROUND(ABS(淡江大學_p8!E54),0) -> 184778 | F60: =ROUND(ABS(淡江大學_p8!F54),0) -> 183028 | G60: =ROUND(ABS(淡江大學_p8!G54),0) -> 181277 | H60: =ROUND(ABS(淡江大學_p8!H54),0) -> 179527 | I60: =ROUND(ABS(淡江大學_p8!I54),0) -> 177776 | J60: =ROUND(ABS(淡江大學_p8!J54),0) -> 176026 | K60: =ROUND(ABS(淡江大學_p8!K54),0) -> 174276 | ... W60: =ROUND(ABS(淡江大學_p8!W54),0) -> 161993
B61: 淡江大學 | D61: =ROUND(ABS(淡江大學_p7!D54),0) -> 231585 | E61: =ROUND(ABS(淡江大學_p7!E54),0) -> 171795 | F61: =ROUND(ABS(淡江大學_p7!F54),0) -> 170044 | G61: =ROUND(ABS(淡江大學_p7!G54),0) -> 168294 | H61: =ROUND(ABS(淡江大學_p7!H54),0) -> 166544 | I61: =ROUND(ABS(淡江大學_p7!I54),0) -> 164793 | J61: =ROUND(ABS(淡江大學_p7!J54),0) -> 163043 | K61: =ROUND(ABS(淡江大學_p7!K54),0) -> 161292 | ... W61: =ROUND(ABS(淡江大學_p7!W54),0) -> 149009
B62: 淡江大學 | D62: =ROUND(ABS(淡江大學_p5!D54),0) -> 205619 | E62: =ROUND(ABS(淡江大學_p5!E54),0) -> 145828 | F62: =ROUND(ABS(淡江大學_p5!F54),0) -> 144078 | G62: =ROUND(ABS(淡江大學_p5!G54),0) -> 142327 | H62: =ROUND(ABS(淡江大學_p5!H54),0) -> 140577 | I62: =ROUND(ABS(淡江大學_p5!I54),0) -> 138827 | J62: =ROUND(ABS(淡江大學_p5!J54),0) -> 137076 | K62: =ROUND(ABS(淡江大學_p5!K54),0) -> 135326 | ... W62: =ROUND(ABS(淡江大學_p5!W54),0) -> 123043
B63: 淡江大學 | D63: =ROUND(ABS(淡江大學_p4!D54),0) -> 192635 | E63: =ROUND(ABS(淡江大學_p4!E54),0) -> 132845 | F63: =ROUND(ABS(淡江大學_p4!F54),0) -> 131094 | G63: =ROUND(ABS(淡江大學_p4!G54),0) -> 129344 | H63: =ROUND(ABS(淡江大學_p4!H54),0) -> 127594 | I63: =ROUND(ABS(淡江大學_p4!I54),0) -> 125843 | J63: =ROUND(ABS(淡江大學_p4!J54),0) -> 124093 | K63: =ROUND(ABS(淡江大學_p4!K54),0) -> 122342 | ... W63: =ROUND(ABS(淡江大學_p4!W54),0) -> 110060
B64: 淡江大學 | D64: =ROUND(ABS(淡江大學_p3!D54),0) -> 179652 | E64: =ROUND(ABS(淡江大學_p3!E54),0) -> 119862 | F64: =ROUND(ABS(淡江大學_p3!F54),0) -> 118111 | G64: =ROUND(ABS(淡江大學_p3!G54),0) -> 116361 | H64: =ROUND(ABS(淡江大學_p3!H54),0) -> 114610 | I64: =ROUND(ABS(淡江大學_p3!I54),0) -> 112860 | J64: =ROUND(ABS(淡江大學_p3!J54),0) -> 111109 | K64: =ROUND(ABS(淡江大學_p3!K54),0) -> 109359 | ... W64: =ROUND(ABS(淡江大學_p3!W54),0) -> 97076
B65: 淡江大學 | D65: =ROUND(ABS(淡江大學_p6!D54),0) -> 218602 | E65: =ROUND(ABS(淡江大學_p6!E54),0) -> 158811 | F65: =ROUND(ABS(淡江大學_p6!F54),0) -> 157061 | G65: =ROUND(ABS(淡江大學_p6!G54),0) -> 155311 | H65: =ROUND(ABS(淡江大學_p6!H54),0) -> 153560 | I65: =ROUND(ABS(淡江大學_p6!I54),0) -> 151810 | J65: =ROUND(ABS(淡江大學_p6!J54),0) -> 150059 | K65: =ROUND(ABS(淡江大學_p6!K54),0) -> 148309 | ... W65: =ROUND(ABS(淡江大學_p6!W54),0) -> 136026
C66: 所得稅/年總計 | D66: =SUM(D60:D65) -> 1272662 | E66: =SUM(E60:E65) -> 913919 | F66: =SUM(F60:F65) -> 903416 | G66: =SUM(G60:G65) -> 892914 | H66: =SUM(H60:H65) -> 882412 | I66: =SUM(I60:I65) -> 871909 | J66: =SUM(J60:J65) -> 861406 | K66: =SUM(K60:K65) -> 850904 | ... W66: =SUM(W60:W65) -> 777207
C67: 年份 | D67: 2020 | E67: 2021 | F67: 2022 | G67: 2023 | H67: 2024 | I67: 2025 | J67: 2026 | K67: 2027 | L67: 2028 | M67: 2029 | N67: 2030 | O67: 2031 | P67: 2032 | Q67: 2033 | R67: 2034 | S67: 2035 | T67: 2036 | U67: 2037 | V67: 2038 | W67: 2039
C68: 設備折舊
B69: 淡江大學 | D69: =ROUND(ABS(淡江大學_p8!D67),0) -> 697760 | E69: =ROUND(ABS(淡江大學_p8!E67),0) -> 697760 | F69: =ROUND(ABS(淡江大學_p8!F67),0) -> 697760 | G69: =ROUND(ABS(淡江大學_p8!G67),0) -> 697760 | H69: =ROUND(ABS(淡江大學_p8!H67),0) -> 697760 | I69: =ROUND(ABS(淡江大學_p8!I67),0) -> 697760 | J69: =ROUND(ABS(淡江大學_p8!J67),0) -> 697760 | K69: =ROUND(ABS(淡江大學_p8!K67),0) -> 697760 | ... W69: =ROUND(ABS(淡江大學_p8!W67),0) -> 697760
B70: 淡江大學 | D70: =ROUND(ABS(淡江大學_p7!D67),0) -> 760060 | E70: =ROUND(ABS(淡江大學_p7!E67),0) -> 760060 | F70: =ROUND(ABS(淡江大學_p7!F67),0) -> 760060 | G70: =ROUND(ABS(淡江大學_p7!G67),0) -> 760060 | H70: =ROUND(ABS(淡江大學_p7!H67),0) -> 760060 | I70: =ROUND(ABS(淡江大學_p7!I67),0) -> 760060 | J70: =ROUND(ABS(淡江大學_p7!J67),0) -> 760060 | K70: =ROUND(ABS(淡江大學_p7!K67),0) -> 760060 | ... W70: =ROUND(ABS(淡江大學_p7!W67),0) -> 760060
B71: 淡江大學 | D71: =ROUND(ABS(淡江大學_p5!D67),0) -> 884660 | E71: =ROUND(ABS(淡江大學_p5!E67),0) -> 884660 | F71: =ROUND(ABS(淡江大學_p5!F67),0) -> 884660 | G71: =ROUND(ABS(淡江大學_p5!G67),0) -> 884660 | H71: =ROUND(ABS(淡江大學_p5!H67),0) -> 884660 | I71: =ROUND(ABS(淡江大學_p5!I67),0) -> 884660 | J71: =ROUND(ABS(淡江大學_p5!J67),0) -> 884660 | K71: =ROUND(ABS(淡江大學_p5!K67),0) -> 884660 | ... W71: =ROUND(ABS(淡江大學_p5!W67),0) -> 884660
B72: 淡江大學 | D72: =ROUND(ABS(淡江大學_p4!D67),0) -> 946960 | E72: =ROUND(ABS(淡江大學_p4!E67),0) -> 946960 | F72: =ROUND(ABS(淡江大學_p4!F67),0) -> 946960 | G72: =ROUND(ABS(淡江大學_p4!G67),0) -> 946960 | H72: =ROUND(ABS(淡江大學_p4!H67),0) -> 946960 | I72: =ROUND(ABS(淡江大學_p4!I67),0) -> 946960 | J72: =ROUND(ABS(淡江大學_p4!J67),0) -> 946960 | K72: =ROUND(ABS(淡江大學_p4!K67),0) -> 946960 | ... W72: =ROUND(ABS(淡江大學_p4!W67),0) -> 946960
B73: 淡江大學 | D73: =ROUND(ABS(淡江大學_p3!D67),0) -> 1009260 | E73: =ROUND(ABS(淡江大學_p3!E67),0) -> 1009260 | F73: =ROUND(ABS(淡江大學_p3!F67),0) -> 1009260 | G73: =ROUND(ABS(淡江大學_p3!G67),0) -> 1009260 | H73: =ROUND(ABS(淡江大學_p3!H67),0) -> 1009260 | I73: =ROUND(ABS(淡江大學_p3!I67),0) -> 1009260 | J73: =ROUND(ABS(淡江大學_p3!J67),0) -> 1009260 | K73: =ROUND(ABS(淡江大學_p3!K67),0) -> 1009260 | ... W73: =ROUND(ABS(淡江大學_p3!W67),0) -> 1009260
B74: 淡江大學 | D74: =ROUND(ABS(淡江大學_p6!D67),0) -> 822360 | E74: =ROUND(ABS(淡江大學_p6!E67),0) -> 822360 | F74: =ROUND(ABS(淡江大學_p6!F67),0) -> 822360 | G74: =ROUND(ABS(淡江大學_p6!G67),0) -> 822360 | H74: =ROUND(ABS(淡江大學_p6!H67),0) -> 822360 | I74: =ROUND(ABS(淡江大學_p6!I67),0) -> 822360 | J74: =ROUND(ABS(淡江大學_p6!J67),0) -> 822360 | K74: =ROUND(ABS(淡江大學_p6!K67),0) -> 822360 | ... W74: =ROUND(ABS(淡江大學_p6!W67),0) -> 822360
C75: 設備折舊/年總計 | D75: =SUM(D69:D74) -> 5121060 | E75: =SUM(E69:E74) -> 5121060 | F75: =SUM(F69:F74) -> 5121060 | G75: =SUM(G69:G74) -> 5121060 | H75: =SUM(H69:H74) -> 5121060 | I75: =SUM(I69:I74) -> 5121060 | J75: =SUM(J69:J74) -> 5121060 | K75: =SUM(K69:K74) -> 5121060 | ... W75: =SUM(W69:W74) -> 5121060
B77: 貸款成數(%) | C77: 0.85
B78: 還款期數 | C78: 10
B79: 股利比率(%) | C79: 0.9
B80: 年底減資攤還期數 | C80: 4
B81: 銀行利率(%) | C81: 0.03
C82: 年份 | D82: 2020 | E82: 2021 | F82: 2022 | G82: 2023 | H82: 2024 | I82: 2025 | J82: 2026 | K82: 2027 | L82: 2028 | M82: 2029 | N82: 2030 | O82: 2031 | P82: 2032 | Q82: 2033 | R82: 2034 | S82: 2035 | T82: 2036 | U82: 2037 | V82: 2038 | W82: 2039
B83: 0
B84: (Unit : Currency) | C84: 0 | D84: 1 | E84: 2 | F84: 3 | G84: 4 | H84: 5 | I84: 6 | J84: 7 | K84: 8 | L84: 9 | M84: 10 | N84: 11 | O84: 12 | P84: 13 | Q84: 14 | R84: 15 | S84: 16 | T84: 17 | U84: 18 | V84: 19 | W84: 20
B85: 發電度數(KWH) | C85: 0 | D85: =D12 -> 3249192 | E85: =E12 -> 3236064 | F85: =F12 -> 3222936 | G85: =G12 -> 3209808 | H85: =H12 -> 3196680 | I85: =I12 -> 3183552 | J85: =J12 -> 3170424 | K85: =K12 -> 3157296 | ... W85: =W12 -> 2999760
B86: Inflow : 電費收入 | C86: - | D86: =D21 -> 12996768 | E86: =E21 -> 12944256 | F86: =F21 -> 12891744 | G86: =G21 -> 12839232 | H86: =H21 -> 12786720 | I86: =I21 -> 12734208 | J86: =J21 -> 12681696 | K86: =K21 -> 12629184 | ... W86: =W21 -> 11999034
B87: Inflow : 政府補助 | C87: - | G87: - | H87: - | I87: - | J87: - | K87: - | L87: - | M87: - | N87: - | O87: - | P87: - | Q87: - | R87: - | S87: - | T87: - | U87: - | V87: - | W87: -
B88: Inflow : 銀行借款
B89: Outflow : 設備費用 | C89: =-SUM(D75:W75) -> -102421200
B90: Outflow : 設備放置區域租金 | C90: - | D90: =-D30 -> -1741206 | E90: =-E30 -> -1741206 | F90: =-F30 -> -1741206 | G90: =-G30 -> -1741206 | H90: =-H30 -> -1741206 | I90: =-I30 -> -1741206 | J90: =-J30 -> -1741206 | K90: =-K30 -> -1741206 | ... W90: =-W30 -> -1741206
B91: Outflow : 返還借款
B92: Outflow : 利息費用 | C92: -
B93: Outflow : 維運費 | C93: - | D93: =-D39 -> -1046640 | E93: =-E39 -> -1046640 | F93: =-F39 -> -1046640 | G93: =-G39 -> -1046640 | H93: =-H39 -> -1046640 | I93: =-I39 -> -1046640 | J93: =-J39 -> -1046640 | K93: =-K39 -> -1046640 | ... W93: =-W39 -> -1046640
B94: Outflow : 保險費 | C94: - | D94: =-D48 -> -204095 | E94: =-E48 -> -204095 | F94: =-F48 -> -204095 | G94: =-G48 -> -204095 | H94: =-H48 -> -204095 | I94: =-I48 -> -204095 | J94: =-J48 -> -204095 | K94: =-K48 -> -204095 | ... W94: =-W48 -> -204095
B95: Outflow : 模組回收費 | D95: =-D57 -> -261660 | E95: =-E57 -> -261660 | F95: =-F57 -> -261660 | G95: =-G57 -> -261660 | H95: =-H57 -> -261660 | I95: =-I57 -> -261660 | J95: =-J57 -> -261660 | K95: =-K57 -> -261660 | ... W95: =-W57 -> 0
B96: Outflow : 其它費用(人事薪資…等)
B97: 1%管理費
B98: 績效獎金
B99: 所得稅20% | D99: =-D122 -> -402073.28 | E99: =-E122 -> -443805.69 | F99: =-F122 -> -485538.1 | G99: =-G122 -> -527270.52 | H99: =-H122 -> -569002.93 | I99: =-I122 -> -610735.34 | J99: =-J122 -> -652467.75 | K99: =-K122 -> -694200.16 | ... W99: =-W122 -> -777206.6
B100: 現金流 | C100: =C89 -> -102421200 | D100: =SUM(D86:D99) -> 9341093.7 | E100: =SUM(E86:E99) -> 9246849.3 | F100: =SUM(F86:F99) -> 9152604.9 | G100: =SUM(G86:G99) -> 9058360.5 | H100: =SUM(H86:H99) -> 8964116.1 | I100: =SUM(I86:I99) -> 8869871.7 | J100: =SUM(J86:J99) -> 8775627.2 | K100: =SUM(K86:K99) -> 8681382.8 | ... W100: =SUM(W86:W99) -> 8229886.4
B101: 累計現金流 | D101: =C55+D55 -> 43610 | E101: =D56+E55 -> 87220 | F101: =E56+F55 -> 87220 | G101: =F56+G55 -> 87220 | H101: =G56+H55 -> 87220 | I101: =H56+I55 -> 87220 | J101: =I56+J55 -> 87220 | K101: =J56+K55 -> 87220 | L101: =K56+L55 -> 87220 | ... W101: =V56+W55 -> 0
B102: 回收年限評估 | D102: =IF((D56)>0,"回收","未回收") -> 回收 | E102: =IF((E56)>0,"回收","未回收") -> 回收 | F102: =IF((F56)>0,"回收","未回收") -> 回收 | G102: =IF((G56)>0,"回收","未回收") -> 回收 | H102: =IF((H56)>0,"回收","未回收") -> 回收 | I102: =IF((I56)>0,"回收","未回收") -> 回收 | J102: =IF((J56)>0,"回收","未回收") -> 回收 | K102: =IF((K56)>0,"回收","未回收") -> 回收 | ... W102: =IF((W56)>0,"回收","未回收") -> 未回收
B103: 專案法IRR | C103: =IRR(C100:W100) -> 0.057801814
C105: 年份 | D105: 2020 | E105: 2021 | F105: 2022 | G105: 2023 | H105: 2024 | I105: 2025 | J105: 2026 | K105: 2027 | L105: 2028 | M105: 2029 | N105: 2030 | O105: 2031 | P105: 2032 | Q105: 2033 | R105: 2034 | S105: 2035 | T105: 2036 | U105: 2037 | V105: 2038 | W105: 2039
...

Sheet 淡江大學_p3
B1: 電站基本資料 | F1: 說明 | P1: =1-D11 -> 0.99 | Q1: =P1-$D12 -> 0.986 | R1: =Q1-$D12 -> 0.982 | S1: =R1-$D12 -> 0.978 | T1: =S1-$D12 -> 0.974 | U1: =T1-$D12 -> 0.97 | V1: =U1-$D12 -> 0.966 | W1: =V1-$D12 -> 0.962 | X1: =W1-$D12 -> 0.958 | ... AI1: =AH1-$D12 -> 0.914
B2: 電站名稱 | C2: 淡江大學 | D2: - | E2: - | F2: 填入本案場名稱
B3: 電站壽命 | C3: 20 | D3: - | E3: - | F3: 預設 20 年，代表財務評估年期。若合約年限不同可依實際情況修改
B4: 建置量(kWp) | C4: 436.1 | D4: - | E4: - | F4: 填入裝置容量（kWp），通常由設計圖面或報價書取得 | M4: 情境編號: 3
B5: 起始年度 | C5: 2020 | D5: 結束年度 | E5: 2039 | F5: 填入電站預計掛表的西元年份（例：2025）。結束年度會自動計算 | M5: 第2次滾算摘要
M6: 價金: 31000
B7: 綜合損益表 | M7: 專案IRR: 3.75
B8: 收入 | M8: 權益法IRR: 8.21
B9: 收支項目 | C9: 相關參數 | D9: 參數數值 | E9: 年限 | F9: 說明 | M9: 利潤率: 30.00%
B10: 電費收入 | C10: 年度AC併網總發電量 | D10: 547002 | E10: 20 | F10: 預估年發電量（kWh），通常來自 PVsyst 模擬或估算：裝置容量 × 年日照時數 × 系統效率 | M10: 第2次滾算，減少 2000 元 - 現金模式，每次減少 2000 元
C11: 首年衰退率 | D11: 0.01 | F11: 第一年發電衰退比率，請填小數（例：1% → 填 0.01）。一般首年衰退約 1~2%(請參考模組規格書)
C12: 次年衰退率 | D12: 0.004 | F12: 第二年起每年固定衰退比率，請填小數（例：0.4% → 填 0.004）。一般約 0.4~0.7%(請參考模組規格書)
C13: 躉售費率(FIT) / 綠電費率 | D13: 4 | F13: 與台電簽訂的躉購費率或綠電合約費率，單位：元/度。請參考台電公告或合約內容
B14: 支出
B15: 收支項目 | C15: 相關參數 | D15: 參數數值 | E15: 攤提年限 | F15: 說明
B16: 設備費用(價金) | C16: 每kWp設備成本 | D16: 31000 | E16: 20 | F16: 每峰瓩設備成本（元/kWp），包含模組、逆變器、支架等硬體，不含工程施工費
C17: 信邦利潤率(ex:20%填0.2) | D17: 0.3 | F17: 公司在設備費用上加計的利潤比率，請填小數（例：20% → 填 0.2）
C18: 開發費 | D18: 2000 | F18: 前期開發費用（元），含可行性評估、申請規費、地主溝通等。若無則填 0
B19: 租金費用 | C19: 租金計算方式 | D19: 1 | E19: 20 | F19: 填 1 = 固定年租金（需填方式1參數）；填 2 = 依電費收入抽成（需填方式2參數）
C20: 【方式1參數】每年相同價格 | D20: 290201 | E20: 20 | F20: 租金計算方式選「1」時填寫，固定年租金金額（元/年），套用至整個電站壽命期
C21: 【方式2參數】抽成比率 | D21: 0 | E21: 20 | F21: 租金計算方式選「2」時填寫，請填小數（例：10% → 填 0.1）。租金 = 當年電費收入 × 抽成比率
B22: 運維費用 | C22: 每kw運維成本 | D22: 400 | E22: 20 | F22: 每峰瓩每年運維費用（元/kWp/年），含清洗、巡檢、維修等。
B23: 保險費用 | C23: 占整體設備費用比例 | D23: 0.003 | E23: 20 | F23: 保險費佔設備總費用比率，填小數（例：0.3% → 填 0.003）。預設 0.003，可依投保條件調整
B24: 模組回收費用 | C24: 每kw模組回收成本 | D24: 1000 | E24: 10 | F24: 每峰瓩模組廢棄回收費用（元/kWp），於第 1~10 年計提（攤提 10 年）。
B25: 利息費用 | C25: 銀行利率 | D25: 0.0256 | E25: 20 | F25: 向銀行貸款的年利率，填小數（例：2.56% → 填 0.0256）。請依銀行核准利率填入
B26: 所得稅 | C26: 所得稅率 | D26: 0.2 | E26: 20 | F26: 公司所得稅率，填小數（例：20% → 填 0.2）。預設 0.2，通常不需更改
B29: 現金流量表
B30: 金流項目 | C30: 相關參數 | D30: 參數數值 | F30: 說明
B31: 貸款成數 | C31: 占總設備費用比例 | D31: 0.8 | F31: 貸款佔設備總費用比例，填小數（例：80% → 填 0.8）。預設 0.8 代表貸八成、自備二成
B32: 貸款還款 | C32: 攤還期數 | D32: 15 | F32: 貸款還款年數（年）。預設 15 年，代表分 15 年平均攤還本金
B33: 現金股利 | C33: 股利比率 | D33: 0.9 | F33: 稅後現金流中分配給股東的比例，填小數（例：90% → 填 0.9）
B34: 年底減資 | C34: 攤還期數 | D34: 4 | F34: 年底減資返還股東的年數。預設 4 年，代表 倒數 4 年進行減資，加速資金返還
C37: 年份 | D37: 2020 | E37: 2021 | F37: 2022 | G37: 2023 | H37: 2024 | I37: 2025 | J37: 2026 | K37: 2027 | L37: 2028 | M37: 2029 | N37: 2030 | O37: 2031 | P37: 2032 | Q37: 2033 | R37: 2034 | S37: 2035 | T37: 2036 | U37: 2037 | V37: 2038 | W37: 2039
B38: 0
B39: (Unit : Currency) | C39: 0 | D39: 1 | E39: 2 | F39: 3 | G39: 4 | H39: 5 | I39: 6 | J39: 7 | K39: 8 | L39: 9 | M39: 10 | N39: 11 | O39: 12 | P39: 13 | Q39: 14 | R39: 15 | S39: 16 | T39: 17 | U39: 18 | V39: 19 | W39: 20
B40: 發電度數(KWH) | C40: 0 | D40: =$D$10*P1 -> 541531.98 | E40: =$D$10*Q1 -> 539343.97 | F40: =$D$10*R1 -> 537155.96 | G40: =$D$10*S1 -> 534967.96 | H40: =$D$10*T1 -> 532779.95 | I40: =$D$10*U1 -> 530591.94 | J40: =$D$10*V1 -> 528403.93 | K40: =$D$10*W1 -> 526215.92 | ... W40: =$D$10*AI1 -> 499959.83
B41: Inflow : 電費收入 | C41: - | D41: =D40*$D$13 -> 2166127.9 | E41: =E40*$D$13 -> 2157375.9 | F41: =F40*$D$13 -> 2148623.9 | G41: =G40*$D$13 -> 2139871.8 | H41: =H40*$D$13 -> 2131119.8 | I41: =I40*$D$13 -> 2122367.8 | J41: =J40*$D$13 -> 2113615.7 | K41: =K40*$D$13 -> 2104863.7 | ... W41: =W40*$D$13 -> 1999839.3
B42: Inflow : 政府補助 | C42: - | G42: - | H42: - | I42: - | J42: - | K42: - | L42: - | M42: - | N42: - | O42: - | P42: - | Q42: - | R42: - | S42: - | T42: - | U42: - | V42: - | W42: -
B43: Inflow : 銀行借款
B44: Outflow : 設備費用 | C44: =-(D16/(1-D17)+D18)*C4 -> -20185200
B45: Outflow : 設備放置區域租金 | C45: - | D45: -290201 | E45: -290201 | F45: -290201 | G45: -290201 | H45: -290201 | I45: -290201 | J45: -290201 | K45: -290201 | L45: -290201 | M45: -290201 | N45: -290201 | O45: -290201 | P45: -290201 | Q45: -290201 | R45: -290201 | S45: -290201 | T45: -290201 | U45: -290201 | V45: -290201 | W45: -290201
B46: Outflow : 返還借款
B47: Outflow : 利息費用 | C47: -
B48: Outflow : 維運費 | C48: - | D48: -174440 | E48: -174440 | F48: -174440 | G48: -174440 | H48: -174440 | I48: -174440 | J48: -174440 | K48: -174440 | L48: -174440 | M48: -174440 | N48: -174440 | O48: -174440 | P48: -174440 | Q48: -174440 | R48: -174440 | S48: -174440 | T48: -174440 | U48: -174440 | V48: -174440 | W48: -174440
B49: Outflow : 保險費 | C49: - | D49: -40557.3 | E49: -40557.3 | F49: -40557.3 | G49: -40557.3 | H49: -40557.3 | I49: -40557.3 | J49: -40557.3 | K49: -40557.3 | L49: -40557.3 | M49: -40557.3 | N49: -40557.3 | O49: -40557.3 | P49: -40557.3 | Q49: -40557.3 | R49: -40557.3 | S49: -40557.3 | T49: -40557.3 | U49: -40557.3 | V49: -40557.3 | W49: -40557.3
B50: Outflow : 模組回收費 | D50: -43610 | E50: -43610 | F50: -43610 | G50: -43610 | H50: -43610 | I50: -43610 | J50: -43610 | K50: -43610 | L50: -43610 | M50: -43610 | N50: 0 | O50: 0 | P50: 0 | Q50: 0 | R50: 0 | S50: 0 | T50: 0 | U50: 0 | V50: 0 | W50: 0
B51: Outflow : 其它費用(人事薪資…等)
B52: 1%管理費
B53: 績效獎金
B54: 所得稅20% | D54: =D77 -> -179652.12 | E54: =E77 -> -119861.52 | F54: =F77 -> -118111.11 | G54: =G77 -> -116360.7 | H54: =H77 -> -114610.3 | I54: =I77 -> -112859.89 | J54: =J77 -> -111109.49 | K54: =K77 -> -109359.08 | ... W54: =W77 -> -97076.202
B55: 現金流 | C55: =C44 -> -20185200 | D55: =SUM(D41:D54) -> 1437667.5 | E55: =SUM(E41:E54) -> 1488706.1 | F55: =SUM(F41:F54) -> 1481704.4 | G55: =SUM(G41:G54) -> 1474702.8 | H55: =SUM(H41:H54) -> 1467701.2 | I55: =SUM(I41:I54) -> 1460699.6 | J55: =SUM(J41:J54) -> 1453697.9 | K55: =SUM(K41:K54) -> 1446696.3 | ... W55: =SUM(W41:W54) -> 1397564.8
B56: 累計現金流 | D56: =C55+D55 -> -18747533 | E56: =D56+E55 -> -17258826 | F56: =E56+F55 -> -15777122 | G56: =F56+G55 -> -14302419 | H56: =G56+H55 -> -12834718 | I56: =H56+I55 -> -11374018 | J56: =I56+J55 -> -9920320.5 | K56: =J56+K55 -> -8473624.1 | L56: =K56+L55 -> -7033929.5 | ... X56: =W56+X55 -> 8689484.9
B57: 回收年限評估 | D57: =IF((D56)>0,"回收","未回收") -> 未回收 | E57: =IF((E56)>0,"回收","未回收") -> 未回收 | F57: =IF((F56)>0,"回收","未回收") -> 未回收 | G57: =IF((G56)>0,"回收","未回收") -> 未回收 | H57: =IF((H56)>0,"回收","未回收") -> 未回收 | I57: =IF((I56)>0,"回收","未回收") -> 未回收 | J57: =IF((J56)>0,"回收","未回收") -> 未回收 | K57: =IF((K56)>0,"回收","未回收") -> 未回收 | ... X57: =IF((X56)>0,"回收","未回收") -> 回收
B58: 專案法IRR | C58: =IRR(C55:W55) -> 0.037139919
C60: 年份 | D60: =D37 -> 2020 | E60: =E37 -> 2021 | F60: =F37 -> 2022 | G60: =G37 -> 2023 | H60: =H37 -> 2024 | I60: =I37 -> 2025 | J60: =J37 -> 2026 | K60: =K37 -> 2027 | ... W60: =W37 -> 2039
B61: 0 | T61: 償還年限
B62: (Unit : Currency) | C62: 0 | D62: 1 | E62: 2 | F62: 3 | G62: 4 | H62: 5 | I62: 6 | J62: 7 | K62: 8 | L62: 9 | M62: 10 | N62: 11 | O62: 12 | P62: 13 | Q62: 14 | R62: 15 | S62: 16 | T62: 17 | U62: 18 | V62: 19 | W62: 20
B63: 發電度數(KWH) | C63: 0 | D63: =D40 -> 541531.98 | E63: =E40 -> 539343.97 | F63: =F40 -> 537155.96 | G63: =G40 -> 534967.96 | H63: =H40 -> 532779.95 | I63: =I40 -> 530591.94 | J63: =J40 -> 528403.93 | K63: =K40 -> 526215.92 | ... W63: =W40 -> 499959.83
B64: Inflow : 電費收入 | C64: - | D64: =D41 -> 2166127.9 | E64: =E41 -> 2157375.9 | F64: =F41 -> 2148623.9 | G64: =G41 -> 2139871.8 | H64: =H41 -> 2131119.8 | I64: =I41 -> 2122367.8 | J64: =J41 -> 2113615.7 | K64: =K41 -> 2104863.7 | ... W64: =W41 -> 1999839.3
B65: Inflow : 政府補助 | C65: - | G65: - | H65: - | I65: - | J65: - | K65: - | L65: - | M65: - | N65: - | O65: - | P65: - | Q65: - | R65: - | S65: - | T65: - | U65: - | V65: - | W65: -
B66: Inflow : 銀行借款
B67: Outflow : 設備折舊 | D67: =$C$44/$E$16 -> -1009260 | E67: =$C$44/$E$16 -> -1009260 | F67: =$C$44/$E$16 -> -1009260 | G67: =$C$44/$E$16 -> -1009260 | H67: =$C$44/$E$16 -> -1009260 | I67: =$C$44/$E$16 -> -1009260 | J67: =$C$44/$E$16 -> -1009260 | K67: =$C$44/$E$16 -> -1009260 | ... W67: =$C$44/$E$16 -> -1009260
B68: Outflow : 設備放置區域租金 | C68: - | D68: =D44 -> 0 | E68: =E45 -> -290201 | F68: =F45 -> -290201 | G68: =G45 -> -290201 | H68: =H45 -> -290201 | I68: =I45 -> -290201 | J68: =J45 -> -290201 | K68: =K45 -> -290201 | L68: =L45 -> -290201 | ... W68: =W45 -> -290201
B69: Outflow : 返還借款
B70: Outflow : 利息費用 | C70: - | D70: 0 | E70: 0 | F70: 0 | G70: 0 | H70: 0 | I70: 0 | J70: 0 | K70: 0 | L70: 0 | M70: 0 | N70: 0 | O70: 0 | P70: 0 | Q70: 0 | R70: 0 | S70: 0 | T70: 0 | U70: 0 | V70: 0 | W70: 0
B71: Outflow : 維運費 | C71: - | D71: =D48 -> -174440 | E71: =E48 -> -174440 | F71: =F48 -> -174440 | G71: =G48 -> -174440 | H71: =H48 -> -174440 | I71: =I48 -> -174440 | J71: =J48 -> -174440 | K71: =K48 -> -174440 | ... W71: =W48 -> -174440
B72: Outflow : 保險費 | C72: - | D72: =D49 -> -40557.3 | E72: =E49 -> -40557.3 | F72: =F49 -> -40557.3 | G72: =G49 -> -40557.3 | H72: =H49 -> -40557.3 | I72: =I49 -> -40557.3 | J72: =J49 -> -40557.3 | K72: =K49 -> -40557.3 | ... W72: =W49 -> -40557.3
B73: Outflow : 模組回收費 | D73: =D50 -> -43610 | E73: =E50 -> -43610 | F73: =F50 -> -43610 | G73: =G50 -> -43610 | H73: =H50 -> -43610 | I73: =I50 -> -43610 | J73: =J50 -> -43610 | K73: =K50 -> -43610 | ... W73: =W50 -> 0
B74: Outflow : 其它費用(人事薪資…等)
B75: 1%管理費
B76: 稅前淨利 | D76: =SUM(D64:D75) -> 898260.62 | E76: =SUM(E64:E75) -> 599307.59 | F76: =SUM(F64:F75) -> 590555.56 | G76: =SUM(G64:G75) -> 581803.52 | H76: =SUM(H64:H75) -> 573051.49 | I76: =SUM(I64:I75) -> 564299.46 | J76: =SUM(J64:J75) -> 555547.43 | K76: =SUM(K64:K75) -> 546795.4 | ... X76: =SUM(X64:X75) -> 0
B77: 所得稅20% | D77: =-D76*0.2 -> -179652.12 | E77: =-E76*0.2 -> -119861.52 | F77: =-F76*0.2 -> -118111.11 | G77: =-G76*0.2 -> -116360.7 | H77: =-H76*0.2 -> -114610.3 | I77: =-I76*0.2 -> -112859.89 | J77: =-J76*0.2 -> -111109.49 | K77: =-K76*0.2 -> -109359.08 | ... X77: =-X76*0.2 -> 0
B78: 稅後淨利 | D78: =SUM(D76:D77) -> 718608.5 | E78: =SUM(E76:E77) -> 479446.07 | F78: =SUM(F76:F77) -> 472444.44 | G78: =SUM(G76:G77) -> 465442.82 | H78: =SUM(H76:H77) -> 458441.19 | I78: =SUM(I76:I77) -> 451439.57 | J78: =SUM(J76:J77) -> 444437.94 | K78: =SUM(K76:K77) -> 437436.32 | ... X78: =SUM(X76:X77) -> 0
B79: 累計現金流
B80: 回收年限評估

Sheet 淡江大學_p4
B1: 電站基本資料 | F1: 說明 | P1: =1-D11 -> 0.99 | Q1: =P1-$D12 -> 0.986 | R1: =Q1-$D12 -> 0.982 | S1: =R1-$D12 -> 0.978 | T1: =S1-$D12 -> 0.974 | U1: =T1-$D12 -> 0.97 | V1: =U1-$D12 -> 0.966 | W1: =V1-$D12 -> 0.962 | X1: =W1-$D12 -> 0.958 | ... AI1: =AH1-$D12 -> 0.914
B2: 電站名稱 | C2: 淡江大學 | D2: - | E2: - | F2: 填入本案場名稱
B3: 電站壽命 | C3: 20 | D3: - | E3: - | F3: 預設 20 年，代表財務評估年期。若合約年限不同可依實際情況修改
B4: 建置量(kWp) | C4: 436.1 | D4: - | E4: - | F4: 填入裝置容量（kWp），通常由設計圖面或報價書取得 | M4: 情境編號: 4
B5: 起始年度 | C5: 2020 | D5: 結束年度 | E5: 2039 | F5: 填入電站預計掛表的西元年份（例：2025）。結束年度會自動計算 | M5: 第3次滾算摘要
M6: 價金: 29000
B7: 綜合損益表 | M7: 專案IRR: 4.39
B8: 收入 | M8: 權益法IRR: 10.59
B9: 收支項目 | C9: 相關參數 | D9: 參數數值 | E9: 年限 | F9: 說明 | M9: 利潤率: 30.00%
B10: 電費收入 | C10: 年度AC併網總發電量 | D10: 547002 | E10: 20 | F10: 預估年發電量（kWh），通常來自 PVsyst 模擬或估算：裝置容量 × 年日照時數 × 系統效率 | M10: 第3次滾算，減少 2000 元 - 現金模式，每次減少 2000 元
C11: 首年衰退率 | D11: 0.01 | F11: 第一年發電衰退比率，請填小數（例：1% → 填 0.01）。一般首年衰退約 1~2%(請參考模組規格書)
C12: 次年衰退率 | D12: 0.004 | F12: 第二年起每年固定衰退比率，請填小數（例：0.4% → 填 0.004）。一般約 0.4~0.7%(請參考模組規格書)
C13: 躉售費率(FIT) / 綠電費率 | D13: 4 | F13: 與台電簽訂的躉購費率或綠電合約費率，單位：元/度。請參考台電公告或合約內容
B14: 支出
B15: 收支項目 | C15: 相關參數 | D15: 參數數值 | E15: 攤提年限 | F15: 說明
B16: 設備費用(價金) | C16: 每kWp設備成本 | D16: 29000 | E16: 20 | F16: 每峰瓩設備成本（元/kWp），包含模組、逆變器、支架等硬體，不含工程施工費
C17: 信邦利潤率(ex:20%填0.2) | D17: 0.3 | F17: 公司在設備費用上加計的利潤比率，請填小數（例：20% → 填 0.2）
C18: 開發費 | D18: 2000 | F18: 前期開發費用（元），含可行性評估、申請規費、地主溝通等。若無則填 0
B19: 租金費用 | C19: 租金計算方式 | D19: 1 | E19: 20 | F19: 填 1 = 固定年租金（需填方式1參數）；填 2 = 依電費收入抽成（需填方式2參數）
C20: 【方式1參數】每年相同價格 | D20: 290201 | E20: 20 | F20: 租金計算方式選「1」時填寫，固定年租金金額（元/年），套用至整個電站壽命期
C21: 【方式2參數】抽成比率 | D21: 0 | E21: 20 | F21: 租金計算方式選「2」時填寫，請填小數（例：10% → 填 0.1）。租金 = 當年電費收入 × 抽成比率
B22: 運維費用 | C22: 每kw運維成本 | D22: 400 | E22: 20 | F22: 每峰瓩每年運維費用（元/kWp/年），含清洗、巡檢、維修等。
B23: 保險費用 | C23: 占整體設備費用比例 | D23: 0.003 | E23: 20 | F23: 保險費佔設備總費用比率，填小數（例：0.3% → 填 0.003）。預設 0.003，可依投保條件調整
B24: 模組回收費用 | C24: 每kw模組回收成本 | D24: 1000 | E24: 10 | F24: 每峰瓩模組廢棄回收費用（元/kWp），於第 1~10 年計提（攤提 10 年）。
B25: 利息費用 | C25: 銀行利率 | D25: 0.0256 | E25: 20 | F25: 向銀行貸款的年利率，填小數（例：2.56% → 填 0.0256）。請依銀行核准利率填入
B26: 所得稅 | C26: 所得稅率 | D26: 0.2 | E26: 20 | F26: 公司所得稅率，填小數（例：20% → 填 0.2）。預設 0.2，通常不需更改
B29: 現金流量表
B30: 金流項目 | C30: 相關參數 | D30: 參數數值 | F30: 說明
B31: 貸款成數 | C31: 占總設備費用比例 | D31: 0.8 | F31: 貸款佔設備總費用比例，填小數（例：80% → 填 0.8）。預設 0.8 代表貸八成、自備二成
B32: 貸款還款 | C32: 攤還期數 | D32: 15 | F32: 貸款還款年數（年）。預設 15 年，代表分 15 年平均攤還本金
B33: 現金股利 | C33: 股利比率 | D33: 0.9 | F33: 稅後現金流中分配給股東的比例，填小數（例：90% → 填 0.9）
B34: 年底減資 | C34: 攤還期數 | D34: 4 | F34: 年底減資返還股東的年數。預設 4 年，代表 倒數 4 年進行減資，加速資金返還
C37: 年份 | D37: 2020 | E37: 2021 | F37: 2022 | G37: 2023 | H37: 2024 | I37: 2025 | J37: 2026 | K37: 2027 | L37: 2028 | M37: 2029 | N37: 2030 | O37: 2031 | P37: 2032 | Q37: 2033 | R37: 2034 | S37: 2035 | T37: 2036 | U37: 2037 | V37: 2038 | W37: 2039
B38: 0
B39: (Unit : Currency) | C39: 0 | D39: 1 | E39: 2 | F39: 3 | G39: 4 | H39: 5 | I39: 6 | J39: 7 | K39: 8 | L39: 9 | M39: 10 | N39: 11 | O39: 12 | P39: 13 | Q39: 14 | R39: 15 | S39: 16 | T39: 17 | U39: 18 | V39: 19 | W39: 20
B40: 發電度數(KWH) | C40: 0 | D40: =$D$10*P1 -> 541531.98 | E40: =$D$10*Q1 -> 539343.97 | F40: =$D$10*R1 -> 537155.96 | G40: =$D$10*S1 -> 534967.96 | H40: =$D$10*T1 -> 532779.95 | I40: =$D$10*U1 -> 530591.94 | J40: =$D$10*V1 -> 528403.93 | K40: =$D$10*W1 -> 526215.92 | ... W40: =$D$10*AI1 -> 499959.83
B41: Inflow : 電費收入 | C41: - | D41: =D40*$D$13 -> 2166127.9 | E41: =E40*$D$13 -> 2157375.9 | F41: =F40*$D$13 -> 2148623.9 | G41: =G40*$D$13 -> 2139871.8 | H41: =H40*$D$13 -> 2131119.8 | I41: =I40*$D$13 -> 2122367.8 | J41: =J40*$D$13 -> 2113615.7 | K41: =K40*$D$13 -> 2104863.7 | ... W41: =W40*$D$13 -> 1999839.3
B42: Inflow : 政府補助 | C42: - | G42: - | H42: - | I42: - | J42: - | K42: - | L42: - | M42: - | N42: - | O42: - | P42: - | Q42: - | R42: - | S42: - | T42: - | U42: - | V42: - | W42: -
B43: Inflow : 銀行借款
B44: Outflow : 設備費用 | C44: =-(D16/(1-D17)+D18)*C4 -> -18939200
B45: Outflow : 設備放置區域租金 | C45: - | D45: -290201 | E45: -290201 | F45: -290201 | G45: -290201 | H45: -290201 | I45: -290201 | J45: -290201 | K45: -290201 | L45: -290201 | M45: -290201 | N45: -290201 | O45: -290201 | P45: -290201 | Q45: -290201 | R45: -290201 | S45: -290201 | T45: -290201 | U45: -290201 | V45: -290201 | W45: -290201
B46: Outflow : 返還借款
B47: Outflow : 利息費用 | C47: -
B48: Outflow : 維運費 | C48: - | D48: -174440 | E48: -174440 | F48: -174440 | G48: -174440 | H48: -174440 | I48: -174440 | J48: -174440 | K48: -174440 | L48: -174440 | M48: -174440 | N48: -174440 | O48: -174440 | P48: -174440 | Q48: -174440 | R48: -174440 | S48: -174440 | T48: -174440 | U48: -174440 | V48: -174440 | W48: -174440
B49: Outflow : 保險費 | C49: - | D49: -37940.7 | E49: -37940.7 | F49: -37940.7 | G49: -37940.7 | H49: -37940.7 | I49: -37940.7 | J49: -37940.7 | K49: -37940.7 | L49: -37940.7 | M49: -37940.7 | N49: -37940.7 | O49: -37940.7 | P49: -37940.7 | Q49: -37940.7 | R49: -37940.7 | S49: -37940.7 | T49: -37940.7 | U49: -37940.7 | V49: -37940.7 | W49: -37940.7
B50: Outflow : 模組回收費 | D50: -43610 | E50: -43610 | F50: -43610 | G50: -43610 | H50: -43610 | I50: -43610 | J50: -43610 | K50: -43610 | L50: -43610 | M50: -43610 | N50: 0 | O50: 0 | P50: 0 | Q50: 0 | R50: 0 | S50: 0 | T50: 0 | U50: 0 | V50: 0 | W50: 0
B51: Outflow : 其它費用(人事薪資…等)
B52: 1%管理費
B53: 績效獎金
B54: 所得稅20% | D54: =D77 -> -192635.44 | E54: =E77 -> -132844.84 | F54: =F77 -> -131094.43 | G54: =G77 -> -129344.02 | H54: =H77 -> -127593.62 | I54: =I77 -> -125843.21 | J54: =J77 -> -124092.81 | K54: =K77 -> -122342.4 | ... W54: =W77 -> -110059.52
B55: 現金流 | C55: =C44 -> -18939200 | D55: =SUM(D41:D54) -> 1427300.8 | E55: =SUM(E41:E54) -> 1478339.4 | F55: =SUM(F41:F54) -> 1471337.7 | G55: =SUM(G41:G54) -> 1464336.1 | H55: =SUM(H41:H54) -> 1457334.5 | I55: =SUM(I41:I54) -> 1450332.8 | J55: =SUM(J41:J54) -> 1443331.2 | K55: =SUM(K41:K54) -> 1436329.6 | ... W55: =SUM(W41:W54) -> 1387198.1
B56: 累計現金流 | D56: =C55+D55 -> -17511899 | E56: =D56+E55 -> -16033560 | F56: =E56+F55 -> -14562222 | G56: =F56+G55 -> -13097886 | H56: =G56+H55 -> -11640552 | I56: =H56+I55 -> -10190219 | J56: =I56+J55 -> -8746887.5 | K56: =J56+K55 -> -7310557.9 | L56: =K56+L55 -> -5881229.9 | ... X56: =W56+X55 -> 9728150.5
B57: 回收年限評估 | D57: =IF((D56)>0,"回收","未回收") -> 未回收 | E57: =IF((E56)>0,"回收","未回收") -> 未回收 | F57: =IF((F56)>0,"回收","未回收") -> 未回收 | G57: =IF((G56)>0,"回收","未回收") -> 未回收 | H57: =IF((H56)>0,"回收","未回收") -> 未回收 | I57: =IF((I56)>0,"回收","未回收") -> 未回收 | J57: =IF((J56)>0,"回收","未回收") -> 未回收 | K57: =IF((K56)>0,"回收","未回收") -> 未回收 | ... X57: =IF((X56)>0,"回收","未回收") -> 回收
B58: 專案法IRR | C58: =IRR(C55:W55) -> 0.043586467
C60: 年份 | D60: =D37 -> 2020 | E60: =E37 -> 2021 | F60: =F37 -> 2022 | G60: =G37 -> 2023 | H60: =H37 -> 2024 | I60: =I37 -> 2025 | J60: =J37 -> 2026 | K60: =K37 -> 2027 | ... W60: =W37 -> 2039
B61: 0 | T61: 償還年限
B62: (Unit : Currency) | C62: 0 | D62: 1 | E62: 2 | F62: 3 | G62: 4 | H62: 5 | I62: 6 | J62: 7 | K62: 8 | L62: 9 | M62: 10 | N62: 11 | O62: 12 | P62: 13 | Q62: 14 | R62: 15 | S62: 16 | T62: 17 | U62: 18 | V62: 19 | W62: 20
B63: 發電度數(KWH) | C63: 0 | D63: =D40 -> 541531.98 | E63: =E40 -> 539343.97 | F63: =F40 -> 537155.96 | G63: =G40 -> 534967.96 | H63: =H40 -> 532779.95 | I63: =I40 -> 530591.94 | J63: =J40 -> 528403.93 | K63: =K40 -> 526215.92 | ... W63: =W40 -> 499959.83
B64: Inflow : 電費收入 | C64: - | D64: =D41 -> 2166127.9 | E64: =E41 -> 2157375.9 | F64: =F41 -> 2148623.9 | G64: =G41 -> 2139871.8 | H64: =H41 -> 2131119.8 | I64: =I41 -> 2122367.8 | J64: =J41 -> 2113615.7 | K64: =K41 -> 2104863.7 | ... W64: =W41 -> 1999839.3
B65: Inflow : 政府補助 | C65: - | G65: - | H65: - | I65: - | J65: - | K65: - | L65: - | M65: - | N65: - | O65: - | P65: - | Q65: - | R65: - | S65: - | T65: - | U65: - | V65: - | W65: -
B66: Inflow : 銀行借款
B67: Outflow : 設備折舊 | D67: =$C$44/$E$16 -> -946960 | E67: =$C$44/$E$16 -> -946960 | F67: =$C$44/$E$16 -> -946960 | G67: =$C$44/$E$16 -> -946960 | H67: =$C$44/$E$16 -> -946960 | I67: =$C$44/$E$16 -> -946960 | J67: =$C$44/$E$16 -> -946960 | K67: =$C$44/$E$16 -> -946960 | ... W67: =$C$44/$E$16 -> -946960
B68: Outflow : 設備放置區域租金 | C68: - | D68: =D44 -> 0 | E68: =E45 -> -290201 | F68: =F45 -> -290201 | G68: =G45 -> -290201 | H68: =H45 -> -290201 | I68: =I45 -> -290201 | J68: =J45 -> -290201 | K68: =K45 -> -290201 | L68: =L45 -> -290201 | ... W68: =W45 -> -290201
B69: Outflow : 返還借款
B70: Outflow : 利息費用 | C70: - | D70: 0 | E70: 0 | F70: 0 | G70: 0 | H70: 0 | I70: 0 | J70: 0 | K70: 0 | L70: 0 | M70: 0 | N70: 0 | O70: 0 | P70: 0 | Q70: 0 | R70: 0 | S70: 0 | T70: 0 | U70: 0 | V70: 0 | W70: 0
B71: Outflow : 維運費 | C71: - | D71: =D48 -> -174440 | E71: =E48 -> -174440 | F71: =F48 -> -174440 | G71: =G48 -> -174440 | H71: =H48 -> -174440 | I71: =I48 -> -174440 | J71: =J48 -> -174440 | K71: =K48 -> -174440 | ... W71: =W48 -> -174440
B72: Outflow : 保險費 | C72: - | D72: =D49 -> -37940.7 | E72: =E49 -> -37940.7 | F72: =F49 -> -37940.7 | G72: =G49 -> -37940.7 | H72: =H49 -> -37940.7 | I72: =I49 -> -37940.7 | J72: =J49 -> -37940.7 | K72: =K49 -> -37940.7 | ... W72: =W49 -> -37940.7
B73: Outflow : 模組回收費 | D73: =D50 -> -43610 | E73: =E50 -> -43610 | F73: =F50 -> -43610 | G73: =G50 -> -43610 | H73: =H50 -> -43610 | I73: =I50 -> -43610 | J73: =J50 -> -43610 | K73: =K50 -> -43610 | ... W73: =W50 -> 0
B74: Outflow : 其它費用(人事薪資…等)
B75: 1%管理費
B76: 稅前淨利 | D76: =SUM(D64:D75) -> 963177.22 | E76: =SUM(E64:E75) -> 664224.19 | F76: =SUM(F64:F75) -> 655472.16 | G76: =SUM(G64:G75) -> 646720.12 | H76: =SUM(H64:H75) -> 637968.09 | I76: =SUM(I64:I75) -> 629216.06 | J76: =SUM(J64:J75) -> 620464.03 | K76: =SUM(K64:K75) -> 611712 | ... X76: =SUM(X64:X75) -> 0
B77: 所得稅20% | D77: =-D76*0.2 -> -192635.44 | E77: =-E76*0.2 -> -132844.84 | F77: =-F76*0.2 -> -131094.43 | G77: =-G76*0.2 -> -129344.02 | H77: =-H76*0.2 -> -127593.62 | I77: =-I76*0.2 -> -125843.21 | J77: =-J76*0.2 -> -124092.81 | K77: =-K76*0.2 -> -122342.4 | ... X77: =-X76*0.2 -> 0
B78: 稅後淨利 | D78: =SUM(D76:D77) -> 770541.78 | E78: =SUM(E76:E77) -> 531379.35 | F78: =SUM(F76:F77) -> 524377.72 | G78: =SUM(G76:G77) -> 517376.1 | H78: =SUM(H76:H77) -> 510374.47 | I78: =SUM(I76:I77) -> 503372.85 | J78: =SUM(J76:J77) -> 496371.22 | K78: =SUM(K76:K77) -> 489369.6 | ... X78: =SUM(X76:X77) -> 0
B79: 累計現金流
B80: 回收年限評估

Sheet 淡江大學_p5
B1: 電站基本資料 | F1: 說明 | P1: =1-D11 -> 0.99 | Q1: =P1-$D12 -> 0.986 | R1: =Q1-$D12 -> 0.982 | S1: =R1-$D12 -> 0.978 | T1: =S1-$D12 -> 0.974 | U1: =T1-$D12 -> 0.97 | V1: =U1-$D12 -> 0.966 | W1: =V1-$D12 -> 0.962 | X1: =W1-$D12 -> 0.958 | ... AI1: =AH1-$D12 -> 0.914
B2: 電站名稱 | C2: 淡江大學 | D2: - | E2: - | F2: 填入本案場名稱
B3: 電站壽命 | C3: 20 | D3: - | E3: - | F3: 預設 20 年，代表財務評估年期。若合約年限不同可依實際情況修改
B4: 建置量(kWp) | C4: 436.1 | D4: - | E4: - | F4: 填入裝置容量（kWp），通常由設計圖面或報價書取得 | M4: 情境編號: 5
B5: 起始年度 | C5: 2020 | D5: 結束年度 | E5: 2039 | F5: 填入電站預計掛表的西元年份（例：2025）。結束年度會自動計算 | M5: 第4次滾算摘要
M6: 價金: 27000
B7: 綜合損益表 | M7: 專案IRR: 5.11
B8: 收入 | M8: 權益法IRR: 13.45
B9: 收支項目 | C9: 相關參數 | D9: 參數數值 | E9: 年限 | F9: 說明 | M9: 利潤率: 30.00%
B10: 電費收入 | C10: 年度AC併網總發電量 | D10: 547002 | E10: 20 | F10: 預估年發電量（kWh），通常來自 PVsyst 模擬或估算：裝置容量 × 年日照時數 × 系統效率 | M10: 第4次滾算，減少 2000 元 - 現金模式，每次減少 2000 元
C11: 首年衰退率 | D11: 0.01 | F11: 第一年發電衰退比率，請填小數（例：1% → 填 0.01）。一般首年衰退約 1~2%(請參考模組規格書)
C12: 次年衰退率 | D12: 0.004 | F12: 第二年起每年固定衰退比率，請填小數（例：0.4% → 填 0.004）。一般約 0.4~0.7%(請參考模組規格書)
C13: 躉售費率(FIT) / 綠電費率 | D13: 4 | F13: 與台電簽訂的躉購費率或綠電合約費率，單位：元/度。請參考台電公告或合約內容
B14: 支出
B15: 收支項目 | C15: 相關參數 | D15: 參數數值 | E15: 攤提年限 | F15: 說明
B16: 設備費用(價金) | C16: 每kWp設備成本 | D16: 27000 | E16: 20 | F16: 每峰瓩設備成本（元/kWp），包含模組、逆變器、支架等硬體，不含工程施工費
C17: 信邦利潤率(ex:20%填0.2) | D17: 0.3 | F17: 公司在設備費用上加計的利潤比率，請填小數（例：20% → 填 0.2）
C18: 開發費 | D18: 2000 | F18: 前期開發費用（元），含可行性評估、申請規費、地主溝通等。若無則填 0
B19: 租金費用 | C19: 租金計算方式 | D19: 1 | E19: 20 | F19: 填 1 = 固定年租金（需填方式1參數）；填 2 = 依電費收入抽成（需填方式2參數）
C20: 【方式1參數】每年相同價格 | D20: 290201 | E20: 20 | F20: 租金計算方式選「1」時填寫，固定年租金金額（元/年），套用至整個電站壽命期
C21: 【方式2參數】抽成比率 | D21: 0 | E21: 20 | F21: 租金計算方式選「2」時填寫，請填小數（例：10% → 填 0.1）。租金 = 當年電費收入 × 抽成比率
B22: 運維費用 | C22: 每kw運維成本 | D22: 400 | E22: 20 | F22: 每峰瓩每年運維費用（元/kWp/年），含清洗、巡檢、維修等。
B23: 保險費用 | C23: 占整體設備費用比例 | D23: 0.003 | E23: 20 | F23: 保險費佔設備總費用比率，填小數（例：0.3% → 填 0.003）。預設 0.003，可依投保條件調整
B24: 模組回收費用 | C24: 每kw模組回收成本 | D24: 1000 | E24: 10 | F24: 每峰瓩模組廢棄回收費用（元/kWp），於第 1~10 年計提（攤提 10 年）。
B25: 利息費用 | C25: 銀行利率 | D25: 0.0256 | E25: 20 | F25: 向銀行貸款的年利率，填小數（例：2.56% → 填 0.0256）。請依銀行核准利率填入
B26: 所得稅 | C26: 所得稅率 | D26: 0.2 | E26: 20 | F26: 公司所得稅率，填小數（例：20% → 填 0.2）。預設 0.2，通常不需更改
B29: 現金流量表
B30: 金流項目 | C30: 相關參數 | D30: 參數數值 | F30: 說明
B31: 貸款成數 | C31: 占總設備費用比例 | D31: 0.8 | F31: 貸款佔設備總費用比例，填小數（例：80% → 填 0.8）。預設 0.8 代表貸八成、自備二成
B32: 貸款還款 | C32: 攤還期數 | D32: 15 | F32: 貸款還款年數（年）。預設 15 年，代表分 15 年平均攤還本金
B33: 現金股利 | C33: 股利比率 | D33: 0.9 | F33: 稅後現金流中分配給股東的比例，填小數（例：90% → 填 0.9）
B34: 年底減資 | C34: 攤還期數 | D34: 4 | F34: 年底減資返還股東的年數。預設 4 年，代表 倒數 4 年進行減資，加速資金返還
C37: 年份 | D37: 2020 | E37: 2021 | F37: 2022 | G37: 2023 | H37: 2024 | I37: 2025 | J37: 2026 | K37: 2027 | L37: 2028 | M37: 2029 | N37: 2030 | O37: 2031 | P37: 2032 | Q37: 2033 | R37: 2034 | S37: 2035 | T37: 2036 | U37: 2037 | V37: 2038 | W37: 2039
B38: 0
B39: (Unit : Currency) | C39: 0 | D39: 1 | E39: 2 | F39: 3 | G39: 4 | H39: 5 | I39: 6 | J39: 7 | K39: 8 | L39: 9 | M39: 10 | N39: 11 | O39: 12 | P39: 13 | Q39: 14 | R39: 15 | S39: 16 | T39: 17 | U39: 18 | V39: 19 | W39: 20
B40: 發電度數(KWH) | C40: 0 | D40: =$D$10*P1 -> 541531.98 | E40: =$D$10*Q1 -> 539343.97 | F40: =$D$10*R1 -> 537155.96 | G40: =$D$10*S1 -> 534967.96 | H40: =$D$10*T1 -> 532779.95 | I40: =$D$10*U1 -> 530591.94 | J40: =$D$10*V1 -> 528403.93 | K40: =$D$10*W1 -> 526215.92 | ... W40: =$D$10*AI1 -> 499959.83
B41: Inflow : 電費收入 | C41: - | D41: =D40*$D$13 -> 2166127.9 | E41: =E40*$D$13 -> 2157375.9 | F41: =F40*$D$13 -> 2148623.9 | G41: =G40*$D$13 -> 2139871.8 | H41: =H40*$D$13 -> 2131119.8 | I41: =I40*$D$13 -> 2122367.8 | J41: =J40*$D$13 -> 2113615.7 | K41: =K40*$D$13 -> 2104863.7 | ... W41: =W40*$D$13 -> 1999839.3
B42: Inflow : 政府補助 | C42: - | G42: - | H42: - | I42: - | J42: - | K42: - | L42: - | M42: - | N42: - | O42: - | P42: - | Q42: - | R42: - | S42: - | T42: - | U42: - | V42: - | W42: -
B43: Inflow : 銀行借款
B44: Outflow : 設備費用 | C44: =-(D16/(1-D17)+D18)*C4 -> -17693200
B45: Outflow : 設備放置區域租金 | C45: - | D45: -290201 | E45: -290201 | F45: -290201 | G45: -290201 | H45: -290201 | I45: -290201 | J45: -290201 | K45: -290201 | L45: -290201 | M45: -290201 | N45: -290201 | O45: -290201 | P45: -290201 | Q45: -290201 | R45: -290201 | S45: -290201 | T45: -290201 | U45: -290201 | V45: -290201 | W45: -290201
B46: Outflow : 返還借款
B47: Outflow : 利息費用 | C47: -
B48: Outflow : 維運費 | C48: - | D48: -174440 | E48: -174440 | F48: -174440 | G48: -174440 | H48: -174440 | I48: -174440 | J48: -174440 | K48: -174440 | L48: -174440 | M48: -174440 | N48: -174440 | O48: -174440 | P48: -174440 | Q48: -174440 | R48: -174440 | S48: -174440 | T48: -174440 | U48: -174440 | V48: -174440 | W48: -174440
B49: Outflow : 保險費 | C49: - | D49: -35324.1 | E49: -35324.1 | F49: -35324.1 | G49: -35324.1 | H49: -35324.1 | I49: -35324.1 | J49: -35324.1 | K49: -35324.1 | L49: -35324.1 | M49: -35324.1 | N49: -35324.1 | O49: -35324.1 | P49: -35324.1 | Q49: -35324.1 | R49: -35324.1 | S49: -35324.1 | T49: -35324.1 | U49: -35324.1 | V49: -35324.1 | W49: -35324.1
B50: Outflow : 模組回收費 | D50: -43610 | E50: -43610 | F50: -43610 | G50: -43610 | H50: -43610 | I50: -43610 | J50: -43610 | K50: -43610 | L50: -43610 | M50: -43610 | N50: 0 | O50: 0 | P50: 0 | Q50: 0 | R50: 0 | S50: 0 | T50: 0 | U50: 0 | V50: 0 | W50: 0
B51: Outflow : 其它費用(人事薪資…等)
B52: 1%管理費
B53: 績效獎金
B54: 所得稅20% | D54: =D77 -> -205618.76 | E54: =E77 -> -145828.16 | F54: =F77 -> -144077.75 | G54: =G77 -> -142327.34 | H54: =H77 -> -140576.94 | I54: =I77 -> -138826.53 | J54: =J77 -> -137076.13 | K54: =K77 -> -135325.72 | ... W54: =W77 -> -123042.84
B55: 現金流 | C55: =C44 -> -17693200 | D55: =SUM(D41:D54) -> 1416934.1 | E55: =SUM(E41:E54) -> 1467972.6 | F55: =SUM(F41:F54) -> 1460971 | G55: =SUM(G41:G54) -> 1453969.4 | H55: =SUM(H41:H54) -> 1446967.8 | I55: =SUM(I41:I54) -> 1439966.1 | J55: =SUM(J41:J54) -> 1432964.5 | K55: =SUM(K41:K54) -> 1425962.9 | ... W55: =SUM(W41:W54) -> 1376831.4
B56: 累計現金流 | D56: =C55+D55 -> -16276266 | E56: =D56+E55 -> -14808293 | F56: =E56+F55 -> -13347322 | G56: =F56+G55 -> -11893353 | H56: =G56+H55 -> -10446385 | I56: =H56+I55 -> -9006419 | J56: =I56+J55 -> -7573454.5 | K56: =J56+K55 -> -6147491.7 | L56: =K56+L55 -> -4728530.4 | ... X56: =W56+X55 -> 10766816
B57: 回收年限評估 | D57: =IF((D56)>0,"回收","未回收") -> 未回收 | E57: =IF((E56)>0,"回收","未回收") -> 未回收 | F57: =IF((F56)>0,"回收","未回收") -> 未回收 | G57: =IF((G56)>0,"回收","未回收") -> 未回收 | H57: =IF((H56)>0,"回收","未回收") -> 未回收 | I57: =IF((I56)>0,"回收","未回收") -> 未回收 | J57: =IF((J56)>0,"回收","未回收") -> 未回收 | K57: =IF((K56)>0,"回收","未回收") -> 未回收 | ... X57: =IF((X56)>0,"回收","未回收") -> 回收
B58: 專案法IRR | C58: =IRR(C55:W55) -> 0.050729975
C60: 年份 | D60: =D37 -> 2020 | E60: =E37 -> 2021 | F60: =F37 -> 2022 | G60: =G37 -> 2023 | H60: =H37 -> 2024 | I60: =I37 -> 2025 | J60: =J37 -> 2026 | K60: =K37 -> 2027 | ... W60: =W37 -> 2039
B61: 0 | T61: 償還年限
B62: (Unit : Currency) | C62: 0 | D62: 1 | E62: 2 | F62: 3 | G62: 4 | H62: 5 | I62: 6 | J62: 7 | K62: 8 | L62: 9 | M62: 10 | N62: 11 | O62: 12 | P62: 13 | Q62: 14 | R62: 15 | S62: 16 | T62: 17 | U62: 18 | V62: 19 | W62: 20
B63: 發電度數(KWH) | C63: 0 | D63: =D40 -> 541531.98 | E63: =E40 -> 539343.97 | F63: =F40 -> 537155.96 | G63: =G40 -> 534967.96 | H63: =H40 -> 532779.95 | I63: =I40 -> 530591.94 | J63: =J40 -> 528403.93 | K63: =K40 -> 526215.92 | ... W63: =W40 -> 499959.83
B64: Inflow : 電費收入 | C64: - | D64: =D41 -> 2166127.9 | E64: =E41 -> 2157375.9 | F64: =F41 -> 2148623.9 | G64: =G41 -> 2139871.8 | H64: =H41 -> 2131119.8 | I64: =I41 -> 2122367.8 | J64: =J41 -> 2113615.7 | K64: =K41 -> 2104863.7 | ... W64: =W41 -> 1999839.3
B65: Inflow : 政府補助 | C65: - | G65: - | H65: - | I65: - | J65: - | K65: - | L65: - | M65: - | N65: - | O65: - | P65: - | Q65: - | R65: - | S65: - | T65: - | U65: - | V65: - | W65: -
B66: Inflow : 銀行借款
B67: Outflow : 設備折舊 | D67: =$C$44/$E$16 -> -884660 | E67: =$C$44/$E$16 -> -884660 | F67: =$C$44/$E$16 -> -884660 | G67: =$C$44/$E$16 -> -884660 | H67: =$C$44/$E$16 -> -884660 | I67: =$C$44/$E$16 -> -884660 | J67: =$C$44/$E$16 -> -884660 | K67: =$C$44/$E$16 -> -884660 | ... W67: =$C$44/$E$16 -> -884660
B68: Outflow : 設備放置區域租金 | C68: - | D68: =D44 -> 0 | E68: =E45 -> -290201 | F68: =F45 -> -290201 | G68: =G45 -> -290201 | H68: =H45 -> -290201 | I68: =I45 -> -290201 | J68: =J45 -> -290201 | K68: =K45 -> -290201 | L68: =L45 -> -290201 | ... W68: =W45 -> -290201
B69: Outflow : 返還借款
B70: Outflow : 利息費用 | C70: - | D70: 0 | E70: 0 | F70: 0 | G70: 0 | H70: 0 | I70: 0 | J70: 0 | K70: 0 | L70: 0 | M70: 0 | N70: 0 | O70: 0 | P70: 0 | Q70: 0 | R70: 0 | S70: 0 | T70: 0 | U70: 0 | V70: 0 | W70: 0
B71: Outflow : 維運費 | C71: - | D71: =D48 -> -174440 | E71: =E48 -> -174440 | F71: =F48 -> -174440 | G71: =G48 -> -174440 | H71: =H48 -> -174440 | I71: =I48 -> -174440 | J71: =J48 -> -174440 | K71: =K48 -> -174440 | ... W71: =W48 -> -174440
B72: Outflow : 保險費 | C72: - | D72: =D49 -> -35324.1 | E72: =E49 -> -35324.1 | F72: =F49 -> -35324.1 | G72: =G49 -> -35324.1 | H72: =H49 -> -35324.1 | I72: =I49 -> -35324.1 | J72: =J49 -> -35324.1 | K72: =K49 -> -35324.1 | ... W72: =W49 -> -35324.1
B73: Outflow : 模組回收費 | D73: =D50 -> -43610 | E73: =E50 -> -43610 | F73: =F50 -> -43610 | G73: =G50 -> -43610 | H73: =H50 -> -43610 | I73: =I50 -> -43610 | J73: =J50 -> -43610 | K73: =K50 -> -43610 | ... W73: =W50 -> 0
B74: Outflow : 其它費用(人事薪資…等)
B75: 1%管理費
B76: 稅前淨利 | D76: =SUM(D64:D75) -> 1028093.8 | E76: =SUM(E64:E75) -> 729140.79 | F76: =SUM(F64:F75) -> 720388.76 | G76: =SUM(G64:G75) -> 711636.72 | H76: =SUM(H64:H75) -> 702884.69 | I76: =SUM(I64:I75) -> 694132.66 | J76: =SUM(J64:J75) -> 685380.63 | K76: =SUM(K64:K75) -> 676628.6 | ... X76: =SUM(X64:X75) -> 0
B77: 所得稅20% | D77: =-D76*0.2 -> -205618.76 | E77: =-E76*0.2 -> -145828.16 | F77: =-F76*0.2 -> -144077.75 | G77: =-G76*0.2 -> -142327.34 | H77: =-H76*0.2 -> -140576.94 | I77: =-I76*0.2 -> -138826.53 | J77: =-J76*0.2 -> -137076.13 | K77: =-K76*0.2 -> -135325.72 | ... X77: =-X76*0.2 -> 0
B78: 稅後淨利 | D78: =SUM(D76:D77) -> 822475.06 | E78: =SUM(E76:E77) -> 583312.63 | F78: =SUM(F76:F77) -> 576311 | G78: =SUM(G76:G77) -> 569309.38 | H78: =SUM(H76:H77) -> 562307.75 | I78: =SUM(I76:I77) -> 555306.13 | J78: =SUM(J76:J77) -> 548304.5 | K78: =SUM(K76:K77) -> 541302.88 | ... X78: =SUM(X76:X77) -> 0
B79: 累計現金流
B80: 回收年限評估

Sheet 淡江大學_p7
B1: 電站基本資料 | F1: 說明 | P1: =1-D11 -> 0.99 | Q1: =P1-$D12 -> 0.986 | R1: =Q1-$D12 -> 0.982 | S1: =R1-$D12 -> 0.978 | T1: =S1-$D12 -> 0.974 | U1: =T1-$D12 -> 0.97 | V1: =U1-$D12 -> 0.966 | W1: =V1-$D12 -> 0.962 | X1: =W1-$D12 -> 0.958 | ... AI1: =AH1-$D12 -> 0.914
B2: 電站名稱 | C2: 淡江大學 | D2: - | E2: - | F2: 填入本案場名稱
B3: 電站壽命 | C3: 20 | D3: - | E3: - | F3: 預設 20 年，代表財務評估年期。若合約年限不同可依實際情況修改
B4: 建置量(kWp) | C4: 436.1 | D4: - | E4: - | F4: 填入裝置容量（kWp），通常由設計圖面或報價書取得 | M4: 情境編號: 7
B5: 起始年度 | C5: 2020 | D5: 結束年度 | E5: 2039 | F5: 填入電站預計掛表的西元年份（例：2025）。結束年度會自動計算 | M5: 第6次滾算摘要
M6: 價金: 23000
B7: 綜合損益表 | M7: 專案IRR: 6.82
B8: 收入 | M8: 權益法IRR: 21.53
B9: 收支項目 | C9: 相關參數 | D9: 參數數值 | E9: 年限 | F9: 說明 | M9: 利潤率: 30.00%
B10: 電費收入 | C10: 年度AC併網總發電量 | D10: 547002 | E10: 20 | F10: 預估年發電量（kWh），通常來自 PVsyst 模擬或估算：裝置容量 × 年日照時數 × 系統效率 | M10: 第6次滾算，減少 2000 元 - 現金模式，每次減少 2000 元
C11: 首年衰退率 | D11: 0.01 | F11: 第一年發電衰退比率，請填小數（例：1% → 填 0.01）。一般首年衰退約 1~2%(請參考模組規格書)
C12: 次年衰退率 | D12: 0.004 | F12: 第二年起每年固定衰退比率，請填小數（例：0.4% → 填 0.004）。一般約 0.4~0.7%(請參考模組規格書)
C13: 躉售費率(FIT) / 綠電費率 | D13: 4 | F13: 與台電簽訂的躉購費率或綠電合約費率，單位：元/度。請參考台電公告或合約內容
B14: 支出
B15: 收支項目 | C15: 相關參數 | D15: 參數數值 | E15: 攤提年限 | F15: 說明
B16: 設備費用(價金) | C16: 每kWp設備成本 | D16: 23000 | E16: 20 | F16: 每峰瓩設備成本（元/kWp），包含模組、逆變器、支架等硬體，不含工程施工費
C17: 信邦利潤率(ex:20%填0.2) | D17: 0.3 | F17: 公司在設備費用上加計的利潤比率，請填小數（例：20% → 填 0.2）
C18: 開發費 | D18: 2000 | F18: 前期開發費用（元），含可行性評估、申請規費、地主溝通等。若無則填 0
B19: 租金費用 | C19: 租金計算方式 | D19: 1 | E19: 20 | F19: 填 1 = 固定年租金（需填方式1參數）；填 2 = 依電費收入抽成（需填方式2參數）
C20: 【方式1參數】每年相同價格 | D20: 290201 | E20: 20 | F20: 租金計算方式選「1」時填寫，固定年租金金額（元/年），套用至整個電站壽命期
C21: 【方式2參數】抽成比率 | D21: 0 | E21: 20 | F21: 租金計算方式選「2」時填寫，請填小數（例：10% → 填 0.1）。租金 = 當年電費收入 × 抽成比率
B22: 運維費用 | C22: 每kw運維成本 | D22: 400 | E22: 20 | F22: 每峰瓩每年運維費用（元/kWp/年），含清洗、巡檢、維修等。
B23: 保險費用 | C23: 占整體設備費用比例 | D23: 0.003 | E23: 20 | F23: 保險費佔設備總費用比率，填小數（例：0.3% → 填 0.003）。預設 0.003，可依投保條件調整
B24: 模組回收費用 | C24: 每kw模組回收成本 | D24: 1000 | E24: 10 | F24: 每峰瓩模組廢棄回收費用（元/kWp），於第 1~10 年計提（攤提 10 年）。
B25: 利息費用 | C25: 銀行利率 | D25: 0.0256 | E25: 20 | F25: 向銀行貸款的年利率，填小數（例：2.56% → 填 0.0256）。請依銀行核准利率填入
B26: 所得稅 | C26: 所得稅率 | D26: 0.2 | E26: 20 | F26: 公司所得稅率，填小數（例：20% → 填 0.2）。預設 0.2，通常不需更改
B29: 現金流量表
B30: 金流項目 | C30: 相關參數 | D30: 參數數值 | F30: 說明
B31: 貸款成數 | C31: 占總設備費用比例 | D31: 0.8 | F31: 貸款佔設備總費用比例，填小數（例：80% → 填 0.8）。預設 0.8 代表貸八成、自備二成
B32: 貸款還款 | C32: 攤還期數 | D32: 15 | F32: 貸款還款年數（年）。預設 15 年，代表分 15 年平均攤還本金
B33: 現金股利 | C33: 股利比率 | D33: 0.9 | F33: 稅後現金流中分配給股東的比例，填小數（例：90% → 填 0.9）
B34: 年底減資 | C34: 攤還期數 | D34: 4 | F34: 年底減資返還股東的年數。預設 4 年，代表 倒數 4 年進行減資，加速資金返還
C37: 年份 | D37: 2020 | E37: 2021 | F37: 2022 | G37: 2023 | H37: 2024 | I37: 2025 | J37: 2026 | K37: 2027 | L37: 2028 | M37: 2029 | N37: 2030 | O37: 2031 | P37: 2032 | Q37: 2033 | R37: 2034 | S37: 2035 | T37: 2036 | U37: 2037 | V37: 2038 | W37: 2039
B38: 0
B39: (Unit : Currency) | C39: 0 | D39: 1 | E39: 2 | F39: 3 | G39: 4 | H39: 5 | I39: 6 | J39: 7 | K39: 8 | L39: 9 | M39: 10 | N39: 11 | O39: 12 | P39: 13 | Q39: 14 | R39: 15 | S39: 16 | T39: 17 | U39: 18 | V39: 19 | W39: 20
B40: 發電度數(KWH) | C40: 0 | D40: =$D$10*P1 -> 541531.98 | E40: =$D$10*Q1 -> 539343.97 | F40: =$D$10*R1 -> 537155.96 | G40: =$D$10*S1 -> 534967.96 | H40: =$D$10*T1 -> 532779.95 | I40: =$D$10*U1 -> 530591.94 | J40: =$D$10*V1 -> 528403.93 | K40: =$D$10*W1 -> 526215.92 | ... W40: =$D$10*AI1 -> 499959.83
B41: Inflow : 電費收入 | C41: - | D41: =D40*$D$13 -> 2166127.9 | E41: =E40*$D$13 -> 2157375.9 | F41: =F40*$D$13 -> 2148623.9 | G41: =G40*$D$13 -> 2139871.8 | H41: =H40*$D$13 -> 2131119.8 | I41: =I40*$D$13 -> 2122367.8 | J41: =J40*$D$13 -> 2113615.7 | K41: =K40*$D$13 -> 2104863.7 | ... W41: =W40*$D$13 -> 1999839.3
B42: Inflow : 政府補助 | C42: - | G42: - | H42: - | I42: - | J42: - | K42: - | L42: - | M42: - | N42: - | O42: - | P42: - | Q42: - | R42: - | S42: - | T42: - | U42: - | V42: - | W42: -
B43: Inflow : 銀行借款
B44: Outflow : 設備費用 | C44: =-(D16/(1-D17)+D18)*C4 -> -15201200
B45: Outflow : 設備放置區域租金 | C45: - | D45: -290201 | E45: -290201 | F45: -290201 | G45: -290201 | H45: -290201 | I45: -290201 | J45: -290201 | K45: -290201 | L45: -290201 | M45: -290201 | N45: -290201 | O45: -290201 | P45: -290201 | Q45: -290201 | R45: -290201 | S45: -290201 | T45: -290201 | U45: -290201 | V45: -290201 | W45: -290201
B46: Outflow : 返還借款
B47: Outflow : 利息費用 | C47: -
B48: Outflow : 維運費 | C48: - | D48: -174440 | E48: -174440 | F48: -174440 | G48: -174440 | H48: -174440 | I48: -174440 | J48: -174440 | K48: -174440 | L48: -174440 | M48: -174440 | N48: -174440 | O48: -174440 | P48: -174440 | Q48: -174440 | R48: -174440 | S48: -174440 | T48: -174440 | U48: -174440 | V48: -174440 | W48: -174440
B49: Outflow : 保險費 | C49: - | D49: -30090.9 | E49: -30090.9 | F49: -30090.9 | G49: -30090.9 | H49: -30090.9 | I49: -30090.9 | J49: -30090.9 | K49: -30090.9 | L49: -30090.9 | M49: -30090.9 | N49: -30090.9 | O49: -30090.9 | P49: -30090.9 | Q49: -30090.9 | R49: -30090.9 | S49: -30090.9 | T49: -30090.9 | U49: -30090.9 | V49: -30090.9 | W49: -30090.9
B50: Outflow : 模組回收費 | D50: -43610 | E50: -43610 | F50: -43610 | G50: -43610 | H50: -43610 | I50: -43610 | J50: -43610 | K50: -43610 | L50: -43610 | M50: -43610 | N50: 0 | O50: 0 | P50: 0 | Q50: 0 | R50: 0 | S50: 0 | T50: 0 | U50: 0 | V50: 0 | W50: 0
B51: Outflow : 其它費用(人事薪資…等)
B52: 1%管理費
B53: 績效獎金
B54: 所得稅20% | D54: =D77 -> -231585.4 | E54: =E77 -> -171794.8 | F54: =F77 -> -170044.39 | G54: =G77 -> -168293.98 | H54: =H77 -> -166543.58 | I54: =I77 -> -164793.17 | J54: =J77 -> -163042.77 | K54: =K77 -> -161292.36 | ... W54: =W77 -> -149009.48
B55: 現金流 | C55: =C44 -> -15201200 | D55: =SUM(D41:D54) -> 1396200.6 | E55: =SUM(E41:E54) -> 1447239.2 | F55: =SUM(F41:F54) -> 1440237.6 | G55: =SUM(G41:G54) -> 1433235.9 | H55: =SUM(H41:H54) -> 1426234.3 | I55: =SUM(I41:I54) -> 1419232.7 | J55: =SUM(J41:J54) -> 1412231.1 | K55: =SUM(K41:K54) -> 1405229.4 | ... W55: =SUM(W41:W54) -> 1356097.9
B56: 累計現金流 | D56: =C55+D55 -> -13804999 | E56: =D56+E55 -> -12357760 | F56: =E56+F55 -> -10917523 | G56: =F56+G55 -> -9484286.7 | H56: =G56+H55 -> -8058052.4 | I56: =H56+I55 -> -6638819.7 | J56: =I56+J55 -> -5226588.6 | K56: =J56+K55 -> -3821359.2 | L56: =K56+L55 -> -2423131.4 | ... X56: =W56+X55 -> 12844147
B57: 回收年限評估 | D57: =IF((D56)>0,"回收","未回收") -> 未回收 | E57: =IF((E56)>0,"回收","未回收") -> 未回收 | F57: =IF((F56)>0,"回收","未回收") -> 未回收 | G57: =IF((G56)>0,"回收","未回收") -> 未回收 | H57: =IF((H56)>0,"回收","未回收") -> 未回收 | I57: =IF((I56)>0,"回收","未回收") -> 未回收 | J57: =IF((J56)>0,"回收","未回收") -> 未回收 | K57: =IF((K56)>0,"回收","未回收") -> 未回收 | ... X57: =IF((X56)>0,"回收","未回收") -> 回收
B58: 專案法IRR | C58: =IRR(C55:W55) -> 0.067709579
C60: 年份 | D60: =D37 -> 2020 | E60: =E37 -> 2021 | F60: =F37 -> 2022 | G60: =G37 -> 2023 | H60: =H37 -> 2024 | I60: =I37 -> 2025 | J60: =J37 -> 2026 | K60: =K37 -> 2027 | ... W60: =W37 -> 2039
B61: 0 | T61: 償還年限
B62: (Unit : Currency) | C62: 0 | D62: 1 | E62: 2 | F62: 3 | G62: 4 | H62: 5 | I62: 6 | J62: 7 | K62: 8 | L62: 9 | M62: 10 | N62: 11 | O62: 12 | P62: 13 | Q62: 14 | R62: 15 | S62: 16 | T62: 17 | U62: 18 | V62: 19 | W62: 20
B63: 發電度數(KWH) | C63: 0 | D63: =D40 -> 541531.98 | E63: =E40 -> 539343.97 | F63: =F40 -> 537155.96 | G63: =G40 -> 534967.96 | H63: =H40 -> 532779.95 | I63: =I40 -> 530591.94 | J63: =J40 -> 528403.93 | K63: =K40 -> 526215.92 | ... W63: =W40 -> 499959.83
B64: Inflow : 電費收入 | C64: - | D64: =D41 -> 2166127.9 | E64: =E41 -> 2157375.9 | F64: =F41 -> 2148623.9 | G64: =G41 -> 2139871.8 | H64: =H41 -> 2131119.8 | I64: =I41 -> 2122367.8 | J64: =J41 -> 2113615.7 | K64: =K41 -> 2104863.7 | ... W64: =W41 -> 1999839.3
B65: Inflow : 政府補助 | C65: - | G65: - | H65: - | I65: - | J65: - | K65: - | L65: - | M65: - | N65: - | O65: - | P65: - | Q65: - | R65: - | S65: - | T65: - | U65: - | V65: - | W65: -
B66: Inflow : 銀行借款
B67: Outflow : 設備折舊 | D67: =$C$44/$E$16 -> -760060 | E67: =$C$44/$E$16 -> -760060 | F67: =$C$44/$E$16 -> -760060 | G67: =$C$44/$E$16 -> -760060 | H67: =$C$44/$E$16 -> -760060 | I67: =$C$44/$E$16 -> -760060 | J67: =$C$44/$E$16 -> -760060 | K67: =$C$44/$E$16 -> -760060 | ... W67: =$C$44/$E$16 -> -760060
B68: Outflow : 設備放置區域租金 | C68: - | D68: =D44 -> 0 | E68: =E45 -> -290201 | F68: =F45 -> -290201 | G68: =G45 -> -290201 | H68: =H45 -> -290201 | I68: =I45 -> -290201 | J68: =J45 -> -290201 | K68: =K45 -> -290201 | L68: =L45 -> -290201 | ... W68: =W45 -> -290201
B69: Outflow : 返還借款
B70: Outflow : 利息費用 | C70: - | D70: 0 | E70: 0 | F70: 0 | G70: 0 | H70: 0 | I70: 0 | J70: 0 | K70: 0 | L70: 0 | M70: 0 | N70: 0 | O70: 0 | P70: 0 | Q70: 0 | R70: 0 | S70: 0 | T70: 0 | U70: 0 | V70: 0 | W70: 0
B71: Outflow : 維運費 | C71: - | D71: =D48 -> -174440 | E71: =E48 -> -174440 | F71: =F48 -> -174440 | G71: =G48 -> -174440 | H71: =H48 -> -174440 | I71: =I48 -> -174440 | J71: =J48 -> -174440 | K71: =K48 -> -174440 | ... W71: =W48 -> -174440
B72: Outflow : 保險費 | C72: - | D72: =D49 -> -30090.9 | E72: =E49 -> -30090.9 | F72: =F49 -> -30090.9 | G72: =G49 -> -30090.9 | H72: =H49 -> -30090.9 | I72: =I49 -> -30090.9 | J72: =J49 -> -30090.9 | K72: =K49 -> -30090.9 | ... W72: =W49 -> -30090.9
B73: Outflow : 模組回收費 | D73: =D50 -> -43610 | E73: =E50 -> -43610 | F73: =F50 -> -43610 | G73: =G50 -> -43610 | H73: =H50 -> -43610 | I73: =I50 -> -43610 | J73: =J50 -> -43610 | K73: =K50 -> -43610 | ... W73: =W50 -> 0
B74: Outflow : 其它費用(人事薪資…等)
B75: 1%管理費
B76: 稅前淨利 | D76: =SUM(D64:D75) -> 1157927 | E76: =SUM(E64:E75) -> 858973.99 | F76: =SUM(F64:F75) -> 850221.96 | G76: =SUM(G64:G75) -> 841469.92 | H76: =SUM(H64:H75) -> 832717.89 | I76: =SUM(I64:I75) -> 823965.86 | J76: =SUM(J64:J75) -> 815213.83 | K76: =SUM(K64:K75) -> 806461.8 | ... X76: =SUM(X64:X75) -> 0
B77: 所得稅20% | D77: =-D76*0.2 -> -231585.4 | E77: =-E76*0.2 -> -171794.8 | F77: =-F76*0.2 -> -170044.39 | G77: =-G76*0.2 -> -168293.98 | H77: =-H76*0.2 -> -166543.58 | I77: =-I76*0.2 -> -164793.17 | J77: =-J76*0.2 -> -163042.77 | K77: =-K76*0.2 -> -161292.36 | ... X77: =-X76*0.2 -> 0
B78: 稅後淨利 | D78: =SUM(D76:D77) -> 926341.62 | E78: =SUM(E76:E77) -> 687179.19 | F78: =SUM(F76:F77) -> 680177.56 | G78: =SUM(G76:G77) -> 673175.94 | H78: =SUM(H76:H77) -> 666174.31 | I78: =SUM(I76:I77) -> 659172.69 | J78: =SUM(J76:J77) -> 652171.06 | K78: =SUM(K76:K77) -> 645169.44 | ... X78: =SUM(X76:X77) -> 0
B79: 累計現金流
B80: 回收年限評估

Sheet 淡江大學_p8
B1: 電站基本資料 | F1: 說明 | P1: =1-D11 -> 0.99 | Q1: =P1-$D12 -> 0.986 | R1: =Q1-$D12 -> 0.982 | S1: =R1-$D12 -> 0.978 | T1: =S1-$D12 -> 0.974 | U1: =T1-$D12 -> 0.97 | V1: =U1-$D12 -> 0.966 | W1: =V1-$D12 -> 0.962 | X1: =W1-$D12 -> 0.958 | ... AI1: =AH1-$D12 -> 0.914
B2: 電站名稱 | C2: 淡江大學 | D2: - | E2: - | F2: 填入本案場名稱
B3: 電站壽命 | C3: 20 | D3: - | E3: - | F3: 預設 20 年，代表財務評估年期。若合約年限不同可依實際情況修改
B4: 建置量(kWp) | C4: 436.1 | D4: - | E4: - | F4: 填入裝置容量（kWp），通常由設計圖面或報價書取得 | M4: 情境編號: 8
B5: 起始年度 | C5: 2020 | D5: 結束年度 | E5: 2039 | F5: 填入電站預計掛表的西元年份（例：2025）。結束年度會自動計算 | M5: 第7次滾算摘要
M6: 價金: 21000
B7: 綜合損益表 | M7: 專案IRR: 7.85
B8: 收入 | M8: 權益法IRR: 27.57
B9: 收支項目 | C9: 相關參數 | D9: 參數數值 | E9: 年限 | F9: 說明 | M9: 利潤率: 30.00%
B10: 電費收入 | C10: 年度AC併網總發電量 | D10: 547002 | E10: 20 | F10: 預估年發電量（kWh），通常來自 PVsyst 模擬或估算：裝置容量 × 年日照時數 × 系統效率 | M10: 第7次滾算，減少 2000 元 - 現金模式，每次減少 2000 元
C11: 首年衰退率 | D11: 0.01 | F11: 第一年發電衰退比率，請填小數（例：1% → 填 0.01）。一般首年衰退約 1~2%(請參考模組規格書)
C12: 次年衰退率 | D12: 0.004 | F12: 第二年起每年固定衰退比率，請填小數（例：0.4% → 填 0.004）。一般約 0.4~0.7%(請參考模組規格書)
C13: 躉售費率(FIT) / 綠電費率 | D13: 4 | F13: 與台電簽訂的躉購費率或綠電合約費率，單位：元/度。請參考台電公告或合約內容
B14: 支出
B15: 收支項目 | C15: 相關參數 | D15: 參數數值 | E15: 攤提年限 | F15: 說明
B16: 設備費用(價金) | C16: 每kWp設備成本 | D16: 21000 | E16: 20 | F16: 每峰瓩設備成本（元/kWp），包含模組、逆變器、支架等硬體，不含工程施工費
C17: 信邦利潤率(ex:20%填0.2) | D17: 0.3 | F17: 公司在設備費用上加計的利潤比率，請填小數（例：20% → 填 0.2）
C18: 開發費 | D18: 2000 | F18: 前期開發費用（元），含可行性評估、申請規費、地主溝通等。若無則填 0
B19: 租金費用 | C19: 租金計算方式 | D19: 1 | E19: 20 | F19: 填 1 = 固定年租金（需填方式1參數）；填 2 = 依電費收入抽成（需填方式2參數）
C20: 【方式1參數】每年相同價格 | D20: 290201 | E20: 20 | F20: 租金計算方式選「1」時填寫，固定年租金金額（元/年），套用至整個電站壽命期
C21: 【方式2參數】抽成比率 | D21: 0 | E21: 20 | F21: 租金計算方式選「2」時填寫，請填小數（例：10% → 填 0.1）。租金 = 當年電費收入 × 抽成比率
B22: 運維費用 | C22: 每kw運維成本 | D22: 400 | E22: 20 | F22: 每峰瓩每年運維費用（元/kWp/年），含清洗、巡檢、維修等。
B23: 保險費用 | C23: 占整體設備費用比例 | D23: 0.003 | E23: 20 | F23: 保險費佔設備總費用比率，填小數（例：0.3% → 填 0.003）。預設 0.003，可依投保條件調整
B24: 模組回收費用 | C24: 每kw模組回收成本 | D24: 1000 | E24: 10 | F24: 每峰瓩模組廢棄回收費用（元/kWp），於第 1~10 年計提（攤提 10 年）。
B25: 利息費用 | C25: 銀行利率 | D25: 0.0256 | E25: 20 | F25: 向銀行貸款的年利率，填小數（例：2.56% → 填 0.0256）。請依銀行核准利率填入
B26: 所得稅 | C26: 所得稅率 | D26: 0.2 | E26: 20 | F26: 公司所得稅率，填小數（例：20% → 填 0.2）。預設 0.2，通常不需更改
B29: 現金流量表
B30: 金流項目 | C30: 相關參數 | D30: 參數數值 | F30: 說明
B31: 貸款成數 | C31: 占總設備費用比例 | D31: 0.8 | F31: 貸款佔設備總費用比例，填小數（例：80% → 填 0.8）。預設 0.8 代表貸八成、自備二成
B32: 貸款還款 | C32: 攤還期數 | D32: 15 | F32: 貸款還款年數（年）。預設 15 年，代表分 15 年平均攤還本金
B33: 現金股利 | C33: 股利比率 | D33: 0.9 | F33: 稅後現金流中分配給股東的比例，填小數（例：90% → 填 0.9）
B34: 年底減資 | C34: 攤還期數 | D34: 4 | F34: 年底減資返還股東的年數。預設 4 年，代表 倒數 4 年進行減資，加速資金返還
C37: 年份 | D37: 2020 | E37: 2021 | F37: 2022 | G37: 2023 | H37: 2024 | I37: 2025 | J37: 2026 | K37: 2027 | L37: 2028 | M37: 2029 | N37: 2030 | O37: 2031 | P37: 2032 | Q37: 2033 | R37: 2034 | S37: 2035 | T37: 2036 | U37: 2037 | V37: 2038 | W37: 2039
B38: 0
B39: (Unit : Currency) | C39: 0 | D39: 1 | E39: 2 | F39: 3 | G39: 4 | H39: 5 | I39: 6 | J39: 7 | K39: 8 | L39: 9 | M39: 10 | N39: 11 | O39: 12 | P39: 13 | Q39: 14 | R39: 15 | S39: 16 | T39: 17 | U39: 18 | V39: 19 | W39: 20
B40: 發電度數(KWH) | C40: 0 | D40: =$D$10*P1 -> 541531.98 | E40: =$D$10*Q1 -> 539343.97 | F40: =$D$10*R1 -> 537155.96 | G40: =$D$10*S1 -> 534967.96 | H40: =$D$10*T1 -> 532779.95 | I40: =$D$10*U1 -> 530591.94 | J40: =$D$10*V1 -> 528403.93 | K40: =$D$10*W1 -> 526215.92 | ... W40: =$D$10*AI1 -> 499959.83
B41: Inflow : 電費收入 | C41: - | D41: =D40*$D$13 -> 2166127.9 | E41: =E40*$D$13 -> 2157375.9 | F41: =F40*$D$13 -> 2148623.9 | G41: =G40*$D$13 -> 2139871.8 | H41: =H40*$D$13 -> 2131119.8 | I41: =I40*$D$13 -> 2122367.8 | J41: =J40*$D$13 -> 2113615.7 | K41: =K40*$D$13 -> 2104863.7 | ... W41: =W40*$D$13 -> 1999839.3
B42: Inflow : 政府補助 | C42: - | G42: - | H42: - | I42: - | J42: - | K42: - | L42: - | M42: - | N42: - | O42: - | P42: - | Q42: - | R42: - | S42: - | T42: - | U42: - | V42: - | W42: -
B43: Inflow : 銀行借款
B44: Outflow : 設備費用 | C44: =-(D16/(1-D17)+D18)*C4 -> -13955200
B45: Outflow : 設備放置區域租金 | C45: - | D45: -290201 | E45: -290201 | F45: -290201 | G45: -290201 | H45: -290201 | I45: -290201 | J45: -290201 | K45: -290201 | L45: -290201 | M45: -290201 | N45: -290201 | O45: -290201 | P45: -290201 | Q45: -290201 | R45: -290201 | S45: -290201 | T45: -290201 | U45: -290201 | V45: -290201 | W45: -290201
B46: Outflow : 返還借款
B47: Outflow : 利息費用 | C47: -
B48: Outflow : 維運費 | C48: - | D48: -174440 | E48: -174440 | F48: -174440 | G48: -174440 | H48: -174440 | I48: -174440 | J48: -174440 | K48: -174440 | L48: -174440 | M48: -174440 | N48: -174440 | O48: -174440 | P48: -174440 | Q48: -174440 | R48: -174440 | S48: -174440 | T48: -174440 | U48: -174440 | V48: -174440 | W48: -174440
B49: Outflow : 保險費 | C49: - | D49: -27474.3 | E49: -27474.3 | F49: -27474.3 | G49: -27474.3 | H49: -27474.3 | I49: -27474.3 | J49: -27474.3 | K49: -27474.3 | L49: -27474.3 | M49: -27474.3 | N49: -27474.3 | O49: -27474.3 | P49: -27474.3 | Q49: -27474.3 | R49: -27474.3 | S49: -27474.3 | T49: -27474.3 | U49: -27474.3 | V49: -27474.3 | W49: -27474.3
B50: Outflow : 模組回收費 | D50: -43610 | E50: -43610 | F50: -43610 | G50: -43610 | H50: -43610 | I50: -43610 | J50: -43610 | K50: -43610 | L50: -43610 | M50: -43610 | N50: 0 | O50: 0 | P50: 0 | Q50: 0 | R50: 0 | S50: 0 | T50: 0 | U50: 0 | V50: 0 | W50: 0
B51: Outflow : 其它費用(人事薪資…等)
B52: 1%管理費
B53: 績效獎金
B54: 所得稅20% | D54: =D77 -> -244568.72 | E54: =E77 -> -184778.12 | F54: =F77 -> -183027.71 | G54: =G77 -> -181277.3 | H54: =H77 -> -179526.9 | I54: =I77 -> -177776.49 | J54: =J77 -> -176026.09 | K54: =K77 -> -174275.68 | ... W54: =W77 -> -161992.8
B55: 現金流 | C55: =C44 -> -13955200 | D55: =SUM(D41:D54) -> 1385833.9 | E55: =SUM(E41:E54) -> 1436872.5 | F55: =SUM(F41:F54) -> 1429870.8 | G55: =SUM(G41:G54) -> 1422869.2 | H55: =SUM(H41:H54) -> 1415867.6 | I55: =SUM(I41:I54) -> 1408866 | J55: =SUM(J41:J54) -> 1401864.3 | K55: =SUM(K41:K54) -> 1394862.7 | ... W55: =SUM(W41:W54) -> 1345731.2
B56: 累計現金流 | D56: =C55+D55 -> -12569366 | E56: =D56+E55 -> -11132494 | F56: =E56+F55 -> -9702622.8 | G56: =F56+G55 -> -8279753.6 | H56: =G56+H55 -> -6863886 | I56: =H56+I55 -> -5455020 | J56: =I56+J55 -> -4053155.7 | K56: =J56+K55 -> -2658292.9 | L56: =K56+L55 -> -1270431.9 | ... X56: =W56+X55 -> 13882813
B57: 回收年限評估 | D57: =IF((D56)>0,"回收","未回收") -> 未回收 | E57: =IF((E56)>0,"回收","未回收") -> 未回收 | F57: =IF((F56)>0,"回收","未回收") -> 未回收 | G57: =IF((G56)>0,"回收","未回收") -> 未回收 | H57: =IF((H56)>0,"回收","未回收") -> 未回收 | I57: =IF((I56)>0,"回收","未回收") -> 未回收 | J57: =IF((J56)>0,"回收","未回收") -> 未回收 | K57: =IF((K56)>0,"回收","未回收") -> 未回收 | ... X57: =IF((X56)>0,"回收","未回收") -> 回收
B58: 專案法IRR | C58: =IRR(C55:W55) -> 0.077973254
C60: 年份 | D60: =D37 -> 2020 | E60: =E37 -> 2021 | F60: =F37 -> 2022 | G60: =G37 -> 2023 | H60: =H37 -> 2024 | I60: =I37 -> 2025 | J60: =J37 -> 2026 | K60: =K37 -> 2027 | ... W60: =W37 -> 2039
B61: 0 | T61: 償還年限
B62: (Unit : Currency) | C62: 0 | D62: 1 | E62: 2 | F62: 3 | G62: 4 | H62: 5 | I62: 6 | J62: 7 | K62: 8 | L62: 9 | M62: 10 | N62: 11 | O62: 12 | P62: 13 | Q62: 14 | R62: 15 | S62: 16 | T62: 17 | U62: 18 | V62: 19 | W62: 20
B63: 發電度數(KWH) | C63: 0 | D63: =D40 -> 541531.98 | E63: =E40 -> 539343.97 | F63: =F40 -> 537155.96 | G63: =G40 -> 534967.96 | H63: =H40 -> 532779.95 | I63: =I40 -> 530591.94 | J63: =J40 -> 528403.93 | K63: =K40 -> 526215.92 | ... W63: =W40 -> 499959.83
B64: Inflow : 電費收入 | C64: - | D64: =D41 -> 2166127.9 | E64: =E41 -> 2157375.9 | F64: =F41 -> 2148623.9 | G64: =G41 -> 2139871.8 | H64: =H41 -> 2131119.8 | I64: =I41 -> 2122367.8 | J64: =J41 -> 2113615.7 | K64: =K41 -> 2104863.7 | ... W64: =W41 -> 1999839.3
B65: Inflow : 政府補助 | C65: - | G65: - | H65: - | I65: - | J65: - | K65: - | L65: - | M65: - | N65: - | O65: - | P65: - | Q65: - | R65: - | S65: - | T65: - | U65: - | V65: - | W65: -
B66: Inflow : 銀行借款
B67: Outflow : 設備折舊 | D67: =$C$44/$E$16 -> -697760 | E67: =$C$44/$E$16 -> -697760 | F67: =$C$44/$E$16 -> -697760 | G67: =$C$44/$E$16 -> -697760 | H67: =$C$44/$E$16 -> -697760 | I67: =$C$44/$E$16 -> -697760 | J67: =$C$44/$E$16 -> -697760 | K67: =$C$44/$E$16 -> -697760 | ... W67: =$C$44/$E$16 -> -697760
B68: Outflow : 設備放置區域租金 | C68: - | D68: =D44 -> 0 | E68: =E45 -> -290201 | F68: =F45 -> -290201 | G68: =G45 -> -290201 | H68: =H45 -> -290201 | I68: =I45 -> -290201 | J68: =J45 -> -290201 | K68: =K45 -> -290201 | L68: =L45 -> -290201 | ... W68: =W45 -> -290201
B69: Outflow : 返還借款
B70: Outflow : 利息費用 | C70: - | D70: 0 | E70: 0 | F70: 0 | G70: 0 | H70: 0 | I70: 0 | J70: 0 | K70: 0 | L70: 0 | M70: 0 | N70: 0 | O70: 0 | P70: 0 | Q70: 0 | R70: 0 | S70: 0 | T70: 0 | U70: 0 | V70: 0 | W70: 0
B71: Outflow : 維運費 | C71: - | D71: =D48 -> -174440 | E71: =E48 -> -174440 | F71: =F48 -> -174440 | G71: =G48 -> -174440 | H71: =H48 -> -174440 | I71: =I48 -> -174440 | J71: =J48 -> -174440 | K71: =K48 -> -174440 | ... W71: =W48 -> -174440
B72: Outflow : 保險費 | C72: - | D72: =D49 -> -27474.3 | E72: =E49 -> -27474.3 | F72: =F49 -> -27474.3 | G72: =G49 -> -27474.3 | H72: =H49 -> -27474.3 | I72: =I49 -> -27474.3 | J72: =J49 -> -27474.3 | K72: =K49 -> -27474.3 | ... W72: =W49 -> -27474.3
B73: Outflow : 模組回收費 | D73: =D50 -> -43610 | E73: =E50 -> -43610 | F73: =F50 -> -43610 | G73: =G50 -> -43610 | H73: =H50 -> -43610 | I73: =I50 -> -43610 | J73: =J50 -> -43610 | K73: =K50 -> -43610 | ... W73: =W50 -> 0
B74: Outflow : 其它費用(人事薪資…等)
B75: 1%管理費
B76: 稅前淨利 | D76: =SUM(D64:D75) -> 1222843.6 | E76: =SUM(E64:E75) -> 923890.59 | F76: =SUM(F64:F75) -> 915138.56 | G76: =SUM(G64:G75) -> 906386.52 | H76: =SUM(H64:H75) -> 897634.49 | I76: =SUM(I64:I75) -> 888882.46 | J76: =SUM(J64:J75) -> 880130.43 | K76: =SUM(K64:K75) -> 871378.4 | ... X76: =SUM(X64:X75) -> 0
B77: 所得稅20% | D77: =-D76*0.2 -> -244568.72 | E77: =-E76*0.2 -> -184778.12 | F77: =-F76*0.2 -> -183027.71 | G77: =-G76*0.2 -> -181277.3 | H77: =-H76*0.2 -> -179526.9 | I77: =-I76*0.2 -> -177776.49 | J77: =-J76*0.2 -> -176026.09 | K77: =-K76*0.2 -> -174275.68 | ... X77: =-X76*0.2 -> 0
B78: 稅後淨利 | D78: =SUM(D76:D77) -> 978274.9 | E78: =SUM(E76:E77) -> 739112.47 | F78: =SUM(F76:F77) -> 732110.84 | G78: =SUM(G76:G77) -> 725109.22 | H78: =SUM(H76:H77) -> 718107.59 | I78: =SUM(I76:I77) -> 711105.97 | J78: =SUM(J76:J77) -> 704104.34 | K78: =SUM(K76:K77) -> 697102.72 | ... X78: =SUM(X76:X77) -> 0
B79: 累計現金流
B80: 回收年限評估

Sheet 淡江大學_p6
B1: 電站基本資料 | F1: 說明 | P1: =1-D11 -> 0.99 | Q1: =P1-$D12 -> 0.986 | R1: =Q1-$D12 -> 0.982 | S1: =R1-$D12 -> 0.978 | T1: =S1-$D12 -> 0.974 | U1: =T1-$D12 -> 0.97 | V1: =U1-$D12 -> 0.966 | W1: =V1-$D12 -> 0.962 | X1: =W1-$D12 -> 0.958 | ... AI1: =AH1-$D12 -> 0.914
B2: 電站名稱 | C2: 淡江大學 | D2: - | E2: - | F2: 填入本案場名稱
B3: 電站壽命 | C3: 20 | D3: - | E3: - | F3: 預設 20 年，代表財務評估年期。若合約年限不同可依實際情況修改
B4: 建置量(kWp) | C4: 436.1 | D4: - | E4: - | F4: 填入裝置容量（kWp），通常由設計圖面或報價書取得 | M4: 情境編號: 6
B5: 起始年度 | C5: 2020 | D5: 結束年度 | E5: 2039 | F5: 填入電站預計掛表的西元年份（例：2025）。結束年度會自動計算 | M5: 第5次滾算摘要
M6: 價金: 25000
B7: 綜合損益表 | M7: 專案IRR: 5.91
B8: 收入 | M8: 權益法IRR: 17.0
B9: 收支項目 | C9: 相關參數 | D9: 參數數值 | E9: 年限 | F9: 說明 | M9: 利潤率: 30.00%
B10: 電費收入 | C10: 年度AC併網總發電量 | D10: 547002 | E10: 20 | F10: 預估年發電量（kWh），通常來自 PVsyst 模擬或估算：裝置容量 × 年日照時數 × 系統效率 | M10: 第5次滾算，減少 2000 元 - 現金模式，每次減少 2000 元
C11: 首年衰退率 | D11: 0.01 | F11: 第一年發電衰退比率，請填小數（例：1% → 填 0.01）。一般首年衰退約 1~2%(請參考模組規格書)
C12: 次年衰退率 | D12: 0.004 | F12: 第二年起每年固定衰退比率，請填小數（例：0.4% → 填 0.004）。一般約 0.4~0.7%(請參考模組規格書)
C13: 躉售費率(FIT) / 綠電費率 | D13: 4 | F13: 與台電簽訂的躉購費率或綠電合約費率，單位：元/度。請參考台電公告或合約內容
B14: 支出
B15: 收支項目 | C15: 相關參數 | D15: 參數數值 | E15: 攤提年限 | F15: 說明
B16: 設備費用(價金) | C16: 每kWp設備成本 | D16: 25000 | E16: 20 | F16: 每峰瓩設備成本（元/kWp），包含模組、逆變器、支架等硬體，不含工程施工費
C17: 信邦利潤率(ex:20%填0.2) | D17: 0.3 | F17: 公司在設備費用上加計的利潤比率，請填小數（例：20% → 填 0.2）
C18: 開發費 | D18: 2000 | F18: 前期開發費用（元），含可行性評估、申請規費、地主溝通等。若無則填 0
B19: 租金費用 | C19: 租金計算方式 | D19: 1 | E19: 20 | F19: 填 1 = 固定年租金（需填方式1參數）；填 2 = 依電費收入抽成（需填方式2參數）
C20: 【方式1參數】每年相同價格 | D20: 290201 | E20: 20 | F20: 租金計算方式選「1」時填寫，固定年租金金額（元/年），套用至整個電站壽命期
C21: 【方式2參數】抽成比率 | D21: 0 | E21: 20 | F21: 租金計算方式選「2」時填寫，請填小數（例：10% → 填 0.1）。租金 = 當年電費收入 × 抽成比率
B22: 運維費用 | C22: 每kw運維成本 | D22: 400 | E22: 20 | F22: 每峰瓩每年運維費用（元/kWp/年），含清洗、巡檢、維修等。
B23: 保險費用 | C23: 占整體設備費用比例 | D23: 0.003 | E23: 20 | F23: 保險費佔設備總費用比率，填小數（例：0.3% → 填 0.003）。預設 0.003，可依投保條件調整
B24: 模組回收費用 | C24: 每kw模組回收成本 | D24: 1000 | E24: 10 | F24: 每峰瓩模組廢棄回收費用（元/kWp），於第 1~10 年計提（攤提 10 年）。
B25: 利息費用 | C25: 銀行利率 | D25: 0.0256 | E25: 20 | F25: 向銀行貸款的年利率，填小數（例：2.56% → 填 0.0256）。請依銀行核准利率填入
B26: 所得稅 | C26: 所得稅率 | D26: 0.2 | E26: 20 | F26: 公司所得稅率，填小數（例：20% → 填 0.2）。預設 0.2，通常不需更改
B29: 現金流量表
B30: 金流項目 | C30: 相關參數 | D30: 參數數值 | F30: 說明
B31: 貸款成數 | C31: 占總設備費用比例 | D31: 0.8 | F31: 貸款佔設備總費用比例，填小數（例：80% → 填 0.8）。預設 0.8 代表貸八成、自備二成
B32: 貸款還款 | C32: 攤還期數 | D32: 15 | F32: 貸款還款年數（年）。預設 15 年，代表分 15 年平均攤還本金
B33: 現金股利 | C33: 股利比率 | D33: 0.9 | F33: 稅後現金流中分配給股東的比例，填小數（例：90% → 填 0.9）
B34: 年底減資 | C34: 攤還期數 | D34: 4 | F34: 年底減資返還股東的年數。預設 4 年，代表 倒數 4 年進行減資，加速資金返還
C37: 年份 | D37: 2020 | E37: 2021 | F37: 2022 | G37: 2023 | H37: 2024 | I37: 2025 | J37: 2026 | K37: 2027 | L37: 2028 | M37: 2029 | N37: 2030 | O37: 2031 | P37: 2032 | Q37: 2033 | R37: 2034 | S37: 2035 | T37: 2036 | U37: 2037 | V37: 2038 | W37: 2039
B38: 0
B39: (Unit : Currency) | C39: 0 | D39: 1 | E39: 2 | F39: 3 | G39: 4 | H39: 5 | I39: 6 | J39: 7 | K39: 8 | L39: 9 | M39: 10 | N39: 11 | O39: 12 | P39: 13 | Q39: 14 | R39: 15 | S39: 16 | T39: 17 | U39: 18 | V39: 19 | W39: 20
B40: 發電度數(KWH) | C40: 0 | D40: =$D$10*P1 -> 541531.98 | E40: =$D$10*Q1 -> 539343.97 | F40: =$D$10*R1 -> 537155.96 | G40: =$D$10*S1 -> 534967.96 | H40: =$D$10*T1 -> 532779.95 | I40: =$D$10*U1 -> 530591.94 | J40: =$D$10*V1 -> 528403.93 | K40: =$D$10*W1 -> 526215.92 | ... W40: =$D$10*AI1 -> 499959.83
B41: Inflow : 電費收入 | C41: - | D41: =D40*$D$13 -> 2166127.9 | E41: =E40*$D$13 -> 2157375.9 | F41: =F40*$D$13 -> 2148623.9 | G41: =G40*$D$13 -> 2139871.8 | H41: =H40*$D$13 -> 2131119.8 | I41: =I40*$D$13 -> 2122367.8 | J41: =J40*$D$13 -> 2113615.7 | K41: =K40*$D$13 -> 2104863.7 | ... W41: =W40*$D$13 -> 1999839.3
B42: Inflow : 政府補助 | C42: - | G42: - | H42: - | I42: - | J42: - | K42: - | L42: - | M42: - | N42: - | O42: - | P42: - | Q42: - | R42: - | S42: - | T42: - | U42: - | V42: - | W42: -
B43: Inflow : 銀行借款
B44: Outflow : 設備費用 | C44: =-(D16/(1-D17)+D18)*C4 -> -16447200
B45: Outflow : 設備放置區域租金 | C45: - | D45: -290201 | E45: -290201 | F45: -290201 | G45: -290201 | H45: -290201 | I45: -290201 | J45: -290201 | K45: -290201 | L45: -290201 | M45: -290201 | N45: -290201 | O45: -290201 | P45: -290201 | Q45: -290201 | R45: -290201 | S45: -290201 | T45: -290201 | U45: -290201 | V45: -290201 | W45: -290201
B46: Outflow : 返還借款
B47: Outflow : 利息費用 | C47: -
B48: Outflow : 維運費 | C48: - | D48: -174440 | E48: -174440 | F48: -174440 | G48: -174440 | H48: -174440 | I48: -174440 | J48: -174440 | K48: -174440 | L48: -174440 | M48: -174440 | N48: -174440 | O48: -174440 | P48: -174440 | Q48: -174440 | R48: -174440 | S48: -174440 | T48: -174440 | U48: -174440 | V48: -174440 | W48: -174440
B49: Outflow : 保險費 | C49: - | D49: -32707.5 | E49: -32707.5 | F49: -32707.5 | G49: -32707.5 | H49: -32707.5 | I49: -32707.5 | J49: -32707.5 | K49: -32707.5 | L49: -32707.5 | M49: -32707.5 | N49: -32707.5 | O49: -32707.5 | P49: -32707.5 | Q49: -32707.5 | R49: -32707.5 | S49: -32707.5 | T49: -32707.5 | U49: -32707.5 | V49: -32707.5 | W49: -32707.5
B50: Outflow : 模組回收費 | D50: -43610 | E50: -43610 | F50: -43610 | G50: -43610 | H50: -43610 | I50: -43610 | J50: -43610 | K50: -43610 | L50: -43610 | M50: -43610 | N50: 0 | O50: 0 | P50: 0 | Q50: 0 | R50: 0 | S50: 0 | T50: 0 | U50: 0 | V50: 0 | W50: 0
B51: Outflow : 其它費用(人事薪資…等)
B52: 1%管理費
B53: 績效獎金
B54: 所得稅20% | D54: =D77 -> -218602.08 | E54: =E77 -> -158811.48 | F54: =F77 -> -157061.07 | G54: =G77 -> -155310.66 | H54: =H77 -> -153560.26 | I54: =I77 -> -151809.85 | J54: =J77 -> -150059.45 | K54: =K77 -> -148309.04 | ... W54: =W77 -> -136026.16
B55: 現金流 | C55: =C44 -> -16447200 | D55: =SUM(D41:D54) -> 1406567.3 | E55: =SUM(E41:E54) -> 1457605.9 | F55: =SUM(F41:F54) -> 1450604.3 | G55: =SUM(G41:G54) -> 1443602.7 | H55: =SUM(H41:H54) -> 1436601 | I55: =SUM(I41:I54) -> 1429599.4 | J55: =SUM(J41:J54) -> 1422597.8 | K55: =SUM(K41:K54) -> 1415596.2 | ... W55: =SUM(W41:W54) -> 1366464.6
B56: 累計現金流 | D56: =C55+D55 -> -15040633 | E56: =D56+E55 -> -13583027 | F56: =E56+F55 -> -12132422 | G56: =F56+G55 -> -10688820 | H56: =G56+H55 -> -9252218.8 | I56: =H56+I55 -> -7822619.4 | J56: =I56+J55 -> -6400021.6 | K56: =J56+K55 -> -4984425.4 | L56: =K56+L55 -> -3575830.9 | ... X56: =W56+X55 -> 11805482
B57: 回收年限評估 | D57: =IF((D56)>0,"回收","未回收") -> 未回收 | E57: =IF((E56)>0,"回收","未回收") -> 未回收 | F57: =IF((F56)>0,"回收","未回收") -> 未回收 | G57: =IF((G56)>0,"回收","未回收") -> 未回收 | H57: =IF((H56)>0,"回收","未回收") -> 未回收 | I57: =IF((I56)>0,"回收","未回收") -> 未回收 | J57: =IF((J56)>0,"回收","未回收") -> 未回收 | K57: =IF((K56)>0,"回收","未回收") -> 未回收 | ... X57: =IF((X56)>0,"回收","未回收") -> 回收
B58: 專案法IRR | C58: =IRR(C55:W55) -> 0.058710079
C60: 年份 | D60: =D37 -> 2020 | E60: =E37 -> 2021 | F60: =F37 -> 2022 | G60: =G37 -> 2023 | H60: =H37 -> 2024 | I60: =I37 -> 2025 | J60: =J37 -> 2026 | K60: =K37 -> 2027 | ... W60: =W37 -> 2039
B61: 0 | T61: 償還年限
B62: (Unit : Currency) | C62: 0 | D62: 1 | E62: 2 | F62: 3 | G62: 4 | H62: 5 | I62: 6 | J62: 7 | K62: 8 | L62: 9 | M62: 10 | N62: 11 | O62: 12 | P62: 13 | Q62: 14 | R62: 15 | S62: 16 | T62: 17 | U62: 18 | V62: 19 | W62: 20
B63: 發電度數(KWH) | C63: 0 | D63: =D40 -> 541531.98 | E63: =E40 -> 539343.97 | F63: =F40 -> 537155.96 | G63: =G40 -> 534967.96 | H63: =H40 -> 532779.95 | I63: =I40 -> 530591.94 | J63: =J40 -> 528403.93 | K63: =K40 -> 526215.92 | ... W63: =W40 -> 499959.83
B64: Inflow : 電費收入 | C64: - | D64: =D41 -> 2166127.9 | E64: =E41 -> 2157375.9 | F64: =F41 -> 2148623.9 | G64: =G41 -> 2139871.8 | H64: =H41 -> 2131119.8 | I64: =I41 -> 2122367.8 | J64: =J41 -> 2113615.7 | K64: =K41 -> 2104863.7 | ... W64: =W41 -> 1999839.3
B65: Inflow : 政府補助 | C65: - | G65: - | H65: - | I65: - | J65: - | K65: - | L65: - | M65: - | N65: - | O65: - | P65: - | Q65: - | R65: - | S65: - | T65: - | U65: - | V65: - | W65: -
B66: Inflow : 銀行借款
B67: Outflow : 設備折舊 | D67: =$C$44/$E$16 -> -822360 | E67: =$C$44/$E$16 -> -822360 | F67: =$C$44/$E$16 -> -822360 | G67: =$C$44/$E$16 -> -822360 | H67: =$C$44/$E$16 -> -822360 | I67: =$C$44/$E$16 -> -822360 | J67: =$C$44/$E$16 -> -822360 | K67: =$C$44/$E$16 -> -822360 | ... W67: =$C$44/$E$16 -> -822360
B68: Outflow : 設備放置區域租金 | C68: - | D68: =D44 -> 0 | E68: =E45 -> -290201 | F68: =F45 -> -290201 | G68: =G45 -> -290201 | H68: =H45 -> -290201 | I68: =I45 -> -290201 | J68: =J45 -> -290201 | K68: =K45 -> -290201 | L68: =L45 -> -290201 | ... W68: =W45 -> -290201
B69: Outflow : 返還借款
B70: Outflow : 利息費用 | C70: - | D70: 0 | E70: 0 | F70: 0 | G70: 0 | H70: 0 | I70: 0 | J70: 0 | K70: 0 | L70: 0 | M70: 0 | N70: 0 | O70: 0 | P70: 0 | Q70: 0 | R70: 0 | S70: 0 | T70: 0 | U70: 0 | V70: 0 | W70: 0
B71: Outflow : 維運費 | C71: - | D71: =D48 -> -174440 | E71: =E48 -> -174440 | F71: =F48 -> -174440 | G71: =G48 -> -174440 | H71: =H48 -> -174440 | I71: =I48 -> -174440 | J71: =J48 -> -174440 | K71: =K48 -> -174440 | ... W71: =W48 -> -174440
B72: Outflow : 保險費 | C72: - | D72: =D49 -> -32707.5 | E72: =E49 -> -32707.5 | F72: =F49 -> -32707.5 | G72: =G49 -> -32707.5 | H72: =H49 -> -32707.5 | I72: =I49 -> -32707.5 | J72: =J49 -> -32707.5 | K72: =K49 -> -32707.5 | ... W72: =W49 -> -32707.5
B73: Outflow : 模組回收費 | D73: =D50 -> -43610 | E73: =E50 -> -43610 | F73: =F50 -> -43610 | G73: =G50 -> -43610 | H73: =H50 -> -43610 | I73: =I50 -> -43610 | J73: =J50 -> -43610 | K73: =K50 -> -43610 | ... W73: =W50 -> 0
B74: Outflow : 其它費用(人事薪資…等)
B75: 1%管理費
B76: 稅前淨利 | D76: =SUM(D64:D75) -> 1093010.4 | E76: =SUM(E64:E75) -> 794057.39 | F76: =SUM(F64:F75) -> 785305.36 | G76: =SUM(G64:G75) -> 776553.32 | H76: =SUM(H64:H75) -> 767801.29 | I76: =SUM(I64:I75) -> 759049.26 | J76: =SUM(J64:J75) -> 750297.23 | K76: =SUM(K64:K75) -> 741545.2 | ... X76: =SUM(X64:X75) -> 0
B77: 所得稅20% | D77: =-D76*0.2 -> -218602.08 | E77: =-E76*0.2 -> -158811.48 | F77: =-F76*0.2 -> -157061.07 | G77: =-G76*0.2 -> -155310.66 | H77: =-H76*0.2 -> -153560.26 | I77: =-I76*0.2 -> -151809.85 | J77: =-J76*0.2 -> -150059.45 | K77: =-K76*0.2 -> -148309.04 | ... X77: =-X76*0.2 -> 0
B78: 稅後淨利 | D78: =SUM(D76:D77) -> 874408.34 | E78: =SUM(E76:E77) -> 635245.91 | F78: =SUM(F76:F77) -> 628244.28 | G78: =SUM(G76:G77) -> 621242.66 | H78: =SUM(H76:H77) -> 614241.03 | I78: =SUM(I76:I77) -> 607239.41 | J78: =SUM(J76:J77) -> 600237.78 | K78: =SUM(K76:K77) -> 593236.16 | ... X78: =SUM(X76:X77) -> 0
B79: 累計現金流
B80: 回收年限評估
