Workbook

Sheet 多站彙整
C4: 年份 | D4: 2020 | E4: 2021 | F4: 2022 | G4: 2023 | H4: 2024 | I4: 2025 | J4: 2026 | K4: 2027 | L4: 2028 | M4: 2029 | N4: 2030 | O4: 2031 | P4: 2032 | Q4: 2033 | R4: 2034 | S4: 2035 | T4: 2036 | U4: 2037 | V4: 2038 | W4: 2039
C5: 預估發電度數
B6: 淡江大學 | D6: =ROUND(ABS(淡江大學_p2!D40),0) -> 541532 | E6: =ROUND(ABS(淡江大學_p2!E40),0) -> 539344 | F6: =ROUND(ABS(淡江大學_p2!F40),0) -> 537156 | G6: =ROUND(ABS(淡江大學_p2!G40),0) -> 534968 | H6: =ROUND(ABS(淡江大學_p2!H40),0) -> 532780 | I6: =ROUND(ABS(淡江大學_p2!I40),0) -> 530592 | J6: =ROUND(ABS(淡江大學_p2!J40),0) -> 528404 | K6: =ROUND(ABS(淡江大學_p2!K40),0) -> 526216 | ... W6: =ROUND(ABS(淡江大學_p2!W40),0) -> 499960
B7: 淡江大學 | D7: =ROUND(ABS(淡江大學_p5!D40),0) -> 541532 | E7: =ROUND(ABS(淡江大學_p5!E40),0) -> 539344 | F7: =ROUND(ABS(淡江大學_p5!F40),0) -> 537156 | G7: =ROUND(ABS(淡江大學_p5!G40),0) -> 534968 | H7: =ROUND(ABS(淡江大學_p5!H40),0) -> 532780 | I7: =ROUND(ABS(淡江大學_p5!I40),0) -> 530592 | J7: =ROUND(ABS(淡江大學_p5!J40),0) -> 528404 | K7: =ROUND(ABS(淡江大學_p5!K40),0) -> 526216 | ... W7: =ROUND(ABS(淡江大學_p5!W40),0) -> 499960
B8: 淡江大學 | D8: =ROUND(ABS(淡江大學_p3!D40),0) -> 541532 | E8: =ROUND(ABS(淡江大學_p3!E40),0) -> 539344 | F8: =ROUND(ABS(淡江大學_p3!F40),0) -> 537156 | G8: =ROUND(ABS(淡江大學_p3!G40),0) -> 534968 | H8: =ROUND(ABS(淡江大學_p3!H40),0) -> 532780 | I8: =ROUND(ABS(淡江大學_p3!I40),0) -> 530592 | J8: =ROUND(ABS(淡江大學_p3!J40),0) -> 528404 | K8: =ROUND(ABS(淡江大學_p3!K40),0) -> 526216 | ... W8: =ROUND(ABS(淡江大學_p3!W40),0) -> 499960
B9: 淡江大學 | D9: =ROUND(ABS(淡江大學_p4!D40),0) -> 541532 | E9: =ROUND(ABS(淡江大學_p4!E40),0) -> 539344 | F9: =ROUND(ABS(淡江大學_p4!F40),0) -> 537156 | G9: =ROUND(ABS(淡江大學_p4!G40),0) -> 534968 | H9: =ROUND(ABS(淡江大學_p4!H40),0) -> 532780 | I9: =ROUND(ABS(淡江大學_p4!I40),0) -> 530592 | J9: =ROUND(ABS(淡江大學_p4!J40),0) -> 528404 | K9: =ROUND(ABS(淡江大學_p4!K40),0) -> 526216 | ... W9: =ROUND(ABS(淡江大學_p4!W40),0) -> 499960
C10: 預估發電度數/年總計 | D10: =SUM(D6:D9) -> 2166128 | E10: =SUM(E6:E9) -> 2157376 | F10: =SUM(F6:F9) -> 2148624 | G10: =SUM(G6:G9) -> 2139872 | H10: =SUM(H6:H9) -> 2131120 | I10: =SUM(I6:I9) -> 2122368 | J10: =SUM(J6:J9) -> 2113616 | K10: =SUM(K6:K9) -> 2104864 | ... W10: =SUM(W6:W9) -> 1999840
C11: 年份 | D11: 2020 | E11: 2021 | F11: 2022 | G11: 2023 | H11: 2024 | I11: 2025 | J11: 2026 | K11: 2027 | L11: 2028 | M11: 2029 | N11: 2030 | O11: 2031 | P11: 2032 | Q11: 2033 | R11: 2034 | S11: 2035 | T11: 2036 | U11: 2037 | V11: 2038 | W11: 2039
C12: 預估收入
B13: 淡江大學 | D13: =ROUND(ABS(淡江大學_p2!D41),0) -> 2166128 | E13: =ROUND(ABS(淡江大學_p2!E41),0) -> 2157376 | F13: =ROUND(ABS(淡江大學_p2!F41),0) -> 2148624 | G13: =ROUND(ABS(淡江大學_p2!G41),0) -> 2139872 | H13: =ROUND(ABS(淡江大學_p2!H41),0) -> 2131120 | I13: =ROUND(ABS(淡江大學_p2!I41),0) -> 2122368 | J13: =ROUND(ABS(淡江大學_p2!J41),0) -> 2113616 | K13: =ROUND(ABS(淡江大學_p2!K41),0) -> 2104864 | ... W13: =ROUND(ABS(淡江大學_p2!W41),0) -> 1999839
B14: 淡江大學 | D14: =ROUND(ABS(淡江大學_p5!D41),0) -> 2166128 | E14: =ROUND(ABS(淡江大學_p5!E41),0) -> 2157376 | F14: =ROUND(ABS(淡江大學_p5!F41),0) -> 2148624 | G14: =ROUND(ABS(淡江大學_p5!G41),0) -> 2139872 | H14: =ROUND(ABS(淡江大學_p5!H41),0) -> 2131120 | I14: =ROUND(ABS(淡江大學_p5!I41),0) -> 2122368 | J14: =ROUND(ABS(淡江大學_p5!J41),0) -> 2113616 | K14: =ROUND(ABS(淡江大學_p5!K41),0) -> 2104864 | ... W14: =ROUND(ABS(淡江大學_p5!W41),0) -> 1999839
B15: 淡江大學 | D15: =ROUND(ABS(淡江大學_p3!D41),0) -> 2166128 | E15: =ROUND(ABS(淡江大學_p3!E41),0) -> 2157376 | F15: =ROUND(ABS(淡江大學_p3!F41),0) -> 2148624 | G15: =ROUND(ABS(淡江大學_p3!G41),0) -> 2139872 | H15: =ROUND(ABS(淡江大學_p3!H41),0) -> 2131120 | I15: =ROUND(ABS(淡江大學_p3!I41),0) -> 2122368 | J15: =ROUND(ABS(淡江大學_p3!J41),0) -> 2113616 | K15: =ROUND(ABS(淡江大學_p3!K41),0) -> 2104864 | ... W15: =ROUND(ABS(淡江大學_p3!W41),0) -> 1999839
B16: 淡江大學 | D16: =ROUND(ABS(淡江大學_p4!D41),0) -> 2166128 | E16: =ROUND(ABS(淡江大學_p4!E41),0) -> 2157376 | F16: =ROUND(ABS(淡江大學_p4!F41),0) -> 2148624 | G16: =ROUND(ABS(淡江大學_p4!G41),0) -> 2139872 | H16: =ROUND(ABS(淡江大學_p4!H41),0) -> 2131120 | I16: =ROUND(ABS(淡江大學_p4!I41),0) -> 2122368 | J16: =ROUND(ABS(淡江大學_p4!J41),0) -> 2113616 | K16: =ROUND(ABS(淡江大學_p4!K41),0) -> 2104864 | ... W16: =ROUND(ABS(淡江大學_p4!W41),0) -> 1999839
C17: 預估收入/年總計 | D17: =SUM(D13:D16) -> 8664512 | E17: =SUM(E13:E16) -> 8629504 | F17: =SUM(F13:F16) -> 8594496 | G17: =SUM(G13:G16) -> 8559488 | H17: =SUM(H13:H16) -> 8524480 | I17: =SUM(I13:I16) -> 8489472 | J17: =SUM(J13:J16) -> 8454464 | K17: =SUM(K13:K16) -> 8419456 | ... W17: =SUM(W13:W16) -> 7999356
C18: 年份 | D18: 2020 | E18: 2021 | F18: 2022 | G18: 2023 | H18: 2024 | I18: 2025 | J18: 2026 | K18: 2027 | L18: 2028 | M18: 2029 | N18: 2030 | O18: 2031 | P18: 2032 | Q18: 2033 | R18: 2034 | S18: 2035 | T18: 2036 | U18: 2037 | V18: 2038 | W18: 2039
C19: 租金
B20: 淡江大學 | D20: =ROUND(ABS(淡江大學_p2!D45),0) -> 290201 | E20: =ROUND(ABS(淡江大學_p2!E45),0) -> 290201 | F20: =ROUND(ABS(淡江大學_p2!F45),0) -> 290201 | G20: =ROUND(ABS(淡江大學_p2!G45),0) -> 290201 | H20: =ROUND(ABS(淡江大學_p2!H45),0) -> 290201 | I20: =ROUND(ABS(淡江大學_p2!I45),0) -> 290201 | J20: =ROUND(ABS(淡江大學_p2!J45),0) -> 290201 | K20: =ROUND(ABS(淡江大學_p2!K45),0) -> 290201 | ... W20: =ROUND(ABS(淡江大學_p2!W45),0) -> 290201
B21: 淡江大學 | D21: =ROUND(ABS(淡江大學_p5!D45),0) -> 290201 | E21: =ROUND(ABS(淡江大學_p5!E45),0) -> 290201 | F21: =ROUND(ABS(淡江大學_p5!F45),0) -> 290201 | G21: =ROUND(ABS(淡江大學_p5!G45),0) -> 290201 | H21: =ROUND(ABS(淡江大學_p5!H45),0) -> 290201 | I21: =ROUND(ABS(淡江大學_p5!I45),0) -> 290201 | J21: =ROUND(ABS(淡江大學_p5!J45),0) -> 290201 | K21: =ROUND(ABS(淡江大學_p5!K45),0) -> 290201 | ... W21: =ROUND(ABS(淡江大學_p5!W45),0) -> 290201
B22: 淡江大學 | D22: =ROUND(ABS(淡江大學_p3!D45),0) -> 290201 | E22: =ROUND(ABS(淡江大學_p3!E45),0) -> 290201 | F22: =ROUND(ABS(淡江大學_p3!F45),0) -> 290201 | G22: =ROUND(ABS(淡江大學_p3!G45),0) -> 290201 | H22: =ROUND(ABS(淡江大學_p3!H45),0) -> 290201 | I22: =ROUND(ABS(淡江大學_p3!I45),0) -> 290201 | J22: =ROUND(ABS(淡江大學_p3!J45),0) -> 290201 | K22: =ROUND(ABS(淡江大學_p3!K45),0) -> 290201 | ... W22: =ROUND(ABS(淡江大學_p3!W45),0) -> 290201
B23: 淡江大學 | D23: =ROUND(ABS(淡江大學_p4!D45),0) -> 290201 | E23: =ROUND(ABS(淡江大學_p4!E45),0) -> 290201 | F23: =ROUND(ABS(淡江大學_p4!F45),0) -> 290201 | G23: =ROUND(ABS(淡江大學_p4!G45),0) -> 290201 | H23: =ROUND(ABS(淡江大學_p4!H45),0) -> 290201 | I23: =ROUND(ABS(淡江大學_p4!I45),0) -> 290201 | J23: =ROUND(ABS(淡江大學_p4!J45),0) -> 290201 | K23: =ROUND(ABS(淡江大學_p4!K45),0) -> 290201 | ... W23: =ROUND(ABS(淡江大學_p4!W45),0) -> 290201
C24: 租金/年總計 | D24: =SUM(D20:D23) -> 1160804 | E24: =SUM(E20:E23) -> 1160804 | F24: =SUM(F20:F23) -> 1160804 | G24: =SUM(G20:G23) -> 1160804 | H24: =SUM(H20:H23) -> 1160804 | I24: =SUM(I20:I23) -> 1160804 | J24: =SUM(J20:J23) -> 1160804 | K24: =SUM(K20:K23) -> 1160804 | ... W24: =SUM(W20:W23) -> 1160804
C25: 年份 | D25: 2020 | E25: 2021 | F25: 2022 | G25: 2023 | H25: 2024 | I25: 2025 | J25: 2026 | K25: 2027 | L25: 2028 | M25: 2029 | N25: 2030 | O25: 2031 | P25: 2032 | Q25: 2033 | R25: 2034 | S25: 2035 | T25: 2036 | U25: 2037 | V25: 2038 | W25: 2039
C26: 運維
B27: 淡江大學 | D27: =ROUND(ABS(淡江大學_p2!D48),0) -> 174440 | E27: =ROUND(ABS(淡江大學_p2!E48),0) -> 174440 | F27: =ROUND(ABS(淡江大學_p2!F48),0) -> 174440 | G27: =ROUND(ABS(淡江大學_p2!G48),0) -> 174440 | H27: =ROUND(ABS(淡江大學_p2!H48),0) -> 174440 | I27: =ROUND(ABS(淡江大學_p2!I48),0) -> 174440 | J27: =ROUND(ABS(淡江大學_p2!J48),0) -> 174440 | K27: =ROUND(ABS(淡江大學_p2!K48),0) -> 174440 | ... W27: =ROUND(ABS(淡江大學_p2!W48),0) -> 174440
B28: 淡江大學 | D28: =ROUND(ABS(淡江大學_p5!D48),0) -> 174440 | E28: =ROUND(ABS(淡江大學_p5!E48),0) -> 174440 | F28: =ROUND(ABS(淡江大學_p5!F48),0) -> 174440 | G28: =ROUND(ABS(淡江大學_p5!G48),0) -> 174440 | H28: =ROUND(ABS(淡江大學_p5!H48),0) -> 174440 | I28: =ROUND(ABS(淡江大學_p5!I48),0) -> 174440 | J28: =ROUND(ABS(淡江大學_p5!J48),0) -> 174440 | K28: =ROUND(ABS(淡江大學_p5!K48),0) -> 174440 | ... W28: =ROUND(ABS(淡江大學_p5!W48),0) -> 174440
B29: 淡江大學 | D29: =ROUND(ABS(淡江大學_p3!D48),0) -> 174440 | E29: =ROUND(ABS(淡江大學_p3!E48),0) -> 174440 | F29: =ROUND(ABS(淡江大學_p3!F48),0) -> 174440 | G29: =ROUND(ABS(淡江大學_p3!G48),0) -> 174440 | H29: =ROUND(ABS(淡江大學_p3!H48),0) -> 174440 | I29: =ROUND(ABS(淡江大學_p3!I48),0) -> 174440 | J29: =ROUND(ABS(淡江大學_p3!J48),0) -> 174440 | K29: =ROUND(ABS(淡江大學_p3!K48),0) -> 174440 | ... W29: =ROUND(ABS(淡江大學_p3!W48),0) -> 174440
B30: 淡江大學 | D30: =ROUND(ABS(淡江大學_p4!D48),0) -> 174440 | E30: =ROUND(ABS(淡江大學_p4!E48),0) -> 174440 | F30: =ROUND(ABS(淡江大學_p4!F48),0) -> 174440 | G30: =ROUND(ABS(淡江大學_p4!G48),0) -> 174440 | H30: =ROUND(ABS(淡江大學_p4!H48),0) -> 174440 | I30: =ROUND(ABS(淡江大學_p4!I48),0) -> 174440 | J30: =ROUND(ABS(淡江大學_p4!J48),0) -> 174440 | K30: =ROUND(ABS(淡江大學_p4!K48),0) -> 174440 | ... W30: =ROUND(ABS(淡江大學_p4!W48),0) -> 174440
C31: 運維/年總計 | D31: =SUM(D27:D30) -> 697760 | E31: =SUM(E27:E30) -> 697760 | F31: =SUM(F27:F30) -> 697760 | G31: =SUM(G27:G30) -> 697760 | H31: =SUM(H27:H30) -> 697760 | I31: =SUM(I27:I30) -> 697760 | J31: =SUM(J27:J30) -> 697760 | K31: =SUM(K27:K30) -> 697760 | ... W31: =SUM(W27:W30) -> 697760
C32: 年份 | D32: 2020 | E32: 2021 | F32: 2022 | G32: 2023 | H32: 2024 | I32: 2025 | J32: 2026 | K32: 2027 | L32: 2028 | M32: 2029 | N32: 2030 | O32: 2031 | P32: 2032 | Q32: 2033 | R32: 2034 | S32: 2035 | T32: 2036 | U32: 2037 | V32: 2038 | W32: 2039
C33: 保險
B34: 淡江大學 | D34: =ROUND(ABS(淡江大學_p2!D49),0) -> 43174 | E34: =ROUND(ABS(淡江大學_p2!E49),0) -> 43174 | F34: =ROUND(ABS(淡江大學_p2!F49),0) -> 43174 | G34: =ROUND(ABS(淡江大學_p2!G49),0) -> 43174 | H34: =ROUND(ABS(淡江大學_p2!H49),0) -> 43174 | I34: =ROUND(ABS(淡江大學_p2!I49),0) -> 43174 | J34: =ROUND(ABS(淡江大學_p2!J49),0) -> 43174 | K34: =ROUND(ABS(淡江大學_p2!K49),0) -> 43174 | ... W34: =ROUND(ABS(淡江大學_p2!W49),0) -> 43174
B35: 淡江大學 | D35: =ROUND(ABS(淡江大學_p5!D49),0) -> 35324 | E35: =ROUND(ABS(淡江大學_p5!E49),0) -> 35324 | F35: =ROUND(ABS(淡江大學_p5!F49),0) -> 35324 | G35: =ROUND(ABS(淡江大學_p5!G49),0) -> 35324 | H35: =ROUND(ABS(淡江大學_p5!H49),0) -> 35324 | I35: =ROUND(ABS(淡江大學_p5!I49),0) -> 35324 | J35: =ROUND(ABS(淡江大學_p5!J49),0) -> 35324 | K35: =ROUND(ABS(淡江大學_p5!K49),0) -> 35324 | ... W35: =ROUND(ABS(淡江大學_p5!W49),0) -> 35324
B36: 淡江大學 | D36: =ROUND(ABS(淡江大學_p3!D49),0) -> 40557 | E36: =ROUND(ABS(淡江大學_p3!E49),0) -> 40557 | F36: =ROUND(ABS(淡江大學_p3!F49),0) -> 40557 | G36: =ROUND(ABS(淡江大學_p3!G49),0) -> 40557 | H36: =ROUND(ABS(淡江大學_p3!H49),0) -> 40557 | I36: =ROUND(ABS(淡江大學_p3!I49),0) -> 40557 | J36: =ROUND(ABS(淡江大學_p3!J49),0) -> 40557 | K36: =ROUND(ABS(淡江大學_p3!K49),0) -> 40557 | ... W36: =ROUND(ABS(淡江大學_p3!W49),0) -> 40557
B37: 淡江大學 | D37: =ROUND(ABS(淡江大學_p4!D49),0) -> 37941 | E37: =ROUND(ABS(淡江大學_p4!E49),0) -> 37941 | F37: =ROUND(ABS(淡江大學_p4!F49),0) -> 37941 | G37: =ROUND(ABS(淡江大學_p4!G49),0) -> 37941 | H37: =ROUND(ABS(淡江大學_p4!H49),0) -> 37941 | I37: =ROUND(ABS(淡江大學_p4!I49),0) -> 37941 | J37: =ROUND(ABS(淡江大學_p4!J49),0) -> 37941 | K37: =ROUND(ABS(淡江大學_p4!K49),0) -> 37941 | ... W37: =ROUND(ABS(淡江大學_p4!W49),0) -> 37941
C38: 保險/年總計 | D38: =SUM(D34:D37) -> 156996 | E38: =SUM(E34:E37) -> 156996 | F38: =SUM(F34:F37) -> 156996 | G38: =SUM(G34:G37) -> 156996 | H38: =SUM(H34:H37) -> 156996 | I38: =SUM(I34:I37) -> 156996 | J38: =SUM(J34:J37) -> 156996 | K38: =SUM(K34:K37) -> 156996 | ... W38: =SUM(W34:W37) -> 156996
C39: 年份 | D39: 2020 | E39: 2021 | F39: 2022 | G39: 2023 | H39: 2024 | I39: 2025 | J39: 2026 | K39: 2027 | L39: 2028 | M39: 2029 | N39: 2030 | O39: 2031 | P39: 2032 | Q39: 2033 | R39: 2034 | S39: 2035 | T39: 2036 | U39: 2037 | V39: 2038 | W39: 2039
C40: 模組回收費
B41: 淡江大學 | D41: =ROUND(ABS(淡江大學_p2!D50),0) -> 43610 | E41: =ROUND(ABS(淡江大學_p2!E50),0) -> 43610 | F41: =ROUND(ABS(淡江大學_p2!F50),0) -> 43610 | G41: =ROUND(ABS(淡江大學_p2!G50),0) -> 43610 | H41: =ROUND(ABS(淡江大學_p2!H50),0) -> 43610 | I41: =ROUND(ABS(淡江大學_p2!I50),0) -> 43610 | J41: =ROUND(ABS(淡江大學_p2!J50),0) -> 43610 | K41: =ROUND(ABS(淡江大學_p2!K50),0) -> 43610 | ... W41: =ROUND(ABS(淡江大學_p2!W50),0) -> 0
B42: 淡江大學 | D42: =ROUND(ABS(淡江大學_p5!D50),0) -> 43610 | E42: =ROUND(ABS(淡江大學_p5!E50),0) -> 43610 | F42: =ROUND(ABS(淡江大學_p5!F50),0) -> 43610 | G42: =ROUND(ABS(淡江大學_p5!G50),0) -> 43610 | H42: =ROUND(ABS(淡江大學_p5!H50),0) -> 43610 | I42: =ROUND(ABS(淡江大學_p5!I50),0) -> 43610 | J42: =ROUND(ABS(淡江大學_p5!J50),0) -> 43610 | K42: =ROUND(ABS(淡江大學_p5!K50),0) -> 43610 | ... W42: =ROUND(ABS(淡江大學_p5!W50),0) -> 0
B43: 淡江大學 | D43: =ROUND(ABS(淡江大學_p3!D50),0) -> 43610 | E43: =ROUND(ABS(淡江大學_p3!E50),0) -> 43610 | F43: =ROUND(ABS(淡江大學_p3!F50),0) -> 43610 | G43: =ROUND(ABS(淡江大學_p3!G50),0) -> 43610 | H43: =ROUND(ABS(淡江大學_p3!H50),0) -> 43610 | I43: =ROUND(ABS(淡江大學_p3!I50),0) -> 43610 | J43: =ROUND(ABS(淡江大學_p3!J50),0) -> 43610 | K43: =ROUND(ABS(淡江大學_p3!K50),0) -> 43610 | ... W43: =ROUND(ABS(淡江大學_p3!W50),0) -> 0
B44: 淡江大學 | D44: =ROUND(ABS(淡江大學_p4!D50),0) -> 43610 | E44: =ROUND(ABS(淡江大學_p4!E50),0) -> 43610 | F44: =ROUND(ABS(淡江大學_p4!F50),0) -> 43610 | G44: =ROUND(ABS(淡江大學_p4!G50),0) -> 43610 | H44: =ROUND(ABS(淡江大學_p4!H50),0) -> 43610 | I44: =ROUND(ABS(淡江大學_p4!I50),0) -> 43610 | J44: =ROUND(ABS(淡江大學_p4!J50),0) -> 43610 | K44: =ROUND(ABS(淡江大學_p4!K50),0) -> 43610 | ... W44: =ROUND(ABS(淡江大學_p4!W50),0) -> 0
C45: 模組回收費/年總計 | D45: =SUM(D41:D44) -> 174440 | E45: =SUM(E41:E44) -> 174440 | F45: =SUM(F41:F44) -> 174440 | G45: =SUM(G41:G44) -> 174440 | H45: =SUM(H41:H44) -> 174440 | I45: =SUM(I41:I44) -> 174440 | J45: =SUM(J41:J44) -> 174440 | K45: =SUM(K41:K44) -> 174440 | ... W45: =SUM(W41:W44) -> 0
C46: 年份 | D46: 2020 | E46: 2021 | F46: 2022 | G46: 2023 | H46: 2024 | I46: 2025 | J46: 2026 | K46: 2027 | L46: 2028 | M46: 2029 | N46: 2030 | O46: 2031 | P46: 2032 | Q46: 2033 | R46: 2034 | S46: 2035 | T46: 2036 | U46: 2037 | V46: 2038 | W46: 2039
C47: 所得稅
B48: 淡江大學 | D48: =ROUND(ABS(淡江大學_p2!D54),0) -> 166669 | E48: =ROUND(ABS(淡江大學_p2!E54),0) -> 106878 | F48: =ROUND(ABS(淡江大學_p2!F54),0) -> 105128 | G48: =ROUND(ABS(淡江大學_p2!G54),0) -> 103377 | H48: =ROUND(ABS(淡江大學_p2!H54),0) -> 101627 | I48: =ROUND(ABS(淡江大學_p2!I54),0) -> 99877 | J48: =ROUND(ABS(淡江大學_p2!J54),0) -> 98126 | K48: =ROUND(ABS(淡江大學_p2!K54),0) -> 96376 | ... W48: =ROUND(ABS(淡江大學_p2!W54),0) -> 84093
B49: 淡江大學 | D49: =ROUND(ABS(淡江大學_p5!D54),0) -> 205619 | E49: =ROUND(ABS(淡江大學_p5!E54),0) -> 145828 | F49: =ROUND(ABS(淡江大學_p5!F54),0) -> 144078 | G49: =ROUND(ABS(淡江大學_p5!G54),0) -> 142327 | H49: =ROUND(ABS(淡江大學_p5!H54),0) -> 140577 | I49: =ROUND(ABS(淡江大學_p5!I54),0) -> 138827 | J49: =ROUND(ABS(淡江大學_p5!J54),0) -> 137076 | K49: =ROUND(ABS(淡江大學_p5!K54),0) -> 135326 | ... W49: =ROUND(ABS(淡江大學_p5!W54),0) -> 123043
B50: 淡江大學 | D50: =ROUND(ABS(淡江大學_p3!D54),0) -> 179652 | E50: =ROUND(ABS(淡江大學_p3!E54),0) -> 119862 | F50: =ROUND(ABS(淡江大學_p3!F54),0) -> 118111 | G50: =ROUND(ABS(淡江大學_p3!G54),0) -> 116361 | H50: =ROUND(ABS(淡江大學_p3!H54),0) -> 114610 | I50: =ROUND(ABS(淡江大學_p3!I54),0) -> 112860 | J50: =ROUND(ABS(淡江大學_p3!J54),0) -> 111109 | K50: =ROUND(ABS(淡江大學_p3!K54),0) -> 109359 | ... W50: =ROUND(ABS(淡江大學_p3!W54),0) -> 97076
B51: 淡江大學 | D51: =ROUND(ABS(淡江大學_p4!D54),0) -> 192635 | E51: =ROUND(ABS(淡江大學_p4!E54),0) -> 132845 | F51: =ROUND(ABS(淡江大學_p4!F54),0) -> 131094 | G51: =ROUND(ABS(淡江大學_p4!G54),0) -> 129344 | H51: =ROUND(ABS(淡江大學_p4!H54),0) -> 127594 | I51: =ROUND(ABS(淡江大學_p4!I54),0) -> 125843 | J51: =ROUND(ABS(淡江大學_p4!J54),0) -> 124093 | K51: =ROUND(ABS(淡江大學_p4!K54),0) -> 122342 | ... W51: =ROUND(ABS(淡江大學_p4!W54),0) -> 110060
C52: 所得稅/年總計 | D52: =SUM(D48:D51) -> 744575 | E52: =SUM(E48:E51) -> 505413 | F52: =SUM(F48:F51) -> 498411 | G52: =SUM(G48:G51) -> 491409 | H52: =SUM(H48:H51) -> 484408 | I52: =SUM(I48:I51) -> 477407 | J52: =SUM(J48:J51) -> 470404 | K52: =SUM(K48:K51) -> 463403 | ... W52: =SUM(W48:W51) -> 414272
C53: 年份 | D53: 2020 | E53: 2021 | F53: 2022 | G53: 2023 | H53: 2024 | I53: 2025 | J53: 2026 | K53: 2027 | L53: 2028 | M53: 2029 | N53: 2030 | O53: 2031 | P53: 2032 | Q53: 2033 | R53: 2034 | S53: 2035 | T53: 2036 | U53: 2037 | V53: 2038 | W53: 2039
C54: 設備折舊
B55: 淡江大學 | D55: =ROUND(ABS(淡江大學_p2!D67),0) -> 1071560 | E55: =ROUND(ABS(淡江大學_p2!E67),0) -> 1071560 | F55: =ROUND(ABS(淡江大學_p2!F67),0) -> 1071560 | G55: =ROUND(ABS(淡江大學_p2!G67),0) -> 1071560 | H55: =ROUND(ABS(淡江大學_p2!H67),0) -> 1071560 | I55: =ROUND(ABS(淡江大學_p2!I67),0) -> 1071560 | J55: =ROUND(ABS(淡江大學_p2!J67),0) -> 1071560 | K55: =ROUND(ABS(淡江大學_p2!K67),0) -> 1071560 | ... W55: =ROUND(ABS(淡江大學_p2!W67),0) -> 1071560
B56: 淡江大學 | D56: =ROUND(ABS(淡江大學_p5!D67),0) -> 884660 | E56: =ROUND(ABS(淡江大學_p5!E67),0) -> 884660 | F56: =ROUND(ABS(淡江大學_p5!F67),0) -> 884660 | G56: =ROUND(ABS(淡江大學_p5!G67),0) -> 884660 | H56: =ROUND(ABS(淡江大學_p5!H67),0) -> 884660 | I56: =ROUND(ABS(淡江大學_p5!I67),0) -> 884660 | J56: =ROUND(ABS(淡江大學_p5!J67),0) -> 884660 | K56: =ROUND(ABS(淡江大學_p5!K67),0) -> 884660 | ... W56: =ROUND(ABS(淡江大學_p5!W67),0) -> 884660
B57: 淡江大學 | D57: =ROUND(ABS(淡江大學_p3!D67),0) -> 1009260 | E57: =ROUND(ABS(淡江大學_p3!E67),0) -> 1009260 | F57: =ROUND(ABS(淡江大學_p3!F67),0) -> 1009260 | G57: =ROUND(ABS(淡江大學_p3!G67),0) -> 1009260 | H57: =ROUND(ABS(淡江大學_p3!H67),0) -> 1009260 | I57: =ROUND(ABS(淡江大學_p3!I67),0) -> 1009260 | J57: =ROUND(ABS(淡江大學_p3!J67),0) -> 1009260 | K57: =ROUND(ABS(淡江大學_p3!K67),0) -> 1009260 | ... W57: =ROUND(ABS(淡江大學_p3!W67),0) -> 1009260
B58: 淡江大學 | D58: =ROUND(ABS(淡江大學_p4!D67),0) -> 946960 | E58: =ROUND(ABS(淡江大學_p4!E67),0) -> 946960 | F58: =ROUND(ABS(淡江大學_p4!F67),0) -> 946960 | G58: =ROUND(ABS(淡江大學_p4!G67),0) -> 946960 | H58: =ROUND(ABS(淡江大學_p4!H67),0) -> 946960 | I58: =ROUND(ABS(淡江大學_p4!I67),0) -> 946960 | J58: =ROUND(ABS(淡江大學_p4!J67),0) -> 946960 | K58: =ROUND(ABS(淡江大學_p4!K67),0) -> 946960 | ... W58: =ROUND(ABS(淡江大學_p4!W67),0) -> 946960
C59: 設備折舊/年總計 | D59: =SUM(D55:D58) -> 3912440 | E59: =SUM(E55:E58) -> 3912440 | F59: =SUM(F55:F58) -> 3912440 | G59: =SUM(G55:G58) -> 3912440 | H59: =SUM(H55:H58) -> 3912440 | I59: =SUM(I55:I58) -> 3912440 | J59: =SUM(J55:J58) -> 3912440 | K59: =SUM(K55:K58) -> 3912440 | ... W59: =SUM(W55:W58) -> 3912440
B61: 貸款成數(%) | C61: 80
B62: 還款期數 | C62: 15
B63: 股利比率(%) | C63: 90
B64: 年底減資攤還期數 | C64: 4
B65: 銀行利率(%) | C65: 3
C66: 年份 | D66: 2020 | E66: 2021 | F66: 2022 | G66: 2023 | H66: 2024 | I66: 2025 | J66: 2026 | K66: 2027 | L66: 2028 | M66: 2029 | N66: 2030 | O66: 2031 | P66: 2032 | Q66: 2033 | R66: 2034 | S66: 2035 | T66: 2036 | U66: 2037 | V66: 2038 | W66: 2039
B67: 0
B68: (Unit : Currency) | C68: 0 | D68: 1 | E68: 2 | F68: 3 | G68: 4 | H68: 5 | I68: 6 | J68: 7 | K68: 8 | L68: 9 | M68: 10 | N68: 11 | O68: 12 | P68: 13 | Q68: 14 | R68: 15 | S68: 16 | T68: 17 | U68: 18 | V68: 19 | W68: 20
B69: 發電度數(KWH) | C69: 0 | D69: =D10 -> 2166128 | E69: =E10 -> 2157376 | F69: =F10 -> 2148624 | G69: =G10 -> 2139872 | H69: =H10 -> 2131120 | I69: =I10 -> 2122368 | J69: =J10 -> 2113616 | K69: =K10 -> 2104864 | ... W69: =W10 -> 1999840
B70: Inflow : 電費收入 | C70: - | D70: =D17 -> 8664512 | E70: =E17 -> 8629504 | F70: =F17 -> 8594496 | G70: =G17 -> 8559488 | H70: =H17 -> 8524480 | I70: =I17 -> 8489472 | J70: =J17 -> 8454464 | K70: =K17 -> 8419456 | ... W70: =W17 -> 7999356
B71: Inflow : 政府補助 | C71: - | G71: - | H71: - | I71: - | J71: - | K71: - | L71: - | M71: - | N71: - | O71: - | P71: - | Q71: - | R71: - | S71: - | T71: - | U71: - | V71: - | W71: -
B72: Inflow : 銀行借款
B73: Outflow : 設備費用 | C73: =-SUM(D59:W59) -> -78248800
B74: Outflow : 設備放置區域租金 | C74: - | D74: =-D24 -> -1160804 | E74: =-E24 -> -1160804 | F74: =-F24 -> -1160804 | G74: =-G24 -> -1160804 | H74: =-H24 -> -1160804 | I74: =-I24 -> -1160804 | J74: =-J24 -> -1160804 | K74: =-K24 -> -1160804 | ... W74: =-W24 -> -1160804
B75: Outflow : 返還借款
B76: Outflow : 利息費用 | C76: -
B77: Outflow : 維運費 | C77: - | D77: =-D31 -> -697760 | E77: =-E31 -> -697760 | F77: =-F31 -> -697760 | G77: =-G31 -> -697760 | H77: =-H31 -> -697760 | I77: =-I31 -> -697760 | J77: =-J31 -> -697760 | K77: =-K31 -> -697760 | ... W77: =-W31 -> -697760
B78: Outflow : 保險費 | C78: - | D78: =-D38 -> -156996 | E78: =-E38 -> -156996 | F78: =-F38 -> -156996 | G78: =-G38 -> -156996 | H78: =-H38 -> -156996 | I78: =-I38 -> -156996 | J78: =-J38 -> -156996 | K78: =-K38 -> -156996 | ... W78: =-W38 -> -156996
B79: Outflow : 模組回收費 | D79: =-D45 -> -174440 | E79: =-E45 -> -174440 | F79: =-F45 -> -174440 | G79: =-G45 -> -174440 | H79: =-H45 -> -174440 | I79: =-I45 -> -174440 | J79: =-J45 -> -174440 | K79: =-K45 -> -174440 | ... W79: =-W45 -> 0
B80: Outflow : 其它費用(人事薪資…等)
B81: 1%管理費
B82: 績效獎金
B83: 所得稅20% | D83: =-D106 -> -136820.16 | E83: =-E106 -> -154858.18 | F83: =-F106 -> -172896.19 | G83: =-G106 -> -190934.21 | H83: =-H106 -> -208972.22 | I83: =-I106 -> -227010.24 | J83: =-J106 -> -245048.26 | K83: =-K106 -> -263086.27 | ... W83: =-W106 -> -414271.2
B84: 現金流 | C84: =C73 -> -78248800 | D84: =SUM(D70:D83) -> 6337691.8 | E84: =SUM(E70:E83) -> 6284645.8 | F84: =SUM(F70:F83) -> 6231599.8 | G84: =SUM(G70:G83) -> 6178553.8 | H84: =SUM(H70:H83) -> 6125507.8 | I84: =SUM(I70:I83) -> 6072461.8 | J84: =SUM(J70:J83) -> 6019415.7 | K84: =SUM(K70:K83) -> 5966369.7 | ... W84: =SUM(W70:W83) -> 5569524.8
B85: 累計現金流 | D85: =C55+D55 -> 1071560 | E85: =D56+E55 -> 1956220 | F85: =E56+F55 -> 1956220 | G85: =F56+G55 -> 1956220 | H85: =G56+H55 -> 1956220 | I85: =H56+I55 -> 1956220 | J85: =I56+J55 -> 1956220 | K85: =J56+K55 -> 1956220 | L85: =K56+L55 -> 1956220 | ... W85: =V56+W55 -> 1956220
B86: 回收年限評估 | D86: =IF((D56)>0,"回收","未回收") -> 回收 | E86: =IF((E56)>0,"回收","未回收") -> 回收 | F86: =IF((F56)>0,"回收","未回收") -> 回收 | G86: =IF((G56)>0,"回收","未回收") -> 回收 | H86: =IF((H56)>0,"回收","未回收") -> 回收 | I86: =IF((I56)>0,"回收","未回收") -> 回收 | J86: =IF((J56)>0,"回收","未回收") -> 回收 | K86: =IF((K56)>0,"回收","未回收") -> 回收 | ... W86: =IF((W56)>0,"回收","未回收") -> 回收
B87: 專案法IRR | C87: =IRR(C84:W84) -> 0.044172268
C89: 年份 | D89: 2020 | E89: 2021 | F89: 2022 | G89: 2023 | H89: 2024 | I89: 2025 | J89: 2026 | K89: 2027 | L89: 2028 | M89: 2029 | N89: 2030 | O89: 2031 | P89: 2032 | Q89: 2033 | R89: 2034 | S89: 2035 | T89: 2036 | U89: 2037 | V89: 2038 | W89: 2039
B90: 0 | T90: 償還年限
B91: (Unit : Currency) | C91: 0 | D91: 1 | E91: 2 | F91: 3 | G91: 4 | H91: 5 | I91: 6 | J91: 7 | K91: 8 | L91: 9 | M91: 10 | N91: 11 | O91: 12 | P91: 13 | Q91: 14 | R91: 15 | S91: 16 | T91: 17 | U91: 18 | V91: 19 | W91: 20
B92: 發電度數(KWH) | C92: 0 | D92: =D10 -> 2166128 | E92: =E10 -> 2157376 | F92: =F10 -> 2148624 | G92: =G10 -> 2139872 | H92: =H10 -> 2131120 | I92: =I10 -> 2122368 | J92: =J10 -> 2113616 | K92: =K10 -> 2104864 | ... W92: =W10 -> 1999840
B93: Inflow : 電費收入 | C93: - | D93: =D17 -> 8664512 | E93: =E17 -> 8629504 | F93: =F17 -> 8594496 | G93: =G17 -> 8559488 | H93: =H17 -> 8524480 | I93: =I17 -> 8489472 | J93: =J17 -> 8454464 | K93: =K17 -> 8419456 | ... W93: =W17 -> 7999356
B94: Inflow : 政府補助 | C94: - | G94: - | H94: - | I94: - | J94: - | K94: - | L94: - | M94: - | N94: - | O94: - | P94: - | Q94: - | R94: - | S94: - | T94: - | U94: - | V94: - | W94: -
B95: Inflow : 銀行借款
B96: Outflow : 設備折舊 | D96: =-D59 -> -3912440 | E96: =-E59 -> -3912440 | F96: =-F59 -> -3912440 | G96: =-G59 -> -3912440 | H96: =-H59 -> -3912440 | I96: =-I59 -> -3912440 | J96: =-J59 -> -3912440 | K96: =-K59 -> -3912440 | ... W96: =-W59 -> -3912440
B97: Outflow : 設備放置區域租金 | C97: - | D97: =-D24 -> -1160804 | E97: =-E24 -> -1160804 | F97: =-F24 -> -1160804 | G97: =-G24 -> -1160804 | H97: =-H24 -> -1160804 | I97: =-I24 -> -1160804 | J97: =-J24 -> -1160804 | K97: =-K24 -> -1160804 | ... W97: =-W24 -> -1160804
B98: Outflow : 返還借款
B99: Outflow : 利息費用 | C99: - | D99: =-D137*C65/100 -> -1877971.2 | E99: =-E137*C65/100 -> -1752773.1 | F99: =-F137*C65/100 -> -1627575 | G99: =-G137*C65/100 -> -1502377 | H99: =-H137*C65/100 -> -1377178.9 | I99: =-I137*C65/100 -> -1251980.8 | J99: =-J137*C65/100 -> -1126782.7 | K99: =-K137*C65/100 -> -1001584.6 | L99: =-L137*C65/100 -> -876386.56 | M99: =-M137*C65/100 -> -751188.48 | N99: =-N137*C65/100 -> -625990.4 | O99: =-O137*C65/100 -> -500792.32 | P99: =-P137*C65/100 -> -375594.24 | Q99: =-Q137*C65/100 -> -250396.16 | R99: =-R137*C65/100 -> -125198.08 | S99: =-S137*C65/100 -> 0 | T99: =-T137*C65/100 -> 0 | U99: =-U137*C65/100 -> 0 | V99: =-V137*C65/100 -> 0 | W99: =-W137*C65/100 -> 0
B100: Outflow : 維運費 | C100: - | D100: =-D31 -> -697760 | E100: =-E31 -> -697760 | F100: =-F31 -> -697760 | G100: =-G31 -> -697760 | H100: =-H31 -> -697760 | I100: =-I31 -> -697760 | J100: =-J31 -> -697760 | K100: =-K31 -> -697760 | ... W100: =-W31 -> -697760
B101: Outflow : 保險費 | C101: - | D101: =-D38 -> -156996 | E101: =-E38 -> -156996 | F101: =-F38 -> -156996 | G101: =-G38 -> -156996 | H101: =-H38 -> -156996 | I101: =-I38 -> -156996 | J101: =-J38 -> -156996 | K101: =-K38 -> -156996 | ... W101: =-W38 -> -156996
B102: Outflow : 模組回收費 | D102: =-D45 -> -174440 | E102: =-E45 -> -174440 | F102: =-F45 -> -174440 | G102: =-G45 -> -174440 | H102: =-H45 -> -174440 | I102: =-I45 -> -174440 | J102: =-J45 -> -174440 | K102: =-K45 -> -174440 | ... W102: =-W45 -> 0
B103: Outflow : 其它費用(人事薪資…等)
B104: 1%管理費
B105: 稅前淨利 | D105: =SUM(D93:D104) -> 684100.8 | E105: =SUM(E93:E104) -> 774290.88 | F105: =SUM(F93:F104) -> 864480.96 | G105: =SUM(G93:G104) -> 954671.04 | H105: =SUM(H93:H104) -> 1044861.1 | I105: =SUM(I93:I104) -> 1135051.2 | J105: =SUM(J93:J104) -> 1225241.3 | K105: =SUM(K93:K104) -> 1315431.4 | ... W105: =SUM(W93:W104) -> 2071356
...

Sheet 淡江大學_p2
B1: 電站基本資料 | F1: 說明 | P1: =1-D11 -> 0.99 | Q1: =P1-$D12 -> 0.986 | R1: =Q1-$D12 -> 0.982 | S1: =R1-$D12 -> 0.978 | T1: =S1-$D12 -> 0.974 | U1: =T1-$D12 -> 0.97 | V1: =U1-$D12 -> 0.966 | W1: =V1-$D12 -> 0.962 | X1: =W1-$D12 -> 0.958 | ... AI1: =AH1-$D12 -> 0.914
B2: 電站名稱 | C2: 淡江大學 | D2: - | E2: - | F2: 填入本案場名稱
B3: 電站壽命 | C3: 20 | D3: - | E3: - | F3: 預設 20 年，代表財務評估年期。若合約年限不同可依實際情況修改
B4: 建置量(kWp) | C4: 436.1 | D4: - | E4: - | F4: 填入裝置容量（kWp），通常由設計圖面或報價書取得 | M4: 情境編號: 2
B5: 起始年度 | C5: 2020 | D5: 結束年度 | E5: 2039 | F5: 填入電站預計掛表的西元年份（例：2025）。結束年度會自動計算 | M5: 第1次滾算摘要
M6: 價金: 33000
B7: 綜合損益表 | M7: 專案IRR: 3.16
B8: 收入 | M8: 權益法IRR: 6.19
B9: 收支項目 | C9: 相關參數 | D9: 參數數值 | E9: 年限 | F9: 說明 | M9: 利潤率: 30.00%
B10: 電費收入 | C10: 年度AC併網總發電量 | D10: 547002 | E10: 20 | F10: 預估年發電量（kWh），通常來自 PVsyst 模擬或估算：裝置容量 × 年日照時數 × 系統效率 | M10: 第1次滾算，減少 2000 元 - 現金模式，每次減少 2000 元
C11: 首年衰退率 | D11: 0.01 | F11: 第一年發電衰退比率，請填小數（例：1% → 填 0.01）。一般首年衰退約 1~2%(請參考模組規格書)
C12: 次年衰退率 | D12: 0.004 | F12: 第二年起每年固定衰退比率，請填小數（例：0.4% → 填 0.004）。一般約 0.4~0.7%(請參考模組規格書)
C13: 躉售費率(FIT) / 綠電費率 | D13: 4 | F13: 與台電簽訂的躉購費率或綠電合約費率，單位：元/度。請參考台電公告或合約內容
B14: 支出
B15: 收支項目 | C15: 相關參數 | D15: 參數數值 | E15: 攤提年限 | F15: 說明
B16: 設備費用(價金) | C16: 每kWp設備成本 | D16: 33000 | E16: 20 | F16: 每峰瓩設備成本（元/kWp），包含模組、逆變器、支架等硬體，不含工程施工費
C17: 信邦利潤率(ex:20%填0.2) | D17: 0.3 | F17: 公司在設備費用上加計的利潤比率，請填小數（例：20% → 填 0.2）
C18: 開發費 | D18: 2000 | F18: 前期開發費用（元），含可行性評估、申請規費、地主溝通等。若無則填 0
B19: 租金費用 | C19: 租金計算方式 | D19: 1 | E19: 20 | F19: 填 1 = 固定年租金（需填方式1參數）；填 2 = 依電費收入抽成（需填方式2參數）
C20: 【方式1參數】每年相同價格 | D20: 290201 | E20: 20 | F20: 租金計算方式選「1」時填寫，固定年租金金額（元/年），套用至整個電站壽命期
C21: 【方式2參數】抽成比率 | D21: 0 | E21: 20 | F21: 租金計算方式選「2」時填寫，請填小數（例：10% → 填 0.1）。租金 = 當年電費收入 × 抽成比率
B22: 運維費用 | C22: 每kw運維成本 | D22: 400 | E22: 20 | F22: 每峰瓩每年運維費用（元/kWp/年），含清洗、巡檢、維修等。
B23: 保險費用 | C23: 占整體設備費用比例 | D23: 0.003 | E23: 20 | F23: 保險費佔設備總費用比率，填小數（例：0.3% → 填 0.003）。預設 0.003，可依投保條件調整
B24: 模組回收費用 | C24: 每kw模組回收成本 | D24: 1000 | E24: 10 | F24: 每峰瓩模組廢棄回收費用（元/kWp），於第 1~10 年計提（攤提 10 年）。
B25: 利息費用 | C25: 銀行利率 | D25: 0.0256 | E25: 20 | F25: 向銀行貸款的年利率，填小數（例：2.56% → 填 0.0256）。請依銀行核准利率填入
B26: 所得稅 | C26: 所得稅率 | D26: 0.2 | E26: 20 | F26: 公司所得稅率，填小數（例：20% → 填 0.2）。預設 0.2，通常不需更改
B29: 現金流量表
B30: 金流項目 | C30: 相關參數 | D30: 參數數值 | F30: 說明
B31: 貸款成數 | C31: 占總設備費用比例 | D31: 0.8 | F31: 貸款佔設備總費用比例，填小數（例：80% → 填 0.8）。預設 0.8 代表貸八成、自備二成
B32: 貸款還款 | C32: 攤還期數 | D32: 15 | F32: 貸款還款年數（年）。預設 15 年，代表分 15 年平均攤還本金
B33: 現金股利 | C33: 股利比率 | D33: 0.9 | F33: 稅後現金流中分配給股東的比例，填小數（例：90% → 填 0.9）
B34: 年底減資 | C34: 攤還期數 | D34: 4 | F34: 年底減資返還股東的年數。預設 4 年，代表 倒數 4 年進行減資，加速資金返還
C37: 年份 | D37: 2020 | E37: 2021 | F37: 2022 | G37: 2023 | H37: 2024 | I37: 2025 | J37: 2026 | K37: 2027 | L37: 2028 | M37: 2029 | N37: 2030 | O37: 2031 | P37: 2032 | Q37: 2033 | R37: 2034 | S37: 2035 | T37: 2036 | U37: 2037 | V37: 2038 | W37: 2039
B38: 0
B39: (Unit : Currency) | C39: 0 | D39: 1 | E39: 2 | F39: 3 | G39: 4 | H39: 5 | I39: 6 | J39: 7 | K39: 8 | L39: 9 | M39: 10 | N39: 11 | O39: 12 | P39: 13 | Q39: 14 | R39: 15 | S39: 16 | T39: 17 | U39: 18 | V39: 19 | W39: 20
B40: 發電度數(KWH) | C40: 0 | D40: =$D$10*P1 -> 541531.98 | E40: =$D$10*Q1 -> 539343.97 | F40: =$D$10*R1 -> 537155.96 | G40: =$D$10*S1 -> 534967.96 | H40: =$D$10*T1 -> 532779.95 | I40: =$D$10*U1 -> 530591.94 | J40: =$D$10*V1 -> 528403.93 | K40: =$D$10*W1 -> 526215.92 | ... W40: =$D$10*AI1 -> 499959.83
B41: Inflow : 電費收入 | C41: - | D41: =D40*$D$13 -> 2166127.9 | E41: =E40*$D$13 -> 2157375.9 | F41: =F40*$D$13 -> 2148623.9 | G41: =G40*$D$13 -> 2139871.8 | H41: =H40*$D$13 -> 2131119.8 | I41: =I40*$D$13 -> 2122367.8 | J41: =J40*$D$13 -> 2113615.7 | K41: =K40*$D$13 -> 2104863.7 | ... W41: =W40*$D$13 -> 1999839.3
B42: Inflow : 政府補助 | C42: - | G42: - | H42: - | I42: - | J42: - | K42: - | L42: - | M42: - | N42: - | O42: - | P42: - | Q42: - | R42: - | S42: - | T42: - | U42: - | V42: - | W42: -
B43: Inflow : 銀行借款
B44: Outflow : 設備費用 | C44: =-(D16/(1-D17)+D18)*C4 -> -21431200
B45: Outflow : 設備放置區域租金 | C45: - | D45: -290201 | E45: -290201 | F45: -290201 | G45: -290201 | H45: -290201 | I45: -290201 | J45: -290201 | K45: -290201 | L45: -290201 | M45: -290201 | N45: -290201 | O45: -290201 | P45: -290201 | Q45: -290201 | R45: -290201 | S45: -290201 | T45: -290201 | U45: -290201 | V45: -290201 | W45: -290201
B46: Outflow : 返還借款
B47: Outflow : 利息費用 | C47: -
B48: Outflow : 維運費 | C48: - | D48: -174440 | E48: -174440 | F48: -174440 | G48: -174440 | H48: -174440 | I48: -174440 | J48: -174440 | K48: -174440 | L48: -174440 | M48: -174440 | N48: -174440 | O48: -174440 | P48: -174440 | Q48: -174440 | R48: -174440 | S48: -174440 | T48: -174440 | U48: -174440 | V48: -174440 | W48: -174440
B49: Outflow : 保險費 | C49: - | D49: -43173.9 | E49: -43173.9 | F49: -43173.9 | G49: -43173.9 | H49: -43173.9 | I49: -43173.9 | J49: -43173.9 | K49: -43173.9 | L49: -43173.9 | M49: -43173.9 | N49: -43173.9 | O49: -43173.9 | P49: -43173.9 | Q49: -43173.9 | R49: -43173.9 | S49: -43173.9 | T49: -43173.9 | U49: -43173.9 | V49: -43173.9 | W49: -43173.9
B50: Outflow : 模組回收費 | D50: -43610 | E50: -43610 | F50: -43610 | G50: -43610 | H50: -43610 | I50: -43610 | J50: -43610 | K50: -43610 | L50: -43610 | M50: -43610 | N50: 0 | O50: 0 | P50: 0 | Q50: 0 | R50: 0 | S50: 0 | T50: 0 | U50: 0 | V50: 0 | W50: 0
B51: Outflow : 其它費用(人事薪資…等)
B52: 1%管理費
B53: 績效獎金
B54: 所得稅20% | D54: =D77 -> -166668.8 | E54: =E77 -> -106878.2 | F54: =F77 -> -105127.79 | G54: =G77 -> -103377.38 | H54: =H77 -> -101626.98 | I54: =I77 -> -99876.572 | J54: =J77 -> -98126.166 | K54: =K77 -> -96375.759 | ... W54: =W77 -> -84092.882
B55: 現金流 | C55: =C44 -> -21431200 | D55: =SUM(D41:D54) -> 1448034.2 | E55: =SUM(E41:E54) -> 1499072.8 | F55: =SUM(F41:F54) -> 1492071.2 | G55: =SUM(G41:G54) -> 1485069.5 | H55: =SUM(H41:H54) -> 1478067.9 | I55: =SUM(I41:I54) -> 1471066.3 | J55: =SUM(J41:J54) -> 1464064.7 | K55: =SUM(K41:K54) -> 1457063 | ... W55: =SUM(W41:W54) -> 1407931.5
B56: 累計現金流 | D56: =C55+D55 -> -19983166 | E56: =D56+E55 -> -18484093 | F56: =E56+F55 -> -16992022 | G56: =F56+G55 -> -15506952 | H56: =G56+H55 -> -14028884 | I56: =H56+I55 -> -12557818 | J56: =I56+J55 -> -11093753 | K56: =J56+K55 -> -9636690.4 | L56: =K56+L55 -> -8186629 | ... X56: =W56+X55 -> 7650819.3
B57: 回收年限評估 | D57: =IF((D56)>0,"回收","未回收") -> 未回收 | E57: =IF((E56)>0,"回收","未回收") -> 未回收 | F57: =IF((F56)>0,"回收","未回收") -> 未回收 | G57: =IF((G56)>0,"回收","未回收") -> 未回收 | H57: =IF((H56)>0,"回收","未回收") -> 未回收 | I57: =IF((I56)>0,"回收","未回收") -> 未回收 | J57: =IF((J56)>0,"回收","未回收") -> 未回收 | K57: =IF((K56)>0,"回收","未回收") -> 未回收 | ... X57: =IF((X56)>0,"回收","未回收") -> 回收
B58: 專案法IRR | C58: =IRR(C55:W55) -> 0.031281562
C60: 年份 | D60: =D37 -> 2020 | E60: =E37 -> 2021 | F60: =F37 -> 2022 | G60: =G37 -> 2023 | H60: =H37 -> 2024 | I60: =I37 -> 2025 | J60: =J37 -> 2026 | K60: =K37 -> 2027 | ... W60: =W37 -> 2039
B61: 0 | T61: 償還年限
B62: (Unit : Currency) | C62: 0 | D62: 1 | E62: 2 | F62: 3 | G62: 4 | H62: 5 | I62: 6 | J62: 7 | K62: 8 | L62: 9 | M62: 10 | N62: 11 | O62: 12 | P62: 13 | Q62: 14 | R62: 15 | S62: 16 | T62: 17 | U62: 18 | V62: 19 | W62: 20
B63: 發電度數(KWH) | C63: 0 | D63: =D40 -> 541531.98 | E63: =E40 -> 539343.97 | F63: =F40 -> 537155.96 | G63: =G40 -> 534967.96 | H63: =H40 -> 532779.95 | I63: =I40 -> 530591.94 | J63: =J40 -> 528403.93 | K63: =K40 -> 526215.92 | ... W63: =W40 -> 499959.83
B64: Inflow : 電費收入 | C64: - | D64: =D41 -> 2166127.9 | E64: =E41 -> 2157375.9 | F64: =F41 -> 2148623.9 | G64: =G41 -> 2139871.8 | H64: =H41 -> 2131119.8 | I64: =I41 -> 2122367.8 | J64: =J41 -> 2113615.7 | K64: =K41 -> 2104863.7 | ... W64: =W41 -> 1999839.3
B65: Inflow : 政府補助 | C65: - | G65: - | H65: - | I65: - | J65: - | K65: - | L65: - | M65: - | N65: - | O65: - | P65: - | Q65: - | R65: - | S65: - | T65: - | U65: - | V65: - | W65: -
B66: Inflow : 銀行借款
B67: Outflow : 設備折舊 | D67: =$C$44/$E$16 -> -1071560 | E67: =$C$44/$E$16 -> -1071560 | F67: =$C$44/$E$16 -> -1071560 | G67: =$C$44/$E$16 -> -1071560 | H67: =$C$44/$E$16 -> -1071560 | I67: =$C$44/$E$16 -> -1071560 | J67: =$C$44/$E$16 -> -1071560 | K67: =$C$44/$E$16 -> -1071560 | ... W67: =$C$44/$E$16 -> -1071560
B68: Outflow : 設備放置區域租金 | C68: - | D68: =D44 -> 0 | E68: =E45 -> -290201 | F68: =F45 -> -290201 | G68: =G45 -> -290201 | H68: =H45 -> -290201 | I68: =I45 -> -290201 | J68: =J45 -> -290201 | K68: =K45 -> -290201 | L68: =L45 -> -290201 | ... W68: =W45 -> -290201
B69: Outflow : 返還借款
B70: Outflow : 利息費用 | C70: - | D70: 0 | E70: 0 | F70: 0 | G70: 0 | H70: 0 | I70: 0 | J70: 0 | K70: 0 | L70: 0 | M70: 0 | N70: 0 | O70: 0 | P70: 0 | Q70: 0 | R70: 0 | S70: 0 | T70: 0 | U70: 0 | V70: 0 | W70: 0
B71: Outflow : 維運費 | C71: - | D71: =D48 -> -174440 | E71: =E48 -> -174440 | F71: =F48 -> -174440 | G71: =G48 -> -174440 | H71: =H48 -> -174440 | I71: =I48 -> -174440 | J71: =J48 -> -174440 | K71: =K48 -> -174440 | ... W71: =W48 -> -174440
B72: Outflow : 保險費 | C72: - | D72: =D49 -> -43173.9 | E72: =E49 -> -43173.9 | F72: =F49 -> -43173.9 | G72: =G49 -> -43173.9 | H72: =H49 -> -43173.9 | I72: =I49 -> -43173.9 | J72: =J49 -> -43173.9 | K72: =K49 -> -43173.9 | ... W72: =W49 -> -43173.9
B73: Outflow : 模組回收費 | D73: =D50 -> -43610 | E73: =E50 -> -43610 | F73: =F50 -> -43610 | G73: =G50 -> -43610 | H73: =H50 -> -43610 | I73: =I50 -> -43610 | J73: =J50 -> -43610 | K73: =K50 -> -43610 | ... W73: =W50 -> 0
B74: Outflow : 其它費用(人事薪資…等)
B75: 1%管理費
B76: 稅前淨利 | D76: =SUM(D64:D75) -> 833344.02 | E76: =SUM(E64:E75) -> 534390.99 | F76: =SUM(F64:F75) -> 525638.96 | G76: =SUM(G64:G75) -> 516886.92 | H76: =SUM(H64:H75) -> 508134.89 | I76: =SUM(I64:I75) -> 499382.86 | J76: =SUM(J64:J75) -> 490630.83 | K76: =SUM(K64:K75) -> 481878.8 | ... X76: =SUM(X64:X75) -> 0
B77: 所得稅20% | D77: =-D76*0.2 -> -166668.8 | E77: =-E76*0.2 -> -106878.2 | F77: =-F76*0.2 -> -105127.79 | G77: =-G76*0.2 -> -103377.38 | H77: =-H76*0.2 -> -101626.98 | I77: =-I76*0.2 -> -99876.572 | J77: =-J76*0.2 -> -98126.166 | K77: =-K76*0.2 -> -96375.759 | ... X77: =-X76*0.2 -> 0
B78: 稅後淨利 | D78: =SUM(D76:D77) -> 666675.22 | E78: =SUM(E76:E77) -> 427512.79 | F78: =SUM(F76:F77) -> 420511.16 | G78: =SUM(G76:G77) -> 413509.54 | H78: =SUM(H76:H77) -> 406507.91 | I78: =SUM(I76:I77) -> 399506.29 | J78: =SUM(J76:J77) -> 392504.66 | K78: =SUM(K76:K77) -> 385503.04 | ... X78: =SUM(X76:X77) -> 0
B79: 累計現金流
B80: 回收年限評估

Sheet 淡江大學_p5
B1: 電站基本資料 | F1: 說明 | P1: =1-D11 -> 0.99 | Q1: =P1-$D12 -> 0.986 | R1: =Q1-$D12 -> 0.982 | S1: =R1-$D12 -> 0.978 | T1: =S1-$D12 -> 0.974 | U1: =T1-$D12 -> 0.97 | V1: =U1-$D12 -> 0.966 | W1: =V1-$D12 -> 0.962 | X1: =W1-$D12 -> 0.958 | ... AI1: =AH1-$D12 -> 0.914
B2: 電站名稱 | C2: 淡江大學 | D2: - | E2: - | F2: 填入本案場名稱
B3: 電站壽命 | C3: 20 | D3: - | E3: - | F3: 預設 20 年，代表財務評估年期。若合約年限不同可依實際情況修改
B4: 建置量(kWp) | C4: 436.1 | D4: - | E4: - | F4: 填入裝置容量（kWp），通常由設計圖面或報價書取得 | M4: 情境編號: 5
B5: 起始年度 | C5: 2020 | D5: 結束年度 | E5: 2039 | F5: 填入電站預計掛表的西元年份（例：2025）。結束年度會自動計算 | M5: 第4次滾算摘要
M6: 價金: 27000
B7: 綜合損益表 | M7: 專案IRR: 5.11
B8: 收入 | M8: 權益法IRR: 13.45
B9: 收支項目 | C9: 相關參數 | D9: 參數數值 | E9: 年限 | F9: 說明 | M9: 利潤率: 30.00%
B10: 電費收入 | C10: 年度AC併網總發電量 | D10: 547002 | E10: 20 | F10: 預估年發電量（kWh），通常來自 PVsyst 模擬或估算：裝置容量 × 年日照時數 × 系統效率 | M10: 第4次滾算，減少 2000 元 - 現金模式，每次減少 2000 元
C11: 首年衰退率 | D11: 0.01 | F11: 第一年發電衰退比率，請填小數（例：1% → 填 0.01）。一般首年衰退約 1~2%(請參考模組規格書)
C12: 次年衰退率 | D12: 0.004 | F12: 第二年起每年固定衰退比率，請填小數（例：0.4% → 填 0.004）。一般約 0.4~0.7%(請參考模組規格書)
C13: 躉售費率(FIT) / 綠電費率 | D13: 4 | F13: 與台電簽訂的躉購費率或綠電合約費率，單位：元/度。請參考台電公告或合約內容
B14: 支出
B15: 收支項目 | C15: 相關參數 | D15: 參數數值 | E15: 攤提年限 | F15: 說明
B16: 設備費用(價金) | C16: 每kWp設備成本 | D16: 27000 | E16: 20 | F16: 每峰瓩設備成本（元/kWp），包含模組、逆變器、支架等硬體，不含工程施工費
C17: 信邦利潤率(ex:20%填0.2) | D17: 0.3 | F17: 公司在設備費用上加計的利潤比率，請填小數（例：20% → 填 0.2）
C18: 開發費 | D18: 2000 | F18: 前期開發費用（元），含可行性評估、申請規費、地主溝通等。若無則填 0
B19: 租金費用 | C19: 租金計算方式 | D19: 1 | E19: 20 | F19: 填 1 = 固定年租金（需填方式1參數）；填 2 = 依電費收入抽成（需填方式2參數）
C20: 【方式1參數】每年相同價格 | D20: 290201 | E20: 20 | F20: 租金計算方式選「1」時填寫，固定年租金金額（元/年），套用至整個電站壽命期
C21: 【方式2參數】抽成比率 | D21: 0 | E21: 20 | F21: 租金計算方式選「2」時填寫，請填小數（例：10% → 填 0.1）。租金 = 當年電費收入 × 抽成比率
B22: 運維費用 | C22: 每kw運維成本 | D22: 400 | E22: 20 | F22: 每峰瓩每年運維費用（元/kWp/年），含清洗、巡檢、維修等。
B23: 保險費用 | C23: 占整體設備費用比例 | D23: 0.003 | E23: 20 | F23: 保險費佔設備總費用比率，填小數（例：0.3% → 填 0.003）。預設 0.003，可依投保條件調整
B24: 模組回收費用 | C24: 每kw模組回收成本 | D24: 1000 | E24: 10 | F24: 每峰瓩模組廢棄回收費用（元/kWp），於第 1~10 年計提（攤提 10 年）。
B25: 利息費用 | C25: 銀行利率 | D25: 0.0256 | E25: 20 | F25: 向銀行貸款的年利率，填小數（例：2.56% → 填 0.0256）。請依銀行核准利率填入
B26: 所得稅 | C26: 所得稅率 | D26: 0.2 | E26: 20 | F26: 公司所得稅率，填小數（例：20% → 填 0.2）。預設 0.2，通常不需更改
B29: 現金流量表
B30: 金流項目 | C30: 相關參數 | D30: 參數數值 | F30: 說明
B31: 貸款成數 | C31: 占總設備費用比例 | D31: 0.8 | F31: 貸款佔設備總費用比例，填小數（例：80% → 填 0.8）。預設 0.8 代表貸八成、自備二成
B32: 貸款還款 | C32: 攤還期數 | D32: 15 | F32: 貸款還款年數（年）。預設 15 年，代表分 15 年平均攤還本金
B33: 現金股利 | C33: 股利比率 | D33: 0.9 | F33: 稅後現金流中分配給股東的比例，填小數（例：90% → 填 0.9）
B34: 年底減資 | C34: 攤還期數 | D34: 4 | F34: 年底減資返還股東的年數。預設 4 年，代表 倒數 4 年進行減資，加速資金返還
C37: 年份 | D37: 2020 | E37: 2021 | F37: 2022 | G37: 2023 | H37: 2024 | I37: 2025 | J37: 2026 | K37: 2027 | L37: 2028 | M37: 2029 | N37: 2030 | O37: 2031 | P37: 2032 | Q37: 2033 | R37: 2034 | S37: 2035 | T37: 2036 | U37: 2037 | V37: 2038 | W37: 2039
B38: 0
B39: (Unit : Currency) | C39: 0 | D39: 1 | E39: 2 | F39: 3 | G39: 4 | H39: 5 | I39: 6 | J39: 7 | K39: 8 | L39: 9 | M39: 10 | N39: 11 | O39: 12 | P39: 13 | Q39: 14 | R39: 15 | S39: 16 | T39: 17 | U39: 18 | V39: 19 | W39: 20
B40: 發電度數(KWH) | C40: 0 | D40: =$D$10*P1 -> 541531.98 | E40: =$D$10*Q1 -> 539343.97 | F40: =$D$10*R1 -> 537155.96 | G40: =$D$10*S1 -> 534967.96 | H40: =$D$10*T1 -> 532779.95 | I40: =$D$10*U1 -> 530591.94 | J40: =$D$10*V1 -> 528403.93 | K40: =$D$10*W1 -> 526215.92 | ... W40: =$D$10*AI1 -> 499959.83
B41: Inflow : 電費收入 | C41: - | D41: =D40*$D$13 -> 2166127.9 | E41: =E40*$D$13 -> 2157375.9 | F41: =F40*$D$13 -> 2148623.9 | G41: =G40*$D$13 -> 2139871.8 | H41: =H40*$D$13 -> 2131119.8 | I41: =I40*$D$13 -> 2122367.8 | J41: =J40*$D$13 -> 2113615.7 | K41: =K40*$D$13 -> 2104863.7 | ... W41: =W40*$D$13 -> 1999839.3
B42: Inflow : 政府補助 | C42: - | G42: - | H42: - | I42: - | J42: - | K42: - | L42: - | M42: - | N42: - | O42: - | P42: - | Q42: - | R42: - | S42: - | T42: - | U42: - | V42: - | W42: -
B43: Inflow : 銀行借款
B44: Outflow : 設備費用 | C44: =-(D16/(1-D17)+D18)*C4 -> -17693200
B45: Outflow : 設備放置區域租金 | C45: - | D45: -290201 | E45: -290201 | F45: -290201 | G45: -290201 | H45: -290201 | I45: -290201 | J45: -290201 | K45: -290201 | L45: -290201 | M45: -290201 | N45: -290201 | O45: -290201 | P45: -290201 | Q45: -290201 | R45: -290201 | S45: -290201 | T45: -290201 | U45: -290201 | V45: -290201 | W45: -290201
B46: Outflow : 返還借款
B47: Outflow : 利息費用 | C47: -
B48: Outflow : 維運費 | C48: - | D48: -174440 | E48: -174440 | F48: -174440 | G48: -174440 | H48: -174440 | I48: -174440 | J48: -174440 | K48: -174440 | L48: -174440 | M48: -174440 | N48: -174440 | O48: -174440 | P48: -174440 | Q48: -174440 | R48: -174440 | S48: -174440 | T48: -174440 | U48: -174440 | V48: -174440 | W48: -174440
B49: Outflow : 保險費 | C49: - | D49: -35324.1 | E49: -35324.1 | F49: -35324.1 | G49: -35324.1 | H49: -35324.1 | I49: -35324.1 | J49: -35324.1 | K49: -35324.1 | L49: -35324.1 | M49: -35324.1 | N49: -35324.1 | O49: -35324.1 | P49: -35324.1 | Q49: -35324.1 | R49: -35324.1 | S49: -35324.1 | T49: -35324.1 | U49: -35324.1 | V49: -35324.1 | W49: -35324.1
B50: Outflow : 模組回收費 | D50: -43610 | E50: -43610 | F50: -43610 | G50: -43610 | H50: -43610 | I50: -43610 | J50: -43610 | K50: -43610 | L50: -43610 | M50: -43610 | N50: 0 | O50: 0 | P50: 0 | Q50: 0 | R50: 0 | S50: 0 | T50: 0 | U50: 0 | V50: 0 | W50: 0
B51: Outflow : 其它費用(人事薪資…等)
B52: 1%管理費
B53: 績效獎金
B54: 所得稅20% | D54: =D77 -> -205618.76 | E54: =E77 -> -145828.16 | F54: =F77 -> -144077.75 | G54: =G77 -> -142327.34 | H54: =H77 -> -140576.94 | I54: =I77 -> -138826.53 | J54: =J77 -> -137076.13 | K54: =K77 -> -135325.72 | ... W54: =W77 -> -123042.84
B55: 現金流 | C55: =C44 -> -17693200 | D55: =SUM(D41:D54) -> 1416934.1 | E55: =SUM(E41:E54) -> 1467972.6 | F55: =SUM(F41:F54) -> 1460971 | G55: =SUM(G41:G54) -> 1453969.4 | H55: =SUM(H41:H54) -> 1446967.8 | I55: =SUM(I41:I54) -> 1439966.1 | J55: =SUM(J41:J54) -> 1432964.5 | K55: =SUM(K41:K54) -> 1425962.9 | ... W55: =SUM(W41:W54) -> 1376831.4
B56: 累計現金流 | D56: =C55+D55 -> -16276266 | E56: =D56+E55 -> -14808293 | F56: =E56+F55 -> -13347322 | G56: =F56+G55 -> -11893353 | H56: =G56+H55 -> -10446385 | I56: =H56+I55 -> -9006419 | J56: =I56+J55 -> -7573454.5 | K56: =J56+K55 -> -6147491.7 | L56: =K56+L55 -> -4728530.4 | ... X56: =W56+X55 -> 10766816
B57: 回收年限評估 | D57: =IF((D56)>0,"回收","未回收") -> 未回收 | E57: =IF((E56)>0,"回收","未回收") -> 未回收 | F57: =IF((F56)>0,"回收","未回收") -> 未回收 | G57: =IF((G56)>0,"回收","未回收") -> 未回收 | H57: =IF((H56)>0,"回收","未回收") -> 未回收 | I57: =IF((I56)>0,"回收","未回收") -> 未回收 | J57: =IF((J56)>0,"回收","未回收") -> 未回收 | K57: =IF((K56)>0,"回收","未回收") -> 未回收 | ... X57: =IF((X56)>0,"回收","未回收") -> 回收
B58: 專案法IRR | C58: =IRR(C55:W55) -> 0.050729975
C60: 年份 | D60: =D37 -> 2020 | E60: =E37 -> 2021 | F60: =F37 -> 2022 | G60: =G37 -> 2023 | H60: =H37 -> 2024 | I60: =I37 -> 2025 | J60: =J37 -> 2026 | K60: =K37 -> 2027 | ... W60: =W37 -> 2039
B61: 0 | T61: 償還年限
B62: (Unit : Currency) | C62: 0 | D62: 1 | E62: 2 | F62: 3 | G62: 4 | H62: 5 | I62: 6 | J62: 7 | K62: 8 | L62: 9 | M62: 10 | N62: 11 | O62: 12 | P62: 13 | Q62: 14 | R62: 15 | S62: 16 | T62: 17 | U62: 18 | V62: 19 | W62: 20
B63: 發電度數(KWH) | C63: 0 | D63: =D40 -> 541531.98 | E63: =E40 -> 539343.97 | F63: =F40 -> 537155.96 | G63: =G40 -> 534967.96 | H63: =H40 -> 532779.95 | I63: =I40 -> 530591.94 | J63: =J40 -> 528403.93 | K63: =K40 -> 526215.92 | ... W63: =W40 -> 499959.83
B64: Inflow : 電費收入 | C64: - | D64: =D41 -> 2166127.9 | E64: =E41 -> 2157375.9 | F64: =F41 -> 2148623.9 | G64: =G41 -> 2139871.8 | H64: =H41 -> 2131119.8 | I64: =I41 -> 2122367.8 | J64: =J41 -> 2113615.7 | K64: =K41 -> 2104863.7 | ... W64: =W41 -> 1999839.3
B65: Inflow : 政府補助 | C65: - | G65: - | H65: - | I65: - | J65: - | K65: - | L65: - | M65: - | N65: - | O65: - | P65: - | Q65: - | R65: - | S65: - | T65: - | U65: - | V65: - | W65: -
B66: Inflow : 銀行借款
B67: Outflow : 設備折舊 | D67: =$C$44/$E$16 -> -884660 | E67: =$C$44/$E$16 -> -884660 | F67: =$C$44/$E$16 -> -884660 | G67: =$C$44/$E$16 -> -884660 | H67: =$C$44/$E$16 -> -884660 | I67: =$C$44/$E$16 -> -884660 | J67: =$C$44/$E$16 -> -884660 | K67: =$C$44/$E$16 -> -884660 | ... W67: =$C$44/$E$16 -> -884660
B68: Outflow : 設備放置區域租金 | C68: - | D68: =D44 -> 0 | E68: =E45 -> -290201 | F68: =F45 -> -290201 | G68: =G45 -> -290201 | H68: =H45 -> -290201 | I68: =I45 -> -290201 | J68: =J45 -> -290201 | K68: =K45 -> -290201 | L68: =L45 -> -290201 | ... W68: =W45 -> -290201
B69: Outflow : 返還借款
B70: Outflow : 利息費用 | C70: - | D70: 0 | E70: 0 | F70: 0 | G70: 0 | H70: 0 | I70: 0 | J70: 0 | K70: 0 | L70: 0 | M70: 0 | N70: 0 | O70: 0 | P70: 0 | Q70: 0 | R70: 0 | S70: 0 | T70: 0 | U70: 0 | V70: 0 | W70: 0
B71: Outflow : 維運費 | C71: - | D71: =D48 -> -174440 | E71: =E48 -> -174440 | F71: =F48 -> -174440 | G71: =G48 -> -174440 | H71: =H48 -> -174440 | I71: =I48 -> -174440 | J71: =J48 -> -174440 | K71: =K48 -> -174440 | ... W71: =W48 -> -174440
B72: Outflow : 保險費 | C72: - | D72: =D49 -> -35324.1 | E72: =E49 -> -35324.1 | F72: =F49 -> -35324.1 | G72: =G49 -> -35324.1 | H72: =H49 -> -35324.1 | I72: =I49 -> -35324.1 | J72: =J49 -> -35324.1 | K72: =K49 -> -35324.1 | ... W72: =W49 -> -35324.1
B73: Outflow : 模組回收費 | D73: =D50 -> -43610 | E73: =E50 -> -43610 | F73: =F50 -> -43610 | G73: =G50 -> -43610 | H73: =H50 -> -43610 | I73: =I50 -> -43610 | J73: =J50 -> -43610 | K73: =K50 -> -43610 | ... W73: =W50 -> 0
B74: Outflow : 其它費用(人事薪資…等)
B75: 1%管理費
B76: 稅前淨利 | D76: =SUM(D64:D75) -> 1028093.8 | E76: =SUM(E64:E75) -> 729140.79 | F76: =SUM(F64:F75) -> 720388.76 | G76: =SUM(G64:G75) -> 711636.72 | H76: =SUM(H64:H75) -> 702884.69 | I76: =SUM(I64:I75) -> 694132.66 | J76: =SUM(J64:J75) -> 685380.63 | K76: =SUM(K64:K75) -> 676628.6 | ... X76: =SUM(X64:X75) -> 0
B77: 所得稅20% | D77: =-D76*0.2 -> -205618.76 | E77: =-E76*0.2 -> -145828.16 | F77: =-F76*0.2 -> -144077.75 | G77: =-G76*0.2 -> -142327.34 | H77: =-H76*0.2 -> -140576.94 | I77: =-I76*0.2 -> -138826.53 | J77: =-J76*0.2 -> -137076.13 | K77: =-K76*0.2 -> -135325.72 | ... X77: =-X76*0.2 -> 0
B78: 稅後淨利 | D78: =SUM(D76:D77) -> 822475.06 | E78: =SUM(E76:E77) -> 583312.63 | F78: =SUM(F76:F77) -> 576311 | G78: =SUM(G76:G77) -> 569309.38 | H78: =SUM(H76:H77) -> 562307.75 | I78: =SUM(I76:I77) -> 555306.13 | J78: =SUM(J76:J77) -> 548304.5 | K78: =SUM(K76:K77) -> 541302.88 | ... X78: =SUM(X76:X77) -> 0
B79: 累計現金流
B80: 回收年限評估

Sheet 淡江大學_p3
B1: 電站基本資料 | F1: 說明 | P1: =1-D11 -> 0.99 | Q1: =P1-$D12 -> 0.986 | R1: =Q1-$D12 -> 0.982 | S1: =R1-$D12 -> 0.978 | T1: =S1-$D12 -> 0.974 | U1: =T1-$D12 -> 0.97 | V1: =U1-$D12 -> 0.966 | W1: =V1-$D12 -> 0.962 | X1: =W1-$D12 -> 0.958 | ... AI1: =AH1-$D12 -> 0.914
B2: 電站名稱 | C2: 淡江大學 | D2: - | E2: - | F2: 填入本案場名稱
B3: 電站壽命 | C3: 20 | D3: - | E3: - | F3: 預設 20 年，代表財務評估年期。若合約年限不同可依實際情況修改
B4: 建置量(kWp) | C4: 436.1 | D4: - | E4: - | F4: 填入裝置容量（kWp），通常由設計圖面或報價書取得 | M4: 情境編號: 3
B5: 起始年度 | C5: 2020 | D5: 結束年度 | E5: 2039 | F5: 填入電站預計掛表的西元年份（例：2025）。結束年度會自動計算 | M5: 第2次滾算摘要
M6: 價金: 31000
B7: 綜合損益表 | M7: 專案IRR: 3.75
B8: 收入 | M8: 權益法IRR: 8.21
B9: 收支項目 | C9: 相關參數 | D9: 參數數值 | E9: 年限 | F9: 說明 | M9: 利潤率: 30.00%
B10: 電費收入 | C10: 年度AC併網總發電量 | D10: 547002 | E10: 20 | F10: 預估年發電量（kWh），通常來自 PVsyst 模擬或估算：裝置容量 × 年日照時數 × 系統效率 | M10: 第2次滾算，減少 2000 元 - 現金模式，每次減少 2000 元
C11: 首年衰退率 | D11: 0.01 | F11: 第一年發電衰退比率，請填小數（例：1% → 填 0.01）。一般首年衰退約 1~2%(請參考模組規格書)
C12: 次年衰退率 | D12: 0.004 | F12: 第二年起每年固定衰退比率，請填小數（例：0.4% → 填 0.004）。一般約 0.4~0.7%(請參考模組規格書)
C13: 躉售費率(FIT) / 綠電費率 | D13: 4 | F13: 與台電簽訂的躉購費率或綠電合約費率，單位：元/度。請參考台電公告或合約內容
B14: 支出
B15: 收支項目 | C15: 相關參數 | D15: 參數數值 | E15: 攤提年限 | F15: 說明
B16: 設備費用(價金) | C16: 每kWp設備成本 | D16: 31000 | E16: 20 | F16: 每峰瓩設備成本（元/kWp），包含模組、逆變器、支架等硬體，不含工程施工費
C17: 信邦利潤率(ex:20%填0.2) | D17: 0.3 | F17: 公司在設備費用上加計的利潤比率，請填小數（例：20% → 填 0.2）
C18: 開發費 | D18: 2000 | F18: 前期開發費用（元），含可行性評估、申請規費、地主溝通等。若無則填 0
B19: 租金費用 | C19: 租金計算方式 | D19: 1 | E19: 20 | F19: 填 1 = 固定年租金（需填方式1參數）；填 2 = 依電費收入抽成（需填方式2參數）
C20: 【方式1參數】每年相同價格 | D20: 290201 | E20: 20 | F20: 租金計算方式選「1」時填寫，固定年租金金額（元/年），套用至整個電站壽命期
C21: 【方式2參數】抽成比率 | D21: 0 | E21: 20 | F21: 租金計算方式選「2」時填寫，請填小數（例：10% → 填 0.1）。租金 = 當年電費收入 × 抽成比率
B22: 運維費用 | C22: 每kw運維成本 | D22: 400 | E22: 20 | F22: 每峰瓩每年運維費用（元/kWp/年），含清洗、巡檢、維修等。
B23: 保險費用 | C23: 占整體設備費用比例 | D23: 0.003 | E23: 20 | F23: 保險費佔設備總費用比率，填小數（例：0.3% → 填 0.003）。預設 0.003，可依投保條件調整
B24: 模組回收費用 | C24: 每kw模組回收成本 | D24: 1000 | E24: 10 | F24: 每峰瓩模組廢棄回收費用（元/kWp），於第 1~10 年計提（攤提 10 年）。
B25: 利息費用 | C25: 銀行利率 | D25: 0.0256 | E25: 20 | F25: 向銀行貸款的年利率，填小數（例：2.56% → 填 0.0256）。請依銀行核准利率填入
B26: 所得稅 | C26: 所得稅率 | D26: 0.2 | E26: 20 | F26: 公司所得稅率，填小數（例：20% → 填 0.2）。預設 0.2，通常不需更改
B29: 現金流量表
B30: 金流項目 | C30: 相關參數 | D30: 參數數值 | F30: 說明
B31: 貸款成數 | C31: 占總設備費用比例 | D31: 0.8 | F31: 貸款佔設備總費用比例，填小數（例：80% → 填 0.8）。預設 0.8 代表貸八成、自備二成
B32: 貸款還款 | C32: 攤還期數 | D32: 15 | F32: 貸款還款年數（年）。預設 15 年，代表分 15 年平均攤還本金
B33: 現金股利 | C33: 股利比率 | D33: 0.9 | F33: 稅後現金流中分配給股東的比例，填小數（例：90% → 填 0.9）
B34: 年底減資 | C34: 攤還期數 | D34: 4 | F34: 年底減資返還股東的年數。預設 4 年，代表 倒數 4 年進行減資，加速資金返還
C37: 年份 | D37: 2020 | E37: 2021 | F37: 2022 | G37: 2023 | H37: 2024 | I37: 2025 | J37: 2026 | K37: 2027 | L37: 2028 | M37: 2029 | N37: 2030 | O37: 2031 | P37: 2032 | Q37: 2033 | R37: 2034 | S37: 2035 | T37: 2036 | U37: 2037 | V37: 2038 | W37: 2039
B38: 0
B39: (Unit : Currency) | C39: 0 | D39: 1 | E39: 2 | F39: 3 | G39: 4 | H39: 5 | I39: 6 | J39: 7 | K39: 8 | L39: 9 | M39: 10 | N39: 11 | O39: 12 | P39: 13 | Q39: 14 | R39: 15 | S39: 16 | T39: 17 | U39: 18 | V39: 19 | W39: 20
B40: 發電度數(KWH) | C40: 0 | D40: =$D$10*P1 -> 541531.98 | E40: =$D$10*Q1 -> 539343.97 | F40: =$D$10*R1 -> 537155.96 | G40: =$D$10*S1 -> 534967.96 | H40: =$D$10*T1 -> 532779.95 | I40: =$D$10*U1 -> 530591.94 | J40: =$D$10*V1 -> 528403.93 | K40: =$D$10*W1 -> 526215.92 | ... W40: =$D$10*AI1 -> 499959.83
B41: Inflow : 電費收入 | C41: - | D41: =D40*$D$13 -> 2166127.9 | E41: =E40*$D$13 -> 2157375.9 | F41: =F40*$D$13 -> 2148623.9 | G41: =G40*$D$13 -> 2139871.8 | H41: =H40*$D$13 -> 2131119.8 | I41: =I40*$D$13 -> 2122367.8 | J41: =J40*$D$13 -> 2113615.7 | K41: =K40*$D$13 -> 2104863.7 | ... W41: =W40*$D$13 -> 1999839.3
B42: Inflow : 政府補助 | C42: - | G42: - | H42: - | I42: - | J42: - | K42: - | L42: - | M42: - | N42: - | O42: - | P42: - | Q42: - | R42: - | S42: - | T42: - | U42: - | V42: - | W42: -
B43: Inflow : 銀行借款
B44: Outflow : 設備費用 | C44: =-(D16/(1-D17)+D18)*C4 -> -20185200
B45: Outflow : 設備放置區域租金 | C45: - | D45: -290201 | E45: -290201 | F45: -290201 | G45: -290201 | H45: -290201 | I45: -290201 | J45: -290201 | K45: -290201 | L45: -290201 | M45: -290201 | N45: -290201 | O45: -290201 | P45: -290201 | Q45: -290201 | R45: -290201 | S45: -290201 | T45: -290201 | U45: -290201 | V45: -290201 | W45: -290201
B46: Outflow : 返還借款
B47: Outflow : 利息費用 | C47: -
B48: Outflow : 維運費 | C48: - | D48: -174440 | E48: -174440 | F48: -174440 | G48: -174440 | H48: -174440 | I48: -174440 | J48: -174440 | K48: -174440 | L48: -174440 | M48: -174440 | N48: -174440 | O48: -174440 | P48: -174440 | Q48: -174440 | R48: -174440 | S48: -174440 | T48: -174440 | U48: -174440 | V48: -174440 | W48: -174440
B49: Outflow : 保險費 | C49: - | D49: -40557.3 | E49: -40557.3 | F49: -40557.3 | G49: -40557.3 | H49: -40557.3 | I49: -40557.3 | J49: -40557.3 | K49: -40557.3 | L49: -40557.3 | M49: -40557.3 | N49: -40557.3 | O49: -40557.3 | P49: -40557.3 | Q49: -40557.3 | R49: -40557.3 | S49: -40557.3 | T49: -40557.3 | U49: -40557.3 | V49: -40557.3 | W49: -40557.3
B50: Outflow : 模組回收費 | D50: -43610 | E50: -43610 | F50: -43610 | G50: -43610 | H50: -43610 | I50: -43610 | J50: -43610 | K50: -43610 | L50: -43610 | M50: -43610 | N50: 0 | O50: 0 | P50: 0 | Q50: 0 | R50: 0 | S50: 0 | T50: 0 | U50: 0 | V50: 0 | W50: 0
B51: Outflow : 其它費用(人事薪資…等)
B52: 1%管理費
B53: 績效獎金
B54: 所得稅20% | D54: =D77 -> -179652.12 | E54: =E77 -> -119861.52 | F54: =F77 -> -118111.11 | G54: =G77 -> -116360.7 | H54: =H77 -> -114610.3 | I54: =I77 -> -112859.89 | J54: =J77 -> -111109.49 | K54: =K77 -> -109359.08 | ... W54: =W77 -> -97076.202
B55: 現金流 | C55: =C44 -> -20185200 | D55: =SUM(D41:D54) -> 1437667.5 | E55: =SUM(E41:E54) -> 1488706.1 | F55: =SUM(F41:F54) -> 1481704.4 | G55: =SUM(G41:G54) -> 1474702.8 | H55: =SUM(H41:H54) -> 1467701.2 | I55: =SUM(I41:I54) -> 1460699.6 | J55: =SUM(J41:J54) -> 1453697.9 | K55: =SUM(K41:K54) -> 1446696.3 | ... W55: =SUM(W41:W54) -> 1397564.8
B56: 累計現金流 | D56: =C55+D55 -> -18747533 | E56: =D56+E55 -> -17258826 | F56: =E56+F55 -> -15777122 | G56: =F56+G55 -> -14302419 | H56: =G56+H55 -> -12834718 | I56: =H56+I55 -> -11374018 | J56: =I56+J55 -> -9920320.5 | K56: =J56+K55 -> -8473624.1 | L56: =K56+L55 -> -7033929.5 | ... X56: =W56+X55 -> 8689484.9
B57: 回收年限評估 | D57: =IF((D56)>0,"回收","未回收") -> 未回收 | E57: =IF((E56)>0,"回收","未回收") -> 未回收 | F57: =IF((F56)>0,"回收","未回收") -> 未回收 | G57: =IF((G56)>0,"回收","未回收") -> 未回收 | H57: =IF((H56)>0,"回收","未回收") -> 未回收 | I57: =IF((I56)>0,"回收","未回收") -> 未回收 | J57: =IF((J56)>0,"回收","未回收") -> 未回收 | K57: =IF((K56)>0,"回收","未回收") -> 未回收 | ... X57: =IF((X56)>0,"回收","未回收") -> 回收
B58: 專案法IRR | C58: =IRR(C55:W55) -> 0.037139919
C60: 年份 | D60: =D37 -> 2020 | E60: =E37 -> 2021 | F60: =F37 -> 2022 | G60: =G37 -> 2023 | H60: =H37 -> 2024 | I60: =I37 -> 2025 | J60: =J37 -> 2026 | K60: =K37 -> 2027 | ... W60: =W37 -> 2039
B61: 0 | T61: 償還年限
B62: (Unit : Currency) | C62: 0 | D62: 1 | E62: 2 | F62: 3 | G62: 4 | H62: 5 | I62: 6 | J62: 7 | K62: 8 | L62: 9 | M62: 10 | N62: 11 | O62: 12 | P62: 13 | Q62: 14 | R62: 15 | S62: 16 | T62: 17 | U62: 18 | V62: 19 | W62: 20
B63: 發電度數(KWH) | C63: 0 | D63: =D40 -> 541531.98 | E63: =E40 -> 539343.97 | F63: =F40 -> 537155.96 | G63: =G40 -> 534967.96 | H63: =H40 -> 532779.95 | I63: =I40 -> 530591.94 | J63: =J40 -> 528403.93 | K63: =K40 -> 526215.92 | ... W63: =W40 -> 499959.83
B64: Inflow : 電費收入 | C64: - | D64: =D41 -> 2166127.9 | E64: =E41 -> 2157375.9 | F64: =F41 -> 2148623.9 | G64: =G41 -> 2139871.8 | H64: =H41 -> 2131119.8 | I64: =I41 -> 2122367.8 | J64: =J41 -> 2113615.7 | K64: =K41 -> 2104863.7 | ... W64: =W41 -> 1999839.3
B65: Inflow : 政府補助 | C65: - | G65: - | H65: - | I65: - | J65: - | K65: - | L65: - | M65: - | N65: - | O65: - | P65: - | Q65: - | R65: - | S65: - | T65: - | U65: - | V65: - | W65: -
B66: Inflow : 銀行借款
B67: Outflow : 設備折舊 | D67: =$C$44/$E$16 -> -1009260 | E67: =$C$44/$E$16 -> -1009260 | F67: =$C$44/$E$16 -> -1009260 | G67: =$C$44/$E$16 -> -1009260 | H67: =$C$44/$E$16 -> -1009260 | I67: =$C$44/$E$16 -> -1009260 | J67: =$C$44/$E$16 -> -1009260 | K67: =$C$44/$E$16 -> -1009260 | ... W67: =$C$44/$E$16 -> -1009260
B68: Outflow : 設備放置區域租金 | C68: - | D68: =D44 -> 0 | E68: =E45 -> -290201 | F68: =F45 -> -290201 | G68: =G45 -> -290201 | H68: =H45 -> -290201 | I68: =I45 -> -290201 | J68: =J45 -> -290201 | K68: =K45 -> -290201 | L68: =L45 -> -290201 | ... W68: =W45 -> -290201
B69: Outflow : 返還借款
B70: Outflow : 利息費用 | C70: - | D70: 0 | E70: 0 | F70: 0 | G70: 0 | H70: 0 | I70: 0 | J70: 0 | K70: 0 | L70: 0 | M70: 0 | N70: 0 | O70: 0 | P70: 0 | Q70: 0 | R70: 0 | S70: 0 | T70: 0 | U70: 0 | V70: 0 | W70: 0
B71: Outflow : 維運費 | C71: - | D71: =D48 -> -174440 | E71: =E48 -> -174440 | F71: =F48 -> -174440 | G71: =G48 -> -174440 | H71: =H48 -> -174440 | I71: =I48 -> -174440 | J71: =J48 -> -174440 | K71: =K48 -> -174440 | ... W71: =W48 -> -174440
B72: Outflow : 保險費 | C72: - | D72: =D49 -> -40557.3 | E72: =E49 -> -40557.3 | F72: =F49 -> -40557.3 | G72: =G49 -> -40557.3 | H72: =H49 -> -40557.3 | I72: =I49 -> -40557.3 | J72: =J49 -> -40557.3 | K72: =K49 -> -40557.3 | ... W72: =W49 -> -40557.3
B73: Outflow : 模組回收費 | D73: =D50 -> -43610 | E73: =E50 -> -43610 | F73: =F50 -> -43610 | G73: =G50 -> -43610 | H73: =H50 -> -43610 | I73: =I50 -> -43610 | J73: =J50 -> -43610 | K73: =K50 -> -43610 | ... W73: =W50 -> 0
B74: Outflow : 其它費用(人事薪資…等)
B75: 1%管理費
B76: 稅前淨利 | D76: =SUM(D64:D75) -> 898260.62 | E76: =SUM(E64:E75) -> 599307.59 | F76: =SUM(F64:F75) -> 590555.56 | G76: =SUM(G64:G75) -> 581803.52 | H76: =SUM(H64:H75) -> 573051.49 | I76: =SUM(I64:I75) -> 564299.46 | J76: =SUM(J64:J75) -> 555547.43 | K76: =SUM(K64:K75) -> 546795.4 | ... X76: =SUM(X64:X75) -> 0
B77: 所得稅20% | D77: =-D76*0.2 -> -179652.12 | E77: =-E76*0.2 -> -119861.52 | F77: =-F76*0.2 -> -118111.11 | G77: =-G76*0.2 -> -116360.7 | H77: =-H76*0.2 -> -114610.3 | I77: =-I76*0.2 -> -112859.89 | J77: =-J76*0.2 -> -111109.49 | K77: =-K76*0.2 -> -109359.08 | ... X77: =-X76*0.2 -> 0
B78: 稅後淨利 | D78: =SUM(D76:D77) -> 718608.5 | E78: =SUM(E76:E77) -> 479446.07 | F78: =SUM(F76:F77) -> 472444.44 | G78: =SUM(G76:G77) -> 465442.82 | H78: =SUM(H76:H77) -> 458441.19 | I78: =SUM(I76:I77) -> 451439.57 | J78: =SUM(J76:J77) -> 444437.94 | K78: =SUM(K76:K77) -> 437436.32 | ... X78: =SUM(X76:X77) -> 0
B79: 累計現金流
B80: 回收年限評估

Sheet 淡江大學_p4
B1: 電站基本資料 | F1: 說明 | P1: =1-D11 -> 0.99 | Q1: =P1-$D12 -> 0.986 | R1: =Q1-$D12 -> 0.982 | S1: =R1-$D12 -> 0.978 | T1: =S1-$D12 -> 0.974 | U1: =T1-$D12 -> 0.97 | V1: =U1-$D12 -> 0.966 | W1: =V1-$D12 -> 0.962 | X1: =W1-$D12 -> 0.958 | ... AI1: =AH1-$D12 -> 0.914
B2: 電站名稱 | C2: 淡江大學 | D2: - | E2: - | F2: 填入本案場名稱
B3: 電站壽命 | C3: 20 | D3: - | E3: - | F3: 預設 20 年，代表財務評估年期。若合約年限不同可依實際情況修改
B4: 建置量(kWp) | C4: 436.1 | D4: - | E4: - | F4: 填入裝置容量（kWp），通常由設計圖面或報價書取得 | M4: 情境編號: 4
B5: 起始年度 | C5: 2020 | D5: 結束年度 | E5: 2039 | F5: 填入電站預計掛表的西元年份（例：2025）。結束年度會自動計算 | M5: 第3次滾算摘要
M6: 價金: 29000
B7: 綜合損益表 | M7: 專案IRR: 4.39
B8: 收入 | M8: 權益法IRR: 10.59
B9: 收支項目 | C9: 相關參數 | D9: 參數數值 | E9: 年限 | F9: 說明 | M9: 利潤率: 30.00%
B10: 電費收入 | C10: 年度AC併網總發電量 | D10: 547002 | E10: 20 | F10: 預估年發電量（kWh），通常來自 PVsyst 模擬或估算：裝置容量 × 年日照時數 × 系統效率 | M10: 第3次滾算，減少 2000 元 - 現金模式，每次減少 2000 元
C11: 首年衰退率 | D11: 0.01 | F11: 第一年發電衰退比率，請填小數（例：1% → 填 0.01）。一般首年衰退約 1~2%(請參考模組規格書)
C12: 次年衰退率 | D12: 0.004 | F12: 第二年起每年固定衰退比率，請填小數（例：0.4% → 填 0.004）。一般約 0.4~0.7%(請參考模組規格書)
C13: 躉售費率(FIT) / 綠電費率 | D13: 4 | F13: 與台電簽訂的躉購費率或綠電合約費率，單位：元/度。請參考台電公告或合約內容
B14: 支出
B15: 收支項目 | C15: 相關參數 | D15: 參數數值 | E15: 攤提年限 | F15: 說明
B16: 設備費用(價金) | C16: 每kWp設備成本 | D16: 29000 | E16: 20 | F16: 每峰瓩設備成本（元/kWp），包含模組、逆變器、支架等硬體，不含工程施工費
C17: 信邦利潤率(ex:20%填0.2) | D17: 0.3 | F17: 公司在設備費用上加計的利潤比率，請填小數（例：20% → 填 0.2）
C18: 開發費 | D18: 2000 | F18: 前期開發費用（元），含可行性評估、申請規費、地主溝通等。若無則填 0
B19: 租金費用 | C19: 租金計算方式 | D19: 1 | E19: 20 | F19: 填 1 = 固定年租金（需填方式1參數）；填 2 = 依電費收入抽成（需填方式2參數）
C20: 【方式1參數】每年相同價格 | D20: 290201 | E20: 20 | F20: 租金計算方式選「1」時填寫，固定年租金金額（元/年），套用至整個電站壽命期
C21: 【方式2參數】抽成比率 | D21: 0 | E21: 20 | F21: 租金計算方式選「2」時填寫，請填小數（例：10% → 填 0.1）。租金 = 當年電費收入 × 抽成比率
B22: 運維費用 | C22: 每kw運維成本 | D22: 400 | E22: 20 | F22: 每峰瓩每年運維費用（元/kWp/年），含清洗、巡檢、維修等。
B23: 保險費用 | C23: 占整體設備費用比例 | D23: 0.003 | E23: 20 | F23: 保險費佔設備總費用比率，填小數（例：0.3% → 填 0.003）。預設 0.003，可依投保條件調整
B24: 模組回收費用 | C24: 每kw模組回收成本 | D24: 1000 | E24: 10 | F24: 每峰瓩模組廢棄回收費用（元/kWp），於第 1~10 年計提（攤提 10 年）。
B25: 利息費用 | C25: 銀行利率 | D25: 0.0256 | E25: 20 | F25: 向銀行貸款的年利率，填小數（例：2.56% → 填 0.0256）。請依銀行核准利率填入
B26: 所得稅 | C26: 所得稅率 | D26: 0.2 | E26: 20 | F26: 公司所得稅率，填小數（例：20% → 填 0.2）。預設 0.2，通常不需更改
B29: 現金流量表
B30: 金流項目 | C30: 相關參數 | D30: 參數數值 | F30: 說明
B31: 貸款成數 | C31: 占總設備費用比例 | D31: 0.8 | F31: 貸款佔設備總費用比例，填小數（例：80% → 填 0.8）。預設 0.8 代表貸八成、自備二成
B32: 貸款還款 | C32: 攤還期數 | D32: 15 | F32: 貸款還款年數（年）。預設 15 年，代表分 15 年平均攤還本金
B33: 現金股利 | C33: 股利比率 | D33: 0.9 | F33: 稅後現金流中分配給股東的比例，填小數（例：90% → 填 0.9）
B34: 年底減資 | C34: 攤還期數 | D34: 4 | F34: 年底減資返還股東的年數。預設 4 年，代表 倒數 4 年進行減資，加速資金返還
C37: 年份 | D37: 2020 | E37: 2021 | F37: 2022 | G37: 2023 | H37: 2024 | I37: 2025 | J37: 2026 | K37: 2027 | L37: 2028 | M37: 2029 | N37: 2030 | O37: 2031 | P37: 2032 | Q37: 2033 | R37: 2034 | S37: 2035 | T37: 2036 | U37: 2037 | V37: 2038 | W37: 2039
B38: 0
B39: (Unit : Currency) | C39: 0 | D39: 1 | E39: 2 | F39: 3 | G39: 4 | H39: 5 | I39: 6 | J39: 7 | K39: 8 | L39: 9 | M39: 10 | N39: 11 | O39: 12 | P39: 13 | Q39: 14 | R39: 15 | S39: 16 | T39: 17 | U39: 18 | V39: 19 | W39: 20
B40: 發電度數(KWH) | C40: 0 | D40: =$D$10*P1 -> 541531.98 | E40: =$D$10*Q1 -> 539343.97 | F40: =$D$10*R1 -> 537155.96 | G40: =$D$10*S1 -> 534967.96 | H40: =$D$10*T1 -> 532779.95 | I40: =$D$10*U1 -> 530591.94 | J40: =$D$10*V1 -> 528403.93 | K40: =$D$10*W1 -> 526215.92 | ... W40: =$D$10*AI1 -> 499959.83
B41: Inflow : 電費收入 | C41: - | D41: =D40*$D$13 -> 2166127.9 | E41: =E40*$D$13 -> 2157375.9 | F41: =F40*$D$13 -> 2148623.9 | G41: =G40*$D$13 -> 2139871.8 | H41: =H40*$D$13 -> 2131119.8 | I41: =I40*$D$13 -> 2122367.8 | J41: =J40*$D$13 -> 2113615.7 | K41: =K40*$D$13 -> 2104863.7 | ... W41: =W40*$D$13 -> 1999839.3
B42: Inflow : 政府補助 | C42: - | G42: - | H42: - | I42: - | J42: - | K42: - | L42: - | M42: - | N42: - | O42: - | P42: - | Q42: - | R42: - | S42: - | T42: - | U42: - | V42: - | W42: -
B43: Inflow : 銀行借款
B44: Outflow : 設備費用 | C44: =-(D16/(1-D17)+D18)*C4 -> -18939200
B45: Outflow : 設備放置區域租金 | C45: - | D45: -290201 | E45: -290201 | F45: -290201 | G45: -290201 | H45: -290201 | I45: -290201 | J45: -290201 | K45: -290201 | L45: -290201 | M45: -290201 | N45: -290201 | O45: -290201 | P45: -290201 | Q45: -290201 | R45: -290201 | S45: -290201 | T45: -290201 | U45: -290201 | V45: -290201 | W45: -290201
B46: Outflow : 返還借款
B47: Outflow : 利息費用 | C47: -
B48: Outflow : 維運費 | C48: - | D48: -174440 | E48: -174440 | F48: -174440 | G48: -174440 | H48: -174440 | I48: -174440 | J48: -174440 | K48: -174440 | L48: -174440 | M48: -174440 | N48: -174440 | O48: -174440 | P48: -174440 | Q48: -174440 | R48: -174440 | S48: -174440 | T48: -174440 | U48: -174440 | V48: -174440 | W48: -174440
B49: Outflow : 保險費 | C49: - | D49: -37940.7 | E49: -37940.7 | F49: -37940.7 | G49: -37940.7 | H49: -37940.7 | I49: -37940.7 | J49: -37940.7 | K49: -37940.7 | L49: -37940.7 | M49: -37940.7 | N49: -37940.7 | O49: -37940.7 | P49: -37940.7 | Q49: -37940.7 | R49: -37940.7 | S49: -37940.7 | T49: -37940.7 | U49: -37940.7 | V49: -37940.7 | W49: -37940.7
B50: Outflow : 模組回收費 | D50: -43610 | E50: -43610 | F50: -43610 | G50: -43610 | H50: -43610 | I50: -43610 | J50: -43610 | K50: -43610 | L50: -43610 | M50: -43610 | N50: 0 | O50: 0 | P50: 0 | Q50: 0 | R50: 0 | S50: 0 | T50: 0 | U50: 0 | V50: 0 | W50: 0
B51: Outflow : 其它費用(人事薪資…等)
B52: 1%管理費
B53: 績效獎金
B54: 所得稅20% | D54: =D77 -> -192635.44 | E54: =E77 -> -132844.84 | F54: =F77 -> -131094.43 | G54: =G77 -> -129344.02 | H54: =H77 -> -127593.62 | I54: =I77 -> -125843.21 | J54: =J77 -> -124092.81 | K54: =K77 -> -122342.4 | ... W54: =W77 -> -110059.52
B55: 現金流 | C55: =C44 -> -18939200 | D55: =SUM(D41:D54) -> 1427300.8 | E55: =SUM(E41:E54) -> 1478339.4 | F55: =SUM(F41:F54) -> 1471337.7 | G55: =SUM(G41:G54) -> 1464336.1 | H55: =SUM(H41:H54) -> 1457334.5 | I55: =SUM(I41:I54) -> 1450332.8 | J55: =SUM(J41:J54) -> 1443331.2 | K55: =SUM(K41:K54) -> 1436329.6 | ... W55: =SUM(W41:W54) -> 1387198.1
B56: 累計現金流 | D56: =C55+D55 -> -17511899 | E56: =D56+E55 -> -16033560 | F56: =E56+F55 -> -14562222 | G56: =F56+G55 -> -13097886 | H56: =G56+H55 -> -11640552 | I56: =H56+I55 -> -10190219 | J56: =I56+J55 -> -8746887.5 | K56: =J56+K55 -> -7310557.9 | L56: =K56+L55 -> -5881229.9 | ... X56: =W56+X55 -> 9728150.5
B57: 回收年限評估 | D57: =IF((D56)>0,"回收","未回收") -> 未回收 | E57: =IF((E56)>0,"回收","未回收") -> 未回收 | F57: =IF((F56)>0,"回收","未回收") -> 未回收 | G57: =IF((G56)>0,"回收","未回收") -> 未回收 | H57: =IF((H56)>0,"回收","未回收") -> 未回收 | I57: =IF((I56)>0,"回收","未回收") -> 未回收 | J57: =IF((J56)>0,"回收","未回收") -> 未回收 | K57: =IF((K56)>0,"回收","未回收") -> 未回收 | ... X57: =IF((X56)>0,"回收","未回收") -> 回收
B58: 專案法IRR | C58: =IRR(C55:W55) -> 0.043586467
C60: 年份 | D60: =D37 -> 2020 | E60: =E37 -> 2021 | F60: =F37 -> 2022 | G60: =G37 -> 2023 | H60: =H37 -> 2024 | I60: =I37 -> 2025 | J60: =J37 -> 2026 | K60: =K37 -> 2027 | ... W60: =W37 -> 2039
B61: 0 | T61: 償還年限
B62: (Unit : Currency) | C62: 0 | D62: 1 | E62: 2 | F62: 3 | G62: 4 | H62: 5 | I62: 6 | J62: 7 | K62: 8 | L62: 9 | M62: 10 | N62: 11 | O62: 12 | P62: 13 | Q62: 14 | R62: 15 | S62: 16 | T62: 17 | U62: 18 | V62: 19 | W62: 20
B63: 發電度數(KWH) | C63: 0 | D63: =D40 -> 541531.98 | E63: =E40 -> 539343.97 | F63: =F40 -> 537155.96 | G63: =G40 -> 534967.96 | H63: =H40 -> 532779.95 | I63: =I40 -> 530591.94 | J63: =J40 -> 528403.93 | K63: =K40 -> 526215.92 | ... W63: =W40 -> 499959.83
B64: Inflow : 電費收入 | C64: - | D64: =D41 -> 2166127.9 | E64: =E41 -> 2157375.9 | F64: =F41 -> 2148623.9 | G64: =G41 -> 2139871.8 | H64: =H41 -> 2131119.8 | I64: =I41 -> 2122367.8 | J64: =J41 -> 2113615.7 | K64: =K41 -> 2104863.7 | ... W64: =W41 -> 1999839.3
B65: Inflow : 政府補助 | C65: - | G65: - | H65: - | I65: - | J65: - | K65: - | L65: - | M65: - | N65: - | O65: - | P65: - | Q65: - | R65: - | S65: - | T65: - | U65: - | V65: - | W65: -
B66: Inflow : 銀行借款
B67: Outflow : 設備折舊 | D67: =$C$44/$E$16 -> -946960 | E67: =$C$44/$E$16 -> -946960 | F67: =$C$44/$E$16 -> -946960 | G67: =$C$44/$E$16 -> -946960 | H67: =$C$44/$E$16 -> -946960 | I67: =$C$44/$E$16 -> -946960 | J67: =$C$44/$E$16 -> -946960 | K67: =$C$44/$E$16 -> -946960 | ... W67: =$C$44/$E$16 -> -946960
B68: Outflow : 設備放置區域租金 | C68: - | D68: =D44 -> 0 | E68: =E45 -> -290201 | F68: =F45 -> -290201 | G68: =G45 -> -290201 | H68: =H45 -> -290201 | I68: =I45 -> -290201 | J68: =J45 -> -290201 | K68: =K45 -> -290201 | L68: =L45 -> -290201 | ... W68: =W45 -> -290201
B69: Outflow : 返還借款
B70: Outflow : 利息費用 | C70: - | D70: 0 | E70: 0 | F70: 0 | G70: 0 | H70: 0 | I70: 0 | J70: 0 | K70: 0 | L70: 0 | M70: 0 | N70: 0 | O70: 0 | P70: 0 | Q70: 0 | R70: 0 | S70: 0 | T70: 0 | U70: 0 | V70: 0 | W70: 0
B71: Outflow : 維運費 | C71: - | D71: =D48 -> -174440 | E71: =E48 -> -174440 | F71: =F48 -> -174440 | G71: =G48 -> -174440 | H71: =H48 -> -174440 | I71: =I48 -> -174440 | J71: =J48 -> -174440 | K71: =K48 -> -174440 | ... W71: =W48 -> -174440
B72: Outflow : 保險費 | C72: - | D72: =D49 -> -37940.7 | E72: =E49 -> -37940.7 | F72: =F49 -> -37940.7 | G72: =G49 -> -37940.7 | H72: =H49 -> -37940.7 | I72: =I49 -> -37940.7 | J72: =J49 -> -37940.7 | K72: =K49 -> -37940.7 | ... W72: =W49 -> -37940.7
B73: Outflow : 模組回收費 | D73: =D50 -> -43610 | E73: =E50 -> -43610 | F73: =F50 -> -43610 | G73: =G50 -> -43610 | H73: =H50 -> -43610 | I73: =I50 -> -43610 | J73: =J50 -> -43610 | K73: =K50 -> -43610 | ... W73: =W50 -> 0
B74: Outflow : 其它費用(人事薪資…等)
B75: 1%管理費
B76: 稅前淨利 | D76: =SUM(D64:D75) -> 963177.22 | E76: =SUM(E64:E75) -> 664224.19 | F76: =SUM(F64:F75) -> 655472.16 | G76: =SUM(G64:G75) -> 646720.12 | H76: =SUM(H64:H75) -> 637968.09 | I76: =SUM(I64:I75) -> 629216.06 | J76: =SUM(J64:J75) -> 620464.03 | K76: =SUM(K64:K75) -> 611712 | ... X76: =SUM(X64:X75) -> 0
B77: 所得稅20% | D77: =-D76*0.2 -> -192635.44 | E77: =-E76*0.2 -> -132844.84 | F77: =-F76*0.2 -> -131094.43 | G77: =-G76*0.2 -> -129344.02 | H77: =-H76*0.2 -> -127593.62 | I77: =-I76*0.2 -> -125843.21 | J77: =-J76*0.2 -> -124092.81 | K77: =-K76*0.2 -> -122342.4 | ... X77: =-X76*0.2 -> 0
B78: 稅後淨利 | D78: =SUM(D76:D77) -> 770541.78 | E78: =SUM(E76:E77) -> 531379.35 | F78: =SUM(F76:F77) -> 524377.72 | G78: =SUM(G76:G77) -> 517376.1 | H78: =SUM(H76:H77) -> 510374.47 | I78: =SUM(I76:I77) -> 503372.85 | J78: =SUM(J76:J77) -> 496371.22 | K78: =SUM(K76:K77) -> 489369.6 | ... X78: =SUM(X76:X77) -> 0
B79: 累計現金流
B80: 回收年限評估
