Workbook

Sheet 多站彙整
C4: 年份 | D4: 2023 | E4: 2024 | F4: 2025 | G4: 2026 | H4: 2027 | I4: 2028 | J4: 2029 | K4: 2030 | L4: 2031 | M4: 2032 | N4: 2033 | O4: 2034 | P4: 2035 | Q4: 2036 | R4: 2037 | S4: 2038 | T4: 2039 | U4: 2040 | V4: 2041 | W4: 2042
C5: 預估發電度數
B6: 淡江大學-財務模擬案場 | D6: =ROUND(ABS('淡江大學-財務模擬案場_p1'!D40),0) -> 541532 | E6: =ROUND(ABS('淡江大學-財務模擬案場_p1'!E40),0) -> 539344 | F6: =ROUND(ABS('淡江大學-財務模擬案場_p1'!F40),0) -> 537156 | G6: =ROUND(ABS('淡江大學-財務模擬案場_p1'!G40),0) -> 534968 | H6: =ROUND(ABS('淡江大學-財務模擬案場_p1'!H40),0) -> 532780 | I6: =ROUND(ABS('淡江大學-財務模擬案場_p1'!I40),0) -> 530592 | J6: =ROUND(ABS('淡江大學-財務模擬案場_p1'!J40),0) -> 528404 | K6: =ROUND(ABS('淡江大學-財務模擬案場_p1'!K40),0) -> 526216 | ... W6: =ROUND(ABS('淡江大學-財務模擬案場_p1'!W40),0) -> 499960
B7: 淡江大學-財務模擬案場 | D7: =ROUND(ABS('淡江大學-財務模擬案場_p2'!D40),0) -> 541532 | E7: =ROUND(ABS('淡江大學-財務模擬案場_p2'!E40),0) -> 539344 | F7: =ROUND(ABS('淡江大學-財務模擬案場_p2'!F40),0) -> 537156 | G7: =ROUND(ABS('淡江大學-財務模擬案場_p2'!G40),0) -> 534968 | H7: =ROUND(ABS('淡江大學-財務模擬案場_p2'!H40),0) -> 532780 | I7: =ROUND(ABS('淡江大學-財務模擬案場_p2'!I40),0) -> 530592 | J7: =ROUND(ABS('淡江大學-財務模擬案場_p2'!J40),0) -> 528404 | K7: =ROUND(ABS('淡江大學-財務模擬案場_p2'!K40),0) -> 526216 | ... W7: =ROUND(ABS('淡江大學-財務模擬案場_p2'!W40),0) -> 499960
B8: 淡江大學-財務模擬案場 | D8: =ROUND(ABS('淡江大學-財務模擬案場_p3'!D40),0) -> 541532 | E8: =ROUND(ABS('淡江大學-財務模擬案場_p3'!E40),0) -> 539344 | F8: =ROUND(ABS('淡江大學-財務模擬案場_p3'!F40),0) -> 537156 | G8: =ROUND(ABS('淡江大學-財務模擬案場_p3'!G40),0) -> 534968 | H8: =ROUND(ABS('淡江大學-財務模擬案場_p3'!H40),0) -> 532780 | I8: =ROUND(ABS('淡江大學-財務模擬案場_p3'!I40),0) -> 530592 | J8: =ROUND(ABS('淡江大學-財務模擬案場_p3'!J40),0) -> 528404 | K8: =ROUND(ABS('淡江大學-財務模擬案場_p3'!K40),0) -> 526216 | ... W8: =ROUND(ABS('淡江大學-財務模擬案場_p3'!W40),0) -> 499960
C9: 預估發電度數/年總計 | D9: =SUM(D6:D8) -> 1624596 | E9: =SUM(E6:E8) -> 1618032 | F9: =SUM(F6:F8) -> 1611468 | G9: =SUM(G6:G8) -> 1604904 | H9: =SUM(H6:H8) -> 1598340 | I9: =SUM(I6:I8) -> 1591776 | J9: =SUM(J6:J8) -> 1585212 | K9: =SUM(K6:K8) -> 1578648 | ... W9: =SUM(W6:W8) -> 1499880
C10: 年份 | D10: 2023 | E10: 2024 | F10: 2025 | G10: 2026 | H10: 2027 | I10: 2028 | J10: 2029 | K10: 2030 | L10: 2031 | M10: 2032 | N10: 2033 | O10: 2034 | P10: 2035 | Q10: 2036 | R10: 2037 | S10: 2038 | T10: 2039 | U10: 2040 | V10: 2041 | W10: 2042
C11: 預估收入
B12: 淡江大學-財務模擬案場 | D12: =ROUND(ABS('淡江大學-財務模擬案場_p1'!D41),0) -> 2011900 | E12: =ROUND(ABS('淡江大學-財務模擬案場_p1'!E41),0) -> 2003771 | F12: =ROUND(ABS('淡江大學-財務模擬案場_p1'!F41),0) -> 1995642 | G12: =ROUND(ABS('淡江大學-財務模擬案場_p1'!G41),0) -> 1987513 | H12: =ROUND(ABS('淡江大學-財務模擬案場_p1'!H41),0) -> 1979384 | I12: =ROUND(ABS('淡江大學-財務模擬案場_p1'!I41),0) -> 1971255 | J12: =ROUND(ABS('淡江大學-財務模擬案場_p1'!J41),0) -> 1963126 | K12: =ROUND(ABS('淡江大學-財務模擬案場_p1'!K41),0) -> 1954997 | ... W12: =ROUND(ABS('淡江大學-財務模擬案場_p1'!W41),0) -> 1857451
B13: 淡江大學-財務模擬案場 | D13: =ROUND(ABS('淡江大學-財務模擬案場_p2'!D41),0) -> 2011900 | E13: =ROUND(ABS('淡江大學-財務模擬案場_p2'!E41),0) -> 2003771 | F13: =ROUND(ABS('淡江大學-財務模擬案場_p2'!F41),0) -> 1995642 | G13: =ROUND(ABS('淡江大學-財務模擬案場_p2'!G41),0) -> 1987513 | H13: =ROUND(ABS('淡江大學-財務模擬案場_p2'!H41),0) -> 1979384 | I13: =ROUND(ABS('淡江大學-財務模擬案場_p2'!I41),0) -> 1971255 | J13: =ROUND(ABS('淡江大學-財務模擬案場_p2'!J41),0) -> 1963126 | K13: =ROUND(ABS('淡江大學-財務模擬案場_p2'!K41),0) -> 1954997 | ... W13: =ROUND(ABS('淡江大學-財務模擬案場_p2'!W41),0) -> 1857451
B14: 淡江大學-財務模擬案場 | D14: =ROUND(ABS('淡江大學-財務模擬案場_p3'!D41),0) -> 2011900 | E14: =ROUND(ABS('淡江大學-財務模擬案場_p3'!E41),0) -> 2003771 | F14: =ROUND(ABS('淡江大學-財務模擬案場_p3'!F41),0) -> 1995642 | G14: =ROUND(ABS('淡江大學-財務模擬案場_p3'!G41),0) -> 1987513 | H14: =ROUND(ABS('淡江大學-財務模擬案場_p3'!H41),0) -> 1979384 | I14: =ROUND(ABS('淡江大學-財務模擬案場_p3'!I41),0) -> 1971255 | J14: =ROUND(ABS('淡江大學-財務模擬案場_p3'!J41),0) -> 1963126 | K14: =ROUND(ABS('淡江大學-財務模擬案場_p3'!K41),0) -> 1954997 | ... W14: =ROUND(ABS('淡江大學-財務模擬案場_p3'!W41),0) -> 1857451
C15: 預估收入/年總計 | D15: =SUM(D12:D14) -> 6035700 | E15: =SUM(E12:E14) -> 6011313 | F15: =SUM(F12:F14) -> 5986926 | G15: =SUM(G12:G14) -> 5962539 | H15: =SUM(H12:H14) -> 5938152 | I15: =SUM(I12:I14) -> 5913765 | J15: =SUM(J12:J14) -> 5889378 | K15: =SUM(K12:K14) -> 5864991 | ... W15: =SUM(W12:W14) -> 5572353
C16: 年份 | D16: 2023 | E16: 2024 | F16: 2025 | G16: 2026 | H16: 2027 | I16: 2028 | J16: 2029 | K16: 2030 | L16: 2031 | M16: 2032 | N16: 2033 | O16: 2034 | P16: 2035 | Q16: 2036 | R16: 2037 | S16: 2038 | T16: 2039 | U16: 2040 | V16: 2041 | W16: 2042
C17: 租金
B18: 淡江大學-財務模擬案場 | D18: =ROUND(ABS('淡江大學-財務模擬案場_p1'!D45),0) -> 290201 | E18: =ROUND(ABS('淡江大學-財務模擬案場_p1'!E45),0) -> 290201 | F18: =ROUND(ABS('淡江大學-財務模擬案場_p1'!F45),0) -> 290201 | G18: =ROUND(ABS('淡江大學-財務模擬案場_p1'!G45),0) -> 290201 | H18: =ROUND(ABS('淡江大學-財務模擬案場_p1'!H45),0) -> 290201 | I18: =ROUND(ABS('淡江大學-財務模擬案場_p1'!I45),0) -> 290201 | J18: =ROUND(ABS('淡江大學-財務模擬案場_p1'!J45),0) -> 290201 | K18: =ROUND(ABS('淡江大學-財務模擬案場_p1'!K45),0) -> 290201 | ... W18: =ROUND(ABS('淡江大學-財務模擬案場_p1'!W45),0) -> 290201
B19: 淡江大學-財務模擬案場 | D19: =ROUND(ABS('淡江大學-財務模擬案場_p2'!D45),0) -> 290201 | E19: =ROUND(ABS('淡江大學-財務模擬案場_p2'!E45),0) -> 290201 | F19: =ROUND(ABS('淡江大學-財務模擬案場_p2'!F45),0) -> 290201 | G19: =ROUND(ABS('淡江大學-財務模擬案場_p2'!G45),0) -> 290201 | H19: =ROUND(ABS('淡江大學-財務模擬案場_p2'!H45),0) -> 290201 | I19: =ROUND(ABS('淡江大學-財務模擬案場_p2'!I45),0) -> 290201 | J19: =ROUND(ABS('淡江大學-財務模擬案場_p2'!J45),0) -> 290201 | K19: =ROUND(ABS('淡江大學-財務模擬案場_p2'!K45),0) -> 290201 | ... W19: =ROUND(ABS('淡江大學-財務模擬案場_p2'!W45),0) -> 290201
B20: 淡江大學-財務模擬案場 | D20: =ROUND(ABS('淡江大學-財務模擬案場_p3'!D45),0) -> 290201 | E20: =ROUND(ABS('淡江大學-財務模擬案場_p3'!E45),0) -> 290201 | F20: =ROUND(ABS('淡江大學-財務模擬案場_p3'!F45),0) -> 290201 | G20: =ROUND(ABS('淡江大學-財務模擬案場_p3'!G45),0) -> 290201 | H20: =ROUND(ABS('淡江大學-財務模擬案場_p3'!H45),0) -> 290201 | I20: =ROUND(ABS('淡江大學-財務模擬案場_p3'!I45),0) -> 290201 | J20: =ROUND(ABS('淡江大學-財務模擬案場_p3'!J45),0) -> 290201 | K20: =ROUND(ABS('淡江大學-財務模擬案場_p3'!K45),0) -> 290201 | ... W20: =ROUND(ABS('淡江大學-財務模擬案場_p3'!W45),0) -> 290201
C21: 租金/年總計 | D21: =SUM(D18:D20) -> 870603 | E21: =SUM(E18:E20) -> 870603 | F21: =SUM(F18:F20) -> 870603 | G21: =SUM(G18:G20) -> 870603 | H21: =SUM(H18:H20) -> 870603 | I21: =SUM(I18:I20) -> 870603 | J21: =SUM(J18:J20) -> 870603 | K21: =SUM(K18:K20) -> 870603 | ... W21: =SUM(W18:W20) -> 870603
C22: 年份 | D22: 2023 | E22: 2024 | F22: 2025 | G22: 2026 | H22: 2027 | I22: 2028 | J22: 2029 | K22: 2030 | L22: 2031 | M22: 2032 | N22: 2033 | O22: 2034 | P22: 2035 | Q22: 2036 | R22: 2037 | S22: 2038 | T22: 2039 | U22: 2040 | V22: 2041 | W22: 2042
C23: 運維
B24: 淡江大學-財務模擬案場 | D24: =ROUND(ABS('淡江大學-財務模擬案場_p1'!D48),0) -> 174440 | E24: =ROUND(ABS('淡江大學-財務模擬案場_p1'!E48),0) -> 174440 | F24: =ROUND(ABS('淡江大學-財務模擬案場_p1'!F48),0) -> 174440 | G24: =ROUND(ABS('淡江大學-財務模擬案場_p1'!G48),0) -> 174440 | H24: =ROUND(ABS('淡江大學-財務模擬案場_p1'!H48),0) -> 174440 | I24: =ROUND(ABS('淡江大學-財務模擬案場_p1'!I48),0) -> 174440 | J24: =ROUND(ABS('淡江大學-財務模擬案場_p1'!J48),0) -> 174440 | K24: =ROUND(ABS('淡江大學-財務模擬案場_p1'!K48),0) -> 174440 | ... W24: =ROUND(ABS('淡江大學-財務模擬案場_p1'!W48),0) -> 174440
B25: 淡江大學-財務模擬案場 | D25: =ROUND(ABS('淡江大學-財務模擬案場_p2'!D48),0) -> 174440 | E25: =ROUND(ABS('淡江大學-財務模擬案場_p2'!E48),0) -> 174440 | F25: =ROUND(ABS('淡江大學-財務模擬案場_p2'!F48),0) -> 174440 | G25: =ROUND(ABS('淡江大學-財務模擬案場_p2'!G48),0) -> 174440 | H25: =ROUND(ABS('淡江大學-財務模擬案場_p2'!H48),0) -> 174440 | I25: =ROUND(ABS('淡江大學-財務模擬案場_p2'!I48),0) -> 174440 | J25: =ROUND(ABS('淡江大學-財務模擬案場_p2'!J48),0) -> 174440 | K25: =ROUND(ABS('淡江大學-財務模擬案場_p2'!K48),0) -> 174440 | ... W25: =ROUND(ABS('淡江大學-財務模擬案場_p2'!W48),0) -> 174440
B26: 淡江大學-財務模擬案場 | D26: =ROUND(ABS('淡江大學-財務模擬案場_p3'!D48),0) -> 174440 | E26: =ROUND(ABS('淡江大學-財務模擬案場_p3'!E48),0) -> 174440 | F26: =ROUND(ABS('淡江大學-財務模擬案場_p3'!F48),0) -> 174440 | G26: =ROUND(ABS('淡江大學-財務模擬案場_p3'!G48),0) -> 174440 | H26: =ROUND(ABS('淡江大學-財務模擬案場_p3'!H48),0) -> 174440 | I26: =ROUND(ABS('淡江大學-財務模擬案場_p3'!I48),0) -> 174440 | J26: =ROUND(ABS('淡江大學-財務模擬案場_p3'!J48),0) -> 174440 | K26: =ROUND(ABS('淡江大學-財務模擬案場_p3'!K48),0) -> 174440 | ... W26: =ROUND(ABS('淡江大學-財務模擬案場_p3'!W48),0) -> 174440
C27: 運維/年總計 | D27: =SUM(D24:D26) -> 523320 | E27: =SUM(E24:E26) -> 523320 | F27: =SUM(F24:F26) -> 523320 | G27: =SUM(G24:G26) -> 523320 | H27: =SUM(H24:H26) -> 523320 | I27: =SUM(I24:I26) -> 523320 | J27: =SUM(J24:J26) -> 523320 | K27: =SUM(K24:K26) -> 523320 | ... W27: =SUM(W24:W26) -> 523320
C28: 年份 | D28: 2023 | E28: 2024 | F28: 2025 | G28: 2026 | H28: 2027 | I28: 2028 | J28: 2029 | K28: 2030 | L28: 2031 | M28: 2032 | N28: 2033 | O28: 2034 | P28: 2035 | Q28: 2036 | R28: 2037 | S28: 2038 | T28: 2039 | U28: 2040 | V28: 2041 | W28: 2042
C29: 保險
B30: 淡江大學-財務模擬案場 | D30: =ROUND(ABS('淡江大學-財務模擬案場_p1'!D49),0) -> 45791 | E30: =ROUND(ABS('淡江大學-財務模擬案場_p1'!E49),0) -> 45791 | F30: =ROUND(ABS('淡江大學-財務模擬案場_p1'!F49),0) -> 45791 | G30: =ROUND(ABS('淡江大學-財務模擬案場_p1'!G49),0) -> 45791 | H30: =ROUND(ABS('淡江大學-財務模擬案場_p1'!H49),0) -> 45791 | I30: =ROUND(ABS('淡江大學-財務模擬案場_p1'!I49),0) -> 45791 | J30: =ROUND(ABS('淡江大學-財務模擬案場_p1'!J49),0) -> 45791 | K30: =ROUND(ABS('淡江大學-財務模擬案場_p1'!K49),0) -> 45791 | ... W30: =ROUND(ABS('淡江大學-財務模擬案場_p1'!W49),0) -> 45791
B31: 淡江大學-財務模擬案場 | D31: =ROUND(ABS('淡江大學-財務模擬案場_p2'!D49),0) -> 43174 | E31: =ROUND(ABS('淡江大學-財務模擬案場_p2'!E49),0) -> 43174 | F31: =ROUND(ABS('淡江大學-財務模擬案場_p2'!F49),0) -> 43174 | G31: =ROUND(ABS('淡江大學-財務模擬案場_p2'!G49),0) -> 43174 | H31: =ROUND(ABS('淡江大學-財務模擬案場_p2'!H49),0) -> 43174 | I31: =ROUND(ABS('淡江大學-財務模擬案場_p2'!I49),0) -> 43174 | J31: =ROUND(ABS('淡江大學-財務模擬案場_p2'!J49),0) -> 43174 | K31: =ROUND(ABS('淡江大學-財務模擬案場_p2'!K49),0) -> 43174 | ... W31: =ROUND(ABS('淡江大學-財務模擬案場_p2'!W49),0) -> 43174
B32: 淡江大學-財務模擬案場 | D32: =ROUND(ABS('淡江大學-財務模擬案場_p3'!D49),0) -> 40557 | E32: =ROUND(ABS('淡江大學-財務模擬案場_p3'!E49),0) -> 40557 | F32: =ROUND(ABS('淡江大學-財務模擬案場_p3'!F49),0) -> 40557 | G32: =ROUND(ABS('淡江大學-財務模擬案場_p3'!G49),0) -> 40557 | H32: =ROUND(ABS('淡江大學-財務模擬案場_p3'!H49),0) -> 40557 | I32: =ROUND(ABS('淡江大學-財務模擬案場_p3'!I49),0) -> 40557 | J32: =ROUND(ABS('淡江大學-財務模擬案場_p3'!J49),0) -> 40557 | K32: =ROUND(ABS('淡江大學-財務模擬案場_p3'!K49),0) -> 40557 | ... W32: =ROUND(ABS('淡江大學-財務模擬案場_p3'!W49),0) -> 40557
C33: 保險/年總計 | D33: =SUM(D30:D32) -> 129522 | E33: =SUM(E30:E32) -> 129522 | F33: =SUM(F30:F32) -> 129522 | G33: =SUM(G30:G32) -> 129522 | H33: =SUM(H30:H32) -> 129522 | I33: =SUM(I30:I32) -> 129522 | J33: =SUM(J30:J32) -> 129522 | K33: =SUM(K30:K32) -> 129522 | ... W33: =SUM(W30:W32) -> 129522
C34: 年份 | D34: 2023 | E34: 2024 | F34: 2025 | G34: 2026 | H34: 2027 | I34: 2028 | J34: 2029 | K34: 2030 | L34: 2031 | M34: 2032 | N34: 2033 | O34: 2034 | P34: 2035 | Q34: 2036 | R34: 2037 | S34: 2038 | T34: 2039 | U34: 2040 | V34: 2041 | W34: 2042
C35: 模組回收費
B36: 淡江大學-財務模擬案場 | D36: =ROUND(ABS('淡江大學-財務模擬案場_p1'!D50),0) -> 43610 | E36: =ROUND(ABS('淡江大學-財務模擬案場_p1'!E50),0) -> 43610 | F36: =ROUND(ABS('淡江大學-財務模擬案場_p1'!F50),0) -> 43610 | G36: =ROUND(ABS('淡江大學-財務模擬案場_p1'!G50),0) -> 43610 | H36: =ROUND(ABS('淡江大學-財務模擬案場_p1'!H50),0) -> 43610 | I36: =ROUND(ABS('淡江大學-財務模擬案場_p1'!I50),0) -> 43610 | J36: =ROUND(ABS('淡江大學-財務模擬案場_p1'!J50),0) -> 43610 | K36: =ROUND(ABS('淡江大學-財務模擬案場_p1'!K50),0) -> 43610 | ... W36: =ROUND(ABS('淡江大學-財務模擬案場_p1'!W50),0) -> 0
B37: 淡江大學-財務模擬案場 | D37: =ROUND(ABS('淡江大學-財務模擬案場_p2'!D50),0) -> 43610 | E37: =ROUND(ABS('淡江大學-財務模擬案場_p2'!E50),0) -> 43610 | F37: =ROUND(ABS('淡江大學-財務模擬案場_p2'!F50),0) -> 43610 | G37: =ROUND(ABS('淡江大學-財務模擬案場_p2'!G50),0) -> 43610 | H37: =ROUND(ABS('淡江大學-財務模擬案場_p2'!H50),0) -> 43610 | I37: =ROUND(ABS('淡江大學-財務模擬案場_p2'!I50),0) -> 43610 | J37: =ROUND(ABS('淡江大學-財務模擬案場_p2'!J50),0) -> 43610 | K37: =ROUND(ABS('淡江大學-財務模擬案場_p2'!K50),0) -> 43610 | ... W37: =ROUND(ABS('淡江大學-財務模擬案場_p2'!W50),0) -> 0
B38: 淡江大學-財務模擬案場 | D38: =ROUND(ABS('淡江大學-財務模擬案場_p3'!D50),0) -> 43610 | E38: =ROUND(ABS('淡江大學-財務模擬案場_p3'!E50),0) -> 43610 | F38: =ROUND(ABS('淡江大學-財務模擬案場_p3'!F50),0) -> 43610 | G38: =ROUND(ABS('淡江大學-財務模擬案場_p3'!G50),0) -> 43610 | H38: =ROUND(ABS('淡江大學-財務模擬案場_p3'!H50),0) -> 43610 | I38: =ROUND(ABS('淡江大學-財務模擬案場_p3'!I50),0) -> 43610 | J38: =ROUND(ABS('淡江大學-財務模擬案場_p3'!J50),0) -> 43610 | K38: =ROUND(ABS('淡江大學-財務模擬案場_p3'!K50),0) -> 43610 | ... W38: =ROUND(ABS('淡江大學-財務模擬案場_p3'!W50),0) -> 0
C39: 模組回收費/年總計 | D39: =SUM(D36:D38) -> 130830 | E39: =SUM(E36:E38) -> 130830 | F39: =SUM(F36:F38) -> 130830 | G39: =SUM(G36:G38) -> 130830 | H39: =SUM(H36:H38) -> 130830 | I39: =SUM(I36:I38) -> 130830 | J39: =SUM(J36:J38) -> 130830 | K39: =SUM(K36:K38) -> 130830 | ... W39: =SUM(W36:W38) -> 0
C40: 年份 | D40: 2023 | E40: 2024 | F40: 2025 | G40: 2026 | H40: 2027 | I40: 2028 | J40: 2029 | K40: 2030 | L40: 2031 | M40: 2032 | N40: 2033 | O40: 2034 | P40: 2035 | Q40: 2036 | R40: 2037 | S40: 2038 | T40: 2039 | U40: 2040 | V40: 2041 | W40: 2042
C41: 所得稅
B42: 淡江大學-財務模擬案場 | D42: =ROUND(ABS('淡江大學-財務模擬案場_p1'!D54),0) -> 60439 | E42: =ROUND(ABS('淡江大學-財務模擬案場_p1'!E54),0) -> 58813 | F42: =ROUND(ABS('淡江大學-財務模擬案場_p1'!F54),0) -> 57187 | G42: =ROUND(ABS('淡江大學-財務模擬案場_p1'!G54),0) -> 55561 | H42: =ROUND(ABS('淡江大學-財務模擬案場_p1'!H54),0) -> 53936 | I42: =ROUND(ABS('淡江大學-財務模擬案場_p1'!I54),0) -> 52310 | J42: =ROUND(ABS('淡江大學-財務模擬案場_p1'!J54),0) -> 50684 | K42: =ROUND(ABS('淡江大學-財務模擬案場_p1'!K54),0) -> 49058 | ... W42: =ROUND(ABS('淡江大學-財務模擬案場_p1'!W54),0) -> 38271
B43: 淡江大學-財務模擬案場 | D43: =ROUND(ABS('淡江大學-財務模擬案場_p2'!D54),0) -> 73422 | E43: =ROUND(ABS('淡江大學-財務模擬案場_p2'!E54),0) -> 71796 | F43: =ROUND(ABS('淡江大學-財務模擬案場_p2'!F54),0) -> 70170 | G43: =ROUND(ABS('淡江大學-財務模擬案場_p2'!G54),0) -> 68545 | H43: =ROUND(ABS('淡江大學-財務模擬案場_p2'!H54),0) -> 66919 | I43: =ROUND(ABS('淡江大學-財務模擬案場_p2'!I54),0) -> 65293 | J43: =ROUND(ABS('淡江大學-財務模擬案場_p2'!J54),0) -> 63667 | K43: =ROUND(ABS('淡江大學-財務模擬案場_p2'!K54),0) -> 62042 | ... W43: =ROUND(ABS('淡江大學-財務模擬案場_p2'!W54),0) -> 51254
B44: 淡江大學-財務模擬案場 | D44: =ROUND(ABS('淡江大學-財務模擬案場_p3'!D54),0) -> 86405 | E44: =ROUND(ABS('淡江大學-財務模擬案場_p3'!E54),0) -> 84779 | F44: =ROUND(ABS('淡江大學-財務模擬案場_p3'!F54),0) -> 83154 | G44: =ROUND(ABS('淡江大學-財務模擬案場_p3'!G54),0) -> 81528 | H44: =ROUND(ABS('淡江大學-財務模擬案場_p3'!H54),0) -> 79902 | I44: =ROUND(ABS('淡江大學-財務模擬案場_p3'!I54),0) -> 78276 | J44: =ROUND(ABS('淡江大學-財務模擬案場_p3'!J54),0) -> 76651 | K44: =ROUND(ABS('淡江大學-財務模擬案場_p3'!K54),0) -> 75025 | ... W44: =ROUND(ABS('淡江大學-財務模擬案場_p3'!W54),0) -> 64237
C45: 所得稅/年總計 | D45: =SUM(D42:D44) -> 220266 | E45: =SUM(E42:E44) -> 215388 | F45: =SUM(F42:F44) -> 210511 | G45: =SUM(G42:G44) -> 205634 | H45: =SUM(H42:H44) -> 200757 | I45: =SUM(I42:I44) -> 195879 | J45: =SUM(J42:J44) -> 191002 | K45: =SUM(K42:K44) -> 186125 | ... W45: =SUM(W42:W44) -> 153762
C46: 年份 | D46: 2023 | E46: 2024 | F46: 2025 | G46: 2026 | H46: 2027 | I46: 2028 | J46: 2029 | K46: 2030 | L46: 2031 | M46: 2032 | N46: 2033 | O46: 2034 | P46: 2035 | Q46: 2036 | R46: 2037 | S46: 2038 | T46: 2039 | U46: 2040 | V46: 2041 | W46: 2042
C47: 設備折舊
B48: 淡江大學-財務模擬案場 | D48: =ROUND(ABS('淡江大學-財務模擬案場_p1'!D67),0) -> 1155665 | E48: =ROUND(ABS('淡江大學-財務模擬案場_p1'!E67),0) -> 1155665 | F48: =ROUND(ABS('淡江大學-財務模擬案場_p1'!F67),0) -> 1155665 | G48: =ROUND(ABS('淡江大學-財務模擬案場_p1'!G67),0) -> 1155665 | H48: =ROUND(ABS('淡江大學-財務模擬案場_p1'!H67),0) -> 1155665 | I48: =ROUND(ABS('淡江大學-財務模擬案場_p1'!I67),0) -> 1155665 | J48: =ROUND(ABS('淡江大學-財務模擬案場_p1'!J67),0) -> 1155665 | K48: =ROUND(ABS('淡江大學-財務模擬案場_p1'!K67),0) -> 1155665 | ... W48: =ROUND(ABS('淡江大學-財務模擬案場_p1'!W67),0) -> 1155665
B49: 淡江大學-財務模擬案場 | D49: =ROUND(ABS('淡江大學-財務模擬案場_p2'!D67),0) -> 1093365 | E49: =ROUND(ABS('淡江大學-財務模擬案場_p2'!E67),0) -> 1093365 | F49: =ROUND(ABS('淡江大學-財務模擬案場_p2'!F67),0) -> 1093365 | G49: =ROUND(ABS('淡江大學-財務模擬案場_p2'!G67),0) -> 1093365 | H49: =ROUND(ABS('淡江大學-財務模擬案場_p2'!H67),0) -> 1093365 | I49: =ROUND(ABS('淡江大學-財務模擬案場_p2'!I67),0) -> 1093365 | J49: =ROUND(ABS('淡江大學-財務模擬案場_p2'!J67),0) -> 1093365 | K49: =ROUND(ABS('淡江大學-財務模擬案場_p2'!K67),0) -> 1093365 | ... W49: =ROUND(ABS('淡江大學-財務模擬案場_p2'!W67),0) -> 1093365
B50: 淡江大學-財務模擬案場 | D50: =ROUND(ABS('淡江大學-財務模擬案場_p3'!D67),0) -> 1031065 | E50: =ROUND(ABS('淡江大學-財務模擬案場_p3'!E67),0) -> 1031065 | F50: =ROUND(ABS('淡江大學-財務模擬案場_p3'!F67),0) -> 1031065 | G50: =ROUND(ABS('淡江大學-財務模擬案場_p3'!G67),0) -> 1031065 | H50: =ROUND(ABS('淡江大學-財務模擬案場_p3'!H67),0) -> 1031065 | I50: =ROUND(ABS('淡江大學-財務模擬案場_p3'!I67),0) -> 1031065 | J50: =ROUND(ABS('淡江大學-財務模擬案場_p3'!J67),0) -> 1031065 | K50: =ROUND(ABS('淡江大學-財務模擬案場_p3'!K67),0) -> 1031065 | ... W50: =ROUND(ABS('淡江大學-財務模擬案場_p3'!W67),0) -> 1031065
C51: 設備折舊/年總計 | D51: =SUM(D48:D50) -> 3280095 | E51: =SUM(E48:E50) -> 3280095 | F51: =SUM(F48:F50) -> 3280095 | G51: =SUM(G48:G50) -> 3280095 | H51: =SUM(H48:H50) -> 3280095 | I51: =SUM(I48:I50) -> 3280095 | J51: =SUM(J48:J50) -> 3280095 | K51: =SUM(K48:K50) -> 3280095 | ... W51: =SUM(W48:W50) -> 3280095
B53: 貸款成數(%) | C53: 80
B54: 還款期數 | C54: 14
B55: 股利比率(%) | C55: 90
B56: 年底減資攤還期數 | C56: 6
B57: 銀行利率(%) | C57: 3
C58: 年份 | D58: 2023 | E58: 2024 | F58: 2025 | G58: 2026 | H58: 2027 | I58: 2028 | J58: 2029 | K58: 2030 | L58: 2031 | M58: 2032 | N58: 2033 | O58: 2034 | P58: 2035 | Q58: 2036 | R58: 2037 | S58: 2038 | T58: 2039 | U58: 2040 | V58: 2041 | W58: 2042
B59: 0
B60: (Unit : Currency) | C60: 0 | D60: 1 | E60: 2 | F60: 3 | G60: 4 | H60: 5 | I60: 6 | J60: 7 | K60: 8 | L60: 9 | M60: 10 | N60: 11 | O60: 12 | P60: 13 | Q60: 14 | R60: 15 | S60: 16 | T60: 17 | U60: 18 | V60: 19 | W60: 20
B61: 發電度數(KWH) | C61: 0 | D61: =D9 -> 1624596 | E61: =E9 -> 1618032 | F61: =F9 -> 1611468 | G61: =G9 -> 1604904 | H61: =H9 -> 1598340 | I61: =I9 -> 1591776 | J61: =J9 -> 1585212 | K61: =K9 -> 1578648 | ... W61: =W9 -> 1499880
B62: Inflow : 電費收入 | C62: - | D62: =D15 -> 6035700 | E62: =E15 -> 6011313 | F62: =F15 -> 5986926 | G62: =G15 -> 5962539 | H62: =H15 -> 5938152 | I62: =I15 -> 5913765 | J62: =J15 -> 5889378 | K62: =K15 -> 5864991 | ... W62: =W15 -> 5572353
B63: Inflow : 政府補助 | C63: - | G63: - | H63: - | I63: - | J63: - | K63: - | L63: - | M63: - | N63: - | O63: - | P63: - | Q63: - | R63: - | S63: - | T63: - | U63: - | V63: - | W63: -
B64: Inflow : 銀行借款
B65: Outflow : 設備費用 | C65: =-SUM(D51:W51) -> -65601900
B66: Outflow : 設備放置區域租金 | C66: - | D66: =-D21 -> -870603 | E66: =-E21 -> -870603 | F66: =-F21 -> -870603 | G66: =-G21 -> -870603 | H66: =-H21 -> -870603 | I66: =-I21 -> -870603 | J66: =-J21 -> -870603 | K66: =-K21 -> -870603 | ... W66: =-W21 -> -870603
B67: Outflow : 返還借款
B68: Outflow : 利息費用 | C68: -
B69: Outflow : 維運費 | C69: - | D69: =-D27 -> -523320 | E69: =-E27 -> -523320 | F69: =-F27 -> -523320 | G69: =-G27 -> -523320 | H69: =-H27 -> -523320 | I69: =-I27 -> -523320 | J69: =-J27 -> -523320 | K69: =-K27 -> -523320 | ... W69: =-W27 -> -523320
B70: Outflow : 保險費 | C70: - | D70: =-D33 -> -129522 | E70: =-E33 -> -129522 | F70: =-F33 -> -129522 | G70: =-G33 -> -129522 | H70: =-H33 -> -129522 | I70: =-I33 -> -129522 | J70: =-J33 -> -129522 | K70: =-K33 -> -129522 | ... W70: =-W33 -> -129522
B71: Outflow : 模組回收費 | D71: =-D39 -> -130830 | E71: =-E39 -> -130830 | F71: =-F39 -> -130830 | G71: =-G39 -> -130830 | H71: =-H39 -> -130830 | I71: =-I39 -> -130830 | J71: =-J39 -> -130830 | K71: =-K39 -> -130830 | ... W71: =-W39 -> 0
B72: Outflow : 其它費用(人事薪資…等)
B73: 1%管理費
B74: 績效獎金
B75: 所得稅20% | D75: =-D98 -> 94623.12 | E75: =-E98 -> 77008.44 | F75: =-F98 -> 59393.76 | G75: =-G98 -> 41779.08 | H75: =-H98 -> 24164.4 | I75: =-I98 -> 6549.72 | J75: =-J98 -> -11064.96 | K75: =-K98 -> -28679.64 | ... W75: =-W98 -> -153762.6
B76: 現金流 | C76: =C65 -> -65601900 | D76: =SUM(D62:D75) -> 4476048.1 | E76: =SUM(E62:E75) -> 4434046.4 | F76: =SUM(F62:F75) -> 4392044.8 | G76: =SUM(G62:G75) -> 4350043.1 | H76: =SUM(H62:H75) -> 4308041.4 | I76: =SUM(I62:I75) -> 4266039.7 | J76: =SUM(J62:J75) -> 4224038 | K76: =SUM(K62:K75) -> 4182036.4 | ... W76: =SUM(W62:W75) -> 3895145.4
B77: 累計現金流 | D77: =C55+D55 -> 90 | E77: =D56+E55 -> 0 | F77: =E56+F55 -> 0 | G77: =F56+G55 -> 0 | H77: =G56+H55 -> 0 | I77: =H56+I55 -> 0 | J77: =I56+J55 -> 0 | K77: =J56+K55 -> 0 | L77: =K56+L55 -> 0 | ... W77: =V56+W55 -> 0
B78: 回收年限評估 | D78: =IF((D56)>0,"回收","未回收") -> 未回收 | E78: =IF((E56)>0,"回收","未回收") -> 未回收 | F78: =IF((F56)>0,"回收","未回收") -> 未回收 | G78: =IF((G56)>0,"回收","未回收") -> 未回收 | H78: =IF((H56)>0,"回收","未回收") -> 未回收 | I78: =IF((I56)>0,"回收","未回收") -> 未回收 | J78: =IF((J56)>0,"回收","未回收") -> 未回收 | K78: =IF((K56)>0,"回收","未回收") -> 未回收 | ... W78: =IF((W56)>0,"回收","未回收") -> 未回收
B79: 專案法IRR | C79: =IRR(C76:W76) -> 0.024037256
C81: 年份 | D81: 2023 | E81: 2024 | F81: 2025 | G81: 2026 | H81: 2027 | I81: 2028 | J81: 2029 | K81: 2030 | L81: 2031 | M81: 2032 | N81: 2033 | O81: 2034 | P81: 2035 | Q81: 2036 | R81: 2037 | S81: 2038 | T81: 2039 | U81: 2040 | V81: 2041 | W81: 2042
B82: 0 | T82: 償還年限
B83: (Unit : Currency) | C83: 0 | D83: 1 | E83: 2 | F83: 3 | G83: 4 | H83: 5 | I83: 6 | J83: 7 | K83: 8 | L83: 9 | M83: 10 | N83: 11 | O83: 12 | P83: 13 | Q83: 14 | R83: 15 | S83: 16 | T83: 17 | U83: 18 | V83: 19 | W83: 20
B84: 發電度數(KWH) | C84: 0 | D84: =D9 -> 1624596 | E84: =E9 -> 1618032 | F84: =F9 -> 1611468 | G84: =G9 -> 1604904 | H84: =H9 -> 1598340 | I84: =I9 -> 1591776 | J84: =J9 -> 1585212 | K84: =K9 -> 1578648 | ... W84: =W9 -> 1499880
B85: Inflow : 電費收入 | C85: - | D85: =D15 -> 6035700 | E85: =E15 -> 6011313 | F85: =F15 -> 5986926 | G85: =G15 -> 5962539 | H85: =H15 -> 5938152 | I85: =I15 -> 5913765 | J85: =J15 -> 5889378 | K85: =K15 -> 5864991 | ... W85: =W15 -> 5572353
B86: Inflow : 政府補助 | C86: - | G86: - | H86: - | I86: - | J86: - | K86: - | L86: - | M86: - | N86: - | O86: - | P86: - | Q86: - | R86: - | S86: - | T86: - | U86: - | V86: - | W86: -
B87: Inflow : 銀行借款
B88: Outflow : 設備折舊 | D88: =-D51 -> -3280095 | E88: =-E51 -> -3280095 | F88: =-F51 -> -3280095 | G88: =-G51 -> -3280095 | H88: =-H51 -> -3280095 | I88: =-I51 -> -3280095 | J88: =-J51 -> -3280095 | K88: =-K51 -> -3280095 | ... W88: =-W51 -> -3280095
B89: Outflow : 設備放置區域租金 | C89: - | D89: =-D21 -> -870603 | E89: =-E21 -> -870603 | F89: =-F21 -> -870603 | G89: =-G21 -> -870603 | H89: =-H21 -> -870603 | I89: =-I21 -> -870603 | J89: =-J21 -> -870603 | K89: =-K21 -> -870603 | ... W89: =-W21 -> -870603
B90: Outflow : 返還借款
B91: Outflow : 利息費用 | C91: - | D91: =-D129*C57/100 -> -1574445.6 | E91: =-E129*C57/100 -> -1461985.2 | F91: =-F129*C57/100 -> -1349524.8 | G91: =-G129*C57/100 -> -1237064.4 | H91: =-H129*C57/100 -> -1124604 | I91: =-I129*C57/100 -> -1012143.6 | J91: =-J129*C57/100 -> -899683.2 | K91: =-K129*C57/100 -> -787222.8 | L91: =-L129*C57/100 -> -674762.4 | M91: =-M129*C57/100 -> -562302 | N91: =-N129*C57/100 -> -449841.6 | O91: =-O129*C57/100 -> -337381.2 | P91: =-P129*C57/100 -> -224920.8 | Q91: =-Q129*C57/100 -> -112460.4 | R91: =-R129*C57/100 -> 0 | S91: =-S129*C57/100 -> 0 | T91: =-T129*C57/100 -> 0 | U91: =-U129*C57/100 -> 0 | V91: =-V129*C57/100 -> 0 | W91: =-W129*C57/100 -> 0
B92: Outflow : 維運費 | C92: - | D92: =-D27 -> -523320 | E92: =-E27 -> -523320 | F92: =-F27 -> -523320 | G92: =-G27 -> -523320 | H92: =-H27 -> -523320 | I92: =-I27 -> -523320 | J92: =-J27 -> -523320 | K92: =-K27 -> -523320 | ... W92: =-W27 -> -523320
B93: Outflow : 保險費 | C93: - | D93: =-D33 -> -129522 | E93: =-E33 -> -129522 | F93: =-F33 -> -129522 | G93: =-G33 -> -129522 | H93: =-H33 -> -129522 | I93: =-I33 -> -129522 | J93: =-J33 -> -129522 | K93: =-K33 -> -129522 | ... W93: =-W33 -> -129522
B94: Outflow : 模組回收費 | D94: =-D39 -> -130830 | E94: =-E39 -> -130830 | F94: =-F39 -> -130830 | G94: =-G39 -> -130830 | H94: =-H39 -> -130830 | I94: =-I39 -> -130830 | J94: =-J39 -> -130830 | K94: =-K39 -> -130830 | ... W94: =-W39 -> 0
B95: Outflow : 其它費用(人事薪資…等)
B96: 1%管理費
B97: 稅前淨利 | D97: =SUM(D85:D96) -> -473115.6 | E97: =SUM(E85:E96) -> -385042.2 | F97: =SUM(F85:F96) -> -296968.8 | G97: =SUM(G85:G96) -> -208895.4 | H97: =SUM(H85:H96) -> -120822 | I97: =SUM(I85:I96) -> -32748.6 | J97: =SUM(J85:J96) -> 55324.8 | K97: =SUM(K85:K96) -> 143398.2 | ... W97: =SUM(W85:W96) -> 768813
B98: 所得稅20% | D98: =D97*0.2 -> -94623.12 | E98: =E97*0.2 -> -77008.44 | F98: =F97*0.2 -> -59393.76 | G98: =G97*0.2 -> -41779.08 | H98: =H97*0.2 -> -24164.4 | I98: =I97*0.2 -> -6549.72 | J98: =J97*0.2 -> 11064.96 | K98: =K97*0.2 -> 28679.64 | ... W98: =W97*0.2 -> 153762.6
B99: 稅後淨利 | D99: =D97-D98 -> -378492.48 | E99: =E97-E98 -> -308033.76 | F99: =F97-F98 -> -237575.04 | G99: =G97-G98 -> -167116.32 | H99: =H97-H98 -> -96657.6 | I99: =I97-I98 -> -26198.88 | J99: =J97-J98 -> 44259.84 | K99: =K97-K98 -> 114718.56 | ... W99: =W97-W98 -> 615050.4
B100: 累計現金流
B101: 回收年限評估
C102: 年份 | D102: 2023 | E102: 2024 | F102: 2025 | G102: 2026 | H102: 2027 | I102: 2028 | J102: 2029 | K102: 2030 | L102: 2031 | M102: 2032 | N102: 2033 | O102: 2034 | P102: 2035 | Q102: 2036 | R102: 2037 | S102: 2038 | T102: 2039 | U102: 2040 | V102: 2041 | W102: 2042
B104: (Unit : Currency) | C104: 0 | D104: 1 | E104: 2 | F104: 3 | G104: 4 | H104: 5 | I104: 6 | J104: 7 | K104: 8 | L104: 9 | M104: 10 | N104: 11 | O104: 12 | P104: 13 | Q104: 14 | R104: 15 | S104: 16 | T104: 17 | U104: 18 | V104: 19 | W104: 20
B105: 稅後淨利 | D105: =D99 -> -378492.48 | E105: =E99 -> -308033.76 | F105: =F99 -> -237575.04 | G105: =G99 -> -167116.32 | H105: =H99 -> -96657.6 | I105: =I99 -> -26198.88 | J105: =J99 -> 44259.84 | K105: =K99 -> 114718.56 | ... W105: =W99 -> 615050.4
B106: 設備折舊 | D106: =D51 -> 3280095 | E106: =E51 -> 3280095 | F106: =F51 -> 3280095 | G106: =G51 -> 3280095 | H106: =H51 -> 3280095 | I106: =I51 -> 3280095 | J106: =J51 -> 3280095 | K106: =K51 -> 3280095 | ... W106: =W51 -> 3280095
...

Sheet 淡江大學-財務模擬案場_p1
B1: 電站基本資料 | F1: 說明 | P1: =1-D11 -> 0.99 | Q1: =P1-$D12 -> 0.986 | R1: =Q1-$D12 -> 0.982 | S1: =R1-$D12 -> 0.978 | T1: =S1-$D12 -> 0.974 | U1: =T1-$D12 -> 0.97 | V1: =U1-$D12 -> 0.966 | W1: =V1-$D12 -> 0.962 | X1: =W1-$D12 -> 0.958 | ... AI1: =AH1-$D12 -> 0.914
B2: 電站名稱 | C2: 淡江大學-財務模擬案場 | D2: - | E2: - | F2: 填入本案場名稱
B3: 電站壽命 | C3: 20 | D3: - | E3: - | F3: 預設 20 年，代表財務評估年期。若合約年限不同可依實際情況修改
B4: 建置量(kWp) | C4: 436.1 | D4: - | E4: - | F4: 填入裝置容量（kWp），通常由設計圖面或報價書取得 | M4: 情境編號: 1
B5: 起始年度 | C5: 2023 | D5: 結束年度 | E5: 2042 | F5: 填入電站預計掛表的西元年份（例：2025）。結束年度會自動計算 | M5: 初始價金摘要
M6: 價金: 35000
B7: 綜合損益表 | M7: 專案IRR: 1.57
B8: 收入 | M8: 權益法IRR: 1.27
B9: 收支項目 | C9: 相關參數 | D9: 參數數值 | E9: 年限 | F9: 說明 | M9: 利潤率: 30.00%
B10: 電費收入 | C10: 年度AC併網總發電量 | D10: 547002 | E10: 20 | F10: 預估年發電量（kWh），通常來自 PVsyst 模擬或估算：裝置容量 × 年日照時數 × 系統效率 | M10: 初始價金 - 現金模式，每次減少 2000 元
C11: 首年衰退率 | D11: 0.01 | F11: 第一年發電衰退比率，請填小數（例：1% → 填 0.01）。一般首年衰退約 1~2%(請參考模組規格書)
C12: 次年衰退率 | D12: 0.004 | F12: 第二年起每年固定衰退比率，請填小數（例：0.4% → 填 0.004）。一般約 0.4~0.7%(請參考模組規格書)
C13: 躉售費率(FIT) / 綠電費率 | D13: 3.7152 | F13: 與台電簽訂的躉購費率或綠電合約費率，單位：元/度。請參考台電公告或合約內容
B14: 支出
B15: 收支項目 | C15: 相關參數 | D15: 參數數值 | E15: 攤提年限 | F15: 說明
B16: 設備費用(價金) | C16: 每kWp設備成本 | D16: 35000 | E16: 20 | F16: 每峰瓩設備成本（元/kWp），包含模組、逆變器、支架等硬體，不含工程施工費
C17: 信邦利潤率(ex:20%填0.2) | D17: 0.3 | F17: 公司在設備費用上加計的利潤比率，請填小數（例：20% → 填 0.2）
C18: 開發費 | D18: 3000 | F18: 前期開發費用（元），含可行性評估、申請規費、地主溝通等。若無則填 0
B19: 租金費用 | C19: 租金計算方式 | D19: 1 | E19: 0 | F19: 填 1 = 固定年租金（需填方式1參數）；填 2 = 依電費收入抽成（需填方式2參數）
C20: 【方式1參數】每年相同價格 | D20: 290201 | E20: 20 | F20: 租金計算方式選「1」時填寫，固定年租金金額（元/年），套用至整個電站壽命期
C21: 【方式2參數】抽成比率 | D21: 0 | E21: 0 | F21: 租金計算方式選「2」時填寫，請填小數（例：10% → 填 0.1）。租金 = 當年電費收入 × 抽成比率
B22: 運維費用 | C22: 每kw運維成本 | D22: 400 | E22: 20 | F22: 每峰瓩每年運維費用（元/kWp/年），含清洗、巡檢、維修等。
B23: 保險費用 | C23: 占整體設備費用比例 | D23: 0.003 | E23: 20 | F23: 保險費佔設備總費用比率，填小數（例：0.3% → 填 0.003）。預設 0.003，可依投保條件調整
B24: 模組回收費用 | C24: 每kw模組回收成本 | D24: 1000 | E24: 10 | F24: 每峰瓩模組廢棄回收費用（元/kWp），於第 1~10 年計提（攤提 10 年）。
B25: 利息費用 | C25: 銀行利率 | D25: 0.025595 | E25: 0 | F25: 向銀行貸款的年利率，填小數（例：2.56% → 填 0.0256）。請依銀行核准利率填入
B26: 所得稅 | C26: 所得稅率 | D26: 0.2 | E26: 0 | F26: 公司所得稅率，填小數（例：20% → 填 0.2）。預設 0.2，通常不需更改
B29: 現金流量表
B30: 金流項目 | C30: 相關參數 | D30: 參數數值 | F30: 說明
B31: 貸款成數 | C31: 占總設備費用比例 | D31: 0.8 | F31: 貸款佔設備總費用比例，填小數（例：80% → 填 0.8）。預設 0.8 代表貸八成、自備二成
B32: 貸款還款 | C32: 攤還期數 | D32: 15 | F32: 貸款還款年數（年）。預設 15 年，代表分 15 年平均攤還本金
B33: 現金股利 | C33: 股利比率 | D33: 0.9 | F33: 稅後現金流中分配給股東的比例，填小數（例：90% → 填 0.9）
B34: 年底減資 | C34: 攤還期數 | D34: 4 | F34: 年底減資返還股東的年數。預設 4 年，代表 倒數 4 年進行減資，加速資金返還
C37: 年份 | D37: 2023 | E37: 2024 | F37: 2025 | G37: 2026 | H37: 2027 | I37: 2028 | J37: 2029 | K37: 2030 | L37: 2031 | M37: 2032 | N37: 2033 | O37: 2034 | P37: 2035 | Q37: 2036 | R37: 2037 | S37: 2038 | T37: 2039 | U37: 2040 | V37: 2041 | W37: 2042
B38: 0
B39: (Unit : Currency) | C39: 0 | D39: 1 | E39: 2 | F39: 3 | G39: 4 | H39: 5 | I39: 6 | J39: 7 | K39: 8 | L39: 9 | M39: 10 | N39: 11 | O39: 12 | P39: 13 | Q39: 14 | R39: 15 | S39: 16 | T39: 17 | U39: 18 | V39: 19 | W39: 20
B40: 發電度數(KWH) | C40: 0 | D40: =$D$10*P1 -> 541531.98 | E40: =$D$10*Q1 -> 539343.97 | F40: =$D$10*R1 -> 537155.96 | G40: =$D$10*S1 -> 534967.96 | H40: =$D$10*T1 -> 532779.95 | I40: =$D$10*U1 -> 530591.94 | J40: =$D$10*V1 -> 528403.93 | K40: =$D$10*W1 -> 526215.92 | ... W40: =$D$10*AI1 -> 499959.83
B41: Inflow : 電費收入 | C41: - | D41: =D40*$D$13 -> 2011899.6 | E41: =E40*$D$13 -> 2003770.7 | F41: =F40*$D$13 -> 1995641.8 | G41: =G40*$D$13 -> 1987513 | H41: =H40*$D$13 -> 1979384.1 | I41: =I40*$D$13 -> 1971255.2 | J41: =J40*$D$13 -> 1963126.3 | K41: =K40*$D$13 -> 1954997.4 | ... W41: =W40*$D$13 -> 1857450.8
B42: Inflow : 政府補助 | C42: - | G42: - | H42: - | I42: - | J42: - | K42: - | L42: - | M42: - | N42: - | O42: - | P42: - | Q42: - | R42: - | S42: - | T42: - | U42: - | V42: - | W42: -
B43: Inflow : 銀行借款
B44: Outflow : 設備費用 | C44: =-(D16/(1-D17)+D18)*C4 -> -23113300
B45: Outflow : 設備放置區域租金 | C45: - | D45: -290201 | E45: -290201 | F45: -290201 | G45: -290201 | H45: -290201 | I45: -290201 | J45: -290201 | K45: -290201 | L45: -290201 | M45: -290201 | N45: -290201 | O45: -290201 | P45: -290201 | Q45: -290201 | R45: -290201 | S45: -290201 | T45: -290201 | U45: -290201 | V45: -290201 | W45: -290201
B46: Outflow : 返還借款
B47: Outflow : 利息費用 | C47: -
B48: Outflow : 維運費 | C48: - | D48: -174440 | E48: -174440 | F48: -174440 | G48: -174440 | H48: -174440 | I48: -174440 | J48: -174440 | K48: -174440 | L48: -174440 | M48: -174440 | N48: -174440 | O48: -174440 | P48: -174440 | Q48: -174440 | R48: -174440 | S48: -174440 | T48: -174440 | U48: -174440 | V48: -174440 | W48: -174440
B49: Outflow : 保險費 | C49: - | D49: -45790.5 | E49: -45790.5 | F49: -45790.5 | G49: -45790.5 | H49: -45790.5 | I49: -45790.5 | J49: -45790.5 | K49: -45790.5 | L49: -45790.5 | M49: -45790.5 | N49: -45790.5 | O49: -45790.5 | P49: -45790.5 | Q49: -45790.5 | R49: -45790.5 | S49: -45790.5 | T49: -45790.5 | U49: -45790.5 | V49: -45790.5 | W49: -45790.5
B50: Outflow : 模組回收費 | D50: -43610 | E50: -43610 | F50: -43610 | G50: -43610 | H50: -43610 | I50: -43610 | J50: -43610 | K50: -43610 | L50: -43610 | M50: -43610 | N50: 0 | O50: 0 | P50: 0 | Q50: 0 | R50: 0 | S50: 0 | T50: 0 | U50: 0 | V50: 0 | W50: 0
B51: Outflow : 其它費用(人事薪資…等)
B52: 1%管理費
B53: 績效獎金
B54: 所得稅20% | D54: =D77 -> -60438.622 | E54: =E77 -> -58812.845 | F54: =F77 -> -57187.067 | G54: =G77 -> -55561.29 | H54: =H77 -> -53935.513 | I54: =I77 -> -52309.735 | J54: =J77 -> -50683.958 | K54: =K77 -> -49058.18 | ... W54: =W77 -> -38270.851
B55: 現金流 | C55: =C44 -> -23113300 | D55: =SUM(D41:D54) -> 1397419.5 | E55: =SUM(E41:E54) -> 1390916.4 | F55: =SUM(F41:F54) -> 1384413.3 | G55: =SUM(G41:G54) -> 1377910.2 | H55: =SUM(H41:H54) -> 1371407.1 | I55: =SUM(I41:I54) -> 1364903.9 | J55: =SUM(J41:J54) -> 1358400.8 | K55: =SUM(K41:K54) -> 1351897.7 | ... W55: =SUM(W41:W54) -> 1308748.4
B56: 累計現金流 | D56: =C55+D55 -> -21715881 | E56: =D56+E55 -> -20324964 | F56: =E56+F55 -> -18940551 | G56: =F56+G55 -> -17562641 | H56: =G56+H55 -> -16191234 | I56: =H56+I55 -> -14826330 | J56: =I56+J55 -> -13467929 | K56: =J56+K55 -> -12116031 | L56: =K56+L55 -> -10770637 | ... X56: =W56+X55 -> 3948378.9
B57: 回收年限評估 | D57: =IF((D56)>0,"回收","未回收") -> 未回收 | E57: =IF((E56)>0,"回收","未回收") -> 未回收 | F57: =IF((F56)>0,"回收","未回收") -> 未回收 | G57: =IF((G56)>0,"回收","未回收") -> 未回收 | H57: =IF((H56)>0,"回收","未回收") -> 未回收 | I57: =IF((I56)>0,"回收","未回收") -> 未回收 | J57: =IF((J56)>0,"回收","未回收") -> 未回收 | K57: =IF((K56)>0,"回收","未回收") -> 未回收 | ... X57: =IF((X56)>0,"回收","未回收") -> 回收
B58: 專案法IRR | C58: =IRR(C55:W55) -> 0.015664515
C60: 年份 | D60: =D37 -> 2023 | E60: =E37 -> 2024 | F60: =F37 -> 2025 | G60: =G37 -> 2026 | H60: =H37 -> 2027 | I60: =I37 -> 2028 | J60: =J37 -> 2029 | K60: =K37 -> 2030 | ... W60: =W37 -> 2042
B61: 0 | T61: 償還年限
B62: (Unit : Currency) | C62: 0 | D62: 1 | E62: 2 | F62: 3 | G62: 4 | H62: 5 | I62: 6 | J62: 7 | K62: 8 | L62: 9 | M62: 10 | N62: 11 | O62: 12 | P62: 13 | Q62: 14 | R62: 15 | S62: 16 | T62: 17 | U62: 18 | V62: 19 | W62: 20
B63: 發電度數(KWH) | C63: 0 | D63: =D40 -> 541531.98 | E63: =E40 -> 539343.97 | F63: =F40 -> 537155.96 | G63: =G40 -> 534967.96 | H63: =H40 -> 532779.95 | I63: =I40 -> 530591.94 | J63: =J40 -> 528403.93 | K63: =K40 -> 526215.92 | ... W63: =W40 -> 499959.83
B64: Inflow : 電費收入 | C64: - | D64: =D41 -> 2011899.6 | E64: =E41 -> 2003770.7 | F64: =F41 -> 1995641.8 | G64: =G41 -> 1987513 | H64: =H41 -> 1979384.1 | I64: =I41 -> 1971255.2 | J64: =J41 -> 1963126.3 | K64: =K41 -> 1954997.4 | ... W64: =W41 -> 1857450.8
B65: Inflow : 政府補助 | C65: - | G65: - | H65: - | I65: - | J65: - | K65: - | L65: - | M65: - | N65: - | O65: - | P65: - | Q65: - | R65: - | S65: - | T65: - | U65: - | V65: - | W65: -
B66: Inflow : 銀行借款
B67: Outflow : 設備折舊 | D67: =$C$44/$E$16 -> -1155665 | E67: =$C$44/$E$16 -> -1155665 | F67: =$C$44/$E$16 -> -1155665 | G67: =$C$44/$E$16 -> -1155665 | H67: =$C$44/$E$16 -> -1155665 | I67: =$C$44/$E$16 -> -1155665 | J67: =$C$44/$E$16 -> -1155665 | K67: =$C$44/$E$16 -> -1155665 | ... W67: =$C$44/$E$16 -> -1155665
B68: Outflow : 設備放置區域租金 | C68: - | D68: =D45 -> -290201 | E68: =E45 -> -290201 | F68: =F45 -> -290201 | G68: =G45 -> -290201 | H68: =H45 -> -290201 | I68: =I45 -> -290201 | J68: =J45 -> -290201 | K68: =K45 -> -290201 | ... W68: =W45 -> -290201
B69: Outflow : 返還借款
B70: Outflow : 利息費用 | C70: - | D70: 0 | E70: 0 | F70: 0 | G70: 0 | H70: 0 | I70: 0 | J70: 0 | K70: 0 | L70: 0 | M70: 0 | N70: 0 | O70: 0 | P70: 0 | Q70: 0 | R70: 0 | S70: 0 | T70: 0 | U70: 0 | V70: 0 | W70: 0
B71: Outflow : 維運費 | C71: - | D71: =D48 -> -174440 | E71: =E48 -> -174440 | F71: =F48 -> -174440 | G71: =G48 -> -174440 | H71: =H48 -> -174440 | I71: =I48 -> -174440 | J71: =J48 -> -174440 | K71: =K48 -> -174440 | ... W71: =W48 -> -174440
B72: Outflow : 保險費 | C72: - | D72: =D49 -> -45790.5 | E72: =E49 -> -45790.5 | F72: =F49 -> -45790.5 | G72: =G49 -> -45790.5 | H72: =H49 -> -45790.5 | I72: =I49 -> -45790.5 | J72: =J49 -> -45790.5 | K72: =K49 -> -45790.5 | ... W72: =W49 -> -45790.5
B73: Outflow : 模組回收費 | D73: =D50 -> -43610 | E73: =E50 -> -43610 | F73: =F50 -> -43610 | G73: =G50 -> -43610 | H73: =H50 -> -43610 | I73: =I50 -> -43610 | J73: =J50 -> -43610 | K73: =K50 -> -43610 | ... W73: =W50 -> 0
B74: Outflow : 其它費用(人事薪資…等)
B75: 1%管理費
B76: 稅前淨利 | D76: =SUM(D64:D75) -> 302193.11 | E76: =SUM(E64:E75) -> 294064.22 | F76: =SUM(F64:F75) -> 285935.34 | G76: =SUM(G64:G75) -> 277806.45 | H76: =SUM(H64:H75) -> 269677.56 | I76: =SUM(I64:I75) -> 261548.68 | J76: =SUM(J64:J75) -> 253419.79 | K76: =SUM(K64:K75) -> 245290.9 | ... X76: =SUM(X64:X75) -> 0
B77: 所得稅20% | D77: =-D76*0.2 -> -60438.622 | E77: =-E76*0.2 -> -58812.845 | F77: =-F76*0.2 -> -57187.067 | G77: =-G76*0.2 -> -55561.29 | H77: =-H76*0.2 -> -53935.513 | I77: =-I76*0.2 -> -52309.735 | J77: =-J76*0.2 -> -50683.958 | K77: =-K76*0.2 -> -49058.18 | ... X77: =-X76*0.2 -> 0
B78: 稅後淨利 | D78: =SUM(D76:D77) -> 241754.49 | E78: =SUM(E76:E77) -> 235251.38 | F78: =SUM(F76:F77) -> 228748.27 | G78: =SUM(G76:G77) -> 222245.16 | H78: =SUM(H76:H77) -> 215742.05 | I78: =SUM(I76:I77) -> 209238.94 | J78: =SUM(J76:J77) -> 202735.83 | K78: =SUM(K76:K77) -> 196232.72 | ... X78: =SUM(X76:X77) -> 0
B79: 累計現金流
B80: 回收年限評估

Sheet 淡江大學-財務模擬案場_p2
B1: 電站基本資料 | F1: 說明 | P1: =1-D11 -> 0.99 | Q1: =P1-$D12 -> 0.986 | R1: =Q1-$D12 -> 0.982 | S1: =R1-$D12 -> 0.978 | T1: =S1-$D12 -> 0.974 | U1: =T1-$D12 -> 0.97 | V1: =U1-$D12 -> 0.966 | W1: =V1-$D12 -> 0.962 | X1: =W1-$D12 -> 0.958 | ... AI1: =AH1-$D12 -> 0.914
B2: 電站名稱 | C2: 淡江大學-財務模擬案場 | D2: - | E2: - | F2: 填入本案場名稱
B3: 電站壽命 | C3: 20 | D3: - | E3: - | F3: 預設 20 年，代表財務評估年期。若合約年限不同可依實際情況修改
B4: 建置量(kWp) | C4: 436.1 | D4: - | E4: - | F4: 填入裝置容量（kWp），通常由設計圖面或報價書取得 | M4: 情境編號: 2
B5: 起始年度 | C5: 2023 | D5: 結束年度 | E5: 2042 | F5: 填入電站預計掛表的西元年份（例：2025）。結束年度會自動計算 | M5: 第1次滾算摘要
M6: 價金: 33000
B7: 綜合損益表 | M7: 專案IRR: 2.06
B8: 收入 | M8: 權益法IRR: 2.75
B9: 收支項目 | C9: 相關參數 | D9: 參數數值 | E9: 年限 | F9: 說明 | M9: 利潤率: 30.00%
B10: 電費收入 | C10: 年度AC併網總發電量 | D10: 547002 | E10: 20 | F10: 預估年發電量（kWh），通常來自 PVsyst 模擬或估算：裝置容量 × 年日照時數 × 系統效率 | M10: 第1次滾算，減少 2000 元 - 現金模式，每次減少 2000 元
C11: 首年衰退率 | D11: 0.01 | F11: 第一年發電衰退比率，請填小數（例：1% → 填 0.01）。一般首年衰退約 1~2%(請參考模組規格書)
C12: 次年衰退率 | D12: 0.004 | F12: 第二年起每年固定衰退比率，請填小數（例：0.4% → 填 0.004）。一般約 0.4~0.7%(請參考模組規格書)
C13: 躉售費率(FIT) / 綠電費率 | D13: 3.7152 | F13: 與台電簽訂的躉購費率或綠電合約費率，單位：元/度。請參考台電公告或合約內容
B14: 支出
B15: 收支項目 | C15: 相關參數 | D15: 參數數值 | E15: 攤提年限 | F15: 說明
B16: 設備費用(價金) | C16: 每kWp設備成本 | D16: 33000 | E16: 20 | F16: 每峰瓩設備成本（元/kWp），包含模組、逆變器、支架等硬體，不含工程施工費
C17: 信邦利潤率(ex:20%填0.2) | D17: 0.3 | F17: 公司在設備費用上加計的利潤比率，請填小數（例：20% → 填 0.2）
C18: 開發費 | D18: 3000 | F18: 前期開發費用（元），含可行性評估、申請規費、地主溝通等。若無則填 0
B19: 租金費用 | C19: 租金計算方式 | D19: 1 | E19: 0 | F19: 填 1 = 固定年租金（需填方式1參數）；填 2 = 依電費收入抽成（需填方式2參數）
C20: 【方式1參數】每年相同價格 | D20: 290201 | E20: 20 | F20: 租金計算方式選「1」時填寫，固定年租金金額（元/年），套用至整個電站壽命期
C21: 【方式2參數】抽成比率 | D21: 0 | E21: 0 | F21: 租金計算方式選「2」時填寫，請填小數（例：10% → 填 0.1）。租金 = 當年電費收入 × 抽成比率
B22: 運維費用 | C22: 每kw運維成本 | D22: 400 | E22: 20 | F22: 每峰瓩每年運維費用（元/kWp/年），含清洗、巡檢、維修等。
B23: 保險費用 | C23: 占整體設備費用比例 | D23: 0.003 | E23: 20 | F23: 保險費佔設備總費用比率，填小數（例：0.3% → 填 0.003）。預設 0.003，可依投保條件調整
B24: 模組回收費用 | C24: 每kw模組回收成本 | D24: 1000 | E24: 10 | F24: 每峰瓩模組廢棄回收費用（元/kWp），於第 1~10 年計提（攤提 10 年）。
B25: 利息費用 | C25: 銀行利率 | D25: 0.025595 | E25: 0 | F25: 向銀行貸款的年利率，填小數（例：2.56% → 填 0.0256）。請依銀行核准利率填入
B26: 所得稅 | C26: 所得稅率 | D26: 0.2 | E26: 0 | F26: 公司所得稅率，填小數（例：20% → 填 0.2）。預設 0.2，通常不需更改
B29: 現金流量表
B30: 金流項目 | C30: 相關參數 | D30: 參數數值 | F30: 說明
B31: 貸款成數 | C31: 占總設備費用比例 | D31: 0.8 | F31: 貸款佔設備總費用比例，填小數（例：80% → 填 0.8）。預設 0.8 代表貸八成、自備二成
B32: 貸款還款 | C32: 攤還期數 | D32: 15 | F32: 貸款還款年數（年）。預設 15 年，代表分 15 年平均攤還本金
B33: 現金股利 | C33: 股利比率 | D33: 0.9 | F33: 稅後現金流中分配給股東的比例，填小數（例：90% → 填 0.9）
B34: 年底減資 | C34: 攤還期數 | D34: 4 | F34: 年底減資返還股東的年數。預設 4 年，代表 倒數 4 年進行減資，加速資金返還
C37: 年份 | D37: 2023 | E37: 2024 | F37: 2025 | G37: 2026 | H37: 2027 | I37: 2028 | J37: 2029 | K37: 2030 | L37: 2031 | M37: 2032 | N37: 2033 | O37: 2034 | P37: 2035 | Q37: 2036 | R37: 2037 | S37: 2038 | T37: 2039 | U37: 2040 | V37: 2041 | W37: 2042
B38: 0
B39: (Unit : Currency) | C39: 0 | D39: 1 | E39: 2 | F39: 3 | G39: 4 | H39: 5 | I39: 6 | J39: 7 | K39: 8 | L39: 9 | M39: 10 | N39: 11 | O39: 12 | P39: 13 | Q39: 14 | R39: 15 | S39: 16 | T39: 17 | U39: 18 | V39: 19 | W39: 20
B40: 發電度數(KWH) | C40: 0 | D40: =$D$10*P1 -> 541531.98 | E40: =$D$10*Q1 -> 539343.97 | F40: =$D$10*R1 -> 537155.96 | G40: =$D$10*S1 -> 534967.96 | H40: =$D$10*T1 -> 532779.95 | I40: =$D$10*U1 -> 530591.94 | J40: =$D$10*V1 -> 528403.93 | K40: =$D$10*W1 -> 526215.92 | ... W40: =$D$10*AI1 -> 499959.83
B41: Inflow : 電費收入 | C41: - | D41: =D40*$D$13 -> 2011899.6 | E41: =E40*$D$13 -> 2003770.7 | F41: =F40*$D$13 -> 1995641.8 | G41: =G40*$D$13 -> 1987513 | H41: =H40*$D$13 -> 1979384.1 | I41: =I40*$D$13 -> 1971255.2 | J41: =J40*$D$13 -> 1963126.3 | K41: =K40*$D$13 -> 1954997.4 | ... W41: =W40*$D$13 -> 1857450.8
B42: Inflow : 政府補助 | C42: - | G42: - | H42: - | I42: - | J42: - | K42: - | L42: - | M42: - | N42: - | O42: - | P42: - | Q42: - | R42: - | S42: - | T42: - | U42: - | V42: - | W42: -
B43: Inflow : 銀行借款
B44: Outflow : 設備費用 | C44: =-(D16/(1-D17)+D18)*C4 -> -21867300
B45: Outflow : 設備放置區域租金 | C45: - | D45: -290201 | E45: -290201 | F45: -290201 | G45: -290201 | H45: -290201 | I45: -290201 | J45: -290201 | K45: -290201 | L45: -290201 | M45: -290201 | N45: -290201 | O45: -290201 | P45: -290201 | Q45: -290201 | R45: -290201 | S45: -290201 | T45: -290201 | U45: -290201 | V45: -290201 | W45: -290201
B46: Outflow : 返還借款
B47: Outflow : 利息費用 | C47: -
B48: Outflow : 維運費 | C48: - | D48: -174440 | E48: -174440 | F48: -174440 | G48: -174440 | H48: -174440 | I48: -174440 | J48: -174440 | K48: -174440 | L48: -174440 | M48: -174440 | N48: -174440 | O48: -174440 | P48: -174440 | Q48: -174440 | R48: -174440 | S48: -174440 | T48: -174440 | U48: -174440 | V48: -174440 | W48: -174440
B49: Outflow : 保險費 | C49: - | D49: -43173.9 | E49: -43173.9 | F49: -43173.9 | G49: -43173.9 | H49: -43173.9 | I49: -43173.9 | J49: -43173.9 | K49: -43173.9 | L49: -43173.9 | M49: -43173.9 | N49: -43173.9 | O49: -43173.9 | P49: -43173.9 | Q49: -43173.9 | R49: -43173.9 | S49: -43173.9 | T49: -43173.9 | U49: -43173.9 | V49: -43173.9 | W49: -43173.9
B50: Outflow : 模組回收費 | D50: -43610 | E50: -43610 | F50: -43610 | G50: -43610 | H50: -43610 | I50: -43610 | J50: -43610 | K50: -43610 | L50: -43610 | M50: -43610 | N50: 0 | O50: 0 | P50: 0 | Q50: 0 | R50: 0 | S50: 0 | T50: 0 | U50: 0 | V50: 0 | W50: 0
B51: Outflow : 其它費用(人事薪資…等)
B52: 1%管理費
B53: 績效獎金
B54: 所得稅20% | D54: =D77 -> -73421.942 | E54: =E77 -> -71796.165 | F54: =F77 -> -70170.387 | G54: =G77 -> -68544.61 | H54: =H77 -> -66918.833 | I54: =I77 -> -65293.055 | J54: =J77 -> -63667.278 | K54: =K77 -> -62041.5 | ... W54: =W77 -> -51254.171
B55: 現金流 | C55: =C44 -> -21867300 | D55: =SUM(D41:D54) -> 1387052.8 | E55: =SUM(E41:E54) -> 1380549.7 | F55: =SUM(F41:F54) -> 1374046.5 | G55: =SUM(G41:G54) -> 1367543.4 | H55: =SUM(H41:H54) -> 1361040.3 | I55: =SUM(I41:I54) -> 1354537.2 | J55: =SUM(J41:J54) -> 1348034.1 | K55: =SUM(K41:K54) -> 1341531 | ... W55: =SUM(W41:W54) -> 1298381.7
B56: 累計現金流 | D56: =C55+D55 -> -20480247 | E56: =D56+E55 -> -19099698 | F56: =E56+F55 -> -17725651 | G56: =F56+G55 -> -16358108 | H56: =G56+H55 -> -14997067 | I56: =H56+I55 -> -13642530 | J56: =I56+J55 -> -12294496 | K56: =J56+K55 -> -10952965 | L56: =K56+L55 -> -9617937 | ... X56: =W56+X55 -> 4987044.5
B57: 回收年限評估 | D57: =IF((D56)>0,"回收","未回收") -> 未回收 | E57: =IF((E56)>0,"回收","未回收") -> 未回收 | F57: =IF((F56)>0,"回收","未回收") -> 未回收 | G57: =IF((G56)>0,"回收","未回收") -> 未回收 | H57: =IF((H56)>0,"回收","未回收") -> 未回收 | I57: =IF((I56)>0,"回收","未回收") -> 未回收 | J57: =IF((J56)>0,"回收","未回收") -> 未回收 | K57: =IF((K56)>0,"回收","未回收") -> 未回收 | ... X57: =IF((X56)>0,"回收","未回收") -> 回收
B58: 專案法IRR | C58: =IRR(C55:W55) -> 0.020619774
C60: 年份 | D60: =D37 -> 2023 | E60: =E37 -> 2024 | F60: =F37 -> 2025 | G60: =G37 -> 2026 | H60: =H37 -> 2027 | I60: =I37 -> 2028 | J60: =J37 -> 2029 | K60: =K37 -> 2030 | ... W60: =W37 -> 2042
B61: 0 | T61: 償還年限
B62: (Unit : Currency) | C62: 0 | D62: 1 | E62: 2 | F62: 3 | G62: 4 | H62: 5 | I62: 6 | J62: 7 | K62: 8 | L62: 9 | M62: 10 | N62: 11 | O62: 12 | P62: 13 | Q62: 14 | R62: 15 | S62: 16 | T62: 17 | U62: 18 | V62: 19 | W62: 20
B63: 發電度數(KWH) | C63: 0 | D63: =D40 -> 541531.98 | E63: =E40 -> 539343.97 | F63: =F40 -> 537155.96 | G63: =G40 -> 534967.96 | H63: =H40 -> 532779.95 | I63: =I40 -> 530591.94 | J63: =J40 -> 528403.93 | K63: =K40 -> 526215.92 | ... W63: =W40 -> 499959.83
B64: Inflow : 電費收入 | C64: - | D64: =D41 -> 2011899.6 | E64: =E41 -> 2003770.7 | F64: =F41 -> 1995641.8 | G64: =G41 -> 1987513 | H64: =H41 -> 1979384.1 | I64: =I41 -> 1971255.2 | J64: =J41 -> 1963126.3 | K64: =K41 -> 1954997.4 | ... W64: =W41 -> 1857450.8
B65: Inflow : 政府補助 | C65: - | G65: - | H65: - | I65: - | J65: - | K65: - | L65: - | M65: - | N65: - | O65: - | P65: - | Q65: - | R65: - | S65: - | T65: - | U65: - | V65: - | W65: -
B66: Inflow : 銀行借款
B67: Outflow : 設備折舊 | D67: =$C$44/$E$16 -> -1093365 | E67: =$C$44/$E$16 -> -1093365 | F67: =$C$44/$E$16 -> -1093365 | G67: =$C$44/$E$16 -> -1093365 | H67: =$C$44/$E$16 -> -1093365 | I67: =$C$44/$E$16 -> -1093365 | J67: =$C$44/$E$16 -> -1093365 | K67: =$C$44/$E$16 -> -1093365 | ... W67: =$C$44/$E$16 -> -1093365
B68: Outflow : 設備放置區域租金 | C68: - | D68: =D45 -> -290201 | E68: =E45 -> -290201 | F68: =F45 -> -290201 | G68: =G45 -> -290201 | H68: =H45 -> -290201 | I68: =I45 -> -290201 | J68: =J45 -> -290201 | K68: =K45 -> -290201 | ... W68: =W45 -> -290201
B69: Outflow : 返還借款
B70: Outflow : 利息費用 | C70: - | D70: 0 | E70: 0 | F70: 0 | G70: 0 | H70: 0 | I70: 0 | J70: 0 | K70: 0 | L70: 0 | M70: 0 | N70: 0 | O70: 0 | P70: 0 | Q70: 0 | R70: 0 | S70: 0 | T70: 0 | U70: 0 | V70: 0 | W70: 0
B71: Outflow : 維運費 | C71: - | D71: =D48 -> -174440 | E71: =E48 -> -174440 | F71: =F48 -> -174440 | G71: =G48 -> -174440 | H71: =H48 -> -174440 | I71: =I48 -> -174440 | J71: =J48 -> -174440 | K71: =K48 -> -174440 | ... W71: =W48 -> -174440
B72: Outflow : 保險費 | C72: - | D72: =D49 -> -43173.9 | E72: =E49 -> -43173.9 | F72: =F49 -> -43173.9 | G72: =G49 -> -43173.9 | H72: =H49 -> -43173.9 | I72: =I49 -> -43173.9 | J72: =J49 -> -43173.9 | K72: =K49 -> -43173.9 | ... W72: =W49 -> -43173.9
B73: Outflow : 模組回收費 | D73: =D50 -> -43610 | E73: =E50 -> -43610 | F73: =F50 -> -43610 | G73: =G50 -> -43610 | H73: =H50 -> -43610 | I73: =I50 -> -43610 | J73: =J50 -> -43610 | K73: =K50 -> -43610 | ... W73: =W50 -> 0
B74: Outflow : 其它費用(人事薪資…等)
B75: 1%管理費
B76: 稅前淨利 | D76: =SUM(D64:D75) -> 367109.71 | E76: =SUM(E64:E75) -> 358980.82 | F76: =SUM(F64:F75) -> 350851.94 | G76: =SUM(G64:G75) -> 342723.05 | H76: =SUM(H64:H75) -> 334594.16 | I76: =SUM(I64:I75) -> 326465.28 | J76: =SUM(J64:J75) -> 318336.39 | K76: =SUM(K64:K75) -> 310207.5 | ... X76: =SUM(X64:X75) -> 0
B77: 所得稅20% | D77: =-D76*0.2 -> -73421.942 | E77: =-E76*0.2 -> -71796.165 | F77: =-F76*0.2 -> -70170.387 | G77: =-G76*0.2 -> -68544.61 | H77: =-H76*0.2 -> -66918.833 | I77: =-I76*0.2 -> -65293.055 | J77: =-J76*0.2 -> -63667.278 | K77: =-K76*0.2 -> -62041.5 | ... X77: =-X76*0.2 -> 0
B78: 稅後淨利 | D78: =SUM(D76:D77) -> 293687.77 | E78: =SUM(E76:E77) -> 287184.66 | F78: =SUM(F76:F77) -> 280681.55 | G78: =SUM(G76:G77) -> 274178.44 | H78: =SUM(H76:H77) -> 267675.33 | I78: =SUM(I76:I77) -> 261172.22 | J78: =SUM(J76:J77) -> 254669.11 | K78: =SUM(K76:K77) -> 248166 | ... X78: =SUM(X76:X77) -> 0
B79: 累計現金流
B80: 回收年限評估

Sheet 淡江大學-財務模擬案場_p3
B1: 電站基本資料 | F1: 說明 | P1: =1-D11 -> 0.99 | Q1: =P1-$D12 -> 0.986 | R1: =Q1-$D12 -> 0.982 | S1: =R1-$D12 -> 0.978 | T1: =S1-$D12 -> 0.974 | U1: =T1-$D12 -> 0.97 | V1: =U1-$D12 -> 0.966 | W1: =V1-$D12 -> 0.962 | X1: =W1-$D12 -> 0.958 | ... AI1: =AH1-$D12 -> 0.914
B2: 電站名稱 | C2: 淡江大學-財務模擬案場 | D2: - | E2: - | F2: 填入本案場名稱
B3: 電站壽命 | C3: 20 | D3: - | E3: - | F3: 預設 20 年，代表財務評估年期。若合約年限不同可依實際情況修改
B4: 建置量(kWp) | C4: 436.1 | D4: - | E4: - | F4: 填入裝置容量（kWp），通常由設計圖面或報價書取得 | M4: 情境編號: 3
B5: 起始年度 | C5: 2023 | D5: 結束年度 | E5: 2042 | F5: 填入電站預計掛表的西元年份（例：2025）。結束年度會自動計算 | M5: 第2次滾算摘要
M6: 價金: 31000
B7: 綜合損益表 | M7: 專案IRR: 2.6
B8: 收入 | M8: 權益法IRR: 4.43
B9: 收支項目 | C9: 相關參數 | D9: 參數數值 | E9: 年限 | F9: 說明 | M9: 利潤率: 30.00%
B10: 電費收入 | C10: 年度AC併網總發電量 | D10: 547002 | E10: 20 | F10: 預估年發電量（kWh），通常來自 PVsyst 模擬或估算：裝置容量 × 年日照時數 × 系統效率 | M10: 第2次滾算，減少 2000 元 - 現金模式，每次減少 2000 元
C11: 首年衰退率 | D11: 0.01 | F11: 第一年發電衰退比率，請填小數（例：1% → 填 0.01）。一般首年衰退約 1~2%(請參考模組規格書)
C12: 次年衰退率 | D12: 0.004 | F12: 第二年起每年固定衰退比率，請填小數（例：0.4% → 填 0.004）。一般約 0.4~0.7%(請參考模組規格書)
C13: 躉售費率(FIT) / 綠電費率 | D13: 3.7152 | F13: 與台電簽訂的躉購費率或綠電合約費率，單位：元/度。請參考台電公告或合約內容
B14: 支出
B15: 收支項目 | C15: 相關參數 | D15: 參數數值 | E15: 攤提年限 | F15: 說明
B16: 設備費用(價金) | C16: 每kWp設備成本 | D16: 31000 | E16: 20 | F16: 每峰瓩設備成本（元/kWp），包含模組、逆變器、支架等硬體，不含工程施工費
C17: 信邦利潤率(ex:20%填0.2) | D17: 0.3 | F17: 公司在設備費用上加計的利潤比率，請填小數（例：20% → 填 0.2）
C18: 開發費 | D18: 3000 | F18: 前期開發費用（元），含可行性評估、申請規費、地主溝通等。若無則填 0
B19: 租金費用 | C19: 租金計算方式 | D19: 1 | E19: 0 | F19: 填 1 = 固定年租金（需填方式1參數）；填 2 = 依電費收入抽成（需填方式2參數）
C20: 【方式1參數】每年相同價格 | D20: 290201 | E20: 20 | F20: 租金計算方式選「1」時填寫，固定年租金金額（元/年），套用至整個電站壽命期
C21: 【方式2參數】抽成比率 | D21: 0 | E21: 0 | F21: 租金計算方式選「2」時填寫，請填小數（例：10% → 填 0.1）。租金 = 當年電費收入 × 抽成比率
B22: 運維費用 | C22: 每kw運維成本 | D22: 400 | E22: 20 | F22: 每峰瓩每年運維費用（元/kWp/年），含清洗、巡檢、維修等。
B23: 保險費用 | C23: 占整體設備費用比例 | D23: 0.003 | E23: 20 | F23: 保險費佔設備總費用比率，填小數（例：0.3% → 填 0.003）。預設 0.003，可依投保條件調整
B24: 模組回收費用 | C24: 每kw模組回收成本 | D24: 1000 | E24: 10 | F24: 每峰瓩模組廢棄回收費用（元/kWp），於第 1~10 年計提（攤提 10 年）。
B25: 利息費用 | C25: 銀行利率 | D25: 0.025595 | E25: 0 | F25: 向銀行貸款的年利率，填小數（例：2.56% → 填 0.0256）。請依銀行核准利率填入
B26: 所得稅 | C26: 所得稅率 | D26: 0.2 | E26: 0 | F26: 公司所得稅率，填小數（例：20% → 填 0.2）。預設 0.2，通常不需更改
B29: 現金流量表
B30: 金流項目 | C30: 相關參數 | D30: 參數數值 | F30: 說明
B31: 貸款成數 | C31: 占總設備費用比例 | D31: 0.8 | F31: 貸款佔設備總費用比例，填小數（例：80% → 填 0.8）。預設 0.8 代表貸八成、自備二成
B32: 貸款還款 | C32: 攤還期數 | D32: 15 | F32: 貸款還款年數（年）。預設 15 年，代表分 15 年平均攤還本金
B33: 現金股利 | C33: 股利比率 | D33: 0.9 | F33: 稅後現金流中分配給股東的比例，填小數（例：90% → 填 0.9）
B34: 年底減資 | C34: 攤還期數 | D34: 4 | F34: 年底減資返還股東的年數。預設 4 年，代表 倒數 4 年進行減資，加速資金返還
C37: 年份 | D37: 2023 | E37: 2024 | F37: 2025 | G37: 2026 | H37: 2027 | I37: 2028 | J37: 2029 | K37: 2030 | L37: 2031 | M37: 2032 | N37: 2033 | O37: 2034 | P37: 2035 | Q37: 2036 | R37: 2037 | S37: 2038 | T37: 2039 | U37: 2040 | V37: 2041 | W37: 2042
B38: 0
B39: (Unit : Currency) | C39: 0 | D39: 1 | E39: 2 | F39: 3 | G39: 4 | H39: 5 | I39: 6 | J39: 7 | K39: 8 | L39: 9 | M39: 10 | N39: 11 | O39: 12 | P39: 13 | Q39: 14 | R39: 15 | S39: 16 | T39: 17 | U39: 18 | V39: 19 | W39: 20
B40: 發電度數(KWH) | C40: 0 | D40: =$D$10*P1 -> 541531.98 | E40: =$D$10*Q1 -> 539343.97 | F40: =$D$10*R1 -> 537155.96 | G40: =$D$10*S1 -> 534967.96 | H40: =$D$10*T1 -> 532779.95 | I40: =$D$10*U1 -> 530591.94 | J40: =$D$10*V1 -> 528403.93 | K40: =$D$10*W1 -> 526215.92 | ... W40: =$D$10*AI1 -> 499959.83
B41: Inflow : 電費收入 | C41: - | D41: =D40*$D$13 -> 2011899.6 | E41: =E40*$D$13 -> 2003770.7 | F41: =F40*$D$13 -> 1995641.8 | G41: =G40*$D$13 -> 1987513 | H41: =H40*$D$13 -> 1979384.1 | I41: =I40*$D$13 -> 1971255.2 | J41: =J40*$D$13 -> 1963126.3 | K41: =K40*$D$13 -> 1954997.4 | ... W41: =W40*$D$13 -> 1857450.8
B42: Inflow : 政府補助 | C42: - | G42: - | H42: - | I42: - | J42: - | K42: - | L42: - | M42: - | N42: - | O42: - | P42: - | Q42: - | R42: - | S42: - | T42: - | U42: - | V42: - | W42: -
B43: Inflow : 銀行借款
B44: Outflow : 設備費用 | C44: =-(D16/(1-D17)+D18)*C4 -> -20621300
B45: Outflow : 設備放置區域租金 | C45: - | D45: -290201 | E45: -290201 | F45: -290201 | G45: -290201 | H45: -290201 | I45: -290201 | J45: -290201 | K45: -290201 | L45: -290201 | M45: -290201 | N45: -290201 | O45: -290201 | P45: -290201 | Q45: -290201 | R45: -290201 | S45: -290201 | T45: -290201 | U45: -290201 | V45: -290201 | W45: -290201
B46: Outflow : 返還借款
B47: Outflow : 利息費用 | C47: -
B48: Outflow : 維運費 | C48: - | D48: -174440 | E48: -174440 | F48: -174440 | G48: -174440 | H48: -174440 | I48: -174440 | J48: -174440 | K48: -174440 | L48: -174440 | M48: -174440 | N48: -174440 | O48: -174440 | P48: -174440 | Q48: -174440 | R48: -174440 | S48: -174440 | T48: -174440 | U48: -174440 | V48: -174440 | W48: -174440
B49: Outflow : 保險費 | C49: - | D49: -40557.3 | E49: -40557.3 | F49: -40557.3 | G49: -40557.3 | H49: -40557.3 | I49: -40557.3 | J49: -40557.3 | K49: -40557.3 | L49: -40557.3 | M49: -40557.3 | N49: -40557.3 | O49: -40557.3 | P49: -40557.3 | Q49: -40557.3 | R49: -40557.3 | S49: -40557.3 | T49: -40557.3 | U49: -40557.3 | V49: -40557.3 | W49: -40557.3
B50: Outflow : 模組回收費 | D50: -43610 | E50: -43610 | F50: -43610 | G50: -43610 | H50: -43610 | I50: -43610 | J50: -43610 | K50: -43610 | L50: -43610 | M50: -43610 | N50: 0 | O50: 0 | P50: 0 | Q50: 0 | R50: 0 | S50: 0 | T50: 0 | U50: 0 | V50: 0 | W50: 0
B51: Outflow : 其它費用(人事薪資…等)
B52: 1%管理費
B53: 績效獎金
B54: 所得稅20% | D54: =D77 -> -86405.262 | E54: =E77 -> -84779.485 | F54: =F77 -> -83153.707 | G54: =G77 -> -81527.93 | H54: =H77 -> -79902.153 | I54: =I77 -> -78276.375 | J54: =J77 -> -76650.598 | K54: =K77 -> -75024.82 | ... W54: =W77 -> -64237.491
B55: 現金流 | C55: =C44 -> -20621300 | D55: =SUM(D41:D54) -> 1376686 | E55: =SUM(E41:E54) -> 1370182.9 | F55: =SUM(F41:F54) -> 1363679.8 | G55: =SUM(G41:G54) -> 1357176.7 | H55: =SUM(H41:H54) -> 1350673.6 | I55: =SUM(I41:I54) -> 1344170.5 | J55: =SUM(J41:J54) -> 1337667.4 | K55: =SUM(K41:K54) -> 1331164.3 | ... W55: =SUM(W41:W54) -> 1288015
B56: 累計現金流 | D56: =C55+D55 -> -19244614 | E56: =D56+E55 -> -17874431 | F56: =E56+F55 -> -16510751 | G56: =F56+G55 -> -15153574 | H56: =G56+H55 -> -13802901 | I56: =H56+I55 -> -12458730 | J56: =I56+J55 -> -11121063 | K56: =J56+K55 -> -9789898.7 | L56: =K56+L55 -> -8465237.5 | ... X56: =W56+X55 -> 6025710.1
B57: 回收年限評估 | D57: =IF((D56)>0,"回收","未回收") -> 未回收 | E57: =IF((E56)>0,"回收","未回收") -> 未回收 | F57: =IF((F56)>0,"回收","未回收") -> 未回收 | G57: =IF((G56)>0,"回收","未回收") -> 未回收 | H57: =IF((H56)>0,"回收","未回收") -> 未回收 | I57: =IF((I56)>0,"回收","未回收") -> 未回收 | J57: =IF((J56)>0,"回收","未回收") -> 未回收 | K57: =IF((K56)>0,"回收","未回收") -> 未回收 | ... X57: =IF((X56)>0,"回收","未回收") -> 回收
B58: 專案法IRR | C58: =IRR(C55:W55) -> 0.026026138
C60: 年份 | D60: =D37 -> 2023 | E60: =E37 -> 2024 | F60: =F37 -> 2025 | G60: =G37 -> 2026 | H60: =H37 -> 2027 | I60: =I37 -> 2028 | J60: =J37 -> 2029 | K60: =K37 -> 2030 | ... W60: =W37 -> 2042
B61: 0 | T61: 償還年限
B62: (Unit : Currency) | C62: 0 | D62: 1 | E62: 2 | F62: 3 | G62: 4 | H62: 5 | I62: 6 | J62: 7 | K62: 8 | L62: 9 | M62: 10 | N62: 11 | O62: 12 | P62: 13 | Q62: 14 | R62: 15 | S62: 16 | T62: 17 | U62: 18 | V62: 19 | W62: 20
B63: 發電度數(KWH) | C63: 0 | D63: =D40 -> 541531.98 | E63: =E40 -> 539343.97 | F63: =F40 -> 537155.96 | G63: =G40 -> 534967.96 | H63: =H40 -> 532779.95 | I63: =I40 -> 530591.94 | J63: =J40 -> 528403.93 | K63: =K40 -> 526215.92 | ... W63: =W40 -> 499959.83
B64: Inflow : 電費收入 | C64: - | D64: =D41 -> 2011899.6 | E64: =E41 -> 2003770.7 | F64: =F41 -> 1995641.8 | G64: =G41 -> 1987513 | H64: =H41 -> 1979384.1 | I64: =I41 -> 1971255.2 | J64: =J41 -> 1963126.3 | K64: =K41 -> 1954997.4 | ... W64: =W41 -> 1857450.8
B65: Inflow : 政府補助 | C65: - | G65: - | H65: - | I65: - | J65: - | K65: - | L65: - | M65: - | N65: - | O65: - | P65: - | Q65: - | R65: - | S65: - | T65: - | U65: - | V65: - | W65: -
B66: Inflow : 銀行借款
B67: Outflow : 設備折舊 | D67: =$C$44/$E$16 -> -1031065 | E67: =$C$44/$E$16 -> -1031065 | F67: =$C$44/$E$16 -> -1031065 | G67: =$C$44/$E$16 -> -1031065 | H67: =$C$44/$E$16 -> -1031065 | I67: =$C$44/$E$16 -> -1031065 | J67: =$C$44/$E$16 -> -1031065 | K67: =$C$44/$E$16 -> -1031065 | ... W67: =$C$44/$E$16 -> -1031065
B68: Outflow : 設備放置區域租金 | C68: - | D68: =D45 -> -290201 | E68: =E45 -> -290201 | F68: =F45 -> -290201 | G68: =G45 -> -290201 | H68: =H45 -> -290201 | I68: =I45 -> -290201 | J68: =J45 -> -290201 | K68: =K45 -> -290201 | ... W68: =W45 -> -290201
B69: Outflow : 返還借款
B70: Outflow : 利息費用 | C70: - | D70: 0 | E70: 0 | F70: 0 | G70: 0 | H70: 0 | I70: 0 | J70: 0 | K70: 0 | L70: 0 | M70: 0 | N70: 0 | O70: 0 | P70: 0 | Q70: 0 | R70: 0 | S70: 0 | T70: 0 | U70: 0 | V70: 0 | W70: 0
B71: Outflow : 維運費 | C71: - | D71: =D48 -> -174440 | E71: =E48 -> -174440 | F71: =F48 -> -174440 | G71: =G48 -> -174440 | H71: =H48 -> -174440 | I71: =I48 -> -174440 | J71: =J48 -> -174440 | K71: =K48 -> -174440 | ... W71: =W48 -> -174440
B72: Outflow : 保險費 | C72: - | D72: =D49 -> -40557.3 | E72: =E49 -> -40557.3 | F72: =F49 -> -40557.3 | G72: =G49 -> -40557.3 | H72: =H49 -> -40557.3 | I72: =I49 -> -40557.3 | J72: =J49 -> -40557.3 | K72: =K49 -> -40557.3 | ... W72: =W49 -> -40557.3
B73: Outflow : 模組回收費 | D73: =D50 -> -43610 | E73: =E50 -> -43610 | F73: =F50 -> -43610 | G73: =G50 -> -43610 | H73: =H50 -> -43610 | I73: =I50 -> -43610 | J73: =J50 -> -43610 | K73: =K50 -> -43610 | ... W73: =W50 -> 0
B74: Outflow : 其它費用(人事薪資…等)
B75: 1%管理費
B76: 稅前淨利 | D76: =SUM(D64:D75) -> 432026.31 | E76: =SUM(E64:E75) -> 423897.42 | F76: =SUM(F64:F75) -> 415768.54 | G76: =SUM(G64:G75) -> 407639.65 | H76: =SUM(H64:H75) -> 399510.76 | I76: =SUM(I64:I75) -> 391381.88 | J76: =SUM(J64:J75) -> 383252.99 | K76: =SUM(K64:K75) -> 375124.1 | ... X76: =SUM(X64:X75) -> 0
B77: 所得稅20% | D77: =-D76*0.2 -> -86405.262 | E77: =-E76*0.2 -> -84779.485 | F77: =-F76*0.2 -> -83153.707 | G77: =-G76*0.2 -> -81527.93 | H77: =-H76*0.2 -> -79902.153 | I77: =-I76*0.2 -> -78276.375 | J77: =-J76*0.2 -> -76650.598 | K77: =-K76*0.2 -> -75024.82 | ... X77: =-X76*0.2 -> 0
B78: 稅後淨利 | D78: =SUM(D76:D77) -> 345621.05 | E78: =SUM(E76:E77) -> 339117.94 | F78: =SUM(F76:F77) -> 332614.83 | G78: =SUM(G76:G77) -> 326111.72 | H78: =SUM(H76:H77) -> 319608.61 | I78: =SUM(I76:I77) -> 313105.5 | J78: =SUM(J76:J77) -> 306602.39 | K78: =SUM(K76:K77) -> 300099.28 | ... X78: =SUM(X76:X77) -> 0
B79: 累計現金流
B80: 回收年限評估
