Workbook

Sheet 多站彙整
C4: 年份 | D4: 2020 | E4: 2021 | F4: 2022 | G4: 2023 | H4: 2024 | I4: 2025 | J4: 2026 | K4: 2027 | L4: 2028 | M4: 2029 | N4: 2030 | O4: 2031 | P4: 2032 | Q4: 2033 | R4: 2034 | S4: 2035 | T4: 2036 | U4: 2037 | V4: 2038 | W4: 2039
C5: 預估發電度數
B6: 淡江大學 | D6: =ROUND(ABS(淡江大學_p2!D40),0) -> 0 | E6: =ROUND(ABS(淡江大學_p2!E40),0) -> 0 | F6: =ROUND(ABS(淡江大學_p2!F40),0) -> 0 | G6: =ROUND(ABS(淡江大學_p2!G40),0) -> 0 | H6: =ROUND(ABS(淡江大學_p2!H40),0) -> 0 | I6: =ROUND(ABS(淡江大學_p2!I40),0) -> 0 | J6: =ROUND(ABS(淡江大學_p2!J40),0) -> 0 | K6: =ROUND(ABS(淡江大學_p2!K40),0) -> 0 | ... W6: =ROUND(ABS(淡江大學_p2!W40),0) -> 0
B7: 淡江大學 | D7: =ROUND(ABS(淡江大學_p3!D40),0) -> 0 | E7: =ROUND(ABS(淡江大學_p3!E40),0) -> 0 | F7: =ROUND(ABS(淡江大學_p3!F40),0) -> 0 | G7: =ROUND(ABS(淡江大學_p3!G40),0) -> 0 | H7: =ROUND(ABS(淡江大學_p3!H40),0) -> 0 | I7: =ROUND(ABS(淡江大學_p3!I40),0) -> 0 | J7: =ROUND(ABS(淡江大學_p3!J40),0) -> 0 | K7: =ROUND(ABS(淡江大學_p3!K40),0) -> 0 | ... W7: =ROUND(ABS(淡江大學_p3!W40),0) -> 0
C8: 預估發電度數/年總計 | D8: =SUM(D6:D7) -> 0 | E8: =SUM(E6:E7) -> 0 | F8: =SUM(F6:F7) -> 0 | G8: =SUM(G6:G7) -> 0 | H8: =SUM(H6:H7) -> 0 | I8: =SUM(I6:I7) -> 0 | J8: =SUM(J6:J7) -> 0 | K8: =SUM(K6:K7) -> 0 | ... W8: =SUM(W6:W7) -> 0
C9: 年份 | D9: 2020 | E9: 2021 | F9: 2022 | G9: 2023 | H9: 2024 | I9: 2025 | J9: 2026 | K9: 2027 | L9: 2028 | M9: 2029 | N9: 2030 | O9: 2031 | P9: 2032 | Q9: 2033 | R9: 2034 | S9: 2035 | T9: 2036 | U9: 2037 | V9: 2038 | W9: 2039
C10: 預估收入
B11: 淡江大學 | D11: =ROUND(ABS(淡江大學_p2!D41),0) -> 0 | E11: =ROUND(ABS(淡江大學_p2!E41),0) -> 0 | F11: =ROUND(ABS(淡江大學_p2!F41),0) -> 0 | G11: =ROUND(ABS(淡江大學_p2!G41),0) -> 0 | H11: =ROUND(ABS(淡江大學_p2!H41),0) -> 0 | I11: =ROUND(ABS(淡江大學_p2!I41),0) -> 0 | J11: =ROUND(ABS(淡江大學_p2!J41),0) -> 0 | K11: =ROUND(ABS(淡江大學_p2!K41),0) -> 0 | ... W11: =ROUND(ABS(淡江大學_p2!W41),0) -> 0
B12: 淡江大學 | D12: =ROUND(ABS(淡江大學_p3!D41),0) -> 0 | E12: =ROUND(ABS(淡江大學_p3!E41),0) -> 0 | F12: =ROUND(ABS(淡江大學_p3!F41),0) -> 0 | G12: =ROUND(ABS(淡江大學_p3!G41),0) -> 0 | H12: =ROUND(ABS(淡江大學_p3!H41),0) -> 0 | I12: =ROUND(ABS(淡江大學_p3!I41),0) -> 0 | J12: =ROUND(ABS(淡江大學_p3!J41),0) -> 0 | K12: =ROUND(ABS(淡江大學_p3!K41),0) -> 0 | ... W12: =ROUND(ABS(淡江大學_p3!W41),0) -> 0
C13: 預估收入/年總計 | D13: =SUM(D11:D12) -> 0 | E13: =SUM(E11:E12) -> 0 | F13: =SUM(F11:F12) -> 0 | G13: =SUM(G11:G12) -> 0 | H13: =SUM(H11:H12) -> 0 | I13: =SUM(I11:I12) -> 0 | J13: =SUM(J11:J12) -> 0 | K13: =SUM(K11:K12) -> 0 | ... W13: =SUM(W11:W12) -> 0
C14: 年份 | D14: 2020 | E14: 2021 | F14: 2022 | G14: 2023 | H14: 2024 | I14: 2025 | J14: 2026 | K14: 2027 | L14: 2028 | M14: 2029 | N14: 2030 | O14: 2031 | P14: 2032 | Q14: 2033 | R14: 2034 | S14: 2035 | T14: 2036 | U14: 2037 | V14: 2038 | W14: 2039
C15: 租金
B16: 淡江大學 | D16: =ROUND(ABS(淡江大學_p2!D45),0) -> 290201 | E16: =ROUND(ABS(淡江大學_p2!E45),0) -> 290201 | F16: =ROUND(ABS(淡江大學_p2!F45),0) -> 290201 | G16: =ROUND(ABS(淡江大學_p2!G45),0) -> 290201 | H16: =ROUND(ABS(淡江大學_p2!H45),0) -> 290201 | I16: =ROUND(ABS(淡江大學_p2!I45),0) -> 290201 | J16: =ROUND(ABS(淡江大學_p2!J45),0) -> 290201 | K16: =ROUND(ABS(淡江大學_p2!K45),0) -> 290201 | ... W16: =ROUND(ABS(淡江大學_p2!W45),0) -> 290201
B17: 淡江大學 | D17: =ROUND(ABS(淡江大學_p3!D45),0) -> 290201 | E17: =ROUND(ABS(淡江大學_p3!E45),0) -> 290201 | F17: =ROUND(ABS(淡江大學_p3!F45),0) -> 290201 | G17: =ROUND(ABS(淡江大學_p3!G45),0) -> 290201 | H17: =ROUND(ABS(淡江大學_p3!H45),0) -> 290201 | I17: =ROUND(ABS(淡江大學_p3!I45),0) -> 290201 | J17: =ROUND(ABS(淡江大學_p3!J45),0) -> 290201 | K17: =ROUND(ABS(淡江大學_p3!K45),0) -> 290201 | ... W17: =ROUND(ABS(淡江大學_p3!W45),0) -> 290201
C18: 租金/年總計 | D18: =SUM(D16:D17) -> 580402 | E18: =SUM(E16:E17) -> 580402 | F18: =SUM(F16:F17) -> 580402 | G18: =SUM(G16:G17) -> 580402 | H18: =SUM(H16:H17) -> 580402 | I18: =SUM(I16:I17) -> 580402 | J18: =SUM(J16:J17) -> 580402 | K18: =SUM(K16:K17) -> 580402 | ... W18: =SUM(W16:W17) -> 580402
C19: 年份 | D19: 2020 | E19: 2021 | F19: 2022 | G19: 2023 | H19: 2024 | I19: 2025 | J19: 2026 | K19: 2027 | L19: 2028 | M19: 2029 | N19: 2030 | O19: 2031 | P19: 2032 | Q19: 2033 | R19: 2034 | S19: 2035 | T19: 2036 | U19: 2037 | V19: 2038 | W19: 2039
C20: 運維
B21: 淡江大學 | D21: =ROUND(ABS(淡江大學_p2!D48),0) -> 174440 | E21: =ROUND(ABS(淡江大學_p2!E48),0) -> 174440 | F21: =ROUND(ABS(淡江大學_p2!F48),0) -> 174440 | G21: =ROUND(ABS(淡江大學_p2!G48),0) -> 174440 | H21: =ROUND(ABS(淡江大學_p2!H48),0) -> 174440 | I21: =ROUND(ABS(淡江大學_p2!I48),0) -> 174440 | J21: =ROUND(ABS(淡江大學_p2!J48),0) -> 174440 | K21: =ROUND(ABS(淡江大學_p2!K48),0) -> 174440 | ... W21: =ROUND(ABS(淡江大學_p2!W48),0) -> 174440
B22: 淡江大學 | D22: =ROUND(ABS(淡江大學_p3!D48),0) -> 174440 | E22: =ROUND(ABS(淡江大學_p3!E48),0) -> 174440 | F22: =ROUND(ABS(淡江大學_p3!F48),0) -> 174440 | G22: =ROUND(ABS(淡江大學_p3!G48),0) -> 174440 | H22: =ROUND(ABS(淡江大學_p3!H48),0) -> 174440 | I22: =ROUND(ABS(淡江大學_p3!I48),0) -> 174440 | J22: =ROUND(ABS(淡江大學_p3!J48),0) -> 174440 | K22: =ROUND(ABS(淡江大學_p3!K48),0) -> 174440 | ... W22: =ROUND(ABS(淡江大學_p3!W48),0) -> 174440
C23: 運維/年總計 | D23: =SUM(D21:D22) -> 348880 | E23: =SUM(E21:E22) -> 348880 | F23: =SUM(F21:F22) -> 348880 | G23: =SUM(G21:G22) -> 348880 | H23: =SUM(H21:H22) -> 348880 | I23: =SUM(I21:I22) -> 348880 | J23: =SUM(J21:J22) -> 348880 | K23: =SUM(K21:K22) -> 348880 | ... W23: =SUM(W21:W22) -> 348880
C24: 年份 | D24: 2020 | E24: 2021 | F24: 2022 | G24: 2023 | H24: 2024 | I24: 2025 | J24: 2026 | K24: 2027 | L24: 2028 | M24: 2029 | N24: 2030 | O24: 2031 | P24: 2032 | Q24: 2033 | R24: 2034 | S24: 2035 | T24: 2036 | U24: 2037 | V24: 2038 | W24: 2039
C25: 保險
B26: 淡江大學 | D26: =ROUND(ABS(淡江大學_p2!D49),0) -> 43174 | E26: =ROUND(ABS(淡江大學_p2!E49),0) -> 43174 | F26: =ROUND(ABS(淡江大學_p2!F49),0) -> 43174 | G26: =ROUND(ABS(淡江大學_p2!G49),0) -> 43174 | H26: =ROUND(ABS(淡江大學_p2!H49),0) -> 43174 | I26: =ROUND(ABS(淡江大學_p2!I49),0) -> 43174 | J26: =ROUND(ABS(淡江大學_p2!J49),0) -> 43174 | K26: =ROUND(ABS(淡江大學_p2!K49),0) -> 43174 | ... W26: =ROUND(ABS(淡江大學_p2!W49),0) -> 43174
B27: 淡江大學 | D27: =ROUND(ABS(淡江大學_p3!D49),0) -> 40557 | E27: =ROUND(ABS(淡江大學_p3!E49),0) -> 40557 | F27: =ROUND(ABS(淡江大學_p3!F49),0) -> 40557 | G27: =ROUND(ABS(淡江大學_p3!G49),0) -> 40557 | H27: =ROUND(ABS(淡江大學_p3!H49),0) -> 40557 | I27: =ROUND(ABS(淡江大學_p3!I49),0) -> 40557 | J27: =ROUND(ABS(淡江大學_p3!J49),0) -> 40557 | K27: =ROUND(ABS(淡江大學_p3!K49),0) -> 40557 | ... W27: =ROUND(ABS(淡江大學_p3!W49),0) -> 40557
C28: 保險/年總計 | D28: =SUM(D26:D27) -> 83731 | E28: =SUM(E26:E27) -> 83731 | F28: =SUM(F26:F27) -> 83731 | G28: =SUM(G26:G27) -> 83731 | H28: =SUM(H26:H27) -> 83731 | I28: =SUM(I26:I27) -> 83731 | J28: =SUM(J26:J27) -> 83731 | K28: =SUM(K26:K27) -> 83731 | ... W28: =SUM(W26:W27) -> 83731
C29: 年份 | D29: 2020 | E29: 2021 | F29: 2022 | G29: 2023 | H29: 2024 | I29: 2025 | J29: 2026 | K29: 2027 | L29: 2028 | M29: 2029 | N29: 2030 | O29: 2031 | P29: 2032 | Q29: 2033 | R29: 2034 | S29: 2035 | T29: 2036 | U29: 2037 | V29: 2038 | W29: 2039
C30: 模組回收費
B31: 淡江大學 | D31: =ROUND(ABS(淡江大學_p2!D50),0) -> 43610 | E31: =ROUND(ABS(淡江大學_p2!E50),0) -> 43610 | F31: =ROUND(ABS(淡江大學_p2!F50),0) -> 43610 | G31: =ROUND(ABS(淡江大學_p2!G50),0) -> 43610 | H31: =ROUND(ABS(淡江大學_p2!H50),0) -> 43610 | I31: =ROUND(ABS(淡江大學_p2!I50),0) -> 43610 | J31: =ROUND(ABS(淡江大學_p2!J50),0) -> 43610 | K31: =ROUND(ABS(淡江大學_p2!K50),0) -> 43610 | ... W31: =ROUND(ABS(淡江大學_p2!W50),0) -> 0
B32: 淡江大學 | D32: =ROUND(ABS(淡江大學_p3!D50),0) -> 43610 | E32: =ROUND(ABS(淡江大學_p3!E50),0) -> 43610 | F32: =ROUND(ABS(淡江大學_p3!F50),0) -> 43610 | G32: =ROUND(ABS(淡江大學_p3!G50),0) -> 43610 | H32: =ROUND(ABS(淡江大學_p3!H50),0) -> 43610 | I32: =ROUND(ABS(淡江大學_p3!I50),0) -> 43610 | J32: =ROUND(ABS(淡江大學_p3!J50),0) -> 43610 | K32: =ROUND(ABS(淡江大學_p3!K50),0) -> 43610 | ... W32: =ROUND(ABS(淡江大學_p3!W50),0) -> 0
C33: 模組回收費/年總計 | D33: =SUM(D31:D32) -> 87220 | E33: =SUM(E31:E32) -> 87220 | F33: =SUM(F31:F32) -> 87220 | G33: =SUM(G31:G32) -> 87220 | H33: =SUM(H31:H32) -> 87220 | I33: =SUM(I31:I32) -> 87220 | J33: =SUM(J31:J32) -> 87220 | K33: =SUM(K31:K32) -> 87220 | ... W33: =SUM(W31:W32) -> 0
C34: 年份 | D34: 2020 | E34: 2021 | F34: 2022 | G34: 2023 | H34: 2024 | I34: 2025 | J34: 2026 | K34: 2027 | L34: 2028 | M34: 2029 | N34: 2030 | O34: 2031 | P34: 2032 | Q34: 2033 | R34: 2034 | S34: 2035 | T34: 2036 | U34: 2037 | V34: 2038 | W34: 2039
C35: 所得稅
B36: 淡江大學 | D36: =ROUND(ABS(淡江大學_p2!D54),0) -> 0 | E36: =ROUND(ABS(淡江大學_p2!E54),0) -> 0 | F36: =ROUND(ABS(淡江大學_p2!F54),0) -> 0 | G36: =ROUND(ABS(淡江大學_p2!G54),0) -> 0 | H36: =ROUND(ABS(淡江大學_p2!H54),0) -> 0 | I36: =ROUND(ABS(淡江大學_p2!I54),0) -> 0 | J36: =ROUND(ABS(淡江大學_p2!J54),0) -> 0 | K36: =ROUND(ABS(淡江大學_p2!K54),0) -> 0 | ... W36: =ROUND(ABS(淡江大學_p2!W54),0) -> 0
B37: 淡江大學 | D37: =ROUND(ABS(淡江大學_p3!D54),0) -> 0 | E37: =ROUND(ABS(淡江大學_p3!E54),0) -> 0 | F37: =ROUND(ABS(淡江大學_p3!F54),0) -> 0 | G37: =ROUND(ABS(淡江大學_p3!G54),0) -> 0 | H37: =ROUND(ABS(淡江大學_p3!H54),0) -> 0 | I37: =ROUND(ABS(淡江大學_p3!I54),0) -> 0 | J37: =ROUND(ABS(淡江大學_p3!J54),0) -> 0 | K37: =ROUND(ABS(淡江大學_p3!K54),0) -> 0 | ... W37: =ROUND(ABS(淡江大學_p3!W54),0) -> 0
C38: 所得稅/年總計 | D38: =SUM(D36:D37) -> 0 | E38: =SUM(E36:E37) -> 0 | F38: =SUM(F36:F37) -> 0 | G38: =SUM(G36:G37) -> 0 | H38: =SUM(H36:H37) -> 0 | I38: =SUM(I36:I37) -> 0 | J38: =SUM(J36:J37) -> 0 | K38: =SUM(K36:K37) -> 0 | ... W38: =SUM(W36:W37) -> 0
C39: 年份 | D39: 2020 | E39: 2021 | F39: 2022 | G39: 2023 | H39: 2024 | I39: 2025 | J39: 2026 | K39: 2027 | L39: 2028 | M39: 2029 | N39: 2030 | O39: 2031 | P39: 2032 | Q39: 2033 | R39: 2034 | S39: 2035 | T39: 2036 | U39: 2037 | V39: 2038 | W39: 2039
C40: 設備折舊
B41: 淡江大學 | D41: =ROUND(ABS(淡江大學_p2!D67),0) -> 0 | E41: =ROUND(ABS(淡江大學_p2!E67),0) -> 0 | F41: =ROUND(ABS(淡江大學_p2!F67),0) -> 0 | G41: =ROUND(ABS(淡江大學_p2!G67),0) -> 0 | H41: =ROUND(ABS(淡江大學_p2!H67),0) -> 0 | I41: =ROUND(ABS(淡江大學_p2!I67),0) -> 0 | J41: =ROUND(ABS(淡江大學_p2!J67),0) -> 0 | K41: =ROUND(ABS(淡江大學_p2!K67),0) -> 0 | ... W41: =ROUND(ABS(淡江大學_p2!W67),0) -> 0
B42: 淡江大學 | D42: =ROUND(ABS(淡江大學_p3!D67),0) -> 0 | E42: =ROUND(ABS(淡江大學_p3!E67),0) -> 0 | F42: =ROUND(ABS(淡江大學_p3!F67),0) -> 0 | G42: =ROUND(ABS(淡江大學_p3!G67),0) -> 0 | H42: =ROUND(ABS(淡江大學_p3!H67),0) -> 0 | I42: =ROUND(ABS(淡江大學_p3!I67),0) -> 0 | J42: =ROUND(ABS(淡江大學_p3!J67),0) -> 0 | K42: =ROUND(ABS(淡江大學_p3!K67),0) -> 0 | ... W42: =ROUND(ABS(淡江大學_p3!W67),0) -> 0
C43: 設備折舊/年總計 | D43: =SUM(D41:D42) -> 0 | E43: =SUM(E41:E42) -> 0 | F43: =SUM(F41:F42) -> 0 | G43: =SUM(G41:G42) -> 0 | H43: =SUM(H41:H42) -> 0 | I43: =SUM(I41:I42) -> 0 | J43: =SUM(J41:J42) -> 0 | K43: =SUM(K41:K42) -> 0 | ... W43: =SUM(W41:W42) -> 0
B45: 貸款成數(%) | C45: 80
B46: 還款期數 | C46: 15
B47: 股利比率(%) | C47: 90
B48: 年底減資攤還期數 | C48: 4
B49: 銀行利率(%) | C49: 3
C50: 年份 | D50: 2020 | E50: 2021 | F50: 2022 | G50: 2023 | H50: 2024 | I50: 2025 | J50: 2026 | K50: 2027 | L50: 2028 | M50: 2029 | N50: 2030 | O50: 2031 | P50: 2032 | Q50: 2033 | R50: 2034 | S50: 2035 | T50: 2036 | U50: 2037 | V50: 2038 | W50: 2039
B51: 0
B52: (Unit : Currency) | C52: 0 | D52: 1 | E52: 2 | F52: 3 | G52: 4 | H52: 5 | I52: 6 | J52: 7 | K52: 8 | L52: 9 | M52: 10 | N52: 11 | O52: 12 | P52: 13 | Q52: 14 | R52: 15 | S52: 16 | T52: 17 | U52: 18 | V52: 19 | W52: 20
B53: 發電度數(KWH) | C53: 0 | D53: =D8 -> 0 | E53: =E8 -> 0 | F53: =F8 -> 0 | G53: =G8 -> 0 | H53: =H8 -> 0 | I53: =I8 -> 0 | J53: =J8 -> 0 | K53: =K8 -> 0 | ... W53: =W8 -> 0
B54: Inflow : 電費收入 | C54: - | D54: =D13 -> 0 | E54: =E13 -> 0 | F54: =F13 -> 0 | G54: =G13 -> 0 | H54: =H13 -> 0 | I54: =I13 -> 0 | J54: =J13 -> 0 | K54: =K13 -> 0 | ... W54: =W13 -> 0
B55: Inflow : 政府補助 | C55: - | G55: - | H55: - | I55: - | J55: - | K55: - | L55: - | M55: - | N55: - | O55: - | P55: - | Q55: - | R55: - | S55: - | T55: - | U55: - | V55: - | W55: -
B56: Inflow : 銀行借款
B57: Outflow : 設備費用 | C57: =-SUM(D43:W43) -> 0
B58: Outflow : 設備放置區域租金 | C58: - | D58: =-D18 -> -580402 | E58: =-E18 -> -580402 | F58: =-F18 -> -580402 | G58: =-G18 -> -580402 | H58: =-H18 -> -580402 | I58: =-I18 -> -580402 | J58: =-J18 -> -580402 | K58: =-K18 -> -580402 | ... W58: =-W18 -> -580402
B59: Outflow : 返還借款
B60: Outflow : 利息費用 | C60: -
B61: Outflow : 維運費 | C61: - | D61: =-D23 -> -348880 | E61: =-E23 -> -348880 | F61: =-F23 -> -348880 | G61: =-G23 -> -348880 | H61: =-H23 -> -348880 | I61: =-I23 -> -348880 | J61: =-J23 -> -348880 | K61: =-K23 -> -348880 | ... W61: =-W23 -> -348880
B62: Outflow : 保險費 | C62: - | D62: =-D28 -> -83731 | E62: =-E28 -> -83731 | F62: =-F28 -> -83731 | G62: =-G28 -> -83731 | H62: =-H28 -> -83731 | I62: =-I28 -> -83731 | J62: =-J28 -> -83731 | K62: =-K28 -> -83731 | ... W62: =-W28 -> -83731
B63: Outflow : 模組回收費 | D63: =-D33 -> -87220 | E63: =-E33 -> -87220 | F63: =-F33 -> -87220 | G63: =-G33 -> -87220 | H63: =-H33 -> -87220 | I63: =-I33 -> -87220 | J63: =-J33 -> -87220 | K63: =-K33 -> -87220 | ... W63: =-W33 -> 0
B64: Outflow : 其它費用(人事薪資…等)
B65: 1%管理費
B66: 績效獎金
B67: 所得稅20% | D67: =-D90 -> 220046.6 | E67: =-E90 -> 220046.6 | F67: =-F90 -> 220046.6 | G67: =-G90 -> 220046.6 | H67: =-H90 -> 220046.6 | I67: =-I90 -> 220046.6 | J67: =-J90 -> 220046.6 | K67: =-K90 -> 220046.6 | ... W67: =-W90 -> 202602.6
B68: 現金流 | C68: =C57 -> 0 | D68: =SUM(D54:D67) -> -880186.4 | E68: =SUM(E54:E67) -> -880186.4 | F68: =SUM(F54:F67) -> -880186.4 | G68: =SUM(G54:G67) -> -880186.4 | H68: =SUM(H54:H67) -> -880186.4 | I68: =SUM(I54:I67) -> -880186.4 | J68: =SUM(J54:J67) -> -880186.4 | K68: =SUM(K54:K67) -> -880186.4 | ... W68: =SUM(W54:W67) -> -810410.4
B69: 累計現金流 | D69: =C55+D55 -> #VALUE! | E69: =D56+E55 -> 0 | F69: =E56+F55 -> 0 | G69: =F56+G55 -> #VALUE! | H69: =G56+H55 -> #VALUE! | I69: =H56+I55 -> #VALUE! | J69: =I56+J55 -> #VALUE! | K69: =J56+K55 -> #VALUE! | L69: =K56+L55 -> #VALUE! | ... W69: =V56+W55 -> #VALUE!
B70: 回收年限評估 | D70: =IF((D56)>0,"回收","未回收") -> 未回收 | E70: =IF((E56)>0,"回收","未回收") -> 未回收 | F70: =IF((F56)>0,"回收","未回收") -> 未回收 | G70: =IF((G56)>0,"回收","未回收") -> 未回收 | H70: =IF((H56)>0,"回收","未回收") -> 未回收 | I70: =IF((I56)>0,"回收","未回收") -> 未回收 | J70: =IF((J56)>0,"回收","未回收") -> 未回收 | K70: =IF((K56)>0,"回收","未回收") -> 未回收 | ... W70: =IF((W56)>0,"回收","未回收") -> 未回收
B71: 專案法IRR | C71: =IRR(C68:W68) -> #N/A
C73: 年份 | D73: 2020 | E73: 2021 | F73: 2022 | G73: 2023 | H73: 2024 | I73: 2025 | J73: 2026 | K73: 2027 | L73: 2028 | M73: 2029 | N73: 2030 | O73: 2031 | P73: 2032 | Q73: 2033 | R73: 2034 | S73: 2035 | T73: 2036 | U73: 2037 | V73: 2038 | W73: 2039
B74: 0 | T74: 償還年限
B75: (Unit : Currency) | C75: 0 | D75: 1 | E75: 2 | F75: 3 | G75: 4 | H75: 5 | I75: 6 | J75: 7 | K75: 8 | L75: 9 | M75: 10 | N75: 11 | O75: 12 | P75: 13 | Q75: 14 | R75: 15 | S75: 16 | T75: 17 | U75: 18 | V75: 19 | W75: 20
B76: 發電度數(KWH) | C76: 0 | D76: =D8 -> 0 | E76: =E8 -> 0 | F76: =F8 -> 0 | G76: =G8 -> 0 | H76: =H8 -> 0 | I76: =I8 -> 0 | J76: =J8 -> 0 | K76: =K8 -> 0 | ... W76: =W8 -> 0
B77: Inflow : 電費收入 | C77: - | D77: =D13 -> 0 | E77: =E13 -> 0 | F77: =F13 -> 0 | G77: =G13 -> 0 | H77: =H13 -> 0 | I77: =I13 -> 0 | J77: =J13 -> 0 | K77: =K13 -> 0 | ... W77: =W13 -> 0
B78: Inflow : 政府補助 | C78: - | G78: - | H78: - | I78: - | J78: - | K78: - | L78: - | M78: - | N78: - | O78: - | P78: - | Q78: - | R78: - | S78: - | T78: - | U78: - | V78: - | W78: -
B79: Inflow : 銀行借款
B80: Outflow : 設備折舊 | D80: =-D43 -> 0 | E80: =-E43 -> 0 | F80: =-F43 -> 0 | G80: =-G43 -> 0 | H80: =-H43 -> 0 | I80: =-I43 -> 0 | J80: =-J43 -> 0 | K80: =-K43 -> 0 | ... W80: =-W43 -> 0
B81: Outflow : 設備放置區域租金 | C81: - | D81: =-D18 -> -580402 | E81: =-E18 -> -580402 | F81: =-F18 -> -580402 | G81: =-G18 -> -580402 | H81: =-H18 -> -580402 | I81: =-I18 -> -580402 | J81: =-J18 -> -580402 | K81: =-K18 -> -580402 | ... W81: =-W18 -> -580402
B82: Outflow : 返還借款
B83: Outflow : 利息費用 | C83: - | D83: =-D121*C49/100 -> 0 | E83: =-E121*C49/100 -> 0 | F83: =-F121*C49/100 -> 0 | G83: =-G121*C49/100 -> 0 | H83: =-H121*C49/100 -> 0 | I83: =-I121*C49/100 -> 0 | J83: =-J121*C49/100 -> 0 | K83: =-K121*C49/100 -> 0 | L83: =-L121*C49/100 -> 0 | M83: =-M121*C49/100 -> 0 | N83: =-N121*C49/100 -> 0 | O83: =-O121*C49/100 -> 0 | P83: =-P121*C49/100 -> 0 | Q83: =-Q121*C49/100 -> 0 | R83: =-R121*C49/100 -> 0 | S83: =-S121*C49/100 -> 0 | T83: =-T121*C49/100 -> 0 | U83: =-U121*C49/100 -> 0 | V83: =-V121*C49/100 -> 0 | W83: =-W121*C49/100 -> 0
B84: Outflow : 維運費 | C84: - | D84: =-D23 -> -348880 | E84: =-E23 -> -348880 | F84: =-F23 -> -348880 | G84: =-G23 -> -348880 | H84: =-H23 -> -348880 | I84: =-I23 -> -348880 | J84: =-J23 -> -348880 | K84: =-K23 -> -348880 | ... W84: =-W23 -> -348880
B85: Outflow : 保險費 | C85: - | D85: =-D28 -> -83731 | E85: =-E28 -> -83731 | F85: =-F28 -> -83731 | G85: =-G28 -> -83731 | H85: =-H28 -> -83731 | I85: =-I28 -> -83731 | J85: =-J28 -> -83731 | K85: =-K28 -> -83731 | ... W85: =-W28 -> -83731
B86: Outflow : 模組回收費 | D86: =-D33 -> -87220 | E86: =-E33 -> -87220 | F86: =-F33 -> -87220 | G86: =-G33 -> -87220 | H86: =-H33 -> -87220 | I86: =-I33 -> -87220 | J86: =-J33 -> -87220 | K86: =-K33 -> -87220 | ... W86: =-W33 -> 0
B87: Outflow : 其它費用(人事薪資…等)
B88: 1%管理費
B89: 稅前淨利 | D89: =SUM(D77:D88) -> -1100233 | E89: =SUM(E77:E88) -> -1100233 | F89: =SUM(F77:F88) -> -1100233 | G89: =SUM(G77:G88) -> -1100233 | H89: =SUM(H77:H88) -> -1100233 | I89: =SUM(I77:I88) -> -1100233 | J89: =SUM(J77:J88) -> -1100233 | K89: =SUM(K77:K88) -> -1100233 | ... W89: =SUM(W77:W88) -> -1013013
B90: 所得稅20% | D90: =D89*0.2 -> -220046.6 | E90: =E89*0.2 -> -220046.6 | F90: =F89*0.2 -> -220046.6 | G90: =G89*0.2 -> -220046.6 | H90: =H89*0.2 -> -220046.6 | I90: =I89*0.2 -> -220046.6 | J90: =J89*0.2 -> -220046.6 | K90: =K89*0.2 -> -220046.6 | ... W90: =W89*0.2 -> -202602.6
B91: 稅後淨利 | D91: =D89-D90 -> -880186.4 | E91: =E89-E90 -> -880186.4 | F91: =F89-F90 -> -880186.4 | G91: =G89-G90 -> -880186.4 | H91: =H89-H90 -> -880186.4 | I91: =I89-I90 -> -880186.4 | J91: =J89-J90 -> -880186.4 | K91: =K89-K90 -> -880186.4 | ... W91: =W89-W90 -> -810410.4
B92: 累計現金流
B93: 回收年限評估
C94: 年份 | D94: 2020 | E94: 2021 | F94: 2022 | G94: 2023 | H94: 2024 | I94: 2025 | J94: 2026 | K94: 2027 | L94: 2028 | M94: 2029 | N94: 2030 | O94: 2031 | P94: 2032 | Q94: 2033 | R94: 2034 | S94: 2035 | T94: 2036 | U94: 2037 | V94: 2038 | W94: 2039
B96: (Unit : Currency) | C96: 0 | D96: 1 | E96: 2 | F96: 3 | G96: 4 | H96: 5 | I96: 6 | J96: 7 | K96: 8 | L96: 9 | M96: 10 | N96: 11 | O96: 12 | P96: 13 | Q96: 14 | R96: 15 | S96: 16 | T96: 17 | U96: 18 | V96: 19 | W96: 20
B97: 稅後淨利 | D97: =D91 -> -880186.4 | E97: =E91 -> -880186.4 | F97: =F91 -> -880186.4 | G97: =G91 -> -880186.4 | H97: =H91 -> -880186.4 | I97: =I91 -> -880186.4 | J97: =J91 -> -880186.4 | K97: =K91 -> -880186.4 | ... W97: =W91 -> -810410.4
B98: 設備折舊 | D98: =D43 -> 0 | E98: =E43 -> 0 | F98: =F43 -> 0 | G98: =G43 -> 0 | H98: =H43 -> 0 | I98: =I43 -> 0 | J98: =J43 -> 0 | K98: =K43 -> 0 | ... W98: =W43 -> 0
B99: 營運活動現金流量 | D99: =D97+D98 -> -880186.4 | E99: =E97+E98 -> -880186.4 | F99: =F97+F98 -> -880186.4 | G99: =G97+G98 -> -880186.4 | H99: =H97+H98 -> -880186.4 | I99: =I97+I98 -> -880186.4 | J99: =J97+J98 -> -880186.4 | K99: =K97+K98 -> -880186.4 | ... W99: =W97+W98 -> -810410.4
B101: 投資活動-設備支出 | D101: =C57 -> 0
B104: 理財活動-借款 | D104: =-D101*C45/100 -> 0
B105: 理財活動-還款 | E105: =-D104/C46 -> 0 | F105: =-D104/C46 -> 0 | G105: =-D104/C46 -> 0 | H105: =-D104/C46 -> 0 | I105: =-D104/C46 -> 0 | J105: =-D104/C46 -> 0 | K105: =-D104/C46 -> 0 | L105: =-D104/C46 -> 0 | M105: =-D104/C46 -> 0 | N105: =-D104/C46 -> 0 | O105: =-D104/C46 -> 0 | P105: =-D104/C46 -> 0 | Q105: =-D104/C46 -> 0 | R105: =-D104/C46 -> 0 | S105: =-D104/C46 -> 0
B106: 理財活動-現金增資 | D106: =-D101*(1-C45/100) -> 0
B107: 現金股利 | E107: =-D97*C47/100 -> 792167.76 | F107: =-E97*C47/100 -> 792167.76 | G107: =-F97*C47/100 -> 792167.76 | H107: =-G97*C47/100 -> 792167.76 | I107: =-H97*C47/100 -> 792167.76 | J107: =-I97*C47/100 -> 792167.76 | K107: =-J97*C47/100 -> 792167.76 | L107: =-K97*C47/100 -> 792167.76 | M107: =-L97*C47/100 -> 792167.76 | N107: =-M97*C47/100 -> 792167.76 | O107: =-N97*C47/100 -> 729369.36 | P107: =-O97*C47/100 -> 729369.36 | Q107: =-P97*C47/100 -> 729369.36 | R107: =-Q97*C47/100 -> 729369.36 | S107: =-R97*C47/100 -> 729369.36 | T107: =-S97*C47/100 -> 729369.36 | U107: =-T97*C47/100 -> 729369.36 | V107: =-U97*C47/100 -> 729369.36 | W107: =-V97*C47/100 -> 729369.36
B108: 年底減資 | T108: =-D106/C48 -> 0 | U108: =-D106/C48 -> 0 | V108: =-D106/C48 -> 0 | W108: =-D106/C48 -> 0
B111: 現金淨流入(出 ) | C111: 0 | D111: =SUM(D99:D108) -> -880186.4 | E111: =SUM(E99:E108) -> -88018.64 | F111: =SUM(F99:F108) -> -88018.64 | G111: =SUM(G99:G108) -> -88018.64 | H111: =SUM(H99:H108) -> -88018.64 | I111: =SUM(I99:I108) -> -88018.64 | J111: =SUM(J99:J108) -> -88018.64 | K111: =SUM(K99:K108) -> -88018.64 | ... W111: =SUM(W99:W108) -> -81041.04
...

Sheet 淡江大學_p2
A1: 電站基本資料(請填寫著色處) | E1: 說明 | O1: =1-C11 -> 0.99 | P1: =O1-$C12 -> 0.986 | Q1: =P1-$C12 -> 0.982 | R1: =Q1-$C12 -> 0.978 | S1: =R1-$C12 -> 0.974 | T1: =S1-$C12 -> 0.97 | U1: =T1-$C12 -> 0.966 | V1: =U1-$C12 -> 0.962 | W1: =V1-$C12 -> 0.958 | ... AH1: =AG1-$C12 -> 0.914
A2: 電站名稱 | B2: 淡江大學 | C2: 淡江大學 | D2: - | E2: 填入本案場名稱
A3: 電站壽命 | B3: 20 | C3: 20 | D3: - | E3: 預設 20 年，代表財務評估年期。若合約年限不同可依實際情況修改
A4: 建置量(kWp) | B4: 436.1 | C4: 436.1 | D4: - | E4: 填入裝置容量（kWp），通常由設計圖面或報價書取得 | M4: 情境編號: 2
A5: 起始年度 | B5: 2020 | C5: 2020 | D5: =B5+B3-1 -> 2039 | E5: 2039 | M5: 第1次滾算摘要
M6: 價金: 33000
A7: 綜合損益表(請填寫著色處) | M7: 專案IRR: 2.97
A8: 收入 | M8: 權益法IRR: 5.57
A9: 收支項目 | B9: 相關參數 | C9: 參數數值 | D9: 年限 | E9: 說明 | M9: 利潤率: 30.00%
A10: 電費收入 | B10: 年度AC併網總發電量 | C10: 547002 | D10: 547002 | E10: 20 | M10: 第1次滾算，減少 2000 元 - 現金模式，每次減少 2000 元
B11: 首年衰退率 | C11: 0.01 | E11: 第一年發電衰退比率，請填小數（例：1% → 填 0.01）。一般首年衰退約 1~2%(請參考模組規格書)
B12: 次年衰退率 | C12: 0.004 | E12: 第二年起每年固定衰退比率，請填小數（例：0.4% → 填 0.004）。一般約 0.4~0.7%(請參考模組規格書)
B13: 躉售費率(FIT) / 綠電費率 | C13: 4 | E13: 與台電簽訂的躉購費率或綠電合約費率，單位：元/度。請參考台電公告或合約內容
A14: 支出(請填寫著色處)
A15: 收支項目 | B15: 相關參數 | C15: 參數數值 | D15: 攤提年限 | E15: 說明
A16: 設備費用(價金) | B16: 每kWp設備成本 | C16: 35000 | D16: 33000 | E16: 20
B17: 信邦利潤率(ex:20%填0.2) | C17: 0.3 | E17: 公司在設備費用上加計的利潤比率，請填小數（例：20% → 填 0.2）
B18: 開發費 | C18: 2000 | E18: 前期開發費用（元），含可行性評估、申請規費、地主溝通等。若無則填 0
A19: 租金費用 | B19: 租金計算方式 | C19: 1 | D19: 1 | E19: 0
B20: 【方式1參數】每年相同價格 | C20: 290201 | D20: 290201 | E20: 20
B21: 【方式2參數】抽成比率 | D21: 0 | E21: 0
A22: 運維費用 | B22: 每kw運維成本 | C22: 400 | D22: 400 | E22: 20
A23: 保險費用 | B23: 占整體設備費用比例 | C23: 0.003 | D23: 0.003 | E23: 20
A24: 模組回收費用 | B24: 每kw模組回收成本 | C24: 1000 | D24: 1000 | E24: 10
A25: 利息費用 | B25: 銀行利率 | C25: 0.0256 | D25: 0.0256 | E25: 0
A26: 所得稅 | B26: 所得稅率 | C26: 0.2 | D26: 0.2 | E26: 0
A29: 現金流量表(請填寫著色處)
A30: 金流項目 | B30: 相關參數 | C30: 參數數值 | E30: 說明
A31: 貸款成數 | B31: 占總設備費用比例 | C31: 0.8 | D31: 0.8 | E31: 貸款佔設備總費用比例，填小數（例：80% → 填 0.8）。預設 0.8 代表貸八成、自備二成
A32: 貸款還款 | B32: 攤還期數 | C32: 15 | D32: 15 | E32: 貸款還款年數（年）。預設 15 年，代表分 15 年平均攤還本金
A33: 現金股利 | B33: 股利比率 | C33: 0.9 | D33: 0.9 | E33: 稅後現金流中分配給股東的比例，填小數（例：90% → 填 0.9）
A34: 年底減資 | B34: 攤還期數 | C34: 4 | D34: 4 | E34: 年底減資返還股東的年數。預設 4 年，代表 倒數 4 年進行減資，加速資金返還
D37: 2020 | E37: 2021 | F37: 2022 | G37: 2023 | H37: 2024 | I37: 2025 | J37: 2026 | K37: 2027 | L37: 2028 | M37: 2029 | N37: 2030 | O37: 2031 | P37: 2032 | Q37: 2033 | R37: 2034 | S37: 2035 | T37: 2036 | U37: 2037 | V37: 2038 | W37: 2039
D45: -290201 | E45: -290201 | F45: -290201 | G45: -290201 | H45: -290201 | I45: -290201 | J45: -290201 | K45: -290201 | L45: -290201 | M45: -290201 | N45: -290201 | O45: -290201 | P45: -290201 | Q45: -290201 | R45: -290201 | S45: -290201 | T45: -290201 | U45: -290201 | V45: -290201 | W45: -290201
D48: -174440 | E48: -174440 | F48: -174440 | G48: -174440 | H48: -174440 | I48: -174440 | J48: -174440 | K48: -174440 | L48: -174440 | M48: -174440 | N48: -174440 | O48: -174440 | P48: -174440 | Q48: -174440 | R48: -174440 | S48: -174440 | T48: -174440 | U48: -174440 | V48: -174440 | W48: -174440
D49: -43173.9 | E49: -43173.9 | F49: -43173.9 | G49: -43173.9 | H49: -43173.9 | I49: -43173.9 | J49: -43173.9 | K49: -43173.9 | L49: -43173.9 | M49: -43173.9 | N49: -43173.9 | O49: -43173.9 | P49: -43173.9 | Q49: -43173.9 | R49: -43173.9 | S49: -43173.9 | T49: -43173.9 | U49: -43173.9 | V49: -43173.9 | W49: -43173.9
D50: -43610 | E50: -43610 | F50: -43610 | G50: -43610 | H50: -43610 | I50: -43610 | J50: -43610 | K50: -43610 | L50: -43610 | M50: -43610 | N50: 0 | O50: 0 | P50: 0 | Q50: 0 | R50: 0 | S50: 0 | T50: 0 | U50: 0 | V50: 0 | W50: 0
D54: =D77 -> 0 | E54: =E77 -> 0 | F54: =F77 -> 0 | G54: =G77 -> 0 | H54: =H77 -> 0 | I54: =I77 -> 0 | J54: =J77 -> 0 | K54: =K77 -> 0 | ... W54: =W77 -> 0
D70: 0 | E70: 0 | F70: 0 | G70: 0 | H70: 0 | I70: 0 | J70: 0 | K70: 0 | L70: 0 | M70: 0 | N70: 0 | O70: 0 | P70: 0 | Q70: 0 | R70: 0 | S70: 0 | T70: 0 | U70: 0 | V70: 0 | W70: 0

Sheet 淡江大學_p3
A1: 電站基本資料(請填寫著色處) | E1: 說明 | O1: =1-C11 -> 0.99 | P1: =O1-$C12 -> 0.986 | Q1: =P1-$C12 -> 0.982 | R1: =Q1-$C12 -> 0.978 | S1: =R1-$C12 -> 0.974 | T1: =S1-$C12 -> 0.97 | U1: =T1-$C12 -> 0.966 | V1: =U1-$C12 -> 0.962 | W1: =V1-$C12 -> 0.958 | ... AH1: =AG1-$C12 -> 0.914
A2: 電站名稱 | B2: 淡江大學 | C2: 淡江大學 | D2: - | E2: 填入本案場名稱
A3: 電站壽命 | B3: 20 | C3: 20 | D3: - | E3: 預設 20 年，代表財務評估年期。若合約年限不同可依實際情況修改
A4: 建置量(kWp) | B4: 436.1 | C4: 436.1 | D4: - | E4: 填入裝置容量（kWp），通常由設計圖面或報價書取得 | M4: 情境編號: 3
A5: 起始年度 | B5: 2020 | C5: 2020 | D5: =B5+B3-1 -> 2039 | E5: 2039 | M5: 第2次滾算摘要
M6: 價金: 31000
A7: 綜合損益表(請填寫著色處) | M7: 專案IRR: 3.54
A8: 收入 | M8: 權益法IRR: 7.49
A9: 收支項目 | B9: 相關參數 | C9: 參數數值 | D9: 年限 | E9: 說明 | M9: 利潤率: 30.00%
A10: 電費收入 | B10: 年度AC併網總發電量 | C10: 547002 | D10: 547002 | E10: 20 | M10: 第2次滾算，減少 2000 元 - 現金模式，每次減少 2000 元
B11: 首年衰退率 | C11: 0.01 | E11: 第一年發電衰退比率，請填小數（例：1% → 填 0.01）。一般首年衰退約 1~2%(請參考模組規格書)
B12: 次年衰退率 | C12: 0.004 | E12: 第二年起每年固定衰退比率，請填小數（例：0.4% → 填 0.004）。一般約 0.4~0.7%(請參考模組規格書)
B13: 躉售費率(FIT) / 綠電費率 | C13: 4 | E13: 與台電簽訂的躉購費率或綠電合約費率，單位：元/度。請參考台電公告或合約內容
A14: 支出(請填寫著色處)
A15: 收支項目 | B15: 相關參數 | C15: 參數數值 | D15: 攤提年限 | E15: 說明
A16: 設備費用(價金) | B16: 每kWp設備成本 | C16: 35000 | D16: 31000 | E16: 20
B17: 信邦利潤率(ex:20%填0.2) | C17: 0.3 | E17: 公司在設備費用上加計的利潤比率，請填小數（例：20% → 填 0.2）
B18: 開發費 | C18: 2000 | E18: 前期開發費用（元），含可行性評估、申請規費、地主溝通等。若無則填 0
A19: 租金費用 | B19: 租金計算方式 | C19: 1 | D19: 1 | E19: 0
B20: 【方式1參數】每年相同價格 | C20: 290201 | D20: 290201 | E20: 20
B21: 【方式2參數】抽成比率 | D21: 0 | E21: 0
A22: 運維費用 | B22: 每kw運維成本 | C22: 400 | D22: 400 | E22: 20
A23: 保險費用 | B23: 占整體設備費用比例 | C23: 0.003 | D23: 0.003 | E23: 20
A24: 模組回收費用 | B24: 每kw模組回收成本 | C24: 1000 | D24: 1000 | E24: 10
A25: 利息費用 | B25: 銀行利率 | C25: 0.0256 | D25: 0.0256 | E25: 0
A26: 所得稅 | B26: 所得稅率 | C26: 0.2 | D26: 0.2 | E26: 0
A29: 現金流量表(請填寫著色處)
A30: 金流項目 | B30: 相關參數 | C30: 參數數值 | E30: 說明
A31: 貸款成數 | B31: 占總設備費用比例 | C31: 0.8 | D31: 0.8 | E31: 貸款佔設備總費用比例，填小數（例：80% → 填 0.8）。預設 0.8 代表貸八成、自備二成
A32: 貸款還款 | B32: 攤還期數 | C32: 15 | D32: 15 | E32: 貸款還款年數（年）。預設 15 年，代表分 15 年平均攤還本金
A33: 現金股利 | B33: 股利比率 | C33: 0.9 | D33: 0.9 | E33: 稅後現金流中分配給股東的比例，填小數（例：90% → 填 0.9）
A34: 年底減資 | B34: 攤還期數 | C34: 4 | D34: 4 | E34: 年底減資返還股東的年數。預設 4 年，代表 倒數 4 年進行減資，加速資金返還
D37: 2020 | E37: 2021 | F37: 2022 | G37: 2023 | H37: 2024 | I37: 2025 | J37: 2026 | K37: 2027 | L37: 2028 | M37: 2029 | N37: 2030 | O37: 2031 | P37: 2032 | Q37: 2033 | R37: 2034 | S37: 2035 | T37: 2036 | U37: 2037 | V37: 2038 | W37: 2039
D45: -290201 | E45: -290201 | F45: -290201 | G45: -290201 | H45: -290201 | I45: -290201 | J45: -290201 | K45: -290201 | L45: -290201 | M45: -290201 | N45: -290201 | O45: -290201 | P45: -290201 | Q45: -290201 | R45: -290201 | S45: -290201 | T45: -290201 | U45: -290201 | V45: -290201 | W45: -290201
D48: -174440 | E48: -174440 | F48: -174440 | G48: -174440 | H48: -174440 | I48: -174440 | J48: -174440 | K48: -174440 | L48: -174440 | M48: -174440 | N48: -174440 | O48: -174440 | P48: -174440 | Q48: -174440 | R48: -174440 | S48: -174440 | T48: -174440 | U48: -174440 | V48: -174440 | W48: -174440
D49: -40557.3 | E49: -40557.3 | F49: -40557.3 | G49: -40557.3 | H49: -40557.3 | I49: -40557.3 | J49: -40557.3 | K49: -40557.3 | L49: -40557.3 | M49: -40557.3 | N49: -40557.3 | O49: -40557.3 | P49: -40557.3 | Q49: -40557.3 | R49: -40557.3 | S49: -40557.3 | T49: -40557.3 | U49: -40557.3 | V49: -40557.3 | W49: -40557.3
D50: -43610 | E50: -43610 | F50: -43610 | G50: -43610 | H50: -43610 | I50: -43610 | J50: -43610 | K50: -43610 | L50: -43610 | M50: -43610 | N50: 0 | O50: 0 | P50: 0 | Q50: 0 | R50: 0 | S50: 0 | T50: 0 | U50: 0 | V50: 0 | W50: 0
D54: =D77 -> 0 | E54: =E77 -> 0 | F54: =F77 -> 0 | G54: =G77 -> 0 | H54: =H77 -> 0 | I54: =I77 -> 0 | J54: =J77 -> 0 | K54: =K77 -> 0 | ... W54: =W77 -> 0
D70: 0 | E70: 0 | F70: 0 | G70: 0 | H70: 0 | I70: 0 | J70: 0 | K70: 0 | L70: 0 | M70: 0 | N70: 0 | O70: 0 | P70: 0 | Q70: 0 | R70: 0 | S70: 0 | T70: 0 | U70: 0 | V70: 0 | W70: 0
