Workbook

Sheet 多站彙整
C4: 年份 | D4: 2020 | E4: 2021 | F4: 2022 | G4: 2023 | H4: 2024 | I4: 2025 | J4: 2026 | K4: 2027 | L4: 2028 | M4: 2029 | N4: 2030 | O4: 2031 | P4: 2032 | Q4: 2033 | R4: 2034 | S4: 2035 | T4: 2036 | U4: 2037 | V4: 2038 | W4: 2039
C5: 預估發電度數
B6: 淡江大學 | D6: =ROUND(ABS(淡江大學_p6_1!D40),0) -> 0 | E6: =ROUND(ABS(淡江大學_p6_1!E40),0) -> 0 | F6: =ROUND(ABS(淡江大學_p6_1!F40),0) -> 0 | G6: =ROUND(ABS(淡江大學_p6_1!G40),0) -> 0 | H6: =ROUND(ABS(淡江大學_p6_1!H40),0) -> 0 | I6: =ROUND(ABS(淡江大學_p6_1!I40),0) -> 0 | J6: =ROUND(ABS(淡江大學_p6_1!J40),0) -> 0 | K6: =ROUND(ABS(淡江大學_p6_1!K40),0) -> 0 | ... W6: =ROUND(ABS(淡江大學_p6_1!W40),0) -> 0
B7: 淡江大學 | D7: =ROUND(ABS(淡江大學_p4_2!D40),0) -> 0 | E7: =ROUND(ABS(淡江大學_p4_2!E40),0) -> 0 | F7: =ROUND(ABS(淡江大學_p4_2!F40),0) -> 0 | G7: =ROUND(ABS(淡江大學_p4_2!G40),0) -> 0 | H7: =ROUND(ABS(淡江大學_p4_2!H40),0) -> 0 | I7: =ROUND(ABS(淡江大學_p4_2!I40),0) -> 0 | J7: =ROUND(ABS(淡江大學_p4_2!J40),0) -> 0 | K7: =ROUND(ABS(淡江大學_p4_2!K40),0) -> 0 | ... W7: =ROUND(ABS(淡江大學_p4_2!W40),0) -> 0
B8: 淡江大學 | D8: =ROUND(ABS(淡江大學_p4_1!D40),0) -> 0 | E8: =ROUND(ABS(淡江大學_p4_1!E40),0) -> 0 | F8: =ROUND(ABS(淡江大學_p4_1!F40),0) -> 0 | G8: =ROUND(ABS(淡江大學_p4_1!G40),0) -> 0 | H8: =ROUND(ABS(淡江大學_p4_1!H40),0) -> 0 | I8: =ROUND(ABS(淡江大學_p4_1!I40),0) -> 0 | J8: =ROUND(ABS(淡江大學_p4_1!J40),0) -> 0 | K8: =ROUND(ABS(淡江大學_p4_1!K40),0) -> 0 | ... W8: =ROUND(ABS(淡江大學_p4_1!W40),0) -> 0
B9: 淡江大學 | D9: =ROUND(ABS(淡江大學_p4!D40),0) -> 0 | E9: =ROUND(ABS(淡江大學_p4!E40),0) -> 0 | F9: =ROUND(ABS(淡江大學_p4!F40),0) -> 0 | G9: =ROUND(ABS(淡江大學_p4!G40),0) -> 0 | H9: =ROUND(ABS(淡江大學_p4!H40),0) -> 0 | I9: =ROUND(ABS(淡江大學_p4!I40),0) -> 0 | J9: =ROUND(ABS(淡江大學_p4!J40),0) -> 0 | K9: =ROUND(ABS(淡江大學_p4!K40),0) -> 0 | ... W9: =ROUND(ABS(淡江大學_p4!W40),0) -> 0
B10: 淡江大學 | D10: =ROUND(ABS(淡江大學_p6!D40),0) -> 0 | E10: =ROUND(ABS(淡江大學_p6!E40),0) -> 0 | F10: =ROUND(ABS(淡江大學_p6!F40),0) -> 0 | G10: =ROUND(ABS(淡江大學_p6!G40),0) -> 0 | H10: =ROUND(ABS(淡江大學_p6!H40),0) -> 0 | I10: =ROUND(ABS(淡江大學_p6!I40),0) -> 0 | J10: =ROUND(ABS(淡江大學_p6!J40),0) -> 0 | K10: =ROUND(ABS(淡江大學_p6!K40),0) -> 0 | ... W10: =ROUND(ABS(淡江大學_p6!W40),0) -> 0
B11: 淡江大學 | D11: =ROUND(ABS(淡江大學_p3!D40),0) -> 0 | E11: =ROUND(ABS(淡江大學_p3!E40),0) -> 0 | F11: =ROUND(ABS(淡江大學_p3!F40),0) -> 0 | G11: =ROUND(ABS(淡江大學_p3!G40),0) -> 0 | H11: =ROUND(ABS(淡江大學_p3!H40),0) -> 0 | I11: =ROUND(ABS(淡江大學_p3!I40),0) -> 0 | J11: =ROUND(ABS(淡江大學_p3!J40),0) -> 0 | K11: =ROUND(ABS(淡江大學_p3!K40),0) -> 0 | ... W11: =ROUND(ABS(淡江大學_p3!W40),0) -> 0
B12: 淡江大學 | D12: =ROUND(ABS(淡江大學_p4_3!D40),0) -> 541532 | E12: =ROUND(ABS(淡江大學_p4_3!E40),0) -> 539344 | F12: =ROUND(ABS(淡江大學_p4_3!F40),0) -> 537156 | G12: =ROUND(ABS(淡江大學_p4_3!G40),0) -> 534968 | H12: =ROUND(ABS(淡江大學_p4_3!H40),0) -> 532780 | I12: =ROUND(ABS(淡江大學_p4_3!I40),0) -> 530592 | J12: =ROUND(ABS(淡江大學_p4_3!J40),0) -> 528404 | K12: =ROUND(ABS(淡江大學_p4_3!K40),0) -> 526216 | ... W12: =ROUND(ABS(淡江大學_p4_3!W40),0) -> 499960
B13: 淡江大學 | D13: =ROUND(ABS(淡江大學_p3_1!D40),0) -> 541532 | E13: =ROUND(ABS(淡江大學_p3_1!E40),0) -> 539344 | F13: =ROUND(ABS(淡江大學_p3_1!F40),0) -> 537156 | G13: =ROUND(ABS(淡江大學_p3_1!G40),0) -> 534968 | H13: =ROUND(ABS(淡江大學_p3_1!H40),0) -> 532780 | I13: =ROUND(ABS(淡江大學_p3_1!I40),0) -> 530592 | J13: =ROUND(ABS(淡江大學_p3_1!J40),0) -> 528404 | K13: =ROUND(ABS(淡江大學_p3_1!K40),0) -> 526216 | ... W13: =ROUND(ABS(淡江大學_p3_1!W40),0) -> 499960
B14: 淡江大學 | D14: =ROUND(ABS(淡江大學_p5!D40),0) -> 541532 | E14: =ROUND(ABS(淡江大學_p5!E40),0) -> 539344 | F14: =ROUND(ABS(淡江大學_p5!F40),0) -> 537156 | G14: =ROUND(ABS(淡江大學_p5!G40),0) -> 534968 | H14: =ROUND(ABS(淡江大學_p5!H40),0) -> 532780 | I14: =ROUND(ABS(淡江大學_p5!I40),0) -> 530592 | J14: =ROUND(ABS(淡江大學_p5!J40),0) -> 528404 | K14: =ROUND(ABS(淡江大學_p5!K40),0) -> 526216 | ... W14: =ROUND(ABS(淡江大學_p5!W40),0) -> 499960
C15: 預估發電度數/年總計 | D15: =SUM(D6:D14) -> 1624596 | E15: =SUM(E6:E14) -> 1618032 | F15: =SUM(F6:F14) -> 1611468 | G15: =SUM(G6:G14) -> 1604904 | H15: =SUM(H6:H14) -> 1598340 | I15: =SUM(I6:I14) -> 1591776 | J15: =SUM(J6:J14) -> 1585212 | K15: =SUM(K6:K14) -> 1578648 | ... W15: =SUM(W6:W14) -> 1499880
C16: 年份 | D16: 2020 | E16: 2021 | F16: 2022 | G16: 2023 | H16: 2024 | I16: 2025 | J16: 2026 | K16: 2027 | L16: 2028 | M16: 2029 | N16: 2030 | O16: 2031 | P16: 2032 | Q16: 2033 | R16: 2034 | S16: 2035 | T16: 2036 | U16: 2037 | V16: 2038 | W16: 2039
C17: 預估收入
B18: 淡江大學 | D18: =ROUND(ABS(淡江大學_p6_1!D41),0) -> 0 | E18: =ROUND(ABS(淡江大學_p6_1!E41),0) -> 0 | F18: =ROUND(ABS(淡江大學_p6_1!F41),0) -> 0 | G18: =ROUND(ABS(淡江大學_p6_1!G41),0) -> 0 | H18: =ROUND(ABS(淡江大學_p6_1!H41),0) -> 0 | I18: =ROUND(ABS(淡江大學_p6_1!I41),0) -> 0 | J18: =ROUND(ABS(淡江大學_p6_1!J41),0) -> 0 | K18: =ROUND(ABS(淡江大學_p6_1!K41),0) -> 0 | ... W18: =ROUND(ABS(淡江大學_p6_1!W41),0) -> 0
B19: 淡江大學 | D19: =ROUND(ABS(淡江大學_p4_2!D41),0) -> 0 | E19: =ROUND(ABS(淡江大學_p4_2!E41),0) -> 0 | F19: =ROUND(ABS(淡江大學_p4_2!F41),0) -> 0 | G19: =ROUND(ABS(淡江大學_p4_2!G41),0) -> 0 | H19: =ROUND(ABS(淡江大學_p4_2!H41),0) -> 0 | I19: =ROUND(ABS(淡江大學_p4_2!I41),0) -> 0 | J19: =ROUND(ABS(淡江大學_p4_2!J41),0) -> 0 | K19: =ROUND(ABS(淡江大學_p4_2!K41),0) -> 0 | ... W19: =ROUND(ABS(淡江大學_p4_2!W41),0) -> 0
B20: 淡江大學 | D20: =ROUND(ABS(淡江大學_p4_1!D41),0) -> 0 | E20: =ROUND(ABS(淡江大學_p4_1!E41),0) -> 0 | F20: =ROUND(ABS(淡江大學_p4_1!F41),0) -> 0 | G20: =ROUND(ABS(淡江大學_p4_1!G41),0) -> 0 | H20: =ROUND(ABS(淡江大學_p4_1!H41),0) -> 0 | I20: =ROUND(ABS(淡江大學_p4_1!I41),0) -> 0 | J20: =ROUND(ABS(淡江大學_p4_1!J41),0) -> 0 | K20: =ROUND(ABS(淡江大學_p4_1!K41),0) -> 0 | ... W20: =ROUND(ABS(淡江大學_p4_1!W41),0) -> 0
B21: 淡江大學 | D21: =ROUND(ABS(淡江大學_p4!D41),0) -> 0 | E21: =ROUND(ABS(淡江大學_p4!E41),0) -> 0 | F21: =ROUND(ABS(淡江大學_p4!F41),0) -> 0 | G21: =ROUND(ABS(淡江大學_p4!G41),0) -> 0 | H21: =ROUND(ABS(淡江大學_p4!H41),0) -> 0 | I21: =ROUND(ABS(淡江大學_p4!I41),0) -> 0 | J21: =ROUND(ABS(淡江大學_p4!J41),0) -> 0 | K21: =ROUND(ABS(淡江大學_p4!K41),0) -> 0 | ... W21: =ROUND(ABS(淡江大學_p4!W41),0) -> 0
B22: 淡江大學 | D22: =ROUND(ABS(淡江大學_p6!D41),0) -> 0 | E22: =ROUND(ABS(淡江大學_p6!E41),0) -> 0 | F22: =ROUND(ABS(淡江大學_p6!F41),0) -> 0 | G22: =ROUND(ABS(淡江大學_p6!G41),0) -> 0 | H22: =ROUND(ABS(淡江大學_p6!H41),0) -> 0 | I22: =ROUND(ABS(淡江大學_p6!I41),0) -> 0 | J22: =ROUND(ABS(淡江大學_p6!J41),0) -> 0 | K22: =ROUND(ABS(淡江大學_p6!K41),0) -> 0 | ... W22: =ROUND(ABS(淡江大學_p6!W41),0) -> 0
B23: 淡江大學 | D23: =ROUND(ABS(淡江大學_p3!D41),0) -> 0 | E23: =ROUND(ABS(淡江大學_p3!E41),0) -> 0 | F23: =ROUND(ABS(淡江大學_p3!F41),0) -> 0 | G23: =ROUND(ABS(淡江大學_p3!G41),0) -> 0 | H23: =ROUND(ABS(淡江大學_p3!H41),0) -> 0 | I23: =ROUND(ABS(淡江大學_p3!I41),0) -> 0 | J23: =ROUND(ABS(淡江大學_p3!J41),0) -> 0 | K23: =ROUND(ABS(淡江大學_p3!K41),0) -> 0 | ... W23: =ROUND(ABS(淡江大學_p3!W41),0) -> 0
B24: 淡江大學 | D24: =ROUND(ABS(淡江大學_p4_3!D41),0) -> 2166128 | E24: =ROUND(ABS(淡江大學_p4_3!E41),0) -> 2157376 | F24: =ROUND(ABS(淡江大學_p4_3!F41),0) -> 2148624 | G24: =ROUND(ABS(淡江大學_p4_3!G41),0) -> 2139872 | H24: =ROUND(ABS(淡江大學_p4_3!H41),0) -> 2131120 | I24: =ROUND(ABS(淡江大學_p4_3!I41),0) -> 2122368 | J24: =ROUND(ABS(淡江大學_p4_3!J41),0) -> 2113616 | K24: =ROUND(ABS(淡江大學_p4_3!K41),0) -> 2104864 | ... W24: =ROUND(ABS(淡江大學_p4_3!W41),0) -> 1999839
B25: 淡江大學 | D25: =ROUND(ABS(淡江大學_p3_1!D41),0) -> 2166128 | E25: =ROUND(ABS(淡江大學_p3_1!E41),0) -> 2157376 | F25: =ROUND(ABS(淡江大學_p3_1!F41),0) -> 2148624 | G25: =ROUND(ABS(淡江大學_p3_1!G41),0) -> 2139872 | H25: =ROUND(ABS(淡江大學_p3_1!H41),0) -> 2131120 | I25: =ROUND(ABS(淡江大學_p3_1!I41),0) -> 2122368 | J25: =ROUND(ABS(淡江大學_p3_1!J41),0) -> 2113616 | K25: =ROUND(ABS(淡江大學_p3_1!K41),0) -> 2104864 | ... W25: =ROUND(ABS(淡江大學_p3_1!W41),0) -> 1999839
B26: 淡江大學 | D26: =ROUND(ABS(淡江大學_p5!D41),0) -> 2166128 | E26: =ROUND(ABS(淡江大學_p5!E41),0) -> 2157376 | F26: =ROUND(ABS(淡江大學_p5!F41),0) -> 2148624 | G26: =ROUND(ABS(淡江大學_p5!G41),0) -> 2139872 | H26: =ROUND(ABS(淡江大學_p5!H41),0) -> 2131120 | I26: =ROUND(ABS(淡江大學_p5!I41),0) -> 2122368 | J26: =ROUND(ABS(淡江大學_p5!J41),0) -> 2113616 | K26: =ROUND(ABS(淡江大學_p5!K41),0) -> 2104864 | ... W26: =ROUND(ABS(淡江大學_p5!W41),0) -> 1999839
C27: 預估收入/年總計 | D27: =SUM(D18:D26) -> 6498384 | E27: =SUM(E18:E26) -> 6472128 | F27: =SUM(F18:F26) -> 6445872 | G27: =SUM(G18:G26) -> 6419616 | H27: =SUM(H18:H26) -> 6393360 | I27: =SUM(I18:I26) -> 6367104 | J27: =SUM(J18:J26) -> 6340848 | K27: =SUM(K18:K26) -> 6314592 | ... W27: =SUM(W18:W26) -> 5999517
C28: 年份 | D28: 2020 | E28: 2021 | F28: 2022 | G28: 2023 | H28: 2024 | I28: 2025 | J28: 2026 | K28: 2027 | L28: 2028 | M28: 2029 | N28: 2030 | O28: 2031 | P28: 2032 | Q28: 2033 | R28: 2034 | S28: 2035 | T28: 2036 | U28: 2037 | V28: 2038 | W28: 2039
C29: 租金
B30: 淡江大學 | D30: =ROUND(ABS(淡江大學_p6_1!D45),0) -> 290201 | E30: =ROUND(ABS(淡江大學_p6_1!E45),0) -> 290201 | F30: =ROUND(ABS(淡江大學_p6_1!F45),0) -> 290201 | G30: =ROUND(ABS(淡江大學_p6_1!G45),0) -> 290201 | H30: =ROUND(ABS(淡江大學_p6_1!H45),0) -> 290201 | I30: =ROUND(ABS(淡江大學_p6_1!I45),0) -> 290201 | J30: =ROUND(ABS(淡江大學_p6_1!J45),0) -> 290201 | K30: =ROUND(ABS(淡江大學_p6_1!K45),0) -> 290201 | ... W30: =ROUND(ABS(淡江大學_p6_1!W45),0) -> 290201
B31: 淡江大學 | D31: =ROUND(ABS(淡江大學_p4_2!D45),0) -> 290201 | E31: =ROUND(ABS(淡江大學_p4_2!E45),0) -> 290201 | F31: =ROUND(ABS(淡江大學_p4_2!F45),0) -> 290201 | G31: =ROUND(ABS(淡江大學_p4_2!G45),0) -> 290201 | H31: =ROUND(ABS(淡江大學_p4_2!H45),0) -> 290201 | I31: =ROUND(ABS(淡江大學_p4_2!I45),0) -> 290201 | J31: =ROUND(ABS(淡江大學_p4_2!J45),0) -> 290201 | K31: =ROUND(ABS(淡江大學_p4_2!K45),0) -> 290201 | ... W31: =ROUND(ABS(淡江大學_p4_2!W45),0) -> 290201
B32: 淡江大學 | D32: =ROUND(ABS(淡江大學_p4_1!D45),0) -> 290201 | E32: =ROUND(ABS(淡江大學_p4_1!E45),0) -> 290201 | F32: =ROUND(ABS(淡江大學_p4_1!F45),0) -> 290201 | G32: =ROUND(ABS(淡江大學_p4_1!G45),0) -> 290201 | H32: =ROUND(ABS(淡江大學_p4_1!H45),0) -> 290201 | I32: =ROUND(ABS(淡江大學_p4_1!I45),0) -> 290201 | J32: =ROUND(ABS(淡江大學_p4_1!J45),0) -> 290201 | K32: =ROUND(ABS(淡江大學_p4_1!K45),0) -> 290201 | ... W32: =ROUND(ABS(淡江大學_p4_1!W45),0) -> 290201
B33: 淡江大學 | D33: =ROUND(ABS(淡江大學_p4!D45),0) -> 290201 | E33: =ROUND(ABS(淡江大學_p4!E45),0) -> 290201 | F33: =ROUND(ABS(淡江大學_p4!F45),0) -> 290201 | G33: =ROUND(ABS(淡江大學_p4!G45),0) -> 290201 | H33: =ROUND(ABS(淡江大學_p4!H45),0) -> 290201 | I33: =ROUND(ABS(淡江大學_p4!I45),0) -> 290201 | J33: =ROUND(ABS(淡江大學_p4!J45),0) -> 290201 | K33: =ROUND(ABS(淡江大學_p4!K45),0) -> 290201 | ... W33: =ROUND(ABS(淡江大學_p4!W45),0) -> 290201
B34: 淡江大學 | D34: =ROUND(ABS(淡江大學_p6!D45),0) -> 290201 | E34: =ROUND(ABS(淡江大學_p6!E45),0) -> 290201 | F34: =ROUND(ABS(淡江大學_p6!F45),0) -> 290201 | G34: =ROUND(ABS(淡江大學_p6!G45),0) -> 290201 | H34: =ROUND(ABS(淡江大學_p6!H45),0) -> 290201 | I34: =ROUND(ABS(淡江大學_p6!I45),0) -> 290201 | J34: =ROUND(ABS(淡江大學_p6!J45),0) -> 290201 | K34: =ROUND(ABS(淡江大學_p6!K45),0) -> 290201 | ... W34: =ROUND(ABS(淡江大學_p6!W45),0) -> 290201
B35: 淡江大學 | D35: =ROUND(ABS(淡江大學_p3!D45),0) -> 290201 | E35: =ROUND(ABS(淡江大學_p3!E45),0) -> 290201 | F35: =ROUND(ABS(淡江大學_p3!F45),0) -> 290201 | G35: =ROUND(ABS(淡江大學_p3!G45),0) -> 290201 | H35: =ROUND(ABS(淡江大學_p3!H45),0) -> 290201 | I35: =ROUND(ABS(淡江大學_p3!I45),0) -> 290201 | J35: =ROUND(ABS(淡江大學_p3!J45),0) -> 290201 | K35: =ROUND(ABS(淡江大學_p3!K45),0) -> 290201 | ... W35: =ROUND(ABS(淡江大學_p3!W45),0) -> 290201
B36: 淡江大學 | D36: =ROUND(ABS(淡江大學_p4_3!D45),0) -> 290201 | E36: =ROUND(ABS(淡江大學_p4_3!E45),0) -> 290201 | F36: =ROUND(ABS(淡江大學_p4_3!F45),0) -> 290201 | G36: =ROUND(ABS(淡江大學_p4_3!G45),0) -> 290201 | H36: =ROUND(ABS(淡江大學_p4_3!H45),0) -> 290201 | I36: =ROUND(ABS(淡江大學_p4_3!I45),0) -> 290201 | J36: =ROUND(ABS(淡江大學_p4_3!J45),0) -> 290201 | K36: =ROUND(ABS(淡江大學_p4_3!K45),0) -> 290201 | ... W36: =ROUND(ABS(淡江大學_p4_3!W45),0) -> 290201
B37: 淡江大學 | D37: =ROUND(ABS(淡江大學_p3_1!D45),0) -> 290201 | E37: =ROUND(ABS(淡江大學_p3_1!E45),0) -> 290201 | F37: =ROUND(ABS(淡江大學_p3_1!F45),0) -> 290201 | G37: =ROUND(ABS(淡江大學_p3_1!G45),0) -> 290201 | H37: =ROUND(ABS(淡江大學_p3_1!H45),0) -> 290201 | I37: =ROUND(ABS(淡江大學_p3_1!I45),0) -> 290201 | J37: =ROUND(ABS(淡江大學_p3_1!J45),0) -> 290201 | K37: =ROUND(ABS(淡江大學_p3_1!K45),0) -> 290201 | ... W37: =ROUND(ABS(淡江大學_p3_1!W45),0) -> 290201
B38: 淡江大學 | D38: =ROUND(ABS(淡江大學_p5!D45),0) -> 290201 | E38: =ROUND(ABS(淡江大學_p5!E45),0) -> 290201 | F38: =ROUND(ABS(淡江大學_p5!F45),0) -> 290201 | G38: =ROUND(ABS(淡江大學_p5!G45),0) -> 290201 | H38: =ROUND(ABS(淡江大學_p5!H45),0) -> 290201 | I38: =ROUND(ABS(淡江大學_p5!I45),0) -> 290201 | J38: =ROUND(ABS(淡江大學_p5!J45),0) -> 290201 | K38: =ROUND(ABS(淡江大學_p5!K45),0) -> 290201 | ... W38: =ROUND(ABS(淡江大學_p5!W45),0) -> 290201
C39: 租金/年總計 | D39: =SUM(D30:D38) -> 2611809 | E39: =SUM(E30:E38) -> 2611809 | F39: =SUM(F30:F38) -> 2611809 | G39: =SUM(G30:G38) -> 2611809 | H39: =SUM(H30:H38) -> 2611809 | I39: =SUM(I30:I38) -> 2611809 | J39: =SUM(J30:J38) -> 2611809 | K39: =SUM(K30:K38) -> 2611809 | ... W39: =SUM(W30:W38) -> 2611809
C40: 年份 | D40: 2020 | E40: 2021 | F40: 2022 | G40: 2023 | H40: 2024 | I40: 2025 | J40: 2026 | K40: 2027 | L40: 2028 | M40: 2029 | N40: 2030 | O40: 2031 | P40: 2032 | Q40: 2033 | R40: 2034 | S40: 2035 | T40: 2036 | U40: 2037 | V40: 2038 | W40: 2039
C41: 運維
B42: 淡江大學 | D42: =ROUND(ABS(淡江大學_p6_1!D48),0) -> 174440 | E42: =ROUND(ABS(淡江大學_p6_1!E48),0) -> 174440 | F42: =ROUND(ABS(淡江大學_p6_1!F48),0) -> 174440 | G42: =ROUND(ABS(淡江大學_p6_1!G48),0) -> 174440 | H42: =ROUND(ABS(淡江大學_p6_1!H48),0) -> 174440 | I42: =ROUND(ABS(淡江大學_p6_1!I48),0) -> 174440 | J42: =ROUND(ABS(淡江大學_p6_1!J48),0) -> 174440 | K42: =ROUND(ABS(淡江大學_p6_1!K48),0) -> 174440 | ... W42: =ROUND(ABS(淡江大學_p6_1!W48),0) -> 174440
B43: 淡江大學 | D43: =ROUND(ABS(淡江大學_p4_2!D48),0) -> 174440 | E43: =ROUND(ABS(淡江大學_p4_2!E48),0) -> 174440 | F43: =ROUND(ABS(淡江大學_p4_2!F48),0) -> 174440 | G43: =ROUND(ABS(淡江大學_p4_2!G48),0) -> 174440 | H43: =ROUND(ABS(淡江大學_p4_2!H48),0) -> 174440 | I43: =ROUND(ABS(淡江大學_p4_2!I48),0) -> 174440 | J43: =ROUND(ABS(淡江大學_p4_2!J48),0) -> 174440 | K43: =ROUND(ABS(淡江大學_p4_2!K48),0) -> 174440 | ... W43: =ROUND(ABS(淡江大學_p4_2!W48),0) -> 174440
B44: 淡江大學 | D44: =ROUND(ABS(淡江大學_p4_1!D48),0) -> 174440 | E44: =ROUND(ABS(淡江大學_p4_1!E48),0) -> 174440 | F44: =ROUND(ABS(淡江大學_p4_1!F48),0) -> 174440 | G44: =ROUND(ABS(淡江大學_p4_1!G48),0) -> 174440 | H44: =ROUND(ABS(淡江大學_p4_1!H48),0) -> 174440 | I44: =ROUND(ABS(淡江大學_p4_1!I48),0) -> 174440 | J44: =ROUND(ABS(淡江大學_p4_1!J48),0) -> 174440 | K44: =ROUND(ABS(淡江大學_p4_1!K48),0) -> 174440 | ... W44: =ROUND(ABS(淡江大學_p4_1!W48),0) -> 174440
B45: 淡江大學 | D45: =ROUND(ABS(淡江大學_p4!D48),0) -> 174440 | E45: =ROUND(ABS(淡江大學_p4!E48),0) -> 174440 | F45: =ROUND(ABS(淡江大學_p4!F48),0) -> 174440 | G45: =ROUND(ABS(淡江大學_p4!G48),0) -> 174440 | H45: =ROUND(ABS(淡江大學_p4!H48),0) -> 174440 | I45: =ROUND(ABS(淡江大學_p4!I48),0) -> 174440 | J45: =ROUND(ABS(淡江大學_p4!J48),0) -> 174440 | K45: =ROUND(ABS(淡江大學_p4!K48),0) -> 174440 | ... W45: =ROUND(ABS(淡江大學_p4!W48),0) -> 174440
B46: 淡江大學 | D46: =ROUND(ABS(淡江大學_p6!D48),0) -> 174440 | E46: =ROUND(ABS(淡江大學_p6!E48),0) -> 174440 | F46: =ROUND(ABS(淡江大學_p6!F48),0) -> 174440 | G46: =ROUND(ABS(淡江大學_p6!G48),0) -> 174440 | H46: =ROUND(ABS(淡江大學_p6!H48),0) -> 174440 | I46: =ROUND(ABS(淡江大學_p6!I48),0) -> 174440 | J46: =ROUND(ABS(淡江大學_p6!J48),0) -> 174440 | K46: =ROUND(ABS(淡江大學_p6!K48),0) -> 174440 | ... W46: =ROUND(ABS(淡江大學_p6!W48),0) -> 174440
B47: 淡江大學 | D47: =ROUND(ABS(淡江大學_p3!D48),0) -> 174440 | E47: =ROUND(ABS(淡江大學_p3!E48),0) -> 174440 | F47: =ROUND(ABS(淡江大學_p3!F48),0) -> 174440 | G47: =ROUND(ABS(淡江大學_p3!G48),0) -> 174440 | H47: =ROUND(ABS(淡江大學_p3!H48),0) -> 174440 | I47: =ROUND(ABS(淡江大學_p3!I48),0) -> 174440 | J47: =ROUND(ABS(淡江大學_p3!J48),0) -> 174440 | K47: =ROUND(ABS(淡江大學_p3!K48),0) -> 174440 | ... W47: =ROUND(ABS(淡江大學_p3!W48),0) -> 174440
B48: 淡江大學 | D48: =ROUND(ABS(淡江大學_p4_3!D48),0) -> 174440 | E48: =ROUND(ABS(淡江大學_p4_3!E48),0) -> 174440 | F48: =ROUND(ABS(淡江大學_p4_3!F48),0) -> 174440 | G48: =ROUND(ABS(淡江大學_p4_3!G48),0) -> 174440 | H48: =ROUND(ABS(淡江大學_p4_3!H48),0) -> 174440 | I48: =ROUND(ABS(淡江大學_p4_3!I48),0) -> 174440 | J48: =ROUND(ABS(淡江大學_p4_3!J48),0) -> 174440 | K48: =ROUND(ABS(淡江大學_p4_3!K48),0) -> 174440 | ... W48: =ROUND(ABS(淡江大學_p4_3!W48),0) -> 174440
B49: 淡江大學 | D49: =ROUND(ABS(淡江大學_p3_1!D48),0) -> 174440 | E49: =ROUND(ABS(淡江大學_p3_1!E48),0) -> 174440 | F49: =ROUND(ABS(淡江大學_p3_1!F48),0) -> 174440 | G49: =ROUND(ABS(淡江大學_p3_1!G48),0) -> 174440 | H49: =ROUND(ABS(淡江大學_p3_1!H48),0) -> 174440 | I49: =ROUND(ABS(淡江大學_p3_1!I48),0) -> 174440 | J49: =ROUND(ABS(淡江大學_p3_1!J48),0) -> 174440 | K49: =ROUND(ABS(淡江大學_p3_1!K48),0) -> 174440 | ... W49: =ROUND(ABS(淡江大學_p3_1!W48),0) -> 174440
B50: 淡江大學 | D50: =ROUND(ABS(淡江大學_p5!D48),0) -> 174440 | E50: =ROUND(ABS(淡江大學_p5!E48),0) -> 174440 | F50: =ROUND(ABS(淡江大學_p5!F48),0) -> 174440 | G50: =ROUND(ABS(淡江大學_p5!G48),0) -> 174440 | H50: =ROUND(ABS(淡江大學_p5!H48),0) -> 174440 | I50: =ROUND(ABS(淡江大學_p5!I48),0) -> 174440 | J50: =ROUND(ABS(淡江大學_p5!J48),0) -> 174440 | K50: =ROUND(ABS(淡江大學_p5!K48),0) -> 174440 | ... W50: =ROUND(ABS(淡江大學_p5!W48),0) -> 174440
C51: 運維/年總計 | D51: =SUM(D42:D50) -> 1569960 | E51: =SUM(E42:E50) -> 1569960 | F51: =SUM(F42:F50) -> 1569960 | G51: =SUM(G42:G50) -> 1569960 | H51: =SUM(H42:H50) -> 1569960 | I51: =SUM(I42:I50) -> 1569960 | J51: =SUM(J42:J50) -> 1569960 | K51: =SUM(K42:K50) -> 1569960 | ... W51: =SUM(W42:W50) -> 1569960
C52: 年份 | D52: 2020 | E52: 2021 | F52: 2022 | G52: 2023 | H52: 2024 | I52: 2025 | J52: 2026 | K52: 2027 | L52: 2028 | M52: 2029 | N52: 2030 | O52: 2031 | P52: 2032 | Q52: 2033 | R52: 2034 | S52: 2035 | T52: 2036 | U52: 2037 | V52: 2038 | W52: 2039
C53: 保險
B54: 淡江大學 | D54: =ROUND(ABS(淡江大學_p6_1!D49),0) -> 32708 | E54: =ROUND(ABS(淡江大學_p6_1!E49),0) -> 32708 | F54: =ROUND(ABS(淡江大學_p6_1!F49),0) -> 32708 | G54: =ROUND(ABS(淡江大學_p6_1!G49),0) -> 32708 | H54: =ROUND(ABS(淡江大學_p6_1!H49),0) -> 32708 | I54: =ROUND(ABS(淡江大學_p6_1!I49),0) -> 32708 | J54: =ROUND(ABS(淡江大學_p6_1!J49),0) -> 32708 | K54: =ROUND(ABS(淡江大學_p6_1!K49),0) -> 32708 | ... W54: =ROUND(ABS(淡江大學_p6_1!W49),0) -> 32708
B55: 淡江大學 | D55: =ROUND(ABS(淡江大學_p4_2!D49),0) -> 37941 | E55: =ROUND(ABS(淡江大學_p4_2!E49),0) -> 37941 | F55: =ROUND(ABS(淡江大學_p4_2!F49),0) -> 37941 | G55: =ROUND(ABS(淡江大學_p4_2!G49),0) -> 37941 | H55: =ROUND(ABS(淡江大學_p4_2!H49),0) -> 37941 | I55: =ROUND(ABS(淡江大學_p4_2!I49),0) -> 37941 | J55: =ROUND(ABS(淡江大學_p4_2!J49),0) -> 37941 | K55: =ROUND(ABS(淡江大學_p4_2!K49),0) -> 37941 | ... W55: =ROUND(ABS(淡江大學_p4_2!W49),0) -> 37941
B56: 淡江大學 | D56: =ROUND(ABS(淡江大學_p4_1!D49),0) -> 37941 | E56: =ROUND(ABS(淡江大學_p4_1!E49),0) -> 37941 | F56: =ROUND(ABS(淡江大學_p4_1!F49),0) -> 37941 | G56: =ROUND(ABS(淡江大學_p4_1!G49),0) -> 37941 | H56: =ROUND(ABS(淡江大學_p4_1!H49),0) -> 37941 | I56: =ROUND(ABS(淡江大學_p4_1!I49),0) -> 37941 | J56: =ROUND(ABS(淡江大學_p4_1!J49),0) -> 37941 | K56: =ROUND(ABS(淡江大學_p4_1!K49),0) -> 37941 | ... W56: =ROUND(ABS(淡江大學_p4_1!W49),0) -> 37941
B57: 淡江大學 | D57: =ROUND(ABS(淡江大學_p4!D49),0) -> 37941 | E57: =ROUND(ABS(淡江大學_p4!E49),0) -> 37941 | F57: =ROUND(ABS(淡江大學_p4!F49),0) -> 37941 | G57: =ROUND(ABS(淡江大學_p4!G49),0) -> 37941 | H57: =ROUND(ABS(淡江大學_p4!H49),0) -> 37941 | I57: =ROUND(ABS(淡江大學_p4!I49),0) -> 37941 | J57: =ROUND(ABS(淡江大學_p4!J49),0) -> 37941 | K57: =ROUND(ABS(淡江大學_p4!K49),0) -> 37941 | ... W57: =ROUND(ABS(淡江大學_p4!W49),0) -> 37941
B58: 淡江大學 | D58: =ROUND(ABS(淡江大學_p6!D49),0) -> 32708 | E58: =ROUND(ABS(淡江大學_p6!E49),0) -> 32708 | F58: =ROUND(ABS(淡江大學_p6!F49),0) -> 32708 | G58: =ROUND(ABS(淡江大學_p6!G49),0) -> 32708 | H58: =ROUND(ABS(淡江大學_p6!H49),0) -> 32708 | I58: =ROUND(ABS(淡江大學_p6!I49),0) -> 32708 | J58: =ROUND(ABS(淡江大學_p6!J49),0) -> 32708 | K58: =ROUND(ABS(淡江大學_p6!K49),0) -> 32708 | ... W58: =ROUND(ABS(淡江大學_p6!W49),0) -> 32708
B59: 淡江大學 | D59: =ROUND(ABS(淡江大學_p3!D49),0) -> 40557 | E59: =ROUND(ABS(淡江大學_p3!E49),0) -> 40557 | F59: =ROUND(ABS(淡江大學_p3!F49),0) -> 40557 | G59: =ROUND(ABS(淡江大學_p3!G49),0) -> 40557 | H59: =ROUND(ABS(淡江大學_p3!H49),0) -> 40557 | I59: =ROUND(ABS(淡江大學_p3!I49),0) -> 40557 | J59: =ROUND(ABS(淡江大學_p3!J49),0) -> 40557 | K59: =ROUND(ABS(淡江大學_p3!K49),0) -> 40557 | ... W59: =ROUND(ABS(淡江大學_p3!W49),0) -> 40557
B60: 淡江大學 | D60: =ROUND(ABS(淡江大學_p4_3!D49),0) -> 37941 | E60: =ROUND(ABS(淡江大學_p4_3!E49),0) -> 37941 | F60: =ROUND(ABS(淡江大學_p4_3!F49),0) -> 37941 | G60: =ROUND(ABS(淡江大學_p4_3!G49),0) -> 37941 | H60: =ROUND(ABS(淡江大學_p4_3!H49),0) -> 37941 | I60: =ROUND(ABS(淡江大學_p4_3!I49),0) -> 37941 | J60: =ROUND(ABS(淡江大學_p4_3!J49),0) -> 37941 | K60: =ROUND(ABS(淡江大學_p4_3!K49),0) -> 37941 | ... W60: =ROUND(ABS(淡江大學_p4_3!W49),0) -> 37941
B61: 淡江大學 | D61: =ROUND(ABS(淡江大學_p3_1!D49),0) -> 40557 | E61: =ROUND(ABS(淡江大學_p3_1!E49),0) -> 40557 | F61: =ROUND(ABS(淡江大學_p3_1!F49),0) -> 40557 | G61: =ROUND(ABS(淡江大學_p3_1!G49),0) -> 40557 | H61: =ROUND(ABS(淡江大學_p3_1!H49),0) -> 40557 | I61: =ROUND(ABS(淡江大學_p3_1!I49),0) -> 40557 | J61: =ROUND(ABS(淡江大學_p3_1!J49),0) -> 40557 | K61: =ROUND(ABS(淡江大學_p3_1!K49),0) -> 40557 | ... W61: =ROUND(ABS(淡江大學_p3_1!W49),0) -> 40557
B62: 淡江大學 | D62: =ROUND(ABS(淡江大學_p5!D49),0) -> 35324 | E62: =ROUND(ABS(淡江大學_p5!E49),0) -> 35324 | F62: =ROUND(ABS(淡江大學_p5!F49),0) -> 35324 | G62: =ROUND(ABS(淡江大學_p5!G49),0) -> 35324 | H62: =ROUND(ABS(淡江大學_p5!H49),0) -> 35324 | I62: =ROUND(ABS(淡江大學_p5!I49),0) -> 35324 | J62: =ROUND(ABS(淡江大學_p5!J49),0) -> 35324 | K62: =ROUND(ABS(淡江大學_p5!K49),0) -> 35324 | ... W62: =ROUND(ABS(淡江大學_p5!W49),0) -> 35324
C63: 保險/年總計 | D63: =SUM(D54:D62) -> 333618 | E63: =SUM(E54:E62) -> 333618 | F63: =SUM(F54:F62) -> 333618 | G63: =SUM(G54:G62) -> 333618 | H63: =SUM(H54:H62) -> 333618 | I63: =SUM(I54:I62) -> 333618 | J63: =SUM(J54:J62) -> 333618 | K63: =SUM(K54:K62) -> 333618 | ... W63: =SUM(W54:W62) -> 333618
C64: 年份 | D64: 2020 | E64: 2021 | F64: 2022 | G64: 2023 | H64: 2024 | I64: 2025 | J64: 2026 | K64: 2027 | L64: 2028 | M64: 2029 | N64: 2030 | O64: 2031 | P64: 2032 | Q64: 2033 | R64: 2034 | S64: 2035 | T64: 2036 | U64: 2037 | V64: 2038 | W64: 2039
C65: 模組回收費
B66: 淡江大學 | D66: =ROUND(ABS(淡江大學_p6_1!D50),0) -> 43610 | E66: =ROUND(ABS(淡江大學_p6_1!E50),0) -> 43610 | F66: =ROUND(ABS(淡江大學_p6_1!F50),0) -> 43610 | G66: =ROUND(ABS(淡江大學_p6_1!G50),0) -> 43610 | H66: =ROUND(ABS(淡江大學_p6_1!H50),0) -> 43610 | I66: =ROUND(ABS(淡江大學_p6_1!I50),0) -> 43610 | J66: =ROUND(ABS(淡江大學_p6_1!J50),0) -> 43610 | K66: =ROUND(ABS(淡江大學_p6_1!K50),0) -> 43610 | ... W66: =ROUND(ABS(淡江大學_p6_1!W50),0) -> 0
B67: 淡江大學 | D67: =ROUND(ABS(淡江大學_p4_2!D50),0) -> 43610 | E67: =ROUND(ABS(淡江大學_p4_2!E50),0) -> 43610 | F67: =ROUND(ABS(淡江大學_p4_2!F50),0) -> 43610 | G67: =ROUND(ABS(淡江大學_p4_2!G50),0) -> 43610 | H67: =ROUND(ABS(淡江大學_p4_2!H50),0) -> 43610 | I67: =ROUND(ABS(淡江大學_p4_2!I50),0) -> 43610 | J67: =ROUND(ABS(淡江大學_p4_2!J50),0) -> 43610 | K67: =ROUND(ABS(淡江大學_p4_2!K50),0) -> 43610 | ... W67: =ROUND(ABS(淡江大學_p4_2!W50),0) -> 0
B68: 淡江大學 | D68: =ROUND(ABS(淡江大學_p4_1!D50),0) -> 43610 | E68: =ROUND(ABS(淡江大學_p4_1!E50),0) -> 43610 | F68: =ROUND(ABS(淡江大學_p4_1!F50),0) -> 43610 | G68: =ROUND(ABS(淡江大學_p4_1!G50),0) -> 43610 | H68: =ROUND(ABS(淡江大學_p4_1!H50),0) -> 43610 | I68: =ROUND(ABS(淡江大學_p4_1!I50),0) -> 43610 | J68: =ROUND(ABS(淡江大學_p4_1!J50),0) -> 43610 | K68: =ROUND(ABS(淡江大學_p4_1!K50),0) -> 43610 | ... W68: =ROUND(ABS(淡江大學_p4_1!W50),0) -> 0
B69: 淡江大學 | D69: =ROUND(ABS(淡江大學_p4!D50),0) -> 43610 | E69: =ROUND(ABS(淡江大學_p4!E50),0) -> 43610 | F69: =ROUND(ABS(淡江大學_p4!F50),0) -> 43610 | G69: =ROUND(ABS(淡江大學_p4!G50),0) -> 43610 | H69: =ROUND(ABS(淡江大學_p4!H50),0) -> 43610 | I69: =ROUND(ABS(淡江大學_p4!I50),0) -> 43610 | J69: =ROUND(ABS(淡江大學_p4!J50),0) -> 43610 | K69: =ROUND(ABS(淡江大學_p4!K50),0) -> 43610 | ... W69: =ROUND(ABS(淡江大學_p4!W50),0) -> 0
B70: 淡江大學 | D70: =ROUND(ABS(淡江大學_p6!D50),0) -> 43610 | E70: =ROUND(ABS(淡江大學_p6!E50),0) -> 43610 | F70: =ROUND(ABS(淡江大學_p6!F50),0) -> 43610 | G70: =ROUND(ABS(淡江大學_p6!G50),0) -> 43610 | H70: =ROUND(ABS(淡江大學_p6!H50),0) -> 43610 | I70: =ROUND(ABS(淡江大學_p6!I50),0) -> 43610 | J70: =ROUND(ABS(淡江大學_p6!J50),0) -> 43610 | K70: =ROUND(ABS(淡江大學_p6!K50),0) -> 43610 | ... W70: =ROUND(ABS(淡江大學_p6!W50),0) -> 0
B71: 淡江大學 | D71: =ROUND(ABS(淡江大學_p3!D50),0) -> 43610 | E71: =ROUND(ABS(淡江大學_p3!E50),0) -> 43610 | F71: =ROUND(ABS(淡江大學_p3!F50),0) -> 43610 | G71: =ROUND(ABS(淡江大學_p3!G50),0) -> 43610 | H71: =ROUND(ABS(淡江大學_p3!H50),0) -> 43610 | I71: =ROUND(ABS(淡江大學_p3!I50),0) -> 43610 | J71: =ROUND(ABS(淡江大學_p3!J50),0) -> 43610 | K71: =ROUND(ABS(淡江大學_p3!K50),0) -> 43610 | ... W71: =ROUND(ABS(淡江大學_p3!W50),0) -> 0
B72: 淡江大學 | D72: =ROUND(ABS(淡江大學_p4_3!D50),0) -> 43610 | E72: =ROUND(ABS(淡江大學_p4_3!E50),0) -> 43610 | F72: =ROUND(ABS(淡江大學_p4_3!F50),0) -> 43610 | G72: =ROUND(ABS(淡江大學_p4_3!G50),0) -> 43610 | H72: =ROUND(ABS(淡江大學_p4_3!H50),0) -> 43610 | I72: =ROUND(ABS(淡江大學_p4_3!I50),0) -> 43610 | J72: =ROUND(ABS(淡江大學_p4_3!J50),0) -> 43610 | K72: =ROUND(ABS(淡江大學_p4_3!K50),0) -> 43610 | ... W72: =ROUND(ABS(淡江大學_p4_3!W50),0) -> 0
B73: 淡江大學 | D73: =ROUND(ABS(淡江大學_p3_1!D50),0) -> 43610 | E73: =ROUND(ABS(淡江大學_p3_1!E50),0) -> 43610 | F73: =ROUND(ABS(淡江大學_p3_1!F50),0) -> 43610 | G73: =ROUND(ABS(淡江大學_p3_1!G50),0) -> 43610 | H73: =ROUND(ABS(淡江大學_p3_1!H50),0) -> 43610 | I73: =ROUND(ABS(淡江大學_p3_1!I50),0) -> 43610 | J73: =ROUND(ABS(淡江大學_p3_1!J50),0) -> 43610 | K73: =ROUND(ABS(淡江大學_p3_1!K50),0) -> 43610 | ... W73: =ROUND(ABS(淡江大學_p3_1!W50),0) -> 0
B74: 淡江大學 | D74: =ROUND(ABS(淡江大學_p5!D50),0) -> 43610 | E74: =ROUND(ABS(淡江大學_p5!E50),0) -> 43610 | F74: =ROUND(ABS(淡江大學_p5!F50),0) -> 43610 | G74: =ROUND(ABS(淡江大學_p5!G50),0) -> 43610 | H74: =ROUND(ABS(淡江大學_p5!H50),0) -> 43610 | I74: =ROUND(ABS(淡江大學_p5!I50),0) -> 43610 | J74: =ROUND(ABS(淡江大學_p5!J50),0) -> 43610 | K74: =ROUND(ABS(淡江大學_p5!K50),0) -> 43610 | ... W74: =ROUND(ABS(淡江大學_p5!W50),0) -> 0
C75: 模組回收費/年總計 | D75: =SUM(D66:D74) -> 392490 | E75: =SUM(E66:E74) -> 392490 | F75: =SUM(F66:F74) -> 392490 | G75: =SUM(G66:G74) -> 392490 | H75: =SUM(H66:H74) -> 392490 | I75: =SUM(I66:I74) -> 392490 | J75: =SUM(J66:J74) -> 392490 | K75: =SUM(K66:K74) -> 392490 | ... W75: =SUM(W66:W74) -> 0
C76: 年份 | D76: 2020 | E76: 2021 | F76: 2022 | G76: 2023 | H76: 2024 | I76: 2025 | J76: 2026 | K76: 2027 | L76: 2028 | M76: 2029 | N76: 2030 | O76: 2031 | P76: 2032 | Q76: 2033 | R76: 2034 | S76: 2035 | T76: 2036 | U76: 2037 | V76: 2038 | W76: 2039
C77: 所得稅
B78: 淡江大學 | D78: =ROUND(ABS(淡江大學_p6_1!D54),0) -> 0 | E78: =ROUND(ABS(淡江大學_p6_1!E54),0) -> 0 | F78: =ROUND(ABS(淡江大學_p6_1!F54),0) -> 0 | G78: =ROUND(ABS(淡江大學_p6_1!G54),0) -> 0 | H78: =ROUND(ABS(淡江大學_p6_1!H54),0) -> 0 | I78: =ROUND(ABS(淡江大學_p6_1!I54),0) -> 0 | J78: =ROUND(ABS(淡江大學_p6_1!J54),0) -> 0 | K78: =ROUND(ABS(淡江大學_p6_1!K54),0) -> 0 | ... W78: =ROUND(ABS(淡江大學_p6_1!W54),0) -> 0
B79: 淡江大學 | D79: =ROUND(ABS(淡江大學_p4_2!D54),0) -> 0 | E79: =ROUND(ABS(淡江大學_p4_2!E54),0) -> 0 | F79: =ROUND(ABS(淡江大學_p4_2!F54),0) -> 0 | G79: =ROUND(ABS(淡江大學_p4_2!G54),0) -> 0 | H79: =ROUND(ABS(淡江大學_p4_2!H54),0) -> 0 | I79: =ROUND(ABS(淡江大學_p4_2!I54),0) -> 0 | J79: =ROUND(ABS(淡江大學_p4_2!J54),0) -> 0 | K79: =ROUND(ABS(淡江大學_p4_2!K54),0) -> 0 | ... W79: =ROUND(ABS(淡江大學_p4_2!W54),0) -> 0
B80: 淡江大學 | D80: =ROUND(ABS(淡江大學_p4_1!D54),0) -> 0 | E80: =ROUND(ABS(淡江大學_p4_1!E54),0) -> 0 | F80: =ROUND(ABS(淡江大學_p4_1!F54),0) -> 0 | G80: =ROUND(ABS(淡江大學_p4_1!G54),0) -> 0 | H80: =ROUND(ABS(淡江大學_p4_1!H54),0) -> 0 | I80: =ROUND(ABS(淡江大學_p4_1!I54),0) -> 0 | J80: =ROUND(ABS(淡江大學_p4_1!J54),0) -> 0 | K80: =ROUND(ABS(淡江大學_p4_1!K54),0) -> 0 | ... W80: =ROUND(ABS(淡江大學_p4_1!W54),0) -> 0
B81: 淡江大學 | D81: =ROUND(ABS(淡江大學_p4!D54),0) -> 0 | E81: =ROUND(ABS(淡江大學_p4!E54),0) -> 0 | F81: =ROUND(ABS(淡江大學_p4!F54),0) -> 0 | G81: =ROUND(ABS(淡江大學_p4!G54),0) -> 0 | H81: =ROUND(ABS(淡江大學_p4!H54),0) -> 0 | I81: =ROUND(ABS(淡江大學_p4!I54),0) -> 0 | J81: =ROUND(ABS(淡江大學_p4!J54),0) -> 0 | K81: =ROUND(ABS(淡江大學_p4!K54),0) -> 0 | ... W81: =ROUND(ABS(淡江大學_p4!W54),0) -> 0
B82: 淡江大學 | D82: =ROUND(ABS(淡江大學_p6!D54),0) -> 0 | E82: =ROUND(ABS(淡江大學_p6!E54),0) -> 0 | F82: =ROUND(ABS(淡江大學_p6!F54),0) -> 0 | G82: =ROUND(ABS(淡江大學_p6!G54),0) -> 0 | H82: =ROUND(ABS(淡江大學_p6!H54),0) -> 0 | I82: =ROUND(ABS(淡江大學_p6!I54),0) -> 0 | J82: =ROUND(ABS(淡江大學_p6!J54),0) -> 0 | K82: =ROUND(ABS(淡江大學_p6!K54),0) -> 0 | ... W82: =ROUND(ABS(淡江大學_p6!W54),0) -> 0
B83: 淡江大學 | D83: =ROUND(ABS(淡江大學_p3!D54),0) -> 0 | E83: =ROUND(ABS(淡江大學_p3!E54),0) -> 0 | F83: =ROUND(ABS(淡江大學_p3!F54),0) -> 0 | G83: =ROUND(ABS(淡江大學_p3!G54),0) -> 0 | H83: =ROUND(ABS(淡江大學_p3!H54),0) -> 0 | I83: =ROUND(ABS(淡江大學_p3!I54),0) -> 0 | J83: =ROUND(ABS(淡江大學_p3!J54),0) -> 0 | K83: =ROUND(ABS(淡江大學_p3!K54),0) -> 0 | ... W83: =ROUND(ABS(淡江大學_p3!W54),0) -> 0
B84: 淡江大學 | D84: =ROUND(ABS(淡江大學_p4_3!D54),0) -> 192635 | E84: =ROUND(ABS(淡江大學_p4_3!E54),0) -> 132845 | F84: =ROUND(ABS(淡江大學_p4_3!F54),0) -> 131094 | G84: =ROUND(ABS(淡江大學_p4_3!G54),0) -> 129344 | H84: =ROUND(ABS(淡江大學_p4_3!H54),0) -> 127594 | I84: =ROUND(ABS(淡江大學_p4_3!I54),0) -> 125843 | J84: =ROUND(ABS(淡江大學_p4_3!J54),0) -> 124093 | K84: =ROUND(ABS(淡江大學_p4_3!K54),0) -> 122342 | ... W84: =ROUND(ABS(淡江大學_p4_3!W54),0) -> 110060
B85: 淡江大學 | D85: =ROUND(ABS(淡江大學_p3_1!D54),0) -> 179652 | E85: =ROUND(ABS(淡江大學_p3_1!E54),0) -> 119862 | F85: =ROUND(ABS(淡江大學_p3_1!F54),0) -> 118111 | G85: =ROUND(ABS(淡江大學_p3_1!G54),0) -> 116361 | H85: =ROUND(ABS(淡江大學_p3_1!H54),0) -> 114610 | I85: =ROUND(ABS(淡江大學_p3_1!I54),0) -> 112860 | J85: =ROUND(ABS(淡江大學_p3_1!J54),0) -> 111109 | K85: =ROUND(ABS(淡江大學_p3_1!K54),0) -> 109359 | ... W85: =ROUND(ABS(淡江大學_p3_1!W54),0) -> 97076
B86: 淡江大學 | D86: =ROUND(ABS(淡江大學_p5!D54),0) -> 205619 | E86: =ROUND(ABS(淡江大學_p5!E54),0) -> 145828 | F86: =ROUND(ABS(淡江大學_p5!F54),0) -> 144078 | G86: =ROUND(ABS(淡江大學_p5!G54),0) -> 142327 | H86: =ROUND(ABS(淡江大學_p5!H54),0) -> 140577 | I86: =ROUND(ABS(淡江大學_p5!I54),0) -> 138827 | J86: =ROUND(ABS(淡江大學_p5!J54),0) -> 137076 | K86: =ROUND(ABS(淡江大學_p5!K54),0) -> 135326 | ... W86: =ROUND(ABS(淡江大學_p5!W54),0) -> 123043
C87: 所得稅/年總計 | D87: =SUM(D78:D86) -> 577906 | E87: =SUM(E78:E86) -> 398535 | F87: =SUM(F78:F86) -> 393283 | G87: =SUM(G78:G86) -> 388032 | H87: =SUM(H78:H86) -> 382781 | I87: =SUM(I78:I86) -> 377530 | J87: =SUM(J78:J86) -> 372278 | K87: =SUM(K78:K86) -> 367027 | ... W87: =SUM(W78:W86) -> 330179
C88: 年份 | D88: 2020 | E88: 2021 | F88: 2022 | G88: 2023 | H88: 2024 | I88: 2025 | J88: 2026 | K88: 2027 | L88: 2028 | M88: 2029 | N88: 2030 | O88: 2031 | P88: 2032 | Q88: 2033 | R88: 2034 | S88: 2035 | T88: 2036 | U88: 2037 | V88: 2038 | W88: 2039
C89: 設備折舊
B90: 淡江大學 | D90: =ROUND(ABS(淡江大學_p6_1!D67),0) -> 0 | E90: =ROUND(ABS(淡江大學_p6_1!E67),0) -> 0 | F90: =ROUND(ABS(淡江大學_p6_1!F67),0) -> 0 | G90: =ROUND(ABS(淡江大學_p6_1!G67),0) -> 0 | H90: =ROUND(ABS(淡江大學_p6_1!H67),0) -> 0 | I90: =ROUND(ABS(淡江大學_p6_1!I67),0) -> 0 | J90: =ROUND(ABS(淡江大學_p6_1!J67),0) -> 0 | K90: =ROUND(ABS(淡江大學_p6_1!K67),0) -> 0 | ... W90: =ROUND(ABS(淡江大學_p6_1!W67),0) -> 0
B91: 淡江大學 | D91: =ROUND(ABS(淡江大學_p4_2!D67),0) -> 0 | E91: =ROUND(ABS(淡江大學_p4_2!E67),0) -> 0 | F91: =ROUND(ABS(淡江大學_p4_2!F67),0) -> 0 | G91: =ROUND(ABS(淡江大學_p4_2!G67),0) -> 0 | H91: =ROUND(ABS(淡江大學_p4_2!H67),0) -> 0 | I91: =ROUND(ABS(淡江大學_p4_2!I67),0) -> 0 | J91: =ROUND(ABS(淡江大學_p4_2!J67),0) -> 0 | K91: =ROUND(ABS(淡江大學_p4_2!K67),0) -> 0 | ... W91: =ROUND(ABS(淡江大學_p4_2!W67),0) -> 0
B92: 淡江大學 | D92: =ROUND(ABS(淡江大學_p4_1!D67),0) -> 0 | E92: =ROUND(ABS(淡江大學_p4_1!E67),0) -> 0 | F92: =ROUND(ABS(淡江大學_p4_1!F67),0) -> 0 | G92: =ROUND(ABS(淡江大學_p4_1!G67),0) -> 0 | H92: =ROUND(ABS(淡江大學_p4_1!H67),0) -> 0 | I92: =ROUND(ABS(淡江大學_p4_1!I67),0) -> 0 | J92: =ROUND(ABS(淡江大學_p4_1!J67),0) -> 0 | K92: =ROUND(ABS(淡江大學_p4_1!K67),0) -> 0 | ... W92: =ROUND(ABS(淡江大學_p4_1!W67),0) -> 0
B93: 淡江大學 | D93: =ROUND(ABS(淡江大學_p4!D67),0) -> 0 | E93: =ROUND(ABS(淡江大學_p4!E67),0) -> 0 | F93: =ROUND(ABS(淡江大學_p4!F67),0) -> 0 | G93: =ROUND(ABS(淡江大學_p4!G67),0) -> 0 | H93: =ROUND(ABS(淡江大學_p4!H67),0) -> 0 | I93: =ROUND(ABS(淡江大學_p4!I67),0) -> 0 | J93: =ROUND(ABS(淡江大學_p4!J67),0) -> 0 | K93: =ROUND(ABS(淡江大學_p4!K67),0) -> 0 | ... W93: =ROUND(ABS(淡江大學_p4!W67),0) -> 0
B94: 淡江大學 | D94: =ROUND(ABS(淡江大學_p6!D67),0) -> 0 | E94: =ROUND(ABS(淡江大學_p6!E67),0) -> 0 | F94: =ROUND(ABS(淡江大學_p6!F67),0) -> 0 | G94: =ROUND(ABS(淡江大學_p6!G67),0) -> 0 | H94: =ROUND(ABS(淡江大學_p6!H67),0) -> 0 | I94: =ROUND(ABS(淡江大學_p6!I67),0) -> 0 | J94: =ROUND(ABS(淡江大學_p6!J67),0) -> 0 | K94: =ROUND(ABS(淡江大學_p6!K67),0) -> 0 | ... W94: =ROUND(ABS(淡江大學_p6!W67),0) -> 0
B95: 淡江大學 | D95: =ROUND(ABS(淡江大學_p3!D67),0) -> 0 | E95: =ROUND(ABS(淡江大學_p3!E67),0) -> 0 | F95: =ROUND(ABS(淡江大學_p3!F67),0) -> 0 | G95: =ROUND(ABS(淡江大學_p3!G67),0) -> 0 | H95: =ROUND(ABS(淡江大學_p3!H67),0) -> 0 | I95: =ROUND(ABS(淡江大學_p3!I67),0) -> 0 | J95: =ROUND(ABS(淡江大學_p3!J67),0) -> 0 | K95: =ROUND(ABS(淡江大學_p3!K67),0) -> 0 | ... W95: =ROUND(ABS(淡江大學_p3!W67),0) -> 0
B96: 淡江大學 | D96: =ROUND(ABS(淡江大學_p4_3!D67),0) -> 946960 | E96: =ROUND(ABS(淡江大學_p4_3!E67),0) -> 946960 | F96: =ROUND(ABS(淡江大學_p4_3!F67),0) -> 946960 | G96: =ROUND(ABS(淡江大學_p4_3!G67),0) -> 946960 | H96: =ROUND(ABS(淡江大學_p4_3!H67),0) -> 946960 | I96: =ROUND(ABS(淡江大學_p4_3!I67),0) -> 946960 | J96: =ROUND(ABS(淡江大學_p4_3!J67),0) -> 946960 | K96: =ROUND(ABS(淡江大學_p4_3!K67),0) -> 946960 | ... W96: =ROUND(ABS(淡江大學_p4_3!W67),0) -> 946960
B97: 淡江大學 | D97: =ROUND(ABS(淡江大學_p3_1!D67),0) -> 1009260 | E97: =ROUND(ABS(淡江大學_p3_1!E67),0) -> 1009260 | F97: =ROUND(ABS(淡江大學_p3_1!F67),0) -> 1009260 | G97: =ROUND(ABS(淡江大學_p3_1!G67),0) -> 1009260 | H97: =ROUND(ABS(淡江大學_p3_1!H67),0) -> 1009260 | I97: =ROUND(ABS(淡江大學_p3_1!I67),0) -> 1009260 | J97: =ROUND(ABS(淡江大學_p3_1!J67),0) -> 1009260 | K97: =ROUND(ABS(淡江大學_p3_1!K67),0) -> 1009260 | ... W97: =ROUND(ABS(淡江大學_p3_1!W67),0) -> 1009260
B98: 淡江大學 | D98: =ROUND(ABS(淡江大學_p5!D67),0) -> 884660 | E98: =ROUND(ABS(淡江大學_p5!E67),0) -> 884660 | F98: =ROUND(ABS(淡江大學_p5!F67),0) -> 884660 | G98: =ROUND(ABS(淡江大學_p5!G67),0) -> 884660 | H98: =ROUND(ABS(淡江大學_p5!H67),0) -> 884660 | I98: =ROUND(ABS(淡江大學_p5!I67),0) -> 884660 | J98: =ROUND(ABS(淡江大學_p5!J67),0) -> 884660 | K98: =ROUND(ABS(淡江大學_p5!K67),0) -> 884660 | ... W98: =ROUND(ABS(淡江大學_p5!W67),0) -> 884660
C99: 設備折舊/年總計 | D99: =SUM(D90:D98) -> 2840880 | E99: =SUM(E90:E98) -> 2840880 | F99: =SUM(F90:F98) -> 2840880 | G99: =SUM(G90:G98) -> 2840880 | H99: =SUM(H90:H98) -> 2840880 | I99: =SUM(I90:I98) -> 2840880 | J99: =SUM(J90:J98) -> 2840880 | K99: =SUM(K90:K98) -> 2840880 | ... W99: =SUM(W90:W98) -> 2840880
B101: 貸款成數(%) | C101: 0.8
B102: 還款期數 | C102: 15
B103: 股利比率(%) | C103: 0.9
B104: 年底減資攤還期數 | C104: 4
...

Sheet 淡江大學_p3
A1: 電站基本資料(請填寫著色處) | E1: 說明 | O1: =1-C11 -> 0.99 | P1: =O1-$C12 -> 0.986 | Q1: =P1-$C12 -> 0.982 | R1: =Q1-$C12 -> 0.978 | S1: =R1-$C12 -> 0.974 | T1: =S1-$C12 -> 0.97 | U1: =T1-$C12 -> 0.966 | V1: =U1-$C12 -> 0.962 | W1: =V1-$C12 -> 0.958 | ... AH1: =AG1-$C12 -> 0.914
A2: 電站名稱 | B2: 淡江大學 | C2: 淡江大學 | D2: - | E2: 填入本案場名稱
A3: 電站壽命 | B3: 20 | C3: 20 | D3: - | E3: 預設 20 年，代表財務評估年期。若合約年限不同可依實際情況修改
A4: 建置量(kWp) | B4: 436.1 | C4: 436.1 | D4: - | E4: 填入裝置容量（kWp），通常由設計圖面或報價書取得 | M4: 情境編號: 3
A5: 起始年度 | B5: 2020 | C5: 2020 | D5: =B5+B3-1 -> 2039 | E5: 2039 | M5: 第2次滾算摘要
M6: 價金: 31000
A7: 綜合損益表(請填寫著色處) | M7: 專案IRR: 3.75
A8: 收入 | M8: 權益法IRR: 8.21
A9: 收支項目 | B9: 相關參數 | C9: 參數數值 | D9: 年限 | E9: 說明 | M9: 利潤率: 30.00%
A10: 電費收入 | B10: 年度AC併網總發電量 | C10: 547002 | D10: 547002 | E10: 20 | M10: 第2次滾算，減少 2000 元 - 現金模式，每次減少 2000 元
B11: 首年衰退率 | C11: 0.01 | E11: 第一年發電衰退比率，請填小數（例：1% → 填 0.01）。一般首年衰退約 1~2%(請參考模組規格書)
B12: 次年衰退率 | C12: 0.004 | E12: 第二年起每年固定衰退比率，請填小數（例：0.4% → 填 0.004）。一般約 0.4~0.7%(請參考模組規格書)
B13: 躉售費率(FIT) / 綠電費率 | C13: 4 | E13: 與台電簽訂的躉購費率或綠電合約費率，單位：元/度。請參考台電公告或合約內容
A14: 支出(請填寫著色處)
A15: 收支項目 | B15: 相關參數 | C15: 參數數值 | D15: 攤提年限 | E15: 說明
A16: 設備費用(價金) | B16: 每kWp設備成本 | C16: 35000 | D16: 31000 | E16: 20
B17: 信邦利潤率(ex:20%填0.2) | C17: 0.3 | E17: 公司在設備費用上加計的利潤比率，請填小數（例：20% → 填 0.2）
B18: 開發費 | C18: 2000 | E18: 前期開發費用（元），含可行性評估、申請規費、地主溝通等。若無則填 0
A19: 租金費用 | B19: 租金計算方式 | C19: 1 | D19: 1 | E19: 0
B20: 【方式1參數】每年相同價格 | C20: 290201 | D20: 290201 | E20: 20
B21: 【方式2參數】抽成比率 | D21: 0 | E21: 0
A22: 運維費用 | B22: 每kw運維成本 | C22: 400 | D22: 400 | E22: 20
A23: 保險費用 | B23: 占整體設備費用比例 | C23: 0.003 | D23: 0.003 | E23: 20
A24: 模組回收費用 | B24: 每kw模組回收成本 | C24: 1000 | D24: 1000 | E24: 10
A25: 利息費用 | B25: 銀行利率 | C25: 0.0256 | D25: 0.0256 | E25: 0
A26: 所得稅 | B26: 所得稅率 | C26: 0.2 | D26: 0.2 | E26: 0
A29: 現金流量表(請填寫著色處)
A30: 金流項目 | B30: 相關參數 | C30: 參數數值 | E30: 說明
A31: 貸款成數 | B31: 占總設備費用比例 | C31: 0.8 | D31: 0.8 | E31: 貸款佔設備總費用比例，填小數（例：80% → 填 0.8）。預設 0.8 代表貸八成、自備二成
A32: 貸款還款 | B32: 攤還期數 | C32: 15 | D32: 15 | E32: 貸款還款年數（年）。預設 15 年，代表分 15 年平均攤還本金
A33: 現金股利 | B33: 股利比率 | C33: 0.9 | D33: 0.9 | E33: 稅後現金流中分配給股東的比例，填小數（例：90% → 填 0.9）
A34: 年底減資 | B34: 攤還期數 | C34: 4 | D34: 4 | E34: 年底減資返還股東的年數。預設 4 年，代表 倒數 4 年進行減資，加速資金返還
D37: 2020 | E37: 2021 | F37: 2022 | G37: 2023 | H37: 2024 | I37: 2025 | J37: 2026 | K37: 2027 | L37: 2028 | M37: 2029 | N37: 2030 | O37: 2031 | P37: 2032 | Q37: 2033 | R37: 2034 | S37: 2035 | T37: 2036 | U37: 2037 | V37: 2038 | W37: 2039
D45: -290201 | E45: -290201 | F45: -290201 | G45: -290201 | H45: -290201 | I45: -290201 | J45: -290201 | K45: -290201 | L45: -290201 | M45: -290201 | N45: -290201 | O45: -290201 | P45: -290201 | Q45: -290201 | R45: -290201 | S45: -290201 | T45: -290201 | U45: -290201 | V45: -290201 | W45: -290201
D48: -174440 | E48: -174440 | F48: -174440 | G48: -174440 | H48: -174440 | I48: -174440 | J48: -174440 | K48: -174440 | L48: -174440 | M48: -174440 | N48: -174440 | O48: -174440 | P48: -174440 | Q48: -174440 | R48: -174440 | S48: -174440 | T48: -174440 | U48: -174440 | V48: -174440 | W48: -174440
D49: -40557.3 | E49: -40557.3 | F49: -40557.3 | G49: -40557.3 | H49: -40557.3 | I49: -40557.3 | J49: -40557.3 | K49: -40557.3 | L49: -40557.3 | M49: -40557.3 | N49: -40557.3 | O49: -40557.3 | P49: -40557.3 | Q49: -40557.3 | R49: -40557.3 | S49: -40557.3 | T49: -40557.3 | U49: -40557.3 | V49: -40557.3 | W49: -40557.3
D50: -43610 | E50: -43610 | F50: -43610 | G50: -43610 | H50: -43610 | I50: -43610 | J50: -43610 | K50: -43610 | L50: -43610 | M50: -43610 | N50: 0 | O50: 0 | P50: 0 | Q50: 0 | R50: 0 | S50: 0 | T50: 0 | U50: 0 | V50: 0 | W50: 0
D54: =D77 -> 0 | E54: =E77 -> 0 | F54: =F77 -> 0 | G54: =G77 -> 0 | H54: =H77 -> 0 | I54: =I77 -> 0 | J54: =J77 -> 0 | K54: =K77 -> 0 | ... W54: =W77 -> 0
D70: 0 | E70: 0 | F70: 0 | G70: 0 | H70: 0 | I70: 0 | J70: 0 | K70: 0 | L70: 0 | M70: 0 | N70: 0 | O70: 0 | P70: 0 | Q70: 0 | R70: 0 | S70: 0 | T70: 0 | U70: 0 | V70: 0 | W70: 0

Sheet 淡江大學_p6
A1: 電站基本資料(請填寫著色處) | E1: 說明 | O1: =1-C11 -> 0.99 | P1: =O1-$C12 -> 0.986 | Q1: =P1-$C12 -> 0.982 | R1: =Q1-$C12 -> 0.978 | S1: =R1-$C12 -> 0.974 | T1: =S1-$C12 -> 0.97 | U1: =T1-$C12 -> 0.966 | V1: =U1-$C12 -> 0.962 | W1: =V1-$C12 -> 0.958 | ... AH1: =AG1-$C12 -> 0.914
A2: 電站名稱 | B2: 淡江大學 | C2: 淡江大學 | D2: - | E2: 填入本案場名稱
A3: 電站壽命 | B3: 20 | C3: 20 | D3: - | E3: 預設 20 年，代表財務評估年期。若合約年限不同可依實際情況修改
A4: 建置量(kWp) | B4: 436.1 | C4: 436.1 | D4: - | E4: 填入裝置容量（kWp），通常由設計圖面或報價書取得 | M4: 情境編號: 6
A5: 起始年度 | B5: 2020 | C5: 2020 | D5: =B5+B3-1 -> 2039 | E5: 2039 | M5: 第5次滾算摘要
M6: 價金: 25000
A7: 綜合損益表(請填寫著色處) | M7: 專案IRR: 5.91
A8: 收入 | M8: 權益法IRR: 17.0
A9: 收支項目 | B9: 相關參數 | C9: 參數數值 | D9: 年限 | E9: 說明 | M9: 利潤率: 30.00%
A10: 電費收入 | B10: 年度AC併網總發電量 | C10: 547002 | D10: 547002 | E10: 20 | M10: 第5次滾算，減少 2000 元 - 現金模式，每次減少 2000 元
B11: 首年衰退率 | C11: 0.01 | E11: 第一年發電衰退比率，請填小數（例：1% → 填 0.01）。一般首年衰退約 1~2%(請參考模組規格書)
B12: 次年衰退率 | C12: 0.004 | E12: 第二年起每年固定衰退比率，請填小數（例：0.4% → 填 0.004）。一般約 0.4~0.7%(請參考模組規格書)
B13: 躉售費率(FIT) / 綠電費率 | C13: 4 | E13: 與台電簽訂的躉購費率或綠電合約費率，單位：元/度。請參考台電公告或合約內容
A14: 支出(請填寫著色處)
A15: 收支項目 | B15: 相關參數 | C15: 參數數值 | D15: 攤提年限 | E15: 說明
A16: 設備費用(價金) | B16: 每kWp設備成本 | C16: 35000 | D16: 25000 | E16: 20
B17: 信邦利潤率(ex:20%填0.2) | C17: 0.3 | E17: 公司在設備費用上加計的利潤比率，請填小數（例：20% → 填 0.2）
B18: 開發費 | C18: 2000 | E18: 前期開發費用（元），含可行性評估、申請規費、地主溝通等。若無則填 0
A19: 租金費用 | B19: 租金計算方式 | C19: 1 | D19: 1 | E19: 0
B20: 【方式1參數】每年相同價格 | C20: 290201 | D20: 290201 | E20: 20
B21: 【方式2參數】抽成比率 | D21: 0 | E21: 0
A22: 運維費用 | B22: 每kw運維成本 | C22: 400 | D22: 400 | E22: 20
A23: 保險費用 | B23: 占整體設備費用比例 | C23: 0.003 | D23: 0.003 | E23: 20
A24: 模組回收費用 | B24: 每kw模組回收成本 | C24: 1000 | D24: 1000 | E24: 10
A25: 利息費用 | B25: 銀行利率 | C25: 0.0256 | D25: 0.0256 | E25: 0
A26: 所得稅 | B26: 所得稅率 | C26: 0.2 | D26: 0.2 | E26: 0
A29: 現金流量表(請填寫著色處)
A30: 金流項目 | B30: 相關參數 | C30: 參數數值 | E30: 說明
A31: 貸款成數 | B31: 占總設備費用比例 | C31: 0.8 | D31: 0.8 | E31: 貸款佔設備總費用比例，填小數（例：80% → 填 0.8）。預設 0.8 代表貸八成、自備二成
A32: 貸款還款 | B32: 攤還期數 | C32: 15 | D32: 15 | E32: 貸款還款年數（年）。預設 15 年，代表分 15 年平均攤還本金
A33: 現金股利 | B33: 股利比率 | C33: 0.9 | D33: 0.9 | E33: 稅後現金流中分配給股東的比例，填小數（例：90% → 填 0.9）
A34: 年底減資 | B34: 攤還期數 | C34: 4 | D34: 4 | E34: 年底減資返還股東的年數。預設 4 年，代表 倒數 4 年進行減資，加速資金返還
D37: 2020 | E37: 2021 | F37: 2022 | G37: 2023 | H37: 2024 | I37: 2025 | J37: 2026 | K37: 2027 | L37: 2028 | M37: 2029 | N37: 2030 | O37: 2031 | P37: 2032 | Q37: 2033 | R37: 2034 | S37: 2035 | T37: 2036 | U37: 2037 | V37: 2038 | W37: 2039
D45: -290201 | E45: -290201 | F45: -290201 | G45: -290201 | H45: -290201 | I45: -290201 | J45: -290201 | K45: -290201 | L45: -290201 | M45: -290201 | N45: -290201 | O45: -290201 | P45: -290201 | Q45: -290201 | R45: -290201 | S45: -290201 | T45: -290201 | U45: -290201 | V45: -290201 | W45: -290201
D48: -174440 | E48: -174440 | F48: -174440 | G48: -174440 | H48: -174440 | I48: -174440 | J48: -174440 | K48: -174440 | L48: -174440 | M48: -174440 | N48: -174440 | O48: -174440 | P48: -174440 | Q48: -174440 | R48: -174440 | S48: -174440 | T48: -174440 | U48: -174440 | V48: -174440 | W48: -174440
D49: -32707.5 | E49: -32707.5 | F49: -32707.5 | G49: -32707.5 | H49: -32707.5 | I49: -32707.5 | J49: -32707.5 | K49: -32707.5 | L49: -32707.5 | M49: -32707.5 | N49: -32707.5 | O49: -32707.5 | P49: -32707.5 | Q49: -32707.5 | R49: -32707.5 | S49: -32707.5 | T49: -32707.5 | U49: -32707.5 | V49: -32707.5 | W49: -32707.5
D50: -43610 | E50: -43610 | F50: -43610 | G50: -43610 | H50: -43610 | I50: -43610 | J50: -43610 | K50: -43610 | L50: -43610 | M50: -43610 | N50: 0 | O50: 0 | P50: 0 | Q50: 0 | R50: 0 | S50: 0 | T50: 0 | U50: 0 | V50: 0 | W50: 0
D54: =D77 -> 0 | E54: =E77 -> 0 | F54: =F77 -> 0 | G54: =G77 -> 0 | H54: =H77 -> 0 | I54: =I77 -> 0 | J54: =J77 -> 0 | K54: =K77 -> 0 | ... W54: =W77 -> 0
D70: 0 | E70: 0 | F70: 0 | G70: 0 | H70: 0 | I70: 0 | J70: 0 | K70: 0 | L70: 0 | M70: 0 | N70: 0 | O70: 0 | P70: 0 | Q70: 0 | R70: 0 | S70: 0 | T70: 0 | U70: 0 | V70: 0 | W70: 0

Sheet 淡江大學_p4
A1: 電站基本資料(請填寫著色處) | E1: 說明 | O1: =1-C11 -> 0.99 | P1: =O1-$C12 -> 0.986 | Q1: =P1-$C12 -> 0.982 | R1: =Q1-$C12 -> 0.978 | S1: =R1-$C12 -> 0.974 | T1: =S1-$C12 -> 0.97 | U1: =T1-$C12 -> 0.966 | V1: =U1-$C12 -> 0.962 | W1: =V1-$C12 -> 0.958 | ... AH1: =AG1-$C12 -> 0.914
A2: 電站名稱 | B2: 淡江大學 | C2: 淡江大學 | D2: - | E2: 填入本案場名稱
A3: 電站壽命 | B3: 20 | C3: 20 | D3: - | E3: 預設 20 年，代表財務評估年期。若合約年限不同可依實際情況修改
A4: 建置量(kWp) | B4: 436.1 | C4: 436.1 | D4: - | E4: 填入裝置容量（kWp），通常由設計圖面或報價書取得 | M4: 情境編號: 4
A5: 起始年度 | B5: 2020 | C5: 2020 | D5: =B5+B3-1 -> 2039 | E5: 2039 | M5: 第3次滾算摘要
M6: 價金: 29000
A7: 綜合損益表(請填寫著色處) | M7: 專案IRR: 4.39
A8: 收入 | M8: 權益法IRR: 10.59
A9: 收支項目 | B9: 相關參數 | C9: 參數數值 | D9: 年限 | E9: 說明 | M9: 利潤率: 30.00%
A10: 電費收入 | B10: 年度AC併網總發電量 | C10: 547002 | D10: 547002 | E10: 20 | M10: 第3次滾算，減少 2000 元 - 現金模式，每次減少 2000 元
B11: 首年衰退率 | C11: 0.01 | E11: 第一年發電衰退比率，請填小數（例：1% → 填 0.01）。一般首年衰退約 1~2%(請參考模組規格書)
B12: 次年衰退率 | C12: 0.004 | E12: 第二年起每年固定衰退比率，請填小數（例：0.4% → 填 0.004）。一般約 0.4~0.7%(請參考模組規格書)
B13: 躉售費率(FIT) / 綠電費率 | C13: 4 | E13: 與台電簽訂的躉購費率或綠電合約費率，單位：元/度。請參考台電公告或合約內容
A14: 支出(請填寫著色處)
A15: 收支項目 | B15: 相關參數 | C15: 參數數值 | D15: 攤提年限 | E15: 說明
A16: 設備費用(價金) | B16: 每kWp設備成本 | C16: 35000 | D16: 29000 | E16: 20
B17: 信邦利潤率(ex:20%填0.2) | C17: 0.3 | E17: 公司在設備費用上加計的利潤比率，請填小數（例：20% → 填 0.2）
B18: 開發費 | C18: 2000 | E18: 前期開發費用（元），含可行性評估、申請規費、地主溝通等。若無則填 0
A19: 租金費用 | B19: 租金計算方式 | C19: 1 | D19: 1 | E19: 0
B20: 【方式1參數】每年相同價格 | C20: 290201 | D20: 290201 | E20: 20
B21: 【方式2參數】抽成比率 | D21: 0 | E21: 0
A22: 運維費用 | B22: 每kw運維成本 | C22: 400 | D22: 400 | E22: 20
A23: 保險費用 | B23: 占整體設備費用比例 | C23: 0.003 | D23: 0.003 | E23: 20
A24: 模組回收費用 | B24: 每kw模組回收成本 | C24: 1000 | D24: 1000 | E24: 10
A25: 利息費用 | B25: 銀行利率 | C25: 0.0256 | D25: 0.0256 | E25: 0
A26: 所得稅 | B26: 所得稅率 | C26: 0.2 | D26: 0.2 | E26: 0
A29: 現金流量表(請填寫著色處)
A30: 金流項目 | B30: 相關參數 | C30: 參數數值 | E30: 說明
A31: 貸款成數 | B31: 占總設備費用比例 | C31: 0.8 | D31: 0.8 | E31: 貸款佔設備總費用比例，填小數（例：80% → 填 0.8）。預設 0.8 代表貸八成、自備二成
A32: 貸款還款 | B32: 攤還期數 | C32: 15 | D32: 15 | E32: 貸款還款年數（年）。預設 15 年，代表分 15 年平均攤還本金
A33: 現金股利 | B33: 股利比率 | C33: 0.9 | D33: 0.9 | E33: 稅後現金流中分配給股東的比例，填小數（例：90% → 填 0.9）
A34: 年底減資 | B34: 攤還期數 | C34: 4 | D34: 4 | E34: 年底減資返還股東的年數。預設 4 年，代表 倒數 4 年進行減資，加速資金返還
D37: 2020 | E37: 2021 | F37: 2022 | G37: 2023 | H37: 2024 | I37: 2025 | J37: 2026 | K37: 2027 | L37: 2028 | M37: 2029 | N37: 2030 | O37: 2031 | P37: 2032 | Q37: 2033 | R37: 2034 | S37: 2035 | T37: 2036 | U37: 2037 | V37: 2038 | W37: 2039
D45: -290201 | E45: -290201 | F45: -290201 | G45: -290201 | H45: -290201 | I45: -290201 | J45: -290201 | K45: -290201 | L45: -290201 | M45: -290201 | N45: -290201 | O45: -290201 | P45: -290201 | Q45: -290201 | R45: -290201 | S45: -290201 | T45: -290201 | U45: -290201 | V45: -290201 | W45: -290201
D48: -174440 | E48: -174440 | F48: -174440 | G48: -174440 | H48: -174440 | I48: -174440 | J48: -174440 | K48: -174440 | L48: -174440 | M48: -174440 | N48: -174440 | O48: -174440 | P48: -174440 | Q48: -174440 | R48: -174440 | S48: -174440 | T48: -174440 | U48: -174440 | V48: -174440 | W48: -174440
D49: -37940.7 | E49: -37940.7 | F49: -37940.7 | G49: -37940.7 | H49: -37940.7 | I49: -37940.7 | J49: -37940.7 | K49: -37940.7 | L49: -37940.7 | M49: -37940.7 | N49: -37940.7 | O49: -37940.7 | P49: -37940.7 | Q49: -37940.7 | R49: -37940.7 | S49: -37940.7 | T49: -37940.7 | U49: -37940.7 | V49: -37940.7 | W49: -37940.7
D50: -43610 | E50: -43610 | F50: -43610 | G50: -43610 | H50: -43610 | I50: -43610 | J50: -43610 | K50: -43610 | L50: -43610 | M50: -43610 | N50: 0 | O50: 0 | P50: 0 | Q50: 0 | R50: 0 | S50: 0 | T50: 0 | U50: 0 | V50: 0 | W50: 0
D54: =D77 -> 0 | E54: =E77 -> 0 | F54: =F77 -> 0 | G54: =G77 -> 0 | H54: =H77 -> 0 | I54: =I77 -> 0 | J54: =J77 -> 0 | K54: =K77 -> 0 | ... W54: =W77 -> 0
D70: 0 | E70: 0 | F70: 0 | G70: 0 | H70: 0 | I70: 0 | J70: 0 | K70: 0 | L70: 0 | M70: 0 | N70: 0 | O70: 0 | P70: 0 | Q70: 0 | R70: 0 | S70: 0 | T70: 0 | U70: 0 | V70: 0 | W70: 0

Sheet 淡江大學_p4_1
A1: 電站基本資料(請填寫著色處) | E1: 說明 | O1: =1-C11 -> 0.99 | P1: =O1-$C12 -> 0.986 | Q1: =P1-$C12 -> 0.982 | R1: =Q1-$C12 -> 0.978 | S1: =R1-$C12 -> 0.974 | T1: =S1-$C12 -> 0.97 | U1: =T1-$C12 -> 0.966 | V1: =U1-$C12 -> 0.962 | W1: =V1-$C12 -> 0.958 | ... AH1: =AG1-$C12 -> 0.914
A2: 電站名稱 | B2: 淡江大學 | C2: 淡江大學 | D2: - | E2: 填入本案場名稱
A3: 電站壽命 | B3: 20 | C3: 20 | D3: - | E3: 預設 20 年，代表財務評估年期。若合約年限不同可依實際情況修改
A4: 建置量(kWp) | B4: 436.1 | C4: 436.1 | D4: - | E4: 填入裝置容量（kWp），通常由設計圖面或報價書取得 | M4: 情境編號: 4
A5: 起始年度 | B5: 2020 | C5: 2020 | D5: =B5+B3-1 -> 2039 | E5: 2039 | M5: 第3次滾算摘要
M6: 價金: 29000
A7: 綜合損益表(請填寫著色處) | M7: 專案IRR: 4.39
A8: 收入 | M8: 權益法IRR: 10.59
A9: 收支項目 | B9: 相關參數 | C9: 參數數值 | D9: 年限 | E9: 說明 | M9: 利潤率: 30.00%
A10: 電費收入 | B10: 年度AC併網總發電量 | C10: 547002 | D10: 547002 | E10: 20 | M10: 第3次滾算，減少 2000 元 - 現金模式，每次減少 2000 元
B11: 首年衰退率 | C11: 0.01 | E11: 第一年發電衰退比率，請填小數（例：1% → 填 0.01）。一般首年衰退約 1~2%(請參考模組規格書)
B12: 次年衰退率 | C12: 0.004 | E12: 第二年起每年固定衰退比率，請填小數（例：0.4% → 填 0.004）。一般約 0.4~0.7%(請參考模組規格書)
B13: 躉售費率(FIT) / 綠電費率 | C13: 4 | E13: 與台電簽訂的躉購費率或綠電合約費率，單位：元/度。請參考台電公告或合約內容
A14: 支出(請填寫著色處)
A15: 收支項目 | B15: 相關參數 | C15: 參數數值 | D15: 攤提年限 | E15: 說明
A16: 設備費用(價金) | B16: 每kWp設備成本 | C16: 35000 | D16: 29000 | E16: 20
B17: 信邦利潤率(ex:20%填0.2) | C17: 0.3 | E17: 公司在設備費用上加計的利潤比率，請填小數（例：20% → 填 0.2）
B18: 開發費 | C18: 2000 | E18: 前期開發費用（元），含可行性評估、申請規費、地主溝通等。若無則填 0
A19: 租金費用 | B19: 租金計算方式 | C19: 1 | D19: 1 | E19: 0
B20: 【方式1參數】每年相同價格 | C20: 290201 | D20: 290201 | E20: 20
B21: 【方式2參數】抽成比率 | D21: 0 | E21: 0
A22: 運維費用 | B22: 每kw運維成本 | C22: 400 | D22: 400 | E22: 20
A23: 保險費用 | B23: 占整體設備費用比例 | C23: 0.003 | D23: 0.003 | E23: 20
A24: 模組回收費用 | B24: 每kw模組回收成本 | C24: 1000 | D24: 1000 | E24: 10
A25: 利息費用 | B25: 銀行利率 | C25: 0.0256 | D25: 0.0256 | E25: 0
A26: 所得稅 | B26: 所得稅率 | C26: 0.2 | D26: 0.2 | E26: 0
A29: 現金流量表(請填寫著色處)
A30: 金流項目 | B30: 相關參數 | C30: 參數數值 | E30: 說明
A31: 貸款成數 | B31: 占總設備費用比例 | C31: 0.8 | D31: 0.8 | E31: 貸款佔設備總費用比例，填小數（例：80% → 填 0.8）。預設 0.8 代表貸八成、自備二成
A32: 貸款還款 | B32: 攤還期數 | C32: 15 | D32: 15 | E32: 貸款還款年數（年）。預設 15 年，代表分 15 年平均攤還本金
A33: 現金股利 | B33: 股利比率 | C33: 0.9 | D33: 0.9 | E33: 稅後現金流中分配給股東的比例，填小數（例：90% → 填 0.9）
A34: 年底減資 | B34: 攤還期數 | C34: 4 | D34: 4 | E34: 年底減資返還股東的年數。預設 4 年，代表 倒數 4 年進行減資，加速資金返還
D37: 2020 | E37: 2021 | F37: 2022 | G37: 2023 | H37: 2024 | I37: 2025 | J37: 2026 | K37: 2027 | L37: 2028 | M37: 2029 | N37: 2030 | O37: 2031 | P37: 2032 | Q37: 2033 | R37: 2034 | S37: 2035 | T37: 2036 | U37: 2037 | V37: 2038 | W37: 2039
D45: -290201 | E45: -290201 | F45: -290201 | G45: -290201 | H45: -290201 | I45: -290201 | J45: -290201 | K45: -290201 | L45: -290201 | M45: -290201 | N45: -290201 | O45: -290201 | P45: -290201 | Q45: -290201 | R45: -290201 | S45: -290201 | T45: -290201 | U45: -290201 | V45: -290201 | W45: -290201
D48: -174440 | E48: -174440 | F48: -174440 | G48: -174440 | H48: -174440 | I48: -174440 | J48: -174440 | K48: -174440 | L48: -174440 | M48: -174440 | N48: -174440 | O48: -174440 | P48: -174440 | Q48: -174440 | R48: -174440 | S48: -174440 | T48: -174440 | U48: -174440 | V48: -174440 | W48: -174440
D49: -37940.7 | E49: -37940.7 | F49: -37940.7 | G49: -37940.7 | H49: -37940.7 | I49: -37940.7 | J49: -37940.7 | K49: -37940.7 | L49: -37940.7 | M49: -37940.7 | N49: -37940.7 | O49: -37940.7 | P49: -37940.7 | Q49: -37940.7 | R49: -37940.7 | S49: -37940.7 | T49: -37940.7 | U49: -37940.7 | V49: -37940.7 | W49: -37940.7
D50: -43610 | E50: -43610 | F50: -43610 | G50: -43610 | H50: -43610 | I50: -43610 | J50: -43610 | K50: -43610 | L50: -43610 | M50: -43610 | N50: 0 | O50: 0 | P50: 0 | Q50: 0 | R50: 0 | S50: 0 | T50: 0 | U50: 0 | V50: 0 | W50: 0
D54: =D77 -> 0 | E54: =E77 -> 0 | F54: =F77 -> 0 | G54: =G77 -> 0 | H54: =H77 -> 0 | I54: =I77 -> 0 | J54: =J77 -> 0 | K54: =K77 -> 0 | ... W54: =W77 -> 0
D70: 0 | E70: 0 | F70: 0 | G70: 0 | H70: 0 | I70: 0 | J70: 0 | K70: 0 | L70: 0 | M70: 0 | N70: 0 | O70: 0 | P70: 0 | Q70: 0 | R70: 0 | S70: 0 | T70: 0 | U70: 0 | V70: 0 | W70: 0

Sheet 淡江大學_p4_2
A1: 電站基本資料(請填寫著色處) | E1: 說明 | O1: =1-C11 -> 0.99 | P1: =O1-$C12 -> 0.986 | Q1: =P1-$C12 -> 0.982 | R1: =Q1-$C12 -> 0.978 | S1: =R1-$C12 -> 0.974 | T1: =S1-$C12 -> 0.97 | U1: =T1-$C12 -> 0.966 | V1: =U1-$C12 -> 0.962 | W1: =V1-$C12 -> 0.958 | ... AH1: =AG1-$C12 -> 0.914
A2: 電站名稱 | B2: 淡江大學 | C2: 淡江大學 | D2: - | E2: 填入本案場名稱
A3: 電站壽命 | B3: 20 | C3: 20 | D3: - | E3: 預設 20 年，代表財務評估年期。若合約年限不同可依實際情況修改
A4: 建置量(kWp) | B4: 436.1 | C4: 436.1 | D4: - | E4: 填入裝置容量（kWp），通常由設計圖面或報價書取得 | M4: 情境編號: 4
A5: 起始年度 | B5: 2020 | C5: 2020 | D5: =B5+B3-1 -> 2039 | E5: 2039 | M5: 第3次滾算摘要
M6: 價金: 29000
A7: 綜合損益表(請填寫著色處) | M7: 專案IRR: 4.39
A8: 收入 | M8: 權益法IRR: 10.59
A9: 收支項目 | B9: 相關參數 | C9: 參數數值 | D9: 年限 | E9: 說明 | M9: 利潤率: 30.00%
A10: 電費收入 | B10: 年度AC併網總發電量 | C10: 547002 | D10: 547002 | E10: 20 | M10: 第3次滾算，減少 2000 元 - 現金模式，每次減少 2000 元
B11: 首年衰退率 | C11: 0.01 | E11: 第一年發電衰退比率，請填小數（例：1% → 填 0.01）。一般首年衰退約 1~2%(請參考模組規格書)
B12: 次年衰退率 | C12: 0.004 | E12: 第二年起每年固定衰退比率，請填小數（例：0.4% → 填 0.004）。一般約 0.4~0.7%(請參考模組規格書)
B13: 躉售費率(FIT) / 綠電費率 | C13: 4 | E13: 與台電簽訂的躉購費率或綠電合約費率，單位：元/度。請參考台電公告或合約內容
A14: 支出(請填寫著色處)
A15: 收支項目 | B15: 相關參數 | C15: 參數數值 | D15: 攤提年限 | E15: 說明
A16: 設備費用(價金) | B16: 每kWp設備成本 | C16: 35000 | D16: 29000 | E16: 20
B17: 信邦利潤率(ex:20%填0.2) | C17: 0.3 | E17: 公司在設備費用上加計的利潤比率，請填小數（例：20% → 填 0.2）
B18: 開發費 | C18: 2000 | E18: 前期開發費用（元），含可行性評估、申請規費、地主溝通等。若無則填 0
A19: 租金費用 | B19: 租金計算方式 | C19: 1 | D19: 1 | E19: 0
B20: 【方式1參數】每年相同價格 | C20: 290201 | D20: 290201 | E20: 20
B21: 【方式2參數】抽成比率 | D21: 0 | E21: 0
A22: 運維費用 | B22: 每kw運維成本 | C22: 400 | D22: 400 | E22: 20
A23: 保險費用 | B23: 占整體設備費用比例 | C23: 0.003 | D23: 0.003 | E23: 20
A24: 模組回收費用 | B24: 每kw模組回收成本 | C24: 1000 | D24: 1000 | E24: 10
A25: 利息費用 | B25: 銀行利率 | C25: 0.0256 | D25: 0.0256 | E25: 0
A26: 所得稅 | B26: 所得稅率 | C26: 0.2 | D26: 0.2 | E26: 0
A29: 現金流量表(請填寫著色處)
A30: 金流項目 | B30: 相關參數 | C30: 參數數值 | E30: 說明
A31: 貸款成數 | B31: 占總設備費用比例 | C31: 0.8 | D31: 0.8 | E31: 貸款佔設備總費用比例，填小數（例：80% → 填 0.8）。預設 0.8 代表貸八成、自備二成
A32: 貸款還款 | B32: 攤還期數 | C32: 15 | D32: 15 | E32: 貸款還款年數（年）。預設 15 年，代表分 15 年平均攤還本金
A33: 現金股利 | B33: 股利比率 | C33: 0.9 | D33: 0.9 | E33: 稅後現金流中分配給股東的比例，填小數（例：90% → 填 0.9）
A34: 年底減資 | B34: 攤還期數 | C34: 4 | D34: 4 | E34: 年底減資返還股東的年數。預設 4 年，代表 倒數 4 年進行減資，加速資金返還
D37: 2020 | E37: 2021 | F37: 2022 | G37: 2023 | H37: 2024 | I37: 2025 | J37: 2026 | K37: 2027 | L37: 2028 | M37: 2029 | N37: 2030 | O37: 2031 | P37: 2032 | Q37: 2033 | R37: 2034 | S37: 2035 | T37: 2036 | U37: 2037 | V37: 2038 | W37: 2039
D45: -290201 | E45: -290201 | F45: -290201 | G45: -290201 | H45: -290201 | I45: -290201 | J45: -290201 | K45: -290201 | L45: -290201 | M45: -290201 | N45: -290201 | O45: -290201 | P45: -290201 | Q45: -290201 | R45: -290201 | S45: -290201 | T45: -290201 | U45: -290201 | V45: -290201 | W45: -290201
D48: -174440 | E48: -174440 | F48: -174440 | G48: -174440 | H48: -174440 | I48: -174440 | J48: -174440 | K48: -174440 | L48: -174440 | M48: -174440 | N48: -174440 | O48: -174440 | P48: -174440 | Q48: -174440 | R48: -174440 | S48: -174440 | T48: -174440 | U48: -174440 | V48: -174440 | W48: -174440
D49: -37940.7 | E49: -37940.7 | F49: -37940.7 | G49: -37940.7 | H49: -37940.7 | I49: -37940.7 | J49: -37940.7 | K49: -37940.7 | L49: -37940.7 | M49: -37940.7 | N49: -37940.7 | O49: -37940.7 | P49: -37940.7 | Q49: -37940.7 | R49: -37940.7 | S49: -37940.7 | T49: -37940.7 | U49: -37940.7 | V49: -37940.7 | W49: -37940.7
D50: -43610 | E50: -43610 | F50: -43610 | G50: -43610 | H50: -43610 | I50: -43610 | J50: -43610 | K50: -43610 | L50: -43610 | M50: -43610 | N50: 0 | O50: 0 | P50: 0 | Q50: 0 | R50: 0 | S50: 0 | T50: 0 | U50: 0 | V50: 0 | W50: 0
D54: =D77 -> 0 | E54: =E77 -> 0 | F54: =F77 -> 0 | G54: =G77 -> 0 | H54: =H77 -> 0 | I54: =I77 -> 0 | J54: =J77 -> 0 | K54: =K77 -> 0 | ... W54: =W77 -> 0
D70: 0 | E70: 0 | F70: 0 | G70: 0 | H70: 0 | I70: 0 | J70: 0 | K70: 0 | L70: 0 | M70: 0 | N70: 0 | O70: 0 | P70: 0 | Q70: 0 | R70: 0 | S70: 0 | T70: 0 | U70: 0 | V70: 0 | W70: 0

Sheet 淡江大學_p6_1
A1: 電站基本資料(請填寫著色處) | E1: 說明 | O1: =1-C11 -> 0.99 | P1: =O1-$C12 -> 0.986 | Q1: =P1-$C12 -> 0.982 | R1: =Q1-$C12 -> 0.978 | S1: =R1-$C12 -> 0.974 | T1: =S1-$C12 -> 0.97 | U1: =T1-$C12 -> 0.966 | V1: =U1-$C12 -> 0.962 | W1: =V1-$C12 -> 0.958 | ... AH1: =AG1-$C12 -> 0.914
A2: 電站名稱 | B2: 淡江大學 | C2: 淡江大學 | D2: - | E2: 填入本案場名稱
A3: 電站壽命 | B3: 20 | C3: 20 | D3: - | E3: 預設 20 年，代表財務評估年期。若合約年限不同可依實際情況修改
A4: 建置量(kWp) | B4: 436.1 | C4: 436.1 | D4: - | E4: 填入裝置容量（kWp），通常由設計圖面或報價書取得 | M4: 情境編號: 6
A5: 起始年度 | B5: 2020 | C5: 2020 | D5: =B5+B3-1 -> 2039 | E5: 2039 | M5: 第5次滾算摘要
M6: 價金: 25000
A7: 綜合損益表(請填寫著色處) | M7: 專案IRR: 5.91
A8: 收入 | M8: 權益法IRR: 17.0
A9: 收支項目 | B9: 相關參數 | C9: 參數數值 | D9: 年限 | E9: 說明 | M9: 利潤率: 30.00%
A10: 電費收入 | B10: 年度AC併網總發電量 | C10: 547002 | D10: 547002 | E10: 20 | M10: 第5次滾算，減少 2000 元 - 現金模式，每次減少 2000 元
B11: 首年衰退率 | C11: 0.01 | E11: 第一年發電衰退比率，請填小數（例：1% → 填 0.01）。一般首年衰退約 1~2%(請參考模組規格書)
B12: 次年衰退率 | C12: 0.004 | E12: 第二年起每年固定衰退比率，請填小數（例：0.4% → 填 0.004）。一般約 0.4~0.7%(請參考模組規格書)
B13: 躉售費率(FIT) / 綠電費率 | C13: 4 | E13: 與台電簽訂的躉購費率或綠電合約費率，單位：元/度。請參考台電公告或合約內容
A14: 支出(請填寫著色處)
A15: 收支項目 | B15: 相關參數 | C15: 參數數值 | D15: 攤提年限 | E15: 說明
A16: 設備費用(價金) | B16: 每kWp設備成本 | C16: 35000 | D16: 25000 | E16: 20
B17: 信邦利潤率(ex:20%填0.2) | C17: 0.3 | E17: 公司在設備費用上加計的利潤比率，請填小數（例：20% → 填 0.2）
B18: 開發費 | C18: 2000 | E18: 前期開發費用（元），含可行性評估、申請規費、地主溝通等。若無則填 0
A19: 租金費用 | B19: 租金計算方式 | C19: 1 | D19: 1 | E19: 0
B20: 【方式1參數】每年相同價格 | C20: 290201 | D20: 290201 | E20: 20
B21: 【方式2參數】抽成比率 | D21: 0 | E21: 0
A22: 運維費用 | B22: 每kw運維成本 | C22: 400 | D22: 400 | E22: 20
A23: 保險費用 | B23: 占整體設備費用比例 | C23: 0.003 | D23: 0.003 | E23: 20
A24: 模組回收費用 | B24: 每kw模組回收成本 | C24: 1000 | D24: 1000 | E24: 10
A25: 利息費用 | B25: 銀行利率 | C25: 0.0256 | D25: 0.0256 | E25: 0
A26: 所得稅 | B26: 所得稅率 | C26: 0.2 | D26: 0.2 | E26: 0
A29: 現金流量表(請填寫著色處)
A30: 金流項目 | B30: 相關參數 | C30: 參數數值 | E30: 說明
A31: 貸款成數 | B31: 占總設備費用比例 | C31: 0.8 | D31: 0.8 | E31: 貸款佔設備總費用比例，填小數（例：80% → 填 0.8）。預設 0.8 代表貸八成、自備二成
A32: 貸款還款 | B32: 攤還期數 | C32: 15 | D32: 15 | E32: 貸款還款年數（年）。預設 15 年，代表分 15 年平均攤還本金
A33: 現金股利 | B33: 股利比率 | C33: 0.9 | D33: 0.9 | E33: 稅後現金流中分配給股東的比例，填小數（例：90% → 填 0.9）
A34: 年底減資 | B34: 攤還期數 | C34: 4 | D34: 4 | E34: 年底減資返還股東的年數。預設 4 年，代表 倒數 4 年進行減資，加速資金返還
D37: 2020 | E37: 2021 | F37: 2022 | G37: 2023 | H37: 2024 | I37: 2025 | J37: 2026 | K37: 2027 | L37: 2028 | M37: 2029 | N37: 2030 | O37: 2031 | P37: 2032 | Q37: 2033 | R37: 2034 | S37: 2035 | T37: 2036 | U37: 2037 | V37: 2038 | W37: 2039
D45: -290201 | E45: -290201 | F45: -290201 | G45: -290201 | H45: -290201 | I45: -290201 | J45: -290201 | K45: -290201 | L45: -290201 | M45: -290201 | N45: -290201 | O45: -290201 | P45: -290201 | Q45: -290201 | R45: -290201 | S45: -290201 | T45: -290201 | U45: -290201 | V45: -290201 | W45: -290201
D48: -174440 | E48: -174440 | F48: -174440 | G48: -174440 | H48: -174440 | I48: -174440 | J48: -174440 | K48: -174440 | L48: -174440 | M48: -174440 | N48: -174440 | O48: -174440 | P48: -174440 | Q48: -174440 | R48: -174440 | S48: -174440 | T48: -174440 | U48: -174440 | V48: -174440 | W48: -174440
D49: -32707.5 | E49: -32707.5 | F49: -32707.5 | G49: -32707.5 | H49: -32707.5 | I49: -32707.5 | J49: -32707.5 | K49: -32707.5 | L49: -32707.5 | M49: -32707.5 | N49: -32707.5 | O49: -32707.5 | P49: -32707.5 | Q49: -32707.5 | R49: -32707.5 | S49: -32707.5 | T49: -32707.5 | U49: -32707.5 | V49: -32707.5 | W49: -32707.5
D50: -43610 | E50: -43610 | F50: -43610 | G50: -43610 | H50: -43610 | I50: -43610 | J50: -43610 | K50: -43610 | L50: -43610 | M50: -43610 | N50: 0 | O50: 0 | P50: 0 | Q50: 0 | R50: 0 | S50: 0 | T50: 0 | U50: 0 | V50: 0 | W50: 0
D54: =D77 -> 0 | E54: =E77 -> 0 | F54: =F77 -> 0 | G54: =G77 -> 0 | H54: =H77 -> 0 | I54: =I77 -> 0 | J54: =J77 -> 0 | K54: =K77 -> 0 | ... W54: =W77 -> 0
D70: 0 | E70: 0 | F70: 0 | G70: 0 | H70: 0 | I70: 0 | J70: 0 | K70: 0 | L70: 0 | M70: 0 | N70: 0 | O70: 0 | P70: 0 | Q70: 0 | R70: 0 | S70: 0 | T70: 0 | U70: 0 | V70: 0 | W70: 0

Sheet 淡江大學_p4_3
B1: 電站基本資料 | F1: 說明 | P1: =1-D11 -> 0.99 | Q1: =P1-$D12 -> 0.986 | R1: =Q1-$D12 -> 0.982 | S1: =R1-$D12 -> 0.978 | T1: =S1-$D12 -> 0.974 | U1: =T1-$D12 -> 0.97 | V1: =U1-$D12 -> 0.966 | W1: =V1-$D12 -> 0.962 | X1: =W1-$D12 -> 0.958 | ... AI1: =AH1-$D12 -> 0.914
B2: 電站名稱 | C2: 淡江大學 | D2: - | E2: - | F2: 填入本案場名稱
B3: 電站壽命 | C3: 20 | D3: - | E3: - | F3: 預設 20 年，代表財務評估年期。若合約年限不同可依實際情況修改
B4: 建置量(kWp) | C4: 436.1 | D4: - | E4: - | F4: 填入裝置容量（kWp），通常由設計圖面或報價書取得 | M4: 情境編號: 4
B5: 起始年度 | C5: 2020 | D5: 結束年度 | E5: 2039 | F5: 填入電站預計掛表的西元年份（例：2025）。結束年度會自動計算 | M5: 第3次滾算摘要
M6: 價金: 29000
B7: 綜合損益表 | M7: 專案IRR: 4.39
B8: 收入 | M8: 權益法IRR: 10.59
B9: 收支項目 | C9: 相關參數 | D9: 參數數值 | E9: 年限 | F9: 說明 | M9: 利潤率: 30.00%
B10: 電費收入 | C10: 年度AC併網總發電量 | D10: 547002 | E10: 20 | F10: 預估年發電量（kWh），通常來自 PVsyst 模擬或估算：裝置容量 × 年日照時數 × 系統效率 | M10: 第3次滾算，減少 2000 元 - 現金模式，每次減少 2000 元
C11: 首年衰退率 | D11: 0.01 | F11: 第一年發電衰退比率，請填小數（例：1% → 填 0.01）。一般首年衰退約 1~2%(請參考模組規格書)
C12: 次年衰退率 | D12: 0.004 | F12: 第二年起每年固定衰退比率，請填小數（例：0.4% → 填 0.004）。一般約 0.4~0.7%(請參考模組規格書)
C13: 躉售費率(FIT) / 綠電費率 | D13: 4 | F13: 與台電簽訂的躉購費率或綠電合約費率，單位：元/度。請參考台電公告或合約內容
B14: 支出
B15: 收支項目 | C15: 相關參數 | D15: 參數數值 | E15: 攤提年限 | F15: 說明
B16: 設備費用(價金) | C16: 每kWp設備成本 | D16: 29000 | E16: 20 | F16: 每峰瓩設備成本（元/kWp），包含模組、逆變器、支架等硬體，不含工程施工費
C17: 信邦利潤率(ex:20%填0.2) | D17: 0.3 | F17: 公司在設備費用上加計的利潤比率，請填小數（例：20% → 填 0.2）
C18: 開發費 | D18: 2000 | F18: 前期開發費用（元），含可行性評估、申請規費、地主溝通等。若無則填 0
B19: 租金費用 | C19: 租金計算方式 | D19: 1 | E19: 20 | F19: 填 1 = 固定年租金（需填方式1參數）；填 2 = 依電費收入抽成（需填方式2參數）
C20: 【方式1參數】每年相同價格 | D20: 290201 | E20: 20 | F20: 租金計算方式選「1」時填寫，固定年租金金額（元/年），套用至整個電站壽命期
C21: 【方式2參數】抽成比率 | D21: 0 | E21: 20 | F21: 租金計算方式選「2」時填寫，請填小數（例：10% → 填 0.1）。租金 = 當年電費收入 × 抽成比率
B22: 運維費用 | C22: 每kw運維成本 | D22: 400 | E22: 20 | F22: 每峰瓩每年運維費用（元/kWp/年），含清洗、巡檢、維修等。
B23: 保險費用 | C23: 占整體設備費用比例 | D23: 0.003 | E23: 20 | F23: 保險費佔設備總費用比率，填小數（例：0.3% → 填 0.003）。預設 0.003，可依投保條件調整
B24: 模組回收費用 | C24: 每kw模組回收成本 | D24: 1000 | E24: 10 | F24: 每峰瓩模組廢棄回收費用（元/kWp），於第 1~10 年計提（攤提 10 年）。
B25: 利息費用 | C25: 銀行利率 | D25: 0.0256 | E25: 20 | F25: 向銀行貸款的年利率，填小數（例：2.56% → 填 0.0256）。請依銀行核准利率填入
B26: 所得稅 | C26: 所得稅率 | D26: 0.2 | E26: 20 | F26: 公司所得稅率，填小數（例：20% → 填 0.2）。預設 0.2，通常不需更改
B29: 現金流量表
B30: 金流項目 | C30: 相關參數 | D30: 參數數值 | F30: 說明
B31: 貸款成數 | C31: 占總設備費用比例 | D31: 0.8 | F31: 貸款佔設備總費用比例，填小數（例：80% → 填 0.8）。預設 0.8 代表貸八成、自備二成
B32: 貸款還款 | C32: 攤還期數 | D32: 15 | F32: 貸款還款年數（年）。預設 15 年，代表分 15 年平均攤還本金
B33: 現金股利 | C33: 股利比率 | D33: 0.9 | F33: 稅後現金流中分配給股東的比例，填小數（例：90% → 填 0.9）
B34: 年底減資 | C34: 攤還期數 | D34: 4 | F34: 年底減資返還股東的年數。預設 4 年，代表 倒數 4 年進行減資，加速資金返還
C37: 年份 | D37: 2020 | E37: 2021 | F37: 2022 | G37: 2023 | H37: 2024 | I37: 2025 | J37: 2026 | K37: 2027 | L37: 2028 | M37: 2029 | N37: 2030 | O37: 2031 | P37: 2032 | Q37: 2033 | R37: 2034 | S37: 2035 | T37: 2036 | U37: 2037 | V37: 2038 | W37: 2039
B38: 0
B39: (Unit : Currency) | C39: 0 | D39: 1 | E39: 2 | F39: 3 | G39: 4 | H39: 5 | I39: 6 | J39: 7 | K39: 8 | L39: 9 | M39: 10 | N39: 11 | O39: 12 | P39: 13 | Q39: 14 | R39: 15 | S39: 16 | T39: 17 | U39: 18 | V39: 19 | W39: 20
B40: 發電度數(KWH) | C40: 0 | D40: =$D$10*P1 -> 541531.98 | E40: =$D$10*Q1 -> 539343.97 | F40: =$D$10*R1 -> 537155.96 | G40: =$D$10*S1 -> 534967.96 | H40: =$D$10*T1 -> 532779.95 | I40: =$D$10*U1 -> 530591.94 | J40: =$D$10*V1 -> 528403.93 | K40: =$D$10*W1 -> 526215.92 | ... W40: =$D$10*AI1 -> 499959.83
B41: Inflow : 電費收入 | C41: - | D41: =D40*$D$13 -> 2166127.9 | E41: =E40*$D$13 -> 2157375.9 | F41: =F40*$D$13 -> 2148623.9 | G41: =G40*$D$13 -> 2139871.8 | H41: =H40*$D$13 -> 2131119.8 | I41: =I40*$D$13 -> 2122367.8 | J41: =J40*$D$13 -> 2113615.7 | K41: =K40*$D$13 -> 2104863.7 | ... W41: =W40*$D$13 -> 1999839.3
B42: Inflow : 政府補助 | C42: - | G42: - | H42: - | I42: - | J42: - | K42: - | L42: - | M42: - | N42: - | O42: - | P42: - | Q42: - | R42: - | S42: - | T42: - | U42: - | V42: - | W42: -
B43: Inflow : 銀行借款
B44: Outflow : 設備費用 | C44: =-(D16/(1-D17)+D18)*C4 -> -18939200
B45: Outflow : 設備放置區域租金 | C45: - | D45: -290201 | E45: -290201 | F45: -290201 | G45: -290201 | H45: -290201 | I45: -290201 | J45: -290201 | K45: -290201 | L45: -290201 | M45: -290201 | N45: -290201 | O45: -290201 | P45: -290201 | Q45: -290201 | R45: -290201 | S45: -290201 | T45: -290201 | U45: -290201 | V45: -290201 | W45: -290201
B46: Outflow : 返還借款
B47: Outflow : 利息費用 | C47: -
B48: Outflow : 維運費 | C48: - | D48: -174440 | E48: -174440 | F48: -174440 | G48: -174440 | H48: -174440 | I48: -174440 | J48: -174440 | K48: -174440 | L48: -174440 | M48: -174440 | N48: -174440 | O48: -174440 | P48: -174440 | Q48: -174440 | R48: -174440 | S48: -174440 | T48: -174440 | U48: -174440 | V48: -174440 | W48: -174440
B49: Outflow : 保險費 | C49: - | D49: -37940.7 | E49: -37940.7 | F49: -37940.7 | G49: -37940.7 | H49: -37940.7 | I49: -37940.7 | J49: -37940.7 | K49: -37940.7 | L49: -37940.7 | M49: -37940.7 | N49: -37940.7 | O49: -37940.7 | P49: -37940.7 | Q49: -37940.7 | R49: -37940.7 | S49: -37940.7 | T49: -37940.7 | U49: -37940.7 | V49: -37940.7 | W49: -37940.7
B50: Outflow : 模組回收費 | D50: -43610 | E50: -43610 | F50: -43610 | G50: -43610 | H50: -43610 | I50: -43610 | J50: -43610 | K50: -43610 | L50: -43610 | M50: -43610 | N50: 0 | O50: 0 | P50: 0 | Q50: 0 | R50: 0 | S50: 0 | T50: 0 | U50: 0 | V50: 0 | W50: 0
B51: Outflow : 其它費用(人事薪資…等)
B52: 1%管理費
B53: 績效獎金
B54: 所得稅20% | D54: =D77 -> -192635.44 | E54: =E77 -> -132844.84 | F54: =F77 -> -131094.43 | G54: =G77 -> -129344.02 | H54: =H77 -> -127593.62 | I54: =I77 -> -125843.21 | J54: =J77 -> -124092.81 | K54: =K77 -> -122342.4 | ... W54: =W77 -> -110059.52
B55: 現金流 | C55: =C44 -> -18939200 | D55: =SUM(D41:D54) -> 1427300.8 | E55: =SUM(E41:E54) -> 1478339.4 | F55: =SUM(F41:F54) -> 1471337.7 | G55: =SUM(G41:G54) -> 1464336.1 | H55: =SUM(H41:H54) -> 1457334.5 | I55: =SUM(I41:I54) -> 1450332.8 | J55: =SUM(J41:J54) -> 1443331.2 | K55: =SUM(K41:K54) -> 1436329.6 | ... W55: =SUM(W41:W54) -> 1387198.1
B56: 累計現金流 | D56: =C55+D55 -> -17511899 | E56: =D56+E55 -> -16033560 | F56: =E56+F55 -> -14562222 | G56: =F56+G55 -> -13097886 | H56: =G56+H55 -> -11640552 | I56: =H56+I55 -> -10190219 | J56: =I56+J55 -> -8746887.5 | K56: =J56+K55 -> -7310557.9 | L56: =K56+L55 -> -5881229.9 | ... X56: =W56+X55 -> 9728150.5
B57: 回收年限評估 | D57: =IF((D56)>0,"回收","未回收") -> 未回收 | E57: =IF((E56)>0,"回收","未回收") -> 未回收 | F57: =IF((F56)>0,"回收","未回收") -> 未回收 | G57: =IF((G56)>0,"回收","未回收") -> 未回收 | H57: =IF((H56)>0,"回收","未回收") -> 未回收 | I57: =IF((I56)>0,"回收","未回收") -> 未回收 | J57: =IF((J56)>0,"回收","未回收") -> 未回收 | K57: =IF((K56)>0,"回收","未回收") -> 未回收 | ... X57: =IF((X56)>0,"回收","未回收") -> 回收
B58: 專案法IRR | C58: =IRR(C55:W55) -> 0.043586467
C60: 年份 | D60: =D37 -> 2020 | E60: =E37 -> 2021 | F60: =F37 -> 2022 | G60: =G37 -> 2023 | H60: =H37 -> 2024 | I60: =I37 -> 2025 | J60: =J37 -> 2026 | K60: =K37 -> 2027 | ... W60: =W37 -> 2039
B61: 0 | T61: 償還年限
B62: (Unit : Currency) | C62: 0 | D62: 1 | E62: 2 | F62: 3 | G62: 4 | H62: 5 | I62: 6 | J62: 7 | K62: 8 | L62: 9 | M62: 10 | N62: 11 | O62: 12 | P62: 13 | Q62: 14 | R62: 15 | S62: 16 | T62: 17 | U62: 18 | V62: 19 | W62: 20
B63: 發電度數(KWH) | C63: 0 | D63: =D40 -> 541531.98 | E63: =E40 -> 539343.97 | F63: =F40 -> 537155.96 | G63: =G40 -> 534967.96 | H63: =H40 -> 532779.95 | I63: =I40 -> 530591.94 | J63: =J40 -> 528403.93 | K63: =K40 -> 526215.92 | ... W63: =W40 -> 499959.83
B64: Inflow : 電費收入 | C64: - | D64: =D41 -> 2166127.9 | E64: =E41 -> 2157375.9 | F64: =F41 -> 2148623.9 | G64: =G41 -> 2139871.8 | H64: =H41 -> 2131119.8 | I64: =I41 -> 2122367.8 | J64: =J41 -> 2113615.7 | K64: =K41 -> 2104863.7 | ... W64: =W41 -> 1999839.3
B65: Inflow : 政府補助 | C65: - | G65: - | H65: - | I65: - | J65: - | K65: - | L65: - | M65: - | N65: - | O65: - | P65: - | Q65: - | R65: - | S65: - | T65: - | U65: - | V65: - | W65: -
B66: Inflow : 銀行借款
B67: Outflow : 設備折舊 | D67: =$C$44/$E$16 -> -946960 | E67: =$C$44/$E$16 -> -946960 | F67: =$C$44/$E$16 -> -946960 | G67: =$C$44/$E$16 -> -946960 | H67: =$C$44/$E$16 -> -946960 | I67: =$C$44/$E$16 -> -946960 | J67: =$C$44/$E$16 -> -946960 | K67: =$C$44/$E$16 -> -946960 | ... W67: =$C$44/$E$16 -> -946960
B68: Outflow : 設備放置區域租金 | C68: - | D68: =D44 -> 0 | E68: =E45 -> -290201 | F68: =F45 -> -290201 | G68: =G45 -> -290201 | H68: =H45 -> -290201 | I68: =I45 -> -290201 | J68: =J45 -> -290201 | K68: =K45 -> -290201 | L68: =L45 -> -290201 | ... W68: =W45 -> -290201
B69: Outflow : 返還借款
B70: Outflow : 利息費用 | C70: - | D70: 0 | E70: 0 | F70: 0 | G70: 0 | H70: 0 | I70: 0 | J70: 0 | K70: 0 | L70: 0 | M70: 0 | N70: 0 | O70: 0 | P70: 0 | Q70: 0 | R70: 0 | S70: 0 | T70: 0 | U70: 0 | V70: 0 | W70: 0
B71: Outflow : 維運費 | C71: - | D71: =D48 -> -174440 | E71: =E48 -> -174440 | F71: =F48 -> -174440 | G71: =G48 -> -174440 | H71: =H48 -> -174440 | I71: =I48 -> -174440 | J71: =J48 -> -174440 | K71: =K48 -> -174440 | ... W71: =W48 -> -174440
B72: Outflow : 保險費 | C72: - | D72: =D49 -> -37940.7 | E72: =E49 -> -37940.7 | F72: =F49 -> -37940.7 | G72: =G49 -> -37940.7 | H72: =H49 -> -37940.7 | I72: =I49 -> -37940.7 | J72: =J49 -> -37940.7 | K72: =K49 -> -37940.7 | ... W72: =W49 -> -37940.7
B73: Outflow : 模組回收費 | D73: =D50 -> -43610 | E73: =E50 -> -43610 | F73: =F50 -> -43610 | G73: =G50 -> -43610 | H73: =H50 -> -43610 | I73: =I50 -> -43610 | J73: =J50 -> -43610 | K73: =K50 -> -43610 | ... W73: =W50 -> 0
B74: Outflow : 其它費用(人事薪資…等)
B75: 1%管理費
B76: 稅前淨利 | D76: =SUM(D64:D75) -> 963177.22 | E76: =SUM(E64:E75) -> 664224.19 | F76: =SUM(F64:F75) -> 655472.16 | G76: =SUM(G64:G75) -> 646720.12 | H76: =SUM(H64:H75) -> 637968.09 | I76: =SUM(I64:I75) -> 629216.06 | J76: =SUM(J64:J75) -> 620464.03 | K76: =SUM(K64:K75) -> 611712 | ... X76: =SUM(X64:X75) -> 0
B77: 所得稅20% | D77: =-D76*0.2 -> -192635.44 | E77: =-E76*0.2 -> -132844.84 | F77: =-F76*0.2 -> -131094.43 | G77: =-G76*0.2 -> -129344.02 | H77: =-H76*0.2 -> -127593.62 | I77: =-I76*0.2 -> -125843.21 | J77: =-J76*0.2 -> -124092.81 | K77: =-K76*0.2 -> -122342.4 | ... X77: =-X76*0.2 -> 0
B78: 稅後淨利 | D78: =SUM(D76:D77) -> 770541.78 | E78: =SUM(E76:E77) -> 531379.35 | F78: =SUM(F76:F77) -> 524377.72 | G78: =SUM(G76:G77) -> 517376.1 | H78: =SUM(H76:H77) -> 510374.47 | I78: =SUM(I76:I77) -> 503372.85 | J78: =SUM(J76:J77) -> 496371.22 | K78: =SUM(K76:K77) -> 489369.6 | ... X78: =SUM(X76:X77) -> 0
B79: 累計現金流
B80: 回收年限評估

Sheet 淡江大學_p3_1
B1: 電站基本資料 | F1: 說明 | P1: =1-D11 -> 0.99 | Q1: =P1-$D12 -> 0.986 | R1: =Q1-$D12 -> 0.982 | S1: =R1-$D12 -> 0.978 | T1: =S1-$D12 -> 0.974 | U1: =T1-$D12 -> 0.97 | V1: =U1-$D12 -> 0.966 | W1: =V1-$D12 -> 0.962 | X1: =W1-$D12 -> 0.958 | ... AI1: =AH1-$D12 -> 0.914
B2: 電站名稱 | C2: 淡江大學 | D2: - | E2: - | F2: 填入本案場名稱
B3: 電站壽命 | C3: 20 | D3: - | E3: - | F3: 預設 20 年，代表財務評估年期。若合約年限不同可依實際情況修改
B4: 建置量(kWp) | C4: 436.1 | D4: - | E4: - | F4: 填入裝置容量（kWp），通常由設計圖面或報價書取得 | M4: 情境編號: 3
B5: 起始年度 | C5: 2020 | D5: 結束年度 | E5: 2039 | F5: 填入電站預計掛表的西元年份（例：2025）。結束年度會自動計算 | M5: 第2次滾算摘要
M6: 價金: 31000
B7: 綜合損益表 | M7: 專案IRR: 3.75
B8: 收入 | M8: 權益法IRR: 8.21
B9: 收支項目 | C9: 相關參數 | D9: 參數數值 | E9: 年限 | F9: 說明 | M9: 利潤率: 30.00%
B10: 電費收入 | C10: 年度AC併網總發電量 | D10: 547002 | E10: 20 | F10: 預估年發電量（kWh），通常來自 PVsyst 模擬或估算：裝置容量 × 年日照時數 × 系統效率 | M10: 第2次滾算，減少 2000 元 - 現金模式，每次減少 2000 元
C11: 首年衰退率 | D11: 0.01 | F11: 第一年發電衰退比率，請填小數（例：1% → 填 0.01）。一般首年衰退約 1~2%(請參考模組規格書)
C12: 次年衰退率 | D12: 0.004 | F12: 第二年起每年固定衰退比率，請填小數（例：0.4% → 填 0.004）。一般約 0.4~0.7%(請參考模組規格書)
C13: 躉售費率(FIT) / 綠電費率 | D13: 4 | F13: 與台電簽訂的躉購費率或綠電合約費率，單位：元/度。請參考台電公告或合約內容
B14: 支出
B15: 收支項目 | C15: 相關參數 | D15: 參數數值 | E15: 攤提年限 | F15: 說明
B16: 設備費用(價金) | C16: 每kWp設備成本 | D16: 31000 | E16: 20 | F16: 每峰瓩設備成本（元/kWp），包含模組、逆變器、支架等硬體，不含工程施工費
C17: 信邦利潤率(ex:20%填0.2) | D17: 0.3 | F17: 公司在設備費用上加計的利潤比率，請填小數（例：20% → 填 0.2）
C18: 開發費 | D18: 2000 | F18: 前期開發費用（元），含可行性評估、申請規費、地主溝通等。若無則填 0
B19: 租金費用 | C19: 租金計算方式 | D19: 1 | E19: 20 | F19: 填 1 = 固定年租金（需填方式1參數）；填 2 = 依電費收入抽成（需填方式2參數）
C20: 【方式1參數】每年相同價格 | D20: 290201 | E20: 20 | F20: 租金計算方式選「1」時填寫，固定年租金金額（元/年），套用至整個電站壽命期
C21: 【方式2參數】抽成比率 | D21: 0 | E21: 20 | F21: 租金計算方式選「2」時填寫，請填小數（例：10% → 填 0.1）。租金 = 當年電費收入 × 抽成比率
B22: 運維費用 | C22: 每kw運維成本 | D22: 400 | E22: 20 | F22: 每峰瓩每年運維費用（元/kWp/年），含清洗、巡檢、維修等。
B23: 保險費用 | C23: 占整體設備費用比例 | D23: 0.003 | E23: 20 | F23: 保險費佔設備總費用比率，填小數（例：0.3% → 填 0.003）。預設 0.003，可依投保條件調整
B24: 模組回收費用 | C24: 每kw模組回收成本 | D24: 1000 | E24: 10 | F24: 每峰瓩模組廢棄回收費用（元/kWp），於第 1~10 年計提（攤提 10 年）。
B25: 利息費用 | C25: 銀行利率 | D25: 0.0256 | E25: 20 | F25: 向銀行貸款的年利率，填小數（例：2.56% → 填 0.0256）。請依銀行核准利率填入
B26: 所得稅 | C26: 所得稅率 | D26: 0.2 | E26: 20 | F26: 公司所得稅率，填小數（例：20% → 填 0.2）。預設 0.2，通常不需更改
B29: 現金流量表
B30: 金流項目 | C30: 相關參數 | D30: 參數數值 | F30: 說明
B31: 貸款成數 | C31: 占總設備費用比例 | D31: 0.8 | F31: 貸款佔設備總費用比例，填小數（例：80% → 填 0.8）。預設 0.8 代表貸八成、自備二成
B32: 貸款還款 | C32: 攤還期數 | D32: 15 | F32: 貸款還款年數（年）。預設 15 年，代表分 15 年平均攤還本金
B33: 現金股利 | C33: 股利比率 | D33: 0.9 | F33: 稅後現金流中分配給股東的比例，填小數（例：90% → 填 0.9）
B34: 年底減資 | C34: 攤還期數 | D34: 4 | F34: 年底減資返還股東的年數。預設 4 年，代表 倒數 4 年進行減資，加速資金返還
C37: 年份 | D37: 2020 | E37: 2021 | F37: 2022 | G37: 2023 | H37: 2024 | I37: 2025 | J37: 2026 | K37: 2027 | L37: 2028 | M37: 2029 | N37: 2030 | O37: 2031 | P37: 2032 | Q37: 2033 | R37: 2034 | S37: 2035 | T37: 2036 | U37: 2037 | V37: 2038 | W37: 2039
B38: 0
B39: (Unit : Currency) | C39: 0 | D39: 1 | E39: 2 | F39: 3 | G39: 4 | H39: 5 | I39: 6 | J39: 7 | K39: 8 | L39: 9 | M39: 10 | N39: 11 | O39: 12 | P39: 13 | Q39: 14 | R39: 15 | S39: 16 | T39: 17 | U39: 18 | V39: 19 | W39: 20
B40: 發電度數(KWH) | C40: 0 | D40: =$D$10*P1 -> 541531.98 | E40: =$D$10*Q1 -> 539343.97 | F40: =$D$10*R1 -> 537155.96 | G40: =$D$10*S1 -> 534967.96 | H40: =$D$10*T1 -> 532779.95 | I40: =$D$10*U1 -> 530591.94 | J40: =$D$10*V1 -> 528403.93 | K40: =$D$10*W1 -> 526215.92 | ... W40: =$D$10*AI1 -> 499959.83
B41: Inflow : 電費收入 | C41: - | D41: =D40*$D$13 -> 2166127.9 | E41: =E40*$D$13 -> 2157375.9 | F41: =F40*$D$13 -> 2148623.9 | G41: =G40*$D$13 -> 2139871.8 | H41: =H40*$D$13 -> 2131119.8 | I41: =I40*$D$13 -> 2122367.8 | J41: =J40*$D$13 -> 2113615.7 | K41: =K40*$D$13 -> 2104863.7 | ... W41: =W40*$D$13 -> 1999839.3
B42: Inflow : 政府補助 | C42: - | G42: - | H42: - | I42: - | J42: - | K42: - | L42: - | M42: - | N42: - | O42: - | P42: - | Q42: - | R42: - | S42: - | T42: - | U42: - | V42: - | W42: -
B43: Inflow : 銀行借款
B44: Outflow : 設備費用 | C44: =-(D16/(1-D17)+D18)*C4 -> -20185200
B45: Outflow : 設備放置區域租金 | C45: - | D45: -290201 | E45: -290201 | F45: -290201 | G45: -290201 | H45: -290201 | I45: -290201 | J45: -290201 | K45: -290201 | L45: -290201 | M45: -290201 | N45: -290201 | O45: -290201 | P45: -290201 | Q45: -290201 | R45: -290201 | S45: -290201 | T45: -290201 | U45: -290201 | V45: -290201 | W45: -290201
B46: Outflow : 返還借款
B47: Outflow : 利息費用 | C47: -
B48: Outflow : 維運費 | C48: - | D48: -174440 | E48: -174440 | F48: -174440 | G48: -174440 | H48: -174440 | I48: -174440 | J48: -174440 | K48: -174440 | L48: -174440 | M48: -174440 | N48: -174440 | O48: -174440 | P48: -174440 | Q48: -174440 | R48: -174440 | S48: -174440 | T48: -174440 | U48: -174440 | V48: -174440 | W48: -174440
B49: Outflow : 保險費 | C49: - | D49: -40557.3 | E49: -40557.3 | F49: -40557.3 | G49: -40557.3 | H49: -40557.3 | I49: -40557.3 | J49: -40557.3 | K49: -40557.3 | L49: -40557.3 | M49: -40557.3 | N49: -40557.3 | O49: -40557.3 | P49: -40557.3 | Q49: -40557.3 | R49: -40557.3 | S49: -40557.3 | T49: -40557.3 | U49: -40557.3 | V49: -40557.3 | W49: -40557.3
B50: Outflow : 模組回收費 | D50: -43610 | E50: -43610 | F50: -43610 | G50: -43610 | H50: -43610 | I50: -43610 | J50: -43610 | K50: -43610 | L50: -43610 | M50: -43610 | N50: 0 | O50: 0 | P50: 0 | Q50: 0 | R50: 0 | S50: 0 | T50: 0 | U50: 0 | V50: 0 | W50: 0
B51: Outflow : 其它費用(人事薪資…等)
B52: 1%管理費
B53: 績效獎金
B54: 所得稅20% | D54: =D77 -> -179652.12 | E54: =E77 -> -119861.52 | F54: =F77 -> -118111.11 | G54: =G77 -> -116360.7 | H54: =H77 -> -114610.3 | I54: =I77 -> -112859.89 | J54: =J77 -> -111109.49 | K54: =K77 -> -109359.08 | ... W54: =W77 -> -97076.202
B55: 現金流 | C55: =C44 -> -20185200 | D55: =SUM(D41:D54) -> 1437667.5 | E55: =SUM(E41:E54) -> 1488706.1 | F55: =SUM(F41:F54) -> 1481704.4 | G55: =SUM(G41:G54) -> 1474702.8 | H55: =SUM(H41:H54) -> 1467701.2 | I55: =SUM(I41:I54) -> 1460699.6 | J55: =SUM(J41:J54) -> 1453697.9 | K55: =SUM(K41:K54) -> 1446696.3 | ... W55: =SUM(W41:W54) -> 1397564.8
B56: 累計現金流 | D56: =C55+D55 -> -18747533 | E56: =D56+E55 -> -17258826 | F56: =E56+F55 -> -15777122 | G56: =F56+G55 -> -14302419 | H56: =G56+H55 -> -12834718 | I56: =H56+I55 -> -11374018 | J56: =I56+J55 -> -9920320.5 | K56: =J56+K55 -> -8473624.1 | L56: =K56+L55 -> -7033929.5 | ... X56: =W56+X55 -> 8689484.9
B57: 回收年限評估 | D57: =IF((D56)>0,"回收","未回收") -> 未回收 | E57: =IF((E56)>0,"回收","未回收") -> 未回收 | F57: =IF((F56)>0,"回收","未回收") -> 未回收 | G57: =IF((G56)>0,"回收","未回收") -> 未回收 | H57: =IF((H56)>0,"回收","未回收") -> 未回收 | I57: =IF((I56)>0,"回收","未回收") -> 未回收 | J57: =IF((J56)>0,"回收","未回收") -> 未回收 | K57: =IF((K56)>0,"回收","未回收") -> 未回收 | ... X57: =IF((X56)>0,"回收","未回收") -> 回收
B58: 專案法IRR | C58: =IRR(C55:W55) -> 0.037139919
C60: 年份 | D60: =D37 -> 2020 | E60: =E37 -> 2021 | F60: =F37 -> 2022 | G60: =G37 -> 2023 | H60: =H37 -> 2024 | I60: =I37 -> 2025 | J60: =J37 -> 2026 | K60: =K37 -> 2027 | ... W60: =W37 -> 2039
B61: 0 | T61: 償還年限
B62: (Unit : Currency) | C62: 0 | D62: 1 | E62: 2 | F62: 3 | G62: 4 | H62: 5 | I62: 6 | J62: 7 | K62: 8 | L62: 9 | M62: 10 | N62: 11 | O62: 12 | P62: 13 | Q62: 14 | R62: 15 | S62: 16 | T62: 17 | U62: 18 | V62: 19 | W62: 20
B63: 發電度數(KWH) | C63: 0 | D63: =D40 -> 541531.98 | E63: =E40 -> 539343.97 | F63: =F40 -> 537155.96 | G63: =G40 -> 534967.96 | H63: =H40 -> 532779.95 | I63: =I40 -> 530591.94 | J63: =J40 -> 528403.93 | K63: =K40 -> 526215.92 | ... W63: =W40 -> 499959.83
B64: Inflow : 電費收入 | C64: - | D64: =D41 -> 2166127.9 | E64: =E41 -> 2157375.9 | F64: =F41 -> 2148623.9 | G64: =G41 -> 2139871.8 | H64: =H41 -> 2131119.8 | I64: =I41 -> 2122367.8 | J64: =J41 -> 2113615.7 | K64: =K41 -> 2104863.7 | ... W64: =W41 -> 1999839.3
B65: Inflow : 政府補助 | C65: - | G65: - | H65: - | I65: - | J65: - | K65: - | L65: - | M65: - | N65: - | O65: - | P65: - | Q65: - | R65: - | S65: - | T65: - | U65: - | V65: - | W65: -
B66: Inflow : 銀行借款
B67: Outflow : 設備折舊 | D67: =$C$44/$E$16 -> -1009260 | E67: =$C$44/$E$16 -> -1009260 | F67: =$C$44/$E$16 -> -1009260 | G67: =$C$44/$E$16 -> -1009260 | H67: =$C$44/$E$16 -> -1009260 | I67: =$C$44/$E$16 -> -1009260 | J67: =$C$44/$E$16 -> -1009260 | K67: =$C$44/$E$16 -> -1009260 | ... W67: =$C$44/$E$16 -> -1009260
B68: Outflow : 設備放置區域租金 | C68: - | D68: =D44 -> 0 | E68: =E45 -> -290201 | F68: =F45 -> -290201 | G68: =G45 -> -290201 | H68: =H45 -> -290201 | I68: =I45 -> -290201 | J68: =J45 -> -290201 | K68: =K45 -> -290201 | L68: =L45 -> -290201 | ... W68: =W45 -> -290201
B69: Outflow : 返還借款
B70: Outflow : 利息費用 | C70: - | D70: 0 | E70: 0 | F70: 0 | G70: 0 | H70: 0 | I70: 0 | J70: 0 | K70: 0 | L70: 0 | M70: 0 | N70: 0 | O70: 0 | P70: 0 | Q70: 0 | R70: 0 | S70: 0 | T70: 0 | U70: 0 | V70: 0 | W70: 0
B71: Outflow : 維運費 | C71: - | D71: =D48 -> -174440 | E71: =E48 -> -174440 | F71: =F48 -> -174440 | G71: =G48 -> -174440 | H71: =H48 -> -174440 | I71: =I48 -> -174440 | J71: =J48 -> -174440 | K71: =K48 -> -174440 | ... W71: =W48 -> -174440
B72: Outflow : 保險費 | C72: - | D72: =D49 -> -40557.3 | E72: =E49 -> -40557.3 | F72: =F49 -> -40557.3 | G72: =G49 -> -40557.3 | H72: =H49 -> -40557.3 | I72: =I49 -> -40557.3 | J72: =J49 -> -40557.3 | K72: =K49 -> -40557.3 | ... W72: =W49 -> -40557.3
B73: Outflow : 模組回收費 | D73: =D50 -> -43610 | E73: =E50 -> -43610 | F73: =F50 -> -43610 | G73: =G50 -> -43610 | H73: =H50 -> -43610 | I73: =I50 -> -43610 | J73: =J50 -> -43610 | K73: =K50 -> -43610 | ... W73: =W50 -> 0
B74: Outflow : 其它費用(人事薪資…等)
B75: 1%管理費
B76: 稅前淨利 | D76: =SUM(D64:D75) -> 898260.62 | E76: =SUM(E64:E75) -> 599307.59 | F76: =SUM(F64:F75) -> 590555.56 | G76: =SUM(G64:G75) -> 581803.52 | H76: =SUM(H64:H75) -> 573051.49 | I76: =SUM(I64:I75) -> 564299.46 | J76: =SUM(J64:J75) -> 555547.43 | K76: =SUM(K64:K75) -> 546795.4 | ... X76: =SUM(X64:X75) -> 0
B77: 所得稅20% | D77: =-D76*0.2 -> -179652.12 | E77: =-E76*0.2 -> -119861.52 | F77: =-F76*0.2 -> -118111.11 | G77: =-G76*0.2 -> -116360.7 | H77: =-H76*0.2 -> -114610.3 | I77: =-I76*0.2 -> -112859.89 | J77: =-J76*0.2 -> -111109.49 | K77: =-K76*0.2 -> -109359.08 | ... X77: =-X76*0.2 -> 0
B78: 稅後淨利 | D78: =SUM(D76:D77) -> 718608.5 | E78: =SUM(E76:E77) -> 479446.07 | F78: =SUM(F76:F77) -> 472444.44 | G78: =SUM(G76:G77) -> 465442.82 | H78: =SUM(H76:H77) -> 458441.19 | I78: =SUM(I76:I77) -> 451439.57 | J78: =SUM(J76:J77) -> 444437.94 | K78: =SUM(K76:K77) -> 437436.32 | ... X78: =SUM(X76:X77) -> 0
B79: 累計現金流
B80: 回收年限評估

Sheet 淡江大學_p5
B1: 電站基本資料 | F1: 說明 | P1: =1-D11 -> 0.99 | Q1: =P1-$D12 -> 0.986 | R1: =Q1-$D12 -> 0.982 | S1: =R1-$D12 -> 0.978 | T1: =S1-$D12 -> 0.974 | U1: =T1-$D12 -> 0.97 | V1: =U1-$D12 -> 0.966 | W1: =V1-$D12 -> 0.962 | X1: =W1-$D12 -> 0.958 | ... AI1: =AH1-$D12 -> 0.914
B2: 電站名稱 | C2: 淡江大學 | D2: - | E2: - | F2: 填入本案場名稱
B3: 電站壽命 | C3: 20 | D3: - | E3: - | F3: 預設 20 年，代表財務評估年期。若合約年限不同可依實際情況修改
B4: 建置量(kWp) | C4: 436.1 | D4: - | E4: - | F4: 填入裝置容量（kWp），通常由設計圖面或報價書取得 | M4: 情境編號: 5
B5: 起始年度 | C5: 2020 | D5: 結束年度 | E5: 2039 | F5: 填入電站預計掛表的西元年份（例：2025）。結束年度會自動計算 | M5: 第4次滾算摘要
M6: 價金: 27000
B7: 綜合損益表 | M7: 專案IRR: 5.11
B8: 收入 | M8: 權益法IRR: 13.45
B9: 收支項目 | C9: 相關參數 | D9: 參數數值 | E9: 年限 | F9: 說明 | M9: 利潤率: 30.00%
B10: 電費收入 | C10: 年度AC併網總發電量 | D10: 547002 | E10: 20 | F10: 預估年發電量（kWh），通常來自 PVsyst 模擬或估算：裝置容量 × 年日照時數 × 系統效率 | M10: 第4次滾算，減少 2000 元 - 現金模式，每次減少 2000 元
C11: 首年衰退率 | D11: 0.01 | F11: 第一年發電衰退比率，請填小數（例：1% → 填 0.01）。一般首年衰退約 1~2%(請參考模組規格書)
C12: 次年衰退率 | D12: 0.004 | F12: 第二年起每年固定衰退比率，請填小數（例：0.4% → 填 0.004）。一般約 0.4~0.7%(請參考模組規格書)
C13: 躉售費率(FIT) / 綠電費率 | D13: 4 | F13: 與台電簽訂的躉購費率或綠電合約費率，單位：元/度。請參考台電公告或合約內容
B14: 支出
B15: 收支項目 | C15: 相關參數 | D15: 參數數值 | E15: 攤提年限 | F15: 說明
B16: 設備費用(價金) | C16: 每kWp設備成本 | D16: 27000 | E16: 20 | F16: 每峰瓩設備成本（元/kWp），包含模組、逆變器、支架等硬體，不含工程施工費
C17: 信邦利潤率(ex:20%填0.2) | D17: 0.3 | F17: 公司在設備費用上加計的利潤比率，請填小數（例：20% → 填 0.2）
C18: 開發費 | D18: 2000 | F18: 前期開發費用（元），含可行性評估、申請規費、地主溝通等。若無則填 0
B19: 租金費用 | C19: 租金計算方式 | D19: 1 | E19: 20 | F19: 填 1 = 固定年租金（需填方式1參數）；填 2 = 依電費收入抽成（需填方式2參數）
C20: 【方式1參數】每年相同價格 | D20: 290201 | E20: 20 | F20: 租金計算方式選「1」時填寫，固定年租金金額（元/年），套用至整個電站壽命期
C21: 【方式2參數】抽成比率 | D21: 0 | E21: 20 | F21: 租金計算方式選「2」時填寫，請填小數（例：10% → 填 0.1）。租金 = 當年電費收入 × 抽成比率
B22: 運維費用 | C22: 每kw運維成本 | D22: 400 | E22: 20 | F22: 每峰瓩每年運維費用（元/kWp/年），含清洗、巡檢、維修等。
B23: 保險費用 | C23: 占整體設備費用比例 | D23: 0.003 | E23: 20 | F23: 保險費佔設備總費用比率，填小數（例：0.3% → 填 0.003）。預設 0.003，可依投保條件調整
B24: 模組回收費用 | C24: 每kw模組回收成本 | D24: 1000 | E24: 10 | F24: 每峰瓩模組廢棄回收費用（元/kWp），於第 1~10 年計提（攤提 10 年）。
B25: 利息費用 | C25: 銀行利率 | D25: 0.0256 | E25: 20 | F25: 向銀行貸款的年利率，填小數（例：2.56% → 填 0.0256）。請依銀行核准利率填入
B26: 所得稅 | C26: 所得稅率 | D26: 0.2 | E26: 20 | F26: 公司所得稅率，填小數（例：20% → 填 0.2）。預設 0.2，通常不需更改
B29: 現金流量表
B30: 金流項目 | C30: 相關參數 | D30: 參數數值 | F30: 說明
B31: 貸款成數 | C31: 占總設備費用比例 | D31: 0.8 | F31: 貸款佔設備總費用比例，填小數（例：80% → 填 0.8）。預設 0.8 代表貸八成、自備二成
B32: 貸款還款 | C32: 攤還期數 | D32: 15 | F32: 貸款還款年數（年）。預設 15 年，代表分 15 年平均攤還本金
B33: 現金股利 | C33: 股利比率 | D33: 0.9 | F33: 稅後現金流中分配給股東的比例，填小數（例：90% → 填 0.9）
B34: 年底減資 | C34: 攤還期數 | D34: 4 | F34: 年底減資返還股東的年數。預設 4 年，代表 倒數 4 年進行減資，加速資金返還
C37: 年份 | D37: 2020 | E37: 2021 | F37: 2022 | G37: 2023 | H37: 2024 | I37: 2025 | J37: 2026 | K37: 2027 | L37: 2028 | M37: 2029 | N37: 2030 | O37: 2031 | P37: 2032 | Q37: 2033 | R37: 2034 | S37: 2035 | T37: 2036 | U37: 2037 | V37: 2038 | W37: 2039
B38: 0
B39: (Unit : Currency) | C39: 0 | D39: 1 | E39: 2 | F39: 3 | G39: 4 | H39: 5 | I39: 6 | J39: 7 | K39: 8 | L39: 9 | M39: 10 | N39: 11 | O39: 12 | P39: 13 | Q39: 14 | R39: 15 | S39: 16 | T39: 17 | U39: 18 | V39: 19 | W39: 20
B40: 發電度數(KWH) | C40: 0 | D40: =$D$10*P1 -> 541531.98 | E40: =$D$10*Q1 -> 539343.97 | F40: =$D$10*R1 -> 537155.96 | G40: =$D$10*S1 -> 534967.96 | H40: =$D$10*T1 -> 532779.95 | I40: =$D$10*U1 -> 530591.94 | J40: =$D$10*V1 -> 528403.93 | K40: =$D$10*W1 -> 526215.92 | ... W40: =$D$10*AI1 -> 499959.83
B41: Inflow : 電費收入 | C41: - | D41: =D40*$D$13 -> 2166127.9 | E41: =E40*$D$13 -> 2157375.9 | F41: =F40*$D$13 -> 2148623.9 | G41: =G40*$D$13 -> 2139871.8 | H41: =H40*$D$13 -> 2131119.8 | I41: =I40*$D$13 -> 2122367.8 | J41: =J40*$D$13 -> 2113615.7 | K41: =K40*$D$13 -> 2104863.7 | ... W41: =W40*$D$13 -> 1999839.3
B42: Inflow : 政府補助 | C42: - | G42: - | H42: - | I42: - | J42: - | K42: - | L42: - | M42: - | N42: - | O42: - | P42: - | Q42: - | R42: - | S42: - | T42: - | U42: - | V42: - | W42: -
B43: Inflow : 銀行借款
B44: Outflow : 設備費用 | C44: =-(D16/(1-D17)+D18)*C4 -> -17693200
B45: Outflow : 設備放置區域租金 | C45: - | D45: -290201 | E45: -290201 | F45: -290201 | G45: -290201 | H45: -290201 | I45: -290201 | J45: -290201 | K45: -290201 | L45: -290201 | M45: -290201 | N45: -290201 | O45: -290201 | P45: -290201 | Q45: -290201 | R45: -290201 | S45: -290201 | T45: -290201 | U45: -290201 | V45: -290201 | W45: -290201
B46: Outflow : 返還借款
B47: Outflow : 利息費用 | C47: -
B48: Outflow : 維運費 | C48: - | D48: -174440 | E48: -174440 | F48: -174440 | G48: -174440 | H48: -174440 | I48: -174440 | J48: -174440 | K48: -174440 | L48: -174440 | M48: -174440 | N48: -174440 | O48: -174440 | P48: -174440 | Q48: -174440 | R48: -174440 | S48: -174440 | T48: -174440 | U48: -174440 | V48: -174440 | W48: -174440
B49: Outflow : 保險費 | C49: - | D49: -35324.1 | E49: -35324.1 | F49: -35324.1 | G49: -35324.1 | H49: -35324.1 | I49: -35324.1 | J49: -35324.1 | K49: -35324.1 | L49: -35324.1 | M49: -35324.1 | N49: -35324.1 | O49: -35324.1 | P49: -35324.1 | Q49: -35324.1 | R49: -35324.1 | S49: -35324.1 | T49: -35324.1 | U49: -35324.1 | V49: -35324.1 | W49: -35324.1
B50: Outflow : 模組回收費 | D50: -43610 | E50: -43610 | F50: -43610 | G50: -43610 | H50: -43610 | I50: -43610 | J50: -43610 | K50: -43610 | L50: -43610 | M50: -43610 | N50: 0 | O50: 0 | P50: 0 | Q50: 0 | R50: 0 | S50: 0 | T50: 0 | U50: 0 | V50: 0 | W50: 0
B51: Outflow : 其它費用(人事薪資…等)
B52: 1%管理費
B53: 績效獎金
B54: 所得稅20% | D54: =D77 -> -205618.76 | E54: =E77 -> -145828.16 | F54: =F77 -> -144077.75 | G54: =G77 -> -142327.34 | H54: =H77 -> -140576.94 | I54: =I77 -> -138826.53 | J54: =J77 -> -137076.13 | K54: =K77 -> -135325.72 | ... W54: =W77 -> -123042.84
B55: 現金流 | C55: =C44 -> -17693200 | D55: =SUM(D41:D54) -> 1416934.1 | E55: =SUM(E41:E54) -> 1467972.6 | F55: =SUM(F41:F54) -> 1460971 | G55: =SUM(G41:G54) -> 1453969.4 | H55: =SUM(H41:H54) -> 1446967.8 | I55: =SUM(I41:I54) -> 1439966.1 | J55: =SUM(J41:J54) -> 1432964.5 | K55: =SUM(K41:K54) -> 1425962.9 | ... W55: =SUM(W41:W54) -> 1376831.4
B56: 累計現金流 | D56: =C55+D55 -> -16276266 | E56: =D56+E55 -> -14808293 | F56: =E56+F55 -> -13347322 | G56: =F56+G55 -> -11893353 | H56: =G56+H55 -> -10446385 | I56: =H56+I55 -> -9006419 | J56: =I56+J55 -> -7573454.5 | K56: =J56+K55 -> -6147491.7 | L56: =K56+L55 -> -4728530.4 | ... X56: =W56+X55 -> 10766816
B57: 回收年限評估 | D57: =IF((D56)>0,"回收","未回收") -> 未回收 | E57: =IF((E56)>0,"回收","未回收") -> 未回收 | F57: =IF((F56)>0,"回收","未回收") -> 未回收 | G57: =IF((G56)>0,"回收","未回收") -> 未回收 | H57: =IF((H56)>0,"回收","未回收") -> 未回收 | I57: =IF((I56)>0,"回收","未回收") -> 未回收 | J57: =IF((J56)>0,"回收","未回收") -> 未回收 | K57: =IF((K56)>0,"回收","未回收") -> 未回收 | ... X57: =IF((X56)>0,"回收","未回收") -> 回收
B58: 專案法IRR | C58: =IRR(C55:W55) -> 0.050729975
C60: 年份 | D60: =D37 -> 2020 | E60: =E37 -> 2021 | F60: =F37 -> 2022 | G60: =G37 -> 2023 | H60: =H37 -> 2024 | I60: =I37 -> 2025 | J60: =J37 -> 2026 | K60: =K37 -> 2027 | ... W60: =W37 -> 2039
B61: 0 | T61: 償還年限
B62: (Unit : Currency) | C62: 0 | D62: 1 | E62: 2 | F62: 3 | G62: 4 | H62: 5 | I62: 6 | J62: 7 | K62: 8 | L62: 9 | M62: 10 | N62: 11 | O62: 12 | P62: 13 | Q62: 14 | R62: 15 | S62: 16 | T62: 17 | U62: 18 | V62: 19 | W62: 20
B63: 發電度數(KWH) | C63: 0 | D63: =D40 -> 541531.98 | E63: =E40 -> 539343.97 | F63: =F40 -> 537155.96 | G63: =G40 -> 534967.96 | H63: =H40 -> 532779.95 | I63: =I40 -> 530591.94 | J63: =J40 -> 528403.93 | K63: =K40 -> 526215.92 | ... W63: =W40 -> 499959.83
B64: Inflow : 電費收入 | C64: - | D64: =D41 -> 2166127.9 | E64: =E41 -> 2157375.9 | F64: =F41 -> 2148623.9 | G64: =G41 -> 2139871.8 | H64: =H41 -> 2131119.8 | I64: =I41 -> 2122367.8 | J64: =J41 -> 2113615.7 | K64: =K41 -> 2104863.7 | ... W64: =W41 -> 1999839.3
B65: Inflow : 政府補助 | C65: - | G65: - | H65: - | I65: - | J65: - | K65: - | L65: - | M65: - | N65: - | O65: - | P65: - | Q65: - | R65: - | S65: - | T65: - | U65: - | V65: - | W65: -
B66: Inflow : 銀行借款
B67: Outflow : 設備折舊 | D67: =$C$44/$E$16 -> -884660 | E67: =$C$44/$E$16 -> -884660 | F67: =$C$44/$E$16 -> -884660 | G67: =$C$44/$E$16 -> -884660 | H67: =$C$44/$E$16 -> -884660 | I67: =$C$44/$E$16 -> -884660 | J67: =$C$44/$E$16 -> -884660 | K67: =$C$44/$E$16 -> -884660 | ... W67: =$C$44/$E$16 -> -884660
B68: Outflow : 設備放置區域租金 | C68: - | D68: =D44 -> 0 | E68: =E45 -> -290201 | F68: =F45 -> -290201 | G68: =G45 -> -290201 | H68: =H45 -> -290201 | I68: =I45 -> -290201 | J68: =J45 -> -290201 | K68: =K45 -> -290201 | L68: =L45 -> -290201 | ... W68: =W45 -> -290201
B69: Outflow : 返還借款
B70: Outflow : 利息費用 | C70: - | D70: 0 | E70: 0 | F70: 0 | G70: 0 | H70: 0 | I70: 0 | J70: 0 | K70: 0 | L70: 0 | M70: 0 | N70: 0 | O70: 0 | P70: 0 | Q70: 0 | R70: 0 | S70: 0 | T70: 0 | U70: 0 | V70: 0 | W70: 0
B71: Outflow : 維運費 | C71: - | D71: =D48 -> -174440 | E71: =E48 -> -174440 | F71: =F48 -> -174440 | G71: =G48 -> -174440 | H71: =H48 -> -174440 | I71: =I48 -> -174440 | J71: =J48 -> -174440 | K71: =K48 -> -174440 | ... W71: =W48 -> -174440
B72: Outflow : 保險費 | C72: - | D72: =D49 -> -35324.1 | E72: =E49 -> -35324.1 | F72: =F49 -> -35324.1 | G72: =G49 -> -35324.1 | H72: =H49 -> -35324.1 | I72: =I49 -> -35324.1 | J72: =J49 -> -35324.1 | K72: =K49 -> -35324.1 | ... W72: =W49 -> -35324.1
B73: Outflow : 模組回收費 | D73: =D50 -> -43610 | E73: =E50 -> -43610 | F73: =F50 -> -43610 | G73: =G50 -> -43610 | H73: =H50 -> -43610 | I73: =I50 -> -43610 | J73: =J50 -> -43610 | K73: =K50 -> -43610 | ... W73: =W50 -> 0
B74: Outflow : 其它費用(人事薪資…等)
B75: 1%管理費
B76: 稅前淨利 | D76: =SUM(D64:D75) -> 1028093.8 | E76: =SUM(E64:E75) -> 729140.79 | F76: =SUM(F64:F75) -> 720388.76 | G76: =SUM(G64:G75) -> 711636.72 | H76: =SUM(H64:H75) -> 702884.69 | I76: =SUM(I64:I75) -> 694132.66 | J76: =SUM(J64:J75) -> 685380.63 | K76: =SUM(K64:K75) -> 676628.6 | ... X76: =SUM(X64:X75) -> 0
B77: 所得稅20% | D77: =-D76*0.2 -> -205618.76 | E77: =-E76*0.2 -> -145828.16 | F77: =-F76*0.2 -> -144077.75 | G77: =-G76*0.2 -> -142327.34 | H77: =-H76*0.2 -> -140576.94 | I77: =-I76*0.2 -> -138826.53 | J77: =-J76*0.2 -> -137076.13 | K77: =-K76*0.2 -> -135325.72 | ... X77: =-X76*0.2 -> 0
B78: 稅後淨利 | D78: =SUM(D76:D77) -> 822475.06 | E78: =SUM(E76:E77) -> 583312.63 | F78: =SUM(F76:F77) -> 576311 | G78: =SUM(G76:G77) -> 569309.38 | H78: =SUM(H76:H77) -> 562307.75 | I78: =SUM(I76:I77) -> 555306.13 | J78: =SUM(J76:J77) -> 548304.5 | K78: =SUM(K76:K77) -> 541302.88 | ... X78: =SUM(X76:X77) -> 0
B79: 累計現金流
B80: 回收年限評估
